Workbook
Name _NG_ad662: #REF!
Name _NG_bcb16: #REF!
Name Adjusted_EBIT: #REF!
Name Adjusted_EBITDA: #REF!
Name Adjusted_EBITDA: #REF!
Name Avg_shares_out__m: #REF!
Name Avg_shares_out__m: #REF!
Name Balance_sheet: #REF!
Name Balance_sheet: #REF!
Name Beer_volumes: #REF!
Name Beer_volumes: #REF!
Name Capital_Expenditures___Goodwill: #REF!
Name Capital_Expenditures___Goodwill: #REF!
Name Cash_Balance: #REF!
Name Cash_Balance: #REF!
Name Cash_Flow: #REF!
Name Cash_Flow: #REF!
Name Cash_Flow_Available_to_Investors: #REF!
Name Cash_Flow_Available_to_Investors: #REF!
Name CCY: #REF!
Name CCY: #REF!
Name Celulose: #REF!
Name Celulose: #REF!
Name Change_in_Working_Capital: #REF!
Name Change_in_Working_Capital: #REF!
Name Class: #REF!
Name Class: #REF!
Name Commission_income: #REF!
Name Commission_income: #REF!
Name CURRENCY: #REF!
Name CURRENCY: #REF!
Name Data: OFFSET(#REF!,#REF!,0,#REF!)
Name Data: OFFSET(#REF!,#REF!,0,#REF!)
Name Dates: OFFSET(#REF!,#REF!,0,#REF!)
Name Dates: OFFSET(#REF!,#REF!,0,#REF!)
Name DCF_Valuation_Summary: #REF!
Name DCF_Valuation_Summary: #REF!
Name Debt_Target_Calculations: #REF!
Name Debt_Target_Calculations: #REF!
Name Deferred_tax_assets: #REF!
Name Deferred_tax_assets: #REF!
Name Deposits: #REF!
Name Deposits: #REF!
Name Dividends: #REF!
Name Dividends: #REF!
Name DivLiq: #REF!
Name DivLiq: #REF!
Name Dupont_Analysis: #REF!
Name Dupont_Analysis: #REF!
Name Earnings_before_taxes: #REF!
Name Earnings_before_taxes: #REF!
Name ebitda03: #REF!
Name ebitda03: #REF!
Name ebitda04: #REF!
Name ebitda04: #REF!
Name ebitda05: #REF!
Name ebitda05: #REF!
Name Economics: #REF!
Name Extra_items__after_tax: #REF!
Name Extra_items__after_tax: #REF!

Sheet Resumo
G1: #VALUE! | M1: {=+_FV(G1,"Price")} -> 40.14 | P1: =+TODAY() -> 46090 | S1: {=+_FV(G1,"Shares outstanding",TRUE)/1000000} -> 3000.619
B2: Mln MXN | C2: 2016 | D2: =+C2+1 -> 2017 | E2: =+D2+1 -> 2018 | F2: =+E2+1 -> 2019 | G2: =+F2+1 -> 2020 | H2: =+G2+1 -> 2021 | I2: =+H2+1 -> 2022 | J2: =+I2+1 -> 2023 | K2: =+J2+1 -> 2024 | ... Q2: =+P2+1 -> 2030
B3: Net Revs | C3: =+PROJ!BP3 -> 35660.295 | D3: =+PROJ!BQ3 -> 37765.76 | E3: =+PROJ!BR3 -> 41026.864 | F3: =+PROJ!BS3 -> 43500.929 | G3: =+PROJ!BT3 -> 46702.895 | H3: =+PROJ!BU3 -> 46893.963 | I3: =+PROJ!BV3 -> 51054.876 | J3: =+PROJ!BW3 -> 53307.054 | ... Q3: =+PROJ!CD3 -> 61358.787
B4: yoy | D4: =+D3/C3-1 -> 0.059042277 | E4: =+E3/D3-1 -> 0.086350811 | F4: =+F3/E3-1 -> 0.060303537 | G4: =+G3/F3-1 -> 0.073606842 | H4: =+H3/G3-1 -> 0.0040911382 | I4: =+I3/H3-1 -> 0.088730249 | J4: =+J3/I3-1 -> 0.044112887 | K4: =+K3/J3-1 -> 0.027682321 | ... Q4: =+Q3/P3-1 -> 0.02
L5: =56674/K3-1 -> 0.034523352
B6: Gross Profit | C6: =+PROJ!BP6 -> 13784.933 | D6: =+PROJ!BQ6 -> 13401.991 | E6: =+PROJ!BR6 -> 14340.566 | F6: =+PROJ!BS6 -> 16321.421 | G6: =+PROJ!BT6 -> 18009.274 | H6: =+PROJ!BU6 -> 15785.676 | I6: =+PROJ!BV6 -> 16772.482 | J6: =+PROJ!BW6 -> 20700.039 | ... Q6: =+PROJ!CD6 -> 24121.062
B7: mrgn | C7: =+C6/C$3 -> 0.38656251 | D7: =+D6/D$3 -> 0.35487148 | E7: =+E6/E$3 -> 0.34954088 | F7: =+F6/F$3 -> 0.37519707 | G7: =+G6/G$3 -> 0.38561365 | H7: =+H6/H$3 -> 0.33662491 | I7: =+I6/I$3 -> 0.32851871 | J7: =+J6/J$3 -> 0.38831707 | ... Q7: =+Q6/Q$3 -> 0.39311504
B8: SG&A | C8: =+PROJ!BP8 -> -5766.523 | D8: =+PROJ!BQ8 -> -6432.926 | E8: =+PROJ!BR8 -> -6845.842 | F8: =+PROJ!BS8 -> -7346.593 | G8: =+PROJ!BT8 -> -7504.876 | H8: =+PROJ!BU8 -> -7450.885 | I8: =+PROJ!BV8 -> -7848.084 | J8: =+PROJ!BW8 -> -8784.296 | ... Q8: =+PROJ!CD8 -> -11240.933
B9: EBIT | C9: =+PROJ!BP14 -> 8018.41 | D9: =+PROJ!BQ14 -> 6977.791 | E9: =+PROJ!BR14 -> 7503.406 | F9: =+PROJ!BS14 -> 8997.295 | G9: =+PROJ!BT14 -> 10537.29 | H9: =+PROJ!BU14 -> 8349.719 | I9: =+PROJ!BV14 -> 8940.054 | J9: =+PROJ!BW14 -> 11932.279 | ... Q9: =+PROJ!CD14 -> 12880.129
B10: Fin Res | C10: =+SUM(PROJ!BP18:BP22) -> -1073.269 | D10: =+SUM(PROJ!BQ18:BQ22) -> -1237.63 | E10: =+SUM(PROJ!BR18:BR22) -> -1512.719 | F10: =+SUM(PROJ!BS18:BS22) -> -1534.814 | G10: =+SUM(PROJ!BT18:BT22) -> -1664.172 | H10: =+SUM(PROJ!BU18:BU22) -> -1739.929 | I10: =+SUM(PROJ!BV18:BV22) -> -1689.82 | J10: =+SUM(PROJ!BW18:BW22) -> -1543.995 | ... Q10: =+SUM(PROJ!CD18:CD22) -> -819.51711
B11: EBT | C11: =+PROJ!BP23 -> 6945.141 | D11: =+PROJ!BQ23 -> 5740.161 | E11: =+PROJ!BR23 -> 5990.687 | F11: =+PROJ!BS23 -> 7462.481 | G11: =+PROJ!BT23 -> 8873.118 | H11: =+PROJ!BU23 -> 6609.79 | I11: =+PROJ!BV23 -> 7250.234 | J11: =+PROJ!BW23 -> 10388.284 | ... Q11: =+PROJ!CD23 -> 12060.612
B12: tax | C12: =+PROJ!BP24 -> -2155.929 | D12: =+PROJ!BQ24 -> -1703.605 | E12: =+PROJ!BR24 -> -1782.604 | F12: =+PROJ!BS24 -> -2314.011 | G12: =+PROJ!BT24 -> -2792.133 | H12: =+PROJ!BU24 -> -2150.052 | I12: =+PROJ!BV24 -> -2314.398 | J12: =+PROJ!BW24 -> -3375.507 | ... Q12: =+PROJ!CD24 -> -3799.0927
B13: rate | C13: =+C12/C11 -> -0.31042264 | D13: =+D12/D11 -> -0.29678697 | E13: =+E12/E11 -> -0.29756253 | F13: =+F12/F11 -> -0.31008602 | G13: =+G12/G11 -> -0.31467326 | H13: =+H12/H11 -> -0.32528295 | I13: =+I12/I11 -> -0.31921701 | J13: =+J12/J11 -> -0.32493403 | ... Q13: =+Q12/Q11 -> -0.315
B15: Net Income | C15: =+PROJ!BP27 -> 4793.565 | D15: =+PROJ!BQ27 -> 4066.689 | E15: =+PROJ!BR27 -> 4214.226 | F15: =+PROJ!BS27 -> 5141.858 | G15: =+PROJ!BT27 -> 6225.568 | H15: =+PROJ!BU27 -> 4493.868 | I15: =+PROJ!BV27 -> 4934.25 | J15: =+PROJ!BW27 -> 7012.845 | ... Q15: =+PROJ!CD27 -> 8261.5191
B17: EBITDA | C17: =+PROJ!BP16 -> 9619.329 | D17: =+PROJ!BQ16 -> 7358.424 | E17: =+PROJ!BR16 -> 7885.744 | F17: =+PROJ!BS16 -> 9456.75 | G17: =+PROJ!BT16 -> 12490.625 | H17: =+PROJ!BU16 -> 10285 | I17: =+PROJ!BV16 -> 10908.78 | J17: =+PROJ!BW16 -> 13916.799 | ... Q17: =+PROJ!CD16 -> 14895.863
B18: mrgn | C18: =+C17/C$3 -> 0.269749 | D18: =+D17/D$3 -> 0.1948438 | E18: =+E17/E$3 -> 0.19220928 | F18: =+F17/F$3 -> 0.21739191 | G18: =+G17/G$3 -> 0.26744862 | H18: =+H17/H$3 -> 0.21932461 | I18: =+I17/I$3 -> 0.21366774 | J18: =+J17/J$3 -> 0.26106862 | ... Q18: =+Q17/Q$3 -> 0.24276658
B20: MULTIPLOS | C20: =+C$2 -> 2016 | D20: =+D$2 -> 2017 | E20: =+E$2 -> 2018 | F20: =+F$2 -> 2019 | G20: =+G$2 -> 2020 | H20: =+H$2 -> 2021 | I20: =+I$2 -> 2022 | J20: =+J$2 -> 2023 | ... Q20: =+Q$2 -> 2030
B21: Mkt Cap | C21: {=+_FV($G$1,"Market cap",TRUE)/1000000} -> 120444.85 | D21: {=+_FV($G$1,"Market cap",TRUE)/1000000} -> 120444.85 | E21: {=+_FV($G$1,"Market cap",TRUE)/1000000} -> 120444.85 | F21: {=+_FV($G$1,"Market cap",TRUE)/1000000} -> 120444.85 | G21: {=+_FV($G$1,"Market cap",TRUE)/1000000} -> 120444.85 | H21: {=+_FV($G$1,"Market cap",TRUE)/1000000} -> 120444.85 | I21: {=+_FV($G$1,"Market cap",TRUE)/1000000} -> 120444.85 | J21: {=+_FV($G$1,"Market cap",TRUE)/1000000} -> 120444.85 | ... Q21: {=+_FV($G$1,"Market cap",TRUE)/1000000} -> 120444.85
B22: Net Debt | C22: =+PROJ!BP145 -> 15814.634 | D22: =+PROJ!BQ145 -> 18630.793 | E22: =+PROJ!BR145 -> 19641.065 | F22: =+PROJ!BS145 -> 17336.939 | G22: =+PROJ!BT145 -> 15907.714 | H22: =+PROJ!BU145 -> 17086.529 | I22: =+PROJ!BV145 -> 17598.026 | J22: =+PROJ!BW145 -> 12745.853 | ... Q22: =+PROJ!CD145 -> 7569.5519
B23: EV | C23: =+C21+C22 -> 136259.48 | D23: =+D21+D22 -> 139075.64 | E23: =+E21+E22 -> 140085.91 | F23: =+F21+F22 -> 137781.79 | G23: =+G21+G22 -> 136352.56 | H23: =+H21+H22 -> 137531.38 | I23: =+I21+I22 -> 138042.87 | J23: =+J21+J22 -> 133190.7 | ... Q23: =+Q21+Q22 -> 128014.4
B25: PE | C25: =+C21/C15 -> 25.126361 | D25: =+D21/D15 -> 29.617423 | E25: =+E21/E15 -> 28.580538 | F25: =+F21/F15 -> 23.424382 | G25: =+G21/G15 -> 19.346804 | H25: =+H21/H15 -> 26.802044 | I25: =+I21/I15 -> 24.40996 | J25: =+J21/J15 -> 17.174891 | ... L25: =+L21/L15 -> 15.892623 | M25: mi al | N25: =+N21/N15 -> 14.827326 | O25: =+O21/O15 -> 14.773125 | P25: =+P21/P15 -> 14.726761 | Q25: =+Q21/Q15 -> 14.579019
B26: P/BV | C26: =+C21/PROJ!BP88 -> 17.208194 | D26: =+D21/PROJ!BQ88 -> 19.776836 | E26: =+E21/PROJ!BR88 -> 21.659696 | F26: =+F21/PROJ!BS88 -> 22.791819 | G26: =+G21/PROJ!BT88 -> 20.733376 | H26: =+H21/PROJ!BU88 -> 21.043441 | I26: =+I21/PROJ!BV88 -> 23.957443 | J26: =+J21/PROJ!BW88 -> 17.402415 | ... Q26: =+Q21/PROJ!CD88 -> 7.9015827
B27: EV/EBITDA | C27: =+C23/C17 -> 14.165175 | D27: =+D23/D17 -> 18.900194 | E27: =+E23/E17 -> 17.764451 | F27: =+F23/F17 -> 14.569676 | G27: =+G23/G17 -> 10.916392 | H27: =+H23/H17 -> 13.372035 | I27: =+I23/I17 -> 12.654291 | J27: =+J23/J17 -> 9.5704982 | ... Q27: =+Q23/Q17 -> 8.5939564
B29: Div yield | C29: =+PROJ!BP121/Resumo!$M$1 -> 0 | D29: =+PROJ!BQ121/Resumo!$M$1 -> 0 | E29: =+PROJ!BR121/Resumo!$M$1 -> 0 | F29: =+PROJ!BS121/Resumo!$M$1 -> 0 | G29: =+PROJ!BT121/Resumo!$M$1 -> 0.039862211 | H29: =+PROJ!BU121/Resumo!$M$1 -> 0.039861727 | I29: =+PROJ!BV121/Resumo!$M$1 -> 0.039861741 | J29: =+PROJ!BW121/Resumo!$M$1 -> 0.039862194 | ... Q29: =+PROJ!CD121/Resumo!$M$1 -> 0.055512189
B30: FCF Yield | F30: =+F45/F21 -> 0.054502234 | G30: =+G45/G21 -> 0.15751406 | H30: =+H45/H21 -> -0.0071047797 | I30: =+I45/I21 -> 0.084117655 | J30: =+J45/J21 -> 0.035718888 | K30: =+K45/K21 -> 0.030652246 | L30: =+L45/L21 -> 0.01917099 | M30: =+M45/M21 -> 0.068321435 | ... Q30: =+Q45/Q21 -> 0.06803554
B31: ROE | C31: =+PROJ!BP165 -> 0.69791526 | D31: =+PROJ!BQ165 -> 0.62136797 | E31: =+PROJ!BR165 -> 0.72341142 | F31: =+PROJ!BS165 -> 0.94821457 | G31: =+PROJ!BT165 -> 1.1223519 | H31: =+PROJ!BU165 -> 0.77931586 | I31: =+PROJ!BV165 -> 0.91790787 | J31: =+PROJ!BW165 -> 1.1738347 | ... Q31: =+PROJ!CD165 -> 0.57436177
B32: ROIC | F32: =+PROJ!BS39 -> 0 | G32: =+PROJ!BT39 -> 0.47247207 | H32: =+PROJ!BU39 -> 0.35620917 | I32: =+PROJ!BV39 -> 0.36687444 | J32: =+PROJ!BW39 -> 0.49119914 | K32: =+PROJ!BX39 -> 0.52447156 | L32: =+PROJ!BY39 -> 0.48755109 | M32: =+PROJ!BZ39 -> 0.49312107 | ... Q32: =+PROJ!CD39 -> 0.48838835
B34: FCFF | C34: =+C$2 -> 2016 | D34: =+D$2 -> 2017 | E34: =+E$2 -> 2018 | F34: =+F$2 -> 2019 | G34: =+G$2 -> 2020 | H34: =+H$2 -> 2021 | I34: =+I$2 -> 2022 | J34: =+J$2 -> 2023 | ... Q34: =+Q$2 -> 2030
B35: EBIT | C35: =+C9 -> 8018.41 | D35: =+D9 -> 6977.791 | E35: =+E9 -> 7503.406 | F35: =+F9 -> 8997.295 | G35: =+G9 -> 10537.29 | H35: =+H9 -> 8349.719 | I35: =+I9 -> 8940.054 | J35: =+J9 -> 11932.279 | ... Q35: =+Q9 -> 12880.129
B36: Impostos | C36: =+C13*C35 -> -2489.096 | D36: =+D13*D35 -> -2070.9175 | E36: =+E13*E35 -> -2232.7325 | F36: =+F13*F35 -> -2789.9354 | G36: =+G13*G35 -> -3315.8034 | H36: =+H13*H35 -> -2716.0212 | I36: =+I13*I35 -> -2853.8173 | J36: =+J13*J35 -> -3877.2035 | ... Q36: =+Q13*Q35 -> -4057.2406
B37: NOPAT | C37: =+C35+C36 -> 5529.314 | D37: =+D35+D36 -> 4906.8735 | E37: =+E35+E36 -> 5270.6735 | F37: =+F35+F36 -> 6207.3596 | G37: =+G35+G36 -> 7221.4866 | H37: =+H35+H36 -> 5633.6978 | I37: =+I35+I36 -> 6086.2367 | J37: =+J35+J36 -> 8055.0755 | ... Q37: =+Q35+Q36 -> 8822.8883
B38: Depr | C38: =+PROJ!BP98 -> 1600.919 | D38: =+PROJ!BQ98 -> 380.633 | E38: =+PROJ!BR98 -> 382.338 | F38: =+PROJ!BS98 -> 459.455 | G38: =+PROJ!BT98 -> 1953.335 | H38: =+PROJ!BU98 -> 1935.281 | I38: =+PROJ!BV98 -> 1968.726 | J38: =+PROJ!BW98 -> 1984.52 | ... Q38: =+PROJ!CD98 -> 2015.7342
B39: Capex | C39: =+PROJ!BP105 -> -2949.503 | D39: =+PROJ!BQ105 -> -2577.711 | E39: =+PROJ!BR105 -> -1792.043 | F39: =+PROJ!BS105 -> -771.988 | G39: =+PROJ!BT105 -> -795.281 | H39: =+PROJ!BU105 -> -2150.474 | I39: =+PROJ!BV105 -> -2141.436 | J39: =+PROJ!BW105 -> -2141.436 | ... Q39: =+PROJ!CD105 -> -2147.5576
B40: WC | C40: =+PROJ!BP99 -> -449.0371 | D40: =+PROJ!BQ99 -> -816.3749 | E40: =+PROJ!BR99 -> 569.8358 | F40: =+PROJ!BS99 -> 2193.6482 | G40: =+PROJ!BT99 -> 1416.601 | H40: =+PROJ!BU99 -> 30.1109 | I40: =+PROJ!BV99 -> 212.4501 | J40: =+PROJ!BW99 -> 245.551 | ... Q40: =+PROJ!CD99 -> 64.834438
B41: Imp dif | C41: =+C12-C36 -> 333.167 | D41: =+D12-D36 -> 367.31246 | E41: =+E12-E36 -> 450.1285 | F41: =+F12-F36 -> 475.92436 | G41: =+G12-G36 -> 523.67043 | H41: =+H12-H36 -> 565.96924 | I41: =+I12-I36 -> 539.41928 | J41: =+J12-J36 -> 501.69652 | ... Q41: =+Q12-Q36 -> 258.14789 | R41: perp
B42: FCFF | C42: =+C37+C38+C39+C40+C41 -> 4064.8599 | D42: =+D37+D38+D39+D40+D41 -> 2260.7331 | E42: =+E37+E38+E39+E40+E41 -> 4880.9328 | F42: =+F37+F38+F39+F40+F41 -> 8564.3992 | G42: =+G37+G38+G39+G40+G41 -> 10319.812 | H42: =+H37+H38+H39+H40+H41 -> 6014.5849 | I42: =+I37+I38+I39+I40+I41 -> 6665.3961 | J42: =+J37+J38+J39+J40+J41 -> 8645.407 | ... Q42: =+Q37+Q38+Q39+Q40+Q41 -> 9014.0473 | R42: =+Q42*(1+Q56)/(Q48-Q56) -> 149174.95
B43: Interest | C43: =+C10 -> -1073.269 | D43: =+D10 -> -1237.63 | E43: =+E10 -> -1512.719 | F43: =+F10 -> -1534.814 | G43: =+G10 -> -1664.172 | H43: =+H10 -> -1739.929 | I43: =+I10 -> -1689.82 | J43: =+J10 -> -1543.995 | ... Q43: =+Q10 -> -819.51711
B44: New Debt | C44: =+PROJ!BP143-PROJ!BO143 -> 6037.9262 | D44: =+PROJ!BQ143-PROJ!BP143 -> 29.0058 | E44: =+PROJ!BR143-PROJ!BQ143 -> 1335.435 | F44: =+PROJ!BS143-PROJ!BR143 -> -465.072 | G44: =+PROJ!BT143-PROJ!BS143 -> 10316.117 | H44: =+PROJ!BU143-PROJ!BT143 -> -5130.39 | I44: =+PROJ!BV143-PROJ!BU143 -> 5155.962 | J44: =+PROJ!BW143-PROJ!BV143 -> -2799.256 | ... Q44: =+PROJ!CD143-PROJ!CC143 -> 0
B45: FCFE | C45: =+C42+C43+C44 -> 9029.5171 | D45: =+D42+D43+D44 -> 1052.1089 | E45: =+E42+E43+E44 -> 4703.6488 | F45: =+F42+F43+F44 -> 6564.5132 | G45: =+G42+G43+G44 -> 18971.757 | H45: =+H42+H43+H44 -> -855.7341 | I45: =+I42+I43+I44 -> 10131.538 | J45: =+J42+J43+J44 -> 4302.156 | ... Q45: =+Q42+Q43+Q44 -> 8194.5302
B47: WACC | C47: =+C$2 -> 2016 | D47: =+D$2 -> 2017 | E47: =+E$2 -> 2018 | F47: =+F$2 -> 2019 | G47: =+G$2 -> 2020 | H47: =+H$2 -> 2021 | I47: =+I$2 -> 2022 | J47: =+J$2 -> 2023 | ... Q47: =+Q$2 -> 2030
K48: WACC | M48: =+(M49*M21+M50*M22)/M23 -> 0.095712928 | N48: =+(N49*N21+N50*N22)/N23 -> 0.095439702 | O48: =+(O49*O21+O50*O22)/O23 -> 0.096205439 | P48: =+(P49*P21+P50*P22)/P23 -> 0.096971743 | Q48: =+(Q49*Q21+Q50*Q22)/Q23 -> 0.097540921
K49: Ke | M49: =M57+M58*M59 -> 0.1008 | N49: =N57+N58*N59 -> 0.1008 | O49: =O57+O58*O59 -> 0.1008 | P49: =P57+P58*P59 -> 0.1008 | Q49: =Q57+Q58*Q59 -> 0.1008
K50: Kd | M50: =+M52*(1+M53) -> 0.052470827 | N50: =+N52*(1+N53) -> 0.043721934 | O50: =+O52*(1+O53) -> 0.045145563 | P50: =+P52*(1+P53) -> 0.046967923 | Q50: =+Q52*(1+Q53) -> 0.045683259
K52: Interest | M52: =+PROJ!BZ147 -> 0.074615834 | N52: =+PROJ!CA147 -> 0.06224317 | O52: =+PROJ!CB147 -> 0.06543651 | P52: =+PROJ!CC147 -> 0.068533621 | Q52: =+PROJ!CD147 -> 0.067707284
K53: tax | M53: =+D13 -> -0.29678697 | N53: =+E13 -> -0.29756253 | O53: =+F13 -> -0.31008602 | P53: =+G13 -> -0.31467326 | Q53: =+H13 -> -0.32528295
K55: Long Term Real Rates | M55: =+M57-M56 -> 0.0298 | N55: =+N57-N56 -> 0.0298 | O55: =+O57-O56 -> 0.0298 | P55: =+P57-P56 -> 0.0298 | Q55: =+Q57-Q56 -> 0.0298
K56: Inflation | M56: =+macro!DN83 -> 0.035 | N56: =+macro!DO83 -> 0.035 | O56: =+macro!DP83 -> 0.035 | P56: =+macro!DQ83 -> 0.035 | Q56: =+macro!DR83 -> 0.035
K57: Nominal Interest Rates | M57: =+macro!DN51 -> 0.0648 | N57: =+macro!DO51 -> 0.0648 | O57: =+macro!DP51 -> 0.0648 | P57: =+macro!DQ51 -> 0.0648 | Q57: =+macro!DR51 -> 0.0648
K58: MRP | M58: 0.045 | N58: 0.045 | O58: 0.045 | P58: 0.045 | Q58: 0.045
K59: Beta | M59: 0.8 | N59: 0.8 | O59: 0.8 | P59: 0.8 | Q59: 0.8
M61: 1 | N61: =+M61*(1+N48) -> 1.0954397 | O61: =+N61*(1+O48) -> 1.200827 | P61: =+O61*(1+P48) -> 1.3172732 | Q61: =+P61*(1+Q48) -> 1.4457613 | R61: =+Q61 -> 1.4457613
L62: VP | M62: =+M42/M61 -> 9367.7377 | N62: =+N42/N61 -> 8375.8756 | O62: =+O42/O61 -> 7595.0987 | P62: =+P42/P61 -> 6896.7796 | Q62: =+Q42/Q61 -> 6234.8102 | R62: =+R42/R61 -> 103180.9
L63: EV | M63: =+SUM(N62:R62) -> 132283.47
L64: Net Debt | M64: =+M22 -> 14169.332
L65: Div | M65: =+M29*M21 -> 8959.654
L66: Mkt Capt | M66: =+M63-M64+M65 -> 127073.79
L67: Shares | M67: {=+_FV(G1,"Shares outstanding",TRUE)/1000000} -> 3000.619
L68: PT | M68: =+M66/M67 -> 42.349191
L69: Upside | M69: =+M68/$M$1-1 -> 0.055037149

Sheet PROJ
B1: =+YEAR(B2) -> 2016 | C1: =+YEAR(C2) -> 2016 | D1: =+YEAR(D2) -> 2016 | E1: =+YEAR(E2) -> 2016 | F1: =+YEAR(F2) -> 2017 | G1: =+YEAR(G2) -> 2017 | H1: =+YEAR(H2) -> 2017 | I1: =+YEAR(I2) -> 2017 | ... AS1: =+YEAR(AS2) -> 2026 | AU1: 2025 | AW1: 1997 | AX1: =+AW1+1 -> 1998 | AY1: =+AX1+1 -> 1999 | AZ1: =+AY1+1 -> 2000 | BA1: =+AZ1+1 -> 2001 | BB1: =+BA1+1 -> 2002 | BC1: =+BB1+1 -> 2003 | BD1: =+BC1+1 -> 2004 | BE1: =+BD1+1 -> 2005 | ... BS1: =+BR1+1 -> 2019 | BT1: =+YEAR(BT2) -> 2020 | BU1: =+YEAR(BU2) -> 2021 | BV1: =+YEAR(BV2) -> 2022 | BW1: =+YEAR(BW2) -> 2023 | BX1: =+YEAR(BX2) -> 2024 | BY1: =+YEAR(BY2) -> 2025 | BZ1: =+YEAR(BZ2) -> 2026 | CA1: =+YEAR(CA2) -> 2027 | ... CD1: =+YEAR(CD2) -> 2030
A2: MXN Millions | B2: 42459 | C2: =+EOMONTH(B2,3) -> 42551 | D2: =+EOMONTH(C2,3) -> 42643 | E2: =+EOMONTH(D2,3) -> 42735 | F2: =+EOMONTH(E2,3) -> 42825 | G2: =+EOMONTH(F2,3) -> 42916 | H2: =+EOMONTH(G2,3) -> 43008 | I2: =+EOMONTH(H2,3) -> 43100 | J2: =+EOMONTH(I2,3) -> 43190 | ... AS2: =+EOMONTH(AR2,3) -> 46387 | AU2: 46022 | AW2: 35795 | AX2: 36160 | AY2: 36525 | AZ2: 36891 | BA2: 37256 | BB2: 37621 | BC2: 37986 | BD2: 38352 | BE2: 38717 | BF2: 39082 | BG2: 39447 | BH2: 39813 | BI2: 40178 | BJ2: 40543 | BK2: 40908 | BL2: 41274 | BM2: 41639 | BN2: 42004 | BO2: 42369 | BP2: 42735 | BQ2: =+EOMONTH(BP2,12) -> 43100 | BR2: =+EOMONTH(BQ2,12) -> 43465 | BS2: =+EOMONTH(BR2,12) -> 43830 | BT2: =+EOMONTH(BS2,12) -> 44196 | BU2: =+EOMONTH(BT2,12) -> 44561 | BV2: =+EOMONTH(BU2,12) -> 44926 | BW2: =+EOMONTH(BV2,12) -> 45291 | BX2: =+EOMONTH(BW2,12) -> 45657 | ... CD2: =+EOMONTH(CC2,12) -> 47848
A3: Revenues | B3: 8728.317 | C3: 8831.353 | D3: 8719.457 | E3: 9381.168 | F3: 9530.508 | G3: 9605.905 | H3: 9197.259 | I3: 9432.088 | J3: 10207.266 | K3: 10588.598 | L3: 9897 | M3: 10334 | N3: 11014 | O3: 11285.929 | P3: 10400 | Q3: 10801 | R3: 11692.238 | S3: 12337.259 | T3: 11097.119 | U3: 11576.279 | V3: 12108.979 | W3: 11722.218 | X3: 11343.49 | Y3: 11719.276 | Z3: 12574 | AA3: 12894.841 | AB3: 12794 | AC3: 12792.035 | AD3: 13549 | AE3: 13714.072 | AF3: 12672.559 | AG3: 13371.423 | AH3: 13789.577 | AI3: 14068 | AJ3: 13154.636 | AK3: 13770.504 | AL3: 13833 | AM3: 14070 | AN3: 13410 | AO3: 14057.927 | AP3: =+FAT!AP11 -> 14109.66 | AQ3: =+FAT!AQ11 -> 14421.75 | AR3: =+FAT!AR11 -> 13745.25 | AS3: =+FAT!AS11 -> 14409.375 | AU3: 13977.062 | AV3: =+AO3/AU3-1 -> 0.0057855823 | AW3: 10305.475 | AX3: 12289.726 | AY3: 13868.222 | AZ3: 15906.374 | BA3: 15633.955 | BB3: 16096.04 | BC3: 17100.169 | BD3: 19798.909 | BE3: 21983.114 | BF3: 20084.472 | BG3: 21480.233 | BH3: 23051.522 | BI3: 24702.207 | BJ3: 26196.519 | BK3: 26732.383 | BL3: 29288.626 | BM3: 29677.516 | BN3: 29106.853 | BO3: 32206.234 | BP3: 35660.295 | BQ3: =+SUMIFS($B3:$AK3,$B$1:$AK$1,"="&BQ$1) -> 37765.76 | BR3: =+SUMIFS($B3:$AK3,$B$1:$AK$1,"="&BR$1) -> 41026.864 | BS3: =+SUMIFS($B3:$AK3,$B$1:$AK$1,"="&BS$1) -> 43500.929 | BT3: =+SUMIFS($B3:$AK3,$B$1:$AK$1,"="&BT$1) -> 46702.895 | BU3: =+SUMIFS($B3:$AK3,$B$1:$AK$1,"="&BU$1) -> 46893.963 | BV3: =+SUMIFS($B3:$AK3,$B$1:$AK$1,"="&BV$1) -> 51054.876 | BW3: =+SUMIFS($B3:$AK3,$B$1:$AK$1,"="&BW$1) -> 53307.054 | BX3: =+SUMIFS($B3:$AO3,$B$1:$AO$1,"="&BX$1) -> 54782.717 | BY3: =+SUMIFS($B3:$AS3,$B$1:$AS$1,"="&BY$1) -> 55370.927 | BZ3: =+SUMIFS($B3:$AS3,$B$1:$AS$1,"="&BZ$1) -> 56686.035 | CA3: =+FAT!CA11 -> 57819.756 | CB3: =+FAT!CB11 -> 58976.151 | CC3: =+FAT!CC11 -> 60155.674 | CD3: =+FAT!CD11 -> 61358.787
A4: Chg YoY | C4: =C3/B3-1 -> 0.011804796 | D4: =D3/C3-1 -> -0.012670312 | E4: =E3/D3-1 -> 0.075889015 | F4: =+F3/B3-1 -> 0.091906722 | G4: =+G3/C3-1 -> 0.087704794 | H4: =+H3/D3-1 -> 0.05479722 | I4: =+I3/E3-1 -> 0.0054278955 | J4: =+J3/F3-1 -> 0.071009646 | K4: =+K3/G3-1 -> 0.10230093 | L4: =+L3/H3-1 -> 0.076081472 | M4: =+M3/I3-1 -> 0.095621669 | ... AS4: =+AS3/AO3-1 -> 0.025 | AU4: 0.015 | AX4: =AX3/AW3-1 -> 0.19254338 | AY4: =AY3/AX3-1 -> 0.12844029 | AZ4: =AZ3/AY3-1 -> 0.14696563 | BA4: =BA3/AZ3-1 -> -0.017126405 | BB4: =BB3/BA3-1 -> 0.029556501 | BC4: =BC3/BB3-1 -> 0.062383605 | BD4: =BD3/BC3-1 -> 0.15781949 | BE4: =BE3/BD3-1 -> 0.11031946 | ... CD4: =CD3/CC3-1 -> 0.02
A5: COGS | B5: -5291.904 | C5: -5378.376 | D5: -5374.796 | E5: -5830.286 | F5: -6145.84 | G5: -6206.55 | H5: -5992.561 | I5: -6018.818 | J5: -6481.295 | K5: -6774.015 | L5: -6539.368 | M5: -6891.62 | N5: =3875-N3 -> -7139 | O5: -7087.416 | P5: -6414.613 | Q5: -6538.479 | R5: -7067.539 | S5: -7617.16 | T5: -6893.956 | U5: -7114.966 | V5: -7445.987 | W5: -7678.542 | X5: -7745.158 | Y5: -8238.6 | Z5: -8636.462 | AA5: -8739.084 | AB5: -8549.618 | AC5: -8357.23 | AD5: -8626.628 | AE5: -8477.774 | AF5: -7582.014 | AG5: -7920.599 | AH5: -7961.006 | AI5: -8113.588 | AJ5: -7942.902 | AK5: =+AK6-AK3 -> -8381.493 | AL5: =+AL6-AL3 -> -8550 | AM5: =+AM6-AM3 -> -8694.075 | AN5: =+AN6-AN3 -> -8218.306 | AO5: =+AO6-AO3 -> -8377.888 | AP5: =+FAT!AP22 -> -8530.187 | AQ5: =+FAT!AQ22 -> -8642.0689 | AR5: =+FAT!AR22 -> -8355.6465 | AS5: =+FAT!AS22 -> -8469.8834 | AU5: -8420.8539 | AW5: -6257.084 | AX5: -7212.551 | AY5: -7828.87 | AZ5: -9061.387 | BA5: -8797.095 | BB5: -9296.092 | BC5: -10269.192 | BD5: -12307.609 | BE5: -13678.619 | BF5: -11326.652 | BG5: -12683.071 | BH5: -13833.201 | BI5: -14564.753 | BJ5: -15640.626 | BK5: -17054 | BL5: -17956.306 | BM5: -17759.99 | BN5: -18379.732 | BO5: -19778.457 | BP5: -21875.362 | BQ5: =+SUMIFS($B5:$AK5,$B$1:$AK$1,"="&BQ$1) -> -24363.769 | BR5: =+SUMIFS($B5:$AK5,$B$1:$AK$1,"="&BR$1) -> -26686.298 | BS5: =+SUMIFS($B5:$AK5,$B$1:$AK$1,"="&BS$1) -> -27179.508 | BT5: =+SUMIFS($B5:$AK5,$B$1:$AK$1,"="&BT$1) -> -28693.621 | BU5: =+SUMIFS($B5:$AK5,$B$1:$AK$1,"="&BU$1) -> -31108.287 | BV5: =+SUMIFS($B5:$AK5,$B$1:$AK$1,"="&BV$1) -> -34282.394 | BW5: =+SUMIFS($B5:$AK5,$B$1:$AK$1,"="&BW$1) -> -32607.015 | BX5: =+SUMIFS($B5:$AO5,$B$1:$AO$1,"="&BX$1) -> -32398.989 | BY5: =+SUMIFS($B5:$AS5,$B$1:$AS$1,"="&BY$1) -> -33840.269 | BZ5: =+SUMIFS($B5:$AS5,$B$1:$AS$1,"="&BZ$1) -> -33997.786 | CA5: =+FAT!CA22 -> -34820.992 | CB5: =+FAT!CB22 -> -35604.055 | CC5: =+FAT!CC22 -> -36409.595 | CD5: =+FAT!CD22 -> -37237.726
A6: Gross Profit | B6: =B3+B5 -> 3436.413 | C6: =C3+C5 -> 3452.977 | D6: =D3+D5 -> 3344.661 | E6: =E3+E5 -> 3550.882 | F6: =F3+F5 -> 3384.668 | G6: =G3+G5 -> 3399.355 | H6: =H3+H5 -> 3204.698 | I6: =I3+I5 -> 3413.27 | ... AJ6: =AJ3+AJ5 -> 5211.734 | AK6: 5389.011 | AL6: 5283 | AM6: 5375.925 | AN6: 5191.694 | AO6: 5680.039 | AP6: =AP3+AP5 -> 5579.473 | AQ6: =AQ3+AQ5 -> 5779.6811 | AR6: =AR3+AR5 -> 5389.6035 | AS6: =AS3+AS5 -> 5939.4918 | AU6: 5556.2076 | AV6: =+AO6/AU6-1 -> 0.022287029 | AW6: =AW3+AW5 -> 4048.391 | AX6: =AX3+AX5 -> 5077.175 | AY6: =AY3+AY5 -> 6039.352 | AZ6: =AZ3+AZ5 -> 6844.987 | BA6: =BA3+BA5 -> 6836.86 | BB6: =BB3+BB5 -> 6799.948 | BC6: =BC3+BC5 -> 6830.977 | BD6: =BD3+BD5 -> 7491.3 | ... CD6: =CD3+CD5 -> 24121.062
A7: Margin (%) | B7: =B6/B3 -> 0.39370855 | C7: =C6/C3 -> 0.39099071 | D7: =D6/D3 -> 0.38358593 | E7: =E6/E3 -> 0.37851172 | F7: =F6/F3 -> 0.35514036 | G7: =G6/G3 -> 0.3538818 | H7: =H6/H3 -> 0.34844055 | I7: =I6/I3 -> 0.36187852 | ... AS7: =AS6/AS3 -> 0.41219635 | AU7: 0.3975233 | AV7: =+AO7-AU7 -> 0.0065219761 | AW7: =AW6/AW3 -> 0.39283886 | AX7: =AX6/AX3 -> 0.41312353 | AY7: =AY6/AY3 -> 0.43548135 | AZ7: =AZ6/AZ3 -> 0.43032982 | BA7: =BA6/BA3 -> 0.43730841 | BB7: =BB6/BB3 -> 0.42246093 | BC7: =BC6/BC3 -> 0.39946839 | BD7: =BD6/BD3 -> 0.37836933 | ... CD7: =CD6/CD3 -> 0.39311504
A8: General & Admininstrative Expenses | B8: -1385.949 | C8: -1505.344 | D8: -1298.673 | E8: -1576.557 | F8: -1556.581 | G8: =+G10+G11 -> -1604.777 | H8: =+H10+H11 -> -1642.969 | I8: =+I10+I11 -> -1624.922 | J8: =+J10+J11 -> -1707.779 | K8: =+K10+K11 -> -1781.698 | L8: =+L10+L11 -> -1666.096 | M8: =+M10+M11 -> -1690.269 | N8: =+N10+N11 -> -1817.224 | ... AO8: =+AO10+AO11 -> -2467.304 | AP8: =+FAT!AP71 -> -2388.1114 | AQ8: =+FAT!AQ71 -> -2427.8699 | AR8: =+FAT!AR71 -> -2426.1828 | AS8: =+FAT!AS71 -> -2553.6596 | AU8: -2452.979 | AV8: =+AO8/AU8-1 -> 0.005839838 | AW8: -1105.632 | AX8: -1286.713 | AY8: -1459.176 | AZ8: -1757.692 | BA8: -1951.21 | BB8: -2097.291 | BC8: -2355.363 | BD8: -2668.549 | BE8: -2940.21 | BF8: -3011.227 | BG8: -3169.131 | BH8: -3267.238 | BI8: -3434.906 | BJ8: -3674.838 | BK8: -3895 | BL8: -4697.221 | BM8: -4709.51 | BN8: -4857.069 | BO8: -5289.686 | BP8: -5766.523 | BQ8: =+BQ10+BQ11 -> -6432.926 | BR8: =+BR10+BR11 -> -6845.842 | BS8: =+BS10+BS11 -> -7346.593 | BT8: =+BT10+BT11 -> -7504.876 | BU8: =+BU10+BU11 -> -7450.885 | BV8: =+BV10+BV11 -> -7848.084 | BW8: =+BW10+BW11 -> -8784.296 | BX8: =+SUMIFS($B8:$AO8,$B$1:$AO$1,"="&BX$1) -> -9572.8899 | BY8: =+SUMIFS($B8:$AS8,$B$1:$AS$1,"="&BY$1) -> -9464.564 | BZ8: =+SUMIFS($B8:$AS8,$B$1:$AS$1,"="&BZ$1) -> -9795.8237 | CA8: =+FAT!CA71 -> -10138.678 | CB8: =+FAT!CB71 -> -10493.531 | CC8: =+FAT!CC71 -> -10860.805 | CD8: =+FAT!CD71 -> -11240.933
A9: Chg YoY | C9: =C8/B8-1 -> 0.086146749 | D9: =D8/C8-1 -> -0.13729154 | E9: =E8/D8-1 -> 0.21397534 | F9: =F8/E8-1 -> -0.012670649 | G9: =G8/F8-1 -> 0.030962732 | H9: =H8/G8-1 -> 0.023798945 | I9: =I8/H8-1 -> -0.010984383 | J9: =J8/I8-1 -> 0.050991371 | ... AS9: =AS8/AR8-1 -> 0.052542128 | AU9: 0.04643114 | AW9: =AW8/A8-1 -> #VALUE! | AX9: =AX8/AW8-1 -> 0.16378053 | AY9: =AY8/AX8-1 -> 0.13403377 | AZ9: =AZ8/AY8-1 -> 0.20457847 | BA9: =BA8/AZ8-1 -> 0.11009779 | BB9: =BB8/BA8-1 -> 0.074866877 | BC9: =BC8/BB8-1 -> 0.12305016 | BD9: =BD8/BC8-1 -> 0.13296719 | BE9: =BE8/BD8-1 -> 0.10180102 | ... CD9: =CD8/CC8-1 -> 0.035
A10: Selling | F10: -1063.753 | G10: -1103.351 | H10: -1131.587 | I10: -1150.137 | J10: -1157.975 | K10: -1228.681 | L10: -1194.458 | M10: -1133.704 | N10: -1229.273 | O10: -1316.393 | P10: -1242.548 | Q10: -1175.834 | R10: -1306.122 | S10: -1308.885 | T10: -1252.027 | U10: -1218.73 | V10: -1297.448 | W10: -1226.776 | X10: -1319.511 | Y10: -1283.357 | Z10: -1310.567 | AA10: -1382.241 | AB10: -1377.03 | AC10: -1363.433 | AD10: -1461.417 | AE10: -1516.571 | AF10: -1479.836 | AG10: -1590.404 | AH10: -1718.988 | AI10: -1687.386 | AJ10: -1592.9219 | AK10: -1664.999 | AL10: -1676.541 | AM10: -1710.924 | AN10: -1684.971 | AO10: -1768.048 | BQ10: =+SUMIFS($B10:$AK10,$B$1:$AK$1,"="&BQ$1) -> -4448.828 | BR10: =+SUMIFS($B10:$AK10,$B$1:$AK$1,"="&BR$1) -> -4714.818 | BS10: =+SUMIFS($B10:$AK10,$B$1:$AK$1,"="&BS$1) -> -4964.048 | BT10: =+SUMIFS($B10:$AK10,$B$1:$AK$1,"="&BT$1) -> -5085.764 | BU10: =+SUMIFS($B10:$AK10,$B$1:$AK$1,"="&BU$1) -> -5127.092 | BV10: =+SUMIFS($B10:$AK10,$B$1:$AK$1,"="&BV$1) -> -5433.271 | BW10: =+SUMIFS($B10:$AK10,$B$1:$AK$1,"="&BW$1) -> -6048.228 | BX10: =+SUMIFS($B10:$AO10,$B$1:$AO$1,"="&BX$1) -> -6664.2949 | BY10: =+SUMIFS($B10:$AS10,$B$1:$AS$1,"="&BY$1) -> -6840.484 | BZ10: =+SUMIFS($B10:$AS10,$B$1:$AS$1,"="&BZ$1) -> 0
A11: Admin Exp | F11: -496.505 | G11: -501.426 | H11: -511.382 | I11: -474.785 | J11: -549.804 | K11: -553.017 | L11: -471.638 | M11: -556.565 | N11: -587.951 | O11: -594.767 | P11: -594.765 | Q11: -605.062 | R11: -619.809 | S11: -592.42 | T11: -592.333 | U11: -614.55 | V11: -625.846 | W11: -585.593 | X11: -546.326 | Y11: -566.028 | Z11: -624.84 | AA11: -619.07 | AB11: -622.306 | AC11: -548.597 | AD11: -681.51 | AE11: -692.352 | AF11: -668.249 | AG11: -693.957 | AH11: -717.34 | AI11: -737.826 | AJ11: -665.449 | AK11: -787.98 | AL11: -630.813 | AM11: -634.844 | AN11: -659.167 | AO11: -699.256 | BQ11: =+SUMIFS($B11:$AK11,$B$1:$AK$1,"="&BQ$1) -> -1984.098 | BR11: =+SUMIFS($B11:$AK11,$B$1:$AK$1,"="&BR$1) -> -2131.024 | BS11: =+SUMIFS($B11:$AK11,$B$1:$AK$1,"="&BS$1) -> -2382.545 | BT11: =+SUMIFS($B11:$AK11,$B$1:$AK$1,"="&BT$1) -> -2419.112 | BU11: =+SUMIFS($B11:$AK11,$B$1:$AK$1,"="&BU$1) -> -2323.793 | BV11: =+SUMIFS($B11:$AK11,$B$1:$AK$1,"="&BV$1) -> -2414.813 | BW11: =+SUMIFS($B11:$AK11,$B$1:$AK$1,"="&BW$1) -> -2736.068 | BX11: =+SUMIFS($B11:$AO11,$B$1:$AO$1,"="&BX$1) -> -2908.595 | BY11: =+SUMIFS($B11:$AS11,$B$1:$AS$1,"="&BY$1) -> -2624.08 | BZ11: =+SUMIFS($B11:$AS11,$B$1:$AS$1,"="&BZ$1) -> 0
A12: Other Income | G12: 2.357 | H12: 4.104 | I12: 2.265 | J12: 2.392 | K12: -2.708 | L12: 3.507 | M12: 5.491 | N12: 2.31 | O12: 9.186 | P12: 7.189 | Q12: 3.782 | R12: 2.831 | S12: 1.444 | T12: 1.164 | U12: 27.453 | V12: 1.755 | W12: 1.247 | X12: 4.846 | Y12: 7.08 | Z12: 3.055 | AA12: 2.676 | AB12: 7.936 | AC12: 1.989 | AD12: 2.759 | AE12: 1.93 | AF12: 1.039 | AG12: 10.808 | AH12: 7.893 | AI12: 9.07 | AJ12: 11.516 | AK12: 8.033 | AL12: 0.733 | AM12: 16.149 | AN12: 2.881 | AO12: 2.604 | BQ12: =+SUMIFS($B12:$AK12,$B$1:$AK$1,"="&BQ$1) -> 8.726 | BR12: =+SUMIFS($B12:$AK12,$B$1:$AK$1,"="&BR$1) -> 8.682 | BS12: =+SUMIFS($B12:$AK12,$B$1:$AK$1,"="&BS$1) -> 22.467 | BT12: =+SUMIFS($B12:$AK12,$B$1:$AK$1,"="&BT$1) -> 32.892 | BU12: =+SUMIFS($B12:$AK12,$B$1:$AK$1,"="&BU$1) -> 14.928 | BV12: =+SUMIFS($B12:$AK12,$B$1:$AK$1,"="&BV$1) -> 15.656 | BW12: =+SUMIFS($B12:$AK12,$B$1:$AK$1,"="&BW$1) -> 16.536 | BX12: =+SUMIFS($B12:$AO12,$B$1:$AO$1,"="&BX$1) -> 36.512 | BY12: =+SUMIFS($B12:$AS12,$B$1:$AS$1,"="&BY$1) -> 22.367 | BZ12: =+SUMIFS($B12:$AS12,$B$1:$AS$1,"="&BZ$1) -> 0
A13: As % Revenues | B13: =-B8/(B3) -> 0.15878766 | C13: =-C8/(C3) -> 0.17045452 | D13: =-D8/(D3) -> 0.14893966 | E13: =-E8/(E3) -> 0.16805551 | F13: =-F8/(F3) -> 0.16332613 | G13: =-G8/(G3) -> 0.16706151 | H13: =-H8/(H3) -> 0.17863681 | I13: =-I8/(I3) -> 0.17227596 | ... AG13: =-AG8/(AG3) -> 0.17083903 | AH13: =-AH8/AH3 -> 0.17667895 | AI13: =-AI8/AI3 -> 0.1723921 | AJ13: =-AJ8/AJ3 -> 0.17167871 | AK13: =-AK8/AK3 -> 0.17813284 | AL13: =-AL8/AL3 -> 0.16680069 | AM13: =-AM8/AM3 -> 0.16672125 | AN13: =-AN8/AN3 -> 0.17480522 | AO13: =-AO8/AO3 -> 0.1755098 | ... AS13: =-AS8/AS3 -> 0.17722209 | AU13: 0.17550034 | AW13: =-AW8/(AW3) -> 0.10728588 | AX13: =-AX8/(AX3) -> 0.10469827 | AY13: =-AY8/(AY3) -> 0.10521724 | AZ13: =-AZ8/(AZ3) -> 0.11050237 | BA13: =-BA8/(BA3) -> 0.12480591 | BB13: =-BB8/(BB3) -> 0.13029857 | BC13: =-BC8/(BC3) -> 0.13773917 | BD13: =-BD8/(BD3) -> 0.13478263 | ... BZ13: =-BZ8/(BZ3) -> 0.17280841 | CA13: =-CA8/CA3 -> 0.17534971 | CB13: =-CB8/CB3 -> 0.17792838 | CC13: =-CC8/CC3 -> 0.18054498 | CD13: =-CD8/CD3 -> 0.18320005
A14: Operating Income | B14: =B8+B6 -> 2050.464 | C14: =C8+C6 -> 1947.633 | D14: =D8+D6 -> 2045.988 | E14: =E8+E6 -> 1974.325 | F14: =F8+F6 -> 1828.087 | G14: =G8+G6+G12 -> 1796.935 | H14: =H8+H6+H12 -> 1565.833 | I14: =I8+I6+I12 -> 1790.613 | J14: =J8+J6+J12 -> 2020.584 | K14: =K8+K6+K12 -> 2030.177 | L14: =L8+L6+L12 -> 1695.043 | M14: =M8+M6+M12 -> 1757.602 | N14: =N8+N6+N12 -> 2060.086 | ... AS14: =AS8+AS6+AS12 -> 3385.8322 | AU14: 3103.2286 | AW14: =AW8+AW6 -> 2942.759 | AX14: =AX8+AX6 -> 3790.462 | AY14: =AY8+AY6 -> 4580.176 | AZ14: =AZ8+AZ6 -> 5087.295 | BA14: =BA8+BA6 -> 4885.65 | BB14: =BB8+BB6 -> 4702.657 | BC14: =BC8+BC6 -> 4475.614 | BD14: =BD8+BD6 -> 4822.751 | ... BP14: =BP8+BP6 -> 8018.41 | BQ14: =BQ8+BQ6+BQ12 -> 6977.791 | BR14: =BR8+BR6+BR12 -> 7503.406 | BS14: =BS8+BS6+BS12 -> 8997.295 | BT14: =BT8+BT6+BT12 -> 10537.29 | BU14: =BU8+BU6+BU12 -> 8349.719 | BV14: =BV8+BV6+BV12 -> 8940.054 | BW14: =BW8+BW6+BW12 -> 11932.279 | BX14: =BX8+BX6+BX12 -> 12847.35 | ... CD14: =CD8+CD6+CD12 -> 12880.129
A15: Op. Margin (%) | B15: =B14/B$3 -> 0.23492089 | C15: =C14/C$3 -> 0.2205362 | D15: =D14/D$3 -> 0.23464626 | E15: =E14/E$3 -> 0.2104562 | F15: =F14/F$3 -> 0.19181422 | G15: =G14/G$3 -> 0.18706566 | H15: =H14/H$3 -> 0.17024996 | I15: =I14/I$3 -> 0.18984269 | ... AS15: =AS14/AS$3 -> 0.23497425 | AU15: 0.22202296 | AW15: =AW14/AW$3 -> 0.28555297 | AX15: =AX14/AX$3 -> 0.30842527 | AY15: =AY14/AY$3 -> 0.33026411 | AZ15: =AZ14/AZ$3 -> 0.31982745 | BA15: =BA14/BA$3 -> 0.3125025 | BB15: =BB14/BB$3 -> 0.29216236 | BC15: =BC14/BC$3 -> 0.26172923 | BD15: =BD14/BD$3 -> 0.2435867 | ... CD15: =CD14/CD$3 -> 0.20991498
A16: EBITDA | B16: =+B14-B65 -> 2458.685 | C16: =+C14-C65 -> 2360.149 | D16: =+D14-D65 -> 2458.251 | E16: =+E14-E65 -> 2342.244 | F16: =+F14-F65 -> 2264.23 | G16: =+G14-G65 -> 2212.047 | H16: =+H14-H65 -> 1933.769 | I16: =+I14-I65 -> 2171.246 | ... AM16: =+AM14-AM65 -> 3568.889 | AN16: 3355 | AO16: =+AO14-AO65 -> 3713.259 | AP16: =+AP14-AP65 -> 3689.4182 | AQ16: =+AQ14-AQ65 -> 3876.5602 | AR16: =+AR14-AR65 -> 3459.206 | AS16: =+AS14-AS65 -> 3877.5065 | AU16: 3672.6968 | AV16: =+AO16/AU16-1 -> 0.011044257 | AW16: =+AW14-AW65 -> 3554.901 | AX16: =+AX14-AX65 -> 4499.979 | AY16: =+AY14-AY65 -> 5391.918 | AZ16: =+AZ14-AZ65 -> 5923.289 | BA16: =+BA14-BA65 -> 5816.681 | BB16: =+BB14-BB65 -> 5786.37 | BC16: =+BC14-BC65 -> 5646.98 | BD16: =+BD14-BD65 -> 6063.76 | ... CD16: =+CD14-CD65 -> 14895.863
A17: EBITDA Margin | B17: =+B16/B3 -> 0.28169062 | C17: =+C16/C3 -> 0.26724659 | D17: =+D16/D3 -> 0.28192707 | E17: =+E16/E3 -> 0.24967509 | F17: =+F16/F3 -> 0.23757705 | G17: =+G16/G3 -> 0.23027992 | H17: =+H16/H3 -> 0.21025492 | I17: =+I16/I3 -> 0.23019781 | ... AG17: =+AG16/AG3 -> 0.27744175 | AH17: =AH16/AH$3 -> 0.28240663 | AI17: =AI16/AI$3 -> 0.286721 | AJ17: =AJ16/AJ$3 -> 0.26338198 | AK17: =AK16/AK$3 -> 0.25434581 | AL17: =AL16/AL$3 -> 0.25089055 | AM17: =AM16/AM$3 -> 0.25365238 | AN17: =AN16/AN$3 -> 0.25018643 | AO17: =AO16/AO$3 -> 0.26413987 | ... AS17: =AS16/AS$3 -> 0.26909609 | AU17: 0.26276602 | AV17: =+AO17-AU17 -> 0.0013738524 | AW17: =+AW16/AW3 -> 0.34495266 | AX17: =+AX16/AX3 -> 0.3661578 | AY17: =+AY16/AY3 -> 0.38879663 | AZ17: =+AZ16/AZ3 -> 0.37238462 | BA17: =+BA16/BA3 -> 0.37205435 | BB17: =+BB16/BB3 -> 0.35949028 | BC17: =+BC16/BC3 -> 0.33022948 | BD17: =+BD16/BD3 -> 0.30626738 | ... BZ17: =+BZ16/BZ3 -> 0.2628988 | CA17: =CA16/CA$3 -> 0.25692555 | CB17: =CB16/CB$3 -> 0.25225174 | CC17: =CC16/CC$3 -> 0.24753228 | CD17: =CD16/CD$3 -> 0.24276658
A18: Financial Income | B18: 64.649 | C18: 83.848 | D18: 80.271 | E18: 41.006 | F18: 89.306 | G18: 72.796 | H18: 55.215 | I18: 47.156 | J18: 102.278 | K18: 37.924 | L18: 89.409 | M18: 58.503 | N18: 95.196 | O18: 87.87 | P18: 76.411 | Q18: 62.251 | R18: 141.812 | S18: 58.338 | T18: 211.122 | U18: 187.161 | V18: 158.794 | W18: 114.064 | X18: 113.424 | Y18: 118.997 | Z18: 113.652 | AA18: 100.584 | AB18: 187.662 | AC18: 314.18 | AD18: 321.205 | AE18: 341.753 | AF18: 316.097 | AG18: 385.093 | AH18: 368.48 | AI18: 290.533 | AJ18: 314.363 | AK18: 234.835 | AL18: 275.092 | AM18: 156.878 | AN18: 109.825 | AO18: 113.351 | AP18: =AO56*AP148/4 -> 109.24788 | AQ18: =AP56*AQ148/4 -> 182.42315 | AR18: =AQ56*AR148/4 -> 154.67496 | AS18: =AR56*AS148/4 -> 144.71073 | AU18: 129.61321 | AW18: 295.808 | AX18: 435.331 | AY18: 400.474 | AZ18: 207.069 | BA18: 131.345 | BB18: 56.392 | BC18: 49.398 | BD18: 78.32 | BE18: 93.12 | BF18: 105.203 | BG18: 198.181 | BH18: 206.737 | BI18: 269.36 | BJ18: 198.807 | BK18: 174.234 | BL18: 103.149 | BM18: 126.874 | BN18: 227.327 | BO18: 206.687 | BP18: 269.774 | BQ18: =+SUMIFS($B18:$AK18,$B$1:$AK$1,"="&BQ$1) -> 264.473 | BR18: =+SUMIFS($B18:$AK18,$B$1:$AK$1,"="&BR$1) -> 288.114 | BS18: =+SUMIFS($B18:$AK18,$B$1:$AK$1,"="&BS$1) -> 321.728 | BT18: =+SUMIFS($B18:$AK18,$B$1:$AK$1,"="&BT$1) -> 598.433 | BU18: =+SUMIFS($B18:$AK18,$B$1:$AK$1,"="&BU$1) -> 505.279 | BV18: =+SUMIFS($B18:$AK18,$B$1:$AK$1,"="&BV$1) -> 716.078 | BW18: =+SUMIFS($B18:$AK18,$B$1:$AK$1,"="&BW$1) -> 1364.148 | BX18: =+SUMIFS($B18:$AO18,$B$1:$AO$1,"="&BX$1) -> 1208.211 | BY18: =+SUMIFS($B18:$AS18,$B$1:$AS$1,"="&BY$1) -> 655.146 | BZ18: =+SUMIFS($B18:$AS18,$B$1:$AS$1,"="&BZ$1) -> 591.05673 | CA18: =BZ56*CA148 -> 441.54435 | CB18: =CA56*CB148 -> 540.60512 | CC18: =CB56*CC148 -> 643.1682 | CD18: =CC56*CD148 -> 750.15066
A19: Financial Expense | B19: -294.576 | C19: -296.024 | D19: -308.224 | E19: -326.169 | F19: -333.154 | G19: -372.366 | H19: -367.679 | I19: -428.904 | J19: -400.968 | K19: -492.473 | L19: -489.413 | M19: -417.979 | N19: -462.856 | O19: -466.389 | P19: -467.203 | Q19: -460.094 | R19: -553.41 | S19: -459.472 | T19: -638.915 | U19: -610.808 | V19: -581.016 | W19: -566.402 | X19: -558.476 | Y19: -539.314 | Z19: -532.603 | AA19: -529.227 | AB19: -612.676 | AC19: -731.392 | AD19: -736.617 | AE19: -723.034 | AF19: -730.112 | AG19: -718.38 | AH19: -684 | AI19: -646.018 | AJ19: -601.191 | AK19: -584.78 | AL19: -569.888 | AM19: -509.047 | AN19: -513.838 | AO19: -512.189 | AP19: =-AP147*AVERAGE(AO143:AP143)/4 -> -439.62335 | AQ19: =-AQ147*AVERAGE(AP143:AQ143)/4 -> -430.1401 | AR19: =-AR147*AVERAGE(AQ143:AR143)/4 -> -430.86899 | AS19: =-AS147*AVERAGE(AR143:AS143)/4 -> -429.19726 | AU19: -432.40945 | AW19: -195.328 | AX19: -218.303 | AY19: -310.505 | AZ19: -425.767 | BA19: -440.695 | BB19: -455.956 | BC19: -492.859 | BD19: -520.195 | BE19: -512.016 | BF19: -478.397 | BG19: -546.48 | BH19: -632.884 | BI19: -778.823 | BJ19: -684.813 | BK19: -805.863 | BL19: -811.661 | BM19: -746.952 | BN19: -906.458 | BO19: -1075.526 | BP19: -1224.993 | BQ19: =+SUMIFS($B19:$AK19,$B$1:$AK$1,"="&BQ$1) -> -1502.103 | BR19: =+SUMIFS($B19:$AK19,$B$1:$AK$1,"="&BR$1) -> -1800.833 | BS19: =+SUMIFS($B19:$AK19,$B$1:$AK$1,"="&BS$1) -> -1856.542 | BT19: =+SUMIFS($B19:$AK19,$B$1:$AK$1,"="&BT$1) -> -2262.605 | BU19: =+SUMIFS($B19:$AK19,$B$1:$AK$1,"="&BU$1) -> -2245.208 | BV19: =+SUMIFS($B19:$AK19,$B$1:$AK$1,"="&BV$1) -> -2405.898 | BW19: =+SUMIFS($B19:$AK19,$B$1:$AK$1,"="&BW$1) -> -2908.143 | BX19: =+SUMIFS($B19:$AO19,$B$1:$AO$1,"="&BX$1) -> -2515.989 | BY19: =+SUMIFS($B19:$AS19,$B$1:$AS$1,"="&BY$1) -> -2104.962 | BZ19: =+SUMIFS($B19:$AS19,$B$1:$AS$1,"="&BZ$1) -> -1729.8297 | CA19: =-CA147*AVERAGE(BZ143:CA143) -> -1442.9924 | CB19: =-CB147*AVERAGE(CA143:CB143) -> -1517.0241 | CC19: =-CC147*AVERAGE(CB143:CC143) -> -1588.8249 | CD19: =-CD147*AVERAGE(CC143:CD143) -> -1569.6678
A20: Equity Income
A21: FX Gain/Loss | B21: -223 | C21: 36.059 | D21: 47.209 | E21: 21.682 | F21: -33.063 | AW21: -59.502 | AX21: -643.196 | AY21: -17.908 | AZ21: -50.158 | BA21: -77.962 | BB21: -588.615 | BC21: -586.62 | BD21: -67.735 | BE21: -914.702 | BF21: -218.421 | BG21: 0 | BH21: 0 | BI21: 0 | BJ21: 0 | BK21: 0 | BL21: 0 | BM21: 0 | BN21: -116.922 | BO21: 0 | BP21: -118.05
A22: Other Income/Expense | B22: 0 | C22: 0 | D22: 0 | E22: 0 | F22: 0 | AW22: 382.728 | AX22: 11.456 | AY22: 15.041 | AZ22: 33.449 | BA22: 5.468 | BB22: 5.142 | BC22: 5.479 | BD22: 10.233 | BE22: 12.077 | BF22: -4.387 | BG22: -461.175 | BH22: 375.647 | BI22: 571.644 | BJ22: 543.926 | BK22: 487.291 | BL22: 0 | BM22: 0 | BN22: 0 | BO22: 0 | BP22: 0
A23: Pre Tax Income | B23: =+SUM(B18:B22)+B14 -> 1597.537 | C23: =+SUM(C18:C22)+C14 -> 1771.516 | D23: =+SUM(D18:D22)+D14 -> 1865.244 | E23: =+SUM(E18:E22)+E14 -> 1710.844 | F23: =+SUM(F18:F22)+F14 -> 1551.176 | G23: =+SUM(G18:G22)+G14 -> 1497.365 | H23: =+SUM(H18:H22)+H14 -> 1253.369 | I23: =+SUM(I18:I22)+I14 -> 1408.865 | ... AS23: =+SUM(AS18:AS22)+AS14 -> 3101.3457 | AU23: 2800.4324 | AW23: =+SUM(AW18:AW22)+AW14 -> 3366.465 | AX23: =+SUM(AX18:AX22)+AX14 -> 3375.75 | AY23: =+SUM(AY18:AY22)+AY14 -> 4667.278 | AZ23: =+SUM(AZ18:AZ22)+AZ14 -> 4851.888 | BA23: =+SUM(BA18:BA22)+BA14 -> 4503.806 | BB23: =+SUM(BB18:BB22)+BB14 -> 3719.62 | BC23: =+SUM(BC18:BC22)+BC14 -> 3451.012 | BD23: =+SUM(BD18:BD22)+BD14 -> 4323.374 | ... CD23: =+SUM(CD18:CD22)+CD14 -> 12060.612
A24: Income Tax | B24: -487.742 | C24: -593.461 | D24: -552.43 | E24: -522.296 | F24: -466.576 | G24: -478.738 | H24: -400.115 | I24: -358.176 | J24: -518.583 | K24: -482.316 | L24: -389.329 | M24: -392.376 | N24: -535.785 | O24: -610.962 | P24: -528.639 | Q24: -638.625 | R24: -770.255 | S24: -749.806 | T24: -619.905 | U24: -652.167 | V24: -735.677 | W24: -564.139 | X24: -418.114 | Y24: -432.122 | Z24: -494.955 | AA24: -552.252 | AB24: -583.408 | AC24: -683.783 | AD24: -754.384 | AE24: -848.714 | AF24: -858.714 | AG24: -913.695 | AH24: -1003.053 | AI24: -1049.445 | AJ24: -853.702 | AK24: -802.609 | AL24: -842.274 | AM24: -828.022 | AN24: -768.573 | AO24: -621.112 | AP24: =-AP25*AP23 -> -886.90571 | AQ24: =-AQ25*AQ23 -> -962.26921 | AR24: =-AR25*AR23 -> -833.04025 | AS24: =-AS25*AS23 -> -961.41715 | AU24: -879.78892 | AW24: -1412.197 | AX24: -1492.884 | AY24: -2098.491 | AZ24: -2035.628 | BA24: -1963.351 | BB24: -1784.682 | BC24: -1590.598 | BD24: -1678.99 | BE24: -1500.179 | BF24: -1759.949 | BG24: -1214.347 | BH24: -831.338 | BI24: -1488.116 | BJ24: -1687.168 | BK24: -1483 | BL24: -1838.273 | BM24: -1990.223 | BN24: -1529.881 | BO24: -1940.202 | BP24: -2155.929 | BQ24: =+SUMIFS($B24:$AK24,$B$1:$AK$1,"="&BQ$1) -> -1703.605 | BR24: =+SUMIFS($B24:$AK24,$B$1:$AK$1,"="&BR$1) -> -1782.604 | BS24: =+SUMIFS($B24:$AK24,$B$1:$AK$1,"="&BS$1) -> -2314.011 | BT24: =+SUMIFS($B24:$AK24,$B$1:$AK$1,"="&BT$1) -> -2792.133 | BU24: =+SUMIFS($B24:$AK24,$B$1:$AK$1,"="&BU$1) -> -2150.052 | BV24: =+SUMIFS($B24:$AK24,$B$1:$AK$1,"="&BV$1) -> -2314.398 | BW24: =+SUMIFS($B24:$AK24,$B$1:$AK$1,"="&BW$1) -> -3375.507 | BX24: =+SUMIFS($B24:$AO24,$B$1:$AO$1,"="&BX$1) -> -3708.809 | BY24: =+SUMIFS($B24:$AS24,$B$1:$AS$1,"="&BY$1) -> -3059.981 | BZ24: =+SUMIFS($B24:$AS24,$B$1:$AS$1,"="&BZ$1) -> -3643.6323 | CA24: =-CA25*CA23 -> -3735.471 | CB24: =-CB25*CB23 -> -3749.176 | CC24: =-CC25*CC23 -> -3760.9794 | CD24: =-CD25*CD23 -> -3799.0927
A25: Effective Tax Rate | B25: =-B24/B23 -> 0.30530873 | C25: =-C24/C23 -> 0.33500177 | D25: =-D24/D23 -> 0.29617037 | E25: =-E24/E23 -> 0.30528558 | F25: =-F24/F23 -> 0.30078856 | G25: =-G24/G23 -> 0.31972031 | H25: =-H24/H23 -> 0.31923161 | I25: =-I24/I23 -> 0.25423018 | ... AO25: =-AO24/AO23 -> 0.22052611 | AP25: 0.31 | AQ25: =+AP25 -> 0.31 | AR25: =+AQ25 -> 0.31 | AS25: =+AR25 -> 0.31 | AU25: 0.31416181 | AW25: =-AW24/AW23 -> 0.41948958 | AX25: =-AX24/AX23 -> 0.44223772 | AY25: =-AY24/AY23 -> 0.44961774 | AZ25: =-AZ24/AZ23 -> 0.41955379 | BA25: =-BA24/BA23 -> 0.43593152 | BB25: =-BB24/BB23 -> 0.47980224 | BC25: =-BC24/BC23 -> 0.4609077 | BD25: =-BD24/BD23 -> 0.38835178 | ... BZ25: =-BZ24/BZ23 -> 0.31 | CA25: 0.315 | CB25: 0.315 | CC25: 0.315 | CD25: 0.315
A26: Minorities | B26: 0 | C26: 0 | D26: 0 | E26: 4.353 | F26: 10.317999 | G26: -5.258 | H26: 1.219 | I26: 23.854 | J26: 3.352 | K26: 1.3 | L26: 1.491 | M26: 0 | N26: -4.209 | O26: 0 | P26: -2.403 | Q26: 0 | R26: 8.125 | S26: 69.897 | T26: 35.682 | U26: 30.879 | V26: 18.644 | W26: 6.146 | X26: 4.786 | Y26: 4.554 | Z26: 0.017 | AA26: -0.81 | AB26: 0.424 | AC26: -1.217 | AD26: 0.017 | AE26: 0.017 | AF26: 0.017 | AG26: 0.017 | AH26: 0 | AI26: 0 | AJ26: 0 | AK26: 0 | AL26: 0 | AM26: 0 | AN26: 0 | AO26: 0 | AP26: 0 | AQ26: 0 | AR26: 0 | AS26: 0 | AU26: 0 | AW26: 0 | AX26: 0 | AY26: 0 | AZ26: 0 | BA26: 0 | BB26: 0 | BC26: 0 | BD26: 0 | BE26: 0 | BF26: 0 | BG26: 0 | BH26: 0 | BI26: 0 | BJ26: 0 | BK26: 0 | BL26: 0 | BM26: 0 | BN26: 0 | BO26: 0 | BP26: 4.353 | BQ26: =+SUMIFS($B26:$AK26,$B$1:$AK$1,"="&BQ$1) -> 30.132999 | BR26: =+SUMIFS($B26:$AK26,$B$1:$AK$1,"="&BR$1) -> 6.143 | BS26: =+SUMIFS($B26:$AK26,$B$1:$AK$1,"="&BS$1) -> -6.612 | BT26: =+SUMIFS($B26:$AK26,$B$1:$AK$1,"="&BT$1) -> 144.583 | BU26: =+SUMIFS($B26:$AK26,$B$1:$AK$1,"="&BU$1) -> 34.13 | BV26: =+SUMIFS($B26:$AK26,$B$1:$AK$1,"="&BV$1) -> -1.586 | BW26: =+SUMIFS($B26:$AK26,$B$1:$AK$1,"="&BW$1) -> 0.068 | BX26: =+SUMIFS($B26:$AO26,$B$1:$AO$1,"="&BX$1) -> 0 | BY26: =+SUMIFS($B26:$AS26,$B$1:$AS$1,"="&BY$1) -> 0 | BZ26: =+SUMIFS($B26:$AS26,$B$1:$AS$1,"="&BZ$1) -> 0 | CA26: 0 | CB26: 0 | CC26: 0 | CD26: 0
A27: Net Income | B27: =+B26+B24+B23 -> 1109.795 | C27: =+C26+C24+C23 -> 1178.055 | D27: =+D26+D24+D23 -> 1312.814 | E27: =+E26+E24+E23 -> 1192.901 | F27: =+F26+F24+F23 -> 1094.918 | G27: =+G26+G24+G23 -> 1013.369 | H27: =+H26+H24+H23 -> 854.473 | I27: =+I26+I24+I23 -> 1074.543 | ... AS27: =+AS26+AS24+AS23 -> 2139.9285 | AU27: 1920.6435 | AV27: =+AO27/AU27-1 -> 0.14304868 | AW27: =+AW26+AW24+AW23 -> 1954.268 | AX27: =+AX26+AX24+AX23 -> 1882.866 | AY27: =+AY26+AY24+AY23 -> 2568.787 | AZ27: =+AZ26+AZ24+AZ23 -> 2816.26 | BA27: =+BA26+BA24+BA23 -> 2540.455 | BB27: =+BB26+BB24+BB23 -> 1934.938 | BC27: =+BC26+BC24+BC23 -> 1860.414 | BD27: =+BD26+BD24+BD23 -> 2644.384 | ... CD27: =+CD26+CD24+CD23 -> 8261.5191
A28: NI Margin | B28: =+B27/B3 -> 0.1271488 | C28: =+C27/C3 -> 0.13339462 | D28: =+D27/D3 -> 0.15056144 | E28: =+E27/E3 -> 0.12715911 | F28: =+F27/F3 -> 0.11488559 | G28: =+G27/G3 -> 0.10549438 | H28: =+H27/H3 -> 0.09290518 | I28: =+I27/I3 -> 0.11392419 | ... AS28: =+AS27/AS3 -> 0.14850946 | AU28: 0.13741397 | AW28: =+AW27/AW3 -> 0.18963396 | AX28: =+AX27/AX3 -> 0.15320651 | AY28: =+AY27/AY3 -> 0.18522829 | AZ28: =+AZ27/AZ3 -> 0.17705229 | BA28: =+BA27/BA3 -> 0.16249599 | BB28: =+BB27/BB3 -> 0.12021205 | BC28: =+BC27/BC3 -> 0.10879507 | BD28: =+BD27/BD3 -> 0.13356211 | ... CD28: =+CD27/CD3 -> 0.1346428
A30: Total Shares | B30: 3091.6731 | C30: 3088.444 | D30: 3088.054 | E30: 3087.974 | F30: 3084.932 | G30: 3084.932 | H30: 3084.932 | I30: 3084.932 | J30: 3084.932 | K30: 3084.932 | L30: 3084.932 | M30: 3084.932 | N30: 3084.932 | O30: 3084.932 | P30: 3084.932 | Q30: 3084.932 | R30: 3084.932 | S30: 3084.932 | T30: 3084.932 | U30: 3084.932 | V30: 3084.932 | W30: 3084.932 | X30: 3084.932 | Y30: 3084.932 | Z30: 3084.932 | AA30: 3084.932 | AB30: 3084.932 | AC30: 3075.1326 | AD30: 3075.1326 | AE30: 3075.1326 | AF30: 3075.1326 | AG30: 3075.1326 | AH30: 3075.1326 | AI30: 3075.1326 | AJ30: 3056.7271 | AK30: =3043.57741 -> 3043.5774 | AL30: 3038.0789 | AM30: 3026.384 | AN30: 3010.7094 | AO30: 3000.8487 | AP30: =+AO30+AP111 -> 2984.7196 | AQ30: =+AP30+AQ111 -> 2968.5906 | AR30: =+AQ30+AR111 -> 2952.4616 | AS30: =+AR30+AS111 -> 2936.3325 | AU30: 2994.5804 | AW30: 1127.635 | AX30: 1171.767 | AY30: 1189.518 | AZ30: 1257.505 | BA30: 1231.187 | BB30: 1204.017 | BC30: 1187.222 | BD30: 1169.583 | BE30: 1157.004 | BF30: 1139.845 | BG30: 1118.155 | BH30: 1098.846 | BI30: 1076.998 | BJ30: 1061.674 | BK30: 3154.6461 | BL30: 3141.2595 | BM30: 3127.3495 | BN30: 3099.0909 | BO30: 3095.5284 | BP30: =+SUMIFS($B30:$AK30,$B$2:$AK$2,"="&BP$2) -> 3087.974 | BQ30: =+SUMIFS($B30:$AK30,$B$2:$AK$2,"="&BQ$2) -> 3084.932 | BR30: =+SUMIFS($B30:$AK30,$B$2:$AK$2,"="&BR$2) -> 3084.932 | BS30: =+SUMIFS($B30:$AK30,$B$2:$AK$2,"="&BS$2) -> 3084.932 | BT30: =+SUMIFS($B30:$AK30,$B$2:$AK$2,"="&BT$2) -> 3084.932 | BU30: =+SUMIFS($B30:$AK30,$B$2:$AK$2,"="&BU$2) -> 3084.932 | BV30: =+SUMIFS($B30:$AK30,$B$2:$AK$2,"="&BV$2) -> 3075.1326 | BW30: =+SUMIFS($B30:$AK30,$B$2:$AK$2,"="&BW$2) -> 3075.1326 | BX30: =+SUMIFS($B30:$AO30,$B$2:$AO$2,"="&BX$2) -> 3043.5774 | BY30: =+SUMIFS($B30:$AS30,$B$2:$AS$2,"="&BY$2) -> 3000.8487 | BZ30: =+SUMIFS($B30:$AS30,$B$2:$AS$2,"="&BZ$2) -> 2936.3325 | CA30: =+BZ30+CA111 -> 2936.3325 | CB30: =+CA30+CB111 -> 2936.3325 | CC30: =+CB30+CC111 -> 2936.3325 | CD30: =+CC30+CD111 -> 2936.3325
A31: EPS | B31: =B27/B30 -> 0.3589626 | C31: =C27/C30 -> 0.38143965 | D31: =D27/D30 -> 0.42512663 | E31: =E27/E30 -> 0.38630539 | F31: =F27/F30 -> 0.35492452 | G31: =G27/G30 -> 0.3284899 | H31: =H27/H30 -> 0.27698277 | I31: =I27/I30 -> 0.34831983 | ... AS31: =AS27/AS30 -> 0.72877594 | AU31: 0.64137315 | AW31: =AW27/AW30 -> 1.7330679 | AX31: =AX27/AX30 -> 1.6068604 | AY31: =AY27/AY30 -> 2.1595192 | AZ31: =AZ27/AZ30 -> 2.2395617 | BA31: =BA27/BA30 -> 2.0634193 | BB31: =BB27/BB30 -> 1.6070687 | BC31: =BC27/BC30 -> 1.5670313 | BD31: =BD27/BD30 -> 2.2609631 | ... CD31: =CD27/CD30 -> 2.8135502
A32: DPS | B32: =-B113/B30 -> 0 | C32: =-C113/C30 -> 0.38059683 | D32: =-D113/D30 -> -0.3806449 | E32: =-E113/E30 -> 1.8597245 | F32: =-F113/F30 -> 1.8615584 | G32: =-G113/G30 -> 0 | H32: =-H113/H30 -> 0 | I32: =-I113/I30 -> 0 | ... AS32: =-AS113/AS30 -> 1.1529283 | AU32: 1.041434 | AW32: =-AW113/AW30 -> 1.1716007 | AX32: =-AX113/AX30 -> 1.9499346 | AY32: =-AY113/AY30 -> 1.5176139 | AZ32: =-AZ113/AZ30 -> 1.6052922 | BA32: =-BA113/BA30 -> 1.7859383 | BB32: =-BB113/BB30 -> 1.9381346 | BC32: =-BC113/BC30 -> 1.9775577 | BD32: =-BD113/BD30 -> 2.0665203 | ... CD32: =-CD113/CD30 -> 2.2282593
A33: Revenue Growth | C33: =C3/B3-1 -> 0.011804796 | D33: =D3/C3-1 -> -0.012670312 | E33: =E3/D3-1 -> 0.075889015 | F33: =F3/E3-1 -> 0.015919126 | G33: =G3/F3-1 -> 0.0079111208 | H33: =H3/G3-1 -> -0.042541124 | I33: =I3/H3-1 -> 0.025532498 | J33: =J3/I3-1 -> 0.082185196 | ... AS33: =AS3/AR3-1 -> 0.048316704 | AU33: 0.04228647 | AW33: =AW3/A3-1 -> #VALUE! | AX33: =AX3/AW3-1 -> 0.19254338 | AY33: =AY3/AX3-1 -> 0.12844029 | AZ33: =AZ3/AY3-1 -> 0.14696563 | BA33: =BA3/AZ3-1 -> -0.017126405 | BB33: =BB3/BA3-1 -> 0.029556501 | BC33: =BC3/BB3-1 -> 0.062383605 | BD33: =BD3/BC3-1 -> 0.15781949 | BE33: =BE3/BD3-1 -> 0.11031946 | ... CD33: =CD3/CC3-1 -> 0.02
A34: EBITDA Growth | C34: =C16/B16-1 -> -0.040076708 | D34: =D16/C16-1 -> 0.04156602 | E34: =E16/D16-1 -> -0.047190869 | F34: =F16/E16-1 -> -0.033307375 | G34: =G16/F16-1 -> -0.023046687 | H34: =H16/G16-1 -> -0.12580112 | I34: =I16/H16-1 -> 0.12280526 | J34: =J16/I16-1 -> 0.12220541 | ... AS34: =AS16/AR16-1 -> 0.12092385 | AU34: 0.09469353 | AW34: =AW16/A16-1 -> #VALUE! | AX34: =AX16/AW16-1 -> 0.26585213 | AY34: =AY16/AX16-1 -> 0.19820959 | AZ34: =AZ16/AY16-1 -> 0.098549533 | BA34: =BA16/AZ16-1 -> -0.017998109 | BB34: =BB16/BA16-1 -> -0.0052110473 | BC34: =BC16/BB16-1 -> -0.024089369 | BD34: =BD16/BC16-1 -> 0.073805822 | BE34: =BE16/BD16-1 -> 0.096550325 | ... CD34: =CD16/CC16-1 -> 0.0003621052
A35: EPS Growth | C35: =C31/B31-1 -> 0.062616698 | D35: =D31/C31-1 -> 0.11453183 | E35: =E31/D31-1 -> -0.091316893 | F35: =F31/E31-1 -> -0.08123333 | G35: =G31/F31-1 -> -0.074479549 | H35: =H31/G31-1 -> -0.15679974 | I35: =I31/H31-1 -> 0.25755056 | J35: =J31/I31-1 -> 0.1229546 | ... AS35: =AS31/AR31-1 -> 0.16044589 | AU35: 0.1508699 | AW35: =AW31/A31-1 -> #VALUE! | AX35: =AX31/AW31-1 -> -0.072823156 | AY35: =AY31/AX31-1 -> 0.34393705 | AZ35: =AZ31/AY31-1 -> 0.037064934 | BA35: =BA31/AZ31-1 -> -0.078650384 | BB35: =BB31/BA31-1 -> -0.22116233 | BC35: =BC31/BB31-1 -> -0.02491331 | BD35: =BD31/BC31-1 -> 0.44283215 | BE35: =BE31/BD31-1 -> -0.028042788 | ... CD35: =CD31/CC31-1 -> 0.010133884
A37: ROE (%) | B37: =B27/AVERAGE(B88:B88) -> 0.36776931 | C37: =C27/AVERAGE(B88:C88) -> 0.31821268 | D37: =D27/AVERAGE(C88:D88) -> 0.25940299 | E37: =E27/AVERAGE(D88:E88) -> 0.18734913 | F37: =F27/AVERAGE(E88:F88) -> 0.21997739 | G37: =G27/AVERAGE(F88:G88) -> 0.28966733 | H37: =H27/AVERAGE(G88:H88) -> 0.1929575 | I37: =I27/AVERAGE(H88:I88) -> 0.19706328 | J37: =J27/AVERAGE(I88:J88) -> 0.29373258 | ... AS37: =AS27/AVERAGE(AR88:AS88) -> 0.23256559 | AU37: 0.40753742 | AW37: =AW27/AVERAGE(A88:AW88) -> 0.39921364 | AX37: =AX27/AVERAGE(AW88:AX88) -> 0.1641115 | AY37: =AY27/AVERAGE(AX88:AY88) -> 0.20602107 | AZ37: =AZ27/AVERAGE(AY88:AZ88) -> 0.23367838 | BA37: =BA27/AVERAGE(AZ88:BA88) -> 0.22181158 | BB37: =BB27/AVERAGE(BA88:BB88) -> 0.16608727 | BC37: =BC27/AVERAGE(BB88:BC88) -> 0.15668538 | BD37: =BD27/AVERAGE(BC88:BD88) -> 0.2172932 | BE37: =BE27/AVERAGE(BD88:BE88) -> 0.20937826 | ... CD37: =CD27/AVERAGE(CC88:CD88) -> 0.57436177
A38: ROA (%) | B38: =B27/AVERAGE(B73:B73) -> 0.029197685 | C38: =C27/AVERAGE(B73:C73) -> 0.031933413 | D38: =D27/AVERAGE(C73:D73) -> 0.0346884 | E38: =E27/AVERAGE(D73:E73) -> 0.029593851 | F38: =F27/AVERAGE(E73:F73) -> 0.027117264 | G38: =G27/AVERAGE(F73:G73) -> 0.025496112 | H38: =H27/AVERAGE(G73:H73) -> 0.021892361 | I38: =I27/AVERAGE(H73:I73) -> 0.027564662 | J38: =J27/AVERAGE(I73:J73) -> 0.030418164 | ... AS38: =AS27/AVERAGE(AR73:AS73) -> 0.044933977 | AU38: 0.043019571 | AW38: =AW27/AVERAGE(A73:AW73) -> 0.041931177 | AX38: =AX27/AVERAGE(AW73:AX73) -> 0.11481985 | AY38: =AY27/AVERAGE(AX73:AY73) -> 0.13723274 | AZ38: =AZ27/AVERAGE(AY73:AZ73) -> 0.13876788 | BA38: =BA27/AVERAGE(AZ73:BA73) -> 0.11861909 | BB38: =BB27/AVERAGE(BA73:BB73) -> 0.086120571 | BC38: =BC27/AVERAGE(BB73:BC73) -> 0.078842084 | BD38: =BD27/AVERAGE(BC73:BD73) -> 0.10659175 | BE38: =BE27/AVERAGE(BD73:BE73) -> 0.1011541 | ... CD38: =CD27/AVERAGE(CC73:CD73) -> 0.15839218
A39: ROIC (%) | BT39: =+Resumo!G37/AVERAGE(PROJ!BS94:BT94) -> 0.47247207 | BU39: =+Resumo!H37/AVERAGE(PROJ!BT94:BU94) -> 0.35620917 | BV39: =+Resumo!I37/AVERAGE(PROJ!BU94:BV94) -> 0.36687444 | BW39: =+Resumo!J37/AVERAGE(PROJ!BV94:BW94) -> 0.49119914 | BX39: =+Resumo!K37/AVERAGE(PROJ!BW94:BX94) -> 0.52447156 | BY39: =+Resumo!L37/AVERAGE(PROJ!BX94:BY94) -> 0.48755109 | BZ39: =+Resumo!M37/AVERAGE(PROJ!BY94:BZ94) -> 0.49312107 | CA39: =+Resumo!N37/AVERAGE(PROJ!BZ94:CA94) -> 0.48915849 | ... CD39: =+Resumo!Q37/AVERAGE(PROJ!CC94:CD94) -> 0.48838835
A41: Net Debt/EBITDA | B41: =B146 -> 0.99237702 | C41: =C146 -> 1.2848131 | D41: =D146 -> 1.3820963 | E41: =E146 -> 1.6879789 | F41: =F146 -> 1.6186801 | G41: =G146 -> 1.7865752 | H41: =H146 -> 2.0913983 | I41: =I146 -> 2.145173 | ... AS41: =AS146 -> 0.9135595 | AU41: 1.1460194 | AW41: =AW146 -> 0.014071559 | AX41: =AX146 -> 0.19053289 | AY41: =AY146 -> 0.19369545 | AZ41: =AZ146 -> 0.33805965 | BA41: =BA146 -> 0.50429583 | BB41: =BB146 -> 0.6093722 | BC41: =BC146 -> 0.77084831 | BD41: =BD146 -> 0.62504189 | ... CD41: =CD146 -> 0.5081647
A42: BVPS | B42: =B88/B30 -> 0.97605372 | C42: =C88/C30 -> 1.4203139 | D42: =D88/D30 -> 1.8572379 | E42: =E88/E30 -> 2.266623 | F42: =F88/F30 -> 0.95806002 | G42: =G88/G30 -> 1.3099893 | H42: =H88/H30 -> 1.5609307 | I42: =I88/I30 -> 1.9741758 | ... AS42: =AS88/AS30 -> 2.9215599 | AU42: 1.3737469 | AW42: =AW88/AW30 -> 9.5411654 | AX42: =AX88/AX30 -> 10.400726 | AY42: =AY88/AY30 -> 10.718544 | AZ42: =AZ88/AZ30 -> 9.0288524 | BA42: =BA88/BA30 -> 9.3833 | BB42: =BB88/BB30 -> 9.7570549 | BC42: =BC88/BC30 -> 10.107183 | BD42: =BD88/BD30 -> 10.550638 | ... CD42: =CD88/CD30 -> 5.1912136
A43: Net Margin (%) | B43: =B27/B3 -> 0.1271488 | C43: =C27/C3 -> 0.13339462 | D43: =D27/D3 -> 0.15056144 | E43: =E27/E3 -> 0.12715911 | F43: =F27/F3 -> 0.11488559 | G43: =G27/G3 -> 0.10549438 | H43: =H27/H3 -> 0.09290518 | I43: =I27/I3 -> 0.11392419 | ... AS43: =AS27/AS3 -> 0.14850946 | AU43: 0.13741397 | AW43: =AW27/AW3 -> 0.18963396 | AX43: =AX27/AX3 -> 0.15320651 | AY43: =AY27/AY3 -> 0.18522829 | AZ43: =AZ27/AZ3 -> 0.17705229 | BA43: =BA27/BA3 -> 0.16249599 | BB43: =BB27/BB3 -> 0.12021205 | BC43: =BC27/BC3 -> 0.10879507 | BD43: =BD27/BD3 -> 0.13356211 | ... CD43: =CD27/CD3 -> 0.1346428
A44: Multiples | B44: =B$2 -> 42459 | C44: =C$2 -> 42551 | D44: =D$2 -> 42643 | E44: =E$2 -> 42735 | F44: =F$2 -> 42825 | G44: =G$2 -> 42916 | H44: =H$2 -> 43008 | I44: =I$2 -> 43100 | ... AS44: =AS$2 -> 46387 | AU44: 46022 | AW44: =AW$2 -> 35795 | AX44: =AX$2 -> 36160 | AY44: =AY$2 -> 36525 | AZ44: =AZ$2 -> 36891 | BA44: =BA$2 -> 37256 | BB44: =BB$2 -> 37621 | BC44: =BC$2 -> 37986 | BD44: =BD$2 -> 38352 | ... CD44: =CD$2 -> 47848
A45: Stock Price (MXN) | BD45: =3*#REF! -> #REF! | BE45: =3*#REF! -> #REF! | BF45: =3*#REF! -> #REF! | BG45: =3*#REF! -> #REF! | BH45: =3*#REF! -> #REF! | BI45: =3*#REF! -> #REF! | BJ45: =3*#REF! -> #REF! | BK45: =+#REF! -> #REF! | BL45: =+#REF! -> #REF! | BM45: =+#REF! -> #REF! | BN45: =+#REF! -> #REF! | BO45: =+#REF! -> #REF! | BP45: =+AVERAGEIFS(Notes!$T5:$T1075,Notes!$R5:$R1075,"="&PROJ!BP$1) -> 28.229811 | BQ45: =+AVERAGEIFS(Notes!$T5:$T1075,Notes!$R5:$R1075,"="&PROJ!BQ$1) -> 25.858077 | BR45: =+AVERAGEIFS(Notes!$T5:$T1075,Notes!$R5:$R1075,"="&PROJ!BR$1) -> 24.394808 | BS45: =+AVERAGEIFS(Notes!$T5:$T1075,Notes!$R5:$R1075,"="&PROJ!BS$1) -> 27.903269 | BT45: =+AVERAGEIFS(Notes!$T5:$T1075,Notes!$R5:$R1075,"="&PROJ!BT$1) -> 28.557885 | BU45: =+AVERAGEIFS(Notes!$T5:$T1075,Notes!$R5:$R1075,"="&PROJ!BU$1) -> 28.982264 | BV45: =+AVERAGEIFS(Notes!$T5:$T1075,Notes!$R5:$R1075,"="&PROJ!BV$1) -> 26.253654 | BW45: =+AVERAGEIFS(Notes!$T5:$T1075,Notes!$R5:$R1075,"="&PROJ!BW$1) -> 35.221538 | BX45: 32 | BY45: =+BX45 -> 32 | BZ45: =+BY45 -> 32 | CA45: =+BZ45 -> 32 | CB45: =+CA45 -> 32 | CC45: =+CB45 -> 32 | CD45: =+CC45 -> 32
A46: Market Cap (MXN 'MM) | AW46: =+AW45*AW30 -> 0 | AX46: =+AX45*AX30 -> 0 | AY46: =+AY45*AY30 -> 0 | AZ46: =+AZ45*AZ30 -> 0 | BA46: =+BA45*BA30 -> 0 | BB46: =+BB45*BB30 -> 0 | BC46: =+BC45*BC30 -> 0 | BD46: =+BD45*BD30 -> #REF! | ... CD46: =+CD45*CD30 -> 93962.641
A47: Market Cap (us$ MM) | AW47: =AW46/FAT!AW3 -> #DIV/0! | AX47: =AX46/FAT!AX3 -> 0 | AY47: =AY46/FAT!AY3 -> 0 | AZ47: =AZ46/FAT!AZ3 -> 0 | BA47: =BA46/FAT!BA3 -> 0 | BB47: =BB46/FAT!BB3 -> 0 | BC47: =BC46/FAT!BC3 -> 0 | BD47: =BD46/FAT!BD3 -> #REF! | ... CD47: =CD46/FAT!CD3 -> 4921.2942
A48: Net Debt | AW48: =AW145 -> 50.023 | AX48: =AX145 -> 857.394 | AY48: =AY145 -> 1044.39 | AZ48: =AZ145 -> 2002.425 | BA48: =BA145 -> 2933.328 | BB48: =BB145 -> 3526.053 | BC48: =BC145 -> 4352.965 | BD48: =BD145 -> 3790.104 | ... CD48: =CD145 -> 7569.5519
A49: P/E | AW49: =AW46/AW27 -> 0 | AX49: =AX46/AX27 -> 0 | AY49: =AY46/AY27 -> 0 | AZ49: =AZ46/AZ27 -> 0 | BA49: =BA46/BA27 -> 0 | BB49: =BB46/BB27 -> 0 | BC49: =BC46/BC27 -> 0 | BD49: =BD46/BD27 -> #REF! | ... CD49: =CD46/CD27 -> 11.373531
A50: P/BV | AW50: =AW46/AW88 -> 0 | AX50: =AX46/AX88 -> 0 | AY50: =AY46/AY88 -> 0 | AZ50: =AZ46/AZ88 -> 0 | BA50: =BA46/BA88 -> 0 | BB50: =BB46/BB88 -> 0 | BC50: =BC46/BC88 -> 0 | BD50: =BD46/BD88 -> #REF! | ... CD50: =CD46/CD88 -> 6.1642619
A51: EV/EBITDA | AW51: =(AW48+AW46)/AW16 -> 0.014071559 | AX51: =(AX48+AX46)/AX16 -> 0.19053289 | AY51: =(AY48+AY46)/AY16 -> 0.19369545 | AZ51: =(AZ48+AZ46)/AZ16 -> 0.33805965 | BA51: =(BA48+BA46)/BA16 -> 0.50429583 | BB51: =(BB48+BB46)/BB16 -> 0.6093722 | BC51: =(BC48+BC46)/BC16 -> 0.77084831 | BD51: =(BD48+BD46)/BD16 -> #REF! | ... CD51: =(CD48+CD46)/CD16 -> 6.8161336
A52: Dividend Yield | AW52: =-AW113/AW46 -> #DIV/0! | AX52: =-AX113/AX46 -> #DIV/0! | AY52: =-AY113/AY46 -> #DIV/0! | AZ52: =-AZ113/AZ46 -> #DIV/0! | BA52: =-BA113/BA46 -> #DIV/0! | BB52: =-BB113/BB46 -> #DIV/0! | BC52: =-BC113/BC46 -> #DIV/0! | BD52: =-BD113/BD46 -> #REF! | ... CD52: =-CD113/CD46 -> 0.069633102
A53: FCF Yield | AW53: =AW107/(AW46+AW48) -> 44.110189 | AX53: =AX107/(AX46+AX48) -> 2.5059051 | AY53: =AY107/(AY46+AY48) -> 2.3024416 | AZ53: =AZ107/(AZ46+AZ48) -> 1.1323655 | BA53: =BA107/(BA46+BA48) -> 0.68920046 | BB53: =BB107/(BB46+BB48) -> 0.74688753 | BC53: =BC107/(BC46+BC48) -> 0.48115756 | BD53: =BD107/(BD46+BD48) -> #REF! | ... CD53: =CD107/(CD46+CD48) -> 0.080708689
A54: EFCF Yield | AW54: =AW107/AW46 -> #DIV/0! | AX54: =AX107/AX46 -> #DIV/0! | AY54: =AY107/AY46 -> #DIV/0! | AZ54: =AZ107/AZ46 -> #DIV/0! | BA54: =BA107/BA46 -> #DIV/0! | BB54: =BB107/BB46 -> #DIV/0! | BC54: =BC107/BC46 -> #DIV/0! | BD54: =BD107/BD46 -> #REF! | ... CD54: =CD107/CD46 -> 0.087210513
A55: Balance Sheet | B55: =B$2 -> 42459 | C55: =C$2 -> 42551 | D55: =D$2 -> 42643 | E55: =E$2 -> 42735 | F55: =F$2 -> 42825 | G55: =G$2 -> 42916 | H55: =H$2 -> 43008 | I55: =I$2 -> 43100 | ... AS55: =AS$2 -> 46387 | AU55: 46022 | AW55: =AW$2 -> 35795 | AX55: =AX$2 -> 36160 | AY55: =AY$2 -> 36525 | AZ55: =AZ$2 -> 36891 | BA55: =BA$2 -> 37256 | BB55: =BB$2 -> 37621 | BC55: =BC$2 -> 37986 | BD55: =BD$2 -> 38352 | ... CD55: =CD$2 -> 47848
A56: Cash & equivalents | B56: 11088.367 | C56: 9588.63 | D56: 8938.922 | E56: 7461.492 | F56: 7275.926 | G56: 6261.141 | H56: 6013.114 | I56: 4674.339 | J56: 5426 | K56: 7509.769 | L56: 5994.873 | M56: 4999.502 | N56: 6534 | O56: 6703 | P56: 7074.719 | Q56: 6838.556 | R56: 9723.223 | S56: 10328.019 | T56: 22033.999 | U56: 18583.898 | V56: 15739.026 | W56: 14264.677 | X56: 14288.94 | Y56: 12274.693 | Z56: 12397.933 | AA56: 9667.933 | AB56: 18113.649 | AC56: 16919.158 | AD56: 17919.129 | AE56: 19112.823 | AF56: 18496.524 | AG56: 18972.075 | AH56: 20193.012 | AI56: 16874.934 | AJ56: 16739.429 | AK56: 15582.477 | AL56: 11782.71 | AM56: 10953.823 | AN56: 10749.482 | AO56: 9660.279 | AP56: =AP130 -> 18067.045 | AQ56: =AQ130 -> 15879.133 | AR56: =AR130 -> 14448.256 | AS56: =AS130 -> 9013.8134 | AU56: 6303.0443 | AW56: 2078.058 | AX56: 1829.076 | AY56: 2571.183 | AZ56: 2018.306 | BA56: 2205.614 | BB56: 1699.29 | BC56: 1709.517 | BD56: 2132.781 | BE56: 1803.061 | BF56: 1776.69 | BG56: 2914.968 | BH56: 3017.607 | BI56: 6460.495 | BJ56: 6306.972 | BK56: 4027.564 | BL56: 3464.93 | BM56: 5390.25 | BN56: 5049.547 | BO56: 7933.699 | BP56: 7461.492 | BQ56: =+SUMIFS($B56:$AK56,$B$2:$AK$2,"="&BQ$2) -> 4674.339 | BR56: =+SUMIFS($B56:$AK56,$B$2:$AK$2,"="&BR$2) -> 4999.502 | BS56: =+SUMIFS($B56:$AK56,$B$2:$AK$2,"="&BS$2) -> 6838.556 | BT56: =+SUMIFS($B56:$AK56,$B$2:$AK$2,"="&BT$2) -> 18583.898 | BU56: =+SUMIFS($B56:$AK56,$B$2:$AK$2,"="&BU$2) -> 12274.693 | BV56: =+SUMIFS($B56:$AK56,$B$2:$AK$2,"="&BV$2) -> 16919.158 | BW56: =+SUMIFS($B56:$AK56,$B$2:$AK$2,"="&BW$2) -> 18972.075 | BX56: =+SUMIFS($B56:$AO56,$B$2:$AO$2,"="&BX$2) -> 15582.477 | BY56: =+SUMIFS($B56:$AS56,$B$2:$AS$2,"="&BY$2) -> 9660.279 | BZ56: =+SUMIFS($B56:$AS56,$B$2:$AS$2,"="&BZ$2) -> 9013.8134 | CA56: =CA130 -> 10699.616 | CB56: =CB130 -> 12345.063 | CC56: =CC130 -> 13961.973 | CD56: =CD130 -> 15613.593
A57: Trade receivables | B57: 5543.53 | C57: 5490.679 | D57: 5965.716 | E57: 5627.05 | F57: 6288.024 | G57: 6353.169 | H57: 5906.508 | I57: 6295.184 | J57: 7538 | K57: 7530.709 | L57: 6784.963 | M57: 7080.478 | N57: 7463 | O57: 7059 | P57: 6519.109 | Q57: 6694.4 | R57: 7172.439 | S57: 6492.731 | T57: 5951.878 | U57: 6051.941 | V57: 6806.524 | W57: 7228.263 | X57: 6787.632 | Y57: 6805.7561 | Z57: 7992.877 | AA57: 7498.75 | AB57: 7024.569 | AC57: 7084.54 | AD57: 8199.284 | AE57: 8120.2222 | AF57: 7082.64 | AG57: 7187.218 | AH57: 8444.773 | AI57: 8650.676 | AJ57: 7933.073 | AK57: 8011.232 | AL57: 8917.121 | AM57: 9065.85 | AN57: 8416.209 | AO57: 8670.669 | AP57: =AP58*AP3*4 -> 8702.577 | AQ57: =AQ58*AQ3*4 -> 8895.0683 | AR57: =AR58*AR3*4 -> 8477.8156 | AS57: =AS58*AS3*4 -> 8887.4357 | AU57: 8772.1008 | AW57: 1928.097 | AX57: 2474.11 | AY57: 2908.596 | AZ57: 3330.75 | BA57: 3479.941 | BB57: 3616.47 | BC57: 3740.375 | BD57: 4119.829 | BE57: 4429.804 | BF57: 3662.796 | BG57: 3564.891 | BH57: 4166.392 | BI57: 4096.047 | BJ57: 4543.91 | BK57: 5383.705 | BL57: 5278.623 | BM57: 4854.761 | BN57: 5053.793 | BO57: 4784.119 | BP57: 5627.05 | BQ57: =+SUMIFS($B57:$AK57,$B$2:$AK$2,"="&BQ$2) -> 6295.184 | BR57: =+SUMIFS($B57:$AK57,$B$2:$AK$2,"="&BR$2) -> 7080.478 | BS57: =+SUMIFS($B57:$AK57,$B$2:$AK$2,"="&BS$2) -> 6694.4 | BT57: =+SUMIFS($B57:$AK57,$B$2:$AK$2,"="&BT$2) -> 6051.941 | BU57: =+SUMIFS($B57:$AK57,$B$2:$AK$2,"="&BU$2) -> 6805.7561 | BV57: =+SUMIFS($B57:$AK57,$B$2:$AK$2,"="&BV$2) -> 7084.54 | BW57: =+SUMIFS($B57:$AK57,$B$2:$AK$2,"="&BW$2) -> 7187.218 | BX57: =+SUMIFS($B57:$AO57,$B$2:$AO$2,"="&BX$2) -> 8011.232 | BY57: =+SUMIFS($B57:$AS57,$B$2:$AS$2,"="&BY$2) -> 8670.669 | BZ57: =+SUMIFS($B57:$AS57,$B$2:$AS$2,"="&BZ$2) -> 8887.4357 | CA57: =CA58*CA3 -> 9065.1844 | CB57: =CB58*CB3 -> 9246.4881 | CC57: =CC58*CC3 -> 9431.4179 | CD57: =CD58*CD3 -> 9620.0462
A58: % of Revenues | B58: =B57/B$3/4 -> 0.15878004 | C58: =C57/C$3/4 -> 0.15543142 | D58: =D57/D$3/4 -> 0.17104609 | E58: =E57/E$3/4 -> 0.14995601 | F58: =F57/F$3/4 -> 0.16494462 | G58: =G57/G$3/4 -> 0.1653454 | H58: =H57/H$3/4 -> 0.16055077 | I58: =I57/I$3/4 -> 0.16685553 | ... AO58: =AO57/AO$3/4 -> 0.15419537 | AP58: =+AO58 -> 0.15419537 | AQ58: =+AP58 -> 0.15419537 | AR58: =+AQ58 -> 0.15419537 | AS58: =+AR58 -> 0.15419537 | AU58: 0.15690173 | AW58: =AW57/AW$3 -> 0.18709443 | AX58: =AX57/AX$3 -> 0.20131531 | AY58: =AY57/AY$3 -> 0.209731 | AZ58: =AZ57/AZ$3 -> 0.20939719 | BA58: =BA57/BA$3 -> 0.22258865 | BB58: =BB57/BB$3 -> 0.22468073 | BC58: =BC57/BC$3 -> 0.21873322 | BD58: =BD57/BD$3 -> 0.20808364 | ... BZ58: =BZ57/BZ$3 -> 0.15678351 | CA58: =+BZ58 -> 0.15678351 | CB58: =+CA58 -> 0.15678351 | CC58: =+CB58 -> 0.15678351 | CD58: =+CC58 -> 0.15678351
A59: Inventories | B59: 2323.451 | C59: 2650.271 | D59: 2989.388 | E59: 2861.198 | F59: 3178.162 | G59: 3441.674 | H59: 3201.401 | I59: 3174.694 | J59: 3402 | K59: 3676.634 | L59: 3696.577 | M59: 3712.003 | N59: 3837 | O59: 3332 | P59: 3281.803 | Q59: 3225.703 | R59: 3503.887 | S59: 3839.695 | T59: 3864.324 | U59: 3792.471 | V59: 3937.266 | W59: 3988.646 | X59: 4093.882 | Y59: 4462.12 | Z59: 4280.009 | AA59: 4667.618 | AB59: 4710.464 | AC59: 4598.306 | AD59: 4611.808 | AE59: 4443.132 | AF59: 4424.69 | AG59: 4113.459 | AH59: 4168.85 | AI59: 4035.713 | AJ59: 4323.08 | AK59: 4197.612 | AL59: 4489.391 | AM59: 4532.927 | AN59: 4238.86 | AO59: 4309.261 | AP59: =AP60*AP3*4 -> 4325.119 | AQ59: =AQ60*AQ3*4 -> 4420.7859 | AR59: =AR60*AR3*4 -> 4213.4142 | AS59: =AS60*AS3*4 -> 4416.9925 | AU59: 4418.1064 | AW59: 830.029 | AX59: 906.656 | AY59: 1119.212 | AZ59: 1210.095 | BA59: 1193.529 | BB59: 1100.855 | BC59: 1404.999 | BD59: 1591.25 | BE59: 1725.96 | BF59: 1552.391 | BG59: 1654.1 | BH59: 1889.735 | BI59: 1681.632 | BJ59: 1915.377 | BK59: 2092.595 | BL59: 1950.268 | BM59: 1844.534 | BN59: 1887.357 | BO59: 2226.509 | BP59: 2861.198 | BQ59: =+SUMIFS($B59:$AK59,$B$2:$AK$2,"="&BQ$2) -> 3174.694 | BR59: =+SUMIFS($B59:$AK59,$B$2:$AK$2,"="&BR$2) -> 3712.003 | BS59: =+SUMIFS($B59:$AK59,$B$2:$AK$2,"="&BS$2) -> 3225.703 | BT59: =+SUMIFS($B59:$AK59,$B$2:$AK$2,"="&BT$2) -> 3792.471 | BU59: =+SUMIFS($B59:$AK59,$B$2:$AK$2,"="&BU$2) -> 4462.12 | BV59: =+SUMIFS($B59:$AK59,$B$2:$AK$2,"="&BV$2) -> 4598.306 | BW59: =+SUMIFS($B59:$AK59,$B$2:$AK$2,"="&BW$2) -> 4113.459 | BX59: =+SUMIFS($B59:$AO59,$B$2:$AO$2,"="&BX$2) -> 4197.612 | BY59: =+SUMIFS($B59:$AS59,$B$2:$AS$2,"="&BY$2) -> 4309.261 | BZ59: =+SUMIFS($B59:$AS59,$B$2:$AS$2,"="&BZ$2) -> 4416.9925 | CA59: =CA60*CA3 -> 4505.3324 | CB59: =CB60*CB3 -> 4595.439 | CC59: =CC60*CC3 -> 4687.3478 | CD59: =CD60*CD3 -> 4781.0948
A60: % of Revenues | B60: =B59/B$3/4 -> 0.066549227 | C60: =C59/C$3/4 -> 0.075024489 | D60: =D59/D$3/4 -> 0.085710268 | E60: =E59/E$3/4 -> 0.076248448 | F60: =F59/F$3/4 -> 0.083368116 | G60: =G59/G$3/4 -> 0.089571831 | H60: =H59/H$3/4 -> 0.087020519 | I60: =I59/I$3/4 -> 0.084146108 | ... AO60: =AO59/AO$3/4 -> 0.076634005 | AP60: =+AO60 -> 0.076634005 | AQ60: =+AP60 -> 0.076634005 | AR60: =+AQ60 -> 0.076634005 | AS60: =+AR60 -> 0.076634005 | AU60: 0.079024236 | AW60: =AW59/AW$3 -> 0.080542527 | AX60: =AX59/AX$3 -> 0.073773492 | AY60: =AY59/AY$3 -> 0.080703352 | AZ60: =AZ59/AZ$3 -> 0.076076106 | BA60: =BA59/BA$3 -> 0.076342103 | BB60: =BB59/BB$3 -> 0.068392909 | BC60: =BC59/BC$3 -> 0.082162872 | BD60: =BD59/BD$3 -> 0.08037059 | ... BZ60: =BZ59/BZ$3 -> 0.077920294 | CA60: =+BZ60 -> 0.077920294 | CB60: =+CA60 -> 0.077920294 | CC60: =+CB60 -> 0.077920294 | CD60: =+CC60 -> 0.077920294
A61: Other | B61: 0 | C61: 0 | D61: 0.0002 | E61: 0.0002 | F61: 0.0002 | G61: 0 | H61: 0 | I61: 0 | J61: 0.0002 | K61: 0 | L61: 0 | M61: 0 | N61: 0 | O61: 0 | P61: 0 | Q61: 0 | R61: 1140.43 | S61: 1064.799 | T61: 846.755 | U61: 396.053 | V61: 0 | W61: 16.801 | X61: 288.055 | Y61: 0 | Z61: 0 | AA61: 0 | AB61: 0 | AC61: 4.116 | AD61: 0 | AE61: 1058.33 | AF61: 1091.09 | AG61: 939.74 | AH61: 1335.99 | AI61: 870.756 | AJ61: 1186.705 | AK61: =+AK63-AK59-AK57-AK56 -> 1503.682 | AL61: =+AL63-AL59-AL57-AL56 -> 0 | AM61: =+AM63-AM59-AM57-AM56 -> 0 | AN61: =+AN63-AN59-AN57-AN56 -> 0 | AO61: =+AO63-AO59-AO57-AO56 -> 0 | AP61: =AP62*AP3*4 -> 0 | AQ61: =AQ62*AQ3*4 -> 0 | AR61: =AR62*AR3*4 -> 0 | AS61: =AS62*AS3*4 -> 0 | AU61: 0 | AW61: 353.456 | AX61: 230.273 | AY61: 235.563 | AZ61: 295.006 | BA61: 333.129 | BB61: 327.77 | BC61: 320.76 | BD61: 315.397 | BE61: 392.447 | BF61: 1355.558 | BG61: 88.927 | BH61: 90.291 | BI61: 364.148 | BJ61: 127.373 | BK61: 64.135 | BL61: 125.186 | BM61: 91.703 | BN61: 43.818 | BO61: 75.256 | BP61: 0.0002 | BQ61: =+SUMIFS($B61:$AK61,$B$2:$AK$2,"="&BQ$2) -> 0 | BR61: =+SUMIFS($B61:$AK61,$B$2:$AK$2,"="&BR$2) -> 0 | BS61: =+SUMIFS($B61:$AK61,$B$2:$AK$2,"="&BS$2) -> 0 | BT61: =+SUMIFS($B61:$AK61,$B$2:$AK$2,"="&BT$2) -> 396.053 | BU61: =+SUMIFS($B61:$AK61,$B$2:$AK$2,"="&BU$2) -> 0 | BV61: =+SUMIFS($B61:$AK61,$B$2:$AK$2,"="&BV$2) -> 4.116 | BW61: =+SUMIFS($B61:$AK61,$B$2:$AK$2,"="&BW$2) -> 939.74 | BX61: =+SUMIFS($B61:$AO61,$B$2:$AO$2,"="&BX$2) -> 1503.682 | BY61: =+SUMIFS($B61:$AS61,$B$2:$AS$2,"="&BY$2) -> 0 | BZ61: =+SUMIFS($B61:$AS61,$B$2:$AS$2,"="&BZ$2) -> 0 | CA61: =CA62*CA3 -> 0 | CB61: =CB62*CB3 -> 0 | CC61: =CC62*CC3 -> 0 | CD61: =CD62*CD3 -> 0
A62: % of Revenues | B62: =B61/B3/4 -> 0 | C62: =C61/C3/4 -> 0 | D62: =D61/D3/4 -> 5.734302e-09 | E62: =E61/E3/4 -> 5.3298267e-09 | F62: =F61/F3/4 -> 5.2463101e-09 | G62: =G61/G3/4 -> 0 | H62: =H61/H3/4 -> 0 | I62: =I61/I3/4 -> 0 | ... AO62: =AO61/AO3/4 -> 0 | AP62: =+AO62 -> 0 | AQ62: =+AP62 -> 0 | AR62: =+AQ62 -> 0 | AS62: =+AR62 -> 0 | AU62: 0 | AW62: =AW61/AW3 -> 0.034297885 | AX62: =AX61/AX3 -> 0.018737033 | AY62: =AY61/AY3 -> 0.016985811 | AZ62: =AZ61/AZ3 -> 0.018546402 | BA62: =BA61/BA3 -> 0.021308044 | BB62: =BB61/BB3 -> 0.020363394 | BC62: =BC61/BC3 -> 0.018757709 | BD62: =BD61/BD3 -> 0.015930019 | ... BZ62: =BZ61/BZ3 -> 0 | CA62: =+BZ62 -> 0 | CB62: =+CA62 -> 0 | CC62: =+CB62 -> 0 | CD62: =+CC62 -> 0
A63: Current Assets | B63: =+B61+B57+B56+B59 -> 18955.348 | C63: =+C61+C57+C56+C59 -> 17729.58 | D63: =+D61+D57+D56+D59 -> 17894.026 | E63: =+E61+E57+E56+E59 -> 15949.74 | F63: =+F61+F57+F56+F59 -> 16742.112 | G63: =+G61+G57+G56+G59 -> 16055.984 | H63: =+H61+H57+H56+H59 -> 15121.023 | I63: =+I61+I57+I56+I59 -> 14144.217 | ... AJ63: =+AJ61+AJ57+AJ56+AJ59 -> 30182.287 | AK63: 29295.003 | AL63: 25189.222 | AM63: 24552.6 | AN63: 23404.551 | AO63: 22640.209 | AP63: =+AP61+AP57+AP56+AP59 -> 31094.741 | AQ63: =+AQ61+AQ57+AQ56+AQ59 -> 29194.987 | AR63: =+AR61+AR57+AR56+AR59 -> 27139.486 | AS63: =+AS61+AS57+AS56+AS59 -> 22318.242 | AU63: 19493.251 | AW63: =+AW61+AW57+AW56+AW59 -> 5189.64 | AX63: =+AX61+AX57+AX56+AX59 -> 5440.115 | AY63: =+AY61+AY57+AY56+AY59 -> 6834.554 | AZ63: =+AZ61+AZ57+AZ56+AZ59 -> 6854.157 | BA63: =+BA61+BA57+BA56+BA59 -> 7212.213 | BB63: =+BB61+BB57+BB56+BB59 -> 6744.385 | BC63: =+BC61+BC57+BC56+BC59 -> 7175.651 | BD63: =+BD61+BD57+BD56+BD59 -> 8159.257 | ... CD63: =+CD61+CD57+CD56+CD59 -> 30014.734
A65: Depreciation | B65: -408.221 | C65: -412.516 | D65: -412.263 | E65: -367.919 | F65: -436.143 | G65: -415.112 | H65: -367.936 | I65: -380.633 | J65: -416 | K65: =-819-J65 -> -403 | L65: =-1180-K65-J65 -> -361 | M65: =-1562.338-L65-K65-J65 -> -382.338 | N65: -498 | O65: =-1002.771-N65 -> -504.771 | P65: =-1486-O65-N65 -> -483.229 | Q65: -459.455 | R65: -512.785 | S65: =-1024.248-R65 -> -511.463 | T65: -485.132 | U65: -443.955 | V65: -501 | W65: =-987-V65 -> -486 | X65: =-1484.417-W65-V65 -> -497.417 | Y65: -450.864 | Z65: -509 | AA65: =-1028-Z65 -> -519 | AB65: =-1531-AA65-Z65 -> -503 | AC65: =-1968.726-SUM(Z65:AB65) -> -437.726 | AD65: -482.959 | AE65: =-965.881-AD65 -> -482.922 | AF65: =-1452-AE65-AD65 -> -486.119 | AG65: =-1984.52-SUM(AD65:AF65) -> -532.52 | AH65: -494.132 | AI65: =-989.453-AH65 -> -495.321 | AJ65: -499.815 | AK65: =-2047.673-AJ65-AI65-AH65 -> -558.405 | AL65: -494.19 | AM65: =-1016.773-AL65 -> -522.583 | AN65: =-1518.677-AM65-AL65 -> -501.904 | AO65: =-2016.597-AN65-AM65-AL65 -> -497.92 | AP65: =+AP66*(AO67+AO71)/4 -> -498.0566 | AQ65: =+AQ66*(AP67+AP71)/4 -> -524.74897 | AR65: =+AR66*(AQ67+AQ71)/4 -> -495.78532 | AS65: =+AS66*(AR67+AR71)/4 -> -491.67429 | AU65: -569.46815 | AW65: -612.142 | AX65: -709.517 | AY65: -811.742 | AZ65: -835.994 | BA65: -931.031 | BB65: -1083.713 | BC65: -1171.366 | BD65: -1241.009 | BE65: -1284.933 | BF65: -1001.336 | BG65: -1045.505 | BH65: -1154.993 | BI65: -1194.231 | BJ65: -1189.583 | BK65: -1343 | BL65: -1498.474 | BM65: -1516.913 | BN65: -1616 | BO65: -1664.773 | BP65: -1600.919 | BQ65: =+SUMIFS($B65:$AK65,$B$2:$AK$2,"="&BQ$2) -> -380.633 | BR65: =+SUMIFS($B65:$AK65,$B$2:$AK$2,"="&BR$2) -> -382.338 | BS65: =+SUMIFS($B65:$AK65,$B$2:$AK$2,"="&BS$2) -> -459.455 | BT65: =+SUMIFS($B65:$AO65,$B$1:$AO$1,"="&BT$1) -> -1953.335 | BU65: =+SUMIFS($B65:$AO65,$B$1:$AO$1,"="&BU$1) -> -1935.281 | BV65: =+SUMIFS($B65:$AO65,$B$1:$AO$1,"="&BV$1) -> -1968.726 | BW65: =+SUMIFS($B65:$AO65,$B$1:$AO$1,"="&BW$1) -> -1984.52 | BX65: =+SUMIFS($B65:$AO65,$B$1:$AO$1,"="&BX$1) -> -2047.673 | BY65: =+SUMIFS($B65:$AS65,$B$1:$AS$1,"="&BY$1) -> -2016.597 | BZ65: =+SUMIFS($B65:$AS65,$B$1:$AS$1,"="&BZ$1) -> -2010.2652 | CA65: =+CA66*(BZ67+BZ70) -> -1995.2862 | CB65: =+CB66*(CA67+CA70) -> -1998.2717 | CC65: =+CC66*(CB67+CB70) -> -2005.1974 | CD65: =+CD66*(CC67+CC70) -> -2015.7342
A66: As a % PP&E | C66: =C65*4/(B67+B70) -> -0.086597786 | D66: =D65*4/(C67+C70) -> -0.091397211 | E66: =E65*4/(D67+D70) -> -0.066816871 | F66: =F65*4/(E67+E70) -> -0.07049093 | G66: =G65*4/(F67+F70) -> -0.07122237 | H66: =H65*4/(G67+G70) -> -0.062947849 | I66: =I65*4/(H67+H70) -> -0.064777804 | J66: =J65*4/(I67+I71) -> -0.066041959 | K66: =K65*4/(J67+J71) -> -0.071945015 | L66: =L65*4/(K67+K71) -> -0.057994234 | M66: =M65*4/(L67+L71) -> -0.063326009 | N66: =N65*4/(M67+M71) -> -0.078384363 | O66: =O65*4/(N67+N71) -> -0.07798089 | P66: =P65*4/(O67+O71) -> -0.075087957 | Q66: =Q65*4/(P67+P71) -> -0.071034319 | ... AO66: =AO65*4/(AN67+AN71) -> -0.085734013 | AP66: =+AL66 -> -0.08664511 | AQ66: =+AM66 -> -0.091158267 | AR66: =+AN66 -> -0.086440829 | AS66: =+AO66 -> -0.085734013 | AU66: -0.098053483 | AW66: =AW65/(A67+A70-0.5*AW105) -> #VALUE! | AX66: =AX65/(AW67+AW70-0.5*AX105) -> -0.068793723 | AY66: =AY65/(AX67+AX70-0.5*AY105) -> -0.063162977 | AZ66: =AZ65/(AY67+AY70-0.5*AZ105) -> -0.061421662 | BA66: =BA65/(AZ67+AZ70-0.5*BA105) -> -0.062968522 | BB66: =BB65/(BA67+BA70-0.5*BB105) -> -0.070820984 | BC66: =BC65/(BB67+BB70-0.5*BC105) -> -0.070906625 | BD66: =BD65/(BC67+BC70-0.5*BD105) -> -0.071237459 | BE66: =BE65/(BD67+BD70-0.5*BE105) -> -0.072861154 | ... BO66: =BO65/(BN67+BN70-0.5*BO105) -> -0.089711012 | BP66: =BP65/(BO67+BO70) -> -0.084137356 | BQ66: =BQ65/(BP67+BP70) -> -0.015379803 | BR66: =BR65/(BQ67+BQ70) -> -0.021877579 | BS66: =BS65/(BR67+BR70) -> -0.025714522 | BT66: =BT65/(BS67+BS70) -> -0.11429829 | BU66: =BU65/(BT67+BT70) -> -0.11822017 | BV66: =BV65/(BU67+BU70) -> -0.11532362 | BW66: =BW65/(BV67+BV70) -> -0.11169045 | ... BZ66: =BZ65/(BY67+BY70) -> -0.10510393 | CA66: =+BZ66 -> -0.10510393 | CB66: =+CA66 -> -0.10510393 | CC66: =+CB66 -> -0.10510393 | CD66: =+CC66 -> -0.10510393
A67: Net PP&E | B67: 15693.96 | C67: 15669.565 | D67: 15649.043 | E67: 16298.731 | F67: 16582.428 | G67: 17005.004 | H67: 17177.095 | I67: 17476.248 | J67: 17592 | K67: 17837.775 | L67: 17895.069 | M67: 17867.53 | N67: 17635 | O67: 17419 | P67: 17260.493 | Q67: 17089.8 | R67: 16836.191 | S67: 16639.909 | T67: 16348.39 | U67: 16370.142 | V67: 16440.218 | W67: 16436.576 | X67: 16761.641 | Y67: 17071.316 | Z67: 17268.39 | AA67: 17488.222 | AB67: 17583.337 | AC67: 17768.037 | AD67: 17741.585 | AE67: 17836.724 | AF67: 17877.642 | AG67: 17924.639 | AH67: 18134.76 | AI67: 18433.204 | AJ67: 18798.746 | AK67: 18841.645 | AL67: 18978.704 | AM67: 19016.92 | AN67: 19119.768 | AO67: 19126.452 | AP67: =+AO67-AP133+AP65 -> 19159.347 | AQ67: =+AP67-AQ133+AQ65 -> 19075.688 | AR67: =+AQ67-AR133+AR65 -> 19073.026 | AS67: =+AR67-AS133+AS65 -> 18983.936 | AU67: 19051.74 | AW67: 9987.723 | AX67: 12179.395 | AY67: 12982.877 | AZ67: 13917.92 | BA67: 14849.542 | BB67: 16129.419 | BC67: 17143.97 | BD67: 17138.172 | BE67: 16622.813 | BF67: 13545.28 | BG67: 14536.877 | BH67: 14453.503 | BI67: 14356.111 | BJ67: 14047.566 | BK67: 16220.682 | BL67: 15734.233 | BM67: 15878.641 | BN67: 15979.624 | BO67: 15670.354 | BP67: 16298.731 | BQ67: =+SUMIFS($B67:$AK67,$B$2:$AK$2,"="&BQ$2) -> 17476.248 | BR67: =+SUMIFS($B67:$AK67,$B$2:$AK$2,"="&BR$2) -> 17867.53 | BS67: =+SUMIFS($B67:$AK67,$B$2:$AK$2,"="&BS$2) -> 17089.8 | BT67: =+SUMIFS($B67:$AK67,$B$2:$AK$2,"="&BT$2) -> 16370.142 | BU67: =+SUMIFS($B67:$AK67,$B$2:$AK$2,"="&BU$2) -> 17071.316 | BV67: =+SUMIFS($B67:$AK67,$B$2:$AK$2,"="&BV$2) -> 17768.037 | BW67: =+SUMIFS($B67:$AK67,$B$2:$AK$2,"="&BW$2) -> 17924.639 | BX67: =+SUMIFS($B67:$AO67,$B$2:$AO$2,"="&BX$2) -> 18841.645 | BY67: =+SUMIFS($B67:$AS67,$B$2:$AS$2,"="&BY$2) -> 19126.452 | BZ67: =+SUMIFS($B67:$AS67,$B$2:$AS$2,"="&BZ$2) -> 18983.936 | CA67: =+BZ67-CA133+CA65 -> 19012.342 | CB67: =+CA67-CB133+CB65 -> 19078.235 | CC67: =+CB67-CC133+CC65 -> 19178.486 | CD67: =+CC67-CD133+CD65 -> 19310.31
A68: Avg Life Assets | B68: =(B70+B67)/B65/4 -> -11.669135 | C68: =(C70+C67)/C65/4 -> -10.934543 | D68: =(D70+D67)/D65/4 -> -13.356471 | E68: =(E70+E67)/E65/4 -> -16.816803 | F68: =(F70+F67)/F65/4 -> -13.363492 | G68: =(G70+G67)/G65/4 -> -14.08076 | H68: =(H70+H67)/H65/4 -> -15.970111 | I68: =(I71+I67)/I65/4 -> -16.548817 | J68: =(J71+J67)/J65/4 -> -13.465144 | K68: =(K71+K67)/K65/4 -> -15.446047 | L68: =(L71+L67)/L65/4 -> -16.724693 | M68: =(M71+M67)/M65/4 -> -16.616993 | N68: =(N71+N67)/N65/4 -> -12.99801 | O68: =(O71+O67)/O65/4 -> -12.749358 | P68: =(P71+P67)/P65/4 -> -13.385105 | ... AS68: =(AS71+AS67)/AS65/4 -> -11.618683 | AU68: -10.168651 | AW68: =(AW70+AW67)/AW65 -> -16.316023 | AX68: =(AX70+AX67)/AX65 -> -17.165755 | AY68: =(AY70+AY67)/AY65 -> -15.993847 | AZ68: =(AZ70+AZ67)/AZ65 -> -16.648349 | BA68: =(BA70+BA67)/BA65 -> -15.949568 | BB68: =(BB70+BB67)/BB65 -> -14.883478 | BC68: =(BC70+BC67)/BC65 -> -14.635878 | BD68: =(BD70+BD67)/BD65 -> -13.809869 | ... BZ68: =(BZ70+BZ67)/BZ65 -> -9.4434986 | CA68: =(CA70+CA67)/CA65/4 -> -2.3821572 | CB68: =(CB70+CB67)/CB65/4 -> -2.3868419 | CC68: =(CC70+CC67)/CC65/4 -> -2.391097 | CD68: =(CD70+CD67)/CD65/4 -> -2.3949474
A70: Equity Investments | B70: 3360.384 | C70: 2373.13 | D70: 6376.472 | E70: 8450.155 | F70: 6731.146 | G70: 6375.366 | H70: =2851.049+3475.771 -> 6326.82 | AW70: 0 | AX70: 0 | AY70: 0 | AZ70: 0 | BA70: 0 | BB70: 0 | BC70: 0 | BD70: 0 | BE70: 0 | BF70: 0 | BG70: 48.919 | BH70: 14.371 | BI70: 0 | BJ70: 0 | BK70: 112.525 | BL70: 1483.181 | BM70: 1479.95 | BN70: 1918.305 | BO70: 3357.092 | BP70: 8450.155 | BQ70: =+SUMIFS($B70:$AK70,$B$2:$AK$2,"="&BQ$2) -> 0 | BR70: =+SUMIFS($B70:$AK70,$B$2:$AK$2,"="&BR$2) -> 0 | BS70: =+SUMIFS($B70:$AK70,$B$2:$AK$2,"="&BS$2) -> 0 | BT70: =+SUMIFS($B70:$AO70,$B$2:$AO$2,"="&BT$2) -> 0 | BU70: =+SUMIFS($B70:$AO70,$B$2:$AO$2,"="&BU$2) -> 0 | BV70: =+SUMIFS($B70:$AO70,$B$2:$AO$2,"="&BV$2) -> 0 | BW70: =+SUMIFS($B70:$AO70,$B$2:$AO$2,"="&BW$2) -> 0 | BX70: =+SUMIFS($B70:$AO70,$B$2:$AO$2,"="&BX$2) -> 0 | BY70: =+SUMIFS($B70:$AS70,$B$2:$AS$2,"="&BY$2) -> 0 | BZ70: =+SUMIFS($B70:$AS70,$B$2:$AS$2,"="&BZ$2) -> 0
A71: Others | B71: 0 | C71: 0 | D71: 0.0001 | E71: 0.0001 | F71: 0.0001 | I71: =+I72-I67 -> 7719.855 | J71: =+J72-J67 -> 4814 | K71: =+K72-K67 -> 7061.252 | L71: =+L72-L67 -> 6255.387 | M71: =+M72-M67 -> 7545.702 | N71: =+N72-N67 -> 8257.036 | O71: =+O72-O67 -> 8323.024 | P71: =+P72-P67 -> 8611.79 | ... AO71: =+AO72-AO67 -> 3866.495 | AP71: =+AO71 -> 3866.495 | AQ71: =+AP71 -> 3866.495 | AR71: =+AQ71 -> 3866.495 | AS71: =+AR71 -> 3866.495 | AU71: 4111.152 | AW71: 0 | AX71: 0 | AY71: 0 | AZ71: 0 | BA71: 0 | BB71: 0 | BC71: 0 | BD71: 0 | BE71: 0 | BF71: 543.5 | BG71: 603.33 | BH71: 617.068 | BI71: 210.097 | BJ71: 0 | BK71: 0 | BL71: 0 | BM71: 0 | BN71: 0 | BO71: 0 | BP71: 0.0001 | BQ71: =+#REF! -> #REF! | BR71: =+#REF! -> #REF! | BS71: =+#REF! -> #REF! | BT71: =+SUMIFS($B71:$AO71,$B$2:$AO$2,"="&BT$2) -> 8122.146 | BU71: =+SUMIFS($B71:$AO71,$B$2:$AO$2,"="&BU$2) -> 8170.112 | BV71: =+SUMIFS($B71:$AO71,$B$2:$AO$2,"="&BV$2) -> 7166.463 | BW71: =+SUMIFS($B71:$AO71,$B$2:$AO$2,"="&BW$2) -> 4781.793 | BX71: =+SUMIFS($B71:$AO71,$B$2:$AO$2,"="&BX$2) -> 3972.799 | BY71: =+SUMIFS($B71:$AS71,$B$2:$AS$2,"="&BY$2) -> 3866.495 | BZ71: =+SUMIFS($B71:$AS71,$B$2:$AS$2,"="&BZ$2) -> 3866.495 | CA71: =+BZ71 -> 3866.495 | CB71: =+CA71 -> 3866.495 | CC71: =+CB71 -> 3866.495 | CD71: =+CC71 -> 3866.495
A72: Non Current Assets | B72: =+B71+B67+B70 -> 19054.344 | C72: =+C71+C67+C70 -> 18042.695 | D72: =+D71+D67+D70 -> 22025.515 | E72: =+E71+E67+E70 -> 24748.886 | F72: =+F71+F67+F70 -> 23313.574 | G72: =+G71+G67+G70 -> 23380.37 | H72: =+H71+H67+H70 -> 23503.915 | I72: 25196.103 | J72: =+J73-J67 -> 22406 | K72: 24899.027 | L72: 24150.456 | M72: 25413.232 | N72: 25892.036 | O72: 25742.024 | P72: 25872.283 | Q72: 24923.576 | R72: 27435.821 | S72: 26841.025 | T72: 26129.168 | U72: 24492.288 | V72: 24782.675 | W72: 24428.805 | X72: 25027.812 | Y72: 25241.428 | Z72: 24807.136 | AA72: 25246.854 | AB72: 25118.77 | AC72: 24934.5 | AD72: 24325.795 | AE72: 22857.32 | AF72: 22823.222 | AG72: 22706.432 | AH72: 22294.504 | AI72: 22459.966 | AJ72: 22779.609 | AK72: 22814.444 | AL72: 22930.8 | AM72: 23225.321 | AN72: 23230.92 | AO72: 22992.947 | AP72: =+AP70+AP67+AP71 -> 23025.842 | AQ72: =+AQ70+AQ67+AQ71 -> 22942.183 | AR72: =+AR70+AR67+AR71 -> 22939.521 | AS72: =+AS70+AS67+AS71 -> 22850.431 | AU72: 23162.892 | AW72: =+AW71+AW67+AW70 -> 9987.723 | AX72: =+AX71+AX67+AX70 -> 12179.395 | AY72: =+AY71+AY67+AY70 -> 12982.877 | AZ72: =+AZ71+AZ67+AZ70 -> 13917.92 | BA72: =+BA71+BA67+BA70 -> 14849.542 | BB72: =+BB71+BB67+BB70 -> 16129.419 | BC72: =+BC71+BC67+BC70 -> 17143.97 | BD72: =+BD71+BD67+BD70 -> 17138.172 | ... BZ72: =+BZ71+BZ67+BZ70 -> 22850.431 | CA72: =+CA70+CA67+CA71 -> 22878.837 | CB72: =+CB70+CB67+CB71 -> 22944.73 | CC72: =+CC70+CC67+CC71 -> 23044.981 | CD72: =+CD70+CD67+CD71 -> 23176.805
A73: Total Assets | B73: =+B72+B63 -> 38009.692 | C73: =+C72+C63 -> 35772.275 | D73: =+D72+D63 -> 39919.541 | E73: =+E72+E63 -> 40698.626 | F73: =+F72+F63 -> 40055.686 | G73: =+G72+G63 -> 39436.354 | H73: =+H72+H63 -> 38624.938 | I73: =+I72+I63 -> 39340.32 | J73: 39998 | K73: =+K72+K63 -> 43616.139 | L73: =+L72+L63 -> 40626.869 | M73: =+M72+M63 -> 41205.215 | N73: =+N72+N63 -> 43726.036 | O73: =+O72+O63 -> 42836.024 | P73: =+P72+P63 -> 42747.914 | Q73: =+Q72+Q63 -> 41682.235 | R73: =+R72+R63 -> 48975.8 | ... AS73: =+AS72+AS63 -> 45168.673 | AU73: 42656.143 | AW73: =+AW72+AW63 -> 15177.363 | AX73: =+AX72+AX63 -> 17619.51 | AY73: =+AY72+AY63 -> 19817.431 | AZ73: =+AZ72+AZ63 -> 20772.077 | BA73: =+BA72+BA63 -> 22061.755 | BB73: =+BB72+BB63 -> 22873.804 | BC73: =+BC72+BC63 -> 24319.621 | BD73: =+BD72+BD63 -> 25297.429 | ... CD73: =+CD72+CD63 -> 53191.539
A75: ST Debt | B75: 0 | C75: 2500 | D75: 2530.565 | E75: 2513.239 | F75: 2606.192 | G75: 175 | H75: 1675 | I75: 1675 | J75: =1500+200 -> 1700 | K75: 1730 | L75: 630 | M75: 635 | N75: =235+400 -> 635 | O75: =635+208.335 -> 843.335 | P75: =235+207.589 -> 442.589 | Q75: 2735 | R75: 7562.082 | S75: 7399.38 | T75: 7200.526 | U75: 4236.165 | V75: 235 | W75: 3235 | X75: 3284.207 | Y75: 3257.893 | Z75: 3242.228 | AA75: 1753.365 | AB75: 2015.424 | AC75: 2048.584 | AD75: 2159.333 | AE75: 6364.242 | AF75: 4634.757 | AG75: 4527.467 | AH75: 8642.751 | AI75: 4638.378 | AJ75: 4970.867 | AK75: 5220 | AL75: 10.821 | AM75: 1501.988 | AN75: 1506.514 | AO75: 1509.011 | AP75: =AP141 -> 1509.011 | AQ75: =AQ141 -> 1509.011 | AR75: =AR141 -> 1509.011 | AS75: =AS141 -> 1509.011 | AU75: 1506.514 | AW75: 139.89 | AX75: 1629.725 | AY75: 135.059 | AZ75: 627.555 | BA75: 876.797 | BB75: 1606.06 | BC75: 107.905 | BD75: 660.496 | BE75: 95.465 | BF75: 96.99 | BG75: 76.108 | BH75: 3529.268 | BI75: 73.677 | BJ75: 46.687 | BK75: 17.297 | BL75: 0 | BM75: 0 | BN75: 0 | BO75: 0 | BP75: 2513.239 | BQ75: =+SUMIFS($B75:$AK75,$B$2:$AK$2,"="&BQ$2) -> 1675 | BR75: =+SUMIFS($B75:$AK75,$B$2:$AK$2,"="&BR$2) -> 635 | BS75: =+SUMIFS($B75:$AK75,$B$2:$AK$2,"="&BS$2) -> 2735 | BT75: =+SUMIFS($B75:$AK75,$B$2:$AK$2,"="&BT$2) -> 4236.165 | BU75: =+SUMIFS($B75:$AK75,$B$2:$AK$2,"="&BU$2) -> 3257.893 | BV75: =+SUMIFS($B75:$AK75,$B$2:$AK$2,"="&BV$2) -> 2048.584 | BW75: =+SUMIFS($B75:$AK75,$B$2:$AK$2,"="&BW$2) -> 4527.467 | BX75: =+SUMIFS($B75:$AO75,$B$2:$AO$2,"="&BX$2) -> 5220 | BY75: =+SUMIFS($B75:$AS75,$B$2:$AS$2,"="&BY$2) -> 1509.011 | BZ75: =+SUMIFS($B75:$AS75,$B$2:$AS$2,"="&BZ$2) -> 1509.011 | CA75: =CA141 -> 1509.011 | CB75: =CB141 -> 1509.011 | CC75: =CC141 -> 1509.011 | CD75: =CD141 -> 1509.011
A76: Trade Payable | B76: 7137.828 | C76: 5839.228 | D76: 5806.001 | E76: 6265.844 | F76: 6411.896 | G76: 6444.59 | H76: 5810.772 | I76: 6476.047 | J76: 7218.257 | K76: 7405.645 | L76: 7050.44 | M76: 7648.773 | N76: 6479 | O76: 7631.352 | P76: 7116.609 | Q76: 7456.608 | R76: 9227.688 | S76: 9186.357 | T76: 8344.511 | U76: 8238.361 | V76: 9131.575 | W76: 9065.442 | X76: 9614.539 | Y76: 10148.806 | Z76: 10195.156 | AA76: 10898.206 | AB76: 10357.12 | AC76: 10154.372 | AD76: 10467.463 | AE76: 11255.236 | AF76: 10293.18 | AG76: 10340.881 | AH76: 10565.714 | AI76: 11505.544 | AJ76: 11322.382 | AK76: 11871.864 | AL76: 11787.193 | AM76: 11743.947 | AN76: 10979.98 | AO76: 11293.771 | AP76: =-AP77*AP5*4 -> 11499.077 | AQ76: =-AQ77*AQ5*4 -> 11649.899 | AR76: =-AR77*AR5*4 -> 11263.788 | AS76: =-AS77*AS5*4 -> 11417.785 | AU76: 11250.592 | AW76: 887.283 | AX76: 1088.288 | AY76: 1375.864 | AZ76: 1223.323 | BA76: 1403.845 | BB76: 1508.761 | BC76: 1584.275 | BD76: 1800.608 | BE76: 2442.758 | BF76: 2657.991 | BG76: 2044.192 | BH76: 2395.287 | BI76: 2633.156 | BJ76: 2691.547 | BK76: 3156.348 | BL76: 2812.375 | BM76: 3319.071 | BN76: 3487.438 | BO76: 3721.679 | BP76: 6265.844 | BQ76: =+SUMIFS($B76:$AK76,$B$2:$AK$2,"="&BQ$2) -> 6476.047 | BR76: =+SUMIFS($B76:$AK76,$B$2:$AK$2,"="&BR$2) -> 7648.773 | BS76: =+SUMIFS($B76:$AK76,$B$2:$AK$2,"="&BS$2) -> 7456.608 | BT76: =+SUMIFS($B76:$AK76,$B$2:$AK$2,"="&BT$2) -> 8238.361 | BU76: =+SUMIFS($B76:$AK76,$B$2:$AK$2,"="&BU$2) -> 10148.806 | BV76: =+SUMIFS($B76:$AK76,$B$2:$AK$2,"="&BV$2) -> 10154.372 | BW76: =+SUMIFS($B76:$AK76,$B$2:$AK$2,"="&BW$2) -> 10340.881 | BX76: =+SUMIFS($B76:$AO76,$B$2:$AO$2,"="&BX$2) -> 11871.864 | BY76: =+SUMIFS($B76:$AS76,$B$2:$AS$2,"="&BY$2) -> 11293.771 | BZ76: =+SUMIFS($B76:$AS76,$B$2:$AS$2,"="&BZ$2) -> 11417.785 | CA76: =-CA77*CA5 -> 11694.25 | CB76: =-CB77*CB5 -> 11957.233 | CC76: =-CC77*CC5 -> 12227.765 | CD76: =-CD77*CD5 -> 12505.883
A77: % of Cash Costs | B77: =-B76/B5/4 -> 0.3372051 | C77: =-C76/C5/4 -> 0.27142152 | D77: =-D76/D5/4 -> 0.27005681 | E77: =-E76/E5/4 -> 0.26867653 | F77: =-F76/F5/4 -> 0.26082261 | G77: =-G76/G5/4 -> 0.25958826 | H77: =-H76/H5/4 -> 0.24241606 | I77: =-I76/I5/4 -> 0.26899164 | ... AO77: =-AO76/AO5/4 -> 0.33701128 | AP77: =+AO77 -> 0.33701128 | AQ77: =+AP77 -> 0.33701128 | AR77: =+AQ77 -> 0.33701128 | AS77: =+AR77 -> 0.33701128 | AU77: 0.33400983 | AW77: =-AW76/AW5 -> 0.14180455 | AX77: =-AX76/AX5 -> 0.15088808 | AY77: =-AY76/AY5 -> 0.17574235 | AZ77: =-AZ76/AZ5 -> 0.13500395 | BA77: =-BA76/BA5 -> 0.15958052 | BB77: =-BB76/BB5 -> 0.16230057 | BC77: =-BC76/BC5 -> 0.15427455 | BD77: =-BD76/BD5 -> 0.14630039 | ... BZ77: =-BZ76/BZ5 -> 0.33583907 | CA77: =BZ77 -> 0.33583907 | CB77: =CA77 -> 0.33583907 | CC77: =CB77 -> 0.33583907 | CD77: =CC77 -> 0.33583907
A78: Other Current Liabilities | B78: 5316.384 | C78: 5218.99 | D78: 4175.8641 | E78: 2221.3331 | F78: 6893.3021 | G78: 5034.815 | H78: 3983.818 | I78: =+I80-I75-I76 -> 1816.543 | J78: =+J80-J75-J76 -> 6991.599 | K78: =+K80-K75-K76 -> 5397.029 | L78: =+L80-L75-L76 -> 4181.609 | M78: =+M80-M75-M76 -> 1935.2268 | N78: =+N80-N75-N76 -> 8835.938 | O78: =+O80-O75-O76 -> 5290.12 | P78: =+P80-P75-P76 -> 4556.299 | ... AO78: =+AO80-AO75-AO76 -> 2767.269 | AP78: =+AL78*AP3/AL3 -> 9575.3102 | AQ78: =+AM78*AQ3/AM3 -> 7490.4079 | AR78: =+AN78*AR3/AN3 -> 6155.3279 | AS78: =+AO78*AS3/AO3 -> 2836.4507 | AU78: 3453.2726 | AW78: 669.036 | AX78: 929.455 | AY78: 1249.152 | AZ78: 1634.3 | BA78: 1472.481 | BB78: 1573.573 | BC78: 1509.557 | BD78: 2233.084 | BE78: 2500.016 | BF78: 3418.837 | BG78: 2180.941 | BH78: 2691.556 | BI78: 6526.026 | BJ78: 2570.963 | BK78: 2391.467 | BL78: 4380.007 | BM78: 5437.757 | BN78: 4388.891 | BO78: 4595.644 | BP78: 2221.3331 | BQ78: =+SUMIFS($B78:$AK78,$B$2:$AK$2,"="&BQ$2) -> 1816.543 | BR78: =+SUMIFS($B78:$AK78,$B$2:$AK$2,"="&BR$2) -> 1935.2268 | BS78: =+SUMIFS($B78:$AK78,$B$2:$AK$2,"="&BS$2) -> 2754.515 | BT78: =+SUMIFS($B78:$AK78,$B$2:$AK$2,"="&BT$2) -> 3087.773 | BU78: =+SUMIFS($B78:$AK78,$B$2:$AK$2,"="&BU$2) -> 1843.457 | BV78: =+SUMIFS($B78:$AK78,$B$2:$AK$2,"="&BV$2) -> 2468.702 | BW78: =+SUMIFS($B78:$AK78,$B$2:$AK$2,"="&BW$2) -> 3858.504 | BX78: =+SUMIFS($B78:$AO78,$B$2:$AO$2,"="&BX$2) -> 3402.239 | BY78: =+SUMIFS($B78:$AS78,$B$2:$AS$2,"="&BY$2) -> 2767.269 | BZ78: =+SUMIFS($B78:$AS78,$B$2:$AS$2,"="&BZ$2) -> 2836.4507 | CA78: =-CA79*CA5 -> 2905.1312 | CB78: =-CB79*CB5 -> 2970.4625 | CC78: =-CC79*CC5 -> 3037.6691 | CD78: =-CD79*CD5 -> 3106.7604
A79: % of Cash Costs | B79: =-B78/B5/4 -> 0.25115648 | C79: =-C78/C5/4 -> 0.24259135 | D79: =-D78/D5/4 -> 0.19423361 | E79: =-E78/E5/4 -> 0.095249748 | F79: =-F78/F5/4 -> 0.2804052 | G79: =-G78/G5/4 -> 0.20280248 | H79: =-H78/H5/4 -> 0.16619848 | I79: =-I78/I5/4 -> 0.075452647 | ... AS79: =-AS78/AS5/4 -> 0.083721658 | AU79: 0.10252145 | AW79: =-AW78/AW5 -> 0.10692457 | AX79: =-AX78/AX5 -> 0.12886633 | AY79: =-AY78/AY5 -> 0.15955713 | AZ79: =-AZ78/AZ5 -> 0.1803587 | BA79: =-BA78/BA5 -> 0.16738264 | BB79: =-BB78/BB5 -> 0.16927253 | BC79: =-BC78/BC5 -> 0.14699861 | BD79: =-BD78/BD5 -> 0.1814393 | ... BZ79: =-BZ78/BZ5 -> 0.083430455 | CA79: =+BZ79 -> 0.083430455 | CB79: =+CA79 -> 0.083430455 | CC79: =+CB79 -> 0.083430455 | CD79: =+CC79 -> 0.083430455
A80: Current Liabilities | B80: =+B78+B75+B76 -> 12454.212 | C80: =+C78+C75+C76 -> 13558.218 | D80: =+D78+D75+D76 -> 12512.43 | E80: =+E78+E75+E76 -> 11000.416 | F80: =+F78+F75+F76 -> 15911.39 | G80: =+G78+G75+G76 -> 11654.405 | H80: =+H78+H75+H76 -> 11469.59 | I80: 9967.59 | J80: 15909.856 | K80: 14532.674 | L80: 11862.049 | M80: 10219 | N80: 15949.938 | O80: 13764.807 | P80: 12115.497 | Q80: 12946.123 | R80: 24333.588 | S80: 22461.63 | T80: 20776.174 | U80: 15562.299 | V80: 17111.278 | W80: 17898.207 | X80: 17377.421 | Y80: 15250.156 | Z80: 20608.55 | AA80: 18365.877 | AB80: 17136.283 | AC80: 14671.658 | AD80: 20440.067 | AE80: 23800.592 | AF80: 20579.327 | AG80: 18726.852 | AH80: 29338.026 | AI80: 23561.679 | AJ80: 22519.237 | AK80: 20494.103 | AL80: 21185.573 | AM80: 20553.65 | AN80: 18491.692 | AO80: 15570.051 | AP80: =+AP78+AP75+AP76 -> 22583.398 | AQ80: =+AQ78+AQ75+AQ76 -> 20649.318 | AR80: =+AR78+AR75+AR76 -> 18928.127 | AS80: =+AS78+AS75+AS76 -> 15763.247 | AU80: 16210.379 | AW80: =+AW78+AW75+AW76 -> 1696.209 | AX80: =+AX78+AX75+AX76 -> 3647.468 | AY80: =+AY78+AY75+AY76 -> 2760.075 | AZ80: =+AZ78+AZ75+AZ76 -> 3485.178 | BA80: =+BA78+BA75+BA76 -> 3753.123 | BB80: =+BB78+BB75+BB76 -> 4688.394 | BC80: =+BC78+BC75+BC76 -> 3201.737 | BD80: =+BD78+BD75+BD76 -> 4694.188 | ... CD80: =+CD78+CD75+CD76 -> 17121.655
A82: LT Debt | B82: 20848.137 | C82: 19218.031 | D82: 19998.515 | E82: 20762.887 | F82: 19329.99 | G82: 21894.094 | H82: 20515.239 | I82: 21630.132 | J82: 20455.88 | K82: 24469.013 | L82: 23404.005 | M82: 24005.567 | N82: 23822 | O82: 23948.913 | P82: 24579.411 | Q82: 21440.495 | R82: 20174.788 | S82: 20155.379 | T82: 30611.357 | U82: 30255.447 | V82: 29666.299 | W82: 26101.866 | X82: 25965.027 | Y82: 26103.329 | Z82: 25677.356 | AA82: 24131.538 | AB82: 32745.334 | AC82: 32468.6 | AD82: 31898.243 | AE82: 27353.563 | AF82: 26879.005 | AG82: 27190.461 | AH82: 22872.937 | AI82: 22783.426 | AJ82: 22935.506 | AK82: 23059.446 | AL82: 23148.931 | AM82: 21781.923 | AN82: 21632.458 | AO82: 21674.134 | AP82: =+AP142 -> 21674.134 | AQ82: =+AQ142 -> 21674.134 | AR82: =+AR142 -> 21674.134 | AS82: =+AS142 -> 21674.134 | AU82: 21632.458 | AW82: 1988.191 | AX82: 1056.745 | AY82: 3480.514 | AZ82: 3393.176 | BA82: 4262.145 | BB82: 3619.283 | BC82: 5954.577 | BD82: 5262.389 | BE82: 5020.497 | BF82: 4971.767 | BG82: 7414.964 | BH82: 4646.471 | BI82: 7315.454 | BJ82: 11265.364 | BK82: 11250 | BL82: 9978.834 | BM82: 10177.845 | BN82: 13086.817 | BO82: 17238.2 | BP82: 20762.887 | BQ82: =+SUMIFS($B82:$AK82,$B$2:$AK$2,"="&BQ$2) -> 21630.132 | BR82: =+SUMIFS($B82:$AK82,$B$2:$AK$2,"="&BR$2) -> 24005.567 | BS82: =+SUMIFS($B82:$AK82,$B$2:$AK$2,"="&BS$2) -> 21440.495 | BT82: =+SUMIFS($B82:$AK82,$B$2:$AK$2,"="&BT$2) -> 30255.447 | BU82: =+SUMIFS($B82:$AK82,$B$2:$AK$2,"="&BU$2) -> 26103.329 | BV82: =+SUMIFS($B82:$AK82,$B$2:$AK$2,"="&BV$2) -> 32468.6 | BW82: =+SUMIFS($B82:$AK82,$B$2:$AK$2,"="&BW$2) -> 27190.461 | BX82: =+SUMIFS($B82:$AO82,$B$2:$AO$2,"="&BX$2) -> 23059.446 | BY82: =+SUMIFS($B82:$AS82,$B$2:$AS$2,"="&BY$2) -> 21674.134 | BZ82: =+SUMIFS($B82:$AS82,$B$2:$AS$2,"="&BZ$2) -> 21674.134 | CA82: =+CA142 -> 21674.134 | CB82: =+CB142 -> 21674.134 | CC82: =+CC142 -> 21674.134 | CD82: =+CD142 -> 21674.134
A83: Deferred Income Tax | B83: 1479.04 | C83: 1384.959 | D83: 1444.648 | E83: 1408.296 | F83: 1339.964 | G83: 1332.599 | H83: 1288.003 | I83: 1108.433 | J83: 970.695 | K83: 857.933 | L83: 727.312 | M83: 826.158 | N83: 682 | O83: 598.661 | P83: 505.474 | Q83: 391.227 | R83: 477.215 | S83: 517.029 | T83: 439.019 | U83: 19.455 | V83: 218.239 | W83: 321.549 | X83: 414.796 | Y83: 198.505 | Z83: 122.78 | AA83: 25.904 | AB83: 0 | AC83: 0 | AD83: =+AC83 -> 0 | AE83: =+AD83 -> 0 | AF83: =+AE83 -> 0 | AG83: =+AF83 -> 0 | AH83: =+AG83 -> 0 | AI83: =+AH83 -> 0 | AJ83: =+AI83 -> 0 | AK83: =+AJ83 -> 0 | ... AS83: =+AR83 -> 0 | AU83: 0 | AW83: 734.009 | AX83: 728.067 | AY83: 826.941 | AZ83: 2539.896 | BA83: 2493.89 | BB83: 2818.467 | BC83: 3163.837 | BD83: 3001.005 | BE83: 2540.778 | BF83: 0 | BG83: 0 | BH83: 0 | BI83: 0 | BJ83: 0 | BK83: 2031.191 | BL83: 1847.104 | BM83: 1712.747 | BN83: 1712.511 | BO83: 1461.82 | BP83: 1408.296 | BQ83: =+SUMIFS($B83:$AK83,$B$2:$AK$2,"="&BQ$2) -> 1108.433 | BR83: =+SUMIFS($B83:$AK83,$B$2:$AK$2,"="&BR$2) -> 826.158 | BS83: =+SUMIFS($B83:$AK83,$B$2:$AK$2,"="&BS$2) -> 391.227 | BT83: =+SUMIFS($B83:$AK83,$B$2:$AK$2,"="&BT$2) -> 19.455 | BU83: =+SUMIFS($B83:$AK83,$B$2:$AK$2,"="&BU$2) -> 198.505 | BV83: =+SUMIFS($B83:$AK83,$B$2:$AK$2,"="&BV$2) -> 0 | BW83: =+SUMIFS($B83:$AK83,$B$2:$AK$2,"="&BW$2) -> 0 | BX83: =+SUMIFS($B83:$AO83,$B$2:$AO$2,"="&BX$2) -> 0 | BY83: =+SUMIFS($B83:$AS83,$B$2:$AS$2,"="&BY$2) -> 0 | BZ83: =+SUMIFS($B83:$AS83,$B$2:$AS$2,"="&BZ$2) -> 0 | CA83: =+BZ83 -> 0 | CB83: =+CA83 -> 0 | CC83: =+CB83 -> 0 | CD83: =+CC83 -> 0
A84: Other LT liabilities | B84: 210.664 | C84: 221.161 | D84: 228.697 | E84: 440.932 | F84: 442.288 | G84: 432.266 | H84: 456.198 | I84: =227.003+260.275 -> 487.278 | J84: =+J85-J83-J82 -> 482.848 | K84: =+K85-K83-K82 -> 491.245 | L84: =+L85-L83-L82 -> 500.88 | M84: =+M85-M83-M82 -> 550.998 | N84: =+N85-N83-N82 -> 1732.491 | O84: =+O85-O83-O82 -> 1689.891 | P84: =+P85-P83-P82 -> 1664.408 | Q84: =+Q85-Q83-Q82 -> 1731.445 | ... AO84: =+AO85-AO83-AO82 -> 1152.621 | AP84: =+AO84 -> 1152.621 | AQ84: =+AP84 -> 1152.621 | AR84: =+AQ84 -> 1152.621 | AS84: =+AR84 -> 1152.621 | AU84: 1199.511 | AW84: 0 | AX84: 0 | AY84: 0 | AZ84: 0 | BA84: 0 | BB84: 0 | BC84: 0 | BD84: 0 | BE84: 427.417 | BF84: 1917.104 | BG84: 2320.425 | BH84: 2283.891 | BI84: 1986.16 | BJ84: 2099.639 | BK84: 375.431 | BL84: 392.041 | BM84: 305.104 | BN84: 323.165 | BO84: 292.148 | BP84: 440.932 | BQ84: =+SUMIFS($B84:$AK84,$B$2:$AK$2,"="&BQ$2) -> 487.278 | BR84: =+SUMIFS($B84:$AK84,$B$2:$AK$2,"="&BR$2) -> 550.998 | BS84: =+SUMIFS($B84:$AK84,$B$2:$AK$2,"="&BS$2) -> 1731.445 | BT84: =+SUMIFS($B84:$AK84,$B$2:$AK$2,"="&BT$2) -> 1786.629 | BU84: =+SUMIFS($B84:$AK84,$B$2:$AK$2,"="&BU$2) -> 1508.373 | BV84: =+SUMIFS($B84:$AK84,$B$2:$AK$2,"="&BV$2) -> 1372.912 | BW84: =+SUMIFS($B84:$AK84,$B$2:$AK$2,"="&BW$2) -> 1080.454 | BX84: =+SUMIFS($B84:$AO84,$B$2:$AO$2,"="&BX$2) -> 1148.982 | BY84: =+SUMIFS($B84:$AS84,$B$2:$AS$2,"="&BY$2) -> 1152.621 | BZ84: =+SUMIFS($B84:$AS84,$B$2:$AS$2,"="&BZ$2) -> 1152.621 | CA84: =+BZ84 -> 1152.621 | CB84: =+CA84 -> 1152.621 | CC84: =+CB84 -> 1152.621 | CD84: =+CC84 -> 1152.621
A85: Non Current Liabilities | B85: =+B84+B82+B83 -> 22537.841 | C85: =+C84+C82+C83 -> 20824.151 | D85: =+D84+D82+D83 -> 21671.86 | E85: =+E84+E82+E83 -> 22612.115 | F85: =+F84+F82+F83 -> 21112.242 | G85: =+G84+G82+G83 -> 23658.959 | H85: =+H84+H82+H83 -> 22259.44 | I85: =+I84+I82+I83 -> 23225.843 | J85: 21909.423 | K85: 25818.191 | L85: 24632.197 | M85: 25382.723 | N85: 26236.491 | O85: 26237.465 | P85: 26749.293 | Q85: 23563.167 | R85: 22632.294 | S85: 22626.597 | T85: 32963.503 | U85: 32061.531 | V85: 31654.278 | W85: 28151.101 | X85: 28165.354 | Y85: 27810.207 | Z85: 27284.498 | AA85: 25706.777 | AB85: 34134.651 | AC85: 33841.512 | AD85: 33211.604 | AE85: 28608.989 | AF85: 28167.487 | AG85: 28270.915 | AH85: 23906.867 | AI85: 23816.667 | AJ85: 23932.896 | AK85: 24208.428 | AL85: 24252.957 | AM85: 23043.768 | AN85: 22831.969 | AO85: 22826.755 | AP85: =+AP84+AP82+AP83 -> 22826.755 | AQ85: =+AQ84+AQ82+AQ83 -> 22826.755 | AR85: =+AR84+AR82+AR83 -> 22826.755 | AS85: =+AS84+AS82+AS83 -> 22826.755 | AU85: 22831.969 | AW85: =+AW84+AW82+AW83 -> 2722.2 | AX85: =+AX84+AX82+AX83 -> 1784.812 | AY85: =+AY84+AY82+AY83 -> 4307.455 | AZ85: =+AZ84+AZ82+AZ83 -> 5933.072 | BA85: =+BA84+BA82+BA83 -> 6756.035 | BB85: =+BB84+BB82+BB83 -> 6437.75 | BC85: =+BC84+BC82+BC83 -> 9118.414 | BD85: =+BD84+BD82+BD83 -> 8263.394 | ... CD85: =+CD84+CD82+CD83 -> 22826.755
A87: Minorities | B87: 0 | C87: 0 | D87: 0.0001 | E87: 86.822 | F87: 76.504 | G87: 81.762 | H87: 80.543 | I87: 56.689 | J87: 53.337 | K87: 51.636 | L87: 53.127 | M87: 42.709 | N87: -112.588 | O87: -107.914 | P87: -110.317 | Q87: -111.62 | R87: -119.74 | S87: -49.843 | T87: -85.525 | U87: -116.404 | V87: -135.048 | W87: -141.194 | X87: -145.98 | Y87: 0 | Z87: 0 | AA87: 0 | AB87: 0 | AC87: 0 | AD87: 0 | AE87: 0 | AF87: 0 | AG87: 0 | AH87: 0 | AI87: 0 | AJ87: 0 | AK87: 0 | AL87: 0 | AM87: =+AL87 -> 0 | AN87: =+AM87 -> 0 | AO87: =+AN87 -> 0 | AP87: =+AO87 -> 0 | AQ87: =+AP87 -> 0 | AR87: =+AQ87 -> 0 | AS87: =+AR87 -> 0 | AU87: 0 | AW87: 0 | AX87: 0 | AY87: 0 | AZ87: 0 | BA87: 0 | BB87: 0 | BC87: 0 | BD87: 0 | BE87: 0 | BF87: 0 | BG87: 0 | BH87: 0 | BI87: 0 | BJ87: 0 | BK87: 0 | BL87: 0 | BM87: 0 | BN87: 0 | BO87: 0 | BP87: 86.822 | BQ87: =+SUMIFS($B87:$AK87,$B$2:$AK$2,"="&BQ$2) -> 56.689 | BR87: =+SUMIFS($B87:$AK87,$B$2:$AK$2,"="&BR$2) -> 42.709 | BS87: =+SUMIFS($B87:$AK87,$B$2:$AK$2,"="&BS$2) -> -111.62 | BT87: =+SUMIFS($B87:$AK87,$B$2:$AK$2,"="&BT$2) -> -116.404 | BU87: =+SUMIFS($B87:$AK87,$B$2:$AK$2,"="&BU$2) -> 0 | BV87: =+SUMIFS($B87:$AK87,$B$2:$AK$2,"="&BV$2) -> 0 | BW87: =+SUMIFS($B87:$AK87,$B$2:$AK$2,"="&BW$2) -> 0 | BX87: =+SUMIFS($B87:$AO87,$B$2:$AO$2,"="&BX$2) -> 0 | BY87: =+SUMIFS($B87:$AS87,$B$2:$AS$2,"="&BY$2) -> 0 | BZ87: =+SUMIFS($B87:$AS87,$B$2:$AS$2,"="&BZ$2) -> 0 | CA87: =+BZ87 -> 0 | CB87: =+CA87 -> 0 | CC87: =+CB87 -> 0 | CD87: =+CC87 -> 0
A88: Shareholders Equity | B88: 3017.639 | C88: 4386.56 | D88: 5735.2509 | E88: 6999.273 | F88: 2955.55 | G88: 4041.228 | H88: 4815.365 | I88: 6090.198 | J88: 2125.867 | K88: =3274.274-51.636 -> 3222.638 | L88: 4079.496 | M88: 5560.782 | N88: 1652.011 | O88: =2833.843+107.914 -> 2941.757 | P88: 3993.441 | Q88: 5284.565 | R88: 2129.358 | S88: 3527.885 | T88: 5171.972 | U88: 5809.225 | V88: 2634.983 | W88: 4019.078 | X88: 5089.526 | Y88: 5723.629 | Z88: 1584.907 | AA88: 3008.501 | AB88: 3696.518 | AC88: 5027.45 | AD88: 1404.345 | AE88: 3182.246 | AF88: 5171.271 | AG88: 6921.157 | AH88: 3192.236 | AI88: 5513.699 | AJ88: 6509.763 | AK88: 7406.916 | AL88: 2681.492 | AM88: 4180.503 | AN88: 5311.81 | AO88: 7236.35 | AP88: =+AO88+AP27+AP113 -> 9210.4305 | AQ88: =+AP88+AQ27+AQ113 -> 9661.0965 | AR88: =+AQ88+AR27+AR113 -> 9824.1239 | AS88: =+AR88+AS27+AS113 -> 8578.6715 | AU88: 4113.7956 | AW88: 10758.952 | AX88: 12187.228 | AY88: 12749.901 | AZ88: 11353.827 | BA88: 11552.597 | BB88: 11747.66 | BC88: 11999.47 | BD88: 12339.847 | BE88: 11947.154 | BF88: 9373.526 | BG88: 9375.382 | BH88: 8702.494 | BI88: 8634.057 | BJ88: 8266.998 | BK88: 8679.472 | BL88: 8626.06 | BM88: 8587.315 | BN88: 6933.622 | BO88: 6737.538 | BP88: 6999.273 | BQ88: =+SUMIFS($B88:$AK88,$B$2:$AK$2,"="&BQ$2) -> 6090.198 | BR88: =+SUMIFS($B88:$AK88,$B$2:$AK$2,"="&BR$2) -> 5560.782 | BS88: =+SUMIFS($B88:$AK88,$B$2:$AK$2,"="&BS$2) -> 5284.565 | BT88: =+SUMIFS($B88:$AK88,$B$2:$AK$2,"="&BT$2) -> 5809.225 | BU88: =+SUMIFS($B88:$AK88,$B$2:$AK$2,"="&BU$2) -> 5723.629 | BV88: =+SUMIFS($B88:$AK88,$B$2:$AK$2,"="&BV$2) -> 5027.45 | BW88: =+SUMIFS($B88:$AK88,$B$2:$AK$2,"="&BW$2) -> 6921.157 | BX88: =+SUMIFS($B88:$AO88,$B$2:$AO$2,"="&BX$2) -> 7406.916 | BY88: =+SUMIFS($B88:$AS88,$B$2:$AS$2,"="&BY$2) -> 7236.35 | BZ88: =+SUMIFS($B88:$AS88,$B$2:$AS$2,"="&BZ$2) -> 8578.6715 | CA88: =+BZ88+CA27+CA113 -> 10213.822 | CB88: =+CA88+CB27+CB113 -> 11868.259 | CC88: =+CB88+CC27+CC113 -> 13524.52 | CD88: =+CC88+CD27+CD113 -> 15243.129
A90: Total Liabilities | B90: =+B85+B80+B88+B87 -> 38009.692 | C90: =+C85+C80+C88+C87 -> 38768.929 | D90: =+D85+D80+D88+D87 -> 39919.541 | E90: =+E85+E80+E88+E87 -> 40698.626 | F90: =+F85+F80+F88+F87 -> 40055.686 | G90: =+G85+G80+G88+G87 -> 39436.354 | H90: =+H85+H80+H88+H87 -> 38624.938 | I90: =+I85+I80+I88+I87 -> 39340.32 | ... AS90: =+AS85+AS80+AS88+AS87 -> 47168.673 | AU90: 43156.143 | AW90: =+AW85+AW80 -> 4418.409 | AX90: =+AX85+AX80 -> 5432.28 | AY90: =+AY85+AY80 -> 7067.53 | AZ90: =+AZ85+AZ80 -> 9418.25 | BA90: =+BA85+BA80 -> 10509.158 | BB90: =+BB85+BB80 -> 11126.144 | BC90: =+BC85+BC80 -> 12320.151 | BD90: =+BD85+BD80 -> 12957.582 | ... BO90: =+BO85+BO80 -> 27309.491 | BP90: =+BP85+BP80+BP88+BP87 -> 40698.626 | BQ90: =+BQ85+BQ80+BQ88+BQ87 -> 39340.32 | BR90: =+BR85+BR80+BR88+BR87 -> 41205.214 | BS90: =+BS85+BS80+BS88+BS87 -> 41682.235 | BT90: =+BT85+BT80+BT88+BT87 -> 53316.651 | BU90: =+BU85+BU80+BU88+BU87 -> 48783.992 | BV90: =+BV85+BV80+BV88+BV87 -> 53540.62 | BW90: =+BW85+BW80+BW88+BW87 -> 53918.924 | ... CD90: =+CD85+CD80+CD88+CD87 -> 55191.539
A91: Check | B91: =+B90-B73 -> 0 | C91: =+C90-C73 -> 2996.654 | D91: =+D90-D73 -> 0 | E91: =+E90-E73 -> 0 | F91: =+F90-F73 -> 0 | G91: =+G90-G73 -> 0 | H91: =+H90-H73 -> 0 | I91: =+I90-I73 -> 0 | ... AS91: =+AS90-AS73 -> 2000 | AU91: 500 | AW91: =AW87+AW88+AW90-AW73 -> -0.002 | AX91: =AX87+AX88+AX90-AX73 -> -0.002 | AY91: =AY87+AY88+AY90-AY73 -> 0 | AZ91: =AZ87+AZ88+AZ90-AZ73 -> 0 | BA91: =BA87+BA88+BA90-BA73 -> 0 | BB91: =BB87+BB88+BB90-BB73 -> 0 | BC91: =BC87+BC88+BC90-BC73 -> 0 | BD91: =BD87+BD88+BD90-BD73 -> 0 | ... BO91: =BO87+BO88+BO90-BO73 -> 0 | BP91: =+BP90-BP73 -> 0 | BQ91: =+BQ90-BQ73 -> #REF! | BR91: =+BR90-BR73 -> #REF! | BS91: =+BS90-BS73 -> #REF! | BT91: =+BT90-BT73 -> 0 | BU91: =+BU90-BU73 -> -0.0051 | BV91: =+BV90-BV73 -> 0 | BW91: =+BW90-BW73 -> 0 | ... CD91: =+CD90-CD73 -> 2000
A93: WK | B93: =(B57+B61+B59-B76-B78) -> -4587.231 | C93: =(C57+C61+C59-C76-C78) -> -2917.268 | D93: =(D57+D61+D59-D76-D78) -> -1026.7609 | E93: =(E57+E61+E59-E76-E78) -> 1.0711 | F93: =(F57+F61+F59-F76-F78) -> -3839.0119 | G93: =(G57+G61+G59-G76-G78) -> -1684.562 | H93: =(H57+H61+H59-H76-H78) -> -686.681 | I93: =(I57+I61+I59-I76-I78) -> 1177.288 | ... AS93: =(AS57+AS61+AS59-AS76-AS78) -> -949.80736 | AU93: -1513.6574 | AW93: =(AW57+AW61+AW59-AW76-AW78) -> 1555.263 | AX93: =(AX57+AX61+AX59-AX76-AX78) -> 1593.296 | AY93: =(AY57+AY61+AY59-AY76-AY78) -> 1638.355 | AZ93: =(AZ57+AZ61+AZ59-AZ76-AZ78) -> 1978.228 | BA93: =(BA57+BA61+BA59-BA76-BA78) -> 2130.273 | BB93: =(BB57+BB61+BB59-BB76-BB78) -> 1962.761 | BC93: =(BC57+BC61+BC59-BC76-BC78) -> 2372.302 | BD93: =(BD57+BD61+BD59-BD76-BD78) -> 1992.784 | ... CD93: =(CD57+CD61+CD59-CD76-CD78) -> -1211.5026
A94: COI | BT94: =+BT93+BT67 -> 15284.473 | BU94: =+BU93+BU67 -> 16346.929 | BV94: =+BV93+BV67 -> 16831.925 | BW94: =+BW93+BW67 -> 15965.671 | BX94: =+BX93+BX67 -> 17280.068 | BY94: =+BY93+BY67 -> 18045.342 | BZ94: =+BZ93+BZ67 -> 18034.129 | CA94: =+CA93+CA67 -> 17983.477 | ... CD94: =+CD93+CD67 -> 18098.807
A96: Cash Flow | B96: =B$2 -> 42459 | C96: =C$2 -> 42551 | D96: =D$2 -> 42643 | E96: =E$2 -> 42735 | F96: =F$2 -> 42825 | G96: =G$2 -> 42916 | H96: =H$2 -> 43008 | I96: =I$2 -> 43100 | ... AS96: =AS$2 -> 46387 | AU96: 46022 | AW96: =AW$2 -> 35795 | AX96: =AX$2 -> 36160 | AY96: =AY$2 -> 36525 | AZ96: =AZ$2 -> 36891 | BA96: =BA$2 -> 37256 | BB96: =BB$2 -> 37621 | BC96: =BC$2 -> 37986 | BD96: =BD$2 -> 38352 | ... CD96: =CD$2 -> 47848
A97: Net Income | B97: =B27 -> 1109.795 | C97: =C27 -> 1178.055 | D97: =D27 -> 1312.814 | E97: =E27 -> 1192.901 | F97: =F27 -> 1094.918 | G97: =G27 -> 1013.369 | H97: =H27 -> 854.473 | I97: =I27 -> 1074.543 | ... AS97: =AS27 -> 2139.9285 | AU97: 1920.6435 | AW97: =AW27 -> 1954.268 | AX97: =AX27 -> 1882.866 | AY97: =AY27 -> 2568.787 | AZ97: =AZ27 -> 2816.26 | BA97: =BA27 -> 2540.455 | BB97: =BB27 -> 1934.938 | BC97: =BC27 -> 1860.414 | BD97: =BD27 -> 2644.384 | ... CD97: =CD27 -> 8261.5191
A98: Amortization | B98: =-B65 -> 408.221 | C98: =-C65 -> 412.516 | D98: =-D65 -> 412.263 | E98: =-E65 -> 367.919 | F98: =-F65 -> 436.143 | G98: =-G65 -> 415.112 | H98: =-H65 -> 367.936 | I98: =-I65 -> 380.633 | ... AS98: =-AS65 -> 491.67429 | AU98: 569.46815 | AW98: =-AW65 -> 612.142 | AX98: =-AX65 -> 709.517 | AY98: =-AY65 -> 811.742 | AZ98: =-AZ65 -> 835.994 | BA98: =-BA65 -> 931.031 | BB98: =-BB65 -> 1083.713 | BC98: =-BC65 -> 1171.366 | BD98: =-BD65 -> 1241.009 | ... CD98: =-CD65 -> 2015.7342
A99: Chg WK | B99: =-((B57+B61-B78-B84-B76)-(#REF!+#REF!-#REF!-#REF!-#REF!)) -> #REF! | C99: =-((C57+C61-C78-C84-C76)-(B57+B61-B78-B84-B76)) -> -1332.646 | D99: =-((D57+D61-D78-D84-D76)-(C57+C61-C78-C84-C76)) -> -1543.8541 | E99: =-((E57+E61-E78-E84-E76)-(D57+D61-D78-D84-D76)) -> -943.787 | F99: =-((F57+F61-F78-F84-F76)-(E57+E61-E78-E84-E76)) -> 4158.403 | G99: =-((G57+G61-G78-G84-G76)-(F57+F61-F78-F84-F76)) -> -1900.9599 | H99: =-((H57+H61-H78-H84-H76)-(G57+G61-G78-G84-G76)) -> -1214.222 | I99: =-((I57+I61-I78-I84-I76)-(H57+H61-H78-H84-H76)) -> -1859.596 | J99: =-((J57+J61-J78-J84-J76)-(I57+I61-I78-I84-I76)) -> 4670.0198 | ... AG99: =-((AG57+AG61-AG78-AG84-AG76)-(AF57+AF61-AF78-AF84-AF76)) -> -1906.441 | AH99: =-((AH57+AH61+AH59-AH78-AH84-AH76)-(AG57+AG61+AG59-AG78-AG84-AG76)) -> 4740.17 | AI99: =-((AI57+AI61+AI59-AI78-AI84-AI76)-(AH57+AH61+AH59-AH78-AH84-AH76)) -> -1380.195 | AJ99: =-((AJ57+AJ61+AJ59-AJ78-AJ84-AJ76)-(AI57+AI61+AI59-AI78-AI84-AI76)) -> -1296.495 | AK99: =-((AK57+AK61+AK59-AK78-AK84-AK76)-(AJ57+AJ61+AJ59-AJ78-AJ84-AJ76)) -> -2392.343 | AL99: =-((AL57+AL61+AL59-AL78-AL84-AL76)-(AK57+AK61+AK59-AK78-AK84-AK76)) -> 6161.707 | AM99: =-((AM57+AM61+AM59-AM78-AM84-AM76)-(AL57+AL61+AL59-AL78-AL84-AL76)) -> -2157.536 | AN99: =-((AN57+AN61+AN59-AN78-AN84-AN76)-(AM57+AM61+AM59-AM78-AM84-AM76)) -> -1185.11 | AO99: =-((AO57+AO61+AO59-AO78-AO84-AO76)-(AN57+AN61+AN59-AN78-AN84-AN76)) -> -3295.889 | ... AS99: =-((AS57+AS61+AS59-AS78-AS84-AS76)-(AR57+AR61+AR59-AR78-AR84-AR76)) -> -3778.0792 | AU99: -2816.4516 | AW99: =-((AW57+AW61-AW78-AW84-AW76)-(A57+A61-A78-A84-A76)) -> #VALUE! | AX99: =-((AX57+AX61-AX78-AX84-AX76)-(AW57+AW61-AW78-AW84-AW76)) -> 38.594 | AY99: =-((AY57+AY61-AY78-AY84-AY76)-(AX57+AX61-AX78-AX84-AX76)) -> 167.497 | AZ99: =-((AZ57+AZ61-AZ78-AZ84-AZ76)-(AY57+AY61-AY78-AY84-AY76)) -> -248.99 | BA99: =-((BA57+BA61-BA78-BA84-BA76)-(AZ57+AZ61-AZ78-AZ84-AZ76)) -> -168.611 | BB99: =-((BB57+BB61-BB78-BB84-BB76)-(BA57+BA61-BA78-BA84-BA76)) -> 74.838 | BC99: =-((BC57+BC61-BC78-BC84-BC76)-(BB57+BB61-BB78-BB84-BB76)) -> -105.397 | BD99: =-((BD57+BD61-BD78-BD84-BD76)-(BC57+BC61-BC78-BC84-BC76)) -> 565.769 | BE99: =-((BE57+BE61-BE78-BE84-BE76)-(BD57+BD61-BD78-BD84-BD76)) -> 949.474 | ... BZ99: =-((BZ57+BZ61-BZ78-BZ84-BZ76)-(BY57+BY61-BY78-BY84-BY76)) -> -23.571116 | CA99: =-((CA57+CA61+CA59-CA78-CA84-CA76)-(BZ57+BZ61+BZ59-BZ78-BZ84-BZ76)) -> 79.056819 | CB99: =-((CB57+CB61+CB59-CB78-CB84-CB76)-(CA57+CA61+CA59-CA78-CA84-CA76)) -> 56.903918 | CC99: =-((CC57+CC61+CC59-CC78-CC84-CC76)-(CB57+CB61+CB59-CB78-CB84-CB76)) -> 60.900088 | CD99: =-((CD57+CD61+CD59-CD78-CD84-CD76)-(CC57+CC61+CC59-CC78-CC84-CC76)) -> 64.834438
A100: Minorities | B100: =-B26 -> 0 | C100: =-C26 -> 0 | D100: =-D26 -> 0 | E100: =-E26 -> -4.353 | F100: =-F26 -> -10.317999 | G100: =-G26 -> 5.258 | H100: =-H26 -> -1.219 | I100: =-I26 -> -23.854 | ... AS100: =-AS26 -> 0 | AU100: 0 | AW100: =-AW26 -> 0 | AX100: =-AX26 -> 0 | AY100: =-AY26 -> 0 | AZ100: =-AZ26 -> 0 | BA100: =-BA26 -> 0 | BB100: =-BB26 -> 0 | BC100: =-BC26 -> 0 | BD100: =-BD26 -> 0 | ... CD100: =-CD26 -> 0
A101: Others | B101: =+B102-SUM(B97:B100) -> #REF! | C101: =+C102-SUM(C97:C100) -> 752.428 | D101: =+D102-SUM(D97:D100) -> -1191.5759 | E101: =+E102-SUM(E97:E100) -> 2156.243 | F101: =+F102-SUM(F97:F100) -> -4725.146 | G101: =+G102-SUM(G97:G100) -> 1333.2209 | H101: =+H102-SUM(H97:H100) -> 1723.745 | I101: =+I102-SUM(I97:I100) -> 2403.658 | ... AO101: =+AO102-SUM(AO97:AO100) -> 3438.548 | AW101: =+AW102-SUM(AW97:AW100) -> #VALUE! | AX101: =+AX102-SUM(AX97:AX100) -> 169.501 | AY101: =+AY102-SUM(AY97:AY100) -> 200.926 | AZ101: =+AZ102-SUM(AZ97:AZ100) -> 119.93 | BA101: =+BA102-SUM(BA97:BA100) -> 454.251 | BB101: =+BB102-SUM(BB97:BB100) -> 445.283 | BC101: =+BC102-SUM(BC97:BC100) -> -51.082 | BD101: =+BD102-SUM(BD97:BD100) -> -124.713 | ... BZ101: =+BZ102-SUM(BZ97:BZ100) -> -107.73153
A102: CF from Operations | B102: 1302.347 | C102: 1010.353 | D102: -1010.353 | E102: 2768.923 | F102: 954 | G102: =1820-F102 -> 866 | H102: =3550.713-G102-F102 -> 1730.713 | I102: =5526.097-H102-G102-F102 -> 1975.384 | J102: 1609 | K102: =2803.578-J102 -> 1194.578 | L102: =6519.859-K102-J102 -> 3716.281 | M102: =6953.794-L102-K102-J102 -> 433.935 | N102: 2277 | O102: =4369-N102 -> 2092 | P102: =4369-O102 -> 2277 | Q102: =9862.111-P102-O102-N102 -> 3216.111 | R102: 2667 | S102: =5319.356-R102 -> 2652.356 | T102: =7594.274-S102-R102 -> 2274.918 | U102: =10333.761-T102-S102-R102 -> 2739.487 | V102: 1863.21 | W102: =2581-V102 -> 717.79 | X102: =5243.309-W102-V102 -> 2662.309 | Y102: =6797.661-X102-W102-V102 -> 1554.352 | Z102: 1551.228 | AA102: =3922.556-Z102 -> 2371.328 | AB102: =6263.363-AA102-Z102 -> 2340.807 | AC102: =8318.94-SUM(Z102:AB102) -> 2055.577 | AD102: 2530.065 | AE102: =5685.113-AD102 -> 3155.048 | AF102: =9293.47-AE102-AD102 -> 3608.357 | AG102: =12760.025-AF102-AE102-AD102 -> 3466.555 | AH102: 2679.268 | AI102: =4691.56-AH102 -> 2012.292 | AJ102: =7831.578-AI102-AH102 -> 3140.018 | AK102: =10601.299-AJ102-AI102-AH102 -> 2769.721 | AL102: 1550.498 | AM102: =3582.386-AL102 -> 2031.888 | AN102: =6976.119-AM102-AL102 -> 3393.733 | AO102: =9812.087-AN102-AM102-AL102 -> 2835.968 | AP102: =SUM(AP97:AP100) -> 9437.7181 | AQ102: =SUM(AQ97:AQ100) -> 444.33547 | AR102: =SUM(AR97:AR100) -> 1253.4057 | AS102: =SUM(AS97:AS100) -> -1146.4764 | AU102: -326.33999 | AW102: 2323.793 | AX102: 2800.478 | AY102: 3748.952 | AZ102: 3523.194 | BA102: 3757.126 | BB102: 3538.772 | BC102: 2875.301 | BD102: 4326.449 | BE102: 3880.849 | BF102: 4071.27 | BG102: 5474.97 | BH102: 5218.283 | BI102: 6644.039 | BJ102: 4860.27 | BK102: 4669.484 | BL102: 6928.654 | BM102: 7501.664 | BN102: 5464.651 | BO102: 7303.392 | BP102: 6659.384 | BQ102: =+SUMIFS($B102:$AK102,$B$1:$AK$1,"="&BQ$1) -> 5526.097 | BR102: =+SUMIFS($B102:$AK102,$B$1:$AK$1,"="&BR$1) -> 6953.794 | BS102: =+SUMIFS($B102:$AK102,$B$1:$AK$1,"="&BS$1) -> 9862.111 | BT102: =+SUMIFS($B102:$AK102,$B$1:$AK$1,"="&BT$1) -> 10333.761 | BU102: =+SUMIFS($B102:$AK102,$B$1:$AK$1,"="&BU$1) -> 6797.661 | BV102: =+SUMIFS($B102:$AK102,$B$1:$AK$1,"="&BV$1) -> 8318.94 | BW102: =+SUMIFS($B102:$AK102,$B$1:$AK$1,"="&BW$1) -> 12760.025 | BX102: =+SUMIFS($B102:$AO102,$B$1:$AO$1,"="&BX$1) -> 10601.299 | BY102: =+SUMIFS($B102:$AS102,$B$1:$AS$1,"="&BY$1) -> 9812.087 | BZ102: =+SUMIFS($B102:$AS102,$B$1:$AS$1,"="&BZ$1) -> 9988.9829 | CA102: =SUM(CA97:CA100) -> 10197.51 | CB102: =SUM(CB97:CB100) -> 10208.146 | CC102: =SUM(CC97:CC100) -> 10244.735 | CD102: =SUM(CD97:CD100) -> 10342.088
A104: Acquisitions e Outras | AJ104: =+AJ106-AJ105 -> -9.069 | AK104: =+AK106-AK105 -> 1212.867 | AL104: =+AL106-AL105 -> 245.73 | AM104: =+AM106-AM105 -> 119.465 | AN104: =+AN106-AN105 -> 98.756 | AO104: =+AO106-AO105 -> 154.277 | BX104: 0 | BY104: 0 | BZ104: 0 | CA104: 0 | CB104: 0 | CC104: 0 | CD104: 0
A105: Capital Expenditure | B105: 184.019 | C105: 274.283 | D105: -274.283 | E105: -3133.522 | F105: -676 | G105: =-1460-F105 -> -784 | H105: =-1952.904-G105-F105 -> -492.904 | I105: =-2577.711-H105-G105-F105 -> -624.807 | J105: -492 | K105: =-1102.895-J105 -> -610.895 | L105: =-1478.277-K105-J105 -> -375.382 | M105: =-1792.043-L105-K105-J105 -> -313.766 | N105: -167 | O105: =-424-N105 -> -257 | P105: =-583.522-O105-N105 -> -159.522 | Q105: =-771.988-P105-O105-N105 -> -188.466 | R105: -150 | S105: =-366.743-R105 -> -216.743 | T105: =-455.006-S105-R105 -> -88.263 | U105: =-795.281-T105-S105-R105 -> -340.275 | V105: -457.5555 | W105: =-813-V105 -> -355.4445 | X105: =-1522.958-W105-V105 -> -709.958 | Y105: =-2150.474-X105-W105-V105 -> -627.516 | Z105: -564.31 | AA105: =-1175.814-Z105 -> -611.504 | AB105: =-1644.177-AA105-Z105 -> -468.363 | AC105: =-2141.436-SUM(Z105:AB105) -> -497.259 | AD105: -350.292 | AE105: =-821.709-AD105 -> -471.417 | AF105: =-1243.695-AE105-AD105 -> -421.986 | AG105: =-2141.436-AF105-AE105-AD105 -> -897.741 | AH105: -591.615 | AI105: =-1286.325-AH105 -> -694.71 | AJ105: =-2028.07-AI105-AH105 -> -741.745 | AK105: =-2503.339-AJ105-AI105-AH105 -> -475.269 | AL105: -520.541 | AM105: =-950.872-AL105 -> -430.331 | AN105: =-1431.968-AM105-AL105 -> -481.096 | AO105: =-1824.734-AN105-AM105-AL105 -> -392.766 | AP105: =AP133 -> -530.95182 | AQ105: =AQ133 -> -441.08927 | AR105: =AR133 -> -493.1234 | AS105: =AS133 -> -402.58515 | AU105: -501.43985 | AW105: -117.269 | AX105: -651.93 | AY105: -1344.305 | AZ105: -1255.717 | BA105: -1735.475 | BB105: -905.207 | BC105: -780.839 | BD105: -553.533 | BE105: -994.385 | BF105: -2949.503 | BG105: -2091.996 | BH105: -670.141 | BI105: -630.304 | BJ105: -270.593 | BK105: -1732.319 | BL105: -2567.822 | BM105: 0 | BN105: -1628.227 | BO105: -1318.27 | BP105: -2949.503 | BQ105: =+SUMIFS($B105:$AK105,$B$1:$AK$1,"="&BQ$1) -> -2577.711 | BR105: =+SUMIFS($B105:$AK105,$B$1:$AK$1,"="&BR$1) -> -1792.043 | BS105: =+SUMIFS($B105:$AK105,$B$1:$AK$1,"="&BS$1) -> -771.988 | BT105: =+SUMIFS($B105:$AK105,$B$1:$AK$1,"="&BT$1) -> -795.281 | BU105: =+SUMIFS($B105:$AK105,$B$1:$AK$1,"="&BU$1) -> -2150.474 | BV105: =+SUMIFS($B105:$AK105,$B$1:$AK$1,"="&BV$1) -> -2141.436 | BW105: =+SUMIFS($B105:$AK105,$B$1:$AK$1,"="&BW$1) -> -2141.436 | BX105: =+SUMIFS($B105:$AO105,$B$1:$AO$1,"="&BX$1) -> -2503.339 | BY105: =+SUMIFS($B105:$AS105,$B$1:$AS$1,"="&BY$1) -> -1824.734 | BZ105: =+SUMIFS($B105:$AS105,$B$1:$AS$1,"="&BZ$1) -> -1867.7496 | CA105: =CA133 -> -2023.6915 | CB105: =CB133 -> -2064.1653 | CC105: =CC133 -> -2105.4486 | CD105: =CD133 -> -2147.5576
A106: CF from Investing | B106: =+SUM(B104:B105) -> 184.019 | C106: =+SUM(C104:C105) -> 274.283 | D106: =+SUM(D104:D105) -> -274.283 | E106: =+SUM(E104:E105) -> -3133.522 | F106: =+SUM(F104:F105) -> -676 | G106: =+SUM(G104:G105) -> -784 | H106: =+SUM(H104:H105) -> -492.904 | I106: =+SUM(I104:I105) -> -624.807 | ... AI106: =+SUM(AI104:AI105) -> -694.71 | AJ106: =-2037.139-AI106-AH106 -> -750.814 | AK106: =-1299.541-AJ106-AI106-AH106 -> 737.598 | AL106: -274.811 | AM106: =-585.677-AL106 -> -310.866 | AN106: =-968.017-AM106-AL106 -> -382.34 | AO106: =-1206.506-AN106-AM106-AL106 -> -238.489 | AP106: =+SUM(AP104:AP105) -> -530.95182 | AQ106: =+SUM(AQ104:AQ105) -> -441.08927 | AR106: =+SUM(AR104:AR105) -> -493.1234 | AS106: =+SUM(AS104:AS105) -> -402.58515 | AU106: -501.43985 | AW106: =+SUM(AW104:AW105) -> -117.269 | AX106: =+SUM(AX104:AX105) -> -651.93 | AY106: =+SUM(AY104:AY105) -> -1344.305 | AZ106: =+SUM(AZ104:AZ105) -> -1255.717 | BA106: =+SUM(BA104:BA105) -> -1735.475 | BB106: =+SUM(BB104:BB105) -> -905.207 | BC106: =+SUM(BC104:BC105) -> -780.839 | BD106: =+SUM(BD104:BD105) -> -553.533 | ... CD106: =+SUM(CD104:CD105) -> -2147.5576
A107: FCF | B107: =+B106+B102 -> 1486.366 | C107: =+C106+C102 -> 1284.636 | D107: =+D106+D102 -> -1284.636 | E107: =+E106+E102 -> -364.599 | F107: =+F106+F102 -> 278 | G107: =+G106+G102 -> 82 | H107: =+H106+H102 -> 1237.809 | I107: =+I106+I102 -> 1350.577 | ... AS107: =+AS106+AS102 -> -1549.0616 | AU107: -827.77984 | AW107: =+AW106+AW102 -> 2206.524 | AX107: =+AX106+AX102 -> 2148.548 | AY107: =+AY106+AY102 -> 2404.647 | AZ107: =+AZ106+AZ102 -> 2267.477 | BA107: =+BA106+BA102 -> 2021.651 | BB107: =+BB106+BB102 -> 2633.565 | BC107: =+BC106+BC102 -> 2094.462 | BD107: =+BD106+BD102 -> 3772.916 | ... CD107: =+CD106+CD102 -> 8194.5302
A109: Pay Out | B109: =B$2 -> 42459 | C109: =C$2 -> 42551 | D109: =D$2 -> 42643 | E109: =E$2 -> 42735 | F109: =F$2 -> 42825 | G109: =G$2 -> 42916 | H109: =H$2 -> 43008 | I109: =I$2 -> 43100 | ... AS109: =AS$2 -> 46387 | AU109: 46022 | AW109: =AW$2 -> 35795 | AX109: =AX$2 -> 36160 | AY109: =AY$2 -> 36525 | AZ109: =AZ$2 -> 36891 | BA109: =BA$2 -> 37256 | BB109: =BB$2 -> 37621 | BC109: =BC$2 -> 37986 | BD109: =BD$2 -> 38352 | ... CD109: =CD$2 -> 47848
A110: Share Buybacks/Capital Incr | B110: 0 | C110: 0 | D110: 0 | E110: -714.756 | F110: -714.756 | G110: 0 | H110: 0 | J110: 0 | K110: 0 | L110: 0 | M110: 0 | N110: 0 | O110: 0 | P110: 0 | Q110: 0 | R110: 0 | S110: 0 | T110: 0 | U110: 0 | V110: 0 | W110: 0 | X110: 0 | Z110: 0 | AA110: 0 | AB110: 0 | AC110: 0 | AD110: 0 | AE110: 0 | AF110: 0 | AG110: 0 | AH110: 0 | AI110: 0 | AJ110: =-605.151-AI110-AH110-AG110 -> -605.151 | AK110: =-975.408-AJ110-AI110-AH110 -> -370.257 | AL110: -173.628 | AM110: =-564.859-AL110 -> -391.231 | AN110: =-1113.928-AM110-AL110 -> -549.069 | AO110: =-1444.138-AN110-AM110-AL110 -> -330.21 | AP110: -500 | AQ110: -500 | AR110: -500 | AS110: -500 | AU110: -500 | AW110: -211.359 | AX110: -661.744 | AY110: -680.783 | AZ110: -1113.279 | BA110: -665.552 | BB110: -725.53 | BC110: -433.359 | BD110: -567.132 | BE110: -469.151 | BF110: -714.756 | BG110: -1009.688 | BH110: 0 | BI110: 0 | BJ110: 0 | BK110: 0 | BL110: 0 | BM110: 0 | BN110: 0 | BO110: -2289.696 | BP110: -714.756 | BT110: =-0.4*4*BT28 -> -0.21328247 | BU110: =-0.4*4*BU28 -> -0.15332867 | BV110: =-0.4*4*BV28 -> -0.15463361 | BW110: =-0.4*4*BW28 -> -0.21048907 | BX110: =+SUMIFS($B110:$AO110,$B$1:$AO$1,"="&BX$1) -> -975.408 | BY110: =+SUMIFS($B110:$AS110,$B$1:$AS$1,"="&BY$1) -> -1444.138 | BZ110: =+SUMIFS($B110:$AS110,$B$1:$AS$1,"="&BZ$1) -> -2000
A111: Total Shs bought | B111: =+B30-A30 -> #VALUE! | C111: =+C30-B30 -> -3.2290769 | D111: =+D30-C30 -> -0.39 | E111: =+E30-D30 -> -0.08 | F111: =+F30-E30 -> -3.042 | G111: =+G30-F30 -> 0 | H111: =+H30-G30 -> 0 | I111: =+I30-H30 -> 0 | ... Y111: =+Y30-X30 -> 0 | AJ111: =+AJ30-AI30 -> -18.405487 | AK111: =+AK30-AJ30 -> -13.149701 | AL111: =+AL30-AK30 -> -5.498533 | AM111: =+AM30-AL30 -> -11.694884 | AN111: =+AN30-AM30 -> -15.674559 | AO111: =+AO30-AN30 -> -9.860765 | AP111: =+AP110/AP112 -> -16.129032 | AQ111: =+AQ110/AQ112 -> -16.129032 | AR111: =+AR110/AR112 -> -16.129032 | AS111: =+AS110/AS112 -> -16.129032 | AU111: -16.129032 | AW111: 14.238 | AX111: 45.832 | AY111: 65.636 | AZ111: 110.103 | BA111: 136.421 | BB111: 46.853 | BC111: 42.06 | BD111: 32.13 | BE111: 26.756 | BF111: 4.885 | BG111: 38.849 | BH111: 40.245 | BI111: 36.875 | BJ111: 36.09 | BK111: 70581.9 | BL111: 42068.12 | BM111: 26299.649 | BN111: 42013.65 | BO111: 31329.078 | BP111: 28826.726 | BX111: =+BX30-BW30 -> -31.555188 | BY111: =+BY30-BX30 -> -42.728741 | BZ111: =+BZ30-BY30 -> -64.516129
A112: Avg Price | B112: =-B110*1000/B111 -> #VALUE! | C112: =-C110*1000/C111 -> 0 | D112: =-D110*1000/D111 -> 0 | E112: =-E110*1000/E111 -> -8934450 | F112: =-F110*1000/F111 -> -234962.52 | G112: =-G110*1000/G111 -> #DIV/0! | H112: =-H110*1000/H111 -> #DIV/0! | I112: =-I110*1000/I111 -> #DIV/0! | ... X112: =-X110*1000/X111 -> #DIV/0! | AJ112: =-AJ110/AJ111 -> -32.878837 | AK112: =-AK110/AK111 -> -28.157066 | AL112: =-AL110/AL111 -> -31.57715 | AM112: =-AM110/AM111 -> -33.453175 | AN112: =-AN110/AN111 -> -35.029311 | AO112: =-AO110/AO111 -> -33.48726 | AP112: 31 | AQ112: 31 | AR112: 31 | AS112: 31 | AU112: 31 | AW112: =-AW110*1000/AW111 -> 14844.711 | AX112: =-AX110*1000/AX111 -> 14438.471 | AY112: =-AY110*1000/AY111 -> 10372.098 | AZ112: =-AZ110*1000/AZ111 -> 10111.25 | BA112: =-BA110*1000/BA111 -> 4878.6624 | BB112: =-BB110*1000/BB111 -> 15485.241 | BC112: =-BC110*1000/BC111 -> 10303.352 | BD112: =-BD110*1000/BD111 -> 17651.167 | ... BS112: =-BS110*1000/BS111 -> #DIV/0! | BX112: =-BX110/BX111 -> -30.911177 | BY112: =-BY110/BY111 -> -33.797813 | BZ112: =-BZ110/BZ111 -> -31
A113: Dividends (Paid) | B113: 0 | C113: -1175.452 | D113: 1175.452 | E113: -5742.781 | F113: -5742.781 | G113: 0 | H113: 0 | I113: 0 | J113: 0 | K113: 0 | L113: 0 | M113: 0 | N113: 0 | O113: 0 | P113: 0 | Q113: 0 | R113: 0 | S113: 0 | T113: 0 | U113: 0 | V113: =-0.43*V30 -> -1326.5208 | W113: =-0.43*W30 -> -1326.5208 | X113: =-0.43*X30 -> -1326.5208 | Y113: =-0.43*Y30 -> -1326.5208 | Z113: =-0.41*Z30 -> -1264.8221 | AA113: =-2520.479-Z113 -> -1255.6569 | AB113: 0 | AC113: =-5043.217-AB113-AA113-Z113 -> -2522.738 | AD113: 0 | AE113: =-1244.871-AD113 -> -1244.871 | AF113: =-2489.742-AE113-AD113 -> -1244.871 | AG113: =-4981.715-AF113-AE113-AD113 -> -2491.973 | AH113: 0 | AI113: =-1429.296-AH113 -> -1429.296 | AJ113: =-2858.593-AI113-AH113 -> -1429.297 | AK113: =-5719.747-AJ113-AI113-AH113 -> -2861.154 | AL113: 0 | AM113: =-1551.522-AL113 -> -1551.522 | AN113: =-3103.044-AM113-AL113 -> -1551.522 | AO113: =-6208.898-AN113-AM113-AL113 -> -3105.854 | AP113: =+AL113*(1+AP115) -> 0 | AQ113: =+AM113*(1+AQ115) -> -1691.159 | AR113: =+AN113*(1+AR115) -> -1691.159 | AS113: =+AO113*(1+AS115) -> -3385.3809 | AU113: -3118.6579 | AW113: -1321.138 | AX113: -2284.869 | AY113: -1805.229 | AZ113: -2018.663 | BA113: -2198.824 | BB113: -2333.547 | BC113: -2347.8 | BD113: -2416.967 | BE113: -2605.019 | BF113: -5742.781 | BG113: -3027.916 | BH113: -3048.751 | BI113: -3207.618 | BJ113: -3455.602 | BK113: -3606.275 | BL113: -3784.235 | BM113: -4146.258 | BN113: -4377.6 | BO113: -4583.023 | BP113: -4703.899 | BQ113: -4874.193 | BR113: =-0.395*4*BR30 -> -4874.1926 | BS113: =-0.3875*4*BS30 -> -4781.6446 | BT113: =-0.4*4*BT30 -> -4935.8912 | BU113: =-0.4*4*BU30 -> -4935.8912 | BV113: =-0.4*4*BV30 -> -4920.2122 | BW113: =-0.4*4*BW30 -> -4920.2122 | BX113: =+SUMIFS($B113:$AO113,$B$1:$AO$1,"="&BX$1) -> -5719.747 | BY113: =+SUMIFS($B113:$AS113,$B$1:$AS$1,"="&BY$1) -> -6208.898 | BZ113: =+SUMIFS($B113:$AS113,$B$1:$AS$1,"="&BZ$1) -> -6767.6988 | CA113: =-CA114*BZ27 -> -6488.0163 | CB113: =-CB114*CA27 -> -6498.5336 | CC113: =-CC114*CB27 -> -6522.376 | CD113: =-CD114*CC27 -> -6542.9102
...

Sheet FAT
A1: Economic Forecasts | B1: 42460 | C1: =+EOMONTH(B1,3) -> 42551 | D1: =+EOMONTH(C1,3) -> 42643 | E1: =+EOMONTH(D1,3) -> 42735 | F1: =+EOMONTH(E1,3) -> 42825 | G1: =+EOMONTH(F1,3) -> 42916 | H1: =+EOMONTH(G1,3) -> 43008 | I1: =+EOMONTH(H1,3) -> 43100 | J1: =+EOMONTH(I1,3) -> 43190 | ... AB1: =+EOMONTH(AA1,3) -> 44834 | AC1: 44925 | AD1: =+EOMONTH(AC1,3) -> 45016 | AE1: =+EOMONTH(AD1,3) -> 45107 | AF1: =+EOMONTH(AE1,3) -> 45199 | AG1: =+EOMONTH(AF1,3) -> 45291 | AH1: =+EOMONTH(AG1,3) -> 45382 | AI1: =+EOMONTH(AH1,3) -> 45473 | AJ1: =+EOMONTH(AI1,3) -> 45565 | AK1: =+EOMONTH(AJ1,3) -> 45657 | ... AS1: =+EOMONTH(AR1,3) -> 46387 | AU1: 46022 | AW1: 35795 | AX1: =+EOMONTH(AW1,12) -> 36160 | AY1: =+EOMONTH(AX1,12) -> 36525 | AZ1: =+EOMONTH(AY1,12) -> 36891 | BA1: =+EOMONTH(AZ1,12) -> 37256 | BB1: =+EOMONTH(BA1,12) -> 37621 | BC1: =+EOMONTH(BB1,12) -> 37986 | BD1: =+EOMONTH(BC1,12) -> 38352 | BE1: =+EOMONTH(BD1,12) -> 38717 | ... CD1: =+EOMONTH(CC1,12) -> 47848
A2: MXN - eop | B2: =+macro!AD42 -> 17.2793 | C2: =+macro!AE42 -> 18.4684 | D2: =+macro!AF42 -> 19.3852 | E2: =+macro!AG42 -> 20.7272 | F2: =+macro!AH42 -> 18.7249 | G2: =+macro!AI42 -> 18.1203 | H2: =+macro!AJ42 -> 18.2545 | I2: =+macro!AK42 -> 19.659 | ... AS2: =+macro!BU42 -> 18.141521 | AU2: 18.008 | AW2: 8.055 | AX2: 9.897 | AY2: 9.505 | AZ2: 9.6225 | BA2: 9.1575 | BB2: 10.37 | BC2: 11.22 | BD2: 11.14 | BE2: 10.635 | BF2: 10.8033 | BG2: 10.8988 | BH2: 13.6733 | BI2: 13.0914 | BJ2: 12.34 | BK2: =+macro!CY42 -> 13.9357 | BL2: =+macro!CZ42 -> 12.9251 | BM2: =+macro!DA42 -> 13.0954 | BN2: =+macro!DB42 -> 14.7472 | BO2: =+macro!DC42 -> 17.2075 | BP2: =+macro!DD42 -> 20.7272 | BQ2: =+macro!DE42 -> 19.659 | BR2: =+macro!DF42 -> 19.6504 | ... CD2: =+macro!DR42 -> 19.232441
A3: Average | B3: =+macro!AD9 -> 18.0272 | C3: =+macro!AE9 -> 18.1073 | D3: =+macro!AF9 -> 18.7626 | E3: =+macro!AG9 -> 19.8451 | F3: =+macro!AH9 -> 20.29942 | G3: =+macro!AI9 -> 18.548848 | H3: =+macro!AJ9 -> 17.818892 | I3: =+macro!AK9 -> 18.986402 | ... AS3: =+macro!BU9 -> 18.032352 | AU3: 18.301782 | AX3: =+AVERAGE(AW2:AX2) -> 8.976 | AY3: =+AVERAGE(AX2:AY2) -> 9.701 | AZ3: =+AVERAGE(AY2:AZ2) -> 9.56375 | BA3: =+AVERAGE(AZ2:BA2) -> 9.39 | BB3: =+AVERAGE(BA2:BB2) -> 9.76375 | BC3: =+AVERAGE(BB2:BC2) -> 10.795 | BD3: =+AVERAGE(BC2:BD2) -> 11.18 | BE3: =+AVERAGE(BD2:BE2) -> 10.8875 | ... CD3: =+AVERAGE(CC2:CD2) -> 19.093076
A4: Chg YoY | F4: =F3/B3-1 -> 0.12604398 | G4: =G3/C3-1 -> 0.024385065 | H4: =H3/D3-1 -> -0.050297277 | I4: =I3/E3-1 -> -0.04327005 | J4: =J3/F3-1 -> -0.077888294 | K4: =K3/G3-1 -> 0.04672063 | L4: =L3/H3-1 -> 0.063037675 | M4: =M3/I3-1 -> 0.044815167 | ... AS4: =AS3/AO3-1 -> -0.014721528 | AU4: -0.088756907 | AX4: =AX3/AW3-1 -> #DIV/0! | AY4: =AY3/AX3-1 -> 0.080770945 | AZ4: =AZ3/AY3-1 -> -0.014148026 | BA4: =BA3/AZ3-1 -> -0.01816756 | BB4: =BB3/BA3-1 -> 0.039802982 | BC4: =BC3/BB3-1 -> 0.10562028 | BD4: =BD3/BC3-1 -> 0.03566466 | BE4: =BE3/BD3-1 -> -0.026162791 | ... CD4: =CD3/CC3-1 -> 0.014705882
A5: Chg QoQ | C5: =C3/B3-1 -> 0.0044432857 | D5: =D3/C3-1 -> 0.036189824 | E5: =E3/D3-1 -> 0.057694563 | F5: =F3/E3-1 -> 0.022893309 | G5: =G3/F3-1 -> -0.086237553 | H5: =H3/G3-1 -> -0.039353139 | I5: =I3/H3-1 -> 0.065520865 | J5: =J3/I3-1 -> -0.014118985 | ... AS5: =AS3/AR3-1 -> 0.0053818641 | AU5: -0.017528951
A6: Inflation YoY | B6: =+macro!AD83 -> 0.026010291 | C6: =+macro!AE83 -> 0.02537965 | D6: =+macro!AF83 -> 0.029689216 | E6: =+macro!AG83 -> 0.033602555 | F6: =+macro!AH83 -> 0.053525748 | G6: =+macro!AI83 -> 0.063136447 | H6: =+macro!AJ83 -> 0.063478818 | I6: =+macro!AK83 -> 0.067731071 | ... AS6: =+macro!BU83 -> 0.035 | AU6: 0.036919441 | BE6: 0.04 | BF6: 0.0363 | BG6: 0.0397 | BH6: 0.0512 | BI6: 0.0531 | BJ6: 0.0416 | BK6: 0.0341 | BL6: =+macro!CZ83 -> 0.035682149 | BM6: =+macro!DA83 -> 0.039741486 | BN6: =+macro!DB83 -> 0.040812891 | BO6: =+macro!DC83 -> 0.021307734 | BP6: =+macro!DD83 -> 0.033602555 | BQ6: =+macro!DE83 -> 0.067731071 | BR6: =+macro!DF83 -> 0.04830528 | BS6: =+macro!DG83 -> 0.02828577 | ... CD6: =+macro!DR83 -> 0.035
A7: US Inflation | B7: =+macro!AD76 -> 0.008916161 | C7: =+macro!AE76 -> 0.010792865 | D7: =+macro!AF76 -> 0.015486446 | E7: =+macro!AG76 -> 0.020507989 | F7: =+macro!AH76 -> 0.024411962 | G7: =+macro!AI76 -> 0.016405658 | H7: =+macro!AJ76 -> 0.021805652 | I7: =+macro!AK76 -> 0.021299307 | ... AS7: =+macro!BU76 -> 0.0268 | AU7: 0.023387688 | BH7: -0.0145 | BI7: 0.0009 | BJ7: 0.0163 | BK7: 0.0317 | BL7: =+macro!CZ76 -> 0.01759505 | BM7: =+macro!DA76 -> 0.015128384 | BN7: =+macro!DB76 -> 0.0065312139 | BO7: =+macro!DC76 -> 0.0063872475 | BP7: =+macro!DD76 -> 0.020507989 | BQ7: =+macro!DE76 -> 0.021299307 | BR7: =+macro!DF76 -> 0.020023809 | BS7: =+macro!DG76 -> 0.023195275 | ... CD7: =+macro!DR76 -> 0.02
A8: Assumptions | B8: =+B1 -> 42460 | C8: =+C1 -> 42551 | D8: =+D1 -> 42643 | E8: =+E1 -> 42735 | F8: =+F1 -> 42825 | G8: =+G1 -> 42916 | H8: =+H1 -> 43008 | I8: =+I1 -> 43100 | ... AS8: =+AS1 -> 46387 | AU8: 46022 | AW8: =+AW$1 -> 35795 | AX8: =+AX$1 -> 36160 | AY8: =+AY$1 -> 36525 | AZ8: =+AZ$1 -> 36891 | BA8: =+BA$1 -> 37256 | BB8: =+BB$1 -> 37621 | BC8: =+BC$1 -> 37986 | BD8: =+BD$1 -> 38352 | ... CD8: =+CD$1 -> 47848
B9: 3 | C9: =+B9+3 -> 6 | D9: =+C9+3 -> 9 | E9: =+D9+3 -> 12 | F9: =+E9+3 -> 15 | G9: =+F9+3 -> 18 | H9: =+G9+3 -> 21 | I9: =+H9+3 -> 24 | J9: =+I9+3 -> 27 | ... AS9: =+AR9+3 -> 132 | AU9: 120
BZ10: =+BZ11/BV11-1 -> 0.11029621
A11: Revenues (MXN) | B11: =+PROJ!B3 -> 8728.317 | C11: =+PROJ!C3 -> 8831.353 | D11: =+PROJ!D3 -> 8719.457 | E11: =+PROJ!E3 -> 9381.168 | F11: =+PROJ!F3 -> 9530.508 | G11: =+PROJ!G3 -> 9605.905 | H11: =+PROJ!H3 -> 9197.259 | I11: =+PROJ!I3 -> 9432.088 | ... AO11: =+PROJ!AO3 -> 14057.927 | AP11: =+AL11*(1+AP12) -> 14109.66 | AQ11: =+AM11*(1+AQ12) -> 14421.75 | AR11: =+AN11*(1+AR12) -> 13745.25 | AS11: =+AO11*(1+AS12) -> 14409.375 | AU11: 13977.062 | AW11: =+PROJ!AW3 -> 10305.475 | AX11: =+PROJ!AX3 -> 12289.726 | AY11: =+PROJ!AY3 -> 13868.222 | AZ11: =+PROJ!AZ3 -> 15906.374 | BA11: =+PROJ!BA3 -> 15633.955 | BB11: =+PROJ!BB3 -> 16096.04 | BC11: =+PROJ!BC3 -> 17100.169 | BD11: =+PROJ!BD3 -> 19798.909 | ... BU11: =+PROJ!BU3 -> 46893.963 | BV11: =+SUMIFS($A11:$AO11,$A$1:$AO$1,"<="&BV$1,$A$1:$AO$1,">"&BU$1) -> 51054.876 | BW11: =+SUMIFS($A11:$AO11,$A$1:$AO$1,"<="&BW$1,$A$1:$AO$1,">"&BV$1) -> 53307.054 | BX11: =+SUMIFS($A11:$AO11,$A$1:$AO$1,"<="&BX$1,$A$1:$AO$1,">"&BW$1) -> 54782.717 | BY11: =+SUMIFS($A11:$AS11,$A$1:$AS$1,"<="&BY$1,$A$1:$AS$1,">"&BX$1) -> 55370.927 | BZ11: =+SUMIFS($A11:$AS11,$A$1:$AS$1,"<="&BZ$1,$A$1:$AS$1,">"&BY$1) -> 56686.035 | CA11: =+BZ11*(1+CA12) -> 57819.756 | CB11: =+CA11*(1+CB12) -> 58976.151 | CC11: =+CB11*(1+CC12) -> 60155.674 | CD11: =+CC11*(1+CD12) -> 61358.787
A12: Chg YoY | F12: =F11/B11-1 -> 0.091906722 | G12: =G11/C11-1 -> 0.087704794 | H12: =H11/D11-1 -> 0.05479722 | I12: =I11/E11-1 -> 0.0054278955 | J12: =J11/F11-1 -> 0.071009646 | K12: =K11/G11-1 -> 0.10230093 | L12: =L11/H11-1 -> 0.076081472 | M12: =M11/I11-1 -> 0.095621669 | ... AO12: =AO11/AK11-1 -> 0.020872366 | AP12: =+AP19 -> 0.02 | AQ12: =+AQ19 -> 0.025 | AR12: =+AR19 -> 0.025 | AS12: =+AS19 -> 0.025 | AU12: 0.015 | AX12: =AX11/AW11-1 -> 0.19254338 | AY12: =AY11/AX11-1 -> 0.12844029 | AZ12: =AZ11/AY11-1 -> 0.14696563 | BA12: =BA11/AZ11-1 -> -0.017126405 | BB12: =BB11/BA11-1 -> 0.029556501 | BC12: =BC11/BB11-1 -> 0.062383605 | BD12: =BD11/BC11-1 -> 0.15781949 | BE12: =BE11/BD11-1 -> 0.11031946 | ... BZ12: =BZ11/BY11-1 -> 0.023750879 | CA12: =+CA19 -> 0.02 | CB12: =+CB19 -> 0.02 | CC12: =+CC19 -> 0.02 | CD12: =+CD19 -> 0.02
A13: Chg QoQ | C13: =C11/B11-1 -> 0.011804796 | D13: =D11/C11-1 -> -0.012670312 | E13: =E11/D11-1 -> 0.075889015 | F13: =F11/E11-1 -> 0.015919126 | G13: =G11/F11-1 -> 0.0079111208 | H13: =H11/G11-1 -> -0.042541124 | I13: =I11/H11-1 -> 0.025532498 | J13: =J11/I11-1 -> 0.082185196 | ... AS13: =AS11/AR11-1 -> 0.048316704 | AU13: 0.04228647
A14: Real Growth | B14: =+B11/SUM($B11:$E11) -> 0.24476289 | C14: =+C11/SUM($B11:$E11) -> 0.24765227 | D14: =+D11/SUM($B11:$E11) -> 0.24451444 | E14: =+E11/SUM($B11:$E11) -> 0.2630704 | F14: =+F11/SUM($F11:$I11) -> 0.25235843 | G14: =+G11/SUM($F11:$I11) -> 0.25435487 | H14: =+H11/SUM($F11:$I11) -> 0.24353433 | I14: =+I11/SUM($F11:$I11) -> 0.24975237 | J14: =+J11/SUM($J11:$M11) -> 0.24879469 | K14: =+K11/SUM($J11:$M11) -> 0.25808938 | L14: =+L11/SUM($J11:$M11) -> 0.24123218 | M14: =+M11/SUM($J11:$M11) -> 0.25188374 | N14: =+N11/SUM($N11:$Q11) -> 0.25319 | O14: =+O11/SUM($N11:$Q11) -> 0.2594411 | P14: =+P11/SUM($N11:$Q11) -> 0.23907535 | Q14: =+Q11/SUM($N11:$Q11) -> 0.24829355 | R14: =+R11/SUM($R11:$U11) -> 0.2503536 | S14: =+S11/SUM($R11:$U11) -> 0.26416476 | T14: =+T11/SUM($R11:$U11) -> 0.23761094 | U14: =+U11/SUM($R11:$U11) -> 0.24787069 | V14: =+V11/SUM($V11:$Y11) -> 0.25822042 | W14: =+W11/SUM($V11:$Y11) -> 0.24997286 | X14: =+X11/SUM($V11:$Y11) -> 0.2418966 | Y14: =+Y11/SUM($V11:$Y11) -> 0.24991012 | Z14: =+Z11/SUM($V11:$Y11) -> 0.26813686 | AA14: =+AA11/SUM($V11:$Y11) -> 0.2749787 | AB14: =+AB11/SUM($V11:$Y11) -> 0.2728283 | AC14: =+AC11/SUM($V11:$Y11) -> 0.27278639 | ... AS14: =+AS11/SUM($V11:$Y11) -> 0.3072757 | AU14: 0.29805674 | BE14: =+BE12-BE6 -> 0.070319463 | BF14: =+BF12-BF6 -> -0.1226682 | BG14: =+BG12-BG6 -> 0.029794533 | BH14: =+BH12-BH6 -> 0.021950463 | BI14: =+BI12-BI6 -> 0.018508504 | BJ14: =+BJ12-BJ6 -> 0.018893056 | BK14: =+BK12-BK6 -> -0.013644458 | BL14: =+BL12-BL6 -> 0.059941313 | ... CD14: =+CD12-CD6 -> -0.015
K16: ` | O16: ` | P16: ` | Q16: ` | R16: ` | S16: ` | T16: ` | U16: ` | V16: ` | W16: ` | X16: ` | Y16: ` | Z16: ` | AA16: ` | AB16: ` | AC16: ` | AD16: ` | AE16: ` | AF16: ` | AG16: ` | AH16: `
A17: Price YOY | F17: 0.069 | G17: 0.07 | H17: 0.039 | I17: 0.031 | J17: 0.052 | K17: 0.068 | L17: 0.087 | M17: 0.09 | N17: 0.08 | O17: 0.08 | P17: 0.06 | Q17: 0 | R17: -0.01 | S17: 0.05 | T17: 0 | U17: 0.04 | V17: 0.06 | W17: 0.01 | X17: 0.02 | Y17: 0.05 | Z17: 0.07 | AA17: 0.13 | AB17: 0.185 | AC17: 0.16 | AD17: 0.11 | AE17: 0.071 | AF17: 0.01 | AG17: 0.063 | AH17: 0.012 | AI17: 0.019 | AJ17: 0.02 | AK17: =+AK12-AK18 -> 0.024845814 | AL17: =+AL12-AL18 -> 0.016148973 | AM17: =+AM12-AM18 -> 0.033142167 | AN17: =+AN12-AN18 -> 0.0074124718 | AO17: =+AO12-AO18 -> 0.010872366 | AP17: 0.015 | AQ17: 0.015 | AR17: 0.015 | AS17: 0.015 | AU17: 0.015 | BQ17: =AVERAGEIFS($B17:$AK17, $B$8:$AK$8, ">=" & BP$8, $B$8:$AK$8, "<=" & BQ$8) -> 0.05225 | BR17: =AVERAGEIFS($B17:$AK17, $B$8:$AK$8, ">=" & BQ$8, $B$8:$AK$8, "<=" & BR$8) -> 0.0656 | BS17: =AVERAGEIFS($B17:$AK17, $B$8:$AK$8, ">=" & BR$8, $B$8:$AK$8, "<=" & BS$8) -> 0.062 | BT17: =AVERAGEIFS($B17:$AK17, $B$8:$AK$8, ">=" & BS$8, $B$8:$AK$8, "<=" & BT$8) -> 0.016 | BU17: =AVERAGEIFS($B17:$AK17, $B$8:$AK$8, ">=" & BT$8, $B$8:$AK$8, "<=" & BU$8) -> 0.036 | BV17: =AVERAGEIFS($B17:$AK17, $B$8:$AK$8, ">=" & BU$8, $B$8:$AK$8, "<=" & BV$8) -> 0.119 | BW17: =AVERAGEIFS($B17:$AK17, $B$8:$AK$8, ">=" & BV$8, $B$8:$AK$8, "<=" & BW$8) -> 0.0635 | BX17: =AVERAGEIFS($B17:$AK17, $B$8:$AK$8, ">=" & BW$8, $B$8:$AK$8, "<=" & BX$8) -> 0.027769163 | BY17: =AVERAGEIFS($B17:$AS17, $B$8:$AS$8, ">=" & BX$8, $B$8:$AS$8, "<=" & BY$8) -> 0.018484358 | BZ17: =AVERAGEIFS($B17:$AS17, $B$8:$AS$8, ">=" & BY$8, $B$8:$AS$8, "<=" & BZ$8) -> 0.014174473 | CA17: 0.015 | CB17: 0.015 | CC17: 0.015 | CD17: 0.015
A18: Volumes YOY | F18: 0.023 | G18: 0.018 | H18: 0.016 | I18: -0.026 | J18: 0.019 | K18: 0.034 | L18: -0.011 | M18: 0.01 | N18: -0.001 | O18: -0.01 | P18: -0.01 | Q18: 0.05 | R18: 0.07 | S18: 0.05 | T18: 0.07 | U18: 0.03 | V18: -0.02 | W18: -0.06 | X18: 0 | Y18: -0.04 | Z18: -0.03 | AA18: -0.03 | AB18: -0.06 | AC18: -0.07 | AD18: -0.04 | AE18: -0.007 | AF18: -0.01 | AG18: -0.018 | AH18: 0.006 | AI18: =+AH18 -> 0.006 | AJ18: 0.018 | AK18: 0.005 | AL18: -0.013 | AM18: -0.033 | AN18: 0.012 | AO18: 0.01 | AP18: 0.005 | AQ18: 0.01 | AR18: 0.01 | AS18: 0.01 | AU18: 0 | BQ18: =AVERAGEIFS($B18:$AK18, $B$8:$AK$8, ">=" & BP$8, $B$8:$AK$8, "<=" & BQ$8) -> 0.00775 | BR18: =AVERAGEIFS($B18:$AK18, $B$8:$AK$8, ">=" & BQ$8, $B$8:$AK$8, "<=" & BR$8) -> 0.0052 | BS18: =AVERAGEIFS($B18:$AK18, $B$8:$AK$8, ">=" & BR$8, $B$8:$AK$8, "<=" & BS$8) -> 0.0078 | BT18: =AVERAGEIFS($B18:$AK18, $B$8:$AK$8, ">=" & BS$8, $B$8:$AK$8, "<=" & BT$8) -> 0.054 | BU18: =AVERAGEIFS($B18:$AK18, $B$8:$AK$8, ">=" & BT$8, $B$8:$AK$8, "<=" & BU$8) -> -0.018 | BV18: =AVERAGEIFS($B18:$AK18, $B$8:$AK$8, ">=" & BU$8, $B$8:$AK$8, "<=" & BV$8) -> -0.046 | BW18: =AVERAGEIFS($B18:$AK18, $B$8:$AK$8, ">=" & BV$8, $B$8:$AK$8, "<=" & BW$8) -> -0.01875 | BX18: =AVERAGEIFS($B18:$AK18, $B$8:$AK$8, ">=" & BW$8, $B$8:$AK$8, "<=" & BX$8) -> 0.0034 | BY18: =AVERAGEIFS($B18:$AS18, $B$8:$AS$8, ">=" & BX$8, $B$8:$AS$8, "<=" & BY$8) -> -0.0038 | BZ18: =AVERAGEIFS($B18:$AS18, $B$8:$AS$8, ">=" & BY$8, $B$8:$AS$8, "<=" & BZ$8) -> 0.009 | CA18: 0.005 | CB18: 0.005 | CC18: 0.005 | CD18: 0.005
A19: Net effect | F19: =+F17+F18 -> 0.092 | G19: =+G17+G18 -> 0.088 | H19: =+H17+H18 -> 0.055 | I19: =+I17+I18 -> 0.005 | J19: =+J17+J18 -> 0.071 | K19: =+K17+K18 -> 0.102 | L19: =+L17+L18 -> 0.076 | M19: =+M17+M18 -> 0.1 | ... AS19: =+AS17+AS18 -> 0.025 | AU19: 0.015 | BQ19: =+BQ17+BQ18 -> 0.06 | BR19: =+BR17+BR18 -> 0.0708 | BS19: =+BS17+BS18 -> 0.0698 | BT19: =+BT17+BT18 -> 0.07 | BU19: =+BU17+BU18 -> 0.018 | BV19: =+BV17+BV18 -> 0.073 | BW19: =+BW17+BW18 -> 0.04475 | BX19: =+BX17+BX18 -> 0.031169163 | ... CD19: =+CD17+CD18 -> 0.02
A22: =+PROJ!A5 -> COGS | B22: =+PROJ!B5 -> -5291.904 | C22: =+PROJ!C5 -> -5378.376 | D22: =+PROJ!D5 -> -5374.796 | E22: =+PROJ!E5 -> -5830.286 | F22: =+PROJ!F5 -> -6145.84 | G22: =+PROJ!G5 -> -6206.55 | H22: =+PROJ!H5 -> -5992.561 | ... AO22: =+PROJ!AO5 -> -8377.888 | AP22: =+AP27+AP81 -> -8530.187 | AQ22: =+AQ27+AQ81 -> -8642.0689 | AR22: =+AR27+AR81 -> -8355.6465 | AS22: =+AS27+AS81 -> -8469.8834 | AU22: -8420.8539 | AW22: =+PROJ!AW5 -> -6257.084 | AX22: =+PROJ!AX5 -> -7212.551 | AY22: =+PROJ!AY5 -> -7828.87 | AZ22: =+PROJ!AZ5 -> -9061.387 | BA22: =+PROJ!BA5 -> -8797.095 | BB22: =+PROJ!BB5 -> -9296.092 | BC22: =+PROJ!BC5 -> -10269.192 | BD22: =+PROJ!BD5 -> -12307.609 | ... BU22: =+PROJ!BU5 -> -31108.287 | BV22: =+SUMIFS($A22:$AO22,$A$1:$AO$1,"<="&BV$1,$A$1:$AO$1,">"&BU$1) -> -34282.394 | BW22: =+SUMIFS($A22:$AO22,$A$1:$AO$1,"<="&BW$1,$A$1:$AO$1,">"&BV$1) -> -32607.015 | BX22: =+SUMIFS($A22:$AO22,$A$1:$AO$1,"<="&BX$1,$A$1:$AO$1,">"&BW$1) -> -32398.989 | BY22: =+SUMIFS($A22:$AS22,$A$1:$AS$1,"<="&BY$1,$A$1:$AS$1,">"&BX$1) -> -33840.269 | BZ22: =+SUMIFS($A22:$AS22,$A$1:$AS$1,"<="&BZ$1,$A$1:$AS$1,">"&BY$1) -> -33997.786 | CA22: =+CA27+CA81 -> -34820.992 | CB22: =+CB27+CB81 -> -35604.055 | CC22: =+CC27+CC81 -> -36409.595 | CD22: =+CD27+CD81 -> -37237.726
A23: % Revs | B23: =-B22/B$11 -> 0.60629145 | C23: =-C22/C$11 -> 0.60900929 | D23: =-D22/D$11 -> 0.61641407 | E23: =-E22/E$11 -> 0.62148828 | F23: =-F22/F$11 -> 0.64485964 | G23: =-G22/G$11 -> 0.6461182 | H23: =-H22/H$11 -> 0.65155945 | I23: =-I22/I$11 -> 0.63812148 | ... AS23: =-AS22/AS$11 -> 0.58780365 | AU23: 0.6024767 | AW23: =-AW22/AW11 -> 0.60716114 | AX23: =-AX22/AX11 -> 0.58687647 | AY23: =-AY22/AY11 -> 0.56451865 | AZ23: =-AZ22/AZ11 -> 0.56967018 | BA23: =-BA22/BA11 -> 0.56269159 | BB23: =-BB22/BB11 -> 0.57753907 | BC23: =-BC22/BC11 -> 0.60053161 | BD23: =-BD22/BD11 -> 0.62163067 | ... BZ23: =-BZ22/BZ11 -> 0.59975593 | CA23: =-CA22/CA$11 -> 0.60223347 | CB23: =-CB22/CB$11 -> 0.60370258 | CC23: =-CC22/CC$11 -> 0.60525621 | CD23: =-CD22/CD$11 -> 0.60688496
A24: Chg YoY | F24: =F22/B22-1 -> 0.16136649 | G24: =G22/C22-1 -> 0.15398217 | H24: =H22/D22-1 -> 0.11493739 | I24: =I22/E22-1 -> 0.032336664 | J24: =J22/F22-1 -> 0.054582449 | K24: =K22/G22-1 -> 0.091430022 | L24: =L22/H22-1 -> 0.091247632 | M24: =M22/I22-1 -> 0.14501219 | ... AS24: =AS22/AO22-1 -> 0.010980733 | AU24: 0.0046961705 | AX24: =AX22/AW22-1 -> 0.15270164 | AY24: =AY22/AX22-1 -> 0.085450904 | AZ24: =AZ22/AY22-1 -> 0.1574323 | BA24: =BA22/AZ22-1 -> -0.029166837 | BB24: =BB22/BA22-1 -> 0.05672293 | BC24: =BC22/BB22-1 -> 0.1046784 | BD24: =BD22/BC22-1 -> 0.19849828 | BE24: =BE22/BD22-1 -> 0.11139532 | ... CD24: =CD22/CC22-1 -> 0.022744834
A25: Chg QoQ | C25: =C22/B22-1 -> 0.016340432 | D25: =D22/C22-1 -> -0.00066562844 | E25: =E22/D22-1 -> 0.084745542 | F25: =F22/E22-1 -> 0.054123245 | G25: =G22/F22-1 -> 0.0098782266 | H25: =H22/G22-1 -> -0.034477931 | I25: =I22/H22-1 -> 0.0043815991 | J25: =J22/I22-1 -> 0.076838509 | ... AS25: =AS22/AR22-1 -> 0.013671812 | AU25: 0.024645945
A27: COGS ex Dep | B27: =+B22-B81 -> -4883.683 | C27: =+C22-C81 -> -4965.86 | D27: =+D22-D81 -> -4962.533 | E27: =+E22-E81 -> -5462.367 | F27: =+F22-F81 -> -5709.697 | G27: =+G22-G81 -> -5791.438 | H27: =+H22-H81 -> -5624.625 | I27: =+I22-I81 -> -5638.185 | ... AO27: =+AO22-AO81 -> -7879.968 | AP27: =+AP32*(1+AP34) -> -8032.1304 | AQ27: =+AQ32*(1+AQ34) -> -8117.32 | AR27: =+AR32*(1+AR34) -> -7859.8612 | AS27: =+AS32*(1+AS34) -> -7978.2091 | AU27: -7851.3858 | AW27: =+AW22-AW81 -> -5644.942 | AX27: =+AX22-AX81 -> -6503.034 | AY27: =+AY22-AY81 -> -7017.128 | AZ27: =+AZ22-AZ81 -> -8225.393 | BA27: =+BA22-BA81 -> -7866.064 | BB27: =+BB22-BB81 -> -8212.379 | BC27: =+BC22-BC81 -> -9097.826 | BD27: =+BD22-BD81 -> -11066.6 | ... BZ27: =+BZ22-BZ81 -> -31987.521 | CA27: =+CA32*(1+CA34) -> -32825.706 | CB27: =+CB32*(1+CB34) -> -33605.783 | CC27: =+CC32*(1+CC34) -> -34404.398 | CD27: =+CD32*(1+CD34) -> -35221.991
A28: % Revs | B28: =-B27/B$11 -> 0.55952173 | C28: =-C27/C$11 -> 0.56229889 | D28: =-D27/D$11 -> 0.56913326 | E28: =-E27/E$11 -> 0.58226939 | F28: =-F27/F$11 -> 0.59909682 | G28: =-G27/G$11 -> 0.60290394 | H28: =-H27/H$11 -> 0.61155449 | I28: =-I27/I$11 -> 0.59776637 | ... AS28: =-AS27/AS$11 -> 0.55368182 | AU28: 0.56173365 | AW28: =-AW27/AW$11 -> 0.54776146 | AX28: =-AX27/AX$11 -> 0.52914394 | AY28: =-AY27/AY$11 -> 0.50598613 | AZ28: =-AZ27/AZ$11 -> 0.51711301 | BA28: =-BA27/BA$11 -> 0.50313974 | BB28: =-BB27/BB$11 -> 0.51021115 | BC28: =-BC27/BC$11 -> 0.53203135 | BD28: =-BD27/BD$11 -> 0.55894999 | ... CD28: =-CD27/CD$11 -> 0.57403337
A29: Chg YoY | F29: =F27/B27-1 -> 0.16913751 | G29: =G27/C27-1 -> 0.16625076 | H29: =H27/D27-1 -> 0.13341816 | I29: =I27/E27-1 -> 0.032187145 | J29: =J27/F27-1 -> 0.062279662 | K29: =K27/G27-1 -> 0.1000748 | L29: =L27/H27-1 -> 0.098449763 | M29: =M27/I27-1 -> 0.15449954 | ... AS29: =AS27/AO27-1 -> 0.01246719 | AU29: 0.0036172118 | AW29: =AW27/AV27-1 -> #DIV/0! | AX29: =AX27/AW27-1 -> 0.15201077 | AY29: =AY27/AX27-1 -> 0.079054484 | AZ29: =AZ27/AY27-1 -> 0.17218797 | BA29: =BA27/AZ27-1 -> -0.043685329 | BB29: =BB27/BA27-1 -> 0.044026466 | BC29: =BC27/BB27-1 -> 0.10781857 | BD29: =BD27/BC27-1 -> 0.21640049 | ... CD29: =CD27/CC27-1 -> 0.023764212
A30: Chg QoQ | C30: =C27/B27-1 -> 0.01682685 | D30: =D27/C27-1 -> -0.00066997459 | E30: =E27/D27-1 -> 0.10072155 | F30: =F27/E27-1 -> 0.045278906 | G30: =G27/F27-1 -> 0.014316171 | H30: =H27/G27-1 -> -0.028803382 | I30: =I27/H27-1 -> 0.0024108274 | J30: =J27/I27-1 -> 0.075753101 | ... AS30: =AS27/AR27-1 -> 0.015057246 | AU30: 0.017493097
A32: COGS EST | V32: =+R27*(1+V36) -> -6627.5367 | W32: =+S27*(1+W36) -> -7055.4092 | X32: =+T27*(1+X36) -> -7057.9914 | Y32: =+U27*(1+Y36) -> -7835.0164 | Z32: =+V27*(1+Z36) -> -8199.3691 | AA32: =+W27*(1+AA36) -> -8234.3432 | AB32: =+X27*(1+AB36) -> -7780.2945 | AC32: =+Y27*(1+AC36) -> -8095.8973 | ... AS32: =+AO27*(1+AS36) -> -7942.3366 | AU32: -7883.2097 | BU32: =+SUM(V32:Y32) -> -28575.954 | BV32: =+SUMIFS($A32:$AO32,$A$1:$AO$1,"<="&BV$1,$A$1:$AO$1,">"&BU$1) -> -32309.904 | BW32: =+SUMIFS($A32:$AO32,$A$1:$AO$1,"<="&BW$1,$A$1:$AO$1,">"&BV$1) -> -31712.114 | BX32: =+SUMIFS($A32:$AO32,$A$1:$AO$1,"<="&BX$1,$A$1:$AO$1,">"&BW$1) -> -31248.392 | BY32: =+SUMIFS($A32:$AS32,$A$1:$AS$1,"<="&BY$1,$A$1:$AS$1,">"&BX$1) -> -31618.404 | BZ32: =+SUMIFS($A32:$AS32,$A$1:$AS$1,"<="&BZ$1,$A$1:$AS$1,">"&BY$1) -> -31843.695 | CA32: =+BZ27*(1+CA36) -> -32678.112 | CB32: =+CA27*(1+CB36) -> -33454.681 | CC32: =+CB27*(1+CC36) -> -34249.705 | CD32: =+CC27*(1+CD36) -> -35063.623
A33: % Revs | V33: =-V32/V$11 -> 0.54732415 | W33: =-W32/W$11 -> 0.60188347 | X33: =-X32/X$11 -> 0.62220634 | Y33: =-Y32/Y$11 -> 0.66855806 | Z33: =-Z32/Z$11 -> 0.65208916 | AA33: =-AA32/AA$11 -> 0.63857656 | AB33: =-AB32/AB$11 -> 0.60812057 | AC33: =-AC32/AC$11 -> 0.6328858 | ... AS33: =-AS32/AS$11 -> 0.5511923 | AU33: 0.56401051 | BU33: =-BU32/BU$11 -> 0.60937383 | BV33: =-BV32/BV$11 -> 0.63284659 | BW33: =-BW32/BW$11 -> 0.59489527 | BX33: =-BX32/BX$11 -> 0.57040604 | BY33: =-BY32/BY$11 -> 0.57102898 | BZ33: =-BZ32/BZ$11 -> 0.56175555 | CA33: =-CA32/CA$11 -> 0.56517208 | CB33: =-CB32/CB$11 -> 0.56725779 | ... CD33: =-CD32/CD$11 -> 0.57145234
A34: error | V34: =+V27/V32-1 -> 0.047898687 | W34: =+W27/W32-1 -> 0.01943655 | X34: =+X27/X32-1 -> 0.026884364 | Y34: =+Y27/Y32-1 -> -0.0060345049 | Z34: =+Z27/Z32-1 -> -0.0087698389 | AA34: =+AA27/AA32-1 -> -0.0017316704 | AB34: =+AB27/AB32-1 -> 0.034230515 | AC34: =+AC27/AC32-1 -> -0.021787981 | ... AO34: =+AO27/AO32-1 -> 0.0045166097 | AP34: =+AO34 -> 0.0045166097 | AQ34: =+AP34 -> 0.0045166097 | AR34: =+AQ34 -> 0.0045166097 | AS34: =+AR34 -> 0.0045166097 | AU34: -0.0040369211 | BU34: =+BU27/BU32-1 -> 0.020893521 | BV34: =+BV27/BV32-1 -> 0.00011649409 | BW34: =+BW27/BW32-1 -> -0.034359719 | BX34: =+BX27/BX32-1 -> -0.028707923 | BY34: =+BY27/BY32-1 -> 0.0064920462 | BZ34: =+BZ27/BZ32-1 -> 0.0045166097 | CA34: =+BZ34 -> 0.0045166097 | CB34: =+CA34 -> 0.0045166097 | CC34: =+CB34 -> 0.0045166097 | CD34: =+CC34 -> 0.0045166097
A36: ESTIMATED COGS Growth yoy | V36: =+V37*V45+V38*V46+V39*V48+V40*V49+V41*V50 -> 0.011103802 | W36: =+W37*W45+W38*W46+W39*W48+W40*W49+W41*W50 -> -0.0070771118 | X36: =+X37*X45+X38*X46+X39*X48+X40*X49+X41*X50 -> 0.10129275 | Y36: =+Y37*Y45+Y38*Y46+Y39*Y48+Y40*Y49+Y41*Y50 -> 0.17448711 | Z36: =+Z37*Z45+Z38*Z46+Z39*Z48+Z40*Z49+Z41*Z50 -> 0.18061692 | AA36: =+AA37*AA45+AA38*AA46+AA39*AA48+AA40*AA49+AA41*AA50 -> 0.14484464 | AB36: =+AB37*AB45+AB38*AB46+AB39*AB48+AB40*AB49+AB41*AB50 -> 0.073478552 | AC36: =+AC37*AC45+AC38*AC46+AC39*AC48+AC40*AC49+AC41*AC50 -> 0.03957007 | ... AS36: =+AS37*AS45+AS38*AS46+AS39*AS48+AS40*AS49+AS41*AS50 -> 0.0079148325 | AU36: 0.0076851573 | BU36: =+BU37*BU45+BU38*BU46+BU39*BU48+BU40*BU49+BU41*BU50 -> 0.15045748 | BV36: =+BV37*BV45+BV38*BV46+BV39*BV48+BV40*BV49+BV41*BV50 -> 0.076459267 | BW36: =+BW37*BW45+BW38*BW46+BW39*BW48+BW40*BW49+BW41*BW50 -> -0.04816806 | BX36: =+BX37*BX45+BX38*BX46+BX39*BX48+BX40*BX49+BX41*BX50 -> 0.023327687 | BY36: =+BY37*BY45+BY38*BY46+BY39*BY48+BY40*BY49+BY41*BY50 -> 0.036960618 | BZ36: =+BZ37*BZ45+BZ38*BZ46+BZ39*BZ48+BZ40*BZ49+BZ41*BZ50 -> 0.00044600869 | CA36: =+CA37*CA45+CA38*CA46+CA39*CA48+CA40*CA49+CA41*CA50 -> 0.021589392 | CB36: =+CB37*CB45+CB38*CB46+CB39*CB48+CB40*CB49+CB41*CB50 -> 0.019161059 | ... CD36: =+CD37*CD45+CD38*CD46+CD39*CD48+CD40*CD49+CD41*CD50 -> 0.019161059
A37: Fibers | V37: =+(1+V18)*(1+V57)-1 -> -0.024537679 | W37: =+(1+W18)*(1+W57)-1 -> -0.10628901 | X37: =+(1+X18)*(1+X57)-1 -> 0.32205065 | Y37: =+(1+Y18)*(1+Y57)-1 -> 0.61875852 | Z37: =+(1+Z18)*(1+Z57)-1 -> 0.63908791 | AA37: =+(1+AA18)*(1+AA57)-1 -> 0.48121233 | AB37: =+(1+AB18)*(1+AB57)-1 -> 0.18290476 | AC37: =+(1+AC18)*(1+AC57)-1 -> 0.059748786 | ... AS37: =+(1+AS18)*(1+AS57)-1 -> -0.028804865 | AU37: -0.029510913 | BU37: =+(1+BU18)*(1+BU57)-1 -> 0.51076233 | BV37: =+(1+BV18)*(1+BV57)-1 -> 0.20482841 | BW37: =+(1+BW18)*(1+BW57)-1 -> -0.27184044 | BX37: =+(1+BX18)*(1+BX57)-1 -> 0.025811966 | BY37: =+(1+BY18)*(1+BY57)-1 -> 0.093783605 | BZ37: =+(1+BZ18)*(1+BZ57)-1 -> -0.059579964 | CA37: =+(1+CA18)*(1+CA57)-1 -> 0.029897467 | CB37: =+(1+CB18)*(1+CB57)-1 -> 0.019779412 | ... CD37: =+(1+CD18)*(1+CD57)-1 -> 0.019779412
A38: Packagings & others
A39: Labour (MXN) | V39: =+(1+V18)*(1+V6)-1 -> 0.025735412 | W39: =+(1+W18)*(1+W6)-1 -> -0.0047411071 | X39: =+(1+X18)*(1+X6)-1 -> 0.06000148 | Y39: =+(1+Y18)*(1+Y6)-1 -> 0.030609036 | Z39: =+(1+Z18)*(1+Z6)-1 -> 0.042300669 | AA39: =+(1+AA18)*(1+AA6)-1 -> 0.047467483 | AB39: =+(1+AB18)*(1+AB6)-1 -> 0.021777646 | AC39: =+(1+AC18)*(1+AC6)-1 -> 0.0026983667 | ... AS39: =+(1+AS18)*(1+AS6)-1 -> 0.04535 | AU39: 0.036919441 | BU39: =+(1+BU18)*(1+BU6)-1 -> 0.05422716 | BV39: =+(1+BV18)*(1+BV6)-1 -> 0.028574454 | BW39: =+(1+BW18)*(1+BW6)-1 -> 0.02698498 | BX39: =+(1+BX18)*(1+BX6)-1 -> 0.045666613 | BY39: =+(1+BY18)*(1+BY6)-1 -> 0.032979147 | BZ39: =+(1+BZ18)*(1+BZ6)-1 -> 0.044315 | CA39: =+(1+CA18)*(1+CA6)-1 -> 0.040175 | CB39: =+(1+CB18)*(1+CB6)-1 -> 0.040175 | ... CD39: =+(1+CD18)*(1+CD6)-1 -> 0.040175
A40: Energy (MXN) | V40: =+V6 -> 0.046668788 | W40: =+W6 -> 0.058786056 | X40: =+X6 -> 0.06000148 | Y40: =+Y6 -> 0.073551079 | Z40: =+Z6 -> 0.074536772 | AA40: =+AA6 -> 0.079863385 | AB40: =+AB6 -> 0.086997496 | AC40: =+AC6 -> 0.078170287 | ... AS40: =+AS6 -> 0.035 | AU40: 0.036919441 | BU40: =+BU6 -> 0.073551079 | BV40: =+BV6 -> 0.078170287 | BW40: =+BW6 -> 0.046608896 | BX40: =+BX6 -> 0.042123394 | BY40: =+BY6 -> 0.036919441 | BZ40: =+BZ6 -> 0.035 | CA40: =+CA6 -> 0.035 | CB40: =+CB6 -> 0.035 | ... CD40: =+CD6 -> 0.035
A41: Raw Materials (MXN) | V41: =+V6 -> 0.046668788 | W41: =+W6 -> 0.058786056 | X41: =+X6 -> 0.06000148 | Y41: =+Y6 -> 0.073551079 | Z41: =+Z6 -> 0.074536772 | AA41: =+AA6 -> 0.079863385 | AB41: =+AB6 -> 0.086997496 | AC41: =+AC6 -> 0.078170287 | ... AS41: =+AS6 -> 0.035 | AU41: 0.036919441 | BU41: =+BU6 -> 0.073551079 | BV41: =+BV6 -> 0.078170287 | BW41: =+BW6 -> 0.046608896 | BX41: =+BX6 -> 0.042123394 | BY41: =+BY6 -> 0.036919441 | BZ41: =+BZ6 -> 0.035 | CA41: =+CA6 -> 0.035 | CB41: =+CB6 -> 0.035 | ... CD41: =+CD6 -> 0.035
A43: Cost Structure
A44: USD Denominated | V44: 0.6 | W44: 0.6 | X44: 0.6 | Y44: 0.6 | Z44: 0.6 | AA44: 0.6 | AB44: 0.6 | AC44: 0.6 | AD44: 0.6 | AE44: 0.6 | AF44: 0.6 | AG44: 0.6 | AH44: 0.6 | AI44: 0.6 | AJ44: 0.6 | AK44: =AJ44 -> 0.6 | AL44: =AK44 -> 0.6 | AM44: =AL44 -> 0.6 | AN44: =AM44 -> 0.6 | AO44: =AN44 -> 0.6 | AP44: =AO44 -> 0.6 | AQ44: =AP44 -> 0.6 | AR44: =AQ44 -> 0.6 | AS44: =AR44 -> 0.6 | AU44: 0.6 | BU44: 0.6 | BV44: 0.6 | BW44: 0.6 | BX44: 0.6 | BY44: 0.6 | BZ44: 0.6 | CA44: =BZ44 -> 0.6 | CB44: =CA44 -> 0.6 | CC44: =CB44 -> 0.6 | CD44: =CC44 -> 0.6
A45: Fibers | V45: 0.24 | W45: =+V45 -> 0.24 | X45: =+W45 -> 0.24 | Y45: =+X45 -> 0.24 | Z45: =+Y45 -> 0.24 | AA45: =+Z45 -> 0.24 | AB45: =+AA45 -> 0.24 | AC45: =+AB45 -> 0.24 | AD45: =+AC45 -> 0.24 | ... AS45: =+AR45 -> 0.24 | AU45: 0.24 | BU45: 0.24 | BV45: 0.24 | BW45: 0.24 | BX45: 0.24 | BY45: 0.24 | BZ45: 0.24 | CA45: =+BZ45 -> 0.24 | CB45: =+CA45 -> 0.24 | CC45: =+CB45 -> 0.24 | CD45: =+CC45 -> 0.24
A46: Packagings & others | V46: =+V44-V45 -> 0.36 | W46: =+W44-W45 -> 0.36 | X46: =+X44-X45 -> 0.36 | Y46: =+Y44-Y45 -> 0.36 | Z46: =+Z44-Z45 -> 0.36 | AA46: =+AA44-AA45 -> 0.36 | AB46: =+AB44-AB45 -> 0.36 | AC46: =+AC44-AC45 -> 0.36 | ... AS46: =+AS44-AS45 -> 0.36 | AU46: 0.36 | BU46: 0.36 | BV46: 0.36 | BW46: 0.36 | BX46: 0.36 | BY46: 0.36 | BZ46: 0.36 | CA46: =+BZ46 -> 0.36 | CB46: =+CA46 -> 0.36 | CC46: =+CB46 -> 0.36 | CD46: =+CC46 -> 0.36
A47: MXN Denominated | V47: =1-V44 -> 0.4 | W47: =1-W44 -> 0.4 | X47: =1-X44 -> 0.4 | Y47: =1-Y44 -> 0.4 | Z47: =1-Z44 -> 0.4 | AA47: =1-AA44 -> 0.4 | AB47: =1-AB44 -> 0.4 | AC47: =1-AC44 -> 0.4 | ... AS47: =1-AS44 -> 0.4 | AU47: 0.4 | BU47: 0.4 | BV47: 0.4 | BW47: 0.4 | BX47: 0.4 | BY47: 0.4 | BZ47: 0.4 | CA47: =+BZ47 -> 0.4 | CB47: =+CA47 -> 0.4 | CC47: =+CB47 -> 0.4 | CD47: =+CC47 -> 0.4
A48: Labour (MXN) | V48: 0.08 | W48: =+V48 -> 0.08 | X48: =+W48 -> 0.08 | Y48: =+X48 -> 0.08 | Z48: =+Y48 -> 0.08 | AA48: =+Z48 -> 0.08 | AB48: =+AA48 -> 0.08 | AC48: =+AB48 -> 0.08 | AD48: =+AC48 -> 0.08 | ... AS48: =+AR48 -> 0.08 | AU48: 0.08 | BU48: 0.08 | BV48: 0.08 | BW48: 0.08 | BX48: 0.08 | BY48: 0.08 | BZ48: 0.08 | CA48: =+BZ48 -> 0.08 | CB48: =+CA48 -> 0.08 | CC48: =+CB48 -> 0.08 | CD48: =+CC48 -> 0.08
A49: Energy (MXN) | V49: 0.09 | W49: =+V49 -> 0.09 | X49: =+W49 -> 0.09 | Y49: =+X49 -> 0.09 | Z49: =+Y49 -> 0.09 | AA49: =+Z49 -> 0.09 | AB49: =+AA49 -> 0.09 | AC49: =+AB49 -> 0.09 | AD49: =+AC49 -> 0.09 | ... AS49: =+AR49 -> 0.09 | AU49: 0.09 | BU49: 0.09 | BV49: 0.09 | BW49: 0.09 | BX49: 0.09 | BY49: 0.09 | BZ49: 0.09 | CA49: =+BZ49 -> 0.09 | CB49: =+CA49 -> 0.09 | CC49: =+CB49 -> 0.09 | CD49: =+CC49 -> 0.09
A50: Raw Materials (MXN) | V50: =+V47-V48-V49 -> 0.23 | W50: =+W47-W48-W49 -> 0.23 | X50: =+X47-X48-X49 -> 0.23 | Y50: =+Y47-Y48-Y49 -> 0.23 | Z50: =+Z47-Z48-Z49 -> 0.23 | AA50: =+AA47-AA48-AA49 -> 0.23 | AB50: =+AB47-AB48-AB49 -> 0.23 | AC50: =+AC47-AC48-AC49 -> 0.23 | ... AS50: =+AS47-AS48-AS49 -> 0.23 | AU50: 0.23 | BU50: 0.23 | BV50: 0.23 | BW50: 0.23 | BX50: 0.23 | BY50: 0.23 | BZ50: 0.23 | CA50: =+BZ50 -> 0.23 | CB50: =+CA50 -> 0.23 | CC50: =+CB50 -> 0.23 | CD50: =+CC50 -> 0.23
A52: Cogs/rev est por regresion | F52: =0.0904*F57+0.5892 -> 0.58626536 | G52: =0.0904*G57+0.5892 -> 0.58144922 | H52: =0.0904*H57+0.5892 -> 0.59573886 | I52: =0.0904*I57+0.5892 -> 0.6112744 | J52: =0.0904*J57+0.5892 -> 0.61854938 | K52: =0.0904*K57+0.5892 -> 0.63911156 | L52: =0.0904*L57+0.5892 -> 0.62701234 | M52: =0.0904*M57+0.5892 -> 0.61236939 | ... AS52: =0.0904*AS57+0.5892 -> 0.58572677 | AU52: 0.58653221 | BP52: =0.0904*BP57+0.5892 -> 0.59396732 | BQ52: =0.0904*BQ57+0.5892 -> 0.61217477 | BR52: =0.0904*BR57+0.5892 -> 0.61017163 | BS52: =0.0904*BS57+0.5892 -> 0.57242892 | BT52: =0.0904*BT57+0.5892 -> 0.57071241 | BU52: =0.0904*BU57+0.5892 -> 0.63787629 | BV52: =0.0904*BV57+0.5892 -> 0.61296823 | BW52: =0.0904*BW57+0.5892 -> 0.56588344 | ... CD52: =0.0904*CD57+0.5892 -> 0.59052941
A53: error | F53: =+F28-F52 -> 0.01283146 | G53: =+G28-G52 -> 0.021454722 | H53: =+H28-H52 -> 0.015815627 | I53: =+I28-I52 -> -0.013508027 | J53: =+J28-J52 -> -0.024335903 | K53: =+K28-K52 -> -0.037425203 | L53: =+L28-L52 -> -0.0027455937 | M53: =+M28-M52 -> 0.017520491 | ... AS53: =+AS28-AS52 -> -0.032044953 | AU53: -0.04150522 | BP53: =+BP28-BP52 -> -0.025423428 | BQ53: =+BQ28-BQ52 -> 0.022874972 | BR53: =+BR28-BR52 -> 0.030968285 | BS53: =+BS28-BS52 -> 0.041812056 | BT53: =+BT28-BT52 -> 0.0018492242 | BU53: =+BU28-BU52 -> -0.015770495 | BV53: =+BV28-BV52 -> 0.019952084 | BW53: =+BW28-BW52 -> 0.0085713978 | ... CD53: =+CD28-CD52 -> -0.016496045
A54: EUR HW PULP Prices (us$/Tn) | B54: =+VLOOKUP(B$8,'Raw Materials (2)'!$B$69:$F$128,4,FALSE) -> 762.43077 | C54: =+VLOOKUP(C8,'Raw Materials (2)'!$B$69:$F$128,4,FALSE) -> 693.27308 | D54: =+VLOOKUP(D8,'Raw Materials (2)'!$B$69:$F$128,4,FALSE) -> 671.49077 | E54: =+VLOOKUP(E8,'Raw Materials (2)'!$B$69:$F$128,4,FALSE) -> 655.10769 | F54: =+VLOOKUP(F8,'Raw Materials (2)'!$B$69:$F$128,4,FALSE) -> 680.46769 | G54: =+VLOOKUP(G8,'Raw Materials (2)'!$B$69:$F$128,4,FALSE) -> 782.79154 | H54: =+VLOOKUP(H8,'Raw Materials (2)'!$B$69:$F$128,4,FALSE) -> 873.24462 | I54: =+VLOOKUP(I8,'Raw Materials (2)'!$B$69:$F$128,4,FALSE) -> 941.09615 | J54: =+VLOOKUP(J8,'Raw Materials (2)'!$B$69:$F$128,4,FALSE) -> 1009.0246 | ... AS54: =+VLOOKUP(AS8,'Raw Materials (2)'!$B$69:$F$128,4,FALSE) -> 1110.1265 | AU54: 1178.06 | AX54: =+AVERAGEIFS('Raw Materials (2)'!$E$9:$E$128,'Raw Materials (2)'!$B$9:$B$128,"<="&AX1,'Raw Materials (2)'!$B$9:$B$128,">"&AW1) -> 418.9325 | AY54: =+AVERAGEIFS('Raw Materials (2)'!$E$9:$E$128,'Raw Materials (2)'!$B$9:$B$128,"<="&AY1,'Raw Materials (2)'!$B$9:$B$128,">"&AX1) -> 484.575 | AZ54: =+AVERAGEIFS('Raw Materials (2)'!$E$9:$E$128,'Raw Materials (2)'!$B$9:$B$128,"<="&AZ1,'Raw Materials (2)'!$B$9:$B$128,">"&AY1) -> 654.4525 | BA54: =+AVERAGEIFS('Raw Materials (2)'!$E$9:$E$128,'Raw Materials (2)'!$B$9:$B$128,"<="&BA1,'Raw Materials (2)'!$B$9:$B$128,">"&AZ1) -> 460.42 | BB54: =+AVERAGEIFS('Raw Materials (2)'!$E$9:$E$128,'Raw Materials (2)'!$B$9:$B$128,"<="&BB1,'Raw Materials (2)'!$B$9:$B$128,">"&BA1) -> 459.2275 | BC54: =+AVERAGEIFS('Raw Materials (2)'!$E$9:$E$128,'Raw Materials (2)'!$B$9:$B$128,"<="&BC1,'Raw Materials (2)'!$B$9:$B$128,">"&BB1) -> 508.9925 | BD54: =+AVERAGEIFS('Raw Materials (2)'!$E$9:$E$128,'Raw Materials (2)'!$B$9:$B$128,"<="&BD1,'Raw Materials (2)'!$B$9:$B$128,">"&BC1) -> 523.91 | BE54: =+AVERAGEIFS('Raw Materials (2)'!$E$9:$E$128,'Raw Materials (2)'!$B$9:$B$128,"<="&BE1,'Raw Materials (2)'!$B$9:$B$128,">"&BD1) -> 587.54 | ... BZ54: =+AVERAGEIFS('Raw Materials (2)'!$E$9:$E$128,'Raw Materials (2)'!$B$9:$B$128,"<="&BZ1,'Raw Materials (2)'!$B$9:$B$128,">"&BY1) -> 1117.148 | CA54: =+BZ54 -> 1117.148 | CB54: =+CA54 -> 1117.148 | CC54: =+CB54 -> 1117.148 | CD54: =+CC54 -> 1117.148
A55: Chg QOQ | F55: =F54/B54-1 -> -0.10750232 | G55: =G54/C54-1 -> 0.12912439 | H55: =H54/D54-1 -> 0.30045662 | I55: =I54/E54-1 -> 0.43655183 | J55: =J54/F54-1 -> 0.48283986 | K55: =K54/G54-1 -> 0.33417483 | L55: =L54/H54-1 -> 0.20241222 | M55: =M54/I54-1 -> 0.11058463 | ... AS55: =AS54/AO54-1 -> 0.030912723 | AU55: 0.065016673 | AY55: =AY54/AX54-1 -> 0.15668992 | AZ55: =AZ54/AY54-1 -> 0.35057009 | BA55: =BA54/AZ54-1 -> -0.29648065 | BB55: =BB54/BA54-1 -> -0.0025900265 | BC55: =BC54/BB54-1 -> 0.10836677 | BD55: =BD54/BC54-1 -> 0.029307897 | BE55: =BE54/BD54-1 -> 0.12145216 | BF55: =BF54/BE54-1 -> 0.10148245 | ... CD55: =CD54/CC54-1 -> 0
A56: MXN/Tn (Lag 1 tri) | B56: =+B54*B$3 -> 13744.492 | C56: =+B54*C3 -> 13805.563 | D56: =+C54*D3 -> 13007.605 | E56: =+D54*E3 -> 13325.801 | F56: =+E54*F3 -> 13298.306 | G56: =+F54*G3 -> 12621.892 | H56: =+G54*H3 -> 13948.478 | I56: =+H54*I3 -> 16579.773 | J56: =+I54*J3 -> 17615.751 | ... AG56: =+AF54*AG3 -> 14655.879 | AH56: =+AG54*AH$3 -> 15417.187 | AI56: =+AH54*AI$3 -> 19174.106 | AJ56: =+AH54*AJ3 -> 21064.706 | AK56: =+AK54*AK3 -> 22216.218 | AL56: =+AL54*(AM$3*0.5+20.7*0.5) -> 21388.261 | AM56: =+AM54*(AN$3*0.5+20.7*0.5) -> 23115.173 | AN56: =+AN54*(AO$3*0.5+20.7*0.5) -> 20178.787 | AO56: =+AO54*(AP$3*0.5+20.7*0.5) -> 20818.033 | AP56: =+AO54*AP$3 -> 19345.511 | AQ56: =+AP54*AQ$3 -> 20414.218 | AR56: =+AQ54*AR$3 -> 19911.032 | AS56: =+AR54*AS$3 -> 20018.191 | AU56: 21560.597 | AX56: =+AX54*AX3 -> 3760.3381 | AY56: =+AY54*AY3 -> 4700.8621 | AZ56: =+AZ54*AZ3 -> 6259.0201 | BA56: =+BA54*BA3 -> 4323.3438 | BB56: =+BB54*BB3 -> 4483.7825 | BC56: =+BC54*BC3 -> 5494.574 | BD56: =+BD54*BD3 -> 5857.3138 | BE56: =+BE54*BE3 -> 6396.8417 | ... BW56: =+BW54*BW3 -> 19042.715 | BX56: =+AVERAGEIFS($A56:$AS56,$A$1:$AS$1,"<="&BX$1,$A$1:$AS$1,">"&BW$1) -> 19468.054 | BY56: =+AVERAGEIFS($A56:$AS56,$A$1:$AS$1,"<="&BY$1,$A$1:$AS$1,">"&BX$1) -> 21375.064 | BZ56: =+AVERAGEIFS($A56:$AS56,$A$1:$AS$1,"<="&BZ$1,$A$1:$AS$1,">"&BY$1) -> 19922.238 | CA56: =+CA54*CA3 -> 20415.783 | CB56: =+CB54*CB3 -> 20716.015 | CC56: =+CC54*CC3 -> 21020.663 | CD56: =+CD54*CD3 -> 21329.79
A57: Chg YoY | F57: =F56/B56-1 -> -0.032462878 | G57: =G56/C56-1 -> -0.085738706 | H57: =H56/D56-1 -> 0.072332505 | I57: =I56/E56-1 -> 0.2441858 | J57: =J56/F56-1 -> 0.32466126 | K57: =K56/G56-1 -> 0.55211907 | L57: =L56/H56-1 -> 0.41827811 | M57: =M56/I56-1 -> 0.25629853 | ... AS57: =AS56/AO56-1 -> -0.038420658 | AU57: -0.029510913 | AY57: =AY56/AX56-1 -> 0.25011686 | AZ57: =AZ56/AY56-1 -> 0.33146219 | BA57: =BA56/AZ56-1 -> -0.30926188 | BB57: =BB56/BA56-1 -> 0.037109865 | BC57: =BC56/BB56-1 -> 0.22543278 | BD57: =BD56/BC56-1 -> 0.066017813 | BE57: =BE56/BD56-1 -> 0.09211184 | BF57: =BF56/BE56-1 -> 0.084450574 | ... CD57: =CD56/CC56-1 -> 0.014705882
A59: WTI (us$/boe) | B59: =+VLOOKUP(B$8,'Raw Materials (2)'!$B$69:$L$128,11,FALSE) -> 35.318154 | C59: =+VLOOKUP(C$8,'Raw Materials (2)'!$B$69:$L$128,11,FALSE) -> 47.027077 | D59: =+VLOOKUP(D$8,'Raw Materials (2)'!$B$69:$L$128,11,FALSE) -> 46.987576 | E59: =+VLOOKUP(E$8,'Raw Materials (2)'!$B$69:$L$128,11,FALSE) -> 51.127231 | F59: =+VLOOKUP(F$8,'Raw Materials (2)'!$B$69:$L$128,11,FALSE) -> 54.608308 | G59: =+VLOOKUP(G$8,'Raw Materials (2)'!$B$69:$L$128,11,FALSE) -> 50.870923 | H59: =+VLOOKUP(H$8,'Raw Materials (2)'!$B$69:$L$128,11,FALSE) -> 52.168308 | I59: =+VLOOKUP(I$8,'Raw Materials (2)'!$B$69:$L$128,11,FALSE) -> 61.514154 | ... AS59: =+VLOOKUP(AS$8,'Raw Materials (2)'!$B$69:$L$128,11,FALSE) -> 75 | AU59: 70 | AX59: =+AVERAGEIFS('Raw Materials (2)'!$L$9:$L$128,'Raw Materials (2)'!$B$9:$B$128,"<="&AX1,'Raw Materials (2)'!$B$9:$B$128,">"&AW1) -> #DIV/0! | AY59: =+AVERAGEIFS('Raw Materials (2)'!$L$9:$L$128,'Raw Materials (2)'!$B$9:$B$128,"<="&AY1,'Raw Materials (2)'!$B$9:$B$128,">"&AX1) -> #DIV/0! | AZ59: =+AVERAGEIFS('Raw Materials (2)'!$L$9:$L$128,'Raw Materials (2)'!$B$9:$B$128,"<="&AZ1,'Raw Materials (2)'!$B$9:$B$128,">"&AY1) -> #DIV/0! | BA59: =+AVERAGEIFS('Raw Materials (2)'!$L$9:$L$128,'Raw Materials (2)'!$B$9:$B$128,"<="&BA1,'Raw Materials (2)'!$B$9:$B$128,">"&AZ1) -> #DIV/0! | BB59: =+AVERAGEIFS('Raw Materials (2)'!$L$9:$L$128,'Raw Materials (2)'!$B$9:$B$128,"<="&BB1,'Raw Materials (2)'!$B$9:$B$128,">"&BA1) -> #DIV/0! | BC59: =+AVERAGEIFS('Raw Materials (2)'!$L$9:$L$128,'Raw Materials (2)'!$B$9:$B$128,"<="&BC1,'Raw Materials (2)'!$B$9:$B$128,">"&BB1) -> #DIV/0! | BD59: =+AVERAGEIFS('Raw Materials (2)'!$L$9:$L$128,'Raw Materials (2)'!$B$9:$B$128,"<="&BD1,'Raw Materials (2)'!$B$9:$B$128,">"&BC1) -> #DIV/0! | BE59: =+AVERAGEIFS('Raw Materials (2)'!$L$9:$L$128,'Raw Materials (2)'!$B$9:$B$128,"<="&BE1,'Raw Materials (2)'!$B$9:$B$128,">"&BD1) -> #DIV/0! | ... BK59: =+AVERAGEIFS('Raw Materials (2)'!$L$9:$L$128,'Raw Materials (2)'!$B$9:$B$128,"<="&BK1,'Raw Materials (2)'!$B$9:$B$128,">"&BJ1) -> #DIV/0! | BL59: 94 | BM59: 96 | BN59: =+AVERAGEIFS('Raw Materials (2)'!$L$9:$L$128,'Raw Materials (2)'!$B$9:$B$128,"<="&BN1,'Raw Materials (2)'!$B$9:$B$128,">"&BM1) -> 99.485637 | BO59: =+AVERAGEIFS('Raw Materials (2)'!$L$9:$L$128,'Raw Materials (2)'!$B$9:$B$128,"<="&BO1,'Raw Materials (2)'!$B$9:$B$128,">"&BN1) -> 53.60689 | BP59: =+AVERAGEIFS('Raw Materials (2)'!$L$9:$L$128,'Raw Materials (2)'!$B$9:$B$128,"<="&BP1,'Raw Materials (2)'!$B$9:$B$128,">"&BO1) -> 45.115009 | BQ59: =+AVERAGEIFS('Raw Materials (2)'!$L$9:$L$128,'Raw Materials (2)'!$B$9:$B$128,"<="&BQ1,'Raw Materials (2)'!$B$9:$B$128,">"&BP1) -> 54.790423 | BR59: =+AVERAGEIFS('Raw Materials (2)'!$L$9:$L$128,'Raw Materials (2)'!$B$9:$B$128,"<="&BR1,'Raw Materials (2)'!$B$9:$B$128,">"&BQ1) -> 71.600027 | BS59: =+AVERAGEIFS('Raw Materials (2)'!$L$9:$L$128,'Raw Materials (2)'!$B$9:$B$128,"<="&BS1,'Raw Materials (2)'!$B$9:$B$128,">"&BR1) -> 64.179489 | BT59: =+AVERAGEIFS('Raw Materials (2)'!$L$9:$L$128,'Raw Materials (2)'!$B$9:$B$128,"<="&BT1,'Raw Materials (2)'!$B$9:$B$128,">"&BS1) -> 43.277053 | BU59: =+AVERAGEIFS('Raw Materials (2)'!$L$9:$L$128,'Raw Materials (2)'!$B$9:$B$128,"<="&BU1,'Raw Materials (2)'!$B$9:$B$128,">"&BT1) -> 70.770807 | ... BZ59: =+AVERAGEIFS('Raw Materials (2)'!$L$9:$L$128,'Raw Materials (2)'!$B$9:$B$128,"<="&BZ1,'Raw Materials (2)'!$B$9:$B$128,">"&BY1) -> 72 | CA59: =+BZ59 -> 72 | CB59: =+CA59 -> 72 | CC59: =+CB59 -> 72 | CD59: =+CC59 -> 72
A60: Chg YoY | F60: =F59/B59-1 -> 0.54618239 | G60: =G59/C59-1 -> 0.081736872 | H60: =H59/D59-1 -> 0.11025749 | I60: =I59/E59-1 -> 0.20315834 | J60: =J59/F59-1 -> 0.23187512 | K60: =K59/G59-1 -> 0.4736936 | L60: =L59/H59-1 -> 0.45372375 | M60: =M59/I59-1 -> 0.11068796 | ... AS60: =AS59/AO59-1 -> 0.18925776 | AU60: -0.054125711 | AY60: =AY59/AX59-1 -> #DIV/0! | AZ60: =AZ59/AY59-1 -> #DIV/0! | BA60: =BA59/AZ59-1 -> #DIV/0! | BB60: =BB59/BA59-1 -> #DIV/0! | BC60: =BC59/BB59-1 -> #DIV/0! | BD60: =BD59/BC59-1 -> #DIV/0! | BE60: =BE59/BD59-1 -> #DIV/0! | BF60: =BF59/BE59-1 -> #DIV/0! | ... CD60: =CD59/CC59-1 -> 0
A61: WIT (MXN/boe) | B61: =+B59*B3 -> 636.68742 | C61: =+C59*C3 -> 851.53339 | D61: =+D59*D3 -> 881.60909 | E61: =+E59*E3 -> 1014.625 | F61: =+F59*F3 -> 1108.517 | G61: =+G59*G3 -> 943.597 | H61: =+H59*H3 -> 929.58146 | I61: =+I59*I3 -> 1167.9324 | ... AS61: =+AS59*AS3 -> 1352.4264 | AU61: 1281.1247 | AX61: =+AX59*AX3 -> #DIV/0! | AY61: =+AY59*AY3 -> #DIV/0! | AZ61: =+AZ59*AZ3 -> #DIV/0! | BA61: =+BA59*BA3 -> #DIV/0! | BB61: =+BB59*BB3 -> #DIV/0! | BC61: =+BC59*BC3 -> #DIV/0! | BD61: =+BD59*BD3 -> #DIV/0! | BE61: =+BE59*BE3 -> #DIV/0! | ... CD61: =+CD59*CD3 -> 1374.7014
A62: Chg YoY | F62: =F61/B61-1 -> 0.74106937 | G62: =G61/C61-1 -> 0.1081151 | H62: =H61/D61-1 -> 0.054414557 | I62: =I61/E61-1 -> 0.15109761 | J62: =J61/F61-1 -> 0.13592647 | K62: =K61/G61-1 -> 0.54254549 | L62: =L61/H61-1 -> 0.54536311 | M62: =M61/I61-1 -> 0.16046363 | ... AS62: =AS61/AO61-1 -> 0.17175007 | AU62: -0.13807859 | AY62: =AY61/AX61-1 -> #DIV/0! | AZ62: =AZ61/AY61-1 -> #DIV/0! | BA62: =BA61/AZ61-1 -> #DIV/0! | BB62: =BB61/BA61-1 -> #DIV/0! | BC62: =BC61/BB61-1 -> #DIV/0! | BD62: =BD61/BC61-1 -> #DIV/0! | BE62: =BE61/BD61-1 -> #DIV/0! | BF62: =BF61/BE61-1 -> #DIV/0! | ... CD62: =CD61/CC61-1 -> 0.014705882
A64: Cost Index MXN | F64: =+$BR$114*F57+F62*$BR$115+F6*$BR$116 -> 0.29243163 | G64: =+$BR$114*G57+G62*$BR$115+G6*$BR$116 -> 0.030060568 | H64: =+$BR$114*H57+H62*$BR$115+H6*$BR$116 -> 0.06295401 | I64: =+$BR$114*I57+I62*$BR$115+I6*$BR$116 -> 0.16023863 | J64: =+$BR$114*J57+J62*$BR$115+J6*$BR$116 -> 0.17699185 | K64: =+$BR$114*K57+K62*$BR$115+K6*$BR$116 -> 0.41185996 | L64: =+$BR$114*L57+L62*$BR$115+L6*$BR$116 -> 0.36845906 | M64: =+$BR$114*M57+M62*$BR$115+M6*$BR$116 -> 0.16276474 | ... AS64: =+$BR$114*AS57+AS62*$BR$115+AS6*$BR$116 -> 0.063369503 | AU64: -0.053916111 | AY64: =+$BR$114*AY57+AY62*$BR$115+AY6*$BR$116 -> #DIV/0! | AZ64: =+$BR$114*AZ57+AZ62*$BR$115+AZ6*$BR$116 -> #DIV/0! | BA64: =+$BR$114*BA57+BA62*$BR$115+BA6*$BR$116 -> #DIV/0! | BB64: =+$BR$114*BB57+BB62*$BR$115+BB6*$BR$116 -> #DIV/0! | BC64: =+$BR$114*BC57+BC62*$BR$115+BC6*$BR$116 -> #DIV/0! | BD64: =+$BR$114*BD57+BD62*$BR$115+BD6*$BR$116 -> #DIV/0! | BE64: =+$BR$114*BE57+BE62*$BR$115+BE6*$BR$116 -> #DIV/0! | BF64: =+$BR$114*BF57+BF62*$BR$115+BF6*$BR$116 -> #DIV/0! | ... CD64: =+$BR$114*CD57+CD62*$BR$115+CD6*$BR$116 -> 0.020185294
A65: Cost Index USD | V65: =+$BR$114*U55+V60*$BR$115+V6*$BR$116 -> 0.082674743 | W65: =+$BR$114*V55+W60*$BR$115+W6*$BR$116 -> 0.46922835 | X65: =+$BR$114*W55+X60*$BR$115+X6*$BR$116 -> 0.4405595 | Y65: =+$BR$114*X55+Y60*$BR$115+Y6*$BR$116 -> 0.54235251 | Z65: =+$BR$114*Y55+Z60*$BR$115+Z6*$BR$116 -> 0.40230098 | AA65: =+$BR$114*Z55+AA60*$BR$115+AA6*$BR$116 -> 0.4432176 | AB65: =+$BR$114*AA55+AB60*$BR$115+AB6*$BR$116 -> 0.2374433 | AC65: =+$BR$114*AB55+AC60*$BR$115+AC6*$BR$116 -> 0.13331608 | ... AS65: =+$BR$114*AR55+AS60*$BR$115+AS6*$BR$116 -> 0.10802352 | AU65: -0.059841603
A67: Gross Profit | B67: =+B22+B11 -> 3436.413 | C67: =+C22+C11 -> 3452.977 | D67: =+D22+D11 -> 3344.661 | E67: =+E22+E11 -> 3550.882 | F67: =+F22+F11 -> 3384.668 | G67: =+G22+G11 -> 3399.355 | H67: =+H22+H11 -> 3204.698 | I67: =+I22+I11 -> 3413.27 | ... AS67: =+AS22+AS11 -> 5939.4918 | AT67: 0.38717375 | AU67: 5556.2076 | AX67: =+AX22+AX11 -> 5077.175 | AY67: =+AY22+AY11 -> 6039.352 | AZ67: =+AZ22+AZ11 -> 6844.987 | BA67: =+BA22+BA11 -> 6836.86 | BB67: =+BB22+BB11 -> 6799.948 | BC67: =+BC22+BC11 -> 6830.977 | BD67: =+BD22+BD11 -> 7491.3 | BE67: =+BE22+BE11 -> 8304.495 | ... CD67: =+CD22+CD11 -> 24121.062
A68: GP Margin | B68: =1-B23 -> 0.39370855 | C68: =1-C23 -> 0.39099071 | D68: =1-D23 -> 0.38358593 | E68: =1-E23 -> 0.37851172 | F68: =1-F23 -> 0.35514036 | G68: =1-G23 -> 0.3538818 | H68: =1-H23 -> 0.34844055 | I68: =1-I23 -> 0.36187852 | ... M68: =1-M23 -> 0.33311206 | N68: =+N67/N11 -> 0.35182495 | O68: =+O67/O11 -> 0.37201306 | P68: =+P67/P11 -> 0.38321029 | Q68: =+Q67/Q11 -> 0.39464133 | R68: =+R67/R11 -> 0.39553582 | S68: =+S67/S11 -> 0.38258895 | T68: =+T67/T11 -> 0.37876164 | U68: =+U67/U11 -> 0.38538403 | ... AS68: =+AS67/AS11 -> 0.41219635 | AU68: 0.3975233 | AX68: =+AX67/AX11 -> 0.41312353 | AY68: =+AY67/AY11 -> 0.43548135 | AZ68: =+AZ67/AZ11 -> 0.43032982 | BA68: =+BA67/BA11 -> 0.43730841 | BB68: =+BB67/BB11 -> 0.42246093 | BC68: =+BC67/BC11 -> 0.39946839 | BD68: =+BD67/BD11 -> 0.37836933 | BE68: =+BE67/BE11 -> 0.377767 | ... CD68: =+CD67/CD11 -> 0.39311504
W69: =+W68-S68 -> -0.037630686 | X69: =+X68-T68 -> -0.06154604 | Y69: =+Y68-U68 -> -0.088379671 | Z69: =+Z68-V68 -> -0.071936284 | AA69: =+AA68-W68 -> -0.022677674 | AB69: =+AB68-X68 -> 0.014532249 | AC69: =+AC68-Y68 -> 0.049680517 | AD69: =+AD68-Z68 -> 0.050152302 | ... AS69: =+AS68-AO68 -> 0.0081510716 | AU69: 0.0061788005 | AX69: =+AX68-AW68 -> 0.41312353 | AY69: =+AY68-AX68 -> 0.022357816 | AZ69: =+AZ68-AY68 -> -0.005151531 | BA69: =+BA68-AZ68 -> 0.0069785936 | BB69: =+BB68-BA68 -> -0.014847482 | BC69: =+BC68-BB68 -> -0.022992537 | BD69: =+BD68-BC68 -> -0.021099058 | BE69: =+BE68-BD68 -> -0.00060233458 | ... CD69: =+CD68-CC68 -> -0.0016287525
A71: =+PROJ!A8 -> General & Admininstrative Expenses | B71: =+PROJ!B8 -> -1385.949 | C71: =+PROJ!C8 -> -1505.344 | D71: =+PROJ!D8 -> -1298.673 | E71: =+PROJ!E8 -> -1576.557 | F71: =+PROJ!F8 -> -1556.581 | G71: =+PROJ!G8 -> -1604.777 | H71: =+PROJ!H8 -> -1642.969 | ... AO71: =+PROJ!AO8 -> -2467.304 | AP71: =+AL71*(1+AP73) -> -2388.1114 | AQ71: =+AM71*(1+AQ73) -> -2427.8699 | AR71: =+AN71*(1+AR73) -> -2426.1828 | AS71: =+AO71*(1+AS73) -> -2553.6596 | AU71: -2452.979 | AW71: =+PROJ!AW8 -> -1105.632 | AX71: =+PROJ!AX8 -> -1286.713 | AY71: =+PROJ!AY8 -> -1459.176 | AZ71: =+PROJ!AZ8 -> -1757.692 | BA71: =+PROJ!BA8 -> -1951.21 | BB71: =+PROJ!BB8 -> -2097.291 | BC71: =+PROJ!BC8 -> -2355.363 | BD71: =+PROJ!BD8 -> -2668.549 | ... BU71: =+PROJ!BU8 -> -7450.885 | BV71: =+SUMIFS($A71:$AO71,$A$1:$AO$1,"<="&BV$1,$A$1:$AO$1,">"&BU$1) -> -7848.084 | BW71: =+SUMIFS($A71:$AO71,$A$1:$AO$1,"<="&BW$1,$A$1:$AO$1,">"&BV$1) -> -8784.296 | BX71: =+SUMIFS($A71:$AO71,$A$1:$AO$1,"<="&BX$1,$A$1:$AO$1,">"&BW$1) -> -9572.8899 | BY71: =+SUMIFS($A71:$AS71,$A$1:$AS$1,"<="&BY$1,$A$1:$AS$1,">"&BX$1) -> -9464.564 | BZ71: =+SUMIFS($A71:$AS71,$A$1:$AS$1,"<="&BZ$1,$A$1:$AS$1,">"&BY$1) -> -9795.8237 | CA71: =+BZ71*(1+CA73) -> -10138.678 | CB71: =+CA71*(1+CB73) -> -10493.531 | CC71: =+CB71*(1+CC73) -> -10860.805 | CD71: =+CC71*(1+CD73) -> -11240.933
A72: % Revs | B72: =-B71/B11 -> 0.15878766 | C72: =-C71/C11 -> 0.17045452 | D72: =-D71/D11 -> 0.14893966 | E72: =-E71/E11 -> 0.16805551 | F72: =-F71/F11 -> 0.16332613 | G72: =-G71/G11 -> 0.16706151 | H72: =-H71/H11 -> 0.17863681 | I72: =-I71/I11 -> 0.17227596 | ... AS72: =-AS71/AS11 -> 0.17722209 | AU72: 0.17550034 | AW72: =-AW71/AW11 -> 0.10728588 | AX72: =-AX71/AX11 -> 0.10469827 | AY72: =-AY71/AY11 -> 0.10521724 | AZ72: =-AZ71/AZ11 -> 0.11050237 | BA72: =-BA71/BA11 -> 0.12480591 | BB72: =-BB71/BB11 -> 0.13029857 | BC72: =-BC71/BC11 -> 0.13773917 | BD72: =-BD71/BD11 -> 0.13478263 | ... CD72: =-CD71/CD11 -> 0.18320005
A73: Chg YoY | F73: =F71/B71-1 -> 0.12311564 | G73: =G71/C71-1 -> 0.066053341 | H73: =H71/D71-1 -> 0.2651137 | I73: =I71/E71-1 -> 0.030677609 | J73: =J71/F71-1 -> 0.097134682 | K73: =K71/G71-1 -> 0.11024647 | L73: =L71/H71-1 -> 0.014076346 | M73: =M71/I71-1 -> 0.040215469 | ... AO73: =AO71/AK71-1 -> 0.005839838 | AP73: 0.035 | AQ73: 0.035 | AR73: 0.035 | AS73: 0.035 | AU73: 0 | AX73: =AX71/AW71-1 -> 0.16378053 | AY73: =AY71/AX71-1 -> 0.13403377 | AZ73: =AZ71/AY71-1 -> 0.20457847 | BA73: =BA71/AZ71-1 -> 0.11009779 | BB73: =BB71/BA71-1 -> 0.074866877 | BC73: =BC71/BB71-1 -> 0.12305016 | BD73: =BD71/BC71-1 -> 0.13296719 | BE73: =BE71/BD71-1 -> 0.10180102 | ... BZ73: =BZ71/BY71-1 -> 0.035 | CA73: =+CA6 -> 0.035 | CB73: =+CB6 -> 0.035 | CC73: =+CC6 -> 0.035 | CD73: =+CD6 -> 0.035
A74: Chg QoQ | C74: =C71/B71-1 -> 0.086146749 | D74: =D71/C71-1 -> -0.13729154 | E74: =E71/D71-1 -> 0.21397534 | F74: =F71/E71-1 -> -0.012670649 | G74: =G71/F71-1 -> 0.030962732 | H74: =H71/G71-1 -> 0.023798945 | I74: =I71/H71-1 -> -0.010984383 | J74: =J71/I71-1 -> 0.050991371 | ... AS74: =AS71/AR71-1 -> 0.052542128 | AU74: 0.04643114
BE75: =+BE73-BE6 -> 0.061801016 | BF75: =+BF73-BF6 -> -0.012146283 | BG75: =+BG73-BG6 -> 0.012738425 | BH75: =+BH73-BH6 -> -0.020242933 | BI75: =+BI73-BI6 -> -0.0017820366 | BJ75: =+BJ73-BJ6 -> 0.028251111 | BK75: =+BK73-BK6 -> 0.025810668 | BL75: =+BL73-BL6 -> 0.1702796 | ... BW75: =+BW73-BW6 -> 0.072682895
A76: Other Income | B76: =+PROJ!B12 -> 0 | C76: =+PROJ!C12 -> 0 | D76: =+PROJ!D12 -> 0 | E76: =+PROJ!E12 -> 0 | F76: =+PROJ!F12 -> 0 | G76: =+PROJ!G12 -> 2.357 | H76: =+PROJ!H12 -> 4.104 | I76: =+PROJ!I12 -> 2.265 | ... AO76: =+PROJ!AO12 -> 2.604
A78: Operating Income | B78: =+B67+B71+B76 -> 2050.464 | C78: =+C67+C71+C76 -> 1947.633 | D78: =+D67+D71+D76 -> 2045.988 | E78: =+E67+E71+E76 -> 1974.325 | F78: =+F67+F71+F76 -> 1828.087 | G78: =+G67+G71+G76 -> 1796.935 | H78: =+H67+H71+H76 -> 1565.833 | I78: =+I67+I71+I76 -> 1790.613 | ... AO78: =+AO67+AO71+AO76 -> 3215.339 | AP78: =+AP67+AP71 -> 3191.3616 | AQ78: =+AQ67+AQ71 -> 3351.8112 | AR78: =+AR67+AR71 -> 2963.4207 | AS78: =+AS67+AS71 -> 3385.8322 | AU78: 3103.2286 | AW78: =+AW11+AW22+AW71 -> 2942.759 | AX78: =+AX11+AX22+AX71 -> 3790.462 | AY78: =+AY11+AY22+AY71 -> 4580.176 | AZ78: =+AZ11+AZ22+AZ71 -> 5087.295 | BA78: =+BA11+BA22+BA71 -> 4885.65 | BB78: =+BB11+BB22+BB71 -> 4702.657 | BC78: =+BC11+BC22+BC71 -> 4475.614 | BD78: =+BD11+BD22+BD71 -> 4822.751 | ... BW78: =+BW11+BW22+BW71 -> 11915.743 | BX78: =+SUMIFS($A78:$AO78,$A$1:$AO$1,"<="&BX$1,$A$1:$AO$1,">"&BW$1) -> 12847.35 | BY78: =+SUMIFS($A78:$AS78,$A$1:$AS$1,"<="&BY$1,$A$1:$AS$1,">"&BX$1) -> 12088.461 | BZ78: =+SUMIFS($A78:$AS78,$A$1:$AS$1,"<="&BZ$1,$A$1:$AS$1,">"&BY$1) -> 12892.426 | CA78: =+CA67+CA71 -> 12860.086 | CB78: =+CB67+CB71 -> 12878.565 | CC78: =+CC67+CC71 -> 12885.274 | CD78: =+CD67+CD71 -> 12880.129
A79: Oper. Income Mg. | B79: =+B78/B$11 -> 0.23492089 | C79: =+C78/C$11 -> 0.2205362 | D79: =+D78/D$11 -> 0.23464626 | E79: =+E78/E$11 -> 0.2104562 | F79: =+F78/F$11 -> 0.19181422 | G79: =+G78/G$11 -> 0.18706566 | H79: =+H78/H$11 -> 0.17024996 | I79: =+I78/I$11 -> 0.18984269 | ... AS79: =+AS78/AS$11 -> 0.23497425 | AU79: 0.22202296 | AW79: =+AW78/AW$11 -> 0.28555297 | AX79: =+AX78/AX$11 -> 0.30842527 | AY79: =+AY78/AY$11 -> 0.33026411 | AZ79: =+AZ78/AZ$11 -> 0.31982745 | BA79: =+BA78/BA$11 -> 0.3125025 | BB79: =+BB78/BB$11 -> 0.29216236 | BC79: =+BC78/BC$11 -> 0.26172923 | BD79: =+BD78/BD$11 -> 0.2435867 | ... CD79: =+CD78/CD$11 -> 0.20991498
AN80: =+AN78/AJ78-1 -> -0.038599247 | AO80: =+AO78/AK78-1 -> 0.092142667
A81: Depreciation | B81: =+PROJ!B65 -> -408.221 | C81: =+PROJ!C65 -> -412.516 | D81: =+PROJ!D65 -> -412.263 | E81: =+PROJ!E65 -> -367.919 | F81: =+PROJ!F65 -> -436.143 | G81: =+PROJ!G65 -> -415.112 | H81: =+PROJ!H65 -> -367.936 | I81: =+PROJ!I65 -> -380.633 | ... AS81: =+PROJ!AS65 -> -491.67429 | AU81: -569.46815 | AW81: =+PROJ!AW65 -> -612.142 | AX81: =+PROJ!AX65 -> -709.517 | AY81: =+PROJ!AY65 -> -811.742 | AZ81: =+PROJ!AZ65 -> -835.994 | BA81: =+PROJ!BA65 -> -931.031 | BB81: =+PROJ!BB65 -> -1083.713 | BC81: =+PROJ!BC65 -> -1171.366 | BD81: =+PROJ!BD65 -> -1241.009 | ... BW81: =+PROJ!BW65 -> -1984.52 | BX81: =+SUMIFS($A81:$AO81,$A$1:$AO$1,"<="&BX$1,$A$1:$AO$1,">"&BW$1) -> -2047.673 | BY81: =+SUMIFS($A81:$AS81,$A$1:$AS$1,"<="&BY$1,$A$1:$AS$1,">"&BX$1) -> -2016.597 | BZ81: =+SUMIFS($A81:$AS81,$A$1:$AS$1,"<="&BZ$1,$A$1:$AS$1,">"&BY$1) -> -2010.2652 | CA81: =+PROJ!CA65 -> -1995.2862 | CB81: =+PROJ!CB65 -> -1998.2717 | CC81: =+PROJ!CC65 -> -2005.1974 | CD81: =+PROJ!CD65 -> -2015.7342
A82: Depreciation % Imob | B82: =-B81/B11 -> 0.046769727 | C82: =-C81/C11 -> 0.046710396 | D82: =-D81/D11 -> 0.047280811 | E82: =-E81/E11 -> 0.03921889 | F82: =-F81/F11 -> 0.045762828 | G82: =-G81/G11 -> 0.043214252 | H82: =-H81/H11 -> 0.040004962 | I82: =-I81/I11 -> 0.040355115 | ... AS82: =-AS81/AS11 -> 0.034121833 | AU82: 0.040743053 | AW82: =-AW81/AW11 -> 0.059399688 | AX82: =-AX81/AX11 -> 0.057732532 | AY82: =-AY81/AY11 -> 0.058532521 | AZ82: =-AZ81/AZ11 -> 0.05255717 | BA82: =-BA81/BA11 -> 0.059551854 | BB82: =-BB81/BB11 -> 0.067327927 | BC82: =-BC81/BC11 -> 0.068500259 | BD82: =-BD81/BD11 -> 0.062680676 | ... CD82: =-CD81/CD11 -> 0.032851598
BZ83: =+BZ84/BV84-1 -> 0.36808236
A84: EBITDA | B84: =+B78-B81 -> 2458.685 | C84: =+C78-C81 -> 2360.149 | D84: =+D78-D81 -> 2458.251 | E84: =+E78-E81 -> 2342.244 | F84: =+F78-F81 -> 2264.23 | G84: =+G78-G81 -> 2212.047 | H84: =+H78-H81 -> 1933.769 | I84: =+I78-I81 -> 2171.246 | ... AS84: =+AS78-AS81 -> 3877.5065 | AU84: 3672.6968 | AW84: =+AW78-AW81 -> 3554.901 | AX84: =+AX78-AX81 -> 4499.979 | AY84: =+AY78-AY81 -> 5391.918 | AZ84: =+AZ78-AZ81 -> 5923.289 | BA84: =+BA78-BA81 -> 5816.681 | BB84: =+BB78-BB81 -> 5786.37 | BC84: =+BC78-BC81 -> 5646.98 | BD84: =+BD78-BD81 -> 6063.76 | ... CD84: =+CD78-CD81 -> 14895.863
A85: EBITDA Mg. | B85: =+B84/B$11 -> 0.28169062 | C85: =+C84/C$11 -> 0.26724659 | D85: =+D84/D$11 -> 0.28192707 | E85: =+E84/E$11 -> 0.24967509 | F85: =+F84/F$11 -> 0.23757705 | G85: =+G84/G$11 -> 0.23027992 | H85: =+H84/H$11 -> 0.21025492 | I85: =+I84/I$11 -> 0.23019781 | ... AS85: =+AS84/AS$11 -> 0.26909609 | AU85: 0.26276602 | AW85: =+AW84/AW$11 -> 0.34495266 | AX85: =+AX84/AX$11 -> 0.3661578 | AY85: =+AY84/AY$11 -> 0.38879663 | AZ85: =+AZ84/AZ$11 -> 0.37238462 | BA85: =+BA84/BA$11 -> 0.37205435 | BB85: =+BB84/BB$11 -> 0.35949028 | BC85: =+BC84/BC$11 -> 0.33022948 | BD85: =+BD84/BD$11 -> 0.30626738 | ... CD85: =+CD84/CD$11 -> 0.24276658
A86: Chg YoY | F86: =F84/B84-1 -> -0.079089025 | G86: =G84/C84-1 -> -0.062751123 | H86: =H84/D84-1 -> -0.21335576 | I86: =I84/E84-1 -> -0.073006057 | J86: =J84/F84-1 -> 0.076120359 | K86: =K84/G84-1 -> 0.09996623 | L86: =L84/H84-1 -> 0.063230924 | M86: =M84/I84-1 -> -0.014418449 | ... AS86: =AS84/AO84-1 -> 0.044232701 | AU86: 0.048601928 | AX86: =AX84/AW84-1 -> 0.26585213 | AY86: =AY84/AX84-1 -> 0.19820959 | AZ86: =AZ84/AY84-1 -> 0.098549533 | BA86: =BA84/AZ84-1 -> -0.017998109 | BB86: =BB84/BA84-1 -> -0.0052110473 | BC86: =BC84/BB84-1 -> -0.024089369 | BD86: =BD84/BC84-1 -> 0.073805822 | BE86: =BE84/BD84-1 -> 0.096550325 | ... CD86: =CD84/CC84-1 -> 0.0003621052
A87: Chg QoQ | C87: =C84/B84-1 -> -0.040076708 | D87: =D84/C84-1 -> 0.04156602 | E87: =E84/D84-1 -> -0.047190869 | F87: =F84/E84-1 -> -0.033307375 | G87: =G84/F84-1 -> -0.023046687 | H87: =H84/G84-1 -> -0.12580112 | I87: =I84/H84-1 -> 0.12280526 | J87: =J84/I84-1 -> 0.12220541 | ... AS87: =AS84/AR84-1 -> 0.12092385 | AU87: 0.095561816
R88: =+R85-N85 -> 0.042658388 | S88: =+S85-O85 -> 0.021839343 | T88: =+T85-P85 -> 0.0026806152 | U88: =+U85-Q85 -> -0.004906466 | V88: =+V85-R85 -> -0.0071434424 | W88: =+W85-S85 -> -0.038137319 | X88: =+X85-T85 -> -0.059373793 | Y88: =+Y85-U85 -> -0.089467311 | ... AS88: =+AS85-AO85 -> 0.0049562176 | AU88: 0.0084202064
N90: 60 basis points derive from IFRS 16.
A94: Consumidor | G94: 0.87 | H94: 0.86
A95: Professional | G95: 0.09 | H95: 0.1
A96: Exportacion | G96: 0.04 | H96: =+H97-SUM(H94:H95) -> 0.04
A97: Total | G97: =+SUM(G94:G96) -> 1 | H97: 1
BP98: Cost Breakdown | BR98: =+BR99*0.4 -> 0.096 | BU98: =+BU1 -> 44561 | BV98: =+BV1 -> 44926
BP99: Fibers - USD | BR99: 0.24 | BS99: 60 recyc aprox. 60% of recycled fiber is imported. Depende precio | BU99: 0.3 | BV99: 0.3
AP100: {=LINEST(K25:AP25,K57:AP57)} -> #VALUE! | AQ100: {=LINEST(L25:AQ25,L57:AQ57)} -> #VALUE! | AR100: {=LINEST(M25:AR25,M57:AR57)} -> #VALUE! | AS100: {=LINEST(N25:AS25,N57:AS57)} -> 0.03363416 | AT100: 0.0061690406 | AU100: #VALUE! | BP100: Fibers - MXN | BR100: 0.1
BP101: Packaging - USD | BR101: 0.3 | BS101: resins, paints, chemicals, superaborventes | BU101: =30%+0.1 -> 0.4 | BV101: =30%+0.1 -> 0.4
BP102: Finishing prod. - USD | BR102: 0.09
BP103: Finishing prod. - MXN | BR103: 0.04
BP104: Energy - MXN/USD | BR104: 0.09 | BU104: 0.1 | BV104: 0.1
BP105: Labour - MXN | BR105: 0.08 | BU105: 0.12 | BV105: 0.12
BP106: Dep | BR106: 0.06
BP107: TOTAL | BR107: =+SUM(BR99:BR106) -> 1 | BU107: =+SUM(BU99:BU105) -> 0.92 | BV107: =+SUM(BV99:BV105) -> 0.92
BP109: USD | BR109: =+BR99+BR101+BR102 -> 0.63
BP110: MXN | BR110: =+BR100+BR103+BR104+BR105 -> 0.31
BP112: dolar linked | BR112: =+BR109+BR104 -> 0.72
BP114: fiber | BR114: =+BR99+BR100 -> 0.34
BP115: Oil | BR115: =+BR101+BR104 -> 0.39
BP116: labour/others local | BR116: =+BR107-BR115-BR114 -> 0.27
BR117: =+SUM(BR114:BR116) -> 1

Sheet Graficos
V57: y=0.0904x+0.5892

Sheet Raw Materials (2)
B7: ASP | C7: CHINA | D7: CHINA | E7: EUROPA | F7: EUROPA | G7: =+AVERAGE(G69:G108) -> -240.27015 | H7: =+AVERAGE(H69:H108) -> 93.650107 | I7: =+AVERAGE(I69:I108) -> 120.77989 | L7: OIL/PET
B8: Average | C8: HW | D8: SW | E8: HW | F8: SW | G8: China-EU | H8: CHN SW-HW | I8: EUR SW-HW
A9: 35885 | B9: =+A9 -> 35885 | E9: =+E10 -> 469.38
A10: =+EOMONTH(A9,3) -> 35976 | B10: =+A10 -> 35976 | E10: 469.38
A11: =+EOMONTH(A10,3) -> 36068 | B11: =+A11 -> 36068 | E11: 376.97
A12: =+EOMONTH(A11,3) -> 36160 | B12: =+A12 -> 36160 | E12: 360
A13: =+EOMONTH(A12,3) -> 36250 | B13: =+A13 -> 36250 | E13: 391.63
A14: =+EOMONTH(A13,3) -> 36341 | B14: =+A14 -> 36341 | E14: 464.67
A15: =+EOMONTH(A14,3) -> 36433 | B15: =+A15 -> 36433 | E15: 502
A16: =+EOMONTH(A15,3) -> 36525 | B16: =+A16 -> 36525 | E16: 580
A17: =+EOMONTH(A16,3) -> 36616 | B17: =+A17 -> 36616 | E17: 601.09
A18: =+EOMONTH(A17,3) -> 36707 | B18: =+A18 -> 36707 | E18: 650.03
A19: =+EOMONTH(A18,3) -> 36799 | B19: =+A19 -> 36799 | E19: 668.55
A20: =+EOMONTH(A19,3) -> 36891 | B20: =+A20 -> 36891 | E20: 698.14
A21: =+EOMONTH(A20,3) -> 36981 | B21: =+A21 -> 36981 | E21: 572.33
... A68: =+EOMONTH(A67,3) -> 41274 | B68: =+A68 -> 41274 | E68: 775.94
A69: =+'[1] FOEX px'!AJ17 -> 41364 | B69: =+A69 -> 41364 | C69: =+'[1] FOEX px'!AL17 -> 661.33833 | D69: =+'[1] FOEX px'!AM17 -> 665.94417 | E69: =+'[1] FOEX px'!AN17 -> 787.6825 | F69: =+'[1] FOEX px'!AO17 -> 822.49417 | G69: =+C69-E69 -> -126.34417 | H69: =D69-C69 -> 4.6058333 | I69: =+F69-E69 -> 34.811667
A70: =+'[1] FOEX px'!AJ18 -> 41455 | B70: =+A70 -> 41455 | C70: =+'[1] FOEX px'!AL18 -> 695.39667 | D70: =+'[1] FOEX px'!AM18 -> 694.12889 | E70: =+'[1] FOEX px'!AN18 -> 810.80222 | F70: =+'[1] FOEX px'!AO18 -> 847.41667 | G70: =+C70-E70 -> -115.40556 | H70: =D70-C70 -> -1.2677778 | I70: =+F70-E70 -> 36.614444
A71: =+'[1] FOEX px'!AJ19 -> 41547 | B71: =+A71 -> 41547 | C71: =+'[1] FOEX px'!AL19 -> 674.41538 | D71: =+'[1] FOEX px'!AM19 -> 681.51385 | E71: =+'[1] FOEX px'!AN19 -> 794.79077 | F71: =+'[1] FOEX px'!AO19 -> 860.77077 | G71: =+C71-E71 -> -120.37538 | H71: =D71-C71 -> 7.0984615 | I71: =+F71-E71 -> 65.98
A72: =+'[1] FOEX px'!AJ20 -> 41639 | B72: =+A72 -> 41639 | C72: =+'[1] FOEX px'!AL20 -> 658.42231 | D72: =+'[1] FOEX px'!AM20 -> 723.02692 | E72: =+'[1] FOEX px'!AN20 -> 770.21846 | F72: =+'[1] FOEX px'!AO20 -> 892.74615 | G72: =+C72-E72 -> -111.79615 | H72: =D72-C72 -> 64.604615 | I72: =+F72-E72 -> 122.52769
A73: =+'[1] FOEX px'!AJ21 -> 41729 | B73: =+A73 -> 41729 | C73: =+'[1] FOEX px'!AL21 -> 651.48333 | D73: =+'[1] FOEX px'!AM21 -> 750.49083 | E73: =+'[1] FOEX px'!AN21 -> 767.875 | F73: =+'[1] FOEX px'!AO21 -> 915.58417 | G73: =+C73-E73 -> -116.39167 | H73: =D73-C73 -> 99.0075 | I73: =+F73-E73 -> 147.70917 | J73: =+YEAR(A73) -> 2014 | K73: =+B73 -> 41729 | L73: =+'[2]CERV VALOR'!AG9 -> 107.91719 | N73: 2014 | O73: =+SUMIF(J73:L128,N73,L73:L128)/4 -> 99.485637
A74: =+'[1] FOEX px'!AJ22 -> 41820 | B74: =+A74 -> 41820 | C74: =+'[1] FOEX px'!AL22 -> 603.255 | D74: =+'[1] FOEX px'!AM22 -> 736.45583 | E74: =+'[1] FOEX px'!AN22 -> 751.04417 | F74: =+'[1] FOEX px'!AO22 -> 924.41167 | G74: =+C74-E74 -> -147.78917 | H74: =D74-C74 -> 133.20083 | I74: =+F74-E74 -> 173.3675 | J74: =+YEAR(A74) -> 2014 | K74: =+B74 -> 41820 | L74: =+'[2]CERV VALOR'!AG10 -> 109.75369 | N74: =+N73+1 -> 2015 | O74: =+SUMIF(J74:L129,N74,L74:L129)/4 -> 53.60689
A75: =+'[1] FOEX px'!AJ23 -> 41912 | B75: =+A75 -> 41912 | C75: =+'[1] FOEX px'!AL23 -> 585.64857 | D75: =+'[1] FOEX px'!AM23 -> 724.105 | E75: =+'[1] FOEX px'!AN23 -> 728.93214 | F75: =+'[1] FOEX px'!AO23 -> 928.88714 | G75: =+C75-E75 -> -143.28357 | H75: =D75-C75 -> 138.45643 | I75: =+F75-E75 -> 199.955 | J75: =+YEAR(A75) -> 2014 | K75: =+B75 -> 41912 | L75: =+'[2]CERV VALOR'!AG11 -> 103.45621 | N75: =+N74+1 -> 2016 | O75: =+SUMIF(J75:L130,N75,L75:L130)/4 -> 45.115009
A76: =+'[1] FOEX px'!AJ24 -> 42004 | B76: =+A76 -> 42004 | C76: =+'[1] FOEX px'!AL24 -> 598.77462 | D76: =+'[1] FOEX px'!AM24 -> 719.22769 | E76: =+'[1] FOEX px'!AN24 -> 735.19385 | F76: =+'[1] FOEX px'!AO24 -> 932.33077 | G76: =+C76-E76 -> -136.41923 | H76: =D76-C76 -> 120.45308 | I76: =+F76-E76 -> 197.13692 | J76: =+YEAR(A76) -> 2014 | K76: =+B76 -> 42004 | L76: =+'[2]CERV VALOR'!AG12 -> 76.815455 | N76: =+N75+1 -> 2017 | O76: =+SUMIF(J76:L131,N76,L76:L131)/4 -> 54.790423
A77: =+'[1] FOEX px'!AJ25 -> 42094 | B77: =+A77 -> 42094 | C77: =+'[1] FOEX px'!AL25 -> 622.31154 | D77: =+'[1] FOEX px'!AM25 -> 682.24615 | E77: =+'[1] FOEX px'!AN25 -> 749.74692 | F77: =+'[1] FOEX px'!AO25 -> 905.10308 | G77: =+C77-E77 -> -127.43538 | H77: =D77-C77 -> 59.934615 | I77: =+F77-E77 -> 155.35615 | J77: =+YEAR(A77) -> 2015 | K77: =+B77 -> 42094 | L77: =+'[2]CERV VALOR'!AG13 -> 55.16875 | N77: =+N76+1 -> 2018 | O77: =+SUMIF(J77:L132,N77,L77:L132)/4 -> 71.600027
A78: =+'[1] FOEX px'!AJ26 -> 42185 | B78: =+A78 -> 42185 | C78: =+'[1] FOEX px'!AL26 -> 653.56846 | D78: =+'[1] FOEX px'!AM26 -> 665.66 | E78: =+'[1] FOEX px'!AN26 -> 781.47538 | F78: =+'[1] FOEX px'!AO26 -> 854.61385 | G78: =+C78-E78 -> -127.90692 | H78: =D78-C78 -> 12.091538 | I78: =+F78-E78 -> 73.138462 | J78: =+YEAR(A78) -> 2015 | K78: =+B78 -> 42185 | L78: =+'[2]CERV VALOR'!AG14 -> 63.371385 | N78: =+N77+1 -> 2019 | O78: =+SUMIF(J78:L133,N78,L78:L133)/4 -> 64.179489
A79: =+'[1] FOEX px'!AJ27 -> 42277 | B79: =+A79 -> 42277 | C79: =+'[1] FOEX px'!AL27 -> 662.19214 | D79: =+'[1] FOEX px'!AM27 -> 649.11357 | E79: =+'[1] FOEX px'!AN27 -> 804.70071 | F79: =+'[1] FOEX px'!AO27 -> 844.38143 | G79: =+C79-E79 -> -142.50857 | H79: =D79-C79 -> -13.078571 | I79: =+F79-E79 -> 39.680714 | J79: =+YEAR(A79) -> 2015 | K79: =+B79 -> 42277 | L79: =+'[2]CERV VALOR'!AG15 -> 51.299545 | N79: =+N78+1 -> 2020 | O79: =+SUMIF(J79:L134,N79,L79:L134)/4 -> 43.277053
A80: =+'[1] FOEX px'!AJ28 -> 42369 | B80: =+A80 -> 42369 | C80: =+'[1] FOEX px'!AL28 -> 621.68167 | D80: =+'[1] FOEX px'!AM28 -> 614.345 | E80: =+'[1] FOEX px'!AN28 -> 801.59917 | F80: =+'[1] FOEX px'!AO28 -> 818.01333 | G80: =+C80-E80 -> -179.9175 | H80: =D80-C80 -> -7.3366667 | I80: =+F80-E80 -> 16.414167 | J80: =+YEAR(A80) -> 2015 | K80: =+B80 -> 42369 | L80: =+'[2]CERV VALOR'!AG16 -> 44.587879 | N80: =+N79+1 -> 2021 | O80: =+SUMIF(J80:L135,N80,L80:L135)/4 -> 70.770807
A81: =+'[1] FOEX px'!AJ29 -> 42460 | B81: =+A81 -> 42460 | C81: =+'[1] FOEX px'!AL29 -> 553.69385 | D81: =+'[1] FOEX px'!AM29 -> 593.69692 | E81: =+'[1] FOEX px'!AN29 -> 762.43077 | F81: =+'[1] FOEX px'!AO29 -> 791.78308 | G81: =+C81-E81 -> -208.73692 | H81: =D81-C81 -> 40.003077 | I81: =+F81-E81 -> 29.352308 | J81: =+YEAR(A81) -> 2016 | K81: =+B81 -> 42460 | L81: =+'[2]CERV VALOR'!AG17 -> 35.318154 | N81: =+N80+1 -> 2022 | O81: =+SUMIF(J81:L136,N81,L81:L136)/4 -> 95.818032
A82: =+'[1] FOEX px'!AJ30 -> 42551 | B82: =+A82 -> 42551 | C82: =+'[1] FOEX px'!AL30 -> 500.21923 | D82: =+'[1] FOEX px'!AM30 -> 608.20308 | E82: =+'[1] FOEX px'!AN30 -> 693.27308 | F82: =+'[1] FOEX px'!AO30 -> 796.43923 | G82: =+C82-E82 -> -193.05385 | H82: =D82-C82 -> 107.98385 | I82: =+F82-E82 -> 103.16615 | J82: =+YEAR(A82) -> 2016 | K82: =+B82 -> 42551 | L82: =+'[2]CERV VALOR'!AG18 -> 47.027077 | N82: =+N81+1 -> 2023 | O82: =+SUMIF(J82:L137,N82,L82:L137)/4 -> 82.180346
A83: =+'[1] FOEX px'!AJ31 -> 42643 | B83: =+A83 -> 42643 | C83: =+'[1] FOEX px'!AL31 -> 486.66154 | D83: =+'[1] FOEX px'!AM31 -> 600.38615 | E83: =+'[1] FOEX px'!AN31 -> 671.49077 | F83: =+'[1] FOEX px'!AO31 -> 811.16077 | G83: =+C83-E83 -> -184.82923 | H83: =D83-C83 -> 113.72462 | I83: =+F83-E83 -> 139.67 | J83: =+YEAR(A83) -> 2016 | K83: =+B83 -> 42643 | L83: =+'[2]CERV VALOR'!AG19 -> 46.987576 | N83: =+N82+1 -> 2024 | O83: =+SUMIF(J83:L138,N83,L83:L138)/4 -> 79.878715
A84: =+'[1] FOEX px'!AJ32 -> 42735 | B84: =+A84 -> 42735 | C84: =+'[1] FOEX px'!AL32 -> 494.68923 | D84: =+'[1] FOEX px'!AM32 -> 592.89538 | E84: =+'[1] FOEX px'!AN32 -> 655.10769 | F84: =+'[1] FOEX px'!AO32 -> 808.88538 | G84: =+C84-E84 -> -160.41846 | H84: =D84-C84 -> 98.206154 | I84: =+F84-E84 -> 153.77769 | J84: =+YEAR(A84) -> 2016 | K84: =+B84 -> 42735 | L84: =+'[2]CERV VALOR'!AG20 -> 51.127231
A85: =+'[1] FOEX px'!AJ33 -> 42825 | B85: =+A85 -> 42825 | C85: =+'[1] FOEX px'!AL33 -> 559.91385 | D85: =+'[1] FOEX px'!AM33 -> 633.37385 | E85: =+'[1] FOEX px'!AN33 -> 680.46769 | F85: =+'[1] FOEX px'!AO33 -> 816.36462 | G85: =+C85-E85 -> -120.55385 | H85: =D85-C85 -> 73.46 | I85: =+F85-E85 -> 135.89692 | J85: =+YEAR(A85) -> 2017 | K85: =+B85 -> 42825 | L85: =+'[2]CERV VALOR'!AG21 -> 54.608308
A86: =+'[1] FOEX px'!AJ34 -> 42916 | B86: =+A86 -> 42916 | C86: =+'[1] FOEX px'!AL34 -> 618.16923 | D86: =+'[1] FOEX px'!AM34 -> 644.88923 | E86: =+'[1] FOEX px'!AN34 -> 782.79154 | F86: =+'[1] FOEX px'!AO34 -> 860.14615 | G86: =+C86-E86 -> -164.62231 | H86: =D86-C86 -> 26.72 | I86: =+F86-E86 -> 77.354615 | J86: =+YEAR(A86) -> 2017 | K86: =+B86 -> 42916 | L86: =+'[2]CERV VALOR'!AG22 -> 50.870923
A87: =+'[1] FOEX px'!AJ35 -> 43008 | B87: =+A87 -> 43008 | C87: =+'[1] FOEX px'!AL35 -> 643.66385 | D87: =+'[1] FOEX px'!AM35 -> 659.68462 | E87: =+'[1] FOEX px'!AN35 -> 873.24462 | F87: =+'[1] FOEX px'!AO35 -> 894.21385 | G87: =+C87-E87 -> -229.58077 | H87: =D87-C87 -> 16.020769 | I87: =+F87-E87 -> 20.969231 | J87: =+YEAR(A87) -> 2017 | K87: =+B87 -> 43008 | L87: =+'[2]CERV VALOR'!AG23 -> 52.168308
A88: =+'[1] FOEX px'!AJ36 -> 43100 | B88: =+A88 -> 43100 | C88: =+'[1] FOEX px'!AL36 -> 724.14231 | D88: =+'[1] FOEX px'!AM36 -> 831.18462 | E88: =+'[1] FOEX px'!AN36 -> 941.09615 | F88: =+'[1] FOEX px'!AO36 -> 952.95308 | G88: =+C88-E88 -> -216.95385 | H88: =D88-C88 -> 107.04231 | I88: =+F88-E88 -> 11.856923 | J88: =+YEAR(A88) -> 2017 | K88: =+B88 -> 43100 | L88: =+'[2]CERV VALOR'!AG24 -> 61.514154
A89: =+'[1] FOEX px'!AJ37 -> 43190 | B89: =+A89 -> 43190 | C89: =+'[1] FOEX px'!AL37 -> 759.79769 | D89: =+'[1] FOEX px'!AM37 -> 892.46538 | E89: =+'[1] FOEX px'!AN37 -> 1009.0246 | F89: =+'[1] FOEX px'!AO37 -> 1056.13 | G89: =+C89-E89 -> -249.22692 | H89: =D89-C89 -> 132.66769 | I89: =+F89-E89 -> 47.105385 | J89: =+YEAR(A89) -> 2018 | K89: =+B89 -> 43190 | L89: =+'[2]CERV VALOR'!AG25 -> 67.270615
A90: =+'[1] FOEX px'!AJ38 -> 43281 | B90: =+A90 -> 43281 | C90: =+'[1] FOEX px'!AL38 -> 769.04154 | D90: =+'[1] FOEX px'!AM38 -> 892.57923 | E90: =+'[1] FOEX px'!AN38 -> 1044.3808 | F90: =+'[1] FOEX px'!AO38 -> 1159.2462 | G90: =+C90-E90 -> -275.33923 | H90: =D90-C90 -> 123.53769 | I90: =+F90-E90 -> 114.86538 | J90: =+YEAR(A90) -> 2018 | K90: =+B90 -> 43281 | L90: =+'[2]CERV VALOR'!AG26 -> 74.968154
A91: =+'[1] FOEX px'!AJ39 -> 43373 | B91: =+A91 -> 43373 | C91: =+'[1] FOEX px'!AL39 -> 769.80077 | D91: =+'[1] FOEX px'!AM39 -> 867.47692 | E91: =+'[1] FOEX px'!AN39 -> 1050 | F91: =+'[1] FOEX px'!AO39 -> 1226.9085 | G91: =+C91-E91 -> -280.19923 | H91: =D91-C91 -> 97.676154 | I91: =+F91-E91 -> 176.90846 | J91: =+YEAR(A91) -> 2018 | K91: =+B91 -> 43373 | L91: =+'[2]CERV VALOR'!AG27 -> 75.838308
A92: =+'[1] FOEX px'!AJ40 -> 43465 | B92: =+A92 -> 43465 | C92: =+'[1] FOEX px'!AL40 -> 741.04923 | D92: =+'[1] FOEX px'!AM40 -> 826.70385 | E92: =+'[1] FOEX px'!AN40 -> 1045.1669 | F92: =+'[1] FOEX px'!AO40 -> 1223.2954 | G92: =+C92-E92 -> -304.11769 | H92: =D92-C92 -> 85.654615 | I92: =+F92-E92 -> 178.12846 | J92: =+YEAR(A92) -> 2018 | K92: =+B92 -> 43465 | L92: =+'[2]CERV VALOR'!AG28 -> 68.32303
A93: =+'[1] FOEX px'!AJ41 -> 43555 | B93: =+A93 -> 43555 | C93: =+'[1] FOEX px'!AL41 -> 668.27615 | D93: =+'[1] FOEX px'!AM41 -> 702.39154 | E93: =+'[1] FOEX px'!AN41 -> 994.79308 | F93: =+'[1] FOEX px'!AO41 -> 1150.3908 | G93: =+C93-E93 -> -326.51692 | H93: =D93-C93 -> 34.115385 | I93: =+F93-E93 -> 155.59769 | J93: =+YEAR(A93) -> 2019 | K93: =+B93 -> 43555 | L93: =+'[2]CERV VALOR'!AG29 -> 63.676719
A94: =+'[1] FOEX px'!AJ42 -> 43646 | B94: =+A94 -> 43646 | C94: =+'[1] FOEX px'!AL42 -> 648.01615 | D94: =+'[1] FOEX px'!AM42 -> 672.36769 | E94: =+'[1] FOEX px'!AN42 -> 938.30462 | F94: =+'[1] FOEX px'!AO42 -> 1049.41 | G94: =+C94-E94 -> -290.28846 | H94: =D94-C94 -> 24.351538 | I94: =+F94-E94 -> 111.10538 | J94: =+YEAR(A94) -> 2019 | K94: =+B94 -> 43646 | L94: =+'[2]CERV VALOR'!AG30 -> 68.521538
A95: =+'[1] FOEX px'!AJ43 -> 43738 | B95: =+A95 -> 43738 | C95: =+'[1] FOEX px'!AL43 -> 494.50923 | D95: =+'[1] FOEX px'!AM43 -> 570.28462 | E95: =+'[1] FOEX px'!AN43 -> 815.20462 | F95: =+'[1] FOEX px'!AO43 -> 917.09615 | G95: =+C95-E95 -> -320.69538 | H95: =D95-C95 -> 75.775385 | I95: =+F95-E95 -> 101.89154 | J95: =+YEAR(A95) -> 2019 | K95: =+B95 -> 43738 | L95: =+'[2]CERV VALOR'!AG31 -> 62.030455
... A113: =+'[1] FOEX px'!AJ61 -> 45382 | B113: =+A113 -> 45382 | C113: =+'[1] FOEX px'!AL61 -> 656.24417 | D113: =+'[1] FOEX px'!AM61 -> 738.02333 | E113: =+'[1] FOEX px'!AN61 -> 1111.7558 | F113: =+'[1] FOEX px'!AO61 -> 1322.0417 | G113: =+C113-E113 -> -455.51167 | H113: =D113-C113 -> 81.779167 | I113: =+F113-E113 -> 210.28583 | J113: =+YEAR(A113) -> 2024 | K113: =+B113 -> 45382 | L113: =+'[2]CERV VALOR'!AG49 -> 81.771692
A114: =+'[1] FOEX px'!AJ62 -> 45473 | B114: =+A114 -> 45473 | C114: =+'[1] FOEX px'!AL62 -> 718.4 | D114: =+'[1] FOEX px'!AM62 -> 687.32643 | E114: =+'[1] FOEX px'!AN62 -> 1344.4393 | F114: =+'[1] FOEX px'!AO62 -> 1497.2429 | G114: =+C114-E114 -> -626.03929 | H114: =D114-C114 -> -31.073571 | I114: =+F114-E114 -> 152.80357 | J114: =+YEAR(A114) -> 2024 | K114: =+B114 -> 45473 | L114: =+[2]Sheet1!AI50 -> 85.029077
A115: =+'[1] FOEX px'!AJ63 -> 45565 | B115: =+A115 -> 45565 | C115: =+'[1] FOEX px'!AL63 -> 641.57923 | D115: =+'[1] FOEX px'!AM63 -> 773.17385 | E115: =+'[1] FOEX px'!AN63 -> 1375.0138 | F115: =+'[1] FOEX px'!AO63 -> 1605.4046 | G115: =+C115-E115 -> -733.43462 | H115: =D115-C115 -> 131.59462 | I115: =+F115-E115 -> 230.39077 | J115: =+YEAR(A115) -> 2024 | K115: =+B115 -> 45565 | L115: =+[2]Sheet1!AI51 -> 78.708485
A116: =+'[1] FOEX px'!AJ64 -> 45657 | B116: =+A116 -> 45657 | C116: =+'[1] FOEX px'!AL64 -> 552.50077 | D116: =+'[1] FOEX px'!AM64 -> 768.45846 | E116: =+'[1] FOEX px'!AN64 -> 1106.1423 | F116: =+'[1] FOEX px'!AO64 -> 1523.1123 | G116: =+C116-E116 -> -553.64154 | H116: =D116-C116 -> 215.95769 | I116: =+F116-E116 -> 416.97 | J116: =+YEAR(A116) -> 2024 | K116: =+B116 -> 45657 | L116: =+[2]Sheet1!AI52 -> 74.005606
A117: =+'[1] FOEX px'!AJ65 -> 45747 | B117: =+A117 -> 45747 | C117: =+'[1] FOEX px'!AL65 -> 528.83615 | D117: =+'[1] FOEX px'!AM65 -> 791.52231 | E117: =+'[1] FOEX px'!AN65 -> 1064.2823 | F117: =+'[1] FOEX px'!AO65 -> 1500.5408 | G117: =+C117-E117 -> -535.44615 | H117: =D117-C117 -> 262.68615 | I117: =+F117-E117 -> 436.25846 | J117: =+YEAR(A117) -> 2025 | K117: =+B117 -> 45747 | L117: =+[2]Sheet1!AI53 -> 74.972187
A118: =+'[1] FOEX px'!AJ66 -> 45838 | B118: =+A118 -> 45838 | C118: =+'[1] FOEX px'!AL66 -> 552.35615 | D118: =+'[1] FOEX px'!AM66 -> 582.24077 | E118: =+'[1] FOEX px'!AN66 -> 1175.4977 | F118: =+'[1] FOEX px'!AO66 -> 1217.5631 | G118: =+C118-E118 -> -623.14154 | H118: =D118-C118 -> 29.884615 | I118: =+F118-E118 -> 42.065385 | J118: =+YEAR(A118) -> 2025 | K118: =+B118 -> 45838 | L118: =+[2]Sheet1!AI54 -> 66.731077
A119: =+'[1] FOEX px'!AJ67 -> 45930 | B119: =+A119 -> 45930 | C119: =+'[1] FOEX px'!AL67 -> 503.11462 | D119: =+'[1] FOEX px'!AM67 -> 0 | E119: =+'[1] FOEX px'!AN67 -> 1034.7623 | F119: =+'[1] FOEX px'!AO67 -> 1194.5513 | G119: =+C119-E119 -> -531.64769 | H119: =D119-C119 -> -503.11462 | I119: =+F119-E119 -> 159.78896 | J119: =+YEAR(A119) -> 2025 | K119: =+B119 -> 45930 | L119: =+[2]Sheet1!AI55 -> 68.165
A120: =+'[1] FOEX px'!AJ68 -> 46022 | B120: =+A120 -> 46022 | C120: =+'[1] FOEX px'!AL68 -> 532.99077 | D120: =+'[1] FOEX px'!AM68 -> 0 | E120: =+'[1] FOEX px'!AN68 -> 1076.8385 | F120: =+'[1] FOEX px'!AO68 -> 1236.6274 | G120: =+C120-E120 -> -543.84769 | H120: =D120-C120 -> -532.99077 | I120: =+F120-E120 -> 159.78896 | J120: =+YEAR(A120) -> 2025 | K120: =+B120 -> 46022 | L120: =+[2]Sheet1!AI56 -> 63.064545
A121: =+'[1] FOEX px'!AJ69 -> 46112 | B121: =+A121 -> 46112 | C121: =+'[1] FOEX px'!AL69 -> 578.37538 | D121: =+'[1] FOEX px'!AM69 -> 0 | E121: =+'[1] FOEX px'!AN69 -> 1138.2124 | F121: =+'[1] FOEX px'!AO69 -> 1298.0014 | G121: =+C121-E121 -> -559.83701 | H121: =D121-C121 -> -578.37538 | I121: =+F121-E121 -> 159.78896 | J121: =+YEAR(A121) -> 2026 | K121: =+B121 -> 46112 | L121: 68
A122: =+'[1] FOEX px'!AJ70 -> 46203 | B122: =+A122 -> 46203 | C122: =+'[1] FOEX px'!AL70 -> 578.37538 | D122: =+'[1] FOEX px'!AM70 -> 696.77382 | E122: =+'[1] FOEX px'!AN70 -> 1110.1265 | F122: =+'[1] FOEX px'!AO70 -> 1269.9154 | G122: =+C122-E122 -> -531.75109 | H122: =D122-C122 -> 118.39843 | I122: =+F122-E122 -> 159.78896 | J122: =+YEAR(A122) -> 2026 | K122: =+B122 -> 46203 | L122: 70
A123: =+'[1] FOEX px'!AJ71 -> 46295 | B123: =+A123 -> 46295 | C123: =+'[1] FOEX px'!AL71 -> 578.37538 | D123: =+'[1] FOEX px'!AM71 -> 696.77382 | E123: =+'[1] FOEX px'!AN71 -> 1110.1265 | F123: =+'[1] FOEX px'!AO71 -> 1269.9154 | G123: =+C123-E123 -> -531.75109 | H123: =D123-C123 -> 118.39843 | I123: =+F123-E123 -> 159.78896 | J123: =+YEAR(A123) -> 2026 | K123: =+B123 -> 46295 | L123: 75
A124: =+'[1] FOEX px'!AJ72 -> 46387 | B124: =+A124 -> 46387 | C124: =+'[1] FOEX px'!AL72 -> 578.37538 | D124: =+'[1] FOEX px'!AM72 -> 696.77382 | E124: =+'[1] FOEX px'!AN72 -> 1110.1265 | F124: =+'[1] FOEX px'!AO72 -> 1269.9154 | G124: =+C124-E124 -> -531.75109 | H124: =D124-C124 -> 118.39843 | I124: =+F124-E124 -> 159.78896 | J124: =+YEAR(A124) -> 2026 | K124: =+B124 -> 46387 | L124: =+L123 -> 75
A125: =+'[1] FOEX px'!AJ73 -> 46477 | B125: =+A125 -> 46477 | C125: =+'[1] FOEX px'!AL73 -> 578.37538 | D125: =+'[1] FOEX px'!AM73 -> 696.77382 | E125: =+'[1] FOEX px'!AN73 -> 1110.1265 | F125: =+'[1] FOEX px'!AO73 -> 1269.9154 | G125: =+C125-E125 -> -531.75109 | H125: =D125-C125 -> 118.39843 | I125: =+F125-E125 -> 159.78896 | J125: =+YEAR(A125) -> 2027 | K125: =+B125 -> 46477 | L125: =+L124 -> 75
A126: =+'[1] FOEX px'!AJ74 -> 46568 | B126: =+A126 -> 46568 | C126: =+'[1] FOEX px'!AL74 -> 578.37538 | D126: =+'[1] FOEX px'!AM74 -> 696.77382 | E126: =+'[1] FOEX px'!AN74 -> 1110.1265 | F126: =+'[1] FOEX px'!AO74 -> 1269.9154 | G126: =+C126-E126 -> -531.75109 | H126: =D126-C126 -> 118.39843 | I126: =+F126-E126 -> 159.78896 | J126: =+YEAR(A126) -> 2027 | K126: =+B126 -> 46568 | L126: =+L125 -> 75
A127: =+'[1] FOEX px'!AJ75 -> 46660 | B127: =+A127 -> 46660 | C127: =+'[1] FOEX px'!AL75 -> 578.37538 | D127: =+'[1] FOEX px'!AM75 -> 696.77382 | E127: =+'[1] FOEX px'!AN75 -> 1110.1265 | F127: =+'[1] FOEX px'!AO75 -> 1269.9154 | G127: =+C127-E127 -> -531.75109 | H127: =D127-C127 -> 118.39843 | I127: =+F127-E127 -> 159.78896 | J127: =+YEAR(A127) -> 2027 | K127: =+B127 -> 46660 | L127: =+L126 -> 75
A128: =+'[1] FOEX px'!AJ76 -> 46752 | B128: =+A128 -> 46752 | C128: =+'[1] FOEX px'!AL76 -> 578.37538 | D128: =+'[1] FOEX px'!AM76 -> 696.77382 | E128: =+'[1] FOEX px'!AN76 -> 1110.1265 | F128: =+'[1] FOEX px'!AO76 -> 1269.9154 | G128: =+C128-E128 -> -531.75109 | H128: =D128-C128 -> 118.39843 | I128: =+F128-E128 -> 159.78896 | J128: =+YEAR(A128) -> 2027 | K128: =+B128 -> 46752 | L128: =+L127 -> 75

Sheet Previews
C4: 4Q24 EST | D4: Actual | E4: Fundamenta | G4: Cons | I4: Citi | J4: MS | K4: Itau | L4: Bofa
C5: Revenues | D5: 13771 | E5: =+FAT!AK11 -> 13770.504 | F5: =+D5/E5-1 -> 3.6019016e-05 | G5: =+AVERAGE(I5:L5) -> 13703.5 | H5: =+D5/G5-1 -> 0.0049257489 | I5: 13739 | J5: 13728 | K5: 13639 | L5: 13708
C6: yoy growth | D6: 0.03 | E6: =+FAT!AK12 -> 0.029845814 | J6: 0.027 | K6: 0.02 | L6: 0.025
C8: price | E8: =+FAT!AK17 -> 0.024845814 | J8: =+J6-J9 -> 0.02
C9: volume | E9: =+FAT!AK18 -> 0.005 | J9: 0.007
C11: EBITDA | D11: 3502 | E11: =+FAT!AK84 -> 3502.47 | F11: =+D11/E11-1 -> -0.00013419101 | G11: =+AVERAGE(I11:L11) -> 3470.75 | H11: =+D11/G11-1 -> 0.0090038176 | I11: 3446 | J11: 3459 | K11: 3567 | L11: 3411
C12: mrgn | D12: =+D11/D5 -> 0.25430252 | E12: =+FAT!AK85 -> 0.25434581 | F12: =+D12-E12 -> -4.3290649e-05 | G12: =+G11/G5 -> 0.25327471 | H12: =+D12-G12 -> 0.0010278089 | I12: =+I11/I5 -> 0.25081884 | J12: =+J11/J5 -> 0.25196678 | K12: =+K11/K5 -> 0.26152944 | L12: =+L11/L5 -> 0.2488328
C14: NI | D14: 1792 | E14: =+PROJ!AK27 -> 1791.511 | F14: =+D14/E14-1 -> 0.00027295395 | G14: =+AVERAGE(I14:L14) -> 1813.75 | H14: =+D14/G14-1 -> -0.01199173 | I14: 1758 | J14: 1914 | K14: 1845 | L14: 1738

Sheet Comps
I3: Mkt Cap | J3: Avg Vol 30D | N3: % Change | Q3: 52W | W3: Last Rep. | X3: Next Rep.
D4: Name | E4: Ticker | F4: Ctry | G4: Sector | H4: Last | I4: US$mm | J4: # shs | K4: 1d | L4: 5d | M4: 1M | N4: 3M | O4: YTD | P4: YOY | Q4: Low | R4: High | S4: P/BV | T4: P/Sales | U4: P/E | V4: EV/EBITDA | W4: Date | X4: Date
C5: =+E5 & " Equity" -> RB/ LN Equity | D5: =_xll.BDP($C5,"Short_Name") -> #NAME? | E5: RB/ LN | F5: =_xll.BDP($C5,"Country") -> #NAME? | G5: =_xll.BDP($C5,"GICS_SECTOR_NAME") -> #NAME? | H5: =_xll.BDP($C5,"PX_LAST") -> #NAME? | I5: =_xll.BDP($C5,"crncy_adj_mkt_cap","eqy_fund_crncy","USD") -> #NAME? | J5: =_xll.BDP($C5,"volume_avg_30D") -> #NAME? | K5: =(1+_xll.BDP($C5,"CHG_PCT_1d")/100)*(1+AF5)-1 -> #NAME? | L5: =(1+_xll.BDP($C5,"CHG_PCT_5d")/100)*(1+AG5)-1 -> #NAME? | M5: =(1+_xll.BDP($C5,"CHG_PCT_1M")/100)*(1+AH5)-1 -> #NAME? | N5: =(1+_xll.BDP($C5,"CHG_PCT_3M")/100)*(1+AI5)-1 -> #NAME? | O5: =(1+_xll.BDP($C5,"CHG_PCT_YTD")/100)*(1+AJ5)-1 -> #NAME? | P5: =(1+_xll.BDP($C5,"CHG_PCT_1YR")/100)*(1+AK5)-1 -> #NAME? | Q5: =_xll.BDP($C5,"low_52week") -> #NAME? | R5: =_xll.BDP($C5,"high_52week") -> #NAME? | S5: =_xll.BDP($C5,"BEST_PX_BPS_RATIO") -> #NAME? | T5: =_xll.BDP($C5,"PX_to_sales_ratio") -> #NAME? | U5: =_xll.BDP($C5,"BEST_EST_PE_NXT_YR") -> #NAME? | V5: =_xll.BDP($C5,"EST_EV_NEXT_YR_EBITDA") -> #NAME? | W5: =_xll.BDP($C5,"latest_announcement_dt") -> #NAME? | X5: =_xll.BDP($C5,"expected_report_dt") -> #NAME?
C6: =+E6 & " Equity" -> HUVr Equity | D6: =_xll.BDP($C6,"Short_Name") -> #NAME? | E6: HUVr | F6: =_xll.BDP($C6,"Country") -> #NAME? | G6: =_xll.BDP($C6,"GICS_SECTOR_NAME") -> #NAME? | H6: =_xll.BDP($C6,"PX_LAST") -> #NAME? | I6: =_xll.BDP($C6,"crncy_adj_mkt_cap","eqy_fund_crncy","USD") -> #NAME? | J6: =_xll.BDP($C6,"volume_avg_30D") -> #NAME? | K6: =(1+_xll.BDP($C6,"CHG_PCT_1d")/100)*(1+AF6)-1 -> #NAME? | L6: =(1+_xll.BDP($C6,"CHG_PCT_5d")/100)*(1+AG6)-1 -> #NAME? | M6: =(1+_xll.BDP($C6,"CHG_PCT_1M")/100)*(1+AH6)-1 -> #NAME? | N6: =(1+_xll.BDP($C6,"CHG_PCT_3M")/100)*(1+AI6)-1 -> #NAME? | O6: =(1+_xll.BDP($C6,"CHG_PCT_YTD")/100)*(1+AJ6)-1 -> #NAME? | P6: =(1+_xll.BDP($C6,"CHG_PCT_1YR")/100)*(1+AK6)-1 -> #NAME? | Q6: =_xll.BDP($C6,"low_52week") -> #NAME? | R6: =_xll.BDP($C6,"high_52week") -> #NAME? | S6: =_xll.BDP($C6,"BEST_PX_BPS_RATIO") -> #NAME? | T6: =_xll.BDP($C6,"PX_to_sales_ratio") -> #NAME? | U6: =_xll.BDP($C6,"BEST_EST_PE_NXT_YR") -> #NAME? | V6: =_xll.BDP($C6,"EST_EV_NEXT_YR_EBITDA") -> #NAME? | W6: =_xll.BDP($C6,"latest_announcement_dt") -> #NAME? | X6: =_xll.BDP($C6,"expected_report_dt") -> #NAME?
