Workbook
Name Celulose: #REF!
Name Class: #REF!
Name DivLiq: #REF!
Name ebitda03: #REF!
Name ebitda04: #REF!
Name ebitda05: #REF!
Name Economics: #REF!
Name IQ_CH: 110000
Name IQ_CQ: 5000
Name IQ_CY: 10000
Name IQ_DAILY: 500000
Name IQ_FH: 100000
Name IQ_FQ: 500
Name IQ_FY: 1000
Name IQ_LTM: 2000
Name IQ_MONTH: 15000
Name IQ_NTM: 6000
Name IQ_WEEK: 50000
Name IQ_YTD: 3000
Name lucro03: #REF!
Name lucro04: #REF!
Name lucro05: #REF!
Name MercadoInterno: #REF!
Name MgBruta: #REF!
Name MgEbitda: #REF!
Name multSecurities_L: #REF!
Name Nacoes: #REF!
Name ROIC: #REF!
Name target: #REF!
Name ticker: OFFSET(#REF!,1,0,COUNTA(#REF!)-1,1)

Sheet VP
B1: FATOR | C1: HOJE | D1: PROJ | E1: DIAS | M1: Preço Gmat3 | N1: {=+_FV(H4,"Price")} -> 15.6 | P1: Cagr | Q1: =+((Resumo!Z22/Resumo!U22)^(1/5))-1 -> 0.12646648
B2: =(1+WACC!I3)^(VP!E2/360) -> 1.118457 | C2: =+TODAY() -> 46105 | D2: 46387 | E2: =+DAYS360(C2,D2) -> 277 | H2: CARLA SSFEIR | J2: 55 51 2121 7006 | M2: Mkt Cap | N2: {=+_FV(H4,"Market cap",TRUE)/1000} -> 15706782
C3: FCF | M3: LL 26 | N3: =+Resumo!V22 -> 1334463.9
B4: Soma dos FCF | C4: =+SUM(WACC!I18:M18) -> 5101703.4 | D4: GR% | H4: #VALUE! | M4: P/E 2026 hj | N4: =+N2/N3 -> 11.770106
B5: (+) Perpetuidade | C5: =C30 -> 11102616 | D5: =+I10 -> 0.0825 | M5: Upside | N5: =+N7/N4-1 -> -0.39150761
B6: EV | C6: =+C4+C5 -> 16204320 | I6: LREN
B7: (-) Total Debt | C7: =PROJ!DQ142 -> 373879 | H7: ROE1 | I7: 0.155 | M7: P/E tgt | N7: =+N9*N27+Q9*Q27 -> 7.1620199
B8: (+) Caixa | C8: =PROJ!DQ140 -> 844610 | D8: =+C8-C7 -> 470731 | H8: ROE2 | I8: 0.15
B9: (+) VP Outros Ativos Fin Líquidos | C9: =PROJ!DI141 -> 0 | H9: G1 | I9: =+Resumo!AA22 -> 0.13180825 | M9: Lula | N9: 0.8 | P9: Tarcísio | Q9: =1-N9 -> 0.2
B10: (+) Investimentos | C10: 0 | H10: G2 | I10: =+I15+I14+I16 -> 0.0825
B11: (+) Outros Ativos Não Oper. | C11: 0 | H11: Ke | I11: =+(I17+I14)+(I19*I18) -> 0.1425 | M11: Gmat3 | P11: Gmat3
B12: (-) Opções | C12: 0 | H12: N (moat) | I12: 5 | M12: ROE1 | N12: =+I7 -> 0.155 | P12: ROE1 | Q12: =+N12 -> 0.155
B13: (+) Ajuste Dividendos | C13: =+PROJ!DQ197 -> 783920.48 | M13: ROE2 | N13: =+I8 -> 0.15 | P13: ROE2 | Q13: =+N13 -> 0.15
B14: (-) Minoritários | C14: =PROJ!DG195 -> 0 | H14: INFL | I14: =+MACRO!EJ8 -> 0.0475 | M14: G1 | N14: =+Q1 -> 0.12646648 | P14: G1 | Q14: =+N14 -> 0.12646648
B15: Valor de Mercado Proj | C15: =+C6-C7+C8+C9+C10+C11-C12+C13-C14 -> 17458971 | H15: GDP Perp | I15: 0.015 | M15: G2 | N15: =+N19+N20+N21 -> 0.07 | P15: G2 | Q15: =+Q19+Q20+Q21 -> 0.075
B16: Num Ações | C16: {=+_FV(H4,"Shares outstanding",TRUE)/1000} -> 1006845 | H16: Aj. G2 | I16: 0.02 | M16: Ke | N16: =+(N22+N19)+(N24*N23) -> 0.16 | P16: Ke | Q16: =+(Q22+Q19)+(Q24*Q23) -> 0.13
B17: Cot R$ DEZ/2026PROJ | C17: =+C15/C16 -> 17.340277 | H17: BNTNB | I17: 0.06 | M17: N (moat) | N17: =+I12 -> 5 | P17: N (moat) | Q17: =+N17 -> 5
B18: Cot R$ HOJE PROJ | C18: =C17/B2 -> 15.503749 | H18: ERP | I18: 0.035
B19: Cot R$ 12m | C19: =+C18*(1+WACC!I3) -> 17.931816 | H19: Beta | I19: =+WACC!$I$13 -> 1 | M19: INFL | N19: 0.045 | P19: INFL | Q19: 0.04
B20: Cot R$ HJ | C20: {=+_FV(H4,"Price")} -> 15.6 | M20: GDP Perp | N20: 0.025 | P20: GDP Perp | Q20: 0.035
B21: var% 12m | C21: =+C18/C20-1 -> -0.0061699526 | H21: P/E Target | I21: =+(((1-I9/I7)*(1+I9)*(1-(((1+I9)^I12)/((1+I11)^I12))))/(I11-I9))+(((1-I10/I8)*((1+I9)^I12)*(1+I10))/((I11-I10)*((1+I11)^I12))) -> 8.4732872 | M21: Aj. G2 | N21: 0 | P21: Aj. G2 | Q21: =+N21 -> 0
H22: vs 2025 | I22: =+I21/Resumo!U66-1 -> -0.25185779 | M22: BNTNB | N22: 0.07 | P22: BNTNB | Q22: 0.045
M23: ERP | N23: 0.045 | P23: ERP | Q23: =+N23 -> 0.045
B24: Valor de Mercado hj | C24: =C16*C20 -> 15706782 | M24: Beta | N24: =+I19 -> 1 | P24: Beta | Q24: =+N24 -> 1
B26: Noplat 2030 | C26: =PROJ!DU50 -> 2275634.5
B27: ROIC | C27: 0.2 | M27: P/E Target 2026 | N27: =+(((1-N14/N12)*(1+N14)*(1-(((1+N14)^N17)/((1+N16)^N17))))/(N16-N14))+(((1-N15/N13)*((1+N14)^N17)*(1+N15))/((N16-N15)*((1+N16)^N17))) -> 6.3193448 | P27: P/E Target 2026 | Q27: =+(((1-Q14/Q12)*(1+Q14)*(1-(((1+Q14)^Q17)/((1+Q16)^Q17))))/(Q16-Q14))+(((1-Q15/Q13)*((1+Q14)^Q17)*(1+Q15))/((Q16-Q15)*((1+Q16)^Q17))) -> 10.53272
B28: G | C28: =D5 -> 0.0825 | Q28: =+Q27/Resumo!V66-1 -> -0.10512952
B29: Wacc | C29: =WACC!M3 -> 0.15536952
B30: Perp | C30: =(C26*(1+C28)*(1-C28/C27)/(C29-C28))/WACC!M17 -> 11102616

Sheet WACC
B1: DRE | E1: 2022 | F1: =+E1+1 -> 2023 | G1: =+F1+1 -> 2024 | H1: =+G1+1 -> 2025 | I1: =+H1+1 -> 2026 | J1: =+I1+1 -> 2027 | K1: =+J1+1 -> 2028 | L1: =+K1+1 -> 2029 | M1: =+L1+1 -> 2030
B3: WACC % | I3: =+I4*I5+(1-I4)*(I9) -> 0.15661161 | J3: =+J4*J5+(1-J4)*(J9) -> 0.15871261 | K3: =+K4*K5+(1-K4)*(K9) -> 0.15613107 | L3: =+L4*L5+(1-L4)*(L9) -> 0.15574852 | M3: =+M4*M5+(1-M4)*(M9) -> 0.15536952
B4: Alavancagem | I4: 0 | J4: 0.05 | K4: 0.05 | L4: 0.05 | M4: 0.05
B5: Rdebt % | I5: =+(I6)*(1-I7) -> 0.10258778 | J5: =+(J6)*(1-J7) -> 0.086752212 | K5: =+(K6)*(1-K7) -> 0.082621315 | L5: =+(L6)*(1-L7) -> 0.074970382 | M5: =+(M6)*(1-M7) -> 0.067390352
B6: Debt Bruto % | I6: =+MACRO!EI6*110% -> 0.14575 | J6: =+MACRO!EJ6*110% -> 0.1265 | K6: =+MACRO!EK6*110% -> 0.121 | L6: =+MACRO!EL6*110% -> 0.11 | M6: =+MACRO!EM6*110% -> 0.099
B7: IR % | I7: =PROJ!DQ181 -> 0.2961387 | J7: =PROJ!DR181 -> 0.31421176 | K7: =PROJ!DS181 -> 0.31717922 | L7: =PROJ!DT181 -> 0.31845107 | M7: =PROJ!DU181 -> 0.31928937
B8: US$ %
B9: Requity % | I9: =I10+I13*I11+I12 -> 0.15661161 | J9: =J10+J13*J11+J12 -> 0.1625 | K9: =K10+K13*K11+K12 -> 0.16 | L9: =L10+L13*L11+L12 -> 0.16 | M9: =M10+M13*M11+M12 -> 0.16
B10: Juros Real | I10: 0.07 | J10: =+I10 -> 0.07 | K10: =+J10 -> 0.07 | L10: =+K10 -> 0.07 | M10: =+L10 -> 0.07
B11: Equity risk premium | I11: 0.045 | J11: =+I11 -> 0.045 | K11: =+J11 -> 0.045 | L11: =+K11 -> 0.045 | M11: =+L11 -> 0.045
B12: IPCA | I12: =+MACRO!EI8 -> 0.041611612 | J12: =+MACRO!EJ8 -> 0.0475 | K12: =+MACRO!EK8 -> 0.045 | L12: =+MACRO!EL8 -> 0.045 | M12: =+MACRO!EM8 -> 0.045
B13: Beta | I13: 1 | J13: =+I13 -> 1 | K13: =+J13 -> 1 | L13: =+K13 -> 1 | M13: =+L13 -> 1
B14: US$ % | I14: =(1+MACRO!EI8)/(1+MACRO!EI12)-1 -> 0.01620645 | J14: =(1+MACRO!EJ8)/(1+MACRO!EJ12)-1 -> 0.02195122 | K14: =(1+MACRO!EK8)/(1+MACRO!EK12)-1 -> 0.019512195 | L14: =(1+MACRO!EL8)/(1+MACRO!EL12)-1 -> 0.019512195 | M14: =(1+MACRO!EM8)/(1+MACRO!EM12)-1 -> 0.019512195
P15: perp
B16: FCFF | F16: =+F20 -> -15706782 | I16: =PROJ!DQ57 -> 970236.26 | J16: =PROJ!DR57 -> 1214524.5 | K16: =PROJ!DS57 -> 1450577.2 | L16: =PROJ!DT57 -> 1589706.6 | M16: =PROJ!DU57 -> 1741795.6 | P16: =+M16*(1+VP!$D$5)/(WACC!M3-VP!D5) -> 25874931
B17: FD | I17: 1 | J17: =+I17*(1+J3) -> 1.1587126 | K17: =+J17*(1+K3) -> 1.3396236 | L17: =+K17*(1+L3) -> 1.548268 | M17: =+L17*(1+M3) -> 1.7888217 | P17: =+M17 -> 1.7888217
B18: VP | I18: =+I16/I17 -> 970236.26 | J18: =+J16/J17 -> 1048167.2 | K18: =+K16/K17 -> 1082824.4 | L18: =+L16/L17 -> 1026764.5 | M18: =+M16/M17 -> 973711.13 | P18: =+P16/P17 -> 14464790
B20: FCFE | F20: =-VP!C24 -> -15706782 | G20: =+PROJ!DO62 -> 1011095.3 | I20: =+PROJ!DQ62 -> 821616.19 | J20: =+PROJ!DR62 -> 1102125.9 | K20: =+PROJ!DS62 -> 1419881 | L20: =+PROJ!DT62 -> 1574327.6 | M20: =+PROJ!DU62 -> 1730929.5 | P20: =+M20*(1+VP!$D$5)/(WACC!M3-VP!D5) -> 25713512
E21: IRR | F21: =+IRR(F16:P16,1) -> 0.14957805
B23: Dividendos | G23: =PROJ!DO197 -> 633574.47 | H23: =PROJ!DP197 -> 806561.37 | I23: =PROJ!DQ197 -> 783920.48 | J23: =PROJ!DR197 -> 806181.66 | K23: =PROJ!DS197 -> 871862.74 | L23: =PROJ!DT197 -> 944784.87 | M23: =PROJ!DU197 -> 1026051.6
B24: FD | G24: 1 | H24: =+G24*(1+H9) -> 1 | I24: =+H24*(1+I9) -> 1.1566116 | J24: =+I24*(1+J9) -> 1.344561 | K24: =+J24*(1+K9) -> 1.5596908 | L24: =+K24*(1+L9) -> 1.8092413 | M24: =+L24*(1+M9) -> 2.0987199
B25: VP | G25: =+G23/G24 -> 633574.47 | H25: =+H23/H24 -> 806561.37 | I25: =+I23/I24 -> 677773.31 | J25: =+J23/J24 -> 599587.27 | K25: =+K23/K24 -> 558997.18 | L25: =+L23/L24 -> 522199.49 | M25: =+M23/M24 -> 488894.02
B27: ROIC | E27: =PROJ!DM255 -> 0.14251749 | F27: =PROJ!DN255 -> 0.089808936 | G27: =PROJ!DO255 -> 0.11115528 | H27: =PROJ!DP255 -> 0.14750077 | I27: =PROJ!DQ255 -> 0.13296108 | J27: =PROJ!DR255 -> 0.17418864 | K27: =PROJ!DS255 -> 0.18717398 | L27: =PROJ!DT255 -> 0.19639868 | M27: =PROJ!DU255 -> 0.20471241
B28: EVA | E28: =+E27-E3 -> 0.14251749 | F28: =+F27-F3 -> 0.089808936 | G28: =+G27-G3 -> 0.11115528 | H28: =+H27-H3 -> 0.14750077 | I28: =+I27-I3 -> -0.023650536 | J28: =+J27-J3 -> 0.015476033 | K28: =+K27-K3 -> 0.031042915 | L28: =+L27-L3 -> 0.040650156 | M28: =+M27-M3 -> 0.049342893
B31: Net Debt | E31: =PROJ!DM111+PROJ!DM120-PROJ!DM90 -> -1679208.3 | F31: =PROJ!DN111+PROJ!DN120-PROJ!DN90 -> -1430312.2 | G31: =PROJ!DO111+PROJ!DO120-PROJ!DO90 -> -1403670 | H31: =PROJ!DP111+PROJ!DP120-PROJ!DP90 -> -519500.96 | I31: =PROJ!DQ111+PROJ!DQ120-PROJ!DQ90 -> -844610 | J31: =PROJ!DR111+PROJ!DR120-PROJ!DR90 -> -1141127.4 | K31: =PROJ!DS111+PROJ!DS120-PROJ!DS90 -> -1982886.1 | L31: =PROJ!DT111+PROJ!DT120-PROJ!DT90 -> -2821288.8 | M31: =PROJ!DU111+PROJ!DU120-PROJ!DU90 -> -3749724.3
B33: NET DEBT/COI | E33: =E31/PROJ!DM138 -> -0.19739162 | F33: =F31/PROJ!DN138 -> -0.17244006 | G33: =G31/PROJ!DO138 -> -0.17006787 | H33: =H31/PROJ!DP138 -> -0.0574352 | I33: =I31/PROJ!DQ138 -> -0.090669214 | J33: =J31/PROJ!DR138 -> -0.11645983 | K33: =K31/PROJ!DS138 -> -0.1929761 | L33: =L31/PROJ!DT138 -> -0.26084539 | M33: =M31/PROJ!DU138 -> -0.32844612
B34: CAIXA/COI | E34: =PROJ!DM90/PROJ!DM138 -> 0.33482485 | F34: =PROJ!DN90/PROJ!DN138 -> 0.30528336 | G34: =PROJ!DO90/PROJ!DO138 -> 0.23336641 | H34: =PROJ!DP90/PROJ!DP138 -> 0.0574352 | I34: =PROJ!DQ90/PROJ!DQ138 -> 0.090669214 | J34: =PROJ!DR90/PROJ!DR138 -> 0.11645983 | K34: =PROJ!DS90/PROJ!DS138 -> 0.1929761 | L34: =PROJ!DT90/PROJ!DT138 -> 0.26084539 | M34: =PROJ!DU90/PROJ!DU138 -> 0.32844612
B35: NET DEBT/BV | E35: =E31/(PROJ!DM126+PROJ!DM127) -> -0.16646402 | F35: =F31/(PROJ!DN126+PROJ!DN127) -> -0.14235899 | G35: =G31/(PROJ!DO126+PROJ!DO127) -> -0.13029578 | H35: =H31/(PROJ!DP126+PROJ!DP127) -> -0.049812962 | I35: =I31/(PROJ!DQ126+PROJ!DQ127) -> -0.076925562 | J35: =J31/(PROJ!DR126+PROJ!DR127) -> -0.095347009 | K35: =K31/(PROJ!DS126+PROJ!DS127) -> -0.15071707 | L35: =L31/(PROJ!DT126+PROJ!DT127) -> -0.19459788 | M35: =M31/(PROJ!DU126+PROJ!DU127) -> -0.23454225
B36: PAY OUT | E36: =PROJ!DM194 -> 0.25177162 | F36: =PROJ!DN194 -> 0 | G36: =PROJ!DO194 -> 0 | H36: =PROJ!DP194 -> 0 | I36: =PROJ!DQ194 -> 0 | J36: =PROJ!DR194 -> 0 | K36: =PROJ!DS194 -> 0 | L36: =PROJ!DT194 -> 0 | M36: =PROJ!DU194 -> 0
B37: Alavancagem Proj | E37: =-E31/(E31+E38) -> -1 | F37: =-F31/(F31+F38) -> -1 | G37: =-G31/(G31+G38) -> -1 | H37: =-H31/(H31+H38) -> -1 | I37: =-I31/(I31+I38) -> -1 | J37: =-J31/(J31+J38) -> -1 | K37: =-K31/(K31+K38) -> -1 | L37: =-L31/(L31+L38) -> -1 | M37: =-M31/(M31+M38) -> -1
B38: VM Proj

Sheet Resumo
B2: Lojas Renner | T2: =+TODAY() -> 46105 | U2: Preço: | V2: =+VP!C20 -> 15.6 | AC2: Bofa | AH2: Bofa | AK2: Itau | AO2: MS | AR2: BTG
B3: DRE | C3: 39447 | D3: =C3+365 -> 39812 | E3: =D3+365 -> 40177 | F3: =E3+365 -> 40542 | G3: =F3+365 -> 40907 | H3: =G3+365 -> 41272 | I3: =H3+365 -> 41637 | J3: =I3+365 -> 42002 | K3: =J3+365 -> 42367 | ... M3: =L3+365 -> 43097 | N3: 2018 | O3: =+N3+1 -> 2019 | P3: =+O3+1 -> 2020 | Q3: =+P3+1 -> 2021 | R3: =+Q3+1 -> 2022 | S3: =+R3+1 -> 2023 | T3: =+S3+1 -> 2024 | U3: =+T3+1 -> 2025 | V3: =+U3+1 -> 2026 | ... Z3: =+Y3+1 -> 2030 | AC3: 2025 | AD3: 2026 | AH3: 2025 | AI3: 2026 | AK3: 2025 | AL3: 2026 | AO3: 2025 | AP3: 2026 | AR3: 2025 | AS3: 2026
B4: Receita Líquida | C4: =+PROJ!CX6 -> 1930939 | D4: =+PROJ!CY6 -> 2183007 | E4: =+PROJ!CZ6 -> 2363628 | F4: =+PROJ!DA6 -> 2751338 | G4: =+PROJ!DB6 -> 3238542 | H4: =+PROJ!DC6 -> 3862508 | I4: =+PROJ!DD6 -> 4370382 | J4: =+PROJ!DE6 -> 5216044 | ... Z4: =+PROJ!DU6 -> 22297186 | AA4: 15837000 | AB4: Net Revenues | AC4: =+AVERAGE(AH4,AK4,AO4,AR4) -> 15291 | AD4: =+AVERAGE(AI4,AL4,AP4,AS4) -> 16260 | AE4: =+(U4/1000)/AC4-1 -> 0.034362134 | AF4: =+(V4/1000)/AD4-1 -> 0.038202688 | AH4: 15291 | AI4: 16260
B5: y-o-y | D5: =+D4/C4-1 -> 0.13054167 | E5: =+E4/D4-1 -> 0.082739542 | F5: =+F4/E4-1 -> 0.16403173 | G5: =+G4/F4-1 -> 0.17707893 | H5: =+H4/G4-1 -> 0.1926688 | I5: =+I4/H4-1 -> 0.13148814 | J5: =+J4/I4-1 -> 0.19349842 | K5: =+K4/J4-1 -> 0.17813385 | ... Z5: =+Z4/Y4-1 -> 0.068194097 | AA5: =+AA4/T4-1 -> 0.097021231 | AH5: =+AH4/($T4/1000)-1 -> 0.059200078 | AI5: =+AI4/AH4-1 -> 0.06337061
B6: Mercadorias | C6: =+FAT!CY30 -> 1751728 | D6: =+FAT!CZ30 -> 1956021 | E6: =+FAT!DA30 -> 2115969 | F6: =+FAT!DB30 -> 2462684 | G6: =+FAT!DC30 -> 2896616 | H6: =+FAT!DD30 -> 3461960 | I6: =+FAT!DE30 -> 3913806 | J6: =+FAT!DF30 -> 4642612 | ... Z6: =+FAT!DV30 -> 20109365 | AC6: =+AVERAGE(AH6,AK6,AO6,AR6) -> 13710.833 | AD6: =+AVERAGE(AI6,AL6,AP6,AS6) -> 14979.3 | AE6: =+(U6/1000)/AC6-1 -> 0.010709809 | AF6: =+(V6/1000)/AD6-1 -> -0.0079122065 | AK6: 13508 | AL6: 14661 | AO6: 13711 | AP6: 14976 | AR6: 13913.5 | AS6: 15300.9
B7: y-o-y | D7: =+D6/C6-1 -> 0.1166237 | E7: =+E6/D6-1 -> 0.081772128 | F7: =+F6/E6-1 -> 0.16385637 | G7: =+G6/F6-1 -> 0.17620287 | H7: =+H6/G6-1 -> 0.19517395 | I7: =+I6/H6-1 -> 0.13051739 | J7: =+J6/I6-1 -> 0.18621414 | K7: =+K6/J6-1 -> 0.17409165 | ... Z7: =+Z6/Y6-1 -> 0.07563575 | AC7: =+AC6/($T6/1000)-1 -> 0.08198291 | AD7: =+AD6/AC6-1 -> 0.092515651 | AK7: =+AK6/($T6/1000)-1 -> 0.065976428 | AL7: =+AL6/AK6-1 -> 0.085356826 | AO7: =+AO6/($T6/1000)-1 -> 0.081996062 | AP7: =+AP6/AO6-1 -> 0.092261688 | AR7: =+AR6/($T6/1000)-1 -> 0.097976239 | AS7: =+AS6/AR6-1 -> 0.099716103
B8: Prod/Serv Financeiros | C8: =+FAT!CY21 -> -9755 | D8: =+FAT!CZ21 -> -13038 | E8: =+FAT!DA21 -> -13703 | F8: =+FAT!DB21 -> -17480.113 | G8: =+FAT!DC21 -> -20583.276 | H8: =+FAT!DD21 -> -24096.251 | I8: =+FAT!DE21 -> -27465.241 | J8: =+FAT!DF21 -> -34494.49 | ... M8: =+FAT!DI21 -> -71380 | N8: =+FAT!DJ34 -> 941108 | O8: =+FAT!DK34 -> 1113744 | P8: =+FAT!DL34 -> 876609 | Q8: =+FAT!DM34 -> 1015829.7 | R8: =+FAT!DN34 -> 1695342 | S8: =+FAT!DO34 -> 1941509 | T8: =+FAT!DP34 -> 1764416 | U8: =+FAT!DQ34 -> 1958757.7 | ... Z8: =+FAT!DV34 -> 2187820.5
B9: y-o-y | D9: =+D8/C8-1 -> 0.33654536 | E9: =+E8/D8-1 -> 0.051004755 | F9: =+F8/E8-1 -> 0.2756413 | G9: =+G8/F8-1 -> 0.17752535 | H9: =+H8/G8-1 -> 0.17067133 | I9: =+I8/H8-1 -> 0.13981388 | J9: =+J8/I8-1 -> 0.25593253 | K9: =+K8/J8-1 -> 0.21085927 | ... Z9: =+Z8/Y8-1 -> 0.0043285472
B10: SSS | C10: =+FAT!CY300 -> 0.086 | D10: =+FAT!CZ300 -> 0.030970467 | E10: =+FAT!DA300 -> 0.019657924 | F10: =+FAT!DB300 -> 0.10374443 | G10: =+FAT!DC300 -> 0.072061827 | H10: =+FAT!DD300 -> 0.090480665 | I10: =+FAT!DE300 -> 0.058862534 | J10: =+FAT!DF300 -> 0.11259133 | ... Z10: =+FAT!DV300 -> 0.05
B11: CPV | C11: =+PROJ!CX7 -> -906712 | D11: =+PROJ!CY7 -> -1022536 | E11: =+PROJ!CZ7 -> -1084911 | F11: =+PROJ!DA7 -> -1209458 | G11: =+PROJ!DB7 -> -1396128 | H11: =+PROJ!DC7 -> -1634247 | I11: =+PROJ!DD7 -> -1867642 | J11: =+PROJ!DE7 -> -2164764 | ... Z11: =+PROJ!DU7 -> -8872728.5 | AO11: -6111 | AP11: -6644
B12: Lucro Bruto | C12: =+PROJ!CX8 -> 1024227 | D12: =+PROJ!CY8 -> 1160471 | E12: =+PROJ!CZ8 -> 1278717 | F12: =+PROJ!DA8 -> 1541880 | G12: =+PROJ!DB8 -> 1842414 | H12: =+PROJ!DC8 -> 2228261 | I12: =+PROJ!DD8 -> 2502740 | J12: =+PROJ!DE8 -> 3051280 | ... Z12: =+PROJ!DU8 -> 13424457 | AA12: 9783 | AB12: Gross Profit | AC12: =+AVERAGE(AH12,AK12,AO12,AR12) -> 7585.5667 | AD12: =+AVERAGE(AI12,AL12,AP12,AS12) -> 8330.7 | AE12: =+(U12/1000)/AC12-1 -> 0.27754952 | AF12: =+(V12/1000)/AD12-1 -> 0.23989914 | AK12: 7474 | AL12: 8196 | AO12: =+AO11+AO6 -> 7600 | AP12: =+AP11+AP6 -> 8332 | AR12: 7682.7 | AS12: 8464.1
B13: Mg Bruta | C13: =+C12/C4 -> 0.5304295 | D13: =+D12/D4 -> 0.53159289 | E13: =+E12/E4 -> 0.54099757 | F13: =+F12/F4 -> 0.56041097 | G13: =+G12/G4 -> 0.5689023 | H13: =+H12/H4 -> 0.57689486 | I13: =+I12/I4 -> 0.57265932 | J13: =+J12/J4 -> 0.58497973 | ... Z13: =+Z12/Z4 -> 0.60206957 | AA13: =1897-AA12 -> -7886 | AB13: mg | AC13: =+AC12/AC6 -> 0.55325351 | AD13: =+AD12/AD6 -> 0.55614748 | AK13: =+AK12/AK6 -> 0.55330175 | AL13: =+AL12/AL6 -> 0.55903417 | AO13: =+AO12/AO6 -> 0.55429947 | AP13: =+AP12/AP6 -> 0.55635684 | AR13: =+AR12/AR6 -> 0.55217594 | AS13: =+AS12/AS6 -> 0.55317661
B14: Mg Bruta retail | C14: =+FAT!CY54 -> 0.48238996 | D14: =+FAT!CZ54 -> 0.4772367 | E14: =+FAT!DA54 -> 0.50105696 | F14: =+FAT!DB54 -> 0.51988724 | G14: =+FAT!DC54 -> 0.52518663 | H14: =+FAT!DD54 -> 0.5330931 | I14: =+FAT!DE54 -> 0.52710814 | J14: =+FAT!DF54 -> 0.53837603 | ... Z14: =+FAT!DV54 -> 0.55743365 | AA14: -13212000
B15: SG&A | C15: =+PROJ!CX10 -> -823249 | D15: =+PROJ!CY10 -> -960711 | E15: =+PROJ!CZ10 -> -1008098 | F15: =+PROJ!DA10 -> -1130353 | G15: =+PROJ!DB10 -> -1366159 | H15: =+PROJ!DC10 -> -1669011 | I15: =+PROJ!DD10 -> -1852306 | J15: =+PROJ!DE10 -> -2060398.2 | ... Z15: =+PROJ!DU10 -> -10214423 | AA15: -1172000 | AB15: SG&A | AC15: =+AVERAGE(AH15,AK15,AO15,AR15) -> -6019.4667 | AD15: =+AVERAGE(AI15,AL15,AP15,AS15) -> -6508 | AE15: =+(U15/1000)/AC15-1 -> 0.31831498 | AF15: =+(V15/1000)/AD15-1 -> 0.32466353 | AK15: =+AK17-AK12 -> -6085 | AL15: =+AL17-AL12 -> -6594 | AO15: =+AO17-AO12 -> -5916 | AP15: =+AP17-AP12 -> -6400 | AR15: =+AR17-AR12 -> -6057.4 | AS15: =+AS17-AS12 -> -6530
B16: % rec liquida | N16: =+N15/N4 -> -0.44124895 | O16: =+O15/O4 -> -0.43610205 | P16: =+P15/P4 -> -0.45862392 | Q16: =+Q15/Q4 -> -0.50687277 | R16: =+R15/R4 -> -0.49561805 | S16: =+S15/S4 -> -0.53719271 | T16: =+T15/T4 -> -0.51831645 | U16: =+U15/U4 -> -0.50172842 | ... Z16: =+Z15/Z4 -> -0.45810367 | AA16: =+AA15+AA14 -> -14384000
B17: EBIT | C17: =+PROJ!CX17 -> 200978 | D17: =+PROJ!CY17 -> 199760 | E17: =+PROJ!CZ17 -> 270619 | F17: =+PROJ!DA17 -> 411527 | G17: =+PROJ!DB17 -> 476255 | H17: =+PROJ!DC17 -> 559250 | I17: =+PROJ!DD17 -> 650434 | J17: =+PROJ!DE17 -> 990881.79 | ... Z17: =+PROJ!DU17 -> 3210034.4 | AB17: Adj EBIT | AC17: =+AVERAGE(AH17,AK17,AO17,AR17) -> 1575.325 | AD17: =+AVERAGE(AI17,AL17,AP17,AS17) -> 1839.775 | AE17: =+(U17/1000)/AC17-1 -> 0.11429958 | AF17: =+(V17/1000)/AD17-1 -> -0.071453021 | AH17: 1603 | AI17: 1891 | AK17: 1389 | AL17: 1602 | AO17: 1684 | AP17: 1932 | AR17: 1625.3 | AS17: 1934.1
B18: Resultado Financeiro | C18: =+PROJ!CX18 -> -14000 | D18: =+PROJ!CY18 -> -6200 | E18: =+PROJ!CZ18 -> -11800 | F18: =+PROJ!DA18 -> 16538 | G18: =+PROJ!DB18 -> 5913 | H18: =+PROJ!DC18 -> -50430 | I18: =+PROJ!DD18 -> -67724 | J18: =+PROJ!DE18 -> -93874 | ... Z18: =+PROJ!DU18 -> 3980.9085 | AC18: =+AVERAGE(AH18,AK18,AO18,AR18) -> -26.325 | AD18: =+AVERAGE(AI18,AL18,AP18,AS18) -> -5.85 | AH18: =+AH19-AH17 -> 41 | AI18: =+AI19-AI17 -> 77 | AK18: =+AK19-AK17 -> 30 | AL18: =+AL19-AL17 -> 56 | AO18: -87 | AP18: -73 | AR18: =+AR19-AR17 -> -89.3 | AS18: =+AS19-AS17 -> -83.4
B19: LAIR | C19: =+PROJ!#REF! -> #REF! | D19: =+PROJ!#REF! -> #REF! | E19: =+PROJ!#REF! -> #REF! | F19: =+PROJ!#REF! -> #REF! | G19: =+PROJ!#REF! -> #REF! | H19: =+PROJ!#REF! -> #REF! | I19: =+PROJ!#REF! -> #REF! | J19: =+PROJ!#REF! -> #REF! | ... M19: =+PROJ!#REF! -> #REF! | N19: =+PROJ!DI22 -> 1370193.6 | O19: =+PROJ!DJ22 -> 1491984 | P19: =+PROJ!DK22 -> 1200731 | Q19: =+PROJ!DL22 -> 640140.15 | R19: =+PROJ!DM22 -> 1384284 | S19: =+PROJ!DN22 -> 840667 | T19: =+PROJ!DO22 -> 1320997 | U19: =+PROJ!DP22 -> 1637247.4 | ... Z19: =+PROJ!DU22 -> 3214015.4 | AC19: =+AVERAGE(AH19,AK19,AO19,AR19) -> 1549 | AD19: =+AVERAGE(AI19,AL19,AP19,AS19) -> 1833.925 | AE19: =+(U19/1000)/AC19-1 -> 0.056970541 | AF19: =+(V19/1000)/AD19-1 -> -0.14604112 | AH19: 1644 | AI19: 1968 | AK19: 1419 | AL19: 1658 | AO19: =+AO18+AO17 -> 1597 | AP19: =+AP18+AP17 -> 1859 | AR19: 1536 | AS19: 1850.7
B20: IR & CS | C20: =+PROJ!CX23 -> -57055 | D20: =+PROJ!CY23 -> -62750 | E20: =+PROJ!CZ23 -> -82278 | F20: =+PROJ!DA23 -> -123743 | G20: =+PROJ!DB23 -> -138486 | H20: =+PROJ!DC23 -> -153420 | I20: =+PROJ!DD23 -> -175310 | J20: =+PROJ!DE23 -> -236755 | ... Z20: =+PROJ!DU23 -> -698593.57 | AC20: =+AVERAGE(AH20,AK20,AO20,AR20) -> -205.275 | AD20: =+AVERAGE(AI20,AL20,AP20,AS20) -> -288.65 | AE20: =+(U20/1000)/AC20-1 -> 0.21997052 | AF20: =+(V20/1000)/AD20-1 -> -0.19753127 | AH20: =+AH22-AH19 -> -213 | AI20: =+AI22-AI19 -> -319 | AK20: =+AK22-AK19 -> -185 | AL20: =+AL22-AL19 -> -249 | AO20: =+AO22-AO19 -> -162 | AP20: =+AP22-AP19 -> -272 | AR20: =+AR22-AR19 -> -261.1 | AS20: =+AS22-AS19 -> -314.6
B21: tax rate | N21: =+N20/N19 -> -0.25547993 | O21: =+O20/O19 -> -0.2719741 | P21: =+P20/P19 -> -0.087023655 | Q21: =+Q20/Q19 -> -0.010530506 | R21: =+R20/R19 -> -0.066880062 | S21: =+S20/S19 -> 0.16129097 | T21: =+T20/T19 -> -0.094117549 | U21: =+U20/U19 -> -0.15295761 | ... Z21: =+Z20/Z19 -> -0.2173585 | AC21: =+AC20/AC19 -> -0.13252098 | AD21: =+AD20/AD19 -> -0.15739466 | AH21: =+AH20/AH19 -> -0.12956204 | AI21: =+AI20/AI19 -> -0.1620935 | AK21: =+AK20/AK19 -> -0.1303735 | AL21: =+AL20/AL19 -> -0.15018094 | AO21: =+AO20/AO19 -> -0.1014402 | AP21: =+AP20/AP19 -> -0.14631522 | AR21: =+AR20/AR19 -> -0.16998698 | AS21: =+AS20/AS19 -> -0.16998973
B22: Lucro Líquido | C22: =+PROJ!CX25 -> 129923 | D22: =+PROJ!CY25 -> 130810 | E22: =+PROJ!CZ25 -> 176541 | F22: =+PROJ!DA25 -> 304322 | G22: =+PROJ!DB25 -> 343682 | H22: =+PROJ!DC25 -> 355400 | I22: =+PROJ!DD25 -> 407400 | J22: =+PROJ!DE25 -> 660252.79 | ... Z22: =+PROJ!DU25 -> 2515421.8 | AA22: =+(Z22/T22)^(1/6)-1 -> 0.13180825 | AB22: Net Income | AC22: =+AVERAGE(AH22,AK22,AO22,AR22) -> 1343.725 | AD22: =+AVERAGE(AI22,AL22,AP22,AS22) -> 1545.275 | AE22: =+(U22/1000)/AC22-1 -> 0.032069747 | AF22: =+(V22/1000)/AD22-1 -> -0.136423 | AH22: 1431 | AI22: 1649 | AK22: 1234 | AL22: 1409 | AO22: 1435 | AP22: 1587 | AR22: 1274.9 | AS22: 1536.1
B23: y-o-y | D23: =+D22/C22-1 -> 0.0068271207 | E23: =+E22/D22-1 -> 0.34959865 | F23: =+F22/E22-1 -> 0.72380354 | G23: =+G22/F22-1 -> 0.12933669 | H23: =+H22/G22-1 -> 0.034095472 | I23: =+I22/H22-1 -> 0.14631401 | J23: =+J22/I22-1 -> 0.62064995 | K23: =+K22/J22-1 -> -0.12330784 | ... Z23: =+Z22/Y22-1 -> 0.10012739
B24: Resultado nao Operacional | N24: =+PROJ!DI31 -> -6130.6034 | O24: =+PROJ!DJ31 -> -23768 | P24: =+PROJ!DK31 -> -19977 | Q24: =+PROJ!DL31 -> -8994 | R24: =+PROJ!DM31 -> 0 | S24: =+PROJ!DN31 -> 0 | T24: =+PROJ!DO31 -> 0 | U24: =+PROJ!DP31 -> 0 | ... Z24: =+PROJ!DU31 -> 0
B27: Recup Credito Fiscal | Q27: =+Q57 -> 0 | R27: =+R57 -> 110064 | S27: =+S57 -> 219246 | T27: =+T57 -> 149681 | U27: =+U57 -> 79941.087 | V27: =+V57 -> 84405.879 | W27: =+W57 -> 91459.374 | X27: =+X57 -> 97700.936 | ... Z27: =+Z57 -> 111485.93
B28: Subv ICMS (cred presum) | N28: =+PROJ!DI216 -> 0 | O28: =+PROJ!DJ216 -> 43088 | P28: =+PROJ!DK216 -> 27445 | Q28: =+PROJ!DL216 -> 98384 | R28: =+PROJ!DM216 -> 127983 | S28: =+PROJ!DN216 -> 141639 | T28: =+PROJ!DO216 -> 45947 | U28: =+PROJ!DP216 -> 39560.193 | ... Z28: =+PROJ!DU216 -> 55801.091
B29: LL adj | N29: =+N22-N28-N27 -> 1020136.7 | O29: =+O22-O28-O27 -> 1043115 | P29: =+P22-P28-P27 -> 1068794 | Q29: =+Q22-Q28-Q27 -> 535015.15 | R29: =+R22-R28-R27 -> 1053656 | S29: =+S22-S28-S27 -> 615374 | T29: =+T22-T28-T27 -> 1001040 | U29: =+U22-U28-U27 -> 1267316.6 | ... Z29: =+Z22-Z28-Z27 -> 2348134.8 | AC29: 22219
B30: y-o-y | D30: =+D29/C29-1 -> #DIV/0! | E30: =+E29/D29-1 -> #DIV/0! | F30: =+F29/E29-1 -> #DIV/0! | G30: =+G29/F29-1 -> #DIV/0! | H30: =+H29/G29-1 -> #DIV/0! | I30: =+I29/H29-1 -> #DIV/0! | J30: =+J29/I29-1 -> #DIV/0! | K30: =+K29/J29-1 -> #DIV/0! | ... Z30: =+Z29/Y29-1 -> 0.10247541 | AC30: 7102 | AD30: 7800
AC31: =+AC30*9 -> 63918 | AD31: =+$AC$29/AD30 -> 2.8485897
AC32: BAP
B34: FLUXO DE CAIXA FIRMA | C34: =C3 -> 39447 | D34: =D3 -> 39812 | E34: =E3 -> 40177 | F34: =F3 -> 40542 | G34: =G3 -> 40907 | H34: =H3 -> 41272 | I34: =I3 -> 41637 | J34: =J3 -> 42002 | ... Z34: =Z3 -> 2030
B35: EBITDA Div | C35: =+PROJ!CX39 -> 200978 | D35: =+PROJ!CY39 -> 199760 | E35: =+PROJ!CZ39 -> 270619 | F35: =+PROJ!DA39 -> 411527 | G35: =+PROJ!DB39 -> 476255 | H35: =+PROJ!DC39 -> 559250 | I35: =+PROJ!DD39 -> 650434 | J35: =+PROJ!DE39 -> 1203613.8 | ... M35: =+PROJ!DH39 -> 1416291 | N35: =+FAT!DJ148 -> 1738395.6 | O35: =+FAT!DK148 -> 2338130 | P35: =+FAT!DL148 -> 1616520 | Q35: =+FAT!DM148 -> 1691247.2 | R35: =+FAT!DN148 -> 2401250 | S35: =+FAT!DO148 -> 1939321 | T35: =+FAT!DP148 -> 2457187 | U35: =+FAT!DQ148 -> 2998339.1 | ... Z35: =+FAT!DV148 -> 4824764.2 | AB35: EBITDA
B36: y-o-y | D36: =+D35/C35-1 -> -0.0060603648 | E36: =+E35/D35-1 -> 0.35472066 | F36: =+F35/E35-1 -> 0.52068776 | G36: =+G35/F35-1 -> 0.15728737 | H36: =+H35/G35-1 -> 0.17426589 | I36: =+I35/H35-1 -> 0.16304694 | J36: =+J35/I35-1 -> 0.85047797 | K36: =+K35/J35-1 -> -0.0046363882 | ... Z36: =+Z35/Y35-1 -> 0.088598014 | AB36: yoy
B37: Mg EBITDA | C37: =+C35/C4 -> 0.10408304 | D37: =+D35/D4 -> 0.091506807 | E37: =+E35/E4 -> 0.11449306 | F37: =+F35/F4 -> 0.14957341 | G37: =+G35/G4 -> 0.14705846 | H37: =+H35/H4 -> 0.14478934 | I37: =+I35/I4 -> 0.14882772 | J37: =+J35/J4 -> 0.23075223 | ... Z37: =+Z35/Z4 -> 0.21638445 | AB37: mrgn
R38: =+R35/$O$35-1 -> 0.026995933 | S38: =+S35/$O$35-1 -> -0.1705675
B40: EBITDA Adj (Con IFRS) | C40: =+FAT!CY139 -> 0 | D40: =+FAT!CZ139 -> 0 | E40: =+FAT!DA139 -> 0 | F40: =+FAT!DB139 -> 0 | G40: =+FAT!DC139 -> 0 | H40: =+FAT!DD139 -> 0 | I40: =+FAT!DE139 -> 0 | J40: =+FAT!DF139 -> 0 | ... M40: =+FAT!DI139 -> 0 | N40: =+FAT!DJ160 -> 1773318 | O40: =+FAT!DK160 -> 2388828 | P40: =+FAT!DL160 -> 1661248 | Q40: =+FAT!DM160 -> 1722346.2 | R40: =+FAT!DN160 -> 2463036 | S40: =+FAT!DO160 -> 2103621 | T40: =+FAT!DP160 -> 2647067 | U40: =+FAT!DQ160 -> 3158272.2 | ... Z40: =+FAT!DV160 -> 5053515.6 | AK40: 2608 | AL40: 2889
B41: Mg EBITDA | C41: =+C40/#REF! -> #REF! | D41: =+D40/#REF! -> #REF! | E41: =+E40/#REF! -> #REF! | F41: =+F40/#REF! -> #REF! | G41: =+G40/#REF! -> #REF! | H41: =+H40/#REF! -> #REF! | I41: =+I40/#REF! -> #REF! | J41: =+J40/#REF! -> #REF! | ... M41: =+M40/#REF! -> #REF! | N41: =+N40/N4 -> 0.21044436 | O41: =+O40/O4 -> 0.24913633 | P41: =+P40/P4 -> 0.2204071 | Q41: =+Q40/Q4 -> 0.16292267 | R41: =+R40/R4 -> 0.18559344 | S41: =+S40/S4 -> 0.15413572 | T41: =+T40/T4 -> 0.18336103 | U41: =+U40/U4 -> 0.19968298 | ... Z41: =+Z40/Z4 -> 0.22664365
B42: vs 2019 | R42: =+R40/O40-1 -> 0.031064606 | S42: =+S40/$O40-1 -> -0.11939202 | T42: =+T40/$O40-1 -> 0.1081028 | U42: =+U40/$O40-1 -> 0.32210113 | V42: =+V40/$O40-1 -> 0.33727136 | W42: =+W40/$O40-1 -> 0.63105556 | X42: =+X40/$O40-1 -> 0.78456069 | Y42: =+Y40/$O40-1 -> 0.94498626 | Z42: =+Z40/$O40-1 -> 1.1154791
B43: EBITDA Adj Retail (Con IFRS) | C43: =+FAT!CY142 -> 0 | D43: =+FAT!CZ142 -> 0 | E43: =+FAT!DA142 -> 0 | F43: =+FAT!DB142 -> 0 | G43: =+FAT!DC142 -> 0 | H43: =+FAT!DD142 -> 0 | I43: =+FAT!DE142 -> 0 | J43: =+FAT!DF142 -> 0 | ... M43: =+FAT!DI142 -> 0 | N43: =+FAT!DJ$177 -> 1423887.1 | O43: =+FAT!DK$177 -> 1997344.6 | P43: =+FAT!DL$177 -> 1579443.3 | Q43: =+FAT!DM$177 -> 1475785 | R43: =+FAT!DN$177 -> 2271435.8 | S43: =+FAT!DO$177 -> 1980246.5 | T43: =+FAT!DP$177 -> 2329530 | U43: =+FAT!DQ$177 -> 2614145.6 | ... Z43: =+FAT!DV$177 -> 4456743.8 | AK43: 2410 | AL43: 2801 | AR43: =+AR44*AR6 -> 2810.527 | AS43: =+AS44*AS6 -> 3182.5872
B44: Mg EBITDA | C44: =+C43/#REF! -> #REF! | D44: =+D43/#REF! -> #REF! | E44: =+E43/#REF! -> #REF! | F44: =+F43/#REF! -> #REF! | G44: =+G43/#REF! -> #REF! | H44: =+H43/#REF! -> #REF! | I44: =+I43/#REF! -> #REF! | J44: =+J43/#REF! -> #REF! | ... M44: =+M43/#REF! -> #REF! | N44: =+N43/N6 -> 0.19022108 | O44: =+O43/O6 -> 0.23568342 | P44: =+P43/P6 -> 0.23713331 | Q44: =+Q43/Q6 -> 0.15443986 | R44: =+R43/R6 -> 0.19622288 | S44: =+S43/S6 -> 0.16916017 | T44: =+T43/T6 -> 0.18383359 | U44: =+U43/U6 -> 0.18864245 | ... Z44: =+Z43/Z6 -> 0.22162529 | AR44: 0.202 | AS44: 0.208
B45: vs 2019 | R45: =+R43/O43-1 -> 0.13722781 | S45: =+S43/$O43-1 -> -0.0085604263 | T45: =+T43/$O43-1 -> 0.16631351 | U45: =+U43/$O43-1 -> 0.3088105 | V45: =+V43/$O43-1 -> 0.44987166 | W45: =+W43/$O43-1 -> 0.69218224 | X45: =+X43/$O43-1 -> 0.85965291 | Y45: =+Y43/$O43-1 -> 1.0390901 | Z45: =+Z43/$O43-1 -> 1.2313345
B46: EBITDA SS Financeiros | C46: =+FAT!CY152 -> 0 | D46: =+FAT!CZ152 -> 0 | E46: =+FAT!DA152 -> 0 | F46: =+FAT!DB152 -> 0 | G46: =+FAT!DC152 -> 0 | H46: =+FAT!DD152 -> 0 | I46: =+FAT!DE152 -> 0 | J46: =+FAT!DF152 -> 0 | ... M46: =+FAT!DI152 -> 0 | N46: =+FAT!DJ181 -> 349430.87 | O46: =+FAT!DK181 -> 391483.4 | P46: =+FAT!DL181 -> 81804.747 | Q46: =+FAT!DM181 -> 246561.15 | R46: =+FAT!DN181 -> 81536.18 | S46: =+FAT!DO181 -> -95871.478 | T46: =+FAT!DP181 -> 167856 | U46: =+FAT!DQ181 -> 464185.54 | ... Z46: =+FAT!DV181 -> 485285.86
B47: Mg EBITDA | C47: =+C46/#REF! -> #REF! | D47: =+D46/#REF! -> #REF! | E47: =+E46/#REF! -> #REF! | F47: =+F46/#REF! -> #REF! | G47: =+G46/#REF! -> #REF! | H47: =+H46/#REF! -> #REF! | I47: =+I46/#REF! -> #REF! | J47: =+J46/#REF! -> #REF! | ... M47: =+M46/#REF! -> #REF! | N47: =+N46/N8 -> 0.37129731 | O47: =+O46/O8 -> 0.35150214 | P47: =+P46/P8 -> 0.093319539 | Q47: =+Q46/Q8 -> 0.24271897 | R47: =+R46/R8 -> 0.048094237 | S47: =+S46/S8 -> -0.049379878 | T47: =+T46/T8 -> 0.095134029 | U47: =+U46/U8 -> 0.23697957 | ... Z47: =+Z46/Z8 -> 0.22181246
B48: vs 2019 | R48: =+R46/O46-1 -> -0.79172506 | S48: =+S46/$O46-1 -> -1.2448928 | T48: =+T46/$O46-1 -> -0.57123086 | U48: =+U46/$O46-1 -> 0.18570938 | V48: =+V46/$O46-1 -> -0.45281955 | W48: =+W46/$O46-1 -> 0.085565197 | X48: =+X46/$O46-1 -> 0.15187493 | Y48: =+Y46/$O46-1 -> 0.19827143 | Z48: =+Z46/$O46-1 -> 0.23960776
B49: Tax Credit | N49: =+N40-N43-N46 -> 0 | O49: =+O40-O43-O46 -> 0 | P49: =+P40-P43-P46 -> 0 | Q49: =+Q40-Q43-Q46 -> 0 | R49: =+R40-R43-R46 -> 110064 | S49: =+S40-S43-S46 -> 219246 | T49: =+T40-T43-T46 -> 149681 | U49: =+U40-U43-U46 -> 79941.087 | ... Z49: =+Z40-Z43-Z46 -> 111485.93
B51: EBITDA Adj (EX IFRS) | C51: =+FAT!CY148 -> 255875 | D51: =+FAT!CZ148 -> 272847 | E51: =+FAT!DA148 -> 361936 | F51: =+FAT!DB148 -> 504699 | G51: =+FAT!DC148 -> 595589 | H51: =+FAT!DD148 -> 714164 | I51: =+FAT!DE148 -> 836609 | J51: =+FAT!DF148 -> 1015155.8 | ... M51: =+FAT!DI148 -> 1416291 | N51: =+FAT!DJ195 -> 1773318 | O51: =+FAT!DK195 -> 1953206.8 | P51: =+FAT!DL195 -> 1190436.6 | Q51: =+FAT!DM195 -> 1108237.2 | R51: =+FAT!DN195 -> 1752877.8 | S51: =+FAT!DO195 -> 1429591.6 | T51: =+FAT!DP195 -> 1934588 | U51: =+FAT!DQ195 -> 2428584.2 | ... Z51: =+FAT!DV195 -> 3844995.6 | AB51: EBITDA
B52: Mg EBITDA | C52: =+C51/C4 -> 0.13251325 | D52: =+D51/D4 -> 0.12498677 | E52: =+E51/E4 -> 0.15312731 | F52: =+F51/F4 -> 0.18343766 | G52: =+G51/G4 -> 0.18390652 | H52: =+H51/H4 -> 0.18489645 | I52: =+I51/I4 -> 0.19142697 | J52: =+J51/J4 -> 0.19462178 | ... Z52: =+Z51/Z4 -> 0.17244309
B53: EBITDA Retail adj (Ex IFRS) | C53: =+FAT!CY151 -> 0.13251325 | D53: =+FAT!CZ151 -> 0.12498677 | E53: =+FAT!DA151 -> 0.15312731 | F53: =+FAT!DB151 -> 0.18343766 | G53: =+FAT!DC151 -> 0.18390652 | H53: =+FAT!DD151 -> 0.18489645 | I53: =+FAT!DE151 -> 0.19142697 | J53: =+FAT!DF151 -> 0 | ... M53: =+FAT!DI151 -> -0.0092269689 | N53: =+FAT!DJ210 -> 1423887.1 | O53: =+FAT!DK210 -> 1561793.2 | P53: =+FAT!DL210 -> 1108523.2 | Q53: =+FAT!DM210 -> 862139 | R53: =+FAT!DN210 -> 1562502.6 | S53: =+FAT!DO210 -> 1306217.1 | T53: =+FAT!DP210 -> 1617051 | U53: =+FAT!DQ210 -> 1884457.6 | ... Z53: =+FAT!DV210 -> 3248223.8 | AB53: EBITDA Retail | AH53: 1.951 | AI53: 2.229
B54: Mg EBITDA | C54: =+C53/C6 -> 7.564716e-08 | D54: =+D53/D6 -> 6.3898482e-08 | E54: =+E53/E6 -> 7.2367464e-08 | F54: =+F53/F6 -> 7.4486884e-08 | G54: =+G53/G6 -> 6.3490129e-08 | H54: =+H53/H6 -> 5.3408025e-08 | I54: =+I53/I6 -> 4.8910696e-08 | J54: =+J53/J6 -> 0 | ... M54: =+M53/M6 -> -1.3980101e-09 | N54: =+FAT!DJ211 -> 0.19022108 | O54: =+FAT!DK211 -> 0.18428905 | P54: =+FAT!DL211 -> 0.16643066 | Q54: =+FAT!DM211 -> 0.090222236 | R54: =+FAT!DN211 -> 0.13498015 | S54: =+FAT!DO211 -> 0.11158202 | T54: =+FAT!DP211 -> 0.12760869 | U54: =+FAT!DQ211 -> 0.13598657 | ... Z54: =+FAT!DV211 -> 0.16152792
B55: EBITDA SS Financeiros | C55: =+FAT!CY161 -> 0.1009683 | D55: =+FAT!CZ161 -> 0.080258852 | E55: =+FAT!DA161 -> 0.12091812 | F55: =+FAT!DB161 -> 0.15578734 | G55: =+FAT!DC161 -> 0.15989796 | H55: =+FAT!DD161 -> 0.16160412 | I55: =+FAT!DE161 -> 0.16933747 | J55: =+FAT!DF161 -> 0.20197419 | ... M55: =+FAT!DI161 -> 0.19824953 | N55: =+FAT!DJ214 -> 349430.87 | O55: =+FAT!DK214 -> 391413.67 | P55: =+FAT!DL214 -> 81913.363 | Q55: =+FAT!DM214 -> 246098.22 | R55: =+FAT!DN214 -> 80311.22 | S55: =+FAT!DO214 -> -95871.478 | T55: =+FAT!DP214 -> 167856 | U55: =+FAT!DQ214 -> 464185.54 | ... Z55: =+FAT!DV214 -> 485285.86 | AB55: EBITDA Retail
B56: Mg EBITDA | C56: =+C55/C9 -> #DIV/0! | D56: =+D55/D9 -> 0.23847856 | E56: =+E55/E9 -> 2.3707225 | F56: =+F55/F9 -> 0.56518144 | G56: =+G55/G9 -> 0.90070498 | H56: =+H55/H9 -> 0.94687325 | I56: =+I55/I9 -> 1.2111635 | J56: =+J55/J9 -> 0.78916968 | ... M56: =+M55/M9 -> 0.31674627 | N56: =+N55/N8 -> 0.37129731 | O56: =+O55/O8 -> 0.35143954 | P56: =+P55/P8 -> 0.093443443 | Q56: =+Q55/Q8 -> 0.24226325 | R56: =+R55/R8 -> 0.047371693 | S56: =+S55/S8 -> -0.049379878 | T56: =+T55/T8 -> 0.095134029 | U56: =+U55/U8 -> 0.23697957 | ... Z56: =+Z55/Z8 -> 0.22181246
B57: Tax Credit | N57: =+N51-N53-N55 -> 0 | O57: =+O51-O53-O55 -> 0 | P57: =+P51-P53-P55 -> 0 | Q57: =+Q51-Q53-Q55 -> 0 | R57: =+R51-R53-R55 -> 110064 | S57: =+S51-S53-S55 -> 219246 | T57: =+T51-T53-T55 -> 149681 | U57: =+U51-U53-U55 -> 79941.087 | ... Z57: =+Z51-Z53-Z55 -> 111485.93
B59: Múltiplos | C59: =+C34 -> 39447 | D59: =+D34 -> 39812 | E59: =+E34 -> 40177 | F59: =+F34 -> 40542 | G59: =+G34 -> 40907 | H59: =+H34 -> 41272 | I59: =+I34 -> 41637 | J59: =+J34 -> 42002 | ... Z59: =+Z34 -> 2030
B60: Mkt Cap | C60: =+VP!C24 -> 15706782 | D60: =+C60 -> 15706782 | E60: =+D60 -> 15706782 | F60: =+E60 -> 15706782 | G60: =+F60 -> 15706782 | H60: =+G60 -> 15706782 | I60: =+H60 -> 15706782 | J60: =+I60 -> 15706782 | K60: =+VP!C24 -> 15706782 | L60: =+K60 -> 15706782 | M60: =+L60 -> 15706782 | N60: =+M60 -> 15706782 | O60: =+N60 -> 15706782 | P60: =+O60 -> 15706782 | Q60: =+P60 -> 15706782 | R60: =+Q60 -> 15706782 | S60: =+R60 -> 15706782 | ... Z60: =+Y60 -> 15706782
B61: Net Debt | C61: =+PROJ!CX139 -> -33302 | D61: =+PROJ!CY139 -> 143563 | E61: =+PROJ!CZ139 -> -3125 | F61: =+PROJ!DA139 -> -377335 | G61: =+PROJ!DB139 -> -89961 | H61: =+PROJ!DC139 -> 625116 | I61: =+PROJ!DD139 -> 973960 | J61: =+PROJ!DE139 -> 1113833 | ... Z61: =+PROJ!DU139 -> -4143134.3
B62: EV | C62: =+C60+C61 -> 15673480 | D62: =+D60+D61 -> 15850345 | E62: =+E60+E61 -> 15703657 | F62: =+F60+F61 -> 15329447 | G62: =+G60+G61 -> 15616821 | H62: =+H60+H61 -> 16331898 | I62: =+I60+I61 -> 16680742 | J62: =+J60+J61 -> 16820615 | ... Z62: =+Z60+Z61 -> 11563648
B64: EPS | N64: =+N22/VP!$C$16 -> 1.0132013 | O64: =+O22/VP!$C$16 -> 1.0788185 | P64: =+P22/VP!$C$16 -> 1.0887863 | Q64: =+Q22/VP!$C$16 -> 0.62909301 | R64: =+R22/VP!$C$16 -> 1.2829214 | S64: =+S22/VP!$C$16 -> 0.96962194 | T64: =+T22/VP!$C$16 -> 1.1885325 | U64: =+U22/VP!$C$16 -> 1.3773897 | ... Z64: =+Z22/VP!$C$16 -> 2.4983208
B65: P/BV | C65: =+C60/PROJ!CX126 -> 26.944635 | D65: =+D60/PROJ!CY126 -> 22.075807 | E65: =+E60/PROJ!CZ126 -> 20.198012 | F65: =+F60/PROJ!DA126 -> 15.379084 | G65: =+G60/PROJ!DB126 -> 13.598969 | H65: =+H60/PROJ!DC126 -> 12.029552 | I65: =+I60/PROJ!DD126 -> 10.5185 | J65: =+J60/PROJ!DE126 -> 8.4660448 | N65: =+N60/PROJ!DI126 -> 3.9718635 | O65: =+O60/PROJ!DJ126 -> 3.338591 | P65: =+P60/PROJ!DK126 -> 2.8550954 | Q65: =+Q60/PROJ!DL126 -> 1.6016508 | R65: =+R60/PROJ!DM126 -> 1.5570517 | S65: =+S60/PROJ!DN126 -> 1.5632962 | T65: =+T60/PROJ!DO126 -> 1.4579832 | U65: =+U60/PROJ!DP126 -> 1.5060633 | ... Z65: =+Z60/PROJ!DU126 -> 0.98244664
B66: P/E | C66: =+C60/C22 -> 120.89301 | D66: =+D60/D22 -> 120.07325 | E66: =+E60/E22 -> 88.969599 | F66: =+F60/F22 -> 51.612378 | G66: =+G60/G22 -> 45.701497 | H66: =+H60/H22 -> 44.19466 | I66: =+I60/I22 -> 38.553711 | J66: =+J60/J22 -> 23.789043 | N66: =+N60/N22 -> 15.396743 | O66: =+O60/O22 -> 14.460264 | P66: =+P60/P22 -> 14.327881 | Q66: =+Q60/Q22 -> 24.797605 | R66: =+R60/R22 -> 12.159747 | S66: =+S60/S22 -> 16.088745 | T66: =+T60/T22 -> 13.12543 | U66: =+U60/U22 -> 11.325771 | ... Z66: =+Z60/Z22 -> 6.2441941
B67: P/E (adj subv e credito | C67: =+C61/C23 -> #DIV/0! | D67: =+D61/D23 -> 21028338 | E67: =+E61/E23 -> -8938.8216 | F67: =+F61/F23 -> -521322.41 | G67: =+G61/G23 -> -695556.69 | H67: =+H61/H23 -> 18334282 | I67: =+I61/I23 -> 6656642 | J67: =+J61/J23 -> 1794623.5 | N67: =+N60/N29 -> 15.396743 | O67: =+O60/O29 -> 15.057575 | P67: =+P60/P29 -> 14.695799 | Q67: =+Q60/Q29 -> 29.35764 | R67: =+R60/R29 -> 14.906935 | S67: =+S60/S29 -> 25.523961 | T67: =+T60/T29 -> 15.690464 | U67: =+U60/U29 -> 12.393731 | ... Z67: =+Z60/Z29 -> 6.6890462
B69: ROE | N69: =+PROJ!DI254 -> 0.28424147 | O69: =+PROJ!DJ254 -> 0.25088052 | P69: =+PROJ!DK254 -> 0.21482393 | Q69: =+PROJ!DL254 -> 0.082754345 | R69: =+PROJ!DM254 -> 0.12985766 | S69: =+PROJ!DN254 -> 0.096972615 | T69: =+PROJ!DO254 -> 0.11495275 | U69: =+PROJ!DP254 -> 0.13081964 | ... Z69: =+PROJ!DU254 -> 0.16502436
B70: ROIC | C70: =+PROJ!CX255 -> 0.13082023 | D70: =+PROJ!CY255 -> 0.26090622 | E70: =+PROJ!CZ255 -> 0.30574485 | F70: =+PROJ!DA255 -> 0.42751666 | G70: =+PROJ!DB255 -> 0.380094 | H70: =+PROJ!DC255 -> 0.32530953 | I70: =+PROJ!DD255 -> 0.29447779 | J70: =+PROJ!DE255 -> 0.26611579 | N70: =+PROJ!DI255 -> 0.25349841 | O70: =+PROJ!DJ255 -> 0.23436837 | P70: =+PROJ!DK255 -> 0.12193129 | Q70: =+PROJ!DL255 -> 0.09344412 | R70: =+PROJ!DM255 -> 0.14251749 | S70: =+PROJ!DN255 -> 0.089808936 | T70: =+PROJ!DO255 -> 0.11115528 | U70: =+PROJ!DP255 -> 0.14750077 | ... Z70: =+PROJ!DU255 -> 0.20471241
B72: EV/EBITDA | C72: =C62/Resumo!C35 -> 77.986048 | D72: =D62/Resumo!D35 -> 79.346941 | E72: =E62/Resumo!E35 -> 58.028657 | F72: =F62/Resumo!F35 -> 37.250161 | G72: =G62/Resumo!G35 -> 32.790881 | H72: =H62/Resumo!H35 -> 29.203215 | I72: =I62/Resumo!I35 -> 25.645557 | J72: =J62/Resumo!J35 -> 13.975093 | N72: =N62/Resumo!N35 -> 9.3454019 | O72: =O62/Resumo!O35 -> 6.8343116 | P72: =P62/Resumo!P35 -> 10.157256 | Q72: =Q62/Resumo!Q35 -> 7.8204903 | R72: =R62/Resumo!R35 -> 6.0837793 | S72: =S62/Resumo!S35 -> 7.4922305 | T72: =T62/Resumo!T35 -> 5.6491325 | U72: =U62/Resumo!U35 -> 4.934022 | ... Z72: =Z62/Resumo!Z35 -> 2.396728
B73: EV/COI | C73: =+C62/PROJ!CX138 -> 24.438606 | D73: =+D62/PROJ!CY138 -> 17.835368 | E73: =+E62/PROJ!CZ138 -> 17.857931 | F73: =+F62/PROJ!DA138 -> 21.484648 | G73: =+G62/PROJ!DB138 -> 14.052434 | H73: =+H62/PROJ!DC138 -> 8.3533266 | I73: =+I62/PROJ!DD138 -> #REF! | J73: =+J62/PROJ!DE138 -> 5.6440433 | N73: =+N62/PROJ!DI138 -> 3.6045276 | O73: =+O62/PROJ!DJ138 -> 3.307201 | P73: =+P62/PROJ!DK138 -> 2.8416449 | Q73: =+Q62/PROJ!DL138 -> 1.9034181 | R73: =+R62/PROJ!DM138 -> 1.7172557 | S73: =+S62/PROJ!DN138 -> 1.751734 | T73: =+T62/PROJ!DO138 -> 1.6818112 | U73: =+U62/PROJ!DP138 -> 1.6355869 | ... Z73: =+Z62/PROJ!DU138 -> 1.0128839
B74: EV/Sales | C74: =+C62/C4 -> 8.1170249 | D74: =+D62/D4 -> 7.2607852 | E74: =+E62/E4 -> 6.6438784 | F74: =+F62/F4 -> 5.5716335 | G74: =+G62/G4 -> 4.8221765 | H74: =+H62/H4 -> 4.2283143 | I74: =+I62/I4 -> 3.8167698 | J74: =+J62/J4 -> 3.224784 | N74: =+N62/N4 -> 1.9279567 | O74: =+O62/O4 -> 1.6665395 | P74: =+P62/P4 -> 2.1784551 | Q74: =+Q62/Q4 -> 1.2511291 | R74: =+R62/R4 -> 1.1007855 | S74: =+S62/S4 -> 1.0646249 | T74: =+T62/T4 -> 0.96152834 | U74: =+U62/U4 -> 0.93534823 | ... Z74: =+Z62/Z4 -> 0.51861468
T76: alavancagem est | U76: =+U60*0.1 -> 1570678.2 | V76: =+V60*0.1 -> 1570678.2 | W76: =+W60*0.1 -> 1570678.2
T77: custo | U77: =+U76*0.074 -> 116230.19 | V77: =+V76*0.074 -> 116230.19 | W77: =+W76*0.074 -> 116230.19
T78: LL adj | U78: =+U22-U77 -> 1270587.7 | V78: =+V22-V77 -> 1218233.8 | W78: =+W22-W77 -> 1678527.1
T79: PE | U79: =+U60/U78 -> 12.361824 | V79: =+V60/V78 -> 12.893077 | W79: =+W60/W78 -> 9.357479
B84: Sensibilidade | N84: 2019 | O84: 2024 | P84: 2025 | R84: Tax Rate | S84: 2024 - PE | T84: Retail EBITDA mrgn
B85: Receita Líquida | N85: =+N86+N87 -> 9588437 | O85: =+O86+O87 -> 14436366 | P85: =+P86+P87 -> 15816431 | S85: =+O120 -> 14.299555 | T85: =+U85-1% -> 0.175 | U85: =+V85-1% -> 0.185 | V85: 0.195 | W85: =+V85+1% -> 0.205 | X85: =+W85+1% -> 0.215
B86: Retail | N86: =+O6 -> 8474693 | O86: =+T6 -> 12671950 | P86: =+U6 -> 13857674 | S86: -0.0779 | T86: 16.078982 | U86: 14.361145 | V86: 12.974937 | W86: 11.832779 | X86: 10.875435 | Y86: 9% de CS taxado na subvencao
B87: Realize | N87: =+O8 -> 1113744 | O87: =+T8 -> 1764416 | P87: =+U8 -> 1958757.7 | S87: =+S86-O115 -> -0.11712682 | T87: 16.607325 | U87: 14.833042 | V87: 13.401284 | W87: 12.221595 | X87: 11.232794 | Y87: 34% taxado na subvencao
B88: CPV | N88: =+N89-N85 -> -3730521 | O88: =+O89-O85 -> -5694417 | P88: =+P89-P85 -> -6125494.3
B89: Lucro Bruto | N89: =+O12 -> 5857916 | O89: =+T12 -> 8741949 | P89: =+U12 -> 9690937.1
B90: Mg Bruta | N90: =+N89/N$85 -> 0.61093544 | O90: =+O89/O$85 -> 0.60555052 | P90: =+P89/P$85 -> 0.61271325 | R90: Tax Rate | S90: 2024 - Net Income | T90: Retail EBITDA mrgn
B91: SG&A (ex dep) | N91: =+N93-N89 -> -3469088 | O91: =+O93-O89 -> -6244563 | P91: =+P93-P89 -> -6612606 | S91: =+O119 -> 1098410.6 | T91: =+U91-0.5% -> 0.1845 | U91: =+V91-0.5% -> 0.1895 | V91: 0.1945 | W91: =+V91+0.5% -> 0.1995 | X91: =+W91+0.5% -> 0.2045
S92: =+$S$86 -> -0.0779 | T92: 1087857.4 | U92: 1146281.4 | V92: 1204705.5 | W92: 1263129.5 | X92: 1321553.5 | Y92: 9% de CS taxado na subvencao
B93: EBITDA adj | N93: =+N95+N97 -> 2388828 | O93: =+O95+O97 -> 2497386 | P93: =+P95+P97 -> 3078331.1 | S93: =+S92-O115 -> -0.11712682 | T93: 1050035.4 | U93: 1106428.2 | V93: 1162821 | W93: 1219213.7 | X93: 1275606.5 | Y93: 34% taxado na subvencao
B94: Mg ebitda | N94: =+N93/N$85 -> 0.24913633 | O94: =+O93/O$85 -> 0.1729927 | P94: =+P93/P$85 -> 0.19462868
B95: Retail | N95: =+O43 -> 1997344.6 | O95: =+O96*O86 -> 2329530 | P95: =+P96*P86 -> 2614145.6
B96: mrgn | N96: =+N95/N86 -> 0.23568342 | O96: =+T44 -> 0.18383359 | P96: =+U44 -> 0.18864245 | R96: Tax Rate | S96: 2025 - PE | T96: Retail EBITDA mrgn
B97: Realize | N97: =+O46 -> 391483.4 | O97: =+T46 -> 167856 | P97: =+U46 -> 464185.54 | S97: =+P120 -> 11.7733 | T97: =+U97-1% -> 0.18 | U97: =+V97-1% -> 0.19 | V97: 0.2 | W97: =+V97+1% -> 0.21 | X97: =+W97+1% -> 0.22
B98: mrgn | N98: =+N97/N87 -> 0.35150214 | O98: =+O97/O87 -> 0.095134029 | P98: =+P97/P87 -> 0.23697957 | S98: -0.0853 | T98: 11.945051 | U98: 10.894809 | V98: 10.014322 | W98: 9.26551 | X98: 8.6208907 | Y98: 9% de CS taxado na subvencao
S99: =+S98-P115 -> -0.11070296 | T99: 12.210172 | U99: 11.13662 | V99: 10.236591 | W99: 9.4711589 | X99: 8.8122323 | Y99: 34% taxado na subvencao
B100: Depreciacao | N100: =+PROJ!DJ13 -> -661751 | O100: =+PROJ!DO13 -> -1197844 | P100: =+PROJ!DP13 -> -1242955.1
B101: Outras Desp/Rec | N101: =+FAT!DK153 -> -50698 | O101: =+FAT!DP153 -> -189880 | P101: =+FAT!DQ153 -> -159933.11
B102: EBIT | N102: =+N93+N100+N101 -> 1676379 | O102: =+O93+O100+O101 -> 1109662 | P102: =+P93+P100+P101 -> 1675442.9 | R102: Tax Rate | S102: 2025 - Net Income | T102: Retail EBITDA mrgn
B103: Resultado Financeiro | N103: =+O18 -> -184395 | O103: =+T18 -> 61654 | P103: =+U18 -> -118136.62 | S103: =+P119 -> 1334101.9 | T103: =+U103-0.5% -> 0.19 | U103: =+V103-0.5% -> 0.195 | V103: 0.2 | W103: =+V103+0.5% -> 0.205 | X103: =+W103+0.5% -> 0.21
S104: -0.0853 | T104: 1441675.8 | U104: 1505053.9 | V104: 1568431.9 | W104: 1631810 | X104: 1695188.1 | Y104: 9% de CS taxado na subvencao
B105: LAIR | N105: =+N102+N103 -> 1491984 | O105: =+O102+O103 -> 1171316 | P105: =+P102+P103 -> 1557306.3 | S105: =+S104-P115 -> -0.11070296 | T105: 1408031.7 | U105: 1469930.8 | V105: 1531829.8 | W105: 1593728.8 | X105: 1655627.9 | Y105: 34% taxado na subvencao
B106: IR & CS | N106: =+N107*N105 -> -404541.56 | O106: =+O107*O105 -> -72905.44 | P106: =+P107*P105 -> -223204.36
B107: Tax rate | N107: -0.27114336 | O107: =+O109+O112+O115+O117 -> -0.062242333 | P107: =+P109+P112+P115+P117 -> -0.14332721
B108: 0.34 | N108: =+N109*N105 -> -507274.56 | O108: =+O109*O105 -> -398247.44 | P108: =+P109*P105 -> -529484.14
B109: % LAIR | N109: -0.34 | O109: -0.34 | P109: -0.34
B110: JCP | N110: =+PROJ!DJ213 -> 85665 | O110: =+PROJ!DO213 -> 215947 | P110: =+PROJ!DP213 -> 274230.24
B111: % RL | N111: =+N110/N$85 -> 0.0089341986 | O111: =+O110/O$85 -> 0.014958543 | P111: =+P110/P$85 -> 0.017338313
B112: % LAIR | N112: =+N110/N$105 -> 0.057416836 | O112: =+O110/O$105 -> 0.18436272 | P112: =+P110/P$105 -> 0.17609268
B113: Subvencao | N113: =+PROJ!DJ216 -> 43088 | O113: =+PROJ!DO216 -> 45947 | P113: =+PROJ!DP216 -> 39560.193
B114: % RL | N114: =+N113/N$85 -> 0.004493746 | O114: =+O113/O$85 -> 0.0031827262 | P114: =+P113/P$85 -> 0.0025012085
B115: % LAIR | N115: =+N113/N$105 -> 0.028879666 | O115: =+O113/O$105 -> 0.039226818 | P115: =+P113/P$105 -> 0.025402962
...

Sheet FAT
B1: 37956 | C1: 38047 | D1: 38139 | E1: 38231 | F1: 38322 | G1: 38412 | H1: 38504 | I1: 38596 | J1: 38687 | K1: 38777 | L1: 38869 | M1: 38961 | N1: 39052 | O1: 39142 | P1: 39234 | Q1: 39326 | R1: 39417 | S1: 39508 | T1: 39600 | U1: 39692 | V1: 39783 | W1: 39873 | X1: 39965 | Y1: 40057 | Z1: 40148 | AA1: 40238 | AB1: 40330 | AC1: 40422 | AD1: 40513 | AE1: 40603 | AF1: 40695 | AG1: 40787 | AH1: 40878 | AI1: 40969 | AJ1: 41061 | AK1: 41153 | AL1: 41244 | AM1: 41334 | AN1: 41426 | AO1: 41518 | AP1: 41609 | AQ1: 41699 | AR1: =+EOMONTH(AQ1,3) -> 41820 | AS1: =+EOMONTH(AR1,3) -> 41912 | AT1: =+EOMONTH(AS1,3) -> 42004 | AU1: =+EOMONTH(AT1,3) -> 42094 | AV1: =+EOMONTH(AU1,3) -> 42185 | AW1: =+EOMONTH(AV1,3) -> 42277 | AX1: =+EOMONTH(AW1,3) -> 42369 | AY1: =+EOMONTH(AX1,3) -> 42460 | ... CP1: =+EOMONTH(CO1,3) -> 46387 | CT1: 46022 | CV1: 38322 | CW1: 38687 | CX1: 39052 | CY1: 39417 | CZ1: 39783 | DA1: 40148 | DB1: 40513 | DC1: 40878 | DD1: 41244 | DE1: 41609 | DF1: 2014 | DG1: =+DF1+1 -> 2015 | DH1: =+DG1+1 -> 2016 | DI1: =+DH1+1 -> 2017 | DJ1: =+DI1+1 -> 2018 | DK1: =+DJ1+1 -> 2019 | DL1: =+DK1+1 -> 2020 | DM1: =+DL1+1 -> 2021 | DN1: =+DM1+1 -> 2022 | ... DV1: =+DU1+1 -> 2030 | DY1: 2026 | DZ1: 2027
A2: Inflação | B2: 0.0115 | C2: 0.0185 | D2: 0.016 | E2: 0.0194 | F2: 0.02 | G2: 0.0179 | H2: 0.013469458 | I2: 0.0077189382 | J2: 0.016688208 | K2: 0.014368541 | L2: 0.00099540016 | M2: 0.004476 | N2: 0.011345219 | O2: 0.0126 | P2: 0.0082 | Q2: 0.0089 | R2: 0.0143 | S2: 0.015149686 | T2: 0.020897661 | U2: 0.0107 | V2: 0.0109 | W2: 0.0124 | X2: 0.0132 | Y2: 0.0066 | Z2: 0.0102 | AA2: 0.0206 | AB2: 0.01 | AC2: 0.005 | AD2: 0.0223 | AE2: 0.0244 | AF2: 0.014 | AG2: 0.0106 | AH2: 0.0144 | AI2: 0.012246463 | AJ2: 0.010831058 | AK2: 0.01416561 | AL2: 0.01992969 | AM2: 0.019420463 | AN2: 0.011844323 | AO2: 0.0062101725 | AP2: 0.020433183 | AQ2: =MACRO!BD8 -> 0.0217 | AR2: =MACRO!BE8 -> 0.0114 | AS2: =MACRO!BF8 -> 0.0104 | AT2: =MACRO!BG8 -> 0.0167 | AU2: =MACRO!BH8 -> 0.013475174 | AV2: =MACRO!BI8 -> 0.013475174 | AW2: =MACRO!BJ8 -> 0.013475174 | AX2: =MACRO!BK8 -> 0.013475174 | ... CG2: =MACRO!CT8 -> 0.0062002866 | CH2: 0.02 | CI2: =MACRO!CV8 -> 0.020403397 | CJ2: =MACRO!CW8 -> 0.0093277668 | CK2: =MACRO!CX8 -> 0.0063043263 | CL2: =MACRO!CY8 -> 0.010934022 | CM2: =MACRO!CZ8 -> 0.015 | CN2: =MACRO!DA8 -> 0.0085 | CO2: =MACRO!DB8 -> 0.006 | CP2: =MACRO!DC8 -> 0.0115 | CT2: 0.010934022 | CV2: 0.075968463 | CW2: 0.055776604 | CX2: 0.03118516 | CY2: 0.0446 | CZ2: 0.0589 | DA2: 0.0431 | DB2: 0.0591 | DC2: 0.0648 | DD2: 0.057172822 | DE2: 0.057908141 | DF2: =MACRO!DW8 -> 0.0641 | DG2: =MACRO!DX8 -> 0.1067 | DH2: =MACRO!DY8 -> 0.062665012 | DI2: =MACRO!DZ8 -> 0.029473499 | DJ2: =MACRO!EA8 -> 0.030601831 | DK2: =MACRO!EB8 -> 0.042901847 | DL2: =MACRO!EC8 -> 0.044908326 | DM2: =MACRO!ED8 -> 0.099766039 | ... DV2: =MACRO!EM8 -> 0.045 | DY2: 0.046799601 | DZ2: 0.0475
A3: Receita Bruta | C3: 230277 | D3: 326148 | E3: 283436 | F3: 449394 | G3: 261957 | H3: 379185 | I3: 344395 | J3: 571973.41 | K3: 347895.36 | L3: 508600.35 | M3: 457408.36 | N3: 723460 | O3: 450331 | P3: 651919 | Q3: 583136 | R3: 872743 | S3: 557955 | T3: 747079 | U3: 660961 | V3: 890242 | W3: 537450 | X3: 803683 | Y3: 715447 | Z3: 1023895 | AA3: 649073 | AB3: 918672 | AC3: 835227 | AD3: 1176249.9 | AE3: 773464.63 | AF3: 1089692.7 | AG3: 963449.2 | AH3: 1387228.5 | AI3: 918699.65 | AJ3: 1243546.6 | AK3: 1175907.7 | AL3: 1689611.4 | AM3: 1079840.5 | AN3: 1379462.7 | AO3: 1327255.5 | AP3: 1901390 | AQ3: =+AQ7+AQ11 -> 1214566.3 | AR3: =+AR7+AR11 -> 1630176.7 | AS3: =+AS7+AS11 -> 1558376.3 | AT3: =+AT7+AT11 -> 2377750.6 | AU3: =+AU7+AU11 -> 1516973.9 | AV3: =+AV7+AV11 -> 1993749.3 | AW3: =+AW7+AW11 -> 1842459.9 | AX3: =+AX7+AX11 -> 2630530.3 | ... CP3: =+CP7+CP11 -> 6756780.6 | CT3: 6218948.9 | CU3: =+CK3/CT3-1 -> -0.26841673 | CV3: 1289255 | CW3: 1557510.4 | CX3: 2037364.1 | CY3: 2558129 | CZ3: 2856237 | DA3: 3080475 | DB3: 3579221.9 | DC3: 4213835 | DD3: 5027765.4 | DE3: 5687948.7 | DF3: =+DF7+DF11 -> 6780869.9 | DG3: =+DG7+DG11 -> 7983713.4 | DH3: =+DH7+DH11 -> 8381526.9 | DI3: =+DI7+DI11 -> 9603278 | DJ3: =+DJ7+DJ11 -> 11004890 | DK3: =+DK7+DK11 -> 12956886 | DL3: =+DL7+DL11 -> 10341605 | DM3: =+DM7+DM11 -> 14391001 | ... DV3: =+DV7+DV11 -> 28682678 | DY3: 21984945 | DZ3: 23787214
A4: var y-o-y | G4: 0.13757344 | H4: 0.16261636 | I4: 0.21507148 | J4: 0.27276601 | K4: 0.32806283 | L4: 0.34129871 | M4: 0.32815042 | N4: 0.26484901 | O4: 0.29444384 | P4: 0.2817903 | Q4: 0.27486957 | R4: 0.20634589 | S4: 0.23898866 | T4: 0.14596905 | U4: 0.13345943 | V4: 0.020050576 | W4: -0.036750276 | X4: 0.075767088 | Y4: 0.082434516 | Z4: 0.15013109 | AA4: 0.20769002 | AB4: 0.14307756 | AC4: 0.16741981 | AD4: 0.14879931 | AE4: 0.19164505 | AF4: 0.18616077 | AG4: 0.15351779 | AH4: 0.17936552 | AI4: 0.18777203 | AJ4: 0.1411902 | AK4: 0.22051868 | AL4: 0.21797625 | AM4: 0.17540099 | AN4: 0.10929713 | AO4: 0.12870718 | AP4: 0.12534158 | AQ4: =AQ3/AM3-1 -> 0.12476453 | AR4: =AR3/AN3-1 -> 0.18174759 | AS4: =AS3/AO3-1 -> 0.17413434 | AT4: =AT3/AP3-1 -> 0.25053286 | AU4: =AU3/AQ3-1 -> 0.24898404 | AV4: =AV3/AR3-1 -> 0.22302647 | AW4: =AW3/AS3-1 -> 0.18229466 | AX4: =AX3/AT3-1 -> 0.10631041 | ... CP4: =CP3/CL3-1 -> 0.086482727 | CT4: 0.049689405 | CW4: 0.20807009 | CX4: 0.30809018 | CY4: 0.2556072 | CZ4: 0.11653361 | DA4: 0.078508191 | DB4: 0.16190583 | DC4: 0.17730479 | DD4: 0.19315667 | DE4: 0.13130749 | DF4: =DF3/DE3-1 -> 0.19214682 | DG4: =DG3/DF3-1 -> 0.17738779 | DH4: =DH3/DG3-1 -> 0.04982813 | DI4: =DI3/DH3-1 -> 0.14576713 | DJ4: =DJ3/DI3-1 -> 0.14595137 | DK4: =DK3/DJ3-1 -> 0.17737538 | DL4: =DL3/DK3-1 -> -0.20184487 | DM4: =DM3/DL3-1 -> 0.39156359 | ... DV4: =DV3/DU3-1 -> 0.069429319 | DY4: 0.071051375 | DZ4: 0.081977441
A5: var q-o-q | D5: 0.41632903 | E5: -0.13095895 | F5: 0.58552195 | G5: -0.41708835 | H5: 0.44750856 | I5: -0.09174941 | J5: 0.66080637 | K5: -0.39176306 | L5: 0.46193487 | M5: -0.10065268 | N5: 0.58165014 | O5: -0.37753158 | P5: 0.44764407 | Q5: -0.10550851 | R5: 0.49663715 | S5: -0.36068808 | T5: 0.33895924 | U5: -0.11527295 | V5: 0.34689036 | W5: -0.39628775 | X5: 0.49536329 | Y5: -0.10978956 | Z5: 0.43112627 | AA5: -0.36607465 | AB5: 0.41536006 | AC5: -0.090832201 | AD5: 0.40829962 | AE5: -0.3424317 | AF5: 0.40884618 | AG5: -0.11585237 | AH5: 0.43985644 | AI5: -0.33774456 | AJ5: 0.3535943 | AK5: -0.054391901 | AL5: 0.43685711 | AM5: -0.36089418 | AN5: 0.27746895 | AO5: -0.037846018 | AP5: 0.43257266 | AQ5: =AQ3/AP3-1 -> -0.3612219 | AR5: =AR3/AQ3-1 -> 0.34218836 | AS5: =AS3/AR3-1 -> -0.04404457 | AT5: =AT3/AS3-1 -> 0.52578724 | AU5: =AU3/AT3-1 -> -0.36201305 | AV5: =AV3/AU3-1 -> 0.31429373 | AW5: =AW3/AV3-1 -> -0.075881817 | AX5: =AX3/AW3-1 -> 0.42772726 | ... CP5: =CP3/CO3-1 -> 0.37583222 | CT5: 0.36689839
A7: Vendas de Merc. | J7: 552336 | K7: 332565 | L7: 486121 | M7: 431726 | N7: 692534 | O7: 411087 | P7: 602910 | Q7: 531794 | R7: 823372 | S7: 506525 | T7: 687179 | U7: 595212 | V7: 827297 | W7: 477646 | X7: 741885 | Y7: 646283 | Z7: 953299 | AA7: 579418 | AB7: 842527 | AC7: 755462 | AD7: 1095680.8 | AE7: 687489.3 | AF7: 997743.67 | AG7: 873479.73 | AH7: 1292613.1 | AI7: 823199.37 | AJ7: 1137234.5 | AK7: 1067982.5 | AL7: 1574704.8 | AM7: 966274.06 | AN7: 1259455 | AO7: 1205849.2 | AP7: 1772329.2 | AQ7: =+AQ30/(1+AQ20) -> 1083003.2 | AR7: =+AR30/(1+AR20) -> 1477482.8 | AS7: =+AS30/(1+AS20) -> 1392237.2 | AT7: =+AT30/(1+AT20) -> 2220220.2 | AU7: =+AU30/(1+AU20) -> 1344113.6 | AV7: =+AV30/(1+AV20) -> 1800615.6 | AW7: =+AW30/(1+AW20) -> 1659858.9 | AX7: =+AX30/(1+AX20) -> 2443011.3 | ... BB7: =+BB30/(1+BB20) -> 2553553.7 | BC7: 1640494 | BD7: 2145733 | BE7: 1982620 | BF7: 2918819 | BG7: 1823658 | BH7: 2328836.5 | BI7: 2234198 | BJ7: 3618440 | BK7: 2295081 | BL7: 2807673 | BM7: 2679703 | BN7: 3991792 | BO7: 2148076 | BP7: 747075 | BQ7: 2386644 | BR7: =9408371-BQ7-BP7-BO7 -> 4126576 | BS7: 1919010 | BT7: 3151300 | BU7: 3291853 | BV7: 4935284 | BW7: 3069733 | BX7: 4392869 | BY7: 3588817 | BZ7: 4908186 | CA7: 3164222 | CB7: 4170321 | CC7: 3673020 | CD7: 5779854 | CE7: 3176292 | CF7: 4010926 | CG7: 3845619 | CH7: 5442480 | CI7: 3586902 | CJ7: 4789516 | CK7: 4026865 | CL7: =+CL30/(1+CL20) -> 5727542.6 | CM7: =+CM30/(1+CM20) -> 3842726.1 | CN7: =+CN30/(1+CN20) -> 5043327.9 | CO7: =+CO30/(1+CO20) -> 4362807.2 | CP7: =+CP30/(1+CP20) -> 6207763 | CT7: 5727542.6 | CU7: =+CK7/CT7-1 -> -0.29692971 | CV7: 0 | CW7: 552336 | CX7: 1942946 | CY7: 2369163 | CZ7: 2616213 | DA7: 2819113 | DB7: 3273087.8 | DC7: 3851325.8 | DD7: 4603121.2 | DE7: 5203907.4 | DF7: =+SUM(AQ7:AT7) -> 6172943.4 | DG7: =+SUM(AU7:AX7) -> 7247599.4 | DH7: =+SUM(AY7:BB7) -> 7607802.9 | DI7: =+SUM(BC7:BF7) -> 8687666 | DJ7: =+SUM(BG7:BJ7) -> 10005133 | DK7: =+SUM(BK7:BN7) -> 11774249 | DL7: =+SUM(BO7:BR7) -> 9408371 | DM7: =+SUM(BS7:BV7) -> 13297447 | DN7: =+SUM(BW7:BZ7) -> 15959605 | DO7: =+SUM(CA7:CD7) -> 16787417 | DP7: =+SUM(CE7:CH7) -> 16475317 | DQ7: =+SUM(CI7:CL7) -> 18130826 | DR7: =+SUM(CM7:CP7) -> 19456624 | DS7: =+DS30/(1+DS20) -> 21110106 | DT7: =+DT30/(1+DT20) -> 22738432 | DU7: =+DU30/(1+DU20) -> 24470734 | DV7: =+DV30/(1+DV20) -> 26322727 | DY7: 19925846 | DZ7: 21727261
A8: % Rec Bruta | J8: 0.96566727 | K8: 0.955934 | L8: 0.95580154 | M8: 0.94385244 | N8: 0.95725265 | O8: 0.91285521 | P8: 0.92482348 | Q8: 0.91195536 | R8: 0.94343008 | S8: 0.90782411 | T8: 0.91982106 | U8: 0.90052514 | V8: 0.92929451 | W8: 0.88872639 | X8: 0.9231065 | Y8: 0.90332757 | Z8: 0.93105152 | AA8: 0.89268541 | AB8: 0.91711405 | AC8: 0.90449902 | AD8: 0.9315034 | AE8: 0.88884388 | AF8: 0.91561931 | AG8: 0.90661732 | AH8: 0.93179533 | AI8: 0.89604842 | AJ8: 0.91450898 | AK8: 0.90821961 | AL8: 0.93199227 | AM8: 0.89483037 | AN8: 0.91300405 | AO8: 0.90852829 | AP8: 0.93212291 | AQ8: =1-AQ12 -> 0.89167894 | AR8: =1-AR12 -> 0.90633289 | AS8: =1-AS12 -> 0.89338965 | AT8: =1-AT12 -> 0.93374814 | AU8: =1-AU12 -> 0.88604925 | AV8: =1-AV12 -> 0.90313044 | AW8: =1-AW12 -> 0.90089282 | AX8: =1-AX12 -> 0.92871436 | ... CP8: =1-CP12 -> 0.91874569 | CT8: 0.92098241 | CV8: 0 | CW8: 0.35462749 | CX8: 0.95365675 | CY8: 0.92613117 | CZ8: 0.91596496 | DA8: 0.91515529 | DB8: 0.91446909 | DC8: 0.91397165 | DD8: 0.91554016 | DE8: 0.91490056 | DF8: =1-DF12 -> 0.91034683 | DG8: =1-DG12 -> 0.90779805 | DH8: =1-DH12 -> 0.90768699 | DI8: =1-DI12 -> 0.90465631 | DJ8: =1-DJ12 -> 0.90915338 | DK8: =1-DK12 -> 0.90872521 | DL8: =1-DL12 -> 0.90975927 | DM8: =1-DM12 -> 0.92401126 | ... DV8: =1-DV12 -> 0.9177221 | DY8: 0.90634049 | DZ8: 0.91340083
A9: yoy | AQ9: =+AQ7/AM7-1 -> 0.12080331 | AR9: =+AR7/AN7-1 -> 0.17311277 | AS9: =+AS7/AO7-1 -> 0.15456995 | AT9: =+AT7/AP7-1 -> 0.25271326 | AU9: =+AU7/AQ7-1 -> 0.24109848 | AV9: =+AV7/AR7-1 -> 0.21870501 | AW9: =+AW7/AS7-1 -> 0.19222421 | AX9: =+AX7/AT7-1 -> 0.10034636 | ... CP9: =+CP7/CL7-1 -> 0.08384407 | CT9: 0.052377328 | DG9: =+DG7/DF7-1 -> 0.17409134 | DH9: =+DH7/DG7-1 -> 0.049699695 | DI9: =+DI7/DH7-1 -> 0.14194152 | DJ9: =+DJ7/DI7-1 -> 0.15164793 | DK9: =+DK7/DJ7-1 -> 0.17682089 | DL9: =+DL7/DK7-1 -> -0.20093664 | DM9: =+DM7/DL7-1 -> 0.41336338 | DN9: =+DN7/DM7-1 -> 0.20020069 | ... DV9: =+DV7/DU7-1 -> 0.075681981 | DY9: 0.085424111 | DZ9: 0.090405982
BS10: =+BS7/BK7-1 -> -0.16385958 | BT10: =+BT7/BL7-1 -> 0.12238854 | BU10: =+BU7/BM7-1 -> 0.22843949 | BV10: =+BV7/BN7-1 -> 0.23635801 | BW10: =+BW7/BK7-1 -> 0.33752709 | BX10: =+BX7/BL7-1 -> 0.56459424 | BY10: =+BY7/BM7-1 -> 0.33925924 | BZ10: =+BZ7/BN7-1 -> 0.22956958 | CA10: =+CA7/BK7-1 -> 0.37869731
A11: Prod/Serv Fin. | J11: 19637.409 | K11: 15330.355 | L11: 22479.352 | M11: 25682.362 | N11: 30926 | O11: 39244 | P11: 49009 | Q11: 51342 | R11: 49371 | S11: 51430 | T11: 59900 | U11: 65749 | V11: 62945 | W11: 59804 | X11: 61798 | Y11: 69164 | Z11: 70596 | AA11: 69655 | AB11: 76145 | AC11: 79765 | AD11: 80569.113 | AE11: 85975.326 | AF11: 91949.016 | AG11: 89969.471 | AH11: 94615.463 | AI11: 95500.277 | AJ11: 106312.07 | AK11: 107925.27 | AL11: 114906.64 | AM11: 113566.42 | AN11: 120007.67 | AO11: 121406.33 | AP11: 129060.82 | AQ11: =AQ34/(1+AQ23) -> 131563.1 | AR11: =AR34/(1+AR23) -> 152693.94 | AS11: =AS34/(1+AS23) -> 166139.04 | AT11: =AT34/(1+AT23) -> 157530.41 | AU11: =AU34/(1+AU23) -> 172860.3 | AV11: =AV34/(1+AV23) -> 193133.62 | AW11: =AW34/(1+AW23) -> 182601.01 | AX11: =AX34/(1+AX23) -> 187519.04 | ... BB11: =BB34/(1+BB23) -> 201745.26 | BC11: 200210 | BD11: 221910 | BE11: 248799 | BF11: 244693 | BG11: 244199 | BH11: 254879 | BI11: 245807 | BJ11: 254872 | BK11: 257282 | BL11: 290023 | BM11: 311398 | BN11: 323934 | BO11: 330783 | BP11: 284466 | BQ11: 150024 | BR11: =933234-BQ11-BP11-BO11 -> 167961 | BS11: 232757 | BT11: 248487 | BU11: 275091 | BV11: 337219 | BW11: 414232 | BX11: 494287 | BY11: 446379 | BZ11: 509236 | CA11: 543159 | CB11: 572561 | CC11: 508796 | CD11: 526390 | CE11: 488560 | CF11: 480488 | CG11: 474595 | CH11: 482081 | CI11: 541317 | CJ11: 557650 | CK11: 522814 | CL11: =CL34/(1+CL23) -> 491406.35 | CM11: =CM34/(1+CM23) -> 537695.35 | CN11: =CN34/(1+CN23) -> 544246.41 | CO11: =CO34/(1+CO23) -> 548242.63 | CP11: =CP34/(1+CP23) -> 549017.53 | CT11: 491406.35 | CU11: =+CK11/CT11-1 -> 0.063913804 | CV11: 0 | CW11: 19637.409 | CX11: 95132 | CY11: 188966 | CZ11: 240024 | DA11: 261362 | DB11: 306134.11 | DC11: 362509.28 | DD11: 424644.25 | DE11: 484041.24 | DF11: =+SUM(AQ11:AT11) -> 607926.49 | DG11: =+SUM(AU11:AX11) -> 736113.97 | DH11: =+SUM(AY11:BB11) -> 773724.01 | DI11: =+SUM(BC11:BF11) -> 915612 | DJ11: =+SUM(BG11:BJ11) -> 999757 | DK11: =+SUM(BK11:BN11) -> 1182637 | DL11: =+SUM(BO11:BR11) -> 933234 | DM11: =+SUM(BS11:BV11) -> 1093554 | DN11: =+SUM(BW11:BZ11) -> 1864134 | DO11: =+SUM(CA11:CD11) -> 2150906 | DP11: =+SUM(CE11:CH11) -> 1925724 | DQ11: =+SUM(CI11:CL11) -> 2113187.4 | DR11: =+SUM(CM11:CP11) -> 2179201.9 | DS11: =DS34/(1+DS23) -> 2332881.2 | DT11: =DT34/(1+DT23) -> 2340487.4 | DU11: =DU34/(1+DU23) -> 2349812 | DV11: =DV34/(1+DV23) -> 2359950.6 | DY11: 2059099 | DZ11: 2059952.9
A12: % Rec Bruta | J12: 0.034332731 | K12: 0.044065995 | L12: 0.044198459 | M12: 0.056147557 | N12: 0.042747353 | O12: 0.087144789 | P12: 0.075176517 | Q12: 0.088044641 | R12: 0.056569918 | S12: 0.092175892 | T12: 0.080178937 | U12: 0.099474856 | V12: 0.070705494 | W12: 0.11127361 | X12: 0.076893502 | Y12: 0.09667243 | Z12: 0.068948476 | AA12: 0.10731459 | AB12: 0.082885948 | AC12: 0.095500984 | AD12: 0.068496597 | AE12: 0.11115612 | AF12: 0.084380686 | AG12: 0.093382683 | AH12: 0.068204669 | AI12: 0.10395158 | AJ12: 0.085491023 | AK12: 0.091780386 | AL12: 0.06800773 | AM12: 0.10516963 | AN12: 0.086995953 | AO12: 0.091471709 | AP12: 0.067877089 | AQ12: =AQ11/AQ3 -> 0.10832106 | AR12: =AR11/AR3 -> 0.093667109 | AS12: =AS11/AS3 -> 0.10661035 | AT12: =AT11/AT3 -> 0.066251861 | AU12: =AU11/AU3 -> 0.11395075 | AV12: =AV11/AV3 -> 0.096869562 | AW12: =AW11/AW3 -> 0.099107181 | AX12: =AX11/AX3 -> 0.071285641 | ... CP12: =CP11/CP3 -> 0.081254308 | CT12: 0.079017589 | CV12: 0 | CW12: 0.012608204 | CX12: 0.046693667 | CY12: 0.073868831 | CZ12: 0.084035043 | DA12: 0.084844707 | DB12: 0.085530913 | DC12: 0.08602835 | DD12: 0.084459838 | DE12: 0.085099439 | DF12: =DF11/DF3 -> 0.089653171 | DG12: =DG11/DG3 -> 0.092201954 | DH12: =DH11/DH3 -> 0.092313013 | DI12: =DI11/DI3 -> 0.095343694 | DJ12: =DJ11/DJ3 -> 0.090846618 | DK12: =DK11/DK3 -> 0.091274786 | DL12: =DL11/DL3 -> 0.090240731 | DM12: =DM11/DM3 -> 0.075988738 | ... DV12: =DV11/DV3 -> 0.082277903 | DY12: 0.093659505 | DZ12: 0.086599166
A13: yoy | AQ13: =+AQ11/AM11-1 -> 0.15846831 | AR13: =+AR11/AN11-1 -> 0.27236816 | AS13: =+AS11/AO11-1 -> 0.36845451 | AT13: =+AT11/AP11-1 -> 0.2205905 | AU13: =+AU11/AQ11-1 -> 0.31389653 | AV13: =+AV11/AR11-1 -> 0.26484141 | AW13: =+AW11/AS11-1 -> 0.099085507 | AX13: =+AX11/AT11-1 -> 0.19036726 | ... CP13: =+CP11/CL11-1 -> 0.11723735 | CT13: 0.01934395 | DG13: =+DG11/DF11-1 -> 0.21086017 | DH13: =+DH11/DG11-1 -> 0.051092676 | DI13: =+DI11/DH11-1 -> 0.18338321 | DJ13: =+DJ11/DI11-1 -> 0.091900281 | DK13: =+DK11/DJ11-1 -> 0.18292445 | DL13: =+DL11/DK11-1 -> -0.2108872 | DM13: =+DM11/DL11-1 -> 0.17178971 | DN13: =+DN11/DM11-1 -> 0.70465656 | ... DV13: =+DV11/DU11-1 -> 0.0043146563 | DY13: -0.05060291 | DZ13: 0.00041467961
A15: Deduções | C15: -53924 | D15: -86679 | E15: -73481 | F15: -121367 | G15: -51753 | H15: -83403 | I15: -72528 | J15: -147698.41 | K15: -81143.355 | L15: -127740.35 | M15: -110621.36 | N15: -186621 | O15: -102776 | P15: -161047 | Q15: -139124 | R15: -224243 | S15: -126158 | T15: -180732 | U15: -149591 | V15: -216749 | W15: -118316 | X15: -190269 | Y15: -163136 | Z15: -245126 | AA15: -143378 | AB15: -216654 | AC15: -191354 | AD15: -276497.87 | AE15: -174697.63 | AF15: -253273.68 | AG15: -221527.2 | AH15: -325794.54 | AI15: -209423.65 | AJ15: -288092.61 | AK15: -270849.74 | AL15: -396891.4 | AM15: -245987.48 | AN15: -319060.69 | AO15: -305820.52 | AP15: -446697.97 | AQ15: =+AQ18+AQ21 -> -275952.27 | AR15: =+AR18+AR21 -> -374948.71 | AS15: =+AS18+AS21 -> -354573.28 | AT15: =+AT18+AT21 -> -559351.64 | AU15: =+AU18+AU21 -> -343026.88 | AV15: =+AV18+AV21 -> -457348.27 | AW15: =+AW18+AW21 -> -421854.95 | AX15: =+AX18+AX21 -> -616285.29 | ... CP15: =+CP18+CP21 -> -1506598.7 | CT15: -1391131.5 | CV15: -335451 | CW15: -355382.41 | CX15: -506126.07 | CY15: -627190 | CZ15: -673230 | DA15: -716847 | DB15: -827883.87 | DC15: -975293.05 | DD15: -1165257.4 | DE15: -1317566.7 | DF15: =+DF18+DF21 -> -1564825.9 | DG15: =+DG18+DG21 -> -1838515.4 | DH15: =+DH18+DH21 -> -1929946.9 | DI15: =+DI18+DI21 -> -2158973 | DJ15: =+DJ18+DJ21 -> -2578348.5 | DK15: =+DK18+DK21 -> -3368449 | DL15: =+DL18+DL21 -> -2804425 | DM15: =+DM18+DM21 -> -3819444.8 | ... DV15: =+DV18+DV21 -> -6385492.3 | DY15: -4809653.1 | DZ15: -5250745.1
A16: % deduções | C16: -0.23417015 | D16: -0.26576585 | E16: -0.25925077 | F16: -0.27006814 | G16: -0.19756296 | H16: -0.21995332 | I16: -0.21059539 | J16: -0.25822601 | K16: -0.2332407 | L16: -0.25116057 | M16: -0.24184377 | N16: -0.25795621 | O16: -0.22822324 | P16: -0.24703529 | Q16: -0.23857899 | R16: -0.25694047 | S16: -0.22610784 | T16: -0.24191819 | U16: -0.22632349 | V16: -0.243472 | W16: -0.22014327 | X16: -0.23674633 | Y16: -0.22801969 | Z16: -0.23940541 | AA16: -0.22089657 | AB16: -0.2358339 | AC16: -0.22910418 | AD16: -0.23506729 | AE16: -0.22586376 | AF16: -0.23242671 | AG16: -0.22993138 | AH16: -0.23485282 | AI16: -0.2279566 | AJ16: -0.23167013 | AK16: -0.23033248 | AL16: -0.234901 | AM16: -0.22779983 | AN16: -0.23129345 | AO16: -0.23041571 | AP16: -0.23493233 | AQ16: =AQ15/AQ3 -> -0.22720231 | AR16: =AR15/AR3 -> -0.23000495 | AS16: =AS15/AS3 -> -0.22752738 | AT16: =AT15/AT3 -> -0.23524403 | AU16: =AU15/AU3 -> -0.22612577 | AV16: =AV15/AV3 -> -0.22939106 | AW16: =AW15/AW3 -> -0.22896289 | AX16: =AX15/AX3 -> -0.23428177 | ... CP16: =CP15/CP3 -> -0.22297582 | CT16: -0.22369239 | CV16: -0.2601898 | CW16: -0.22817338 | CX16: -0.24842201 | CY16: -0.24517528 | CZ16: -0.23570523 | DA16: -0.23270664 | DB16: -0.23130275 | DC16: -0.23145022 | DD16: -0.23176447 | DE16: -0.2316418 | DF16: =DF15/DF3 -> -0.23077067 | DG16: =DG15/DG3 -> -0.23028324 | DH16: =DH15/DH3 -> -0.23026197 | DI16: =DI15/DI3 -> -0.22481626 | DJ16: =DJ15/DJ3 -> -0.23429118 | DK16: =DK15/DK3 -> -0.25997365 | DL16: =DL15/DL3 -> -0.27117889 | DM16: =DM15/DM3 -> -0.26540509 | ... DV16: =DV15/DV3 -> -0.22262539 | DY16: -0.21877031 | DZ16: -0.22073813
A18: Imp vdas e merc | O18: -100794 | P18: -158555 | Q18: -136436 | R18: -221650 | S18: -123142 | T18: -177333 | U18: -146178 | V18: -213539 | W18: -114997 | X18: -187153 | Y18: -159553 | Z18: -241441 | AA18: -139172 | AB18: -212538 | AC18: -186722 | AD18: -271971.76 | AE18: -169782.3 | AF18: -248090.67 | AG18: -216403.73 | AH18: -320433.07 | AI18: -204000.37 | AJ18: -282065.54 | AK18: -264722.48 | AL18: -390372.77 | AM18: -239543.06 | AN18: -312252.02 | AO18: -298931.19 | AP18: -439375.16 | AQ18: =+AQ30-AQ7 -> -268487.16 | AR18: =+AR30-AR7 -> -366284.77 | AS18: =+AS30-AS7 -> -345146.24 | AT18: =+AT30-AT7 -> -550413.24 | AU18: =+AU30-AU7 -> -333218.58 | AV18: =+AV30-AV7 -> -446389.65 | AW18: =+AW30-AW7 -> -411493.94 | AX18: =+AX30-AX7 -> -605645.26 | ... CP18: =+CP30-CP7 -> -1466619.4 | CT18: -1355526.8 | CV18: 0 | CW18: 0 | CX18: 0 | CY18: -617435 | CZ18: -660192 | DA18: -703144 | DB18: -810403.76 | DC18: -954709.77 | DD18: -1141161.2 | DE18: -1290101.4 | DF18: =+SUM(AQ18:AT18) -> -1530331.4 | DG18: =+SUM(AU18:AX18) -> -1796747.4 | DH18: =+SUM(AY18:BB18) -> -1886044.9 | DI18: =+SUM(BC18:BF18) -> -2087593 | DJ18: =+SUM(BG18:BJ18) -> -2519699.5 | DK18: =+SUM(BK18:BN18) -> -3299556 | DL18: =+SUM(BO18:BR18) -> -2747800 | DM18: =+SUM(BS18:BV18) -> -3741720.6 | DN18: =+SUM(BW18:BZ18) -> -4383810 | DO18: =+SUM(CA18:CD18) -> -5081077 | DP18: =+SUM(CE18:CH18) -> -3803367 | DQ18: =+SUM(CI18:CL18) -> -4273151.8 | DR18: =+SUM(CM18:CP18) -> -4595843.6 | DS18: =+DS30-DS7 -> -4980866.7 | DT18: =+DT30-DT7 -> -5368052 | DU18: =+DU30-DU7 -> -5775403.9 | DV18: =+DV30-DV7 -> -6213362.3 | DY18: -4648191 | DZ18: -5094727.4
A19: % deduções | O19: 0.98071534 | P19: 0.98452626 | Q19: 0.98067911 | R19: 0.98843665 | S19: 0.97609347 | T19: 0.98119315 | U19: 0.97718446 | V19: 0.98519024 | W19: 0.971948 | X19: 0.98362319 | Y19: 0.97803673 | Z19: 0.98496691 | AA19: 0.97066496 | AB19: 0.98100197 | AC19: 0.97579356 | AD19: 0.98363057 | AE19: 0.97186381 | AF19: 0.97953591 | AG19: 0.97687205 | AH19: 0.98354342 | AI19: 0.9741038 | AJ19: 0.9790794 | AK19: 0.97737762 | AL19: 0.98357577 | AM19: 0.97380182 | AN19: 0.97866026 | AO19: 0.97747263 | AP19: 0.98360679 | AQ19: =AQ18/AQ15 -> 0.97294785 | AR19: =AR18/AR15 -> 0.976893 | AS19: =AS18/AS15 -> 0.973413 | AT19: =AT18/AT15 -> 0.98402006 | AU19: =AU18/AU15 -> 0.9714066 | AV19: =AV18/AV15 -> 0.97603879 | AW19: =AW18/AW15 -> 0.9754394 | AX19: =AX18/AX15 -> 0.98273521 | ... CP19: =CP18/CP15 -> 0.97346387 | CT19: 0.97440594 | CV19: 0 | CW19: 0 | CX19: 0 | CY19: 0.9844465 | CZ19: 0.98063366 | DA19: 0.98088434 | DB19: 0.97888579 | DC19: 0.97889529 | DD19: 0.97932109 | DE19: 0.97915457 | DF19: =DF18/DF15 -> 0.97795634 | DG19: =DG18/DG15 -> 0.97728168 | DH19: =DH18/DH15 -> 0.97725222 | DI19: =DI18/DI15 -> 0.96693798 | DJ19: =DJ18/DJ15 -> 0.97725327 | DK19: =DK18/DK15 -> 0.97954756 | DL19: =DL18/DL15 -> 0.9798087 | DM19: =DM18/DM15 -> 0.97965038 | ... DV19: =DV18/DV15 -> 0.97304357 | DY19: 0.96642958 | DZ19: 0.97028656
A20: % Rec Bruta Merc | O20: -0.24518897 | P20: -0.26298287 | Q20: -0.25655799 | R20: -0.26919788 | S20: -0.2431114 | T20: -0.2580594 | U20: -0.24558981 | V20: -0.25811649 | W20: -0.2407578 | X20: -0.25226686 | Y20: -0.24687792 | Z20: -0.25326891 | AA20: -0.24019275 | AB20: -0.25226254 | AC20: -0.24716266 | AD20: -0.24822171 | AE20: -0.24695992 | AF20: -0.24865171 | AG20: -0.247749 | AH20: -0.24789558 | AI20: -0.24781405 | AJ20: -0.24802759 | AK20: -0.24787156 | AL20: -0.24790219 | AM20: -0.24790385 | AN20: -0.2479263 | AO20: -0.24790097 | AP20: -0.24790833 | AQ20: =+AVERAGE(AM20:AP20) -> -0.24790986 | AR20: =+AVERAGE(AN20:AQ20) -> -0.24791136 | AS20: =+AVERAGE(AO20:AR20) -> -0.24790763 | AT20: =+AVERAGE(AP20:AS20) -> -0.2479093 | AU20: =+AVERAGE(AQ20:AT20) -> -0.24790954 | AV20: =+AVERAGE(AR20:AU20) -> -0.24790946 | AW20: =+AVERAGE(AS20:AV20) -> -0.24790898 | AX20: =+AVERAGE(AT20:AW20) -> -0.24790932 | ... BF20: =+AVERAGE(BB20:BE20) -> -0.24790927 | BG20: =+BG18/BG7 -> -0.2329598 | BH20: =+BH18/BH7 -> -0.23565653 | BI20: =+BI18/BI7 -> -0.23397076 | BJ20: =+BJ18/BJ7 -> -0.2828064 | BK20: =+BK18/BK7 -> -0.28092429 | BL20: =+BL18/BL7 -> -0.28076596 | BM20: =+BM18/BM7 -> -0.27905294 | BN20: =+BN18/BN7 -> -0.28025859 | ... CK20: =+CK18/CK7 -> -0.23534834 | CL20: =+AVERAGE(CJ20:CK20) -> -0.23666814 | CM20: =+AVERAGE(CK20:CL20) -> -0.23600824 | CN20: =+AVERAGE(CL20:CM20) -> -0.23633819 | CO20: =+AVERAGE(CM20:CN20) -> -0.23617321 | CP20: =+AVERAGE(CN20:CO20) -> -0.2362557 | CT20: -0.23666814 | CV20: #DIV/0! | CW20: 0 | CX20: 0 | CY20: -0.26061314 | CZ20: -0.25234643 | DA20: -0.2494203 | DB20: -0.2475961 | DC20: -0.2478912 | DD20: -0.2479103 | DE20: -0.24791014 | DF20: =DF18/DF7 -> -0.24790952 | DH20: =DH18/DH7 -> -0.24790927 | DI20: =DI18/DI7 -> -0.24029388 | DJ20: =DJ18/DJ7 -> -0.2518407 | DK20: =DK18/DK7 -> -0.28023494 | DL20: =DL18/DL7 -> -0.29205906 | DM20: =DM18/DM7 -> -0.28138639 | DN20: =DN18/DN7 -> -0.27468161 | DO20: =DO18/DO7 -> -0.30267176 | ... DR20: =DR18/DR7 -> -0.23620971 | DS20: =+AVERAGE(DQ20:DR20) -> -0.23594703 | DT20: =+AVERAGE(DR20:DS20) -> -0.23607837 | DU20: =+AVERAGE(DS20:DT20) -> -0.2360127 | DV20: =+AVERAGE(DT20:DU20) -> -0.23604554 | DY20: -0.23327447 | DZ20: -0.23448549
A21: Imp. Prod/serv fin. | O21: -1982 | P21: -2492 | Q21: -2688 | R21: -2593 | S21: -3016 | T21: -3399 | U21: -3413 | V21: -3210 | W21: -3319 | X21: -3116 | Y21: -3583 | Z21: -3685 | AA21: -4206 | AB21: -4116 | AC21: -4632 | AD21: -4526.1127 | AE21: -4915.3262 | AF21: -5183.0161 | AG21: -5123.4708 | AH21: -5361.4626 | AI21: -5423.2773 | AJ21: -6027.0715 | AK21: -6127.2662 | AL21: -6518.6359 | AM21: -6444.4237 | AN21: -6808.671 | AO21: -6889.3307 | AP21: -7322.8157 | AQ21: =+AQ34-AQ11 -> -7465.1034 | AR21: =+AR34-AR11 -> -8663.9396 | AS21: =+AS34-AS11 -> -9427.0407 | AT21: =+AT34-AT11 -> -8938.4059 | AU21: =+AU34-AU11 -> -9808.3047 | AV21: =+AV34-AV11 -> -10958.618 | AW21: =+AW34-AW11 -> -10361.012 | AX21: =+AX34-AX11 -> -10640.038 | ... CP21: =+CP34-CP11 -> -39979.297 | CT21: -35604.697 | CV21: 0 | CW21: 0 | CX21: 0 | CY21: -9755 | CZ21: -13038 | DA21: -13703 | DB21: -17480.113 | DC21: -20583.276 | DD21: -24096.251 | DE21: -27465.241 | DF21: =+SUM(AQ21:AT21) -> -34494.49 | DG21: =+SUM(AU21:AX21) -> -41767.973 | DH21: =+SUM(AY21:BB21) -> -43902.006 | DI21: =+SUM(BC21:BF21) -> -71380 | DJ21: =+SUM(BG21:BJ21) -> -58649 | DK21: =+SUM(BK21:BN21) -> -68893 | DL21: =+SUM(BO21:BR21) -> -56625 | DM21: =+SUM(BS21:BV21) -> -77724.251 | DN21: =+SUM(BW21:BZ21) -> -168792 | DO21: =+SUM(CA21:CD21) -> -209397 | DP21: =+SUM(CE21:CH21) -> -161308 | DQ21: =+SUM(CI21:CL21) -> -154429.7 | DR21: =+SUM(CM21:CP21) -> -158806.9 | DS21: =+DS34-DS11 -> -170245.41 | DT21: =+DT34-DT11 -> -170680.44 | DU21: =+DU34-DU11 -> -171420.7 | DV21: =+DV34-DV11 -> -172130.06 | DY21: -161462.06 | DZ21: -156017.69
A22: % deduções | O22: 0.019284658 | P22: 0.015473744 | Q22: 0.019320894 | R22: 0.011563349 | S22: 0.02390653 | T22: 0.018806852 | U22: 0.022815544 | V22: 0.014809757 | W22: 0.028051996 | X22: 0.016376814 | Y22: 0.02196327 | Z22: 0.015033085 | AA22: 0.029335044 | AB22: 0.018998034 | AC22: 0.024206445 | AD22: 0.016369431 | AE22: 0.028136194 | AF22: 0.020464093 | AG22: 0.023127954 | AH22: 0.016456576 | AI22: 0.025896203 | AJ22: 0.020920604 | AK22: 0.022622381 | AL22: 0.01642423 | AM22: 0.026198178 | AN22: 0.021339736 | AO22: 0.022527366 | AP22: 0.016393215 | AQ22: =AQ21/AQ15 -> 0.027052155 | AR22: =AR21/AR15 -> 0.023106999 | AS22: =AS21/AS15 -> 0.026587003 | AT22: =AT21/AT15 -> 0.01597994 | AU22: =AU21/AU15 -> 0.0285934 | AV22: =AV21/AV15 -> 0.02396121 | AW22: =AW21/AW15 -> 0.024560603 | AX22: =AX21/AX15 -> 0.017264793 | ... CP22: =CP21/CP15 -> 0.026536129 | CT22: 0.025594056 | CV22: 0 | CW22: 0 | CX22: 0 | CY22: 0.015553501 | CZ22: 0.019366338 | DA22: 0.019115655 | DB22: 0.021114209 | DC22: 0.021104709 | DD22: 0.020678908 | DE22: 0.020845428 | DF22: =DF21/DF15 -> 0.02204366 | DG22: =DG21/DG15 -> 0.022718315 | DH22: =DH21/DH15 -> 0.022747779 | DI22: =DI21/DI15 -> 0.033062016 | DJ22: =DJ21/DJ15 -> 0.022746731 | DK22: =DK21/DK15 -> 0.02045244 | DL22: =DL21/DL15 -> 0.020191305 | DM22: =DM21/DM15 -> 0.02034962 | ... DV22: =DV21/DV15 -> 0.026956427 | DY22: 0.033570417 | DZ22: 0.029713438
A23: % Rec Bruta Serv Fin | O23: -0.050504536 | P23: -0.050847803 | Q23: -0.052354797 | R23: -0.052520711 | S23: -0.058642815 | T23: -0.056744574 | U23: -0.051909535 | V23: -0.050996902 | W23: -0.05549796 | X23: -0.050422344 | Y23: -0.051804407 | Z23: -0.052198425 | AA23: -0.060383318 | AB23: -0.054054764 | AC23: -0.058070582 | AD23: -0.056176772 | AE23: -0.057171359 | AF23: -0.056368369 | AG23: -0.056946771 | AH23: -0.056665818 | AI23: -0.056788079 | AJ23: -0.056692259 | AK23: -0.056773232 | AL23: -0.056729847 | AM23: -0.056745854 | AN23: -0.056735298 | AO23: -0.056746058 | AP23: -0.056739264 | AQ23: =+AVERAGE(AM23:AP23) -> -0.056741619 | AR23: =+AVERAGE(AN23:AQ23) -> -0.05674056 | AS23: =+AVERAGE(AO23:AR23) -> -0.056741875 | AT23: =+AVERAGE(AP23:AS23) -> -0.056740829 | AU23: =+AVERAGE(AQ23:AT23) -> -0.056741221 | AV23: =+AVERAGE(AR23:AU23) -> -0.056741121 | AW23: =+AVERAGE(AS23:AV23) -> -0.056741262 | AX23: =+AVERAGE(AT23:AW23) -> -0.056741108 | ... BF23: =+AVERAGE(BB23:BE23) -> -0.056741167 | BG23: =+BG21/BG11 -> -0.060331942 | BH23: =+BH21/BH11 -> -0.058117774 | BI23: =+BI21/BI11 -> -0.056873889 | BJ23: =+BJ21/BJ11 -> -0.059335667 | BK23: =+BK21/BK11 -> -0.060252952 | BL23: =+BL21/BL11 -> -0.059971106 | BM23: =+BM21/BM11 -> -0.056413336 | BN23: =+BN21/BN11 -> -0.056897393 | ... CK23: =+CK21/CK11 -> -0.073622742 | CL23: =+AVERAGE(CJ23:CK23) -> -0.072454695 | CM23: =+AVERAGE(CK23:CL23) -> -0.073038718 | CN23: =+AVERAGE(CL23:CM23) -> -0.072746707 | CO23: =+AVERAGE(CM23:CN23) -> -0.072892713 | CP23: =+AVERAGE(CN23:CO23) -> -0.07281971 | CT23: -0.072454695 | CV23: #DIV/0! | CW23: 0 | CX23: 0 | CY23: -0.051623043 | CZ23: -0.054319568 | DA23: -0.052429198 | DB23: -0.057099526 | DC23: -0.056779997 | DD23: -0.056744559 | DE23: -0.056741531 | DF23: =DF21/DF11 -> -0.056741218 | DG23: =DG21/DG11 -> -0.056741176 | DH23: =DH21/DH11 -> -0.05674117 | DI23: =DI21/DI11 -> -0.077958786 | DJ23: =DJ21/DJ11 -> -0.058663255 | DK23: =DK21/DK11 -> -0.058253716 | DL23: =DL21/DL11 -> -0.060676101 | DM23: =DM21/DM11 -> -0.071074909 | ... DR23: =DR21/DR11 -> -0.072873882 | DS23: =+AVERAGE(DQ23:DR23) -> -0.07297646 | DT23: =+AVERAGE(DR23:DS23) -> -0.072925171 | DU23: =+AVERAGE(DS23:DT23) -> -0.072950815 | DV23: =+AVERAGE(DT23:DU23) -> -0.072937993 | DY23: -0.078413937 | DZ23: -0.075738475
AV25: =+AV26-AU26 -> 362454 | BD25: =+BD26-BC26 -> 415808 | BH25: =+BH26-BG26 -> 391812 | BL25: =+BL26-BK26 -> 399887 | BP25: =+BP26-BO26 -> -1055255 | BX25: =+BX26-BW26 -> 1013313 | CB25: =+CB26-CA26 -> 728791
A26: Receita Liq | C26: 176353 | D26: 239469 | E26: 209955 | F26: 328027 | G26: 210204 | H26: 295782 | I26: 271867 | J26: 424275 | K26: 266752 | L26: 380860 | M26: 346787 | N26: 536839 | O26: 347555 | P26: 490872 | Q26: 444012 | R26: 648500 | S26: 431797 | T26: 566347 | U26: 511370 | V26: 673493 | W26: 419134 | X26: 613414 | Y26: 552311 | Z26: 778769 | AA26: 505695 | AB26: 702018 | AC26: 643873 | AD26: 899752 | AE26: 598767 | AF26: 836419 | AG26: 741922 | AH26: 1061434 | AI26: 709276 | AJ26: 955454 | AK26: 905058 | AL26: 1292720 | AM26: 833853 | AN26: 1060402 | AO26: 1021435 | AP26: 1454692 | AQ26: =AQ30+AQ34 -> 938614 | AR26: =AR30+AR34 -> 1255228 | AS26: =AS30+AS34 -> 1203803 | AT26: =AT30+AT34 -> 1818399 | AU26: =AU30+AU34 -> 1173947 | AV26: =AV30+AV34 -> 1536401 | AW26: =AW30+AW34 -> 1420605 | AX26: =AX30+AX34 -> 2014245 | ... CP26: =CP30+CP34 -> 5250181.9 | CT26: 4827817.4 | CU26: =+CK26/CT26-1 -> -0.26188758 | CV26: 953804 | CW26: 1202128 | CX26: 1531238 | CY26: 1930939 | CZ26: 2183007 | DA26: 2363628 | DB26: 2751338 | DC26: 3238542 | DD26: 3862508 | DE26: 4370382 | DF26: =+SUM(AQ26:AT26) -> 5216044 | DG26: =+SUM(AU26:AX26) -> 6145198 | DH26: =+SUM(AY26:BB26) -> 6451580 | DI26: =+SUM(BC26:BF26) -> 7444305 | DJ26: =+SUM(BG26:BJ26) -> 8426541 | DK26: =+SUM(BK26:BN26) -> 9588437 | DL26: =+SUM(BO26:BR26) -> 7537180 | DM26: =DM30+DM34 -> 10571556 | DN26: =DN30+DN34 -> 13271137 | DO26: =DO30+DO34 -> 13647849 | DP26: =DP30+DP34 -> 14436366 | DQ26: =DQ30+DQ34 -> 15816431 | DR26: =DR30+DR34 -> 16881176 | DS26: =DS30+DS34 -> 18291875 | DT26: =DT30+DT34 -> 19540187 | ... DV26: =DV30+DV34 -> 22297186 | DY26: 17175292 | DZ26: 18536469
A27: var y-o-y | G27: 0.19195024 | H27: 0.23515779 | I27: 0.29488224 | J27: 0.29341487 | K27: 0.26901486 | L27: 0.28763752 | M27: 0.27557592 | N27: 0.26530906 | O27: 0.30291432 | P27: 0.28885155 | Q27: 0.28035941 | R27: 0.20799718 | S27: 0.24238466 | T27: 0.15375699 | U27: 0.15170311 | V27: 0.038539707 | W27: -0.029326281 | X27: 0.083106293 | Y27: 0.080061404 | Z27: 0.15631343 | AA27: 0.20652345 | AB27: 0.14444405 | AC27: 0.16577979 | AD27: 0.15535159 | AE27: 0.1840477 | AF27: 0.19144951 | AG27: 0.15228003 | AH27: 0.17969618 | AI27: 0.18456094 | AJ27: 0.14231504 | AK27: 0.21988295 | AL27: 0.21789956 | AM27: 0.17563967 | AN27: 0.10984098 | AO27: 0.12858513 | AP27: 0.1252955 | AQ27: =AQ26/AM26-1 -> 0.12563485 | AR27: =AR26/AN26-1 -> 0.18372844 | AS27: =AS26/AO26-1 -> 0.17854097 | AT27: =AT26/AP26-1 -> 0.25002337 | AU27: =AU26/AQ26-1 -> 0.25072394 | AV27: =AV26/AR26-1 -> 0.22400154 | AW27: =AW26/AS26-1 -> 0.18009757 | AX27: =AX26/AT26-1 -> 0.10770243 | ... CP27: =CP26/CL26-1 -> 0.087485595 | CT27: 0.045611976 | CW27: 0.26035118 | CX27: 0.27377284 | CY27: 0.26103127 | CZ27: 0.13054167 | DA27: 0.082739542 | DB27: 0.16403173 | DC27: 0.17707893 | DD27: 0.1926688 | DE27: 0.13148814 | DF27: =DF26/DE26-1 -> 0.19349842 | DG27: =DG26/DF26-1 -> 0.17813385 | DH27: =DH26/DG26-1 -> 0.04985714 | DI27: =DI26/DH26-1 -> 0.15387316 | DJ27: =DJ26/DI26-1 -> 0.13194462 | DK27: =DK26/DJ26-1 -> 0.13788528 | DL27: =DL26/DK26-1 -> -0.21393028 | DM27: =DM26/DL26-1 -> 0.40258773 | ... DV27: =DV26/DU26-1 -> 0.068194097 | DY27: 0.070698049 | DZ27: 0.079252074
A28: var q-o-q | D28: 0.35789581 | E28: -0.12324769 | F28: 0.56236813 | G28: -0.3591869 | H28: 0.4071188 | I28: -0.080853466 | J28: 0.56059765 | K28: -0.37127571 | L28: 0.42776811 | M28: -0.08946332 | N28: 0.54803669 | O28: -0.35258988 | P28: 0.41235776 | Q28: -0.095462768 | R28: 0.46054611 | S28: -0.33416037 | T28: 0.31160476 | U28: -0.097072996 | V28: 0.31703659 | W28: -0.37767133 | X28: 0.46352718 | Y28: -0.099611355 | Z28: 0.41001899 | AA28: -0.35064827 | AB28: 0.38822413 | AC28: -0.082825512 | AD28: 0.39740601 | AE28: -0.33451996 | AF28: 0.3969023 | AG28: -0.11297806 | AH28: 0.43065444 | AI28: -0.33177569 | AJ28: 0.3470835 | AK28: -0.052745606 | AL28: 0.42832835 | AM28: -0.3549624 | AN28: 0.27168937 | AO28: -0.036747384 | AP28: 0.42416502 | AQ28: =AQ26/AP26-1 -> -0.35476788 | AR28: =AR26/AQ26-1 -> 0.33732077 | AS28: =AS26/AR26-1 -> -0.040968653 | AT28: =AT26/AS26-1 -> 0.51054533 | AU28: =AU26/AT26-1 -> -0.35440627 | AV28: =AV26/AU26-1 -> 0.30874818 | AW28: =AW26/AV26-1 -> -0.075368345 | AX28: =AX26/AW26-1 -> 0.4178783 | ... CP28: =CP26/CO26-1 -> 0.36698256 | CT28: 0.35480716
W29: 0.17138673 | X29: 0.26216452 | Y29: 0.230027 | Z29: 0.33642175 | AA29: 0.17876674 | AB29: 0.25581398 | AC29: 0.23094315 | AD29: 0.33447612 | BQ29: =+BQ26/BI26-1 -> -0.078860673 | BR29: =+BR26/BJ26-1 -> 0.084660995 | BS29: =+BS26/BK26-1 -> -0.16421976 | BT29: =+BT26/BL26-1 -> 0.086513374 | BU29: =+BU26/BM26-1 -> 0.18085294 | BV29: =+BV26/BN26-1 -> 0.21802911 | BW29: =+BW26/BK26-1 -> 0.38100551 | BX29: =+BX26/BL26-1 -> 0.5821687 | DM29: =+DM30/DK30-1 -> 0.12756018 | DN29: =+DN30/DL30-1 -> 0.73795835 | DO29: =+DO30/DM30-1 -> 0.22506019 | DP29: =+DP30/DN30-1 -> 0.094693712 | DQ29: =+DQ30/DO30-1 -> 0.18377509 | DR29: =+DR30/DP30-1 -> 0.17273038
A30: Vendas de Merc. | G30: 198012 | H30: 279148 | I30: 255413 | J30: 403861 | K30: 250995 | L30: 357709 | M30: 320523 | N30: 506879 | O30: 310293 | P30: 444355 | Q30: 395358 | R30: 601722 | S30: 383383 | T30: 509846 | U30: 449034 | V30: 613758 | W30: 362649 | X30: 554732 | Y30: 486730 | Z30: 711858 | AA30: 440246 | AB30: 629989 | AC30: 568740 | AD30: 823709 | AE30: 517707 | AF30: 749653 | AG30: 657076 | AH30: 972180 | AI30: 619199 | AJ30: 855169 | AK30: 803260 | AL30: 1184332 | AM30: 726731 | AN30: 947203 | AO30: 906918 | AP30: 1332954 | AQ30: 814516 | AR30: 1111198 | AS30: 1047091 | AT30: 1669807 | AU30: 1010895 | AV30: 1354226 | AW30: 1248365 | AX30: 1837366 | AY30: 1076148 | AZ30: 1464688 | BA30: 1260418 | BB30: 1920504 | BC30: 1234684 | BD30: 1630456 | BE30: 1512578 | BF30: 2222355 | BG30: 1398819 | BH30: 1780031 | BI30: 1711461 | BJ30: 2595122 | BK30: 1650337 | BL30: 2019374 | BM30: 1931924 | BN30: 2873058 | BO30: 1550180 | BP30: 539636 | BQ30: 1651197 | BR30: 2919558 | BS30: 1364417 | BT30: 2258723 | BU30: 2371924.4 | BV30: 3560662 | BW30: 2229665 | BX30: 3175745 | BY30: 2615521 | BZ30: 3554864 | CA30: 2277999 | CB30: 2985304 | CC30: 2636106 | CD30: 3806931 | CE30: 2461296 | CF30: 3079923 | CG30: 2955952 | CH30: 4174779 | CI30: 2756840 | CJ30: 3649669 | CK30: 3079149 | CL30: =CL278 -> 4372015.7 | CM30: =CM278 -> 2935811.1 | CN30: =CN278 -> 3851397 | CO30: =CO278 -> 3332429 | CP30: =CP278 -> 4741143.6 | CT30: 4372015.7 | CU30: =+CK30/CT30-1 -> -0.29571411 | CX30: 1436106 | CY30: 1751728 | CZ30: 1956021 | DA30: 2115969 | DB30: 2462684 | DC30: 2896616 | DD30: 3461960 | DE30: 3913806 | DF30: =+SUM(AQ30:AT30) -> 4642612 | DG30: =+SUM(AU30:AX30) -> 5450852 | DH30: =+SUM(AY30:BB30) -> 5721758 | DI30: =+SUM(BC30:BF30) -> 6600073 | DJ30: =+SUM(BG30:BJ30) -> 7485433 | DK30: =+SUM(BK30:BN30) -> 8474693 | DL30: =+SUM(BO30:BR30) -> 6660571 | DM30: =+SUM(BS30:BV30) -> 9555726.4 | DN30: =+SUM(BW30:BZ30) -> 11575795 | DO30: =+SUM(CA30:CD30) -> 11706340 | DP30: =+SUM(CE30:CH30) -> 12671950 | DQ30: =+SUM(CI30:CL30) -> 13857674 | DR30: =+SUM(CM30:CP30) -> 14860781 | DS30: =DS278 -> 16129239 | DT30: =DT278 -> 17370380 | DU30: =DU278 -> 18695330 | DV30: =DV278 -> 20109365 | DY30: 15277655 | DZ30: 16632534
A31: % Rec Líquida | J31: 0.95188498 | K31: 0.94093015 | L31: 0.93921388 | M31: 0.92426475 | N31: 0.94419183 | O31: 0.89278819 | P31: 0.90523599 | Q31: 0.89042188 | R31: 0.92786739 | S31: 0.88787787 | T31: 0.90023607 | U31: 0.87810001 | V31: 0.91130569 | W31: 0.86523403 | X31: 0.90433541 | Y31: 0.88126074 | Z31: 0.91408107 | AA31: 0.87057614 | AB31: 0.89739722 | AC31: 0.88331084 | AD31: 0.91548449 | AE31: 0.8646218 | AF31: 0.89626491 | AG31: 0.88564027 | AH31: 0.91591187 | AI31: 0.87300148 | AJ31: 0.89503943 | AK31: 0.88752323 | AL31: 0.91615508 | AM31: 0.87153371 | AN31: 0.89324898 | AO31: 0.88788616 | AP31: 0.91631356 | AQ31: =AQ30/AQ26 -> 0.86778591 | AR31: =AR30/AR26 -> 0.88525591 | AS31: =AS30/AS26 -> 0.86981923 | AT31: =AT30/AT26 -> 0.91828416 | AU31: =AU30/AU26 -> 0.86110787 | AV31: =AV30/AV26 -> 0.88142744 | AW31: =AW30/AW26 -> 0.87875588 | AX31: =AX30/AX26 -> 0.91218596 | ... CP31: =CP30/CP26 -> 0.9030437 | CT31: 0.90558846 | CX31: 0.93787249 | CY31: 0.90718971 | CZ31: 0.89602141 | DA31: 0.89522082 | DB31: 0.89508595 | DC31: 0.89441977 | DD31: 0.89629847 | DE31: 0.8955295 | DF31: =DF30/DF26 -> 0.89006381 | DG31: =DG30/DG26 -> 0.88700999 | DH31: =DH30/DH26 -> 0.88687701 | DI31: =DI30/DI26 -> 0.88659358 | DJ31: =DJ30/DJ26 -> 0.88831621 | DK31: =DK30/DK26 -> 0.88384509 | DL31: =DL30/DL26 -> 0.88369536 | DM31: =DM30/DM26 -> 0.90390916 | ... DV31: =DV30/DV26 -> 0.90187907 | DY31: 0.88951355 | DZ31: 0.89728706
A32: var y-o-y | N32: 0.25508281 | O32: 0.23625172 | P32: 0.24222483 | Q32: 0.23347778 | R32: 0.18711172 | S32: 0.23555156 | T32: 0.14738441 | U32: 0.13576556 | V32: 0.020002593 | W32: -0.054081689 | X32: 0.088038349 | Y32: 0.0839491 | Z32: 0.15983498 | AA32: 0.21397274 | AB32: 0.13566371 | AC32: 0.16849177 | AD32: 0.15712544 | AE32: 0.17594936 | AF32: 0.18994617 | AG32: 0.15531877 | AH32: 0.18024691 | AI32: 0.19604139 | AJ32: 0.14075312 | AK32: 0.22247655 | AL32: 0.21822296 | AM32: 0.17366307 | AN32: 0.10762083 | AO32: 0.12904663 | AP32: 0.12549015 | AQ32: =AQ30/AM30-1 -> 0.12079435 | AR32: =AR30/AN30-1 -> 0.17313606 | AS32: =AS30/AO30-1 -> 0.15455973 | AT32: =AT30/AP30-1 -> 0.25271165 | AU32: =AU30/AQ30-1 -> 0.24109901 | AV32: =AV30/AR30-1 -> 0.2187081 | AW32: =AW30/AS30-1 -> 0.19222207 | AX32: =AX30/AT30-1 -> 0.10034633 | ... CP32: =CP30/CL30-1 -> 0.084429682 | CT32: 0.047244834 | CY32: 0.21977626 | CZ32: 0.1166237 | DA32: 0.081772128 | DB32: 0.16385637 | DC32: 0.17620287 | DD32: 0.19517395 | DE32: 0.13051739 | DF32: =DF30/DE30-1 -> 0.18621414 | DG32: =DG30/DF30-1 -> 0.17409165 | DH32: =DH30/DG30-1 -> 0.049699753 | DI32: =DI30/DH30-1 -> 0.15350439 | DJ32: =DJ30/DI30-1 -> 0.13414397 | DK32: =DK30/DJ30-1 -> 0.13215802 | DL32: =DL30/DK30-1 -> -0.21406345 | DM32: =DM30/DL30-1 -> 0.43467075 | ... DV32: =DV30/DU30-1 -> 0.07563575 | DY32: 0.088863761 | DZ32: 0.088683721
BS33: =+BS30/BK30-1 -> -0.17324946 | BT33: =+BT30/BL30-1 -> 0.11852634 | BU33: =+BU30/BM30-1 -> 0.22775242 | BV33: =+BV30/BN30-1 -> 0.23932828 | BW33: =+BW30/BK30-1 -> 0.35103618 | BX33: =+BX30/BL30-1 -> 0.57263835 | BY33: =+BY30/BM30-1 -> 0.35384259 | BZ33: =+BZ30/BN30-1 -> 0.23731021 | CA33: =+CA30/BO30-1 -> 0.46950612 | DN33: =+DN30/DK30-1 -> 0.365925
A34: Prod/Serv Fin. | G34: 12192 | H34: 16634 | I34: 16454 | J34: 20414 | K34: 15757 | L34: 23151 | M34: 26264 | N34: 29960 | O34: 37200 | P34: 46500 | Q34: 48600 | R34: 46778 | S34: 48414 | T34: 56501 | U34: 62336 | V34: 59735 | W34: 56485 | X34: 58682 | Y34: 65581 | Z34: 66911 | AA34: 65449 | AB34: 72029 | AC34: 75133 | AD34: 76043 | AE34: 81060 | AF34: 86766 | AG34: 84846 | AH34: 89254 | AI34: 90077 | AJ34: 100285 | AK34: 101798 | AL34: 108388 | AM34: 107122 | AN34: 113199 | AO34: 114517 | AP34: 121738 | AQ34: 124098 | AR34: 144030 | AS34: 156712 | AT34: 148592 | AU34: 163052 | AV34: 182175 | AW34: 172240 | AX34: 176879 | AY34: 171221 | AZ34: 182892 | BA34: 185411 | BB34: 190298 | BC34: 180640 | BD34: 200676 | BE34: 233799 | BF34: 229117 | BG34: 229466 | BH34: 240066 | BI34: 231827 | BJ34: 239749 | BK34: 241780 | BL34: 272630 | BM34: 293831 | BN34: 305503 | BO34: 313581 | BP34: 268870 | BQ34: 138842 | BR34: 155316 | BS34: 216977 | BT34: 231570 | BU34: 256364.97 | BV34: 310917.78 | BW34: 383359 | BX34: 450592 | BY34: 402111 | BZ34: 459280 | CA34: 497293 | CB34: 518779 | CC34: 460990 | CD34: 464447 | CE34: 446953 | CF34: 440468 | CG34: 434557 | CH34: 442438 | CI34: 500736 | CJ34: 517897 | CK34: 484323 | CL34: =(Cartao!CL64)*1000/(1+CL45) -> 455801.65 | CM34: =(Cartao!CM64)*1000/(1+CM45) -> 498422.77 | CN34: =(Cartao!CN64)*1000/(1+CN45) -> 504654.28 | CO34: =(Cartao!CO64)*1000/(1+CO45) -> 508279.74 | CP34: =(Cartao!CP64)*1000/(1+CP45) -> 509038.23 | CT34: 455801.65 | CU34: =+CK34/CT34-1 -> 0.06257403 | CV34: 0 | CW34: 45280 | CX34: 95132 | CY34: 179078 | CZ34: 226986 | DA34: 247659 | DB34: 288654 | DC34: 341926 | DD34: 400548 | DE34: 456576 | DF34: =+SUM(AQ34:AT34) -> 573432 | DG34: =+SUM(AU34:AX34) -> 694346 | DH34: =+SUM(AY34:BB34) -> 729822 | DI34: =+SUM(BC34:BF34) -> 844232 | DJ34: =+SUM(BG34:BJ34) -> 941108 | DK34: =+SUM(BK34:BN34) -> 1113744 | DL34: =+SUM(BO34:BR34) -> 876609 | DM34: =+SUM(BS34:BV34) -> 1015829.7 | DN34: =+SUM(BW34:BZ34) -> 1695342 | DO34: =+SUM(CA34:CD34) -> 1941509 | DP34: =+SUM(CE34:CH34) -> 1764416 | DQ34: =+SUM(CI34:CL34) -> 1958757.7 | DR34: =+SUM(CM34:CP34) -> 2020395 | DS34: =(Cartao!DR64)*1000/(1+DS45) -> 2162635.8 | DT34: =(Cartao!DS64)*1000/(1+DT45) -> 2169807 | DU34: =(Cartao!DT64)*1000/(1+DU45) -> 2178391.3 | DV34: =(Cartao!DU64)*1000/(1+DV45) -> 2187820.5 | DY34: 1897637 | DZ34: 1903935.2
A35: % Rec Líquida | J35: 0.04811502 | K35: 0.059069848 | L35: 0.060786116 | M35: 0.07573525 | N35: 0.055808166 | O35: 0.10703342 | P35: 0.09472938 | Q35: 0.1094565 | R35: 0.072132614 | S35: 0.11212213 | T35: 0.099763926 | U35: 0.12189999 | V35: 0.088694315 | W35: 0.13476597 | X35: 0.095664592 | Y35: 0.11873926 | Z35: 0.085918931 | AA35: 0.12942386 | AB35: 0.10260278 | AC35: 0.11668916 | AD35: 0.084515511 | AE35: 0.1353782 | AF35: 0.10373509 | AG35: 0.11435973 | AH35: 0.08408813 | AI35: 0.12699852 | AJ35: 0.10496057 | AK35: 0.11247677 | AL35: 0.083844916 | AM35: 0.12846629 | AN35: 0.10675102 | AO35: 0.11211384 | AP35: 0.083686444 | AQ35: =AQ34/AQ26 -> 0.13221409 | AR35: =AR34/AR26 -> 0.11474409 | AS35: =AS34/AS26 -> 0.13018077 | AT35: =AT34/AT26 -> 0.081715839 | AU35: =AU34/AU26 -> 0.13889213 | AV35: =AV34/AV26 -> 0.11857256 | AW35: =AW34/AW26 -> 0.12124412 | AX35: =AX34/AX26 -> 0.087814044 | ... CP35: =CP34/CP26 -> 0.096956305 | CT35: 0.094411536 | CV35: 0 | CW35: 0.037666538 | CX35: 0.062127507 | CY35: 0.092741407 | CZ35: 0.10397859 | DA35: 0.10477918 | DB35: 0.10491405 | DC35: 0.10558023 | DD35: 0.10370153 | DE35: 0.1044705 | DF35: =DF34/DF26 -> 0.10993619 | DG35: =DG34/DG26 -> 0.11299001 | DH35: =DH34/DH26 -> 0.11312299 | DI35: =DI34/DI26 -> 0.11340642 | DJ35: =DJ34/DJ26 -> 0.11168379 | DK35: =DK34/DK26 -> 0.11615491 | DL35: =DL34/DL26 -> 0.11630464 | DM35: =DM34/DM26 -> 0.096090844 | ... DV35: =DV34/DV26 -> 0.098120927 | DY35: 0.11048645 | DZ35: 0.10271294
A36: var y-o-y | N36: 0.46762026 | O36: 1.3608555 | P36: 1.0085525 | Q36: 0.85044167 | R36: 0.56134846 | S36: 0.30145161 | T36: 0.21507527 | U36: 0.28263374 | V36: 0.27698918 | W36: 0.16670798 | X36: 0.038601087 | Y36: 0.052056597 | Z36: 0.12013058 | AA36: 0.158697 | AB36: 0.22744624 | AC36: 0.14565194 | AD36: 0.1364798 | AE36: 0.2385216 | AF36: 0.20459815 | AG36: 0.12927741 | AH36: 0.17373065 | AI36: 0.11123859 | AJ36: 0.15580988 | AK36: 0.19979728 | AL36: 0.21437695 | AM36: 0.18922699 | AN36: 0.128773 | AO36: 0.12494352 | AP36: 0.12316862 | AQ36: =AQ34/AM34-1 -> 0.15847352 | AR36: =AR34/AN34-1 -> 0.27236106 | AS36: =AS34/AO34-1 -> 0.36846058 | AT36: =AT34/AP34-1 -> 0.22058848 | AU36: =AU34/AQ34-1 -> 0.31389708 | AV36: =AV34/AR34-1 -> 0.26484066 | AW36: =AW34/AS34-1 -> 0.099086222 | AX36: =AX34/AT34-1 -> 0.19036691 | ... CP36: =CP34/CL34-1 -> 0.11679769 | CT36: 0.030204579 | CY36: 0.88241601 | CZ36: 0.26752588 | DA36: 0.091076102 | DB36: 0.16553002 | DC36: 0.18455313 | DD36: 0.17144645 | DE36: 0.13987837 | DF36: =DF34/DE34-1 -> 0.25593987 | DG36: =DG34/DF34-1 -> 0.21086022 | DH36: =DH34/DG34-1 -> 0.051092683 | DI36: =DI34/DH34-1 -> 0.15676425 | DJ36: =DJ34/DI34-1 -> 0.11475045 | DK36: =DK34/DJ34-1 -> 0.1834391 | DL36: =DL34/DK34-1 -> -0.21291697 | DM36: =DM34/DL34-1 -> 0.15881739 | ... DV36: =DV34/DU34-1 -> 0.0043285472 | DY36: -0.056083488 | DZ36: 0.0033189887
A38: CPV | C38: -91627 | D38: -129428 | E38: -115478 | F38: -181258 | G38: -99565 | H38: -142704 | I38: -139259 | J38: -212094 | K38: -124610 | L38: -188701 | M38: -173772 | N38: -264700 | O38: -157849 | P38: -232147 | Q38: -205376 | R38: -311340 | S38: -191412 | T38: -261493 | U38: -237809 | V38: -331822 | W38: -187018 | X38: -287563 | Y38: -256866 | Z38: -353464 | AA38: -212790 | AB38: -296956 | AC38: -289980 | AD38: -409732 | AE38: -249547 | AF38: -351223 | AG38: -332789 | AH38: -462569 | AI38: -294842 | AJ38: -393264 | AK38: -394603 | AL38: -551538 | AM38: -358005 | AN38: -444292 | AO38: -457550 | AP38: -607795 | AQ38: =+AQ41+AQ44 -> -396256 | AR38: =+AR41+AR44 -> -512414 | AS38: =+AS41+AS44 -> -507111 | AT38: =+AT41+AT44 -> -748983 | AU38: =+AU41+AU44 -> -472175 | AV38: =+AV41+AV44 -> -618617 | AW38: =+AW41+AW44 -> -596697 | AX38: =+AX41+AX44 -> -823863 | ... CP38: =+CP41+CP44 -> -2112547.6 | CT38: -1948240.3 | CV38: -517791 | CW38: -593622 | CX38: -751783 | CY38: -906712 | CZ38: -1022536 | DA38: -1084911 | DB38: -1209458 | DC38: -1396128 | DD38: -1634247 | DE38: -1867642 | DF38: =+SUM(AQ38:AT38) -> -2164764 | DG38: =+SUM(AU38:AX38) -> -2511352 | DH38: =+SUM(AY38:BB38) -> -2575083 | DI38: =+SUM(BC38:BF38) -> -2944913 | DJ38: =+SUM(BG38:BJ38) -> -3284517 | DK38: =+SUM(BK38:BN38) -> -3730521 | DL38: =+SUM(BO38:BR38) -> -3223570 | DM38: =+SUM(BS38:BV38) -> -4398891 | DN38: =+SUM(BW38:BZ38) -> -5286322 | DO38: =+SUM(CA38:CD38) -> -5427247 | DP38: =+SUM(CE38:CH38) -> -5694417 | DQ38: =+SUM(CI38:CL38) -> -6125494.3 | DR38: =+SUM(CM38:CP38) -> -6551947.9 | DS38: =+DS41+DS44 -> -7111569.5 | DT38: =+DT41+DT44 -> -7660768.3 | DU38: =+DU41+DU44 -> -8247040.5 | DV38: =+DV41+DV44 -> -8872728.5 | DY38: -6749709 | DZ38: -7346401.1
A39: % rec líq | C39: -0.51956587 | D39: -0.54047914 | E39: -0.5500131 | F39: -0.55257037 | G39: -0.47365892 | H39: -0.48246344 | I39: -0.51223208 | J39: -0.49989747 | K39: -0.46713802 | L39: -0.49546027 | M39: -0.50109145 | N39: -0.49307148 | O39: -0.45416984 | P39: -0.47292777 | Q39: -0.46254606 | R39: -0.48009252 | S39: -0.44329164 | T39: -0.4617187 | U39: -0.46504292 | V39: -0.49268812 | W39: -0.44620098 | X39: -0.46879106 | Y39: -0.46507493 | Z39: -0.45387528 | AA39: -0.42078723 | AB39: -0.4230034 | AC39: -0.45036832 | AD39: -0.45538326 | AE39: -0.41676813 | AF39: -0.41991275 | AG39: -0.44854985 | AH39: -0.43579629 | AI39: -0.41569431 | AJ39: -0.41159909 | AK39: -0.43599747 | AL39: -0.42664924 | AM39: -0.42933826 | AN39: -0.4189845 | AO39: -0.44794823 | AP39: -0.41781697 | AQ39: =AQ38/AQ26 -> -0.42217141 | AR39: =AR38/AR26 -> -0.40822384 | AS39: =AS38/AS26 -> -0.42125746 | AT39: =AT38/AT26 -> -0.41189145 | AU39: =AU38/AU26 -> -0.40221151 | AV39: =AV38/AV26 -> -0.40264033 | AW39: =AW38/AW26 -> -0.4200302 | AX39: =AX38/AX26 -> -0.40901827 | ... CP39: =CP38/CP26 -> -0.40237607 | CT39: -0.40354474 | CV39: -0.54286939 | CW39: -0.49380931 | CX39: -0.49096417 | CY39: -0.4695705 | CZ39: -0.46840711 | DA39: -0.45900243 | DB39: -0.43958903 | DC39: -0.4310977 | DD39: -0.42310514 | DE39: -0.42734068 | DF39: =DF38/DF26 -> -0.41502027 | DG39: =DG38/DG26 -> -0.40866901 | DH39: =DH38/DH26 -> -0.3991399 | DI39: =DI38/DI26 -> -0.39559274 | DJ39: =DJ38/DJ26 -> -0.38978236 | DK39: =DK38/DK26 -> -0.38906456 | DL39: =DL38/DL26 -> -0.42768914 | DM39: =DM38/DM26 -> -0.41610629 | ... DV39: =DV38/DV26 -> -0.39793043 | DY39: -0.39298949 | DZ39: -0.39632149
A41: CPV Retail | W41: -180650 | X41: -279624 | Y41: -248591 | Z41: -346883 | AA41: -206779 | AB41: -290145 | AC41: -282458 | AD41: -402984 | AE41: -243500 | AF41: -345698 | AG41: -327502 | AH41: -458652 | AI41: -290630 | AJ41: -387880 | AK41: -390194 | AL41: -547709 | AM41: -354819 | AN41: -440050 | AO41: -452488 | AP41: -603450 | AQ41: -392224 | AR41: -509222 | AS41: -501369 | AT41: -740326 | AU41: -460582 | AV41: -604983 | AW41: -586005 | AX41: -814610 | AY41: -477582 | AZ41: -626777 | BA41: -583810 | BB41: -848461 | BC41: -563126 | BD41: -706711 | BE41: -696818 | BF41: -956227 | BG41: -612639 | BH41: -757798 | BI41: -782320 | BJ41: -1104641 | BK41: -738430 | BL41: -879737 | BM41: -882033 | BN41: -1207106 | BO41: -691240 | BP41: -297841 | BQ41: -862993 | BR41: -1349235 | BS41: -653502 | BT41: -1016802 | BU41: -1105494 | BV41: -1599088 | BW41: -1001768 | BX41: -1394013 | BY41: -1207204 | BZ41: -1573289 | CA41: -1044471 | CB41: -1375910 | CC41: -1223052 | CD41: -1678128 | CE41: -1121075 | CF41: -1348375 | CG41: -1340034 | CH41: -1846711 | CI41: -1238915 | CJ41: -1565380 | CK41: -1383359 | CL41: =+CL53-CL30 -> -1953865.3 | CM41: =+CM53-CM30 -> -1316548.6 | CN41: =+CN53-CN30 -> -1647504.1 | CO41: =+CO53-CO30 -> -1493999.2 | CP41: =+CP53-CP30 -> -2118829.6 | CT41: -1953865.3 | DB41: -1182366 | DC41: -1375352 | DD41: -1616413 | DE41: -1850807 | DF41: =+SUM(AQ41:AT41) -> -2143141 | DG41: =+SUM(AU41:AX41) -> -2466180 | DH41: =+SUM(AY41:BB41) -> -2536630 | DI41: =+SUM(BC41:BF41) -> -2922882 | DJ41: =+SUM(BG41:BJ41) -> -3257398 | DK41: =+SUM(BK41:BN41) -> -3707306 | DL41: =+SUM(BO41:BR41) -> -3201309 | DM41: =+SUM(BS41:BV41) -> -4374886 | DN41: =+SUM(BW41:BZ41) -> -5176274 | DO41: =+SUM(CA41:CD41) -> -5321561 | DP41: =+SUM(CE41:CH41) -> -5656195 | DQ41: =+SUM(CI41:CL41) -> -6141519.3 | DR41: =+SUM(CM41:CP41) -> -6576881.5 | DS41: =+DS53-DS30 -> -7138258.4 | DT41: =+DT53-DT30 -> -7687545.8 | DU41: =+DU53-DU30 -> -8273923.9 | DV41: =+DV53-DV30 -> -8899728.3 | DY41: -6727484 | DZ41: -7324102.3
A42: % rec líq | W42: -0.49814007 | X42: -0.50407043 | Y42: -0.51073696 | Z42: -0.48729241 | AA42: -0.46968967 | AB42: -0.46055566 | AC42: -0.49663818 | AD42: -0.48923103 | AE42: -0.47034326 | AF42: -0.46114402 | AG42: -0.49842332 | AH42: -0.47177683 | AI42: -0.46936445 | AJ42: -0.45357117 | AK42: -0.48576302 | AL42: -0.46246238 | AM42: -0.4882398 | AN42: -0.46457834 | AO42: -0.49892934 | AP42: -0.4527163 | AQ42: =AQ41/AQ30 -> -0.48154241 | AR42: =AR41/AR30 -> -0.45826396 | AS42: =AS41/AS30 -> -0.47882085 | AT42: =AT41/AT30 -> -0.44336022 | AU42: =AU41/AU30 -> -0.45561804 | AV42: =AV41/AV30 -> -0.4467371 | AW42: =AW41/AW30 -> -0.469418 | AX42: =AX41/AX30 -> -0.4433575 | ... CP42: =CP41/CP30 -> -0.44690263 | CT42: -0.44690263 | DB42: -0.48011276 | DC42: -0.47481337 | DD42: -0.4669069 | DE42: -0.47289186 | DF42: =DF41/DF30 -> -0.46162397 | DG42: =DG41/DG30 -> -0.45243936 | DH42: =DH41/DH30 -> -0.44333053 | DI42: =DI41/DI30 -> -0.44285601 | DJ42: =DJ41/DJ30 -> -0.43516494 | DK42: =DK41/DK30 -> -0.43745608 | DL42: =DL41/DL30 -> -0.48063582 | DM42: =+DL42 -> -0.48063582 | DN42: =+DM42 -> -0.48063582 | DO42: =+DN42 -> -0.48063582 | DP42: =+DO42 -> -0.48063582 | DQ42: =+DP42 -> -0.48063582 | DR42: =+DQ42 -> -0.48063582 | DS42: =DS41/DS30 -> -0.44256635 | DT42: =DT41/DT30 -> -0.44256635 | DU42: =DU41/DU30 -> -0.44256635 | DV42: =DV41/DV30 -> -0.44256635 | DY42: -0.44034796 | DZ42: -0.44034796
A43: var y-o-y | AA43: 0.1446388 | AB43: 0.037625526 | AC43: 0.13623583 | AD43: 0.16172888 | AE43: 0.17758573 | AF43: 0.19146634 | AG43: 0.1594715 | AH43: 0.13813948 | AI43: 0.19355236 | AJ43: 0.1220198 | AK43: 0.19142479 | AL43: 0.19417118 | AM43: 0.22086158 | AN43: 0.13450036 | AO43: 0.15964879 | AP43: 0.1017712 | AQ43: =AQ41/AM41-1 -> 0.10541995 | AR43: =AR41/AN41-1 -> 0.15719123 | AS43: =AS41/AO41-1 -> 0.10802717 | AT43: =AT41/AP41-1 -> 0.22682244 | AU43: =AU41/AQ41-1 -> 0.17428306 | AV43: =AV41/AR41-1 -> 0.18805354 | AW43: =AW41/AS41-1 -> 0.1688098 | AX43: =AX41/AT41-1 -> 0.10033958 | ... CP43: =CP41/CL41-1 -> 0.084429682 | CT43: 0.058024419 | DC43: 0.16322019 | DD43: 0.17527222 | DE43: 0.14500873 | DF43: =DF41/DE41-1 -> 0.15794948 | DG43: =DG41/DF41-1 -> 0.15073157 | DH43: =DH41/DG41-1 -> 0.028566447 | DI43: =DI41/DH41-1 -> 0.15226974 | DJ43: =DJ41/DI41-1 -> 0.11444732 | DK43: =DK41/DJ41-1 -> 0.13811883 | DL43: =DL41/DK41-1 -> -0.13648644 | DM43: =DM41/DL41-1 -> 0.36659285 | ... DR43: =DR41/DQ41-1 -> 0.070888345 | DS43: =DS41/DO41-1 -> 0.34138431 | DT43: =DT41/DP41-1 -> 0.35913733 | DU43: =DU41/DQ41-1 -> 0.34721124 | DV43: =DV41/DR41-1 -> 0.35318362 | DY43: 0.29967694 | DZ43: 0.37630712
A44: CPV Financeiro | W44: -6368 | X44: -7939 | Y44: -8275 | Z44: -6581 | AA44: -6011 | AB44: -6811 | AC44: -7522 | AD44: -6748 | AE44: -6047 | AF44: -5525 | AG44: -5287 | AH44: -3917 | AI44: -4212 | AJ44: -5384 | AK44: -4409 | AL44: -3829 | AM44: -3186 | AN44: -4242 | AO44: -5062 | AP44: -4345 | AQ44: -4032 | AR44: -3192 | AS44: -5742 | AT44: -8657 | AU44: -11593 | AV44: -13634 | AW44: -10692 | AX44: -9253 | AY44: -10842 | AZ44: -10298 | BA44: -10406 | BB44: -6907 | BC44: -6430 | BD44: -5328 | BE44: -5735 | BF44: -4538 | BG44: -6783 | BH44: -7226 | BI44: -6861 | BJ44: -6249 | BK44: -5601 | BL44: -5755 | BM44: -7164 | BN44: -4695 | BO44: -5434 | BP44: -6802 | BQ44: -6368 | BR44: -3657 | BS44: -3898 | BT44: -3556 | BU44: -5441 | BV44: -11110 | BW44: -16616 | BX44: -27403 | BY44: -34224 | BZ44: -31805 | CA44: -28356 | CB44: -30387 | CC44: -26363 | CD44: -20580 | CE44: -17659 | CF44: -14447 | CG44: -7748 | CH44: 1632 | CI44: 2809 | CJ44: 1614 | CK44: 5977 | CL44: =+CL45*CL34 -> 5625.0198 | CM44: =+CM45*CM34 -> 6151.0043 | CN44: =+CN45*CN34 -> 6227.907 | CO44: =+CO45*CO34 -> 6272.6486 | CP44: =+CP45*CP34 -> 6282.0092 | CT44: 5625.0198 | DB44: -27092 | DC44: -20776 | DD44: -17834 | DE44: -16835 | DF44: =+SUM(AQ44:AT44) -> -21623 | DG44: =+SUM(AU44:AX44) -> -45172 | DH44: =+SUM(AY44:BB44) -> -38453 | DI44: =+SUM(BC44:BF44) -> -22031 | DJ44: =+SUM(BG44:BJ44) -> -27119 | DK44: =+SUM(BK44:BN44) -> -23215 | DL44: =+SUM(BO44:BR44) -> -22261 | DM44: =+SUM(BS44:BV44) -> -24005 | DN44: =+SUM(BW44:BZ44) -> -110048 | DO44: =+SUM(CA44:CD44) -> -105686 | DP44: =+SUM(CE44:CH44) -> -38222 | DQ44: =+SUM(CI44:CL44) -> 16025.02 | DR44: =+SUM(CM44:CP44) -> 24933.569 | DS44: =+DS57-DS34 -> 26688.954 | DT44: =+DT57-DT34 -> 26777.453 | DU44: =+DU57-DU34 -> 26883.391 | DV44: =+DV57-DV34 -> 26999.757 | DY44: -22225.044 | DZ44: -22298.809
A45: % rec líq | W45: -0.1127379 | X45: -0.1352885 | Y45: -0.12617984 | Z45: -0.098354531 | AA45: -0.091842503 | AB45: -0.094559136 | AC45: -0.10011579 | AD45: -0.088739266 | AE45: -0.074599062 | AF45: -0.063677016 | AG45: -0.062312896 | AH45: -0.043885988 | AI45: -0.046759994 | AJ45: -0.053686992 | AK45: -0.043311263 | AL45: -0.035326789 | AM45: -0.02974179 | AN45: -0.037473829 | AO45: -0.044203044 | AP45: -0.035691403 | AQ45: =AQ44/AQ34 -> -0.032490451 | AR45: =AR44/AR34 -> -0.02216205 | AS45: =AS44/AS34 -> -0.036640461 | AT45: =AT44/AT34 -> -0.058260202 | AU45: =AU44/AU34 -> -0.071100017 | AV45: =AV44/AV34 -> -0.074840126 | AW45: =AW44/AW34 -> -0.062076173 | AX45: =AX44/AX34 -> -0.052312598 | ... CK45: =CK44/CK34 -> 0.012340938 | CL45: =+CK45 -> 0.012340938 | CM45: =+CL45 -> 0.012340938 | CN45: =+CM45 -> 0.012340938 | CO45: =+CN45 -> 0.012340938 | CP45: =+CO45 -> 0.012340938 | CT45: 0.012340938 | DB45: -0.093856312 | DC45: -0.060761685 | DD45: -0.044524002 | DE45: -0.036872284 | DF45: =DF44/DF34 -> -0.037708046 | DG45: =DG44/DG34 -> -0.065056902 | DH45: =DH44/DH34 -> -0.05268819 | DI45: =DI44/DI34 -> -0.026095907 | DJ45: =DJ44/DJ34 -> -0.028816034 | DK45: =DK44/DK34 -> -0.020844108 | DL45: =DL44/DL34 -> -0.025394446 | DM45: =DL45 -> -0.025394446 | DN45: =DM45 -> -0.025394446 | DO45: =DN45 -> -0.025394446 | DP45: =DO45 -> -0.025394446 | DQ45: =DP45 -> -0.025394446 | DR45: =DQ45 -> -0.025394446 | DS45: =DR45 -> -0.025394446 | DT45: =DS45 -> -0.025394446 | ... DV45: =DU45 -> -0.025394446 | DY45: -0.025394446 | DZ45: -0.025394446
A46: var y-o-y | AA46: -0.056061558 | AB46: -0.14208339 | AC46: -0.090996979 | AD46: 0.025376083 | AE46: 0.0059890201 | AF46: -0.18881222 | AG46: -0.29712842 | AH46: -0.41953171 | AI46: -0.30345626 | AJ46: -0.025520362 | AK46: -0.16606771 | AL46: -0.022466173 | AM46: -0.24358974 | AN46: -0.21210996 | AO46: 0.14810615 | AP46: 0.13476103 | AQ46: =AQ44/AM44-1 -> 0.26553672 | AR46: =AR44/AN44-1 -> -0.24752475 | AS46: =AS44/AO44-1 -> 0.13433426 | AT46: =AT44/AP44-1 -> 0.99240506 | AU46: =AU44/AQ44-1 -> 1.875248 | AV46: =AV44/AR44-1 -> 3.2713033 | AW46: =AW44/AS44-1 -> 0.86206897 | AX46: =AX44/AT44-1 -> 0.068846021 | ... CP46: =CP44/CL44-1 -> 0.11679769 | CT46: 2.4467033 | DC46: -0.23313155 | DD46: -0.1416057 | DE46: -0.056016598 | DF46: =DF44/DE44-1 -> 0.28440748 | DG46: =DG44/DF44-1 -> 1.0890718 | DH46: =DH44/DG44-1 -> -0.14874258 | DI46: =DI44/DH44-1 -> -0.42706681 | DJ46: =DJ44/DI44-1 -> 0.2309473 | DK46: =DK44/DJ44-1 -> -0.14395811 | DL46: =DL44/DK44-1 -> -0.04109412 | DM46: =DM44/DL44-1 -> 0.078343291 | ... DV46: =DV44/DU44-1 -> 0.0043285472 | DY46: -2.3338627 | DZ46: 0.0033189887
BT48: =1468746-BT49 -> -1189
A49: Lucro Bruto | C49: 84726 | D49: 110041 | E49: 94477 | F49: 146769 | G49: 110639 | H49: 153078 | I49: 132608 | J49: 212181 | K49: 142142 | L49: 192159 | M49: 173015 | N49: 272139 | O49: 189706 | P49: 258725 | Q49: 238636 | R49: 337160 | S49: 240385 | T49: 304854 | U49: 273561 | V49: 341671 | W49: 232116 | X49: 325851 | Y49: 295445 | Z49: 425305 | AA49: 292905 | AB49: 405062 | AC49: 353893 | AD49: 490020 | AE49: 349220 | AF49: 485196 | AG49: 409133 | AH49: 598865 | AI49: 414434 | AJ49: 562190 | AK49: 510455 | AL49: 741182 | AM49: 475848 | AN49: 616110 | AO49: 563885 | AP49: 846897 | AQ49: =AQ26+AQ38 -> 542358 | AR49: =AR26+AR38 -> 742814 | AS49: =AS26+AS38 -> 696692 | AT49: =AT26+AT38 -> 1069416 | AU49: =AU26+AU38 -> 701772 | AV49: =AV26+AV38 -> 917784 | AW49: =AW26+AW38 -> 823908 | AX49: =AX26+AX38 -> 1190382 | ... CP49: =CP26+CP38 -> 3137634.3 | CT49: 2879577.1 | CU49: =+CK49/CT49-1 -> -0.24082949 | CV49: 436013 | CW49: 608506 | CX49: 779455 | CY49: 1024227 | CZ49: 1160471 | DA49: 1278717 | DB49: 1541880 | DC49: 1842414 | DD49: 2228261 | DE49: 2502740 | DF49: =+SUM(AQ49:AT49) -> 3051280 | DG49: =+SUM(AU49:AX49) -> 3633846 | DH49: =+SUM(AY49:BB49) -> 3876497 | DI49: =+SUM(BC49:BF49) -> 4499392 | DJ49: =+SUM(BG49:BJ49) -> 5142024 | DK49: =+SUM(BK49:BN49) -> 5857916 | DL49: =+SUM(BO49:BR49) -> 4313610 | DM49: =DM26+DM38 -> 6172665.2 | DN49: =DN26+DN38 -> 7984815 | DO49: =DO26+DO38 -> 8220602 | DP49: =DP26+DP38 -> 8741949 | DQ49: =DQ26+DQ38 -> 9690937.1 | DR49: =DR26+DR38 -> 10329228 | DS49: =DS26+DS38 -> 11180305 | DT49: =DT26+DT38 -> 11879419 | ... DV49: =DV26+DV38 -> 13424457 | DY49: 10425583 | DZ49: 11190068
A50: margem bruta | C50: 0.48043413 | D50: 0.45952086 | E50: 0.4499869 | F50: 0.44742963 | G50: 0.52634108 | H50: 0.51753656 | I50: 0.48776792 | J50: 0.50010253 | K50: 0.53286198 | L50: 0.50453973 | M50: 0.49890855 | N50: 0.50692852 | O50: 0.54583016 | P50: 0.52707223 | Q50: 0.53745394 | R50: 0.51990748 | S50: 0.55670836 | T50: 0.5382813 | U50: 0.53495708 | V50: 0.50731188 | W50: 0.55379902 | X50: 0.53120894 | Y50: 0.53492507 | Z50: 0.54612472 | AA50: 0.57921277 | AB50: 0.5769966 | AC50: 0.54963168 | AD50: 0.54461674 | AE50: 0.58323187 | AF50: 0.58008725 | AG50: 0.55145015 | AH50: 0.56420371 | AI50: 0.58430569 | AJ50: 0.58840091 | AK50: 0.56400253 | AL50: 0.57335076 | AM50: 0.57066174 | AN50: 0.5810155 | AO50: 0.55205177 | AP50: 0.58218303 | AQ50: =AQ49/AQ26 -> 0.57782859 | AR50: =AR49/AR26 -> 0.59177616 | AS50: =AS49/AS26 -> 0.57874254 | AT50: =AT49/AT26 -> 0.58810855 | AU50: =AU49/AU26 -> 0.59778849 | AV50: =AV49/AV26 -> 0.59735967 | AW50: =AW49/AW26 -> 0.5799698 | AX50: =AX49/AX26 -> 0.59098173 | ... CP50: =CP49/CP26 -> 0.59762393 | CT50: 0.59645526 | CU50: =+CK50-CT50 -> 0.017016657 | CV50: 0.45713061 | CW50: 0.50619069 | CX50: 0.50903583 | CY50: 0.5304295 | CZ50: 0.53159289 | DA50: 0.54099757 | DB50: 0.56041097 | DC50: 0.5689023 | DD50: 0.57689486 | DE50: 0.57265932 | DF50: =DF49/DF26 -> 0.58497973 | DG50: =DG49/DG26 -> 0.59133099 | DH50: =DH49/DH26 -> 0.6008601 | DI50: =DI49/DI26 -> 0.60440726 | DJ50: =DJ49/DJ26 -> 0.61021764 | DK50: =DK49/DK26 -> 0.61093544 | DL50: =DL49/DL26 -> 0.57231086 | DM50: =DM49/DM26 -> 0.58389371 | ... DV50: =DV49/DV26 -> 0.60206957 | DY50: 0.60701051 | DZ50: 0.60367851
AI51: 0.0010738115 | AJ51: 0.0083136539 | AK51: 0.012552376 | AL51: 0.009147055 | AM51: -0.013643951 | AN51: -0.0073854051 | AO51: -0.011950758 | AP51: 0.0088322683 | AQ51: =+AQ50-AM50 -> 0.0071668502 | AR51: =+AR50-AN50 -> 0.010760654 | AS51: =+AS50-AO50 -> 0.026690765 | AT51: =+AT50-AP50 -> 0.0059255179 | AU51: =+AU50-AQ50 -> 0.019959901 | AV51: =+AV50-AR50 -> 0.0055835183 | AW51: =+AW50-AS50 -> 0.0012272665 | AX51: =+AX50-AT50 -> 0.0028731822 | ... CP51: =+CP50-CL50 -> 0.0011686689 | CT51: -0.0039362742 | DM51: =+DM50-$DK$50 -> -0.027041731 | DN51: =+DN50-$DK$50 -> -0.0092677028 | DO51: =+DO50-$DK$50 -> -0.0085986199 | DP51: =+DP50-$DK$50 -> -0.0053849181 | DQ51: =+DQ50-$DK$50 -> 0.0017778075 | DR51: =+DR50-$DK$50 -> 0.00094301807
A53: Lucro Bruto Retail | J53: 191767 | K53: 126385 | L53: 169008 | M53: 146751 | N53: 242179 | O53: 152444 | P53: 212208 | Q53: 189982 | R53: 290382 | S53: 191971 | T53: 248353 | U53: 211225 | V53: 281936 | W53: 181999 | X53: 275108 | Y53: 238139 | Z53: 364975 | AA53: 233467 | AB53: 339844 | AC53: 286282 | AD53: 420725 | AE53: 274207 | AF53: 403955 | AG53: 329574 | AH53: 513528 | AI53: 328569 | AJ53: 467289 | AK53: 413066 | AL53: 636623 | AM53: 371912 | AN53: 507153 | AO53: 454430 | AP53: 729504 | AQ53: =+AQ30+AQ41 -> 422292 | AR53: =+AR30+AR41 -> 601976 | AS53: =+AS30+AS41 -> 545722 | AT53: =+AT30+AT41 -> 929481 | AU53: =+AU30+AU41 -> 550313 | AV53: =+AV30+AV41 -> 749243 | AW53: =+AW30+AW41 -> 662360 | AX53: =+AX30+AX41 -> 1022756 | ... CK53: =+CK30+CK41 -> 1695790 | CL53: =+CL258 -> 2418150.4 | CM53: =+CM258 -> 1619262.5 | CN53: =+CN258 -> 2203892.8 | CO53: =+CO258 -> 1838429.8 | CP53: =+CP258 -> 2622314.1 | CT53: 2418150.4 | CU53: =+CK53/CT53-1 -> -0.29872435 | CX53: 684323 | CY53: 845016 | CZ53: 933485 | DA53: 1060221 | DB53: 1280318 | DC53: 1521264 | DD53: 1845547 | DE53: 2062999 | DF53: =+SUM(AQ53:AT53) -> 2499471 | DG53: =+SUM(AU53:AX53) -> 2984672 | DH53: =+SUM(AY53:BB53) -> 3185128 | DI53: =+SUM(BC53:BF53) -> 3677191 | DJ53: =+SUM(BG53:BJ53) -> 4228035 | DK53: =+SUM(BK53:BN53) -> 4767387 | DL53: =+SUM(BO53:BR53) -> 3459262 | DM53: =+DM30+DM41 -> 5180840.4 | DN53: =+DN30+DN41 -> 6399521 | DO53: =+DO30+DO41 -> 6384779 | DP53: =+DP30+DP41 -> 7015755 | DQ53: =+DQ30+DQ41 -> 7716154.4 | DR53: =+DR30+DR41 -> 8283899.2 | DS53: =+DS54*DS30 -> 8990980.5 | DT53: =+DT54*DT30 -> 9682834.4 | DU53: =+DU54*DU30 -> 10421406 | DV53: =+DV54*DV30 -> 11209637 | DY53: 8550170.6 | DZ53: 9308431.6
A54: margem bruta Retail | J54: 0.47483416 | K54: 0.50353593 | L54: 0.47247344 | M54: 0.45784858 | N54: 0.47778464 | O54: 0.49129049 | P54: 0.47756411 | Q54: 0.48053157 | R54: 0.48258498 | S54: 0.50072904 | T54: 0.48711376 | U54: 0.47039868 | V54: 0.4593602 | W54: 0.50185993 | X54: 0.49592957 | Y54: 0.48926304 | Z54: 0.51270759 | AA54: 0.53031033 | AB54: 0.53944434 | AC54: 0.50336182 | AD54: 0.51076897 | AE54: 0.52965674 | AF54: 0.53885598 | AG54: 0.50157668 | AH54: 0.52822317 | AI54: 0.53063555 | AJ54: 0.54642883 | AK54: 0.51423698 | AL54: 0.53753762 | AM54: 0.5117602 | AN54: 0.53542166 | AO54: 0.50107066 | AP54: 0.5472837 | AQ54: =AQ53/AQ30 -> 0.51845759 | AR54: =AR53/AR30 -> 0.54173604 | AS54: =AS53/AS30 -> 0.52117915 | AT54: =AT53/AT30 -> 0.55663978 | AU54: =AU53/AU30 -> 0.54438196 | AV54: =AV53/AV30 -> 0.5532629 | AW54: =AW53/AW30 -> 0.530582 | AX54: =AX53/AX30 -> 0.5566425 | ... CP54: =CP53/CP30 -> 0.55309737 | CT54: 0.55309737 | CU54: =+CK54-CT54 -> -0.0023640341 | CX54: 0.47651288 | CY54: 0.48238996 | CZ54: 0.4772367 | DA54: 0.50105696 | DB54: 0.51988724 | DC54: 0.52518663 | DD54: 0.5330931 | DE54: 0.52710814 | DF54: =DF53/DF30 -> 0.53837603 | DG54: =DG53/DG30 -> 0.54756064 | DH54: =DH53/DH30 -> 0.55666947 | DI54: =DI53/DI30 -> 0.55714399 | DJ54: =DJ53/DJ30 -> 0.56483506 | DK54: =DK53/DK30 -> 0.56254392 | DL54: =DL53/DL30 -> 0.51936418 | DM54: =DM53/DM30 -> 0.54217128 | ... DR54: =DR53/DR30 -> 0.55743365 | DS54: =+DR54+DS55 -> 0.55743365 | DT54: =+DS54+DT55 -> 0.55743365 | DU54: =+DT54+DU55 -> 0.55743365 | DV54: =+DU54+DV55 -> 0.55743365 | DY54: 0.55965204 | DZ54: 0.55965204
A55: dif yoy | AQ55: =+AQ54-AM54 -> 0.0066973897 | AR55: =+AR54-AN54 -> 0.006314379 | AS55: =+AS54-AO54 -> 0.020108493 | AT55: =+AT54-AP54 -> 0.0093560771 | AU55: =+AU54-AQ54 -> 0.025924371 | AV55: =+AV54-AR54 -> 0.011526861 | AW55: =+AW54-AS54 -> 0.0094028487 | AX55: =+AX54-AT54 -> 2.7186829e-06 | ... CP55: =+CP54-CL54 -> 0 | CT55: -0.0045532267 | DG55: =+DG54-DF54 -> 0.009184612 | DH55: =+DH54-DG54 -> 0.0091088329 | DI55: =+DI54-DH54 -> 0.000474518 | DJ55: =+DJ54-DI54 -> 0.0076910711 | DK55: =+DK54-DJ54 -> -0.0022911428 | DL55: =+DL54-DK54 -> -0.043179737 | DM55: =+DM54-DL54 -> 0.022807098 | DN55: =+DN54-DM54 -> 0.010665136 | ... DR55: =+DR54-DQ54 -> 0.00061909667 | DS55: 0 | DT55: 0 | DU55: 0 | DV55: 0 | DY55: 0 | DZ55: 0
BV56: =+BV54-BN54 -> -0.02895175 | BW56: =+BW54-BK54 -> -0.001848866 | BX56: =+BX54-BL54 -> -0.0033078392 | BY56: =+BY54-BM54 -> -0.0049971517 | BZ56: =+BZ54-BN54 -> -0.022426855 | CA56: =+CA54-BK54 -> -0.011061766 | CB56: =+CB54-BL54 -> -0.025246061 | CC56: =+CC54-BM54 -> -0.0074048364 | DO56: =+DO54-DK54 -> -0.017131859 | DP56: =+DP54-DL54 -> 0.034280286 | DQ56: =+DQ54-DM54 -> 0.014643274 | DR56: =+DR54-DN54 -> 0.0045972352
A57: Lucro Bruto Financeiro | J57: 191767 | K57: 126385 | L57: 169008 | M57: 146751 | N57: 242179 | O57: 152444 | P57: 212208 | Q57: 189982 | R57: 290382 | S57: 191971 | T57: 248353 | U57: 211225 | V57: 281936 | W57: 181999 | X57: 275108 | Y57: 238139 | Z57: 364975 | AA57: 233467 | AB57: 339844 | AC57: 286282 | AD57: 420725 | AE57: 274207 | AF57: 403955 | AG57: 329574 | AH57: 513528 | AI57: 328569 | AJ57: 467289 | AK57: 413066 | AL57: 636623 | AM57: 371912 | AN57: 507153 | AO57: 454430 | AP57: 729504 | AQ57: =+AQ34+AQ44 -> 120066 | AR57: =+AR34+AR44 -> 140838 | AS57: =+AS34+AS44 -> 150970 | AT57: =+AT34+AT44 -> 139935 | AU57: =+AU34+AU44 -> 151459 | AV57: =+AV34+AV44 -> 168541 | AW57: =+AW34+AW44 -> 161548 | AX57: =+AX34+AX44 -> 167626 | ... CP57: =+CP34+CP44 -> 515320.24 | CT57: 461426.67 | CX57: 684323 | CY57: 845016 | CZ57: 933485 | DA57: 1060221 | DB57: 1280318 | DC57: 1521264 | DD57: 1845547 | DE57: 2062999 | DF57: =+DF34+DF44 -> 551809 | DG57: =+DG34+DG44 -> 649174 | DH57: =+DH34+DH44 -> 691369 | DI57: =+DI34+DI44 -> 822201 | DJ57: =+DJ34+DJ44 -> 913989 | DK57: =+DK34+DK44 -> 1090529 | DL57: =+DL34+DL44 -> 854348 | DM57: =+DM34+DM44 -> 991824.75 | ... DR57: =+DR34+DR44 -> 2045328.6 | DS57: =+DS58*DS34 -> 2189324.7 | DT57: =+DT58*DT34 -> 2196584.4 | DU57: =+DU58*DU34 -> 2205274.7 | DV57: =+DV58*DV34 -> 2214820.3 | DY57: 1875411.9 | DZ57: 1881636.4
A58: margem bruta Retail | J58: 0.47483416 | K58: 0.50353593 | L58: 0.47247344 | M58: 0.45784858 | N58: 0.47778464 | O58: 0.49129049 | P58: 0.47756411 | Q58: 0.48053157 | R58: 0.48258498 | S58: 0.50072904 | T58: 0.48711376 | U58: 0.47039868 | V58: 0.4593602 | W58: 0.50185993 | X58: 0.49592957 | Y58: 0.48926304 | Z58: 0.51270759 | AA58: 0.53031033 | AB58: 0.53944434 | AC58: 0.50336182 | AD58: 0.51076897 | AE58: 0.52965674 | AF58: 0.53885598 | AG58: 0.50157668 | AH58: 0.52822317 | AI58: 0.53063555 | AJ58: 0.54642883 | AK58: 0.51423698 | AL58: 0.53753762 | AM58: 0.5117602 | AN58: 0.53542166 | AO58: 0.50107066 | AP58: 0.5472837 | AQ58: =AQ57/AQ34 -> 0.96750955 | AR58: =AR57/AR34 -> 0.97783795 | AS58: =AS57/AS34 -> 0.96335954 | AT58: =AT57/AT34 -> 0.9417398 | AU58: =AU57/AU34 -> 0.92889998 | AV58: =AV57/AV34 -> 0.92515987 | AW58: =AW57/AW34 -> 0.93792383 | AX58: =AX57/AX34 -> 0.9476874 | ... CP58: =CP57/CP34 -> 1.0123409 | CT58: 1.0123409 | CX58: 0.47651288 | CY58: 0.48238996 | CZ58: 0.4772367 | DA58: 0.50105696 | DB58: 0.51988724 | DC58: 0.52518663 | DD58: 0.5330931 | DE58: 0.52710814 | DF58: =DF57/DF34 -> 0.96229195 | DG58: =DG57/DG34 -> 0.9349431 | DH58: =DH57/DH34 -> 0.94731181 | DI58: =DI57/DI34 -> 0.97390409 | DJ58: =DJ57/DJ34 -> 0.97118397 | DK58: =DK57/DK34 -> 0.97915589 | DL58: =DL57/DL34 -> 0.97460555 | DM58: =DM57/DM34 -> 0.97636907 | ... DR58: =DR57/DR34 -> 1.0123409 | DS58: =+DR58+DS59 -> 1.0123409 | DT58: =+DS58+DT59 -> 1.0123409 | DU58: =+DT58+DU59 -> 1.0123409 | DV58: =+DU58+DV59 -> 1.0123409 | DY58: 0.98828804 | DZ58: 0.98828804
A59: dif yoy | AQ59: =+AQ58-AM58 -> 0.45574935 | AR59: =+AR58-AN58 -> 0.44241629 | AS59: =+AS58-AO58 -> 0.46228888 | AT59: =+AT58-AP58 -> 0.3944561 | AU59: =+AU58-AQ58 -> -0.038609566 | AV59: =+AV58-AR58 -> -0.052678077 | AW59: =+AW58-AS58 -> -0.025435711 | AX59: =+AX58-AT58 -> 0.0059476046 | ... CP59: =+CP58-CL58 -> 0 | CT59: 0.0086522853 | DG59: =+DG58-DF58 -> -0.027348857 | DH59: =+DH58-DG58 -> 0.012368713 | DI59: =+DI58-DH58 -> 0.026592282 | DJ59: =+DJ58-DI58 -> -0.0027201266 | DK59: =+DK58-DJ58 -> 0.0079719261 | DL59: =+DL58-DK58 -> -0.0045503383 | DM59: =+DM58-DL58 -> 0.0017635178 | DN59: =+DN58-DM58 -> -0.041281048 | ... DR59: =+DR58-DQ58 -> 0.0041597216 | DS59: 0 | DT59: 0 | DU59: 0 | DV59: 0 | DY59: -0.02 | DZ59: 0
A61: Carteira Total | AQ61: =+Cartao!AQ21 -> 1129443 | AR61: =+Cartao!AR21 -> 1197445 | AS61: =+Cartao!AS21 -> 1183199 | AT61: =+Cartao!AT21 -> 1576372 | AU61: =+Cartao!AU21 -> 1392225 | AV61: =+Cartao!AV21 -> 1472249.4 | AW61: =+Cartao!AW21 -> 1423136 | AX61: =+Cartao!AX21 -> 1762658 | ... CP61: =+Cartao!CP21 -> 6979342.7 | CT61: 6568557 | DF61: =+(Cartao!DE166+Cartao!DE240) -> 1576372 | DG61: =+(Cartao!DF166+Cartao!DF240) -> 1762658 | DH61: =+Cartao!DH21 -> 2286651.6 | DI61: =+Cartao!DI21 -> 2761210.8 | DJ61: =+Cartao!DJ21 -> 3417337.8 | DK61: =+Cartao!DK21 -> 3535836.4 | DL61: =+Cartao!DL21 -> 4811666 | DM61: =+Cartao!DM21 -> 6368525 | DN61: =+Cartao!DN21 -> 6186858 | DO61: =+Cartao!DO21 -> 6182188.4 | ... DV61: =+Cartao!DV21 -> 0 | DY61: 0 | DZ61: 0
A62: Yield / cartera total | L62: 0.48528184 | N62: 0.47006171 | P62: 0.48320807 | R62: 0.48177077 | T62: 0.49295757 | V62: 0.464024 | X62: 0.49827389 | Z62: 0.50318708 | AB62: 0.53568702 | AD62: 0.50774355 | AE62: 0.51805853 | AF62: 0.53509816 | AG62: 0.52144301 | AH62: 0.51747669 | AI62: 0.52916182 | AJ62: 0.53979603 | AK62: 0.53083671 | AL62: 0.52812096 | AM62: 0.52773509 | AN62: 0.52514914 | AO62: 0.51861933 | AP62: 0.52857217 | AQ62: =+AQ57/AQ61/3 -> 0.035435166 | AR62: =+AR57/AR61/3 -> 0.039205141 | AS62: =+AS57/AS61/3 -> 0.042531589 | AT62: =+AT57/AT61/3 -> 0.029590097 | AU62: =+AU57/AU61/3 -> 0.036263056 | AV62: =+AV57/AV61/3 -> 0.038159521 | AW62: =+AW57/AW61/3 -> 0.037838501 | AX62: =+AX57/AX61/3 -> 0.031699475 | ... CP62: =+CP57/CP61/3 -> 0.024611689 | CT62: 0.023415933 | DF62: =+DF57/DF61/12 -> 0.029170832 | DG62: =+DG57/DG61/12 -> 0.030691055 | DH62: =+DH57/DH61/12 -> 0.025195829 | DI62: =+DI57/DI61/12 -> 0.024814024 | DJ62: =+DJ57/DJ61/12 -> 0.022288036 | DK62: =+DK57/DK61/12 -> 0.025701816 | DL62: =+DL57/DL61/12 -> 0.014796469 | DM62: =+DM57/DM61/12 -> 0.012978211 | ... DV62: =+DV57/DV61/12 -> #DIV/0! | DY62: #DIV/0! | DZ62: #DIV/0!
A64: SG&A Total (varejo+cartão) | C64: -84750 | D64: -91784 | E64: -95129 | F64: -135134 | G64: -95514 | H64: -117471 | I64: -111847 | J64: -162929 | K64: -117831 | L64: -151756 | M64: -141088 | N64: -208668 | O64: -164909 | P64: -201551 | Q64: -193465 | R64: -263324 | S64: -204130 | T64: -247727 | U64: -232710 | V64: -276144 | W64: -214414 | X64: -254160 | Y64: -249284 | Z64: -290240 | AA64: -242834 | AB64: -275480 | AC64: -275741 | AD64: -336298 | AE64: -290161 | AF64: -333704 | AG64: -332503 | AH64: -409791 | AI64: -365206 | AJ64: -407715 | AK64: -400138 | AL64: -495952 | AM64: -429671 | AN64: -458689 | AO64: -453196 | AP64: -510750 | AQ64: =AQ73+AQ82+AQ89+AQ94+AQ96 -> -458621.48 | AR64: =AR73+AR82+AR89+AR94+AR96 -> -553031 | AS64: =AS73+AS82+AS89+AS94+AS96 -> -554792 | AT64: =AT73+AT82+AT89+AT94+AT96 -> -682411.73 | AU64: =AU73+AU82+AU89+AU94+AU96 -> -571198.72 | AV64: =AV73+AV82+AV89+AV94+AV96 -> -663910.36 | AW64: =AW73+AW82+AW89+AW94+AW96 -> -667252 | AX64: =AX73+AX82+AX89+AX94+AX96 -> -798231.7 | ... CP64: =CP73+CP82+CP89+CP94+CP96 -> -2398421.4 | CT64: -2233803.1 | CU64: =+CK64/CT64-1 -> -0.14612572 | CV64: -406797 | CW64: -487761 | CX64: -619343 | CY64: -823249 | CZ64: -960711 | DA64: -1008098 | DB64: -1130353 | DC64: -1366159 | DD64: -1669011 | DE64: -1852306 | DF64: =DF73+DF82+DF89+DF94+DF96 -> -2248856.2 | DG64: =DG73+DG82+DG89+DG94+DG96 -> -2700592.8 | DH64: =DH73+DH82+DH89+DH94+DH96 -> -2900806 | DI64: =DI73+DI82+DI89+DI94+DI96 -> -3412153 | DJ64: =DJ73+DJ82+DJ89+DJ94+DJ96 -> -3718202.4 | DK64: =DK73+DK82+DK89+DK94+DK96 -> -4181537 | DL64: =DL73+DL82+DL89+DL94+DL96 -> -3456731 | DM64: =DM73+DM82+DM89+DM94+DM96 -> -5358434 | ... DV64: =DV73+DV82+DV89+DV94+DV96 -> -10214423 | DY64: -8430181.8 | DZ64: -8645911.9
A65: % rec líq | C65: -0.48057022 | D65: -0.38328134 | E65: -0.45309233 | F65: -0.41195999 | G65: -0.45438717 | H65: -0.39715399 | I65: -0.41140337 | J65: -0.38401744 | K65: -0.4417249 | L65: -0.39845613 | M65: -0.40684339 | N65: -0.38869754 | O65: -0.47448318 | P65: -0.41059787 | Q65: -0.43572021 | R65: -0.40605089 | S65: -0.47274529 | T65: -0.43741205 | U65: -0.45507167 | V65: -0.41001762 | W65: -0.51156432 | X65: -0.41433681 | Y65: -0.45134716 | Z65: -0.37269075 | AA65: -0.48019854 | AB65: -0.39241159 | AC65: -0.42825371 | AD65: -0.37376744 | AE65: -0.48459751 | AF65: -0.3989675 | AG65: -0.44816436 | AH65: -0.38607299 | AI65: -0.5148997 | AJ65: -0.42672384 | AK65: -0.4421131 | AL65: -0.38364998 | AM65: -0.51528387 | AN65: -0.43256142 | AO65: -0.4436856 | AP65: -0.35110525 | AQ65: =AQ64/AQ26 -> -0.48861564 | AR65: =AR64/AR26 -> -0.44058211 | AS65: =AS64/AS26 -> -0.46086611 | AT65: =AT64/AT26 -> -0.37528162 | AU65: =AU64/AU26 -> -0.48656261 | AV65: =AV64/AV26 -> -0.43212049 | AW65: =AW64/AW26 -> -0.46969566 | AX65: =AX64/AX26 -> -0.39629325 | ... CP65: =CP64/CP26 -> -0.45682635 | CT65: -0.4626942 | CU65: =+CK65-CT65 -> -0.072566638 | CV65: -0.42649957 | CW65: -0.40574797 | CX65: -0.40447207 | CY65: -0.42634646 | CZ65: -0.44008608 | DA65: -0.42650451 | DB65: -0.41083756 | DC65: -0.42184384 | DD65: -0.43210551 | DE65: -0.4238316 | DF65: =DF64/DF26 -> -0.43114211 | DG65: =DG64/DG26 -> -0.43946392 | DH65: =DH64/DH26 -> -0.44962722 | DI65: =DI64/DI26 -> -0.4583575 | DJ65: =DJ64/DJ26 -> -0.44124895 | DK65: =DK64/DK26 -> -0.43610205 | DL65: =DL64/DL26 -> -0.45862392 | DM65: =DM64/DM26 -> -0.50687277 | ... DV65: =DV64/DV26 -> -0.45810367 | DY65: -0.49083195 | DZ65: -0.46642712
A66: var q-o-q | D66: 0.08299705 | E66: 0.03644426 | F66: 0.42053422 | G66: -0.29319046 | H66: 0.22988253 | I66: -0.047875646 | J66: 0.45671319 | K66: -0.27679541 | L66: 0.28791235 | M66: -0.070297056 | N66: 0.47899183 | O66: -0.20970633 | P66: 0.22219527 | Q66: -0.040118878 | R66: 0.36109374 | S66: -0.22479531 | T66: 0.21357468 | U66: -0.060619149 | V66: 0.18664432 | W66: -0.22354279 | X66: 0.18537036 | Y66: -0.019184766 | Z66: 0.16429454 | AA66: -0.16333379 | AB66: 0.13443752 | AC66: 0.0009474372 | AD66: 0.21961551 | AE66: -0.13719082 | AF66: 0.15006496 | AG66: -0.0035989979 | AH66: 0.23244302 | AI66: -0.10879936 | AJ66: 0.11639732 | AK66: -0.01858406 | AL66: 0.23945239 | AM66: -0.13364398 | AN66: 0.067535393 | AO66: -0.011975434 | AP66: 0.12699583 | AQ66: =AQ64/AP64-1 -> -0.10206269 | AR66: =AR64/AQ64-1 -> 0.20585499 | AS66: =AS64/AR64-1 -> 0.00318427 | AT66: =AT64/AS64-1 -> 0.23003167 | AU66: =AU64/AT64-1 -> -0.16297054 | AV66: =AV64/AU64-1 -> 0.16231066 | AW66: =AW64/AV64-1 -> 0.0050332708 | AX66: =AX64/AW64-1 -> 0.1962972 | ... CP66: =CP64/CO64-1 -> 0.15959031 | CT66: 0.1711326
A67: var y-o-y | G67: 0.12700885 | H67: 0.27986359 | I67: 0.17574031 | J67: 0.20568473 | K67: 0.23365161 | L67: 0.29185927 | M67: 0.2614375 | N67: 0.28072964 | O67: 0.39953832 | P67: 0.32812541 | Q67: 0.37123639 | R67: 0.26192804 | S67: 0.2378342 | T67: 0.2291033 | U67: 0.20285323 | V67: 0.04868527 | W67: 0.05037966 | X67: 0.025968102 | Y67: 0.071221692 | Z67: 0.051045831 | AA67: 0.13254732 | AB67: 0.083884167 | AC67: 0.10613196 | AD67: 0.15868936 | AE67: 0.19489445 | AF67: 0.21135473 | AG67: 0.20585259 | AH67: 0.21853535 | AI67: 0.25863228 | AJ67: 0.22178637 | AK67: 0.2034117 | AL67: 0.21025596 | AM67: 0.17651682 | AN67: 0.12502361 | AO67: 0.13259925 | AP67: 0.029837565 | AQ67: =AQ64/AM64-1 -> 0.06737825 | AR67: =AR64/AN64-1 -> 0.20567749 | AS67: =AS64/AO64-1 -> 0.22417674 | AT67: =AT64/AP64-1 -> 0.33609737 | AU67: =AU64/AQ64-1 -> 0.24546875 | AV67: =AV64/AR64-1 -> 0.20049393 | AW67: =AW64/AS64-1 -> 0.2027066 | AX67: =AX64/AT64-1 -> 0.16972153 | ... CP67: =CP64/CL64-1 -> 0.073694202 | CT67: 0.0077264755 | CW67: 0.19902802 | CX67: 0.26976737 | CY67: 0.32922952 | CZ67: 0.166975 | DA67: 0.049324927 | DB67: 0.12127293 | DC67: 0.20861271 | DD67: 0.22168137 | DE67: 0.10982252 | DF67: =DF64/DE64-1 -> 0.21408461 | DG67: =DG64/DF64-1 -> 0.20087392 | DH67: =DH64/DG64-1 -> 0.074136769 | DI67: =DI64/DH64-1 -> 0.17627756 | DJ67: =DJ64/DI64-1 -> 0.089693912 | DK67: =DK64/DJ64-1 -> 0.12461254 | DL67: =DL64/DK64-1 -> -0.17333483 | DM67: =DM64/DL64-1 -> 0.55014492 | ... DV67: =DV64/DU64-1 -> 0.051751055 | DY67: 0.059308118 | DZ67: 0.025590199
A69: SG&A Retail | AQ69: =+AQ64-AQ94-AQ99-AQ114-AQ117-AQ120 -> -396953.19 | AR69: =+AR64-AR94-AR99-AR114-AR117-AR120 -> -457896 | AS69: =+AS64-AS94-AS99-AS114-AS117-AS120 -> -458088 | AT69: =+AT64-AT94-AT99-AT114-AT117-AT120 -> -563692.53 | AU69: =+AU64-AU94-AU99-AU114-AU117-AU120 -> -480995.82 | AV69: =+AV64-AV94-AV99-AV114-AV117-AV120 -> -540741.02 | AW69: =+AW64-AW94-AW99-AW114-AW117-AW120 -> -547937 | AX69: =+AX64-AX94-AX99-AX114-AX117-AX120 -> -641008 | ... CH69: =+CH64-CH94-CH99-CH114-CH117-CH120 -> -1674539 | CI69: =+CI73+CI82+CI108 -> -1143625 | CJ69: =+CJ64-CJ94-CJ99-CJ114-CJ117-CJ120 -> -1635493 | CK69: =+CK64-CK94-CK99-CK114-CK117-CK120 -> -1489490 | CL69: =+CL64-CL94-CL99-CL114-CL117-CL120 -> -1713024.5 | CM69: =+CM64-CM94-CM99-CM114-CM117-CM120 -> -1520052.8 | CN69: =+CN64-CN94-CN99-CN114-CN117-CN120 -> -1683342.4 | CO69: =+CO64-CO94-CO99-CO114-CO117-CO120 -> -1587485.4 | CP69: =+CP64-CP94-CP99-CP114-CP117-CP120 -> -1825725.7 | CT69: -1713024.5 | CU69: =+CK69/CT69-1 -> -0.13049113
A70: % Net Rev Retail | AQ70: =+AQ69/AQ30 -> -0.48734855 | AR70: =+AR69/AR30 -> -0.41207418 | AS70: =+AS69/AS30 -> -0.43748633 | AT70: =+AT69/AT30 -> -0.33757945 | AU70: =+AU69/AU30 -> -0.47581185 | AV70: =+AV69/AV30 -> -0.39929895 | AW70: =+AW69/AW30 -> -0.43892371 | AX70: =+AX69/AX30 -> -0.34887333 | ... CP70: =+CP69/CP30 -> -0.38508129 | CT70: -0.39181572
A71: yoy | AU71: =+AU69/AQ69-1 -> 0.21171924 | AV71: =+AV69/AR69-1 -> 0.18092541 | AW71: =+AW69/AS69-1 -> 0.19613917 | AX71: =+AX69/AT69-1 -> 0.13715895 | AY71: =+AY69/AU69-1 -> 0.15378966 | AZ71: =+AZ69/AV69-1 -> 0.13361845 | BA71: =+BA69/AW69-1 -> 0.078655028 | BB71: =+BB69/AX69-1 -> 0.013325887 | ... CP71: =+CP69/CL69-1 -> 0.06579077 | CT71: 0.022982749
CA72: =+CA73-BW73 -> -44226 | CB72: =+CB73-BX73 -> -9260 | CC72: =+CC73-BY73 -> -14976 | CD72: =+CD73-BZ73 -> -46702 | CE72: =+CE73-CA73 -> -23560 | CF72: =+CF73-CB73 -> -24628 | CG72: =+CG73-CC73 -> -55450 | CH72: =+CH73+CH82+CH108+CH111 -> -1368069 | CI72: =+CI73-CE73 -> -59764 | CJ72: =+CJ73-CF73 -> -97647 | CK72: =+CK73-CG73 -> -57138 | CL72: =+CL73-CH73 -> -41613.357 | CM72: =+CM73-CI73 -> -41069.242 | CN72: =+CN73-CJ73 -> -38950.134 | CO72: =+CO73-CK73 -> -62476.59 | CP72: =+CP73-CL73 -> -83456.652 | CT72: -41613.357 | CU72: =+CK72/CT72-1 -> 0.37306875
A73: Vendas | C73: -51603 | D73: -64147 | E73: -58677 | F73: -76991 | G73: -59875 | H73: -74554 | I73: -71689 | J73: -92534 | K73: -75638 | L73: -94012 | M73: -89403 | N73: -119546 | O73: -91089 | P73: -107330 | Q73: -104190 | R73: -137318 | S73: -113624 | T73: -130237 | U73: -121301 | V73: -149932 | W73: -120897 | X73: -136055 | Y73: -137375 | Z73: -160143 | AA73: -137053 | AB73: -148731 | AC73: -159934 | AD73: -195985 | AE73: -167000 | AF73: -185211 | AG73: -189434 | AH73: -233896 | AI73: -208242 | AJ73: -226085 | AK73: -217724 | AL73: -277504 | AM73: -240057 | AN73: -249580 | AO73: -249297 | AP73: -291122 | AQ73: -256198 | AR73: -286169 | AS73: -287355 | AT73: -342031 | AU73: -307292 | AV73: -343999 | AW73: -339070 | AX73: -399367 | AY73: -353110 | AZ73: -394357 | BA73: -375259 | BB73: -424735 | BC73: -418444.63 | BD73: -463130.49 | BE73: -455512.74 | BF73: -528912.5 | BG73: -478099 | BH73: -507826 | BI73: -504648 | BJ73: -584814 | BK73: -439174 | BL73: -495829 | BM73: -481346 | BN73: -559371 | BO73: -475090 | BP73: -271005 | BQ73: -478255 | BR73: -661278 | BS73: -538038 | BT73: -600683 | BU73: -629903 | BV73: -776488 | BW73: -629768 | BX73: -729685 | BY73: -675481 | BZ73: -794501 | CA73: -673994 | CB73: -738945 | CC73: -690457 | CD73: -841203 | CE73: -697554 | CF73: -763573 | CG73: -745907 | CH73: -912334 | CI73: -757318 | CJ73: -861220 | CK73: -803045 | CL73: =+CL74*CL26 -> -953947.36 | CM73: =+CM74*CM26 -> -798387.24 | CN73: =+CN74*CN26 -> -900170.13 | CO73: =+CO74*CO26 -> -865521.59 | CP73: =+CP74*CP26 -> -1037404 | CT73: -953947.36 | CU73: =+CK73/CT73-1 -> -0.1581873 | CV73: -251418 | CW73: -298652 | CX73: -378599 | CY73: -439927 | CZ73: -515094 | DA73: -554470 | DB73: -641703 | DC73: -775541 | DD73: -929555 | DE73: -1030056 | DF73: =+SUM(AQ73:AT73) -> -1171753 | DG73: =+SUM(AU73:AX73) -> -1389728 | DH73: =+SUM(AY73:BB73) -> -1547461 | DI73: =+SUM(BC73:BF73) -> -1866000.4 | DJ73: =+SUM(BG73:BJ73) -> -2075387 | DK73: =+SUM(BK73:BN73) -> -1975720 | DL73: =+SUM(BO73:BR73) -> -1885628 | DM73: =+SUM(BS73:BV73) -> -2545112 | DN73: =+SUM(BW73:BZ73) -> -2829435 | DO73: =+SUM(CA73:CD73) -> -2944599 | DP73: =+SUM(CE73:CH73) -> -3119368 | DQ73: =+SUM(CI73:CL73) -> -3375530.4 | DR73: =+SUM(CM73:CP73) -> -3601483 | DS73: =+DS74*DS26 -> -3810986.6 | DT73: =+DT74*DT26 -> -4071063.9 | DU73: =+DU74*DU26 -> -4348896.5 | DV73: =+DV74*DV26 -> -4645465.6 | DY73: -3623986.5 | DZ73: -3707293.8
A74: % Rec.Líq | C74: -0.29261198 | D74: -0.26787183 | E74: -0.27947417 | F74: -0.23470934 | G74: -0.28484234 | H74: -0.25205726 | I74: -0.26369144 | J74: -0.21809911 | K74: -0.28355176 | L74: -0.24684136 | M74: -0.25780378 | N74: -0.22268501 | O74: -0.26208514 | P74: -0.21865171 | Q74: -0.23465582 | R74: -0.21174711 | S74: -0.26314217 | T74: -0.22995972 | U74: -0.23720789 | V74: -0.2226185 | W74: -0.28844475 | X74: -0.22179963 | Y74: -0.24872762 | Z74: -0.20563607 | AA74: -0.27101909 | AB74: -0.21186209 | AC74: -0.2483937 | AD74: -0.21782113 | AE74: -0.27890649 | AF74: -0.22143328 | AG74: -0.25532873 | AH74: -0.2203585 | AI74: -0.29359798 | AJ74: -0.23662573 | AK74: -0.24056359 | AL74: -0.21466675 | AM74: -0.28788887 | AN74: -0.23536357 | AO74: -0.24406546 | AP74: -0.20012621 | AQ74: =AQ73/AQ26 -> -0.27295353 | AR74: =AR73/AR26 -> -0.22798169 | AS74: =AS73/AS26 -> -0.238706 | AT74: =AT73/AT26 -> -0.18809458 | AU74: =AU73/AU26 -> -0.26175969 | AV74: =AV73/AV26 -> -0.22389923 | AW74: =AW73/AW26 -> -0.23868 | AX74: =AX73/AX26 -> -0.19827131 | ... CK74: =CK73/CK26 -> -0.22535465 | CL74: =+CH74 -> -0.19759392 | CM74: =+CI74 -> -0.232479 | CN74: =+CJ74 -> -0.2066482 | CO74: =+CK74 -> -0.22535465 | CP74: =+CL74 -> -0.19759392 | CT74: -0.19759392 | CU74: =+CK74-CT74 -> -0.027760736 | CV74: -0.26359504 | CW74: -0.24843611 | CX74: -0.24725026 | CY74: -0.2278306 | CZ74: -0.23595618 | DA74: -0.23458429 | DB74: -0.23323307 | DC74: -0.23947227 | DD74: -0.24066099 | DE74: -0.23569015 | DF74: =DF73/DF26 -> -0.224644 | DG74: =DG73/DG26 -> -0.22614861 | DH74: =DH73/DH26 -> -0.23985768 | DI74: =DI73/DI26 -> -0.25066146 | DJ74: =DJ73/DJ26 -> -0.24629169 | DK74: =DK73/DK$26 -> -0.20605235 | DL74: =DL73/DL26 -> -0.25017686 | DM74: =DM73/DM26 -> -0.24075093 | DN74: =DN73/DN26 -> -0.21320215 | DO74: =DO73/DO26 -> -0.21575554 | DP74: =DP73/DP26 -> -0.21607709 | DQ74: =DQ73/DQ26 -> -0.21341921 | DR74: =DR73/DR26 -> -0.21334314 | DS74: =+DR74+0.5% -> -0.20834314 | DT74: =+DS74 -> -0.20834314 | DU74: =+DT74 -> -0.20834314 | DV74: =+DU74 -> -0.20834314 | DY74: -0.211 | DZ74: -0.2
A75: % Rec.Líq Merc | C75: #DIV/0! | D75: #DIV/0! | E75: #DIV/0! | F75: #DIV/0! | G75: -0.30238066 | H75: -0.26707696 | I75: -0.28067874 | J75: -0.22912339 | K75: -0.30135262 | L75: -0.26281698 | M75: -0.2789285 | N75: -0.23584721 | O75: -0.29355802 | P75: -0.24154111 | Q75: -0.2635333 | R75: -0.22820838 | S75: -0.29637204 | T75: -0.2554438 | U75: -0.27013767 | V75: -0.24428521 | W75: -0.33337194 | X75: -0.24526258 | Y75: -0.28224067 | Z75: -0.22496481 | AA75: -0.31131004 | AB75: -0.23608507 | AC75: -0.28120758 | AD75: -0.2379299 | AE75: -0.32257628 | AF75: -0.24706231 | AG75: -0.28829846 | AH75: -0.24058919 | AI75: -0.33630868 | AJ75: -0.26437464 | AK75: -0.27105047 | AL75: -0.23431268 | AM75: -0.33032443 | AN75: -0.26349156 | AO75: -0.27488373 | AP75: -0.21840364 | AQ75: =AQ73/AQ$30 -> -0.31454017 | AR75: =AR73/AR$30 -> -0.25753196 | AS75: =AS73/AS$30 -> -0.27443174 | AT75: =AT73/AT$30 -> -0.20483265 | AU75: =AU73/AU$30 -> -0.30398014 | AV75: =AV73/AV$30 -> -0.2540189 | AW75: =AW73/AW$30 -> -0.27161127 | AX75: =AX73/AX$30 -> -0.21735844 | ... CP75: =CP73/CP$30 -> -0.21880881 | CT75: -0.21819394 | CV75: #DIV/0! | CW75: #DIV/0! | CX75: -0.26362887 | CY75: -0.25113888 | CZ75: -0.26333766 | DA75: -0.2620407 | DB75: -0.26057058 | DC75: -0.26774036 | DD75: -0.26850541 | DE75: -0.26318525 | DF75: =DF73/DF$30 -> -0.2523909 | DG75: =DG73/DG$30 -> -0.25495611 | DH75: =DH73/DH$30 -> -0.27045202 | DI75: =DI73/DI$30 -> -0.2827242 | DJ75: =DJ73/DJ$30 -> -0.27725677 | DK75: =DK73/DK$30 -> -0.23313175 | DL75: =DL73/DL$30 -> -0.28310306 | DM75: =DM73/DM$30 -> -0.26634417 | ... DV75: =DV73/DV$30 -> -0.23101006 | DY75: -0.2372083 | DZ75: -0.22289411
A76: var y-o-y | G76: 0.16030076 | H76: 0.16223674 | I76: 0.2217564 | J76: 0.20188074 | K76: 0.26326514 | L76: 0.26099203 | M76: 0.24709509 | N76: 0.29191432 | O76: 0.20427563 | P76: 0.14166277 | Q76: 0.16539713 | R76: 0.14866244 | S76: 0.2473954 | T76: 0.21342588 | U76: 0.16422881 | V76: 0.091859771 | W76: 0.064009364 | X76: 0.044672405 | Y76: 0.13251333 | Z76: 0.068104207 | AA76: 0.13363442 | AB76: 0.093168204 | AC76: 0.16421474 | AD76: 0.22381247 | AE76: 0.21850671 | AF76: 0.24527503 | AG76: 0.18445109 | AH76: 0.19343827 | AI76: 0.24695808 | AJ76: 0.22068884 | AK76: 0.14933961 | AL76: 0.18644184 | AM76: 0.15277898 | AN76: 0.10392109 | AO76: 0.14501387 | AP76: 0.049073167 | AQ76: =AQ73/AM73-1 -> 0.067238198 | AR76: =AR73/AN73-1 -> 0.14660229 | AS76: =AS73/AO73-1 -> 0.15266128 | AT76: =AT73/AP73-1 -> 0.1748717 | AU76: =AU73/AQ73-1 -> 0.19943169 | AV76: =AV73/AR73-1 -> 0.20208338 | AW76: =AW73/AS73-1 -> 0.17996903 | AX76: =AX73/AT73-1 -> 0.16763393 | ... CP76: =CP73/CL73-1 -> 0.087485595 | CT76: 0.045611976 | CW76: 0.1878704 | CX76: 0.26769283 | CY76: 0.16198669 | CZ76: 0.17086244 | DA76: 0.076444299 | DB76: 0.15732682 | DC76: 0.20856689 | DD76: 0.19858911 | DE76: 0.10811732 | DF76: =DF73/DE73-1 -> 0.13756242 | DG76: =DG73/DF73-1 -> 0.1860247 | DH76: =DH73/DG73-1 -> 0.11349919 | DI76: =DI73/DH73-1 -> 0.20584646 | DJ76: =DJ73/DI73-1 -> 0.11221147 | DK76: =DK73/DJ73-1 -> -0.048023333 | DL76: =DL73/DK73-1 -> -0.045599579 | DM76: =DM73/DL73-1 -> 0.34974237 | ... DV76: =DV73/DU73-1 -> 0.068194097 | DY76: 0.059662187 | DZ76: 0.022987748
A77: var q-o-q | D77: 0.24308664 | E77: -0.085272889 | F77: 0.31211548 | G77: -0.2223117 | H77: 0.24516075 | I77: -0.038428522 | J77: 0.29076985 | K77: -0.18259234 | L77: 0.24292023 | M77: -0.049025656 | N77: 0.33715871 | O77: -0.23804226 | P77: 0.17829815 | Q77: -0.029255567 | R77: 0.31795758 | S77: -0.17254839 | T77: 0.14621031 | U77: -0.068613374 | V77: 0.23603268 | W77: -0.19365446 | X77: 0.12537946 | Y77: 0.0097019588 | Z77: 0.16573612 | AA77: -0.14418364 | AB77: 0.085207912 | AC77: 0.075323907 | AD77: 0.22541173 | AE77: -0.14789397 | AF77: 0.1090479 | AG77: 0.022801022 | AH77: 0.23470971 | AI77: -0.10968123 | AJ77: 0.085683964 | AK77: -0.036981666 | AL77: 0.2745678 | AM77: -0.1349422 | AN77: 0.039669745 | AO77: -0.001133905 | AP77: 0.16777177 | AQ77: =AQ73/AP73-1 -> -0.11996345 | AR77: =AR73/AQ73-1 -> 0.11698374 | AS77: =AS73/AR73-1 -> 0.0041444042 | AT77: =AT73/AS73-1 -> 0.19027336 | AU77: =AU73/AT73-1 -> -0.10156682 | AV77: =AV73/AU73-1 -> 0.11945316 | AW77: =AW73/AV73-1 -> -0.01432853 | AX77: =AX73/AW73-1 -> 0.17783054 | ... CP77: =CP73/CO73-1 -> 0.19858825 | CT77: 0.1879127 | CW77: 0.26035118 | CX77: 0.27377284 | CY77: 0.26103127 | CZ77: 0.13054167 | DA77: 0.082739542 | DB77: 0.16403173 | DC77: 0.17707893 | DD77: 0.1926688 | DE77: 0.13148814 | DF77: =+DF27 -> 0.19349842
A78: Fator de cres desp | N78: 1.1443904 | O78: 0.86465246 | P78: 0.58484 | Q78: 0.7084063 | R78: 0.79451165 | S78: 1.0502813 | T78: 1.4480899 | U78: 1.20965 | V78: 4.5923932 | W78: -1.1835682 | X78: 0.50741984 | Y78: 1.5784962 | Z78: 0.42609074 | AA78: 0.62453945 | AB78: 0.6867585 | AC78: 0.97461579 | AD78: 1.4244191 | AE78: 1.2418727 | AF78: 1.291287 | AG78: 1.1875646 | AH78: 1.073185 | AI78: 1.2597242 | AJ78: 1.5679143 | AK78: 0.67126002 | AL78: 0.85436397 | AM78: 0.87974362 | AN78: 0.96562244 | AO78: 1.1237323 | AP78: 0.39105194 | AQ78: =+AQ76/AQ32 -> 0.55663362 | AR78: =+AR76/AR32 -> 0.84674612 | AS78: =+AS76/AS32 -> 0.98771708 | AT78: =+AT76/AT32 -> 0.69198118 | AU78: =+AU76/AU32 -> 0.82717756 | AV78: =+AV76/AV32 -> 0.92398675 | AW78: =+AW76/AW32 -> 0.9362558 | AX78: =+AX76/AX32 -> 1.6705537 | ... CP78: =+CP76/CP32 -> 1.0361948 | CT78: 0.9654384 | CZ78: 1.4650748 | DA78: 0.93484542 | DB78: 0.96015075 | DC78: 1.1836747 | DD78: 1.017498 | DE78: 0.82837483 | DF78: =+DF76/DF32 -> 0.73873245 | DG78: =+DG76/DG32 -> 1.0685446 | DH78: =+DH76/DH32 -> 2.2836972 | DI78: =+DI76/DI32 -> 1.3409809 | DJ78: =+DJ76/DJ32 -> 0.83650027 | DK78: =+DK76/DK32 -> -0.36337812 | DL78: =+DL76/DL32 -> 0.21301899 | DM78: =+DM76/DM32 -> 0.80461445 | ... DV78: =+DV76/DV32 -> 0.90161196 | DY78: 0.6713894 | DZ78: 0.25921046
BT80: =-236832-BT82 -> 0 | CA80: =+CA81/BW82-1 -> 0.067778366 | CB80: =+CB81/BX82-1 -> 0.025277763 | CC80: =+CC81/BY81-1 -> 0.01623868 | CD80: =+CD81/BZ81-1 -> 0.10288425 | CF80: =90000*0.4 -> 36000
BY81: =+BY82+18000 -> -314496 | BZ81: =+BZ82+18000 -> -319320 | CA81: =+CA82+17000 -> -318435 | CB81: =+CB82+18000 -> -336084 | CC81: =+CC82+27000 -> -319603 | CD81: =+CD82+28000 -> -352173
A82: G&A | C82: -15655 | D82: -19373 | E82: -19823 | F82: -31015 | G82: -17328 | H82: -22856 | I82: -22355 | J82: -27692 | K82: -23220 | L82: -32309 | M82: -31618 | N82: -41292 | O82: -32044 | P82: -34024 | Q82: -36511 | R82: -48809 | S82: -36682 | T82: -43903 | U82: -46977 | V82: -51406 | W82: -38003 | X82: -46198 | Y82: -43957 | Z82: -52188 | AA82: -40966 | AB82: -50098 | AC82: -56810 | AD82: -63890 | AE82: -51523 | AF82: -60560 | AG82: -63936 | AH82: -74662 | AI82: -64196 | AJ82: -68973 | AK82: -74110 | AL82: -86652 | AM82: -78755 | AN82: -79154 | AO82: -86293 | AP82: -86053 | AQ82: -81634 | AR82: -92299 | AS82: -98792 | AT82: -125275 | AU82: -100353 | AV82: -116651 | AW82: -122131 | AX82: -130254 | AY82: -120667 | AZ82: -130629 | BA82: -134271 | BB82: -135497 | BC82: -129705.13 | BD82: -135603.5 | BE82: -150096.69 | BF82: -169379.94 | BG82: -149298 | BH82: -161412 | BI82: -176513 | BJ82: -200229 | BK82: -170241 | BL82: -182454 | BM82: -196024 | BN82: -212317 | BO82: -190264 | BP82: -150478 | BQ82: -175639 | BR82: -206902 | BS82: -211525 | BT82: -236832 | BU82: -236494 | BV82: -299809 | BW82: -298222 | BX82: -327798 | BY82: -332496 | BZ82: -337320 | CA82: -335435 | CB82: -354084 | CC82: -346603 | CD82: -380173 | CE82: -338911 | CF82: -357670 | CG82: -357141 | CH82: -393110 | CI82: -363661 | CJ82: -414964 | CK82: -372974 | CL82: =+CH82*(1+CL85) -> -412765.5 | CM82: =+CI82*(1+CM85) -> -374570.83 | CN82: =+CJ82*(1+CN85) -> -427412.92 | CO82: =+CK82*(1+CO85) -> -384163.22 | CP82: =+CL82*(1+CP85) -> -425148.47 | CT82: -412765.5 | CU82: =+CK82/CT82-1 -> -0.096402194 | CV82: -85866 | CW82: -90231 | CX82: -128439 | CY82: -151388 | CZ82: -178968 | DA82: -180346 | DB82: -211764 | DC82: -250681 | DD82: -293931 | DE82: -330255 | DF82: =+SUM(AQ82:AT82) -> -398000 | DG82: =+SUM(AU82:AX82) -> -469389 | DH82: =+SUM(AY82:BB82) -> -521064 | DI82: =+SUM(BC82:BF82) -> -584785.26 | DJ82: =+SUM(BG82:BJ82) -> -687452 | DK82: =+SUM(BK82:BN82) -> -761036 | DL82: =+SUM(BO82:BR82) -> -723283 | DM82: =+SUM(BS82:BV82) -> -984660 | DN82: =+SUM(BW82:BZ82) -> -1295836 | DO82: =+SUM(CA82:CD82) -> -1416295 | DP82: =+SUM(CE82:CH82) -> -1446832 | DQ82: =+SUM(CI82:CL82) -> -1564364.5 | DR82: =+SUM(CM82:CP82) -> -1611295.4 | DS82: =+DR82*(1+DS85) -> -1691860.2 | DT82: =+DS82*(1+DT85) -> -1776453.2 | DU82: =+DT82*(1+DU85) -> -1865275.9 | DV82: =+DU82*(1+DV85) -> -1958539.7 | DY82: -1642582.7 | DZ82: -1724711.9
A83: % rec líq | C83: -0.088770818 | D83: -0.080899824 | E83: -0.09441547 | F83: -0.094550144 | G83: -0.082434207 | H83: -0.077273127 | I83: -0.082227707 | J83: -0.065268988 | K83: -0.087047145 | L83: -0.084831697 | M83: -0.091174121 | N83: -0.076916915 | O83: -0.092198357 | P83: -0.069313385 | Q83: -0.08222976 | R83: -0.075264456 | S83: -0.084951957 | T83: -0.077519613 | U83: -0.09186499 | V83: -0.076327445 | W83: -0.090670287 | X83: -0.075312921 | Y83: -0.079587406 | Z83: -0.067013453 | AA83: -0.081009304 | AB83: -0.071362843 | AC83: -0.088231685 | AD83: -0.071008456 | AE83: -0.086048496 | AF83: -0.072403903 | AG83: -0.086176175 | AH83: -0.07034069 | AI83: -0.090509195 | AJ83: -0.072188719 | AK83: -0.081884255 | AL83: -0.067030757 | AM83: -0.094447103 | AN83: -0.074645276 | AO83: -0.084482126 | AP83: -0.059155478 | AQ83: =AQ82/AQ26 -> -0.08697292 | AR83: =AR82/AR26 -> -0.073531661 | AS83: =AS82/AS26 -> -0.082066584 | AT83: =AT82/AT26 -> -0.068893021 | AU83: =AU82/AU26 -> -0.085483416 | AV83: =AV82/AV26 -> -0.07592484 | AW83: =AW82/AW26 -> -0.085971118 | AX83: =AX82/AX26 -> -0.064666413 | ... CP83: =CP82/CP26 -> -0.080977855 | CT83: -0.085497331 | CU83: =+CK83-CT83 -> -0.019168568 | CV83: -0.090024785 | CW83: -0.075059395 | CX83: -0.083879188 | CY83: -0.078401234 | CZ83: -0.08198233 | DA83: -0.076300501 | DB83: -0.076967643 | DC83: -0.077405511 | DD83: -0.076098483 | DE83: -0.075566621 | DF83: =DF82/DF26 -> -0.076303037 | DG83: =DG82/DG26 -> -0.076383056 | DH83: =DH82/DH26 -> -0.080765332 | DI83: =DI82/DI26 -> -0.078554716 | DJ83: =DJ82/DJ26 -> -0.081581755 | DK83: =DK82/DK26 -> -0.079370183 | DL83: =DL82/DL26 -> -0.095962018 | DM83: =DM82/DM26 -> -0.093142389 | DN83: =DN82/DN26 -> -0.097643179 | DO83: =DO82/DO$26 -> -0.10377423 | DP83: =DP82/DP$26 -> -0.10022134 | DQ83: =DQ82/DQ$26 -> -0.098907551 | DR83: =DR82/DR$26 -> -0.095449243 | DS83: =DS82/DS$26 -> -0.092492444 | DT83: =DT82/DT$26 -> -0.090912804 | DU83: =DU82/DU$26 -> -0.089360008 | DV83: =DV82/DV$26 -> -0.087837977 | DY83: -0.095636381 | DZ83: -0.09304425
A84: % Rec.Líq Merc | J84: -0.068568146 | K84: -0.092511803 | L84: -0.090322022 | M84: -0.098645027 | N84: -0.081463229 | O84: -0.10327014 | P84: -0.07656941 | Q84: -0.092349213 | R84: -0.081115532 | S84: -0.095679777 | T84: -0.086110316 | U84: -0.10461791 | V84: -0.083756138 | W84: -0.10479279 | X84: -0.083279854 | Y84: -0.09031085 | Z84: -0.073312374 | AA84: -0.093052521 | AB84: -0.079522023 | AC84: -0.099887471 | AD84: -0.0775638 | AE84: -0.099521544 | AF84: -0.080784043 | AG84: -0.097303813 | AH84: -0.076798535 | AI84: -0.10367588 | AJ84: -0.080654233 | AK84: -0.092261534 | AL84: -0.073165295 | AM84: -0.10836885 | AN84: -0.083566036 | AO84: -0.095149727 | AP84: -0.064558117 | AQ84: =AQ82/AQ$30 -> -0.10022394 | AR84: =AR82/AR$30 -> -0.083062605 | AS84: =AS82/AS$30 -> -0.094349011 | AT84: =AT82/AT$30 -> -0.07502364 | AU84: =AU82/AU$30 -> -0.099271438 | AV84: =AV82/AV$30 -> -0.086138503 | AW84: =AW82/AW$30 -> -0.097832765 | AX84: =AX82/AX$30 -> -0.0708917 | ... CP84: =CP82/CP$30 -> -0.089672133 | CT84: -0.094410799 | CV84: 4.8411e-07 | CX84: -0.089435599 | CY84: -0.086422093 | CZ84: -0.09149595 | DA84: -0.085230927 | DB84: -0.085989108 | DC84: -0.086542711 | DD84: -0.084903061 | DE84: -0.084382057 | DF84: =DF82/DF$30 -> -0.085727603 | DG84: =DG82/DG$30 -> -0.08611296 | DH84: =DH82/DH$30 -> -0.091067116 | DI84: =DI82/DI$30 -> -0.088602848 | DJ84: =DJ82/DJ$30 -> -0.091838642 | DK84: =DK82/DK$30 -> -0.089801011 | DL84: =DL82/DL$30 -> -0.10859174 | DM84: =DM82/DM$30 -> -0.10304397 | ... DV84: =DV82/DV$30 -> -0.097394406 | DY84: -0.10751537 | DZ84: -0.10369508
A85: var y-o-y | G85: 0.10686682 | H85: 0.1797863 | I85: 0.12773041 | J85: -0.10714171 | K85: 0.3400277 | L85: 0.41358943 | M85: 0.4143592 | N85: 0.49111657 | O85: 0.38001723 | P85: 0.053081185 | Q85: 0.15475362 | R85: 0.18204495 | S85: 0.14473848 | T85: 0.29035387 | U85: 0.28665334 | V85: 0.0532074 | W85: 0.036012213 | X85: 0.052274332 | Y85: -0.064286779 | Z85: 0.015212232 | AA85: 0.077967529 | AB85: 0.084419239 | AC85: 0.29239939 | AD85: 0.22422779 | AE85: 0.25770151 | AF85: 0.20883069 | AG85: 0.12543566 | AH85: 0.16860229 | AI85: 0.24596782 | AJ85: 0.13892008 | AK85: 0.15912788 | AL85: 0.16059039 | AM85: 0.22678983 | AN85: 0.14760848 | AO85: 0.16439077 | AP85: -0.0069127083 | AQ85: =AQ82/AM82-1 -> 0.036556409 | AR85: =AR82/AN82-1 -> 0.16606868 | AS85: =AS82/AO82-1 -> 0.14484373 | AT85: =AT82/AP82-1 -> 0.45578887 | AU85: =AU82/AQ82-1 -> 0.22930397 | AV85: =AV82/AR82-1 -> 0.26383818 | AW85: =AW82/AS82-1 -> 0.23624383 | AX85: =AX82/AT82-1 -> 0.039744562 | ... CK85: =CK82/CG82-1 -> 0.044332631 | CL85: 0.05 | CM85: 0.03 | CN85: 0.03 | CO85: 0.03 | CP85: 0.03 | CT85: 0.05 | CW85: 0.050835022 | CX85: 0.42344649 | CY85: 0.17867626 | CZ85: 0.18218089 | DA85: 0.0076997005 | DB85: 0.17420957 | DC85: 0.18377533 | DD85: 0.17253003 | DE85: 0.12358002 | DF85: =DF82/DE82-1 -> 0.20512937 | DG85: =DG82/DF82-1 -> 0.17936935 | DH85: =DH82/DG82-1 -> 0.11008993 | DI85: =DI82/DH82-1 -> 0.12229066 | DJ85: =DJ82/DI82-1 -> 0.17556314 | DK85: =DK82/DJ82-1 -> 0.10703875 | DL85: =DL82/DK82-1 -> -0.049607377 | DM85: =DM82/DL82-1 -> 0.36137584 | ... DR85: =DR82/DQ82-1 -> 0.03 | DS85: 0.05 | DT85: 0.05 | DU85: 0.05 | DV85: 0.05 | DY85: 0.05 | DZ85: 0.05
A86: var q-o-q | D86: 0.23749601 | E86: 0.023228204 | F86: 0.56459668 | G86: -0.4413026 | H86: 0.31902124 | I86: -0.021919846 | J86: 0.23873854 | K86: -0.16149068 | L86: 0.3914298 | M86: -0.02138723 | N86: 0.30596496 | O86: -0.2239659 | P86: 0.061790039 | Q86: 0.073095462 | R86: 0.33683 | S86: -0.24845828 | T86: 0.19685404 | U86: 0.070017994 | V86: 0.09428018 | W86: -0.26072832 | X86: 0.21564087 | Y86: -0.048508593 | Z86: 0.18725118 | AA86: -0.21503028 | AB86: 0.22291656 | AC86: 0.1339774 | AD86: 0.12462595 | AE86: -0.19356707 | AF86: 0.1753974 | AG86: 0.055746367 | AH86: 0.16776151 | AI86: -0.1401784 | AJ86: 0.074412736 | AK86: 0.074478419 | AL86: 0.16923492 | AM86: -0.091134654 | AN86: 0.005066345 | AO86: 0.090191273 | AP86: -0.0027812221 | AQ86: =AQ82/AP82-1 -> -0.051352074 | AR86: =AR82/AQ82-1 -> 0.13064409 | AS86: =AS82/AR82-1 -> 0.070347458 | AT86: =AT82/AS82-1 -> 0.26806826 | AU86: =AU82/AT82-1 -> -0.19893834 | AV86: =AV82/AU82-1 -> 0.1624067 | AW86: =AW82/AV82-1 -> 0.046977737 | AX86: =AX82/AW82-1 -> 0.06651055 | ... CP86: =CP82/CO82-1 -> 0.10668706 | CT86: 0.10668706
A87: Fator de cres desp | G87: 0.5567423 | H87: 0.76453475 | I87: 0.43315737 | J87: -0.36515431 | K87: 1.2639737 | L87: 1.4378842 | M87: 1.5036118 | N87: 1.8511112 | O87: 1.254537 | P87: 0.18376632 | Q87: 0.55198297 | R87: 0.87522795 | S87: 0.59714375 | T87: 1.8883946 | U87: 1.889568 | V87: 1.3805865 | W87: -1.2279843 | X87: 0.6290057 | Y87: -0.80296842 | Z87: 0.097318779 | AA87: 0.37752385 | AB87: 0.5844425 | AC87: 1.7637819 | AD87: 1.4433569 | AE87: 1.4001887 | AF87: 1.0907873 | AG87: 0.82371709 | AH87: 0.93826303 | AI87: 1.2546729 | AJ87: 0.9869769 | AK87: 0.71525686 | AL87: 0.73590053 | AM87: 1.3059186 | AN87: 1.3715605 | AO87: 1.2738865 | AP87: -0.055085665 | AQ87: =+AQ85/AQ32 -> 0.30263343 | AR87: =+AR85/AR32 -> 0.95918015 | AS87: =+AS85/AS32 -> 0.93713758 | AT87: =+AT85/AT32 -> 1.8035927 | AU87: =+AU85/AU32 -> 0.95107802 | AV87: =+AV85/AV32 -> 1.2063485 | AW87: =+AW85/AW32 -> 1.2290151 | AX87: =+AX85/AX32 -> 0.39607391 | ... CP87: =+CP85/CP32 -> 0.35532528 | CT87: 1.0583168 | CW87: 0.19525558 | CX87: 1.5467074 | CY87: 0.68450136 | CZ87: 1.3955765 | DA87: 0.093059501 | DB87: 1.062048 | DC87: 1.0378159 | DD87: 0.89547466 | DE87: 0.9398568 | DF87: =+DF85/DF27 -> 1.0601088 | DG87: =+DG85/DG32 -> 1.0303156 | DH87: =+DH85/DH32 -> 2.2151 | DI87: =+DI85/DI32 -> 0.79665904 | DJ87: =+DJ85/DJ32 -> 1.3087665 | DK87: =+DK85/DK32 -> 0.80993001 | DL87: =+DL85/DL32 -> 0.23174147 | DM87: =+DM85/DM32 -> 0.83137832 | DN87: =+DN85/DN32 -> 1.4949181 | ... DR87: =+DR85/DR32 -> 0.41444256 | DS87: 0.8 | DT87: 0.8 | DU87: 0.8 | DV87: 0.8 | DY87: 0.8 | DZ87: 0.8
A89: Depreciação | C89: -6509 | D89: -6762 | E89: -6894 | F89: -7178 | G89: -7112 | H89: -7870 | I89: -7917 | J89: -8159 | K89: -8540 | L89: -9355 | M89: -10043 | N89: -10721 | O89: -11703 | P89: -12100 | Q89: -12625 | R89: -13279 | S89: -14580 | T89: -15315 | U89: -15975 | V89: -16157 | W89: -18139 | X89: -18343 | Y89: -18799 | Z89: -18793 | AA89: -18795 | AB89: -17923 | AC89: -18294 | AD89: -20775 | AE89: -21515 | AF89: -22579 | AG89: -24173 | AH89: -29371 | AI89: -30147 | AJ89: -31930 | AK89: -33749 | AL89: -37124 | AM89: -39291 | AN89: -40586 | AO89: -42276 | AP89: -45284 | AQ89: -48304 | AR89: -51633 | AS89: -55024 | AT89: =-212732-AS89-AR89-AQ89 -> -57771 | AU89: -61385.209 | AV89: -63684.936 | AW89: -68235 | AX89: -71475 | AY89: -73366 | AZ89: -76912 | BA89: -78601 | BB89: -82382 | BC89: -79114 | BD89: -79710 | BE89: -82769 | BF89: -87459 | BG89: -73848 | BH89: -76281 | BI89: -81285 | BJ89: -83160 | BK89: -162480 | BL89: -164860 | BM89: -167149 | BN89: -167262 | BO89: -181578 | BP89: -183013 | BQ89: -198282 | BR89: -196768 | BS89: -201478 | BT89: -212132 | BU89: -226399 | BV89: -237007 | BW89: -235030 | BX89: -251053 | BY89: -251178 | BZ89: -256589 | CA89: -256590 | CB89: -247648 | CC89: -264253 | CD89: -281753 | CE89: -295856 | CF89: -299295 | CG89: -296223 | CH89: -306470 | CI89: -304951 | CJ89: -323073 | CK89: -307242 | CL89: =-CL130 -> -307689.11 | CM89: =-CM130 -> -340391.79 | CN89: =-CN130 -> -329862.66 | CO89: =-CO130 -> -321580.08 | CP89: =-CP130 -> -321171.78 | CT89: -307689.11 | CU89: =+CK89/CT89-1 -> -0.0014531326 | CV89: -27343 | CW89: -31058 | CX89: -38659 | CY89: -49707 | CZ89: -62027 | DA89: -74074 | DB89: -75787 | DC89: -97638 | DD89: -132950 | DE89: -167437 | DF89: =+SUM(AQ89:AT89) -> -212732 | DG89: =+SUM(AU89:AX89) -> -264780.14 | DH89: =-DH130 -> -311261 | DI89: =-DI130 -> -329052 | DJ89: =-DJ130 -> -314574 | DK89: =-DK130 -> -661751 | DL89: =+SUM(BO89:BR89) -> -759641 | DM89: =+SUM(BS89:BV89) -> -877016 | DN89: =+SUM(BW89:BZ89) -> -993850 | DO89: =+SUM(CA89:CD89) -> -1050244 | DP89: =+SUM(CE89:CH89) -> -1197844 | DQ89: =+SUM(CI89:CL89) -> -1242955.1 | DR89: =+SUM(CM89:CP89) -> -1313006.3 | DS89: =-DS130 -> -1363267.3 | DT89: =-DT130 -> -1432873.8 | DU89: =-DU130 -> -1517234.7 | DV89: =-DV130 -> -1614729.8 | DY89: -1301369 | DZ89: -1372549.9
A90: % Rec.Líq | C90: -0.036908927 | D90: -0.028237475 | E90: -0.032835608 | F90: -0.021882345 | G90: -0.0338338 | H90: -0.026607434 | I90: -0.029120857 | J90: -0.019230452 | K90: -0.032014755 | L90: -0.024562831 | M90: -0.02896014 | N90: -0.019970606 | O90: -0.033672368 | P90: -0.024650011 | Q90: -0.028433916 | R90: -0.020476484 | S90: -0.033765867 | T90: -0.027041725 | U90: -0.031239611 | V90: -0.023989856 | W90: -0.043277329 | X90: -0.029903132 | Y90: -0.034036983 | Z90: -0.024131674 | AA90: -0.037166672 | AB90: -0.025530684 | AC90: -0.028412435 | AD90: -0.023089696 | AE90: -0.035932174 | AF90: -0.026994843 | AG90: -0.032581592 | AH90: -0.027671056 | AI90: -0.042503905 | AJ90: -0.033418668 | AK90: -0.037289323 | AL90: -0.028717742 | AM90: -0.047119816 | AN90: -0.038274164 | AO90: -0.04138883 | AP90: -0.031129614 | AQ90: =AQ89/AQ26 -> -0.051463115 | AR90: =AR89/AR26 -> -0.04113436 | AS90: =AS89/AS26 -> -0.045708476 | AT90: =AT89/AT26 -> -0.031770255 | AU90: =AU89/AU26 -> -0.052289591 | AV90: =AV89/AV26 -> -0.041450725 | AW90: =AW89/AW26 -> -0.048032352 | AX90: =AX89/AX26 -> -0.03548476 | ... CP90: =CP89/CP26 -> -0.061173458 | CT90: -0.06373255 | CU90: =+CK90-CT90 -> -0.022487294 | CV90: -0.028667315 | CW90: -0.025835851 | CX90: -0.025246892 | CY90: -0.025742398 | CZ90: -0.02841356 | DA90: -0.031339111 | DB90: -0.027545507 | DC90: -0.030148752 | DD90: -0.034420641 | DE90: -0.038311754 | DF90: =DF89/DF26 -> -0.040784165 | DG90: =DG89/DG26 -> -0.043087325 | DH90: =DH89/DH26 -> -0.048245701 | DI90: =DI89/DI26 -> -0.044201843 | DJ90: =DJ89/DJ26 -> -0.037331332 | DK90: =DK89/DK26 -> -0.069015524 | DL90: =DL89/DL26 -> -0.10078584 | DM90: =DM89/DM26 -> -0.082959972 | ... DV90: =DV89/DV26 -> -0.072418546 | DY90: -0.075769832 | DZ90: -0.07404592
A91: var y-o-y | G91: 0.092640959 | H91: 0.16385685 | I91: 0.1483899 | J91: 0.1366676 | K91: 0.2007874 | L91: 0.18869123 | M91: 0.26853606 | N91: 0.31400907 | O91: 0.37037471 | P91: 0.29342598 | Q91: 0.25709449 | R91: 0.23859715 | S91: 0.2458344 | T91: 0.26570248 | U91: 0.26534653 | V91: 0.21673319 | W91: 0.24410151 | X91: 0.19771466 | Y91: 0.17677621 | Z91: 0.1631491 | AA91: 0.036165169 | AB91: -0.022897018 | AC91: -0.026863131 | AD91: 0.1054648 | AE91: 0.14471934 | AF91: 0.25977794 | AG91: 0.3213622 | AH91: 0.41376655 | AI91: 0.40120846 | AJ91: 0.41414589 | AK91: 0.39614446 | AL91: 0.26396786 | AM91: 0.30331376 | AN91: 0.27109302 | AO91: 0.25265934 | AP91: 0.2198039 | AQ91: =AQ89/AM89-1 -> 0.22939095 | AR91: =AR89/AN89-1 -> 0.27218745 | AS91: =AS89/AO89-1 -> 0.30154225 | AT91: =AT89/AP89-1 -> 0.27574861 | AU91: =AU89/AQ89-1 -> 0.27081006 | AV91: =AV89/AR89-1 -> 0.23341537 | AW91: =AW89/AS89-1 -> 0.24009523 | AX91: =AX89/AT89-1 -> 0.23721244 | ... CP91: =CP89/CL89-1 -> 0.04381913 | CT91: 0.0039779198 | CW91: 0.13586658 | CX91: 0.24473566 | CY91: 0.2857808 | CZ91: 0.24785242 | DA91: 0.19422187 | DB91: 0.023125523 | DC91: 0.28832122 | DD91: 0.36166247 | DE91: 0.25939827 | DF91: =DF89/DE89-1 -> 0.27051966 | DG91: =DG89/DF89-1 -> 0.24466533 | DH91: =DH89/DG89-1 -> 0.17554509 | DI91: =DI89/DH89-1 -> 0.057157819 | DJ91: =DJ89/DI89-1 -> -0.043999125 | DK91: =DK89/DJ89-1 -> 1.1036418 | DL91: =DL89/DK89-1 -> 0.14792573 | DM91: =DM89/DL89-1 -> 0.15451378 | ... DV91: =DV89/DU89-1 -> 0.064258411 | DY91: 0.046995939 | DZ91: 0.054696971
A92: var q-o-q | D92: 0.038869258 | E92: 0.019520852 | F92: 0.041195242 | G92: -0.0091947618 | H92: 0.10658043 | I92: 0.0059720457 | J92: 0.030567134 | K92: 0.046696899 | L92: 0.095433255 | M92: 0.07354356 | N92: 0.067509708 | O92: 0.091595933 | P92: 0.033922926 | Q92: 0.04338843 | R92: 0.05180198 | S92: 0.097974245 | T92: 0.050411523 | U92: 0.043095005 | V92: 0.011392801 | W92: 0.12267129 | X92: 0.011246485 | Y92: 0.024859619 | Z92: -0.00031916591 | AA92: 0.0001064226 | AB92: -0.046395318 | AC92: 0.02069966 | AD92: 0.13561824 | AE92: 0.035619735 | AF92: 0.049453869 | AG92: 0.070596572 | AH92: 0.2150333 | AI92: 0.026420619 | AJ92: 0.05914353 | AK92: 0.056968368 | AL92: 0.10000296 | AM92: 0.058371943 | AN92: 0.032959202 | AO92: 0.041639974 | AP92: 0.071151481 | AQ92: =AQ89/AP89-1 -> 0.066690222 | AR92: =AR89/AQ89-1 -> 0.068917688 | AS92: =AS89/AR89-1 -> 0.065675053 | AT92: =AT89/AS89-1 -> 0.04992367 | AU92: =AU89/AT89-1 -> 0.062560957 | AV92: =AV89/AU89-1 -> 0.037463856 | AW92: =AW89/AV89-1 -> 0.071446477 | AX92: =AX89/AW89-1 -> 0.047482963 | ... CP92: =CP89/CO89-1 -> -0.0012696675 | CT92: 0.0014552473
A94: PDD líq | C94: 0 | D94: 0 | E94: 0 | F94: 0 | G94: -6073 | H94: -9448 | I94: -8298 | J94: -15100 | K94: -8250 | L94: -12081 | M94: -11360 | N94: -20307 | O94: -16190 | P94: -27243 | Q94: -23773 | R94: -32999 | S94: -22079 | T94: -29959 | U94: -26464 | V94: -32625 | W94: -22262 | X94: -32035 | Y94: -28487 | Z94: -29635 | AA94: -23584 | AB94: -28568 | AC94: -18758 | AD94: -17262 | AE94: -18809 | AF94: -28926 | AG94: -24384 | AH94: -37307 | AI94: -20227 | AJ94: -33397 | AK94: -29018 | AL94: -43438 | AM94: -28825 | AN94: -37145 | AO94: -33115 | AP94: -43403 | AQ94: -29171 | AR94: -54043 | AS94: -51852 | AT94: -53392 | AU94: -45737 | AV94: -74136 | AW94: -76307 | AX94: -84962 | AY94: -50177 | AZ94: -77523 | BA94: -68812 | BB94: -65692 | BC94: -46366 | BD94: -59277 | BE94: -71408 | BF94: -78784 | BG94: -57423 | BH94: -79119 | BI94: -68260 | BJ94: -75871 | BK94: -72516 | BL94: -98456 | BM94: -101371 | BN94: -108707 | BO94: -199325 | BP94: -133866 | BQ94: -91399 | BR94: 11954 | BS94: -52105 | BT94: -77434 | BU94: -74765 | BV94: -135497 | BW94: -167454 | BX94: -281521 | BY94: -236888 | BZ94: -305880 | CA94: -346812 | CB94: -396108 | CC94: -329561 | CD94: -270796 | CE94: -264539 | CF94: -253546 | CG94: -224796 | CH94: -214399 | CI94: -177141 | CJ94: -255735 | CK94: -263131 | CL94: =+Cartao!CL99*1000 -> -214314.7 | CM94: =+Cartao!CM99*1000 -> -259626.27 | CN94: =+Cartao!CN99*1000 -> -386239.61 | CO94: =+Cartao!CO99*1000 -> -321963.18 | CP94: =+Cartao!CP99*1000 -> -251004.88 | CT94: -214314.7 | CW94: -38919 | CX94: -51998 | CY94: -100205 | CZ94: -111127 | DA94: -112419 | DB94: -88172 | DC94: -109426 | DD94: -126080 | DE94: -142488 | DF94: =+SUM(AQ94:AT94) -> -188458 | DG94: =+SUM(AU94:AX94) -> -281142 | DH94: =+SUM(AY94:BB94) -> -262204 | DI94: =+SUM(BC94:BF94) -> -255835 | DJ94: =+SUM(BG94:BJ94) -> -280673 | DK94: =+SUM(BK94:BN94) -> -381050 | DL94: =+SUM(BO94:BR94) -> -412636 | DM94: =+SUM(BS94:BV94) -> -339801 | DN94: =+SUM(BW94:BZ94) -> -991743 | DO94: =+SUM(CA94:CD94) -> -1343277 | DP94: =+SUM(CE94:CH94) -> -957280 | DQ94: =+SUM(CI94:CL94) -> -910321.7 | DR94: =+SUM(CM94:CP94) -> -1218833.9 | DS94: =+Cartao!DR99*1000 -> -1052085 | DT94: =+Cartao!DS99*1000 -> -1014195.4 | DU94: =+Cartao!DT99*1000 -> -984911.14 | DV94: =+Cartao!DU99*1000 -> -957846.74 | DY94: -1028288.1 | DZ94: -971759.93
A96: Outras | C96: -5655 | D96: 3826 | E96: -4407 | F96: -14622 | G96: -8450 | H96: -12133 | I96: -9857 | J96: -34515 | K96: -10404 | L96: -16051 | M96: -9995 | N96: -37109 | O96: -30073 | P96: -48097 | Q96: -40139 | R96: -63918 | S96: -39244 | T96: -58272 | U96: -48457 | V96: -58649 | W96: -37375 | X96: -53564 | Y96: -49153 | Z96: -59116 | AA96: -46020 | AB96: -58728 | AC96: -40703 | AD96: -55648 | AE96: -50123 | AF96: -65354 | AG96: -54960 | AH96: -71862 | AI96: -62621 | AJ96: -80727 | AK96: -74555 | AL96: -94672 | AM96: -71568 | AN96: -89369 | AO96: -75330 | AP96: -88291 | AQ96: =+AQ117+AQ99+AQ102+AQ105+AQ108+AQ111+AQ120+AQ114 -> -43314.48 | AR96: =+AR117+AR99+AR102+AR105+AR108+AR111+AR120+AR114 -> -68887 | AS96: =+AS117+AS99+AS102+AS105+AS108+AS111+AS120+AS114 -> -61769 | AT96: =+AT117+AT99+AT102+AT105+AT108+AT111+AT120+AT114 -> -103942.73 | AU96: =+AU117+AU99+AU102+AU105+AU108+AU111+AU120+AU114 -> -56431.511 | AV96: =+AV117+AV99+AV102+AV105+AV108+AV111+AV120+AV114 -> -65439.424 | AW96: =+AW117+AW99+AW102+AW105+AW108+AW111+AW120+AW114 -> -61509 | AX96: =+AX117+AX99+AX102+AX105+AX108+AX111+AX120+AX114 -> -112173.7 | ... CP96: =+CP117+CP99+CP102+CP105+CP108+CP111+CP120+CP114 -> -363692.29 | CT96: -345086.42 | CV96: -20858 | CW96: -64955 | CX96: -73559 | CY96: -182227 | CZ96: -204622 | DA96: -199208 | DB96: -201099 | DC96: -242299 | DD96: -312575 | DE96: -324558 | DF96: =+DF117+DF99+DF102+DF105+DF108+DF111+DF120+DF114 -> -277913.21 | DG96: =+DG117+DG99+DG102+DG105+DG108+DG111+DG120+DG114 -> -295553.63 | DH96: =+DH117+DH99+DH102+DH105+DH108+DH111+DH120+DH114 -> -258816 | DI96: =+DI117+DI99+DI102+DI105+DI108+DI111+DI120+DI114 -> -376480.38 | DJ96: =+DJ117+DJ99+DJ102+DJ105+DJ108+DJ111+DJ120+DJ114 -> -360116.35 | DK96: =+DK117+DK99+DK102+DK105+DK108+DK111+DK120+DK114 -> -401980 | DL96: =+DL117+DL99+DL102+DL105+DL108+DL111+DL120+DL114 -> 324457 | DM96: =+DM117+DM99+DM102+DM105+DM108+DM111+DM120+DM114 -> -611845 | ... DV96: =+DV117+DV99+DV102+DV105+DV108+DV111+DV120+DV114 -> -1037840.8 | DY96: -833955.5 | DZ96: -869596.37
A97: % rec.líq | C97: -0.032066367 | D97: 0.015977016 | E97: -0.020990212 | F97: -0.044575599 | G97: -0.040199045 | H97: -0.041020076 | I97: -0.036256699 | J97: -0.081350539 | K97: -0.039002519 | L97: -0.042144095 | M97: -0.028821726 | N97: -0.069125008 | O97: -0.086527312 | P97: -0.097982774 | Q97: -0.09040071 | R97: -0.098562837 | S97: -0.0908853 | T97: -0.10289098 | U97: -0.094759176 | V97: -0.087081826 | W97: -0.089171959 | X97: -0.087321124 | Y97: -0.088995149 | Z97: -0.075909544 | AA97: -0.09100347 | AB97: -0.083655975 | AC97: -0.063215883 | AD97: -0.061848154 | AE97: -0.083710358 | AF97: -0.07813548 | AG97: -0.074077868 | AH97: -0.067702749 | AI97: -0.088288621 | AJ97: -0.084490724 | AK97: -0.082375936 | AL97: -0.07323473 | AM97: -0.085828078 | AN97: -0.084278415 | AO97: -0.073749186 | AP97: -0.060693948 | AQ97: =AQ96/AQ26 -> -0.046147277 | AR97: =AR96/AR26 -> -0.05488007 | AS97: =AS96/AS26 -> -0.051311552 | AT97: =AT96/AT26 -> -0.057161674 | AU97: =AU96/AU26 -> -0.048069897 | AV97: =AV96/AV26 -> -0.042592672 | AW97: =AW96/AW26 -> -0.04329775 | AX97: =AX96/AX26 -> -0.055690195 | ... CP97: =CP96/CP26 -> -0.069272322 | CT97: -0.071478765 | CV97: -0.021868224 | CW97: -0.054033348 | CX97: -0.048038907 | CY97: -0.09437222 | CZ97: -0.09373401 | DA97: -0.084280606 | DB97: -0.073091347 | DC97: -0.07481731 | DD97: -0.080925399 | DE97: -0.074263074 | DF97: =DF96/DF26 -> -0.053280458 | DG97: =DG96/DG26 -> -0.048095054 | DH97: =DH96/DH26 -> -0.040116685 | DI97: =DI96/DI26 -> -0.050572938 | DJ97: =DJ96/DJ26 -> -0.042735964 | DK97: =DK96/DK26 -> -0.041923413 | DL97: =DL96/DL26 -> 0.043047532 | DM97: =DM96/DM26 -> -0.057876531 | ... DV97: =DV96/DV26 -> -0.046545822 | DY97: -0.048555537 | DZ97: -0.04691273
A99: Produtos/serviçõs financeiros | G99: -2379 | H99: -2775 | I99: -3034 | J99: -3290 | K99: -2910 | L99: -4254 | M99: -4230 | N99: -4706 | O99: -5112 | P99: -7000 | Q99: -7056 | R99: -9905 | S99: -7829 | T99: -10547 | U99: -9061 | V99: -10648 | W99: -7767 | X99: -9636 | Y99: -9667 | Z99: -11431 | AA99: -9571 | AB99: -11872 | AC99: -12363 | AD99: -18540 | AE99: -17629 | AF99: -20167 | AG99: -21205 | AH99: -27541 | AI99: -24735 | AJ99: -29247 | AK99: -25387 | AL99: -28405 | AM99: -27545 | AN99: -30667 | AO99: -31322 | AP99: -33864 | AQ99: -29477.52 | AR99: -34028 | AS99: -37435 | AT99: -44477.509 | AU99: -37620.853 | AV99: -40432.875 | AW99: -37366 | AX99: -44218 | AY99: -41368 | AZ99: -40828 | BA99: -40858 | BB99: -54845 | BC99: -48785 | BD99: -56839 | BE99: -58469 | BF99: -69772 | BG99: -62226 | BH99: -72174 | BI99: -69896 | BJ99: -78766 | BK99: -65655 | BL99: -76757 | BM99: -81478 | BN99: -92209 | BO99: -87571 | BP99: -74857 | BQ99: -91593 | BR99: -103393 | BS99: -91006 | BT99: -98211 | BU99: -101114 | BV99: -114112 | BW99: -113611 | BX99: -129208 | BY99: -111354 | BZ99: -155622 | CA99: -131754 | CB99: -145323 | CC99: -139401 | CD99: -169393 | CE99: -150799 | CF99: -137174 | CG99: -143163 | CH99: -167749 | CI99: -135328 | CJ99: -144714 | CK99: -146804 | CL99: =+Cartao!CL124*1000 -> -171654.78 | CM99: =+Cartao!CM124*1000 -> -138657.65 | CN99: =+Cartao!CN124*1000 -> -148231.9 | CO99: =+Cartao!CO124*1000 -> -150305.16 | CP99: =+Cartao!CP124*1000 -> -175087.88 | CT99: -171654.78 | CW99: -11478 | CX99: -16100 | CY99: -29073 | CZ99: -38085 | DA99: -38501 | DB99: -52346 | DC99: -86542 | DD99: -107774 | DE99: -123398 | DF99: =+SUM(AQ99:AT99) -> -145418.03 | DG99: =+SUM(AU99:AX99) -> -159637.73 | DH99: =+SUM(AY99:BB99) -> -177899 | DI99: =+SUM(BC99:BF99) -> -233865 | DJ99: =+SUM(BG99:BJ99) -> -283062 | DK99: =+SUM(BK99:BN99) -> -316099 | DL99: =+SUM(BO99:BR99) -> -357414 | DM99: =+SUM(BS99:BV99) -> -404443 | DN99: =+SUM(BW99:BZ99) -> -509795 | DO99: =+SUM(CA99:CD99) -> -585871 | DP99: =+SUM(CE99:CH99) -> -598885 | DQ99: =+SUM(CI99:CL99) -> -598500.78 | DR99: =+SUM(CM99:CP99) -> -612282.58 | DS99: =+Cartao!DR124*1000 -> -630651.06 | DT99: =+Cartao!DS124*1000 -> -649570.59 | DU99: =+Cartao!DT124*1000 -> -669057.7 | DV99: =+Cartao!DU124*1000 -> -689129.44 | DY99: -618285.35 | DZ99: -636833.91
A100: % Rec Fin | G100: =+G99/G34 -> -0.19512795 | H100: =+H99/H34 -> -0.16682698 | I100: =+I99/I34 -> -0.18439285 | J100: =+J99/J34 -> -0.16116391 | K100: =+K99/K34 -> -0.18467982 | L100: =+L99/L34 -> -0.18375016 | M100: =+M99/M34 -> -0.16105696 | N100: =+N99/N34 -> -0.1570761 | ... CP100: =+CP99/CP34 -> -0.3439582 | CT100: -0.37659973 | DI100: =+DI99/DI34 -> -0.27701509 | DJ100: =+DJ99/DJ34 -> -0.30077526 | DK100: =+DK99/DK34 -> -0.28381657 | DL100: =+DL99/DL34 -> -0.4077234 | DM100: =+DM99/DM34 -> -0.39814054 | DN100: =+DN99/DN34 -> -0.30070334 | DO100: =+DO99/DO34 -> -0.30176064 | DP100: =+DP99/DP34 -> -0.33942392 | ... DV100: =+DV99/DV34 -> -0.31498445 | DY100: -0.32581856 | DZ100: -0.33448297
A102: Rem dos Adm - mgnt compensation | G102: -250 | H102: -777 | I102: -726 | J102: -1363 | K102: -856 | L102: -884 | M102: -914 | N102: -1677 | O102: -1176 | P102: -1470 | Q102: -959 | R102: -1823 | S102: -1023 | T102: -1137 | U102: -1157 | V102: -1215 | W102: -1335 | X102: -1334 | Y102: -1252 | Z102: -2105 | AA102: -1801 | AB102: -1908 | AC102: -1441 | AD102: -1961 | AE102: -1413 | AF102: -1607 | AG102: -1528 | AH102: -1565 | AI102: -1653 | AJ102: -1752 | AK102: -1764 | AL102: -1762 | AM102: -1873 | AN102: -1887 | AO102: -1916 | AP102: -1827 | AQ102: -2033 | AR102: -4019 | AS102: -2102 | AT102: =-11858-AS102-AR102-AQ102 -> -3704 | AU102: -2294.39 | AV102: -2673.2147 | AW102: -2285 | AX102: -2719 | AY102: -2065 | AZ102: -2526 | BA102: -2598 | BB102: -2608 | BC102: -2786 | BD102: -3483 | BE102: -2962 | BF102: -2985 | BG102: -3050 | BH102: -3091 | BI102: -3077 | BJ102: -2901 | CW102: -3116 | CX102: -4331 | CY102: -5428 | CZ102: -4532 | DA102: -6026 | DB102: -7111 | DC102: -6113 | DD102: -6931 | DE102: -7503 | DF102: =+SUM(AQ102:AT102) -> -11858 | DG102: =+SUM(AU102:AX102) -> -9971.6047 | DH102: =+SUM(AY102:BB102) -> -9797 | DI102: =+SUM(BC102:BF102) -> -12216 | DJ102: =+SUM(BG102:BJ102) -> -12119
A103: % rec líq | G103: -0.0011893209 | H103: -0.0026269347 | I103: -0.0026704234 | J103: -0.003212539 | K103: -0.0032089731 | L103: -0.0023210629 | M103: -0.0026356236 | N103: -0.0031238416 | O103: -0.0033836371 | P103: -0.0029946707 | Q103: -0.0021598515 | R103: -0.0028111025 | S103: -0.0023691688 | T103: -0.0020076031 | U103: -0.0022625496 | V103: -0.0018040277 | W103: -0.0031851389 | X103: -0.002174714 | Y103: -0.0022668388 | Z103: -0.0027029838 | AA103: -0.0035614353 | AB103: -0.002717879 | AC103: -0.002238019 | AD103: -0.0021794895 | AE103: -0.0023598495 | AF103: -0.0019212859 | AG103: -0.0020595157 | AH103: -0.0014744205 | AI103: -0.0023305455 | AJ103: -0.0018336833 | AK103: -0.0019490464 | AL103: -0.0013630175 | AM103: -0.0022461993 | AN103: -0.0017795138 | AO103: -0.0018757924 | AP103: -0.001255936 | AQ103: =+AQ102/AQ$26 -> -0.0021659596 | AR103: =+AR102/AR$26 -> -0.0032018088 | AS103: =+AS102/AS$26 -> -0.0017461329 | AT103: =+AT102/AT$26 -> -0.0020369567 | AU103: =+AU102/AU$26 -> -0.0019544238 | AV103: =+AV102/AV$26 -> -0.0017399199 | AW103: =+AW102/AW$26 -> -0.0016084696 | AX103: =+AX102/AX$26 -> -0.0013498854 | ... BJ103: =+BJ102/BJ$26 -> -0.001023327 | CZ103: -0.0020760355 | DA103: -0.0025494706 | DB103: -0.0025845607 | DC103: -0.0018875778 | DD103: -0.0017944299 | DE103: -0.0017167836 | DF103: =+DF102/DF$26 -> -0.0022733704 | DG103: =+DG102/DG$26 -> -0.0016226661 | DH103: =+DH102/DH$26 -> -0.0015185427 | DI103: =+DI102/DI$26 -> -0.001640986 | DJ103: =+DJ102/DJ$26 -> -0.0014381939
A105: Tributárias | G105: -3702 | H105: -3266 | I105: -4226 | J105: -4162 | K105: -2495 | L105: -2353 | M105: -3145 | N105: -2430 | O105: -2631 | P105: -3184 | Q105: -3039 | R105: -411 | S105: -3238 | T105: -3746 | U105: -3382 | V105: -2583 | W105: -3388 | X105: -4248 | Y105: -3643 | Z105: -2391 | AA105: -5158 | AB105: -6429 | AC105: -5611 | AD105: -6362 | AE105: -6128 | AF105: -5092 | AG105: -6701 | AH105: -7195 | AI105: -7654 | AJ105: -8333 | AK105: -8559 | AL105: -8032 | AM105: -8299 | AN105: -8061 | AO105: -7907 | AP105: -5106 | AQ105: -6601.49 | AR105: -8227 | AS105: -8537 | AT105: -7094.446 | AU105: -9380 | AV105: -10230.751 | AW105: -11128 | AX105: -9083 | AY105: -10504 | AZ105: -11761 | BA105: -11953 | BB105: -8860 | CW105: -15356 | CX105: -10423 | CY105: -9265 | CZ105: -12949 | DA105: -13670 | DB105: -23560 | DC105: -25116 | DD105: -32578 | DE105: -29373 | DF105: =+SUM(AQ105:AT105) -> -30459.936 | DG105: =+SUM(AU105:AX105) -> -39821.751 | DH105: =+SUM(AY105:BB105) -> -43078
A106: % rec líq | G106: -0.017611463 | H106: -0.011041916 | I106: -0.015544365 | J106: -0.0098096753 | K106: -0.009353257 | L106: -0.0061781232 | M106: -0.0090689674 | N106: -0.0045264968 | O106: -0.0075700249 | P106: -0.006486416 | Q106: -0.0068444096 | R106: -0.00063377024 | S106: -0.0074988942 | T106: -0.0066143195 | U106: -0.0066136066 | V106: -0.0038352292 | W106: -0.0080833337 | X106: -0.0069251761 | Y106: -0.0065959215 | Z106: -0.0030702301 | AA106: -0.010199824 | AB106: -0.0091578848 | AC106: -0.0087144515 | AD106: -0.0070708373 | AE106: -0.010234365 | AF106: -0.0060878579 | AG106: -0.0090319468 | AH106: -0.0067785656 | AI106: -0.010791286 | AJ106: -0.0087215083 | AK106: -0.0094568525 | AL106: -0.0062132558 | AM106: -0.0099525936 | AN106: -0.007601834 | AO106: -0.0077410702 | AP106: -0.0035100214 | AQ106: =+AQ105/AQ$26 -> -0.007033232 | AR106: =+AR105/AR$26 -> -0.0065541878 | AS106: =+AS105/AS$26 -> -0.0070916919 | AT106: =+AT105/AT$26 -> -0.0039014793 | AU106: =+AU105/AU$26 -> -0.0079901392 | AV106: =+AV105/AV$26 -> -0.0066589068 | AW106: =+AW105/AW$26 -> -0.0078332823 | AX106: =+AX105/AX$26 -> -0.0045093819 | ... BB106: =+BB105/BB$26 -> -0.0041974567 | CZ106: -0.0059317263 | DA106: -0.005783482 | DB106: -0.0085631064 | DC106: -0.0077553418 | DD106: -0.0084344162 | DE106: -0.0067209228 | DF106: =+DF105/DF$26 -> -0.0058396624 | DG106: =+DG105/DG$26 -> -0.0064801413 | DH106: =+DH105/DH$26 -> -0.0066771241
A108: Participação empregados - Employee profit sharing | G108: 14 | H108: -141 | I108: -1 | J108: -8208 | K108: -1011 | L108: -58 | M108: -12 | N108: -12983 | O108: -1401 | P108: -3304 | Q108: -3364 | R108: -5033 | S108: -2049 | T108: -355 | U108: -1486 | V108: 2552 | W108: -1413 | X108: -3681 | Y108: -2876 | Z108: -11121 | AA108: -2708 | AB108: -5611 | AC108: -5325 | AD108: -8228 | AE108: -2256 | AF108: -3413 | AG108: -46 | AH108: 766 | AI108: -2729 | AJ108: -6298 | AK108: -6416 | AL108: -12103 | AM108: -3216 | AN108: -8079 | AO108: -64 | AP108: -22675 | AQ108: -4374.54 | AR108: -17383 | AS108: -10089 | AT108: -31056.179 | AU108: -6793.0968 | AV108: -16521.555 | AW108: -8931 | AX108: -32040 | AY108: -4304 | AZ108: -9920 | BA108: -3100 | BB108: -29931 | BC108: -9722 | BD108: -21190 | BE108: -10657 | BF108: -36077 | BG108: -8508 | BH108: -5846 | BI108: -8761 | BJ108: -36721 | BK108: -12961 | BL108: -18677 | BM108: -14281 | BN108: -50833 | BO108: -28 | BP108: 1471 | BQ108: -49 | BR108: -23920 | BS108: 0 | BT108: -27322 | BU108: -42254 | BV108: -147757 | BW108: -16977 | BX108: -40253 | BY108: -470 | BZ108: 44056 | CA108: -1958 | CB108: 567 | CC108: -90 | CD108: -24211 | CE108: -16627 | CF108: -19535 | CG108: -26230 | CH108: =-150702-CG108-CF108-CE108 -> -88310 | CI108: -22646 | CJ108: -45614 | CK108: -32867 | CL108: =+CL109*CL$26 -> -62761.626 | CM108: =+CM109*CM$26 -> -23874.089 | CN108: =+CN109*CN$26 -> -47676.97 | CO108: =+CO109*CO$26 -> -35424.04 | CP108: =+CP109*CP$26 -> -68252.364 | CT108: -62761.626 | CU108: =+CK108/CT108-1 -> -0.47632013 | CW108: -8336 | CX108: -14064 | CY108: -13102 | CZ108: -1338 | DA108: -19091 | DB108: -21872 | DC108: -4949 | DD108: -27546 | DE108: -34034 | DF108: =+SUM(AQ108:AT108) -> -62902.719 | DG108: =+SUM(AU108:AX108) -> -64285.652 | DH108: =+SUM(AY108:BB108) -> -47255 | DI108: =+SUM(BC108:BF108) -> -77646 | DJ108: =+SUM(BG108:BJ108) -> -59836 | DK108: =+SUM(BK108:BN108) -> -96752 | DL108: =+SUM(BO108:BR108) -> -22526 | DM108: =+SUM(BS108:BV108) -> -217333 | DN108: =+SUM(BW108:BZ108) -> -13644 | DO108: =+SUM(CA108:CD108) -> -25692 | DP108: =+SUM(CE108:CH108) -> -150702 | DQ108: =+SUM(CI108:CL108) -> -163888.63 | DR108: =+SUM(CM108:CP108) -> -175227.46 | DS108: =+DS109*DS$26 -> -189870.59 | DT108: =+DT109*DT$26 -> -202828.14 | DU108: =+DU109*DU$26 -> -216670.29 | DV108: =+DV109*DV$26 -> -231445.92 | DY108: -178603.93 | DZ108: -192758.67
A109: % rec líq | G109: 6.6601968e-05 | H109: -0.00047670244 | I109: -3.6782692e-06 | J109: -0.019345943 | K109: -0.0037900372 | L109: -0.00015228693 | M109: -3.4603373e-05 | N109: -0.024184159 | O109: -0.0040310167 | P109: -0.0067308789 | Q109: -0.0075763718 | R109: -0.0077609869 | S109: -0.0047452854 | T109: -0.00062682419 | U109: -0.0029059194 | V109: 0.0037892005 | W109: -0.0033712369 | X109: -0.0060008412 | Y109: -0.0052072112 | Z109: -0.014280229 | AA109: -0.0053550065 | AB109: -0.0079926726 | AC109: -0.0082702645 | AD109: -0.0091447421 | AE109: -0.0037677427 | AF109: -0.0040804908 | AG109: -6.2001127e-05 | AH109: 0.00072166522 | AI109: -0.0038475854 | AJ109: -0.0065916308 | AK109: -0.0070890484 | AL109: -0.0093624296 | AM109: -0.0038567949 | AN109: -0.0076188087 | AO109: -6.2656948e-05 | AP109: -0.015587492 | AQ109: =+AQ108/AQ$26 -> -0.0046606379 | AR109: =+AR108/AR$26 -> -0.01384848 | AS109: =+AS108/AS$26 -> -0.0083809394 | AT109: =+AT108/AT$26 -> -0.017078858 | AU109: =+AU108/AU$26 -> -0.0057865447 | AV109: =+AV108/AV$26 -> -0.010753414 | AW109: =+AW108/AW$26 -> -0.0062867581 | AX109: =+AX108/AX$26 -> -0.015906704 | ... CK109: =+CK108/CK$26 -> -0.0092233081 | CL109: -0.013 | CM109: =+CI109 -> -0.0069517948 | CN109: =+CJ109 -> -0.010944998 | CO109: =+CK109 -> -0.0092233081 | CP109: =+CL109 -> -0.013 | CT109: -0.013 | CZ109: -0.00061291604 | DA109: -0.0080769901 | DB109: -0.0079495867 | DC109: -0.0015281568 | DD109: -0.0071316357 | DE109: -0.00778742 | DF109: =+DF108/DF$26 -> -0.012059469 | DG109: =+DG108/DG$26 -> -0.01046112 | DH109: =+DH108/DH$26 -> -0.0073245624 | DI109: =+DI108/DI$26 -> -0.010430255 | DJ109: =+DJ108/DJ$26 -> -0.007100897 | DK109: =+DK108/DK$26 -> -0.010090487 | DL109: =+DL108/DL$26 -> -0.0029886509 | DM109: =+DM108/DM$26 -> -0.020558279 | ... DR109: =+DR108/DR$26 -> -0.010380051 | DS109: =+DR109 -> -0.010380051 | DT109: =+DS109 -> -0.010380051 | DU109: =+DT109 -> -0.010380051 | DV109: =+DU109 -> -0.010380051 | DY109: -0.010398888 | DZ109: -0.010398888
A111: Outras | G111: 296 | H111: 516 | I111: 522 | J111: 919 | K111: 1674 | L111: 530 | M111: 619 | N111: 1580 | O111: -1143 | P111: -456 | Q111: 7900 | R111: -891 | S111: 587 | T111: 240 | U111: -2205 | V111: -583 | W111: 1132 | X111: 683 | Y111: -66 | Z111: -377 | AA111: 631 | AB111: 289 | AC111: 7254 | AD111: 1173 | AE111: 839 | AF111: -600 | AG111: 3164 | AH111: 4518 | AI111: -1548 | AJ111: 2306 | AK111: 590 | AL111: 8950 | AM111: 2669 | AN111: -187 | AO111: 681 | AP111: 27813 | AQ111: 2191.84 | AR111: 1834 | AS111: 3811 | AT111: 3239.1 | AU111: 6501.8795 | AV111: 13019.435 | AW111: 3843 | AX111: 3930 | AY111: 9048 | AZ111: 13111 | BA111: 14747 | BB111: 34463 | BC111: 482.76789 | BD111: 3163.9909 | BE111: 4518.4293 | BF111: -1379.5645 | BG111: -749 | BH111: 8586 | BI111: 24010 | BJ111: -2024 | BK111: 28122 | BL111: 9834 | BM111: 2308 | BN111: 21305 | BO111: 3918 | BP111: 742921 | BQ111: 3606 | BR111: -1320 | BS111: 462 | BT111: 47740 | BU111: 4961 | BV111: -12133 | BW111: 14638 | BX111: 5175 | BY111: 40013 | BZ111: 58848 | CA111: =3224+36044 -> 39268 | CB111: 17708 | CC111: 21008 | CD111: 120769 | CE111: 76820 | CF111: =42742-CF120 -> 44414 | CG111: 31266 | CH111: 25685 | CI111: 19786 | CJ111: 9378 | CK111: 26638 | CL111: =+CL112*CL$26 -> 24139.087 | CM111: =+CM112*CM$26 -> 17171.169 | CN111: =+CN112*CN$26 -> 21780.256 | CO111: =+CO112*CO$26 -> 19203.544 | CP111: =+CP112*CP$26 -> 26250.909 | CT111: 24139.087 | CW111: 2253 | CX111: 4403 | CY111: 5410 | CZ111: -1961 | DA111: 1372 | DB111: 9347 | DC111: 7921 | DD111: 10298 | DE111: 30976 | DF111: =+SUM(AQ111:AT111) -> 11075.94 | DG111: =+SUM(AU111:AX111) -> 27294.315 | DH111: =+SUM(AY111:BB111) -> 71369 | DI111: =+SUM(BC111:BF111) -> 6785.6235 | DJ111: =+SUM(BG111:BJ111) -> 29823 | DK111: =+SUM(BK111:BN111) -> 61569 | DL111: =+SUM(BO111:BR111) -> 749125 | DM111: =+SUM(BS111:BV111) -> 41030 | DN111: =+SUM(BW111:BZ111) -> 118674 | DO111: =+SUM(CA111:CD111) -> 198753 | DP111: =+SUM(CE111:CH111) -> 178185 | DQ111: =+SUM(CI111:CL111) -> 79941.087 | DR111: =+SUM(CM111:CP111) -> 84405.879 | DS111: =+DS112*DS$26 -> 91459.374 | DT111: =+DT112*DT$26 -> 97700.936 | DU111: =+DU112*DU$26 -> 104368.61 | DV111: =+DV112*DV$26 -> 111485.93 | DY111: 86796.112 | DZ111: 93674.884
A112: % rec líq | G112: 0.0014081559 | H112: 0.0017445281 | I112: 0.0019200565 | J112: 0.002166048 | K112: 0.0062754918 | L112: 0.0013915875 | M112: 0.0017849573 | N112: 0.0029431543 | O112: -0.0032886881 | P112: -0.00092895908 | Q112: 0.017792312 | R112: -0.0013739399 | S112: 0.0013594351 | T112: 0.00042376847 | U112: -0.0043119463 | V112: -0.00086563632 | W112: 0.0027008069 | X112: 0.0011134405 | Y112: -0.00011949789 | Z112: -0.00048409734 | AA112: 0.0012477877 | AB112: 0.00041167036 | AC112: 0.011266197 | AD112: 0.0013036926 | AE112: 0.0014012128 | AF112: -0.00071734382 | AG112: 0.0042645992 | AH112: 0.0042565058 | AI112: -0.0021825072 | AJ112: 0.0024135123 | AK112: 0.00065189192 | AL112: 0.0069233863 | AM112: 0.003200804 | AN112: -0.00017634822 | AO112: 0.00066670909 | AP112: 0.019119511 | AQ112: =+AQ111/AQ$26 -> 0.0023351878 | AR112: =+AR111/AR$26 -> 0.0014610891 | AS112: =+AS111/AS$26 -> 0.0031658004 | AT112: =+AT111/AT$26 -> 0.0017812922 | AU112: =+AU111/AU$26 -> 0.0055384779 | AV112: =+AV111/AV$26 -> 0.0084739824 | AW112: =+AW111/AW$26 -> 0.0027051855 | AX112: =+AX111/AX$26 -> 0.0019511033 | ... CK112: =+CK111/CK$26 -> 0.0074752938 | CL112: 0.005 | CM112: 0.005 | CN112: 0.005 | CO112: 0.005 | CP112: 0.005 | CT112: 0.005 | CZ112: -0.0008983022 | DA112: 0.00058046359 | DB112: 0.0033972562 | DC112: 0.0024458537 | DD112: 0.0026661433 | DE112: 0.00708771 | DF112: =+DF111/DF$26 -> 0.0021234368 | DG112: =+DG111/DG$26 -> 0.004441568 | DH112: =+DH111/DH$26 -> 0.011062251 | DI112: =+DI111/DI$26 -> 0.00091151874 | DJ112: =+DJ111/DJ$26 -> 0.0035391746 | DK112: =+DK111/DK$26 -> 0.0064211717 | DL112: =+DL111/DL$26 -> 0.099390621 | DM112: =+DM111/DM$26 -> 0.0038811694 | ... DR112: =+DR111/DR$26 -> 0.005 | DS112: =+DR112 -> 0.005 | DT112: =+DS112 -> 0.005 | DU112: =+DT112 -> 0.005 | DV112: =+DU112 -> 0.005 | DY112: 0.0050535452 | DZ112: 0.0050535452
A114: Result on Sales, Write-off of or Impairment of Fixed Assets | G114: 0 | H114: 0 | I114: 0 | J114: 0 | K114: 0 | L114: 0 | M114: 0 | N114: 0 | O114: 0 | P114: 0 | Q114: 0 | R114: -5190 | S114: -2077 | T114: -3029 | U114: -3096 | V114: -2858 | W114: -3585 | X114: -4835 | Y114: -4431 | Z114: -4392 | AA114: -3829 | AB114: -4629 | AC114: -4459 | AD114: -4468 | AE114: -4727 | AF114: -5549 | AG114: -4260 | AH114: -3538 | AI114: -4075 | AJ114: -4006 | AK114: -4001 | AL114: -4045 | AM114: -4479 | AN114: -3360 | AO114: -1687 | AP114: -3613 | AQ114: -136.77 | AR114: -61 | AS114: -98 | AT114: -1444.562 | AU114: -378.03441 | AV114: -1057 | AW114: -144 | AX114: -11178 | AY114: -153 | AZ114: -962 | BA114: -12228 | BB114: -8035 | BC114: -431 | BD114: -725 | BE114: -3411 | BF114: -16783 | BG114: -523 | BH114: -1220.0351 | BI114: -1268.5683 | BJ114: -3119 | BK114: -500 | BL114: -289 | BM114: -1926 | BN114: -21053 | BO114: 168 | BP114: -9905 | BQ114: -10240 | BR114: -556 | BS114: 67 | BT114: -228 | BU114: 84 | BV114: -8917 | BW114: 7 | BX114: -9510 | BY114: -844 | BZ114: -27358 | CA114: -16040 | CB114: -3076 | CC114: 27 | CD114: -121753 | CE114: 78 | CF114: -8600 | CG114: -1311 | CH114: -133504 | CI114: -3563 | CJ114: -1328 | CK114: -3034 | CL114: =+CL115*CL$26 -> -120695.43 | CM114: =+CM115*CM$26 -> -3756.221 | CN114: =+CN115*CN$26 -> -1388.0611 | CO114: =+CO115*CO$26 -> -3270.044 | CP114: =+CP115*CP$26 -> -131254.55 | CT114: -120695.43 | CW114: 0 | CX114: 0 | CY114: -5190 | CZ114: -11060 | DA114: -17243 | DB114: -17385 | DC114: -18074 | DD114: -16127 | DE114: -13139 | DF114: =+SUM(AQ114:AT114) -> -1740.332 | DG114: =+SUM(AU114:AX114) -> -12757.034 | DH114: =+SUM(AY114:BB114) -> -21378 | DI114: =+SUM(BC114:BF114) -> -21350 | DJ114: =+SUM(BG114:BJ114) -> -6130.6034 | DK114: =+SUM(BK114:BN114) -> -23768 | DL114: =+SUM(BO114:BR114) -> -20533 | DM114: =+SUM(BS114:BV114) -> -8994 | DN114: =+SUM(BW114:BZ114) -> -37705 | DO114: =+SUM(CA114:CD114) -> -140842 | DP114: =+SUM(CE114:CH114) -> -143337 | DQ114: =+SUM(CI114:CL114) -> -128620.43 | DR114: =+SUM(CM114:CP114) -> -139668.87 | DS114: =+DS115*DS$26 -> -151340.5 | DT114: =+DT115*DT$26 -> -161668.59 | DU114: =+DU115*DU$26 -> -172701.78 | DV114: =+DV115*DV$26 -> -184479.02 | DY114: -89632.342 | DZ114: -96735.891
A115: % rec líq | R115: -0.008003084 | S115: -0.0048101307 | T115: -0.0053483112 | U115: -0.0060543247 | V115: -0.0042435482 | W115: -0.0085533505 | X115: -0.0078821155 | Y115: -0.0080226539 | Z115: -0.0056396698 | AA115: -0.0075717577 | AB115: -0.006593848 | AC115: -0.0069252787 | AD115: -0.0049658128 | AE115: -0.0078945566 | AF115: -0.0066342348 | AG115: -0.0057418435 | AH115: -0.0033332266 | AI115: -0.0057452952 | AJ115: -0.0041927712 | AK115: -0.0044207112 | AL115: -0.0031290612 | AM115: -0.0053714504 | AN115: -0.0031686096 | AO115: -0.001651598 | AP115: -0.0024836873 | AQ115: =+AQ114/AQ$26 -> -0.00014571485 | AR115: =+AR114/AR$26 -> -4.8596749e-05 | AS115: =+AS114/AS$26 -> -8.1408669e-05 | AT115: =+AT114/AT$26 -> -0.00079441421 | AU115: =+AU114/AU$26 -> -0.00032202 | AV115: =+AV114/AV$26 -> -0.00068797143 | AW115: =+AW114/AW$26 -> -0.00010136526 | AX115: =+AX114/AX$26 -> -0.0055494739 | ... CK115: =+CK114/CK$26 -> -0.00085141682 | CL115: -0.025 | CM115: =+CI115 -> -0.0010937581 | CN115: =+CJ115 -> -0.00031865122 | CO115: =+CK115 -> -0.00085141682 | CP115: =+CL115 -> -0.025 | CT115: -0.025 | CZ115: -0.0050664061 | DA115: -0.0072951412 | DB115: -0.0063187438 | DC115: -0.0055809065 | DD115: -0.0041752664 | DE115: -0.0030063734 | DF115: =+DF114/DF$26 -> -0.00033364979 | DG115: =+DG114/DG$26 -> -0.0020759355 | DH115: =+DH114/DH$26 -> -0.0033136069 | DI115: =+DI114/DI$26 -> -0.0028679642 | DJ115: =+DJ114/DJ$26 -> -0.00072753499 | DK115: =+DK114/DK$26 -> -0.002478819 | DL115: =+DL114/DL$26 -> -0.0027242284 | DM115: =+DM114/DM$26 -> -0.00085077352 | ... DR115: =+DR114/DR$26 -> -0.0082736461 | DS115: =+DR115 -> -0.0082736461 | DT115: =+DS115 -> -0.0082736461 | DU115: =+DT115 -> -0.0082736461 | DV115: =+DU115 -> -0.0082736461 | DY115: -0.0052186795 | DZ115: -0.0052186795
A117: Stock Options | G117: 0 | H117: 0 | I117: 0 | J117: 0 | K117: 0 | L117: 0 | M117: 0 | N117: 0 | O117: 0 | P117: 0 | Q117: 0 | R117: -5190 | S117: -2077 | T117: -3029 | U117: -3096 | V117: -2858 | W117: -3585 | X117: -4835 | Y117: -4431 | Z117: -4392 | AA117: -3829 | AB117: -4629 | AC117: -4459 | AD117: -4468 | AE117: -4727 | AF117: -5549 | AG117: -4260 | AH117: -3538 | AI117: -4075 | AJ117: -4006 | AK117: -4001 | AL117: -4045 | AM117: -4479 | AN117: -3360 | AO117: -1687 | AP117: -3613 | AQ117: -2883 | AR117: -7003 | AS117: -7319 | AT117: =-24953-AS117-AR117-AQ117 -> -7748 | AU117: -6467.0165 | AV117: -7543.4621 | AW117: -5498 | AX117: -6922 | AY117: -6736 | AZ117: -5739 | BA117: -5786 | BB117: -5783 | BC117: -6861 | BD117: -7591 | BE117: -7129 | BF117: -6057 | BG117: -5084 | BH117: -4716 | BI117: -5920 | BJ117: -4777 | BK117: -4805 | BL117: -5160 | BM117: -5247 | BN117: -5863 | BO117: -4982 | BP117: -5392 | BQ117: -5440 | BR117: -7018 | BS117: -3734 | BT117: -4239 | BU117: -3430 | BV117: -3948 | BW117: -4381 | BX117: -6429 | BY117: -6511 | BZ117: -4478 | CA117: -5811 | CB117: -6447 | CC117: -6523 | CD117: -4677 | CE117: -5917 | CF117: -6200 | CG117: -6269 | CH117: =-31884-CG117-CF117-CE117 -> -13498 | CI117: -3642 | CJ117: -8629 | CK117: -4928 | CL117: =+CL118*CL$26 -> -14113.67 | CM117: =+CM118*CM$26 -> -3839.5051 | CN117: =+CN118*CN$26 -> -9019.2611 | CO117: =+CO118*CO$26 -> -5311.3965 | CP117: =+CP118*CP$26 -> -15348.413 | CT117: -14113.67 | CW117: 0 | CX117: 0 | CY117: -5190 | CZ117: -11060 | DA117: -17243 | DB117: -17385 | DC117: -18074 | DD117: -16127 | DE117: -13139 | DF117: =+SUM(AQ117:AT117) -> -24953 | DG117: =+SUM(AU117:AX117) -> -26430.479 | DH117: =+SUM(AY117:BB117) -> -24044 | DI117: =+SUM(BC117:BF117) -> -27638 | DJ117: =+SUM(BG117:BJ117) -> -20497 | DK117: =+SUM(BK117:BN117) -> -21075 | DL117: =+SUM(BO117:BR117) -> -22832 | DM117: =+SUM(BS117:BV117) -> -15351 | DN117: =+SUM(BW117:BZ117) -> -21799 | DO117: =+SUM(CA117:CD117) -> -23458 | DP117: =+SUM(CE117:CH117) -> -31884 | DQ117: =+SUM(CI117:CL117) -> -31312.67 | DR117: =+SUM(CM117:CP117) -> -33518.576 | DS117: =+DS118*DS$26 -> -36319.603 | DT117: =+DT118*DT$26 -> -38798.201 | DU117: =+DU118*DU$26 -> -41446.012 | DV117: =+DV118*DV$26 -> -44272.385 | DY117: -34229.989 | DZ117: -36942.787
A118: % rec líq | R118: -0.008003084 | S118: -0.0048101307 | T118: -0.0053483112 | U118: -0.0060543247 | V118: -0.0042435482 | W118: -0.0085533505 | X118: -0.0078821155 | Y118: -0.0080226539 | Z118: -0.0056396698 | AA118: -0.0075717577 | AB118: -0.006593848 | AC118: -0.0069252787 | AD118: -0.0049658128 | AE118: -0.0078945566 | AF118: -0.0066342348 | AG118: -0.0057418435 | AH118: -0.0033332266 | AI118: -0.0057452952 | AJ118: -0.0041927712 | AK118: -0.0044207112 | AL118: -0.0031290612 | AM118: -0.0053714504 | AN118: -0.0031686096 | AO118: -0.001651598 | AP118: -0.0024836873 | AQ118: =+AQ117/AQ$26 -> -0.0030715502 | AR118: =+AR117/AR26 -> -0.0055790661 | AS118: =+AS117/AS26 -> -0.0060798985 | AT118: =+AT117/AT26 -> -0.004260891 | AU118: =+AU117/AU26 -> -0.0055087806 | AV118: =+AV117/AV26 -> -0.0049098263 | AW118: =+AW117/AW26 -> -0.0038701821 | AX118: =+AX117/AX26 -> -0.0034365234 | AY118: =+AY117/AY26 -> -0.0054001663 | ... CK118: =+CK117/CK26 -> -0.0013829209 | CL118: =+CH118 -> -0.002923406 | CM118: =+CI118 -> -0.0011180092 | CN118: =+CJ118 -> -0.0020705131 | CO118: =+CK118 -> -0.0013829209 | CP118: =+CL118 -> -0.002923406 | CT118: -0.002923406 | CZ118: -0.0050664061 | DA118: -0.0072951412 | DB118: -0.0063187438 | DC118: -0.0055809065 | DD118: -0.0041752664 | DE118: -0.0030063734 | DF118: =+DF117/DF$26 -> -0.0047838937 | DG118: =+DG117/DG$26 -> -0.0043009971 | DH118: =+DH117/DH$26 -> -0.003726839 | DI118: =+DI117/DI$26 -> -0.0037126367 | DJ118: =+DJ117/DJ$26 -> -0.0024324334 | DK118: =+DK117/DK$26 -> -0.0021979599 | DL118: =+DL117/DL$26 -> -0.0030292497 | DM118: =+DM117/DM$26 -> -0.0014521041 | ... DR118: =+DR117/DR$26 -> -0.0019855593 | DS118: =+DR118 -> -0.0019855593 | DT118: =+DS118 -> -0.0019855593 | DU118: =+DT118 -> -0.0019855593 | DV118: =+DU118 -> -0.0019855593 | DY118: -0.0019929786 | DZ118: -0.0019929786
A120: Statutory Participation | G120: 0 | H120: 0 | I120: 0 | J120: 0 | K120: 0 | L120: 0 | M120: 0 | N120: 0 | O120: 0 | P120: 0 | Q120: 0 | R120: -5190 | S120: -2077 | T120: -3029 | U120: -3096 | V120: -2858 | W120: -3585 | X120: -4835 | Y120: -4431 | Z120: -4392 | AA120: -3829 | AB120: -4629 | AC120: -4459 | AD120: -4468 | AE120: -4727 | AF120: -5549 | AG120: -4260 | AH120: -3538 | AI120: -4075 | AJ120: -4006 | AK120: -4001 | AL120: -4045 | AM120: -4479 | AN120: -3360 | AO120: -1687 | AP120: -3613 | AQ120: 0 | AR120: 0 | AS120: 0 | AT120: -11657.135 | AU120: 0 | AV120: 0 | AW120: 0 | AX120: -9943.6966 | AY120: 0 | AZ120: 0 | BA120: 0 | BB120: -6734 | BC120: 0 | BD120: 0 | BE120: 0 | BF120: -10551 | BG120: 0 | BH120: 0 | BI120: 0 | BJ120: -8294.7492 | BK120: 0 | BL120: 0 | BM120: 0 | BN120: -5855 | BO120: 0 | BP120: 517 | BQ120: 0 | BR120: -1880 | BS120: 0 | BT120: 0 | BU120: 0 | BV120: -6754 | BW120: 0 | BX120: 0 | BY120: 0 | BZ120: -2282 | CA120: 0 | CB120: 0 | CC120: 0 | CD120: 0 | CE120: 0 | CF120: -1672 | CG120: 0 | CH120: -12987 | CI120: 0 | CJ120: 0 | CK120: 0 | CL120: =+CL121*CL$26 -> 0 | CM120: =+CM121*CM$26 -> 0 | CN120: =+CN121*CN$26 -> 0 | CO120: =+CO121*CO$26 -> 0 | CP120: =+CP121*CP$26 -> 0 | CT120: 0 | CW120: 0 | CX120: 0 | CY120: -5190 | CZ120: -11060 | DA120: -17243 | DB120: -17385 | DC120: -18074 | DD120: -16127 | DE120: -13139 | DF120: =+SUM(AQ120:AT120) -> -11657.135 | DG120: =+SUM(AU120:AX120) -> -9943.6966 | DH120: =+SUM(AY120:BB120) -> -6734 | DI120: =+SUM(BC120:BF120) -> -10551 | DJ120: =+SUM(BG120:BJ120) -> -8294.7492 | DK120: =+SUM(BK120:BN120) -> -5855 | DL120: =+SUM(BO120:BR120) -> -1363 | DM120: =+SUM(BS120:BV120) -> -6754 | DN120: =+SUM(BW120:BZ120) -> -2282 | DO120: =+SUM(CA120:CD120) -> 0 | DP120: =+SUM(CE120:CH120) -> -14659 | DQ120: =+SUM(CI120:CL120) -> 0 | DR120: =+SUM(CM120:CP120) -> 0 | DS120: =+DS121*DS$26 -> 0 | DT120: =+DT121*DT$26 -> 0 | DU120: =+DU121*DU$26 -> 0 | DV120: =+DV121*DV$26 -> 0 | DY120: 0 | DZ120: 0
A121: % rec líq | R121: -0.008003084 | S121: -0.0048101307 | T121: -0.0053483112 | U121: -0.0060543247 | V121: -0.0042435482 | W121: -0.0085533505 | X121: -0.0078821155 | Y121: -0.0080226539 | Z121: -0.0056396698 | AA121: -0.0075717577 | AB121: -0.006593848 | AC121: -0.0069252787 | AD121: -0.0049658128 | AE121: -0.0078945566 | AF121: -0.0066342348 | AG121: -0.0057418435 | AH121: -0.0033332266 | AI121: -0.0057452952 | AJ121: -0.0041927712 | AK121: -0.0044207112 | AL121: -0.0031290612 | AM121: -0.0053714504 | AN121: -0.0031686096 | AO121: -0.001651598 | AP121: -0.0024836873 | AQ121: =+AQ120/AQ$26 -> 0 | AR121: =+AR120/AR$26 -> 0 | AS121: =+AS120/AS$26 -> 0 | AT121: =+AT120/AT$26 -> -0.0064106585 | AU121: =+AU120/AU$26 -> 0 | AV121: =+AV120/AV$26 -> 0 | AW121: =+AW120/AW$26 -> 0 | AX121: =+AX120/AX$26 -> -0.0049366867 | ... CK121: =+CK120/CK$26 -> 0 | CL121: 0 | CM121: 0 | CN121: 0 | CO121: 0 | CP121: 0 | CT121: 0 | CZ121: -0.0050664061 | DA121: -0.0072951412 | DB121: -0.0063187438 | DC121: -0.0055809065 | DD121: -0.0041752664 | DE121: -0.0030063734 | DF121: =+DF120/DF$26 -> -0.0022348613 | DG121: =+DG120/DG$26 -> -0.0016181247 | DH121: =+DH120/DH$26 -> -0.0010437753 | DI121: =+DI120/DI$26 -> -0.0014173251 | DJ121: =+DJ120/DJ$26 -> -0.00098435992 | DK121: =+DK120/DK$26 -> -0.00061063133 | DL121: =+DL120/DL$26 -> -0.00018083686 | DM121: =+DM120/DM$26 -> -0.00063888418 | ... DR121: =+DR120/DR$26 -> 0 | DS121: =+DR121 -> 0 | DT121: =+DS121 -> 0 | DU121: =+DT121 -> 0 | DV121: =+DU121 -> 0 | DY121: 0 | DZ121: 0
A124: EBIT | C124: -24 | D124: 18257 | E124: -652 | F124: 11635 | G124: 15125 | H124: 35607 | I124: 20761 | J124: 49252 | K124: 24311 | L124: 40403 | M124: 31927 | N124: 63471 | O124: 24797 | P124: 57174 | Q124: 45171 | R124: 73836 | S124: 36255 | T124: 57127 | U124: 40851 | V124: 65527 | W124: 17702 | X124: 71691 | Y124: 46161 | Z124: 135065 | AA124: 50071 | AB124: 129582 | AC124: 78152 | AD124: 153722 | AE124: 59059 | AF124: 151492 | AG124: 76630 | AH124: 189074 | AI124: 49228 | AJ124: 154475 | AK124: 110317 | AL124: 245230 | AM124: 46177 | AN124: 157421 | AO124: 110689 | AP124: 336147 | AQ124: =AQ49+AQ64 -> 83736.52 | AR124: =AR49+AR64 -> 189783 | AS124: =AS49+AS64 -> 141900 | AT124: =AT49+AT64 -> 387004.27 | AU124: =AU49+AU64 -> 130573.28 | AV124: =AV49+AV64 -> 253873.64 | AW124: =AW49+AW64 -> 156656 | AX124: =AX49+AX64 -> 392150.3 | ... CP124: =CP49+CP64 -> 739212.89 | CT124: 645773.99 | CU124: =+CK124/CT124-1 -> -0.56842021 | CV124: 29216 | CW124: 120745 | CX124: 160112 | CY124: 200978 | CZ124: 199760 | DA124: 270619 | DB124: 411527 | DC124: 476255 | DD124: 559250 | DE124: 650434 | DF124: =+SUM(AQ124:AT124) -> 802423.79 | DG124: =+SUM(AU124:AX124) -> 933253.22 | DH124: =+SUM(AY124:BB124) -> 975691 | DI124: =+SUM(BC124:BF124) -> 1087239 | DJ124: =+SUM(BG124:BJ124) -> 1423821.6 | DK124: =+SUM(BK124:BN124) -> 1676379 | DL124: =+SUM(BO124:BR124) -> 856879 | DM124: =+SUM(BS124:BV124) -> 814231.15 | DN124: =+SUM(BW124:BZ124) -> 1407400 | DO124: =+SUM(CA124:CD124) -> 889077 | DP124: =+SUM(CE124:CH124) -> 1259343 | DQ124: =+SUM(CI124:CL124) -> 1755384 | DR124: =+SUM(CM124:CP124) -> 1708317.5 | DS124: =DS49+DS64 -> 2345383.7 | DT124: =DT49+DT64 -> 2629668 | DU124: =DU49+DU64 -> 2914855.2 | DV124: =DV49+DV64 -> 3210034.4 | DY124: 1995400.7 | DZ124: 2544156.1
A125: margem ebit | C125: -0.00013609068 | D125: 0.076239513 | E125: -0.0031054274 | F125: 0.035469641 | G125: 0.071953911 | H125: 0.12038258 | I125: 0.076364546 | J125: 0.11608509 | K125: 0.091137086 | L125: 0.1060836 | M125: 0.092065158 | N125: 0.11823098 | O125: 0.071346981 | P125: 0.11647436 | Q125: 0.10173374 | R125: 0.11385659 | S125: 0.083963066 | T125: 0.10086926 | U125: 0.079885406 | V125: 0.097294255 | W125: 0.042234703 | X125: 0.11687213 | Y125: 0.083577912 | Z125: 0.17343397 | AA125: 0.099014228 | AB125: 0.18458501 | AC125: 0.12137797 | AD125: 0.1708493 | AE125: 0.09863436 | AF125: 0.18111975 | AG125: 0.10328579 | AH125: 0.17813072 | AI125: 0.069405986 | AJ125: 0.16167707 | AK125: 0.12188943 | AL125: 0.18970079 | AM125: 0.055377866 | AN125: 0.14845408 | AO125: 0.10836617 | AP125: 0.23107778 | AQ125: =AQ124/AQ26 -> 0.089212946 | AR125: =AR124/AR26 -> 0.15119405 | AS125: =AS124/AS26 -> 0.11787643 | AT125: =AT124/AT26 -> 0.21282693 | AU125: =AU124/AU26 -> 0.11122587 | AV125: =AV124/AV26 -> 0.16523918 | AW125: =AW124/AW26 -> 0.11027414 | AX125: =AX124/AX26 -> 0.19468848 | ... CP125: =CP124/CP26 -> 0.14079758 | CT125: 0.13376106 | CU125: =+CK125-CT125 -> -0.055549981 | CV125: 0.030631031 | CW125: 0.10044271 | CX125: 0.10456376 | CY125: 0.10408304 | CZ125: 0.091506807 | DA125: 0.11449306 | DB125: 0.14957341 | DC125: 0.14705846 | DD125: 0.14478934 | DE125: 0.14882772 | DF125: =DF124/DF26 -> 0.15383762 | DG125: =DG124/DG26 -> 0.15186707 | DH125: =DH124/DH26 -> 0.15123288 | DI125: =DI124/DI26 -> 0.14604977 | DJ125: =DJ124/DJ26 -> 0.1689687 | DK125: =DK124/DK26 -> 0.1748334 | DL125: =DL124/DL26 -> 0.11368695 | DM125: =DM124/DM26 -> 0.077020936 | ... DV125: =DV124/DV26 -> 0.1439659 | DY125: 0.11617856 | DZ125: 0.13725139
...

Sheet PROJ
B2: DRE | C2: 38077 | D2: 38168 | E2: 38260 | F2: 38351 | G2: 38441 | H2: 38533 | I2: 38625 | J2: 38717 | K2: 38806 | L2: 38898 | M2: 38990 | N2: 39082 | O2: 39172 | P2: 39263 | Q2: 39355 | R2: 39447 | S2: 39538 | T2: 39629 | U2: 39721 | V2: 39813 | W2: 39903 | X2: 39994 | Y2: 40086 | Z2: 40178 | AA2: 40268 | AB2: 40359 | AC2: 40451 | AD2: 40543 | AE2: 40633 | AF2: 40724 | AG2: 40816 | AH2: 40908 | AI2: 40999 | AJ2: 41090 | AK2: 41182 | AL2: 41274 | AM2: 41364 | AN2: 41455 | AO2: 41547 | AP2: 41639 | AQ2: 41729 | AR2: 41820 | AS2: 41912 | AT2: 42004 | AU2: 42094 | AV2: 42185 | AW2: 42277 | AX2: 42369 | AY2: 42460 | AZ2: 42551 | BA2: 42643 | BB2: 42735 | BC2: 42825 | BD2: 42916 | BE2: 43008 | BF2: 43100 | BG2: 43190 | BH2: 43281 | BI2: 43373 | BJ2: 43465 | BK2: 43555 | BL2: 43646 | BM2: 43738 | BN2: 43830 | BO2: 43921 | BP2: 44012 | BQ2: 44104 | BR2: 44196 | BS2: 44286 | BT2: 44377 | BU2: 44469 | BV2: 44561 | BW2: 44651 | BX2: 44742 | BY2: 44834 | BZ2: 44926 | CA2: 45016 | CB2: 45107 | CC2: 45199 | CD2: 45291 | CE2: 45382 | CF2: 45473 | CG2: 45565 | CH2: 45657 | CI2: =+CH2+90 -> 45747 | CJ2: =+CI2+90 -> 45837 | CK2: =+CJ2+90 -> 45927 | CL2: =+CK2+90 -> 46017 | CM2: =+CL2+90 -> 46107 | CN2: =+CM2+90 -> 46197 | CO2: =+CN2+90 -> 46287 | CP2: =+CO2+90 -> 46377 | CR2: 46017 | CX2: 39447 | CY2: 39813 | CZ2: 40178 | DA2: 40543 | DB2: 40908 | DC2: 41274 | DD2: 41639 | DE2: 2014 | DF2: =+DE2+1 -> 2015 | DG2: =+DF2+1 -> 2016 | DH2: =+DG2+1 -> 2017 | DI2: =+DH2+1 -> 2018 | DJ2: =+DI2+1 -> 2019 | DK2: =+DJ2+1 -> 2020 | DL2: =+DK2+1 -> 2021 | DM2: =+DL2+1 -> 2022 | ... DU2: =+DT2+1 -> 2030 | DX2: 2026 | DY2: 2027
B3: Receita Bruta | C3: =FAT!C3 -> 230277 | D3: =FAT!D3 -> 326148 | E3: =FAT!E3 -> 283436 | F3: =FAT!F3 -> 449394 | G3: =FAT!G3 -> 261957 | H3: =FAT!H3 -> 379185 | I3: =FAT!I3 -> 344395 | J3: =FAT!J3 -> 571973.41 | ... BB3: =FAT!BB3 -> 2755298.9 | BC3: 1840704 | BD3: 2367643 | BE3: =FAT!BE3 -> 2231419 | BF3: =FAT!BF3 -> 3163512 | BG3: =FAT!BG3 -> 2067857 | BH3: =FAT!BH3 -> 2583715.5 | BI3: =FAT!BI3 -> 2480005 | BJ3: =FAT!BJ3 -> 3873312 | BK3: =FAT!BK3 -> 2552363 | BL3: =FAT!BL3 -> 3097696 | ... CG3: =FAT!CG3 -> 4320214 | CH3: 5924561 | CI3: =FAT!CI3 -> 4128219 | CJ3: =FAT!CJ3 -> 5347166 | CK3: =FAT!CK3 -> 4549679 | CL3: =FAT!CL3 -> 6218948.9 | CM3: =FAT!CM3 -> 4380421.5 | CN3: =FAT!CN3 -> 5587574.4 | CO3: =FAT!CO3 -> 4911049.8 | CP3: =FAT!CP3 -> 6756780.6 | CR3: 6218948.9 | CT3: =+CH3/CR3-1 -> -0.047337246 | CX3: =SUM(O3:R3) -> 2558129 | CY3: =SUM(S3:V3) -> 2856237 | CZ3: =SUM(W3:Z3) -> 3080475 | DA3: =SUM(AA3:AD3) -> 3579221.9 | DB3: =SUM(AE3:AH3) -> 4213835 | DC3: =+SUM(AI3:AL3) -> 5027765.4 | DD3: =+SUM(AM3:AP3) -> 5687948.7 | DE3: =+SUM(AQ3:AT3) -> 6780869.9 | DF3: =+SUM(AU3:AX3) -> 7983713.4 | DG3: =FAT!DH3 -> 8381526.9 | DH3: =FAT!DI3 -> 9603278 | DI3: =FAT!DJ3 -> 11004890 | DJ3: =FAT!DK3 -> 12956886 | DK3: =FAT!DL3 -> 10341605 | DL3: =FAT!DM3 -> 14391001 | DM3: =FAT!DN3 -> 17823739 | DN3: =FAT!DO3 -> 18938323 | ... DU3: =FAT!DV3 -> 28682678 | DX3: 21984945 | DY3: 23787214
B4: Impostos e Ajustes | C4: =FAT!C15 -> -53924 | D4: =FAT!D15 -> -86679 | E4: =FAT!E15 -> -73481 | F4: =FAT!F15 -> -121367 | G4: =FAT!G15 -> -51753 | H4: =FAT!H15 -> -83403 | I4: =FAT!I15 -> -72528 | J4: =FAT!J15 -> -147698.41 | ... BB4: =FAT!BB15 -> -644496.92 | BC4: -425380 | BD4: =+BD6-BD3 -> -536511 | BE4: =FAT!BE15 -> -485042 | BF4: =FAT!BF15 -> -712040 | BG4: =FAT!BG15 -> -439572 | BH4: =FAT!BH15 -> -563618.54 | BI4: =FAT!BI15 -> -536717 | BJ4: =FAT!BJ15 -> -1038441 | BK4: =FAT!BK15 -> -660246 | BL4: =FAT!BL15 -> -805692 | ... CG4: =FAT!CG15 -> -929705 | CH4: -1307344 | CI4: =FAT!CI15 -> -870643 | CJ4: =FAT!CJ15 -> -1179600 | CK4: =FAT!CK15 -> -986207 | CL4: =FAT!CL15 -> -1391131.5 | CM4: =FAT!CM15 -> -946187.6 | CN4: =FAT!CN15 -> -1231523.1 | CO4: =FAT!CO15 -> -1070341.1 | CP4: =FAT!CP15 -> -1506598.7 | CR4: -1391131.5 | CX4: =SUM(O4:R4) -> -627190 | CY4: =SUM(S4:V4) -> -673230 | CZ4: =SUM(W4:Z4) -> -716847 | DA4: =SUM(AA4:AD4) -> -827883.87 | DB4: =SUM(AE4:AH4) -> -975293.05 | DC4: =+SUM(AI4:AL4) -> -1165257.4 | DD4: =+SUM(AM4:AP4) -> -1317566.7 | DE4: =+SUM(AQ4:AT4) -> -1564825.9 | DF4: =+SUM(AU4:AX4) -> -1838515.4 | DG4: =+SUM(AY4:BB4) -> -1929946.9 | DH4: =+SUM(BC4:BF4) -> -2158973 | DI4: =FAT!DJ15 -> -2578348.5 | DJ4: =FAT!DK15 -> -3368449 | DK4: =FAT!DL15 -> -2804425 | DL4: =FAT!DM15 -> -3819444.8 | DM4: =FAT!DN15 -> -4552602 | DN4: =FAT!DO15 -> -5290474 | DO4: =FAT!DP15 -> -3964675 | DP4: =FAT!DQ15 -> -4427581.5 | ... DU4: =FAT!DV15 -> -6385492.3 | DX4: -4809653.1 | DY4: -5250745.1
B6: Receita Líquida | C6: =C3+C4 -> 176353 | D6: =D3+D4 -> 239469 | E6: =E3+E4 -> 209955 | F6: =F3+F4 -> 328027 | G6: =G3+G4 -> 210204 | H6: =H3+H4 -> 295782 | I6: =I3+I4 -> 271867 | J6: =J3+J4 -> 424275 | ... BC6: =BC3+BC4 -> 1415324 | BD6: =+FAT!BD26 -> 1831132 | BE6: =BE3+BE4 -> 1746377 | BF6: =BF3+BF4 -> 2451472 | BG6: =BG3+BG4 -> 1628285 | BH6: =BH3+BH4 -> 2020097 | BI6: =BI3+BI4 -> 1943288 | BJ6: =BJ3+BJ4 -> 2834871 | BK6: =BK3+BK4 -> 1892117 | BL6: =BL3+BL4 -> 2292004 | ... CP6: =CP3+CP4 -> 5250181.9 | CR6: 4827817.4 | CT6: =+CH6/CR6-1 -> -0.043622278 | CX6: =+SUM(O6:R6) -> 1930939 | CY6: =SUM(S6:V6) -> 2183007 | CZ6: =SUM(W6:Z6) -> 2363628 | DA6: =SUM(AA6:AD6) -> 2751338 | DB6: =SUM(AE6:AH6) -> 3238542 | DC6: =+SUM(AI6:AL6) -> 3862508 | DD6: =+SUM(AM6:AP6) -> 4370382 | DE6: =+SUM(AQ6:AT6) -> 5216044 | DF6: =+SUM(AU6:AX6) -> 6145198 | DG6: =+SUM(AY6:BB6) -> 6451580 | DH6: =+SUM(BC6:BF6) -> 7444305 | DI6: =DI3+DI4 -> 8426541 | DJ6: =DJ3+DJ4 -> 9588437 | DK6: =DK3+DK4 -> 7537180 | DL6: =DL3+DL4 -> 10571556 | DM6: =DM3+DM4 -> 13271137 | DN6: =DN3+DN4 -> 13647849 | DO6: =DO3+DO4 -> 14436366 | DP6: =DP3+DP4 -> 15816431 | ... DU6: =DU3+DU4 -> 22297186 | DX6: 17175292 | DY6: 18536469
B7: CPV | C7: =FAT!C38 -> -91627 | D7: =FAT!D38 -> -129428 | E7: =FAT!E38 -> -115478 | F7: =FAT!F38 -> -181258 | G7: =FAT!G38 -> -99565 | H7: =FAT!H38 -> -142704 | I7: =FAT!I38 -> -139259 | J7: =FAT!J38 -> -212094 | ... CG7: =FAT!CG38 -> -1347782 | CH7: -1845079 | CI7: =FAT!CI38 -> -1236106 | CJ7: =FAT!CJ38 -> -1563766 | CK7: =FAT!CK38 -> -1377382 | CL7: =FAT!CL38 -> -1948240.3 | CM7: =FAT!CM38 -> -1310397.6 | CN7: =FAT!CN38 -> -1641276.2 | CO7: =FAT!CO38 -> -1487726.6 | CP7: =FAT!CP38 -> -2112547.6 | CR7: -1948240.3 | CX7: =+SUM(O7:R7) -> -906712 | CY7: =SUM(S7:V7) -> -1022536 | CZ7: =SUM(W7:Z7) -> -1084911 | DA7: =SUM(AA7:AD7) -> -1209458 | DB7: =SUM(AE7:AH7) -> -1396128 | DC7: =+SUM(AI7:AL7) -> -1634247 | DD7: =+SUM(AM7:AP7) -> -1867642 | DE7: =+SUM(AQ7:AT7) -> -2164764 | DF7: =+SUM(AU7:AX7) -> -2511352 | DG7: =+SUM(AY7:BB7) -> -2575083 | DH7: =+SUM(BC7:BF7) -> -2944913 | DI7: =FAT!DJ38 -> -3284517 | DJ7: =FAT!DK38 -> -3730521 | DK7: =FAT!DL38 -> -3223570 | DL7: =FAT!DM38 -> -4398891 | DM7: =FAT!DN38 -> -5286322 | DN7: =FAT!DO38 -> -5427247 | DO7: =FAT!DP38 -> -5694417 | DP7: =FAT!DQ38 -> -6125494.3 | ... DU7: =FAT!DV38 -> -8872728.5 | DX7: -6749709 | DY7: -7346401.1
B8: Lucro Bruto | C8: =+C6+C7 -> 84726 | D8: =+D6+D7 -> 110041 | E8: =+E6+E7 -> 94477 | F8: =+F6+F7 -> 146769 | G8: =+G6+G7 -> 110639 | H8: =+H6+H7 -> 153078 | I8: =+I6+I7 -> 132608 | J8: =+J6+J7 -> 212181 | ... CP8: =+CP6+CP7 -> 3137634.3 | CR8: 2879577.1 | CX8: =+SUM(O8:R8) -> 1024227 | CY8: =SUM(S8:V8) -> 1160471 | CZ8: =SUM(W8:Z8) -> 1278717 | DA8: =SUM(AA8:AD8) -> 1541880 | DB8: =SUM(AE8:AH8) -> 1842414 | DC8: =+SUM(AI8:AL8) -> 2228261 | DD8: =+SUM(AM8:AP8) -> 2502740 | DE8: =+SUM(AQ8:AT8) -> 3051280 | DF8: =+SUM(AU8:AX8) -> 3633846 | DG8: =+SUM(AY8:BB8) -> 3876497 | DH8: =+SUM(BC8:BF8) -> 4499392 | DI8: =+DI6+DI7 -> 5142024 | DJ8: =+DJ6+DJ7 -> 5857916 | DK8: =+DK6+DK7 -> 4313610 | DL8: =+DL6+DL7 -> 6172665.2 | DM8: =+DM6+DM7 -> 7984815 | DN8: =+DN6+DN7 -> 8220602 | DO8: =+DO6+DO7 -> 8741949 | DP8: =+DP6+DP7 -> 9690937.1 | ... DU8: =+DU6+DU7 -> 13424457 | DX8: 10425583 | DY8: 11190068
