Workbook
Name \0: [1]Ativo!#REF!
Name \a: #REF!
Name \b: #REF!
Name \c: #REF!
Name \D: #REF!
Name \DCS: #REF!
Name \e: #REF!
Name \g: #REF!
Name \i: #REF!
Name \k: #REF!
Name \l: #REF!
Name \m: #REF!
Name \N: #REF!
Name \o: #REF!
Name \p: #REF!
Name \PRINT_BALANCO: #REF!
Name \s: #REF!
Name \x: #REF!
Name \Z: #REF!
Name _: #REF!
Name _: #REF!
Name ______________________cen301: {#N/A,#N/A,FALSE,"SIM95"}
Name ______________________cen31: {#N/A,#N/A,FALSE,"SIM95"}
Name ______________________mil1: {#N/A,#N/A,FALSE,"QuadroAntigo"}
Name ______________________mil2: {#N/A,#N/A,FALSE,"Lojas por Faturamento (R$)"}
Name ____________________a4: {"SCH54",#N/A,FALSE,"upside";"SCH55",#N/A,FALSE,"upside"}
Name ____________________E21: {"Despesas Diferidas Indedutíveis de 1998",#N/A,FALSE,"Impressão"}
Name ___________________a4: {"SCH54",#N/A,FALSE,"upside";"SCH55",#N/A,FALSE,"upside"}
Name ___________________CC1: {#N/A,#N/A,FALSE,"1321";#N/A,#N/A,FALSE,"1324";#N/A,#N/A,FALSE,"1333";#N/A,#N/A,FALSE,"1371"}
Name ___________________E21: {"Despesas Diferidas Indedutíveis de 1998",#N/A,FALSE,"Impressão"}
Name ___________________Jul04: {#N/A,#N/A,FALSE,"Count";#N/A,#N/A,FALSE,"Cash-Flow";#N/A,#N/A,FALSE,"Assumptions";#N/A,#N/A,FALSE,"Right"}
Name ___________________T2: {#N/A,#N/A,FALSE,"1321";#N/A,#N/A,FALSE,"1324";#N/A,#N/A,FALSE,"1333";#N/A,#N/A,FALSE,"1371"}
Name __________________a4: {"SCH54",#N/A,FALSE,"upside";"SCH55",#N/A,FALSE,"upside"}
Name __________________E21: {"Despesas Diferidas Indedutíveis de 1998",#N/A,FALSE,"Impressão"}
Name __________________Jul04: {#N/A,#N/A,FALSE,"Count";#N/A,#N/A,FALSE,"Cash-Flow";#N/A,#N/A,FALSE,"Assumptions";#N/A,#N/A,FALSE,"Right"}
Name _________________a4: {"SCH54",#N/A,FALSE,"upside";"SCH55",#N/A,FALSE,"upside"}
Name _________________E21: {"Despesas Diferidas Indedutíveis de 1998",#N/A,FALSE,"Impressão"}
Name _________________Jul04: {#N/A,#N/A,FALSE,"Count";#N/A,#N/A,FALSE,"Cash-Flow";#N/A,#N/A,FALSE,"Assumptions";#N/A,#N/A,FALSE,"Right"}
Name ________________a4: {"SCH54",#N/A,FALSE,"upside";"SCH55",#N/A,FALSE,"upside"}
Name ________________E21: {"Despesas Diferidas Indedutíveis de 1998",#N/A,FALSE,"Impressão"}
Name ________________Jul04: {#N/A,#N/A,FALSE,"Count";#N/A,#N/A,FALSE,"Cash-Flow";#N/A,#N/A,FALSE,"Assumptions";#N/A,#N/A,FALSE,"Right"}
Name _______________a4: {"SCH54",#N/A,FALSE,"upside";"SCH55",#N/A,FALSE,"upside"}
Name _______________E21: {"Despesas Diferidas Indedutíveis de 1998",#N/A,FALSE,"Impressão"}
Name _______________Jul04: {#N/A,#N/A,FALSE,"Count";#N/A,#N/A,FALSE,"Cash-Flow";#N/A,#N/A,FALSE,"Assumptions";#N/A,#N/A,FALSE,"Right"}
Name ______________a4: {"SCH54",#N/A,FALSE,"upside";"SCH55",#N/A,FALSE,"upside"}
Name ______________E21: {"Despesas Diferidas Indedutíveis de 1998",#N/A,FALSE,"Impressão"}
Name ______________Jul04: {#N/A,#N/A,FALSE,"Count";#N/A,#N/A,FALSE,"Cash-Flow";#N/A,#N/A,FALSE,"Assumptions";#N/A,#N/A,FALSE,"Right"}
Name _____________a4: {"SCH54",#N/A,FALSE,"upside";"SCH55",#N/A,FALSE,"upside"}
Name _____________E21: {"Despesas Diferidas Indedutíveis de 1998",#N/A,FALSE,"Impressão"}
Name _____________Jul04: {#N/A,#N/A,FALSE,"Count";#N/A,#N/A,FALSE,"Cash-Flow";#N/A,#N/A,FALSE,"Assumptions";#N/A,#N/A,FALSE,"Right"}
Name _____________k1: {"'Generacion'!$A$2:$N$27"}
Name _____________m1: {"'Generacion'!$A$2:$N$27"}
Name _____________n1: {"'Generacion'!$A$2:$N$27"}
Name _____________qw1: {"'Generacion'!$A$2:$N$27"}
Name _____________qw3: {"'Generacion'!$A$2:$N$27"}
Name _____________tc2: 8.07
Name _____________y1: {"'Generacion'!$A$2:$N$27"}
Name ____________a4: {"SCH54",#N/A,FALSE,"upside";"SCH55",#N/A,FALSE,"upside"}
Name ____________as4: {"'Generacion'!$A$2:$N$27"}
Name ____________as5: {"'Generacion'!$A$2:$N$27"}

Sheet Capa | Cover

Sheet Full model
B1: Pro-forma | C1: Pro-forma | D1: Pro-forma | E1: Pro-forma | F1: Pro-forma | G1: Pro-forma | H1: Pro-forma | I1: Cosméticos | J1: Cosméticos | K1: Pro-forma
A2: ATUALIZAR / AZUL Input / PRETO Fórmula | B2: Q1-24 | C2: Q2-24 | D2: Q3-24 | E2: Q4-24 | F2: 2024 | G2: Q1-25 | H2: Q2-25 | I2: Q3-25 | J2: Q4-25 | K2: 2025
A3: Operational
A5: Identified clients | B5: =B6+B7 -> 6.837163 | C5: =C6+C7 -> 7.336918 | D5: =D6+D7 -> 7.785096 | E5: =E6+E7 -> 8.341635 | F5: =F6+F7 -> 8.229739 | G5: =G6+G7 -> 8.591559 | H5: =H6+H7 -> 8.984118 | I5: =I6+I7 -> 9.368033 | ... K5: =K6+K7 -> 9.368033
A6: Brazil | B6: 6.165783 | C6: 6.59113 | D6: 6.946996 | E6: 7.391639 | F6: 7.391639 | G6: 7.581797 | H6: 7.890822 | I6: 8.202492 | J6: 9.41921 | K6: 8.202492
A7: Hispana | B7: 0.67138 | C7: 0.745788 | D7: 0.8381 | E7: 0.949996 | F7: 0.8381 | G7: 1.009762 | H7: 1.093296 | I7: 1.165541 | J7: 1.2854767 | K7: 1.165541
A9: Consultants | B9: =B10+B11 -> 3098.9537 | C9: =C10+C11 -> 3066.277 | D9: =D10+D11 -> 3071.7944 | E9: =E10+E11 -> 3044.2959 | F9: =F10+F11 -> 3070.3303 | G9: =G10+G11 -> 2911.0785 | H9: =H10+H11 -> 2884.4734 | I9: =I10+I11 -> 2767.3503 | ... K9: =K10+K11 -> 2843.8711
A10: Brazil | B10: 1590.3965 | C10: 1569.2398 | D10: 1582.641 | E10: 1563.683 | F10: 1576.4901 | G10: 1513.0463 | H10: 1518.5376 | I10: 1513.8874 | J10: 1486.7884 | K10: 1508.0649
A11: Hispana | B11: =SUM(B12:B18) -> 1508.5572 | C11: =SUM(C12:C18) -> 1497.0372 | D11: =SUM(D12:D18) -> 1489.1534 | E11: =SUM(E12:E18) -> 1480.6129 | F11: =SUM(F12:F18) -> 1493.8402 | G11: =SUM(G12:G18) -> 1398.0322 | H11: =SUM(H12:H18) -> 1365.9358 | I11: =SUM(I12:I18) -> 1253.4629 | ... K11: =SUM(K12:K18) -> 1335.8062
A12: Mexico | B12: 563.67475 | C12: 548.93275 | D12: 545.374 | E12: 535.1905 | F12: 548.293 | G12: 515.011 | H12: 497.87725 | I12: 440.3464 | J12: 413.73675 | K12: 481.02192
A13: Argentina | B13: 466.71675 | C13: 460.7025 | D13: 456.79775 | E13: 461.9722 | F13: 461.5473 | G13: 415.519 | H13: 396.2406 | I13: 343.3415 | J13: 281.3768 | K13: 385.0337
A14: Peru | B14: 129.99825 | C14: 129.56775 | D14: 131.8956 | E14: 129.4446 | F14: 130.22655 | G14: 130.291 | H14: 131.753 | I14: 130.6506 | J14: 124.978 | K14: 130.87915
A15: Colombia | B15: 192.51075 | C15: 191.4875 | D15: 190.69 | E15: 189.81825 | F15: 191.12662 | G15: 182.843 | H15: 188.15075 | I15: 189 | J15: 189.94875 | K15: 186.66458
A16: Chile | B16: 92.64925 | C16: 104.66275 | D16: 102.574 | E16: 101.26233 | F16: 100.28708 | G16: 98.966 | H16: 98.41575 | I16: 99.594 | J16: 97.406833 | K16: 99.038231
A17: Ecuador | B17: 52.8825 | C17: 51.6602 | D17: 51.555 | E17: 52.53425 | F17: 52.157988 | G17: 45.98775 | H17: 44.8102 | I17: 43.5798 | J17: 44.31375 | K17: 44.727692
A18: Uruguay | B18: 10.125 | C18: 10.0238 | D18: 10.267 | E18: 10.39075 | F18: 10.201638 | G18: 9.4145 | H18: 8.6882 | I18: 6.9506 | J18: 0 | K18: 8.4409231
A20: Number of stores | B20: =B21+B24 -> 940 | C20: =C21+C24 -> 967 | D20: =D21+D24 -> 1001 | E20: =E21+E24 -> 1076 | F20: =F21+F24 -> 1076 | G20: =G21+G24 -> 1087 | H20: =H21+H24 -> 1103 | I20: =I21+I24 -> 1122 | ... K20: =K21+K24 -> 1183
A21: Brazil | B21: =B22+B23 -> 895 | C21: =C22+C23 -> 921 | D21: =D22+D23 -> 943 | E21: =E22+E23 -> 1008 | F21: =F22+F23 -> 1008 | G21: =G22+G23 -> 1018 | H21: =H22+H23 -> 1024 | I21: =I22+I23 -> 1032 | ... K21: =K22+K23 -> 1084
A22: Own | B22: 115 | C22: 123 | D22: 128 | E22: 145 | F22: 145 | G22: 149 | H22: 154 | I22: 160 | J22: 174 | K22: 174
A23: Franchises | B23: 780 | C23: 798 | D23: 815 | E23: 863 | F23: 863 | G23: 869 | H23: 870 | I23: 872 | J23: 910 | K23: 910
A24: Hispana | B24: =B25+B26 -> 45 | C24: =C25+C26 -> 46 | D24: =D25+D26 -> 58 | E24: =E25+E26 -> 68 | F24: =F25+F26 -> 68 | G24: =G25+G26 -> 69 | H24: =H25+H26 -> 79 | I24: =I25+I26 -> 90 | ... K24: =K25+K26 -> 99
A25: Own | B25: 45 | C25: 46 | D25: 58 | E25: 68 | F25: 68 | G25: 69 | H25: 79 | I25: 90 | J25: 97 | K25: 97
A26: Franchises | B26: 0 | C26: 0 | D26: 0 | E26: 0 | F26: 0 | G26: 0 | H26: 0 | I26: 0 | J26: 2 | K26: 2
A28: % SSS
A29: Brazil | B29: 0.15389632 | C29: 0.18062463 | D29: 0.10759047 | E29: 0.12164761 | F29: 0.13760503 | G29: 0.095930404 | H29: 0.091042327 | I29: 0.063427969 | J29: 0.013699303 | K29: 0.058380708
A30: Hispana
A32: Emana Pay
A33: # active users (k) | B33: 270.069 | C33: 300.302 | D33: 363.394 | E33: 422.113 | F33: 422.113 | G33: 445.942 | H33: 465.161 | I33: 542.932 | J33: 628.233 | K33: 628.233
A34: Total payment volume | B34: 12356.811 | C34: 14507.707 | D34: 16160.598 | E34: 17015.19 | F34: 60040.307 | G34: 14445.545 | H34: 15800.453 | I34: 15845.608 | J34: 15806.022 | K34: 61897.628
A35: Credit penetration - % sell-in | B35: 0 | C35: 0.021140456 | D35: 0.099009632 | E35: 0.19344875 | F35: 0.07839971 | G35: 0.19671756 | H35: 0.21768212 | I35: 0.31695406 | J35: 0.40550821 | K35: 0.28421549
A36: NPL - 90 days (%) | B36: 0.0043333333 | C36: 0.008 | D36: 0.011333333 | E36: 0.012333333 | F36: 0.012333333 | G36: 0.027 | H36: 0.042666667 | I36: 0.047 | J36: 0.045333333 | K36: 0.045333333
A40: Receitas CC
A42: Total | B42: 0.031 | C42: 0.1 | D42: 0.185 | E42: 0.161 | F42: 0.124 | G42: 0.12811116 | H42: 0.047385036 | I42: -0.037955652 | J42: -0.034511367 | K42: 0.018202786
A43: Brazil | D43: 0.164 | E43: 0.15072 | F43: 0.11454309 | G43: 0.045150903 | H43: 0.050251975 | I43: -0.037403851 | J43: -0.047899105 | K43: -0.0014631976
A44: Natura | B44: 0.113 | C44: 0.148 | D44: 0.194 | E44: 0.211 | F44: 0.1703601 | G44: 0.081846407 | H44: 0.10257942 | I44: -0.0018503785 | J44: -0.021895333 | K44: 0.034919951
A45: Avon | B45: -0.113 | C45: -0.008 | D45: 0.144 | E45: -0.01 | F45: -0.0018013809 | G45: -0.11966359 | H45: -0.12852205 | I45: -0.17296836 | J45: -0.11527025 | K45: -0.13438702
A46: Home & Style | B46: -0.421 | C46: -0.424 | D46: -0.298 | E46: -0.358 | F46: -0.37863856 | G46: -0.15913886 | H46: 0.028142536 | I46: -0.08955691 | J46: -0.2146747 | K46: -0.10922602
A47: Others | G47: 0.47478034 | H47: -0.83882289 | I47: -0.41247374 | J47: -0.61330955 | K47: -0.39668387
A48: Hispana | D48: 0.226 | E48: 0.18279184 | F48: 0.14110667 | G48: 0.2484378 | H48: 0.042883948 | I48: -0.038705631 | J48: -0.013622513 | K48: 0.047414442
A49: Natura | B49: 0.223 | C49: 0.274 | D49: 0.347 | E49: 0.335 | F49: 0.2856559 | G49: 0.38421973 | H49: 0.1785533 | I49: 0.12292409 | J49: 0.067355751 | K49: 0.17120669
A50: Avon | B50: -0.118 | C50: 0.02 | D50: 0.198 | E50: 0.017 | F50: -0.0092053768 | G50: 0.15621557 | H50: -0.13629189 | I50: -0.2720137 | J50: -0.14710511 | K50: -0.11580529
A51: Home & Style | B51: -0.261 | C51: -0.201 | D51: -0.135 | E51: -0.171 | F51: -0.13671531 | G51: -0.14972074 | H51: -0.25895558 | I51: -0.3585027 | J51: -0.26787059 | K51: -0.26129547
A52: Others | G52: -0.062832322 | H52: -0.0061065902 | I52: -0.062103193 | J52: 0.073531397 | K52: -0.0027637841
A55: Receitas BRL
A57: Total | B57: =B59+B74 -> 4581.8834 | C57: =C59+C74 -> 5784.2133 | D57: =D59+D74 -> 5975.5789 | E57: =E59+E74 -> 7046.2696 | F57: =F59+F74 -> 23387.945 | G57: =G59+G74 -> 5143.0461 | H57: =H59+H74 -> 5687.2174 | I57: =I59+I74 -> 5194.1 | ... K57: =K59+K74 -> 22219.311
A58: % YoY | G58: =G57/B57-1 -> 0.12247424 | H58: =H57/C57-1 -> -0.016769069 | I58: =I57/D57-1 -> -0.13077878 | J58: =J57/E57-1 -> -0.12081881 | K58: =K57/F57-1 -> -0.049967365
A59: Brazil | B59: =B62+B65+B68+B71 -> 2714.9633 | C59: =C62+C65+C68+C71 -> 3430.2998 | D59: =D62+D65+D68+D71 -> 3334.6279 | E59: =E62+E65+E68+E71 -> 3964.7209 | F59: =F62+F65+F68+F71 -> 13444.612 | G59: =G62+G65+G68+G71 -> 2837.5463 | H59: =H62+H65+H68+H71 -> 3602.6792 | I59: =I62+I65+I68+I71 -> 3209.9 | ... K59: =K62+K65+K68+K71 -> 13424.94
A60: % total | B60: =B59/B$57 -> 0.59254307 | C60: =C59/C$57 -> 0.59304518 | D60: =D59/D$57 -> 0.55804266 | E60: =E59/E$57 -> 0.56266949 | F60: =F59/F$57 -> 0.57485221 | G60: =G59/G$57 -> 0.55172484 | H60: =H59/H$57 -> 0.63346957 | I60: =I59/I$57 -> 0.61798964 | ... K60: =K59/K$57 -> 0.60420144
A61: % YoY | G61: =G59/B59-1 -> 0.045150903 | H61: =H59/C59-1 -> 0.050251975 | I61: =I59/D59-1 -> -0.037403851 | J61: =J59/E59-1 -> -0.047899105 | K61: =K59/F59-1 -> -0.0014631976
A62: Natura | B62: 2115.328 | C62: 2745.0172 | D62: 2670.4603 | E62: 3287.8047 | F62: =B62+C62+D62+E62 -> 10818.61 | G62: 2288.46 | H62: 3026.5995 | I62: 2665.519 | J62: 3215.8171 | K62: =G62+H62+I62+J62 -> 11196.396
A63: % total Brasil | B63: =B62/B$59 -> 0.77913685 | C63: =C62/C$59 -> 0.80022663 | D63: =D62/D$59 -> 0.80082708 | E63: =E62/E$59 -> 0.82926509 | F63: =F62/F$59 -> 0.80467999 | G63: =G62/G$59 -> 0.80649254 | H63: =H62/H$59 -> 0.84009688 | I63: =I62/I$59 -> 0.83040561 | ... K63: =K62/K$59 -> 0.83399968
A64: % YoY | B64: 0.113 | C64: 0.148 | D64: 0.194 | E64: 0.211 | G64: =G62/B62-1 -> 0.081846407 | H64: =H62/C62-1 -> 0.10257942 | I64: =I62/D62-1 -> -0.0018503785 | J64: =J62/E62-1 -> -0.021895333 | K64: =K62/F62-1 -> 0.034919951
A65: Avon | B65: 479.98813 | C65: 554.0293 | D65: 528.61733 | E65: 527.19819 | F65: =B65+C65+D65+E65 -> 2089.8329 | G65: 422.55103 | H65: 482.82432 | I65: 437.18325 | J65: 466.42792 | K65: =G65+H65+I65+J65 -> 1808.9865
A66: % total Brasil | B66: =B65/B$59 -> 0.1767936 | C66: =C65/C$59 -> 0.16151046 | D66: =D65/D$59 -> 0.15852363 | E66: =E65/E$59 -> 0.13297233 | F66: =F65/F$59 -> 0.15544018 | G66: =G65/G$59 -> 0.14891423 | H66: =H65/H$59 -> 0.13401813 | I66: =I65/I$59 -> 0.1361984 | ... K66: =K65/K$59 -> 0.1347482
A67: % YoY | B67: -0.113 | C67: -0.008 | D67: 0.144 | E67: -0.01 | G67: =G65/B65-1 -> -0.11966359 | H67: =H65/C65-1 -> -0.12852205 | I67: =I65/D65-1 -> -0.17296836 | J67: =J65/E65-1 -> -0.11527025 | K67: =K65/F65-1 -> -0.13438702
A68: Home & Style | B68: 78.745026 | C68: 83.16396 | D68: 85.342198 | E68: 86.98384 | F68: =B68+C68+D68+E68 -> 334.23502 | G68: 66.213633 | H68: 85.504405 | I68: 77.699214 | J68: 68.310611 | K68: =G68+H68+I68+J68 -> 297.72786
A69: % total Brasil | B69: =B68/B$59 -> 0.029004085 | C69: =C68/C$59 -> 0.024243933 | D69: =D68/D$59 -> 0.02559272 | E69: =E68/E$59 -> 0.021939461 | F69: =F68/F$59 -> 0.024860147 | G69: =G68/G$59 -> 0.02333482 | H69: =H68/H$59 -> 0.023733561 | I69: =I68/I$59 -> 0.024206117 | ... K69: =K68/K$59 -> 0.022177221
A70: % YoY | B70: -0.421 | C70: -0.424 | D70: -0.298 | E70: -0.358 | G70: =G68/B68-1 -> -0.15913886 | H70: =H68/C68-1 -> 0.028142536 | I70: =I68/D68-1 -> -0.08955691 | J70: =J68/E68-1 -> -0.2146747 | K70: =K68/F68-1 -> -0.10922602
A71: Others | B71: 40.902177 | C71: 48.089301 | D71: 50.208062 | E71: 62.734245 | F71: =B71+C71+D71+E71 -> 201.93379 | G71: 60.321727 | H71: 7.7508948 | I71: 29.498555 | J71: 24.258733 | K71: =G71+H71+I71+J71 -> 121.82991
A72: % total Brasil | B72: =B71/B$59 -> 0.015065462 | C72: =C71/C$59 -> 0.014018979 | D72: =D71/D$59 -> 0.015056571 | E72: =E71/E$59 -> 0.015823118 | F72: =F71/F$59 -> 0.015019681 | G72: =G71/G$59 -> 0.021258411 | H72: =H71/H$59 -> 0.0021514252 | I72: =I71/I$59 -> 0.0091898673 | ... K72: =K71/K$59 -> 0.0090748943
A73: % YoY | G73: =G71/B71-1 -> 0.47478034 | H73: =H71/C71-1 -> -0.83882289 | I73: =I71/D71-1 -> -0.41247374 | J73: =J71/E71-1 -> -0.61330955 | K73: =K71/F71-1 -> -0.39668387
A74: Hispana | B74: =B77+B80+B83+B86 -> 1866.9202 | C74: =C77+C80+C83+C86 -> 2353.9134 | D74: =D77+D80+D83+D86 -> 2640.951 | E74: =E77+E80+E83+E86 -> 3081.5487 | F74: =F77+F80+F83+F86 -> 9943.3333 | G74: =G77+G80+G83+G86 -> 2305.4998 | H74: =H77+H80+H83+H86 -> 2084.5382 | I74: =I77+I80+I83+I86 -> 1984.2 | ... K74: =K77+K80+K83+K86 -> 8794.3714
A75: % total | B75: =B74/B$57 -> 0.40745693 | C75: =C74/C$57 -> 0.40695482 | D75: =D74/D$57 -> 0.44195734 | E75: =E74/E$57 -> 0.43733051 | F75: =F74/F$57 -> 0.42514779 | G75: =G74/G$57 -> 0.44827516 | H75: =H74/H$57 -> 0.36653043 | I75: =I74/I$57 -> 0.38201036 | ... K75: =K74/K$57 -> 0.39579856
A76: % YoY | G76: =G74/B74-1 -> 0.23492149 | H76: =H74/C74-1 -> -0.11443718 | I76: =I74/D74-1 -> -0.24867973 | J76: =J74/E74-1 -> -0.21463732 | K76: =K74/F74-1 -> -0.11555098
A77: Natura | B77: 1113.8118 | C77: 1467.7313 | D77: 1582.0645 | E77: 2045.7931 | F77: =B77+C77+D77+E77 -> 6209.4006 | G77: 1526.8467 | H77: 1432.8497 | I77: 1388.6317 | J77: 1766.7411 | K77: =G77+H77+I77+J77 -> 6115.0692
A78: % total Hispana | B78: =B77/B$74 -> 0.59660387 | C78: =C77/C$74 -> 0.62352815 | D78: =D77/D$74 -> 0.59905106 | E78: =E77/E$74 -> 0.66388472 | F78: =F77/F$74 -> 0.62447878 | G78: =G77/G$74 -> 0.66226278 | H78: =H77/H$74 -> 0.68737032 | I78: =I77/I$74 -> 0.69984462 | ... K78: =K77/K$74 -> 0.69533898
A79: % YoY | G79: =G77/B77-1 -> 0.37083008 | H79: =H77/C77-1 -> -0.023765643 | I79: =I77/D77-1 -> -0.12226606 | J79: =J77/E77-1 -> -0.13640285 | K79: =K77/F77-1 -> -0.015191716
A80: Avon | B80: 479.04283 | C80: 595.72897 | D80: 713.64857 | E80: 715.65937 | F80: =B80+C80+D80+E80 -> 2504.0797 | G80: 554.26614 | H80: 449.22215 | I80: 414.92302 | J80: 455.92816 | K80: =G80+H80+I80+J80 -> 1874.3395
A81: % total Hispana | B81: =B80/B$74 -> 0.25659524 | C81: =C80/C$74 -> 0.25308024 | D81: =D80/D$74 -> 0.27022409 | E81: =E80/E$74 -> 0.23224016 | F81: =F80/F$74 -> 0.25183504 | G81: =G80/G$74 -> 0.2404104 | H81: =H80/H$74 -> 0.215502 | I81: =I80/I$74 -> 0.20911351 | ... K81: =K80/K$74 -> 0.21312944
A82: % YoY | G82: =G80/B80-1 -> 0.15702836 | H82: =H80/C80-1 -> -0.24592865 | I82: =I80/D80-1 -> -0.41858916 | J82: =J80/E80-1 -> -0.36292575 | K82: =K80/F80-1 -> -0.25148571
A83: Home & Style | B83: 253.18675 | C83: 264.45958 | D83: 331.39939 | E83: 289.24995 | F83: =B83+C83+D83+E83 -> 1138.2957 | G83: 210.84807 | H83: 178.75959 | I83: 169.93577 | J83: 168.94166 | K83: =G83+H83+I83+J83 -> 728.48509
A84: % total Hispana | B84: =B83/B$74 -> 0.13561735 | C84: =C83/C$74 -> 0.1123489 | D84: =D83/D$74 -> 0.12548487 | E84: =E83/E$74 -> 0.093865123 | F84: =F83/F$74 -> 0.11447828 | G84: =G83/G$74 -> 0.091454387 | H84: =H83/H$74 -> 0.085755007 | I84: =I83/I$74 -> 0.085644479 | ... K84: =K83/K$74 -> 0.08283538
A85: % YoY | G85: =G83/B83-1 -> -0.16722313 | H85: =H83/C83-1 -> -0.32405704 | I85: =I83/D83-1 -> -0.4872176 | J85: =J83/E83-1 -> -0.41593194 | K85: =K83/F83-1 -> -0.3600212
A86: Others | B86: 20.878781 | C86: 25.993595 | D86: 13.838535 | E86: 30.846299 | F86: =B86+C86+D86+E86 -> 91.55721 | G86: 13.538897 | H86: 23.706769 | I86: 10.709518 | J86: 28.522457 | K86: =G86+H86+I86+J86 -> 76.47764
A87: % total Hispana | B87: =B86/B$74 -> 0.011183543 | C87: =C86/C$74 -> 0.011042715 | D87: =D86/D$74 -> 0.0052399817 | E87: =E86/E$74 -> 0.010009999 | F87: =F86/F$74 -> 0.0092078992 | G87: =G86/G$74 -> 0.0058724345 | H87: =H86/H$74 -> 0.011372672 | I87: =I86/I$74 -> 0.0053973986 | ... K87: =K86/K$74 -> 0.0086962032
A88: % YoY | G88: =G86/B86-1 -> -0.35154755 | H88: =H86/C86-1 -> -0.087976528 | I88: =I86/D86-1 -> -0.22610895 | J88: =J86/E86-1 -> -0.075336193 | K88: =K86/F86-1 -> -0.16470106
A90: Total | B90: =B92+B104 -> 4581.8834 | C90: =C92+C104 -> 5784.2133 | D90: =D92+D104 -> 5975.5789 | E90: =E92+E104 -> 7046.2696 | F90: =F92+F104 -> 23387.945 | G90: =G92+G104 -> 5143.0461 | H90: =H92+H104 -> 5687.2174 | I90: =I92+I104 -> 5194.1 | ... K90: =K92+K104 -> 22219.311
A91: % YoY | G91: =G90/B90-1 -> 0.12247424 | H91: =H90/C90-1 -> -0.016769069 | I91: =I90/D90-1 -> -0.13077878 | J91: =J90/E90-1 -> -0.12081881 | K91: =K90/F90-1 -> -0.049967365
A92: Brazil | B92: =B95+B98+B101 -> 2714.9633 | C92: =C95+C98+C101 -> 3430.2998 | D92: =D95+D98+D101 -> 3334.6279 | E92: =E95+E98+E101 -> 3964.7209 | F92: =F95+F98+F101 -> 13444.612 | G92: =G95+G98+G101 -> 2837.5463 | H92: =H95+H98+H101 -> 3602.6792 | I92: =I95+I98+I101 -> 3209.9 | ... K92: =K95+K98+K101 -> 13424.94
A93: % total | B93: =B92/B$90 -> 0.59254307 | C93: =C92/C$90 -> 0.59304518 | D93: =D92/D$90 -> 0.55804266 | E93: =E92/E$90 -> 0.56266949 | F93: =F92/F$90 -> 0.57485221 | G93: =G92/G$90 -> 0.55172484 | H93: =H92/H$90 -> 0.63346957 | I93: =I92/I$90 -> 0.61798964 | ... K93: =K92/K$90 -> 0.60420144
A94: % YoY | G94: =G92/B92-1 -> 0.045150903 | H94: =H92/C92-1 -> 0.050251975 | I94: =I92/D92-1 -> -0.037403851 | J94: =J92/E92-1 -> -0.047899105 | K94: =K92/F92-1 -> -0.0014631976
A95: Retail | B95: 138.46313 | C95: 174.94529 | D95: 166.7314 | E95: 311.89368 | F95: =SUM(B95:E95) -> 792.0335 | G95: 170.25278 | H95: 219.76343 | I95: 186.1742 | J95: 352.15036 | K95: =SUM(G95:J95) -> 928.34077
A96: % Brazil | B96: =B95/B$92 -> 0.051 | C96: =C95/C$92 -> 0.051 | D96: =D95/D$92 -> 0.05 | E96: =E95/E$92 -> 0.078667247 | F96: =F95/F$92 -> 0.058910848 | G96: =G95/G$92 -> 0.06 | H96: =H95/H$92 -> 0.061 | I96: =I95/I$92 -> 0.058 | ... K96: =K95/K$92 -> 0.06915046
A97: % YoY | G97: =G95/B95-1 -> 0.2295893 | H97: =H95/C95-1 -> 0.25618374 | I97: =I95/D95-1 -> 0.11661153 | J97: =J95/E95-1 -> 0.1290718 | K97: =K95/F95-1 -> 0.17209786
A98: Digital | B98: 154.75291 | C98: 181.80589 | D98: 216.75082 | E98: 402.17058 | F98: =SUM(B98:E98) -> 955.48019 | G98: 195.7907 | H98: 241.3795 | I98: 272.8415 | J98: 500.67929 | K98: =SUM(G98:J98) -> 1210.691
A99: % Brazil | B99: =B98/B$92 -> 0.057 | C99: =C98/C$92 -> 0.053 | D99: =D98/D$92 -> 0.065 | E99: =E98/E$92 -> 0.1014373 | F99: =F98/F$92 -> 0.071067889 | G99: =G98/G$92 -> 0.069 | H99: =H98/H$92 -> 0.067 | I99: =I98/I$92 -> 0.085 | ... K99: =K98/K$92 -> 0.090182229
A100: % YoY | G100: =G98/B98-1 -> 0.26518267 | H100: =H98/C98-1 -> 0.32767703 | I100: =I98/D98-1 -> 0.25877958 | J100: =J98/E98-1 -> 0.24494261 | K100: =K98/F98-1 -> 0.26710214
A101: Relationship Selling | B101: 2421.7473 | C101: 3073.5486 | D101: 2951.1457 | E101: 3250.6567 | F101: =SUM(B101:E101) -> 11697.098 | G101: 2471.5029 | H101: 3141.5362 | I101: 2750.8843 | J101: 2921.9847 | K101: =SUM(G101:J101) -> 11285.908
A102: % Brazil | B102: =B101/B$92 -> 0.892 | C102: =C101/C$92 -> 0.896 | D102: =D101/D$92 -> 0.885 | E102: =E101/E$92 -> 0.81989545 | F102: =F101/F$92 -> 0.87002126 | G102: =G101/G$92 -> 0.871 | H102: =H101/H$92 -> 0.872 | I102: =I101/I$92 -> 0.857 | ... K102: =K101/K$92 -> 0.84066731
A103: % YoY | G103: =G101/B101-1 -> 0.020545333 | H103: =H101/C101-1 -> 0.022120226 | I103: =I101/D101-1 -> -0.067858871 | J103: =J101/E101-1 -> -0.10110941 | K103: =K101/F101-1 -> -0.03515318
A104: Hispana | B104: =B107+B110+B113 -> 1866.9202 | C104: =C107+C110+C113 -> 2353.9134 | D104: =D107+D110+D113 -> 2640.951 | E104: =E107+E110+E113 -> 3081.5487 | F104: =F107+F110+F113 -> 9943.3333 | G104: =G107+G110+G113 -> 2305.4998 | H104: =H107+H110+H113 -> 2084.5382 | I104: =I107+I110+I113 -> 1984.2 | ... K104: =K107+K110+K113 -> 8794.3714
A105: % total | B105: =B104/B$90 -> 0.40745693 | C105: =C104/C$90 -> 0.40695482 | D105: =D104/D$90 -> 0.44195734 | E105: =E104/E$90 -> 0.43733051 | F105: =F104/F$90 -> 0.42514779 | G105: =G104/G$90 -> 0.44827516 | H105: =H104/H$90 -> 0.36653043 | I105: =I104/I$90 -> 0.38201036 | ... K105: =K104/K$90 -> 0.39579856
A106: % YoY | G106: =G104/B104-1 -> 0.23492149 | H106: =H104/C104-1 -> -0.11443718 | I106: =I104/D104-1 -> -0.24867973 | J106: =J104/E104-1 -> -0.21463732 | K106: =K104/F104-1 -> -0.11555098
A107: Retail | B107: 28.003802 | C107: 37.662615 | D107: 42.255216 | E107: 73.451213 | F107: =SUM(B107:E107) -> 181.37285 | G107: 46.109996 | H107: 52.113456 | I107: 49.605 | J107: 94.028015 | K107: =SUM(G107:J107) -> 241.85647
A108: % Hispana | B108: =B107/B$104 -> 0.015 | C108: =C107/C$104 -> 0.016 | D108: =D107/D$104 -> 0.016 | E108: =E107/E$104 -> 0.023835811 | F108: =F107/F$104 -> 0.018240648 | G108: =G107/G$104 -> 0.02 | H108: =H107/H$104 -> 0.025 | I108: =I107/I$104 -> 0.025 | ... K108: =K107/K$104 -> 0.02750128
A109: % YoY | G109: =G107/B107-1 -> 0.64656198 | H109: =H107/C107-1 -> 0.38369191 | I109: =I107/D107-1 -> 0.17393792 | J109: =J107/E107-1 -> 0.28014245 | K109: =K107/F107-1 -> 0.33347672
A110: Digital | B110: 31.737643 | C110: 54.140009 | D110: 58.100921 | E110: 190.66725 | F110: =SUM(B110:E110) -> 334.64582 | G110: 50.771792 | H110: 66.651126 | I110: 49.605 | J110: 163.13908 | K110: =SUM(G110:J110) -> 330.16699
A111: % Hispana | B111: =B110/B$104 -> 0.017 | C111: =C110/C$104 -> 0.023 | D111: =D110/D$104 -> 0.022 | E111: =E110/E$104 -> 0.06187384 | F111: =F110/F$104 -> 0.033655296 | G111: =G110/G$104 -> 0.022022033 | H111: =H110/H$104 -> 0.031974048 | I111: =I110/I$104 -> 0.025 | ... K111: =K110/K$104 -> 0.03754299
A112: % YoY | G112: =G110/B110-1 -> 0.59973419 | H112: =H110/C110-1 -> 0.23108819 | I112: =I110/D110-1 -> -0.14622696 | J112: =J110/E110-1 -> -0.1443781 | K112: =K110/F110-1 -> -0.01338379
A113: Relationship Selling | B113: 1807.1787 | C113: 2262.1108 | D113: 2540.5948 | E113: 2817.4302 | F113: =SUM(B113:E113) -> 9427.3146 | G113: 2208.618 | H113: 1965.7736 | I113: 1884.99 | J113: 2162.9663 | K113: =SUM(G113:J113) -> 8222.3479
...

Sheet Histórico | Historic data
AB1: IFRS-16 | AC1: IFRS-16 | AD1: IFRS-16 | AE1: IFRS-16 | AF1: IFRS-16 | AG1: IFRS-16 | AH1: IFRS-16 | AI1: IFRS-16 | AJ1: IFRS-16 | AK1: IFRS-16 | AL1: IFRS-16 | AM1: IFRS-16 | AN1: IFRS-16 | AO1: IFRS-16 | AP1: IFRS-16 | AQ1: IFRS-16 | AR1: IFRS-16 | AS1: IFRS-16 | AT1: IFRS-16 | AU1: IFRS-16
A2: Unidades de negócio | B2: Business units | AV2: Latam + Holding | AW2: Latam + Holding | AX2: Latam + Holding | AY2: Latam + Holding | BA2: Latam + Holding | BB2: Latam + Holding
C3: 1Q15 | D3: 2Q15 | E3: 3Q15 | F3: 4Q15 | G3: 2015 | H3: 1Q16 | I3: 2Q16 | J3: 3Q16 | K3: 4Q16 | L3: 2016 | M3: 1Q17 | N3: 2Q17 | O3: 3Q17 | P3: 4Q17 | Q3: 2017 | R3: 1Q18 | S3: 2Q18 | T3: 3Q18 | U3: 4Q18 | V3: 2018 | W3: 1Q19 | X3: 2Q19 | Y3: 3Q19 | Z3: 4Q19 | AA3: 2019 | AB3: 1Q20 | AC3: 2Q20 | AD3: 3Q20 | AE3: 4Q20 | AF3: 2020 | AG3: 1Q21 | AH3: 2Q21 | AI3: 3Q21 | AJ3: 4Q21 | AK3: 2021 | AL3: 1Q22 | AM3: 2Q22 | AN3: 3Q22 | AO3: 4Q22 | AP3: 2022 | AQ3: 1Q23 | AR3: 2Q23 | AS3: 3Q23 | AT3: 4Q23 | AU3: 2023 | AV3: 1Q24 | AW3: 2Q24 | AX3: 3Q24 | AY3: 4Q24 | AZ3: 2024 | BA3: 1Q25 | BB3: 2Q25
A4: Demonstração de Resultados | B4: Income Statements | AV4: API e suas subsidiárias foram desconsolidadas e estão sendo apresentadas na linha de operações descontinuadas | AY4: Avon Internacional considerada a partir de Dez | AZ4: Avon Internacional considerada a partir de Dez
AV5: API and its subsidiaries were deconsolidated and are being presented under the discontinued operations line | AY5: Consolidating Avon International only in December | AZ5: Consolidating Avon International only in December
A6: Receita Bruta | B6: Gross Revenues | C6: 2205.8399 | D6: 2637.31 | E6: 2763.0574 | F6: 3200.2328 | G6: =F6+E6+D6+C6 -> 10806.44 | H6: 2320.028 | I6: 2815.4641 | J6: 2656.2 | K6: 3198.6641 | L6: 10993.142 | M6: =M8+M11+M14+M17 -> 2395.9488 | N6: =N8+N11+N14+N17 -> 2801.6006 | O6: =O8+O11+O14+O17 -> 3203.2068 | P6: =P8+P11+P14+P17 -> 5350.196 | Q6: =P6+O6+N6+M6 -> 13750.952 | R6: =R8+R11+R14+R17 -> 3708.4434 | S6: =S8+S11+S14+S17 -> 4301.1209 | T6: =T8+T11+T14+T17 -> 4392.9386 | U6: =U8+U11+U14+U17 -> 6111.9653 | V6: =V8+V11+V14+V17 -> 18561.961 | W6: =W8+W11+W14+W17 -> 3940.5753 | X6: =X8+X11+X14+X17 -> 4629.9414 | Y6: =Y8+Y11+Y14+Y17 -> 4705.0087 | ... AK6: =AK8+AK11+AK14+AK17 -> 51644.321 | AL6: =(AL8+AL11+AL14+AL17)+0.2 -> 10642.222 | AM6: =AM8+AM11+AM14+AM17 -> 11271.673 | AN6: =AN8+AN11+AN14+AN17-0.2 -> 11693.126 | AO6: =AO8+AO11+AO14+AO17 -> 13501.6 | AP6: =AP8+AP11+AP14+AP17 -> 47108.62 | AQ6: =AQ8+AQ11+AQ14+AQ17 -> 10342.4 | AR6: =AR8+AR11+AR14+AR17 -> 10944.63 | AS6: =AS8+AS11+AS14+AS17 -> 9822.436 | AT6: =AT8+AT11+AT14+AT17 -> 10478.9 | AU6: =AU8+AU11+AU14+AU17 -> 41588.366 | AV6: =AV8+AV11+AV14+AV17+AV20 -> 6228.1 | AW6: =AW8+AW11+AW14+AW17+AW20 -> 7782.1 | AX6: =AX8+AX11+AX14+AX17+AX20 -> 7901.4 | AY6: =AY8+AY11+AY14+AY17+AY20 -> 10140.3 | AZ6: =AZ8+AZ11+AZ14+AZ17+AZ20 -> 32051.4 | BA6: =BA8+BA11+BA14+BA17+BA20 -> 6819.9 | BB6: =BB8+BB11+BB14+BB17+BB20 -> 7545.9
A7: % variação anual | B7: % YoY growth | C7: - | D7: - | E7: - | F7: - | G7: - | H7: =H6/C6-1 -> 0.051766254 | I7: =I6/D6-1 -> 0.067551467 | J7: =J6/E6-1 -> -0.038673598 | K7: =K6/F6-1 -> -0.00049018569 | L7: =L6/G6-1 -> 0.017276912 | M7: =M6/H6-1 -> 0.032724096 | N7: =N6/I6-1 -> -0.0049240771 | O7: =O6/J6-1 -> 0.20593587 | ... AU7: =AU6/AP6-1 -> -0.11718141
A8: Natura & Co América Latina | B8: Natura & Co Latam | C8: 2132.7861 | D8: 2545.51 | E8: 2643.3574 | F8: 3012.7328 | G8: 10334.386 | H8: 2176.5148 | I8: 2676.3052 | J8: 2511.3 | K8: 2986.3732 | L8: 10353.279 | M8: 2236.5143 | N8: 2634.1489 | O8: 2671.6419 | P8: 3173.896 | Q8: 10716.201 | R8: 2327.5731 | S8: 2850.488 | T8: 2790.0844 | U8: 3631.6412 | V8: 11647.28 | W8: 2409.367 | X8: 3107.5158 | Y8: 3084.8295 | Z8: 3785.8129 | AA8: 12387.525 | AB8: 5593.2083 | AC8: 5420.6714 | AD8: 8275.9068 | AE8: 8294.7467 | AF8: 27584.533 | AG8: 6857.1875 | AH8: 7347.9368 | AI8: 7409.161 | AJ8: 8079.1461 | AK8: 29693.431 | AL8: 6286.722 | AM8: 7284.4 | AN8: 7700.042 | AO8: 7886.9 | AP8: 29158.064 | AQ8: 6445.3 | AR8: 7274 | AS8: 6930.214 | AT8: 6571.3 | AU8: =AT8+AS8+AR8+AQ8 -> 27220.814 | AV8: 6224.1 | AW8: 7778.8 | AX8: 7900.7 | AY8: 9369.6 | AZ8: 31272.7 | BA8: 6819.9 | BB8: 7545.9
A9: % receita bruta | B9: % gross revenues | C9: =C8/C6 -> 0.96688161 | D9: =D8/D6 -> 0.9651918 | E9: =E8/E6 -> 0.95667842 | F9: =F8/F6 -> 0.94141051 | G9: =G8/G6 -> 0.95631736 | H9: =H8/H6 -> 0.9381416 | I9: =I8/I6 -> 0.95057337 | J9: =J8/J6 -> 0.94544838 | ... BB9: =BB8/BB6 -> 1
A10: % variação anual | B10: % YoY growth | C10: - | D10: - | E10: - | F10: - | G10: - | H10: =H8/C8-1 -> 0.020503103 | I10: =I8/D8-1 -> 0.051382731 | J10: =J8/E8-1 -> -0.049958198 | K10: =K8/F8-1 -> -0.0087494076 | L10: =L8/G8-1 -> 0.0018281448 | M10: =M8/H8-1 -> 0.027566774 | N10: =N8/I8-1 -> -0.015751701 | O10: =O8/J8-1 -> 0.063848146 | ... BB10: =BB8/AW8-1 -> -0.029940351
A11: Avon International | B11: Avon International | C11: 0 | D11: 0 | E11: 0 | F11: 0 | G11: 0 | H11: 0 | I11: 0 | J11: 0 | K11: 0 | L11: 0 | M11: 0 | N11: 0 | O11: 0 | P11: 0 | Q11: 0 | R11: 0 | S11: 0 | T11: 0 | U11: 0 | V11: 0 | W11: 0 | X11: 0 | Y11: 0 | Z11: 0 | AA11: 0 | AB11: 2531.3979 | AC11: 1995.651 | AD11: 2958.2472 | AE11: 3406.1622 | AF11: 10891.458 | AG11: 2835.9077 | AH11: 2644.6511 | AI11: 2460.0331 | AJ11: 3248.39 | AK11: 11188.982 | AL11: 2207.3551 | AM11: 2099.7441 | AN11: 1965.095 | AO11: 2456.4 | AP11: 8728.5942 | AQ11: 1921 | AR11: 1795.1 | AS11: 1733.308 | AT11: 2038.6 | AU11: =AT11+AS11+AR11+AQ11 -> 7488.008 | AV11: 0 | AW11: 0 | AY11: 770.7 | AZ11: =AY11 -> 770.7 | BA11: 0 | BB11: 0
A12: % receita bruta | B12: % gross revenues | C12: - | D12: - | E12: - | F12: - | G12: - | H12: - | I12: - | J12: - | K12: - | L12: - | M12: - | N12: - | O12: - | P12: - | Q12: - | R12: - | S12: - | T12: - | U12: - | V12: - | W12: - | X12: - | Y12: - | Z12: - | AA12: - | AB12: =AB11/AB6 -> 0.26045723 | AC12: =AC11/AC6 -> 0.218924 | AD12: =AD11/AD6 -> 0.21749769 | AE12: =AE11/AE6 -> 0.22319757 | AF12: =AF11/AF6 -> 0.22834773 | AG12: =AG11/AG6 -> 0.2351663 | AH12: =AH11/AH6 -> 0.21618989 | AI12: =AI11/AI6 -> 0.19952973 | ... AZ12: =AZ11/AZ6 -> 0.024045752
A13: % variação anual | B13: % YoY growth | C13: - | D13: - | E13: - | F13: - | G13: - | H13: - | I13: - | J13: - | K13: - | L13: - | M13: - | N13: - | O13: - | P13: - | Q13: - | R13: - | S13: - | T13: - | U13: - | V13: - | W13: - | X13: - | Y13: - | Z13: - | AA13: - | AB13: - | AC13: - | AD13: - | AE13: - | AF13: - | AG13: =AG11/AB11-1 -> 0.12029313 | AH13: =AH11/AC11-1 -> 0.32520722 | AI13: =AI11/AD11-1 -> -0.1684153 | AJ13: =AJ11/AE11-1 -> -0.046319644 | AK13: =AK11/AF11-1 -> 0.027317146 | AL13: =AL11/AG11-1 -> -0.22164071 | AM13: =AM11/AH11-1 -> -0.20604117 | AN13: =AN11/AI11-1 -> -0.20119164 | ... AZ13: =AZ11/AU11-1 -> -0.89707543
A14: The Body Shop | B14: The Body Shop | C14: 0 | D14: 0 | E14: 0 | F14: 0 | G14: 0 | H14: 0 | I14: 0 | J14: 0 | K14: 0 | L14: 0 | M14: 0 | N14: 0 | O14: 354.87262 | P14: 1900.1 | Q14: =P14+O14+N14+M14 -> 2254.9726 | R14: 1158.8732 | S14: 1190.6804 | T14: 1307.7313 | U14: 2082.9565 | V14: =U14+T14+S14+R14 -> 5740.2414 | W14: 1219.8443 | X14: 1217.7669 | Y14: 1288.6482 | Z14: 2145.3599 | AA14: =Z14+Y14+X14+W14 -> 5871.6192 | AB14: 1213.3703 | AC14: 1272.5262 | AD14: 1814.9631 | AE14: 2741.682 | AF14: =AE14+AD14+AC14+AB14 -> 7042.5416 | AG14: 1711.1484 | AH14: 1612.3885 | AI14: 1841.5255 | AJ14: 2677.8065 | AK14: =AJ14+AI14+AH14+AG14 -> 7842.8689 | AL14: 1426.7368 | AM14: 1220.6572 | AN14: 1351.789 | AO14: 2181.7 | AP14: =AO14+AN14+AM14+AL14 -> 6180.883 | AQ14: 1191.1 | AR14: 1116.6 | AS14: 1158.914 | AT14: 1869 | AU14: =AT14+AS14+AR14+AQ14 -> 5335.614
A15: % receita bruta | B15: % gross revenues | C15: - | D15: - | E15: - | F15: - | G15: - | H15: - | I15: - | J15: - | K15: - | L15: - | M15: - | N15: - | O15: =O14/O6 -> 0.11078667 | P15: =P14/P6 -> 0.35514587 | Q15: =Q14/Q6 -> 0.16398665 | R15: =R14/R6 -> 0.31249587 | S15: =S14/S6 -> 0.27683026 | T15: =T14/T6 -> 0.29768941 | U15: =U14/U6 -> 0.34079979 | V15: =V14/V6 -> 0.30924758 | ... AU15: =AU14/AU6 -> 0.12829583
A16: % variação anual | B16: % YoY growth | C16: - | D16: - | E16: - | F16: - | G16: - | H16: - | I16: - | J16: - | K16: - | L16: - | M16: - | N16: - | O16: - | P16: - | Q16: - | R16: - | S16: - | T16: =T14/O14-1 -> 2.6850724 | U16: =U14/P14-1 -> 0.096235176 | V16: =V14/Q14-1 -> 1.5455925 | W16: =W14/R14-1 -> 0.052612327 | X16: =X14/S14-1 -> 0.022748753 | Y16: =Y14/T14-1 -> -0.014592531 | Z16: =Z14/U14-1 -> 0.029959063 | AA16: =AA14/V14-1 -> 0.02288716 | ... AU16: =AU14/AP14-1 -> -0.13675537
A17: Aesop | B17: Aesop | C17: 73.053874 | D17: 91.8 | E17: 119.7 | F17: 187.5 | G17: 472.05387 | H17: 143.51321 | I17: 139.1589 | J17: 144.9 | K17: 212.29092 | L17: 639.86303 | M17: 159.43454 | N17: 167.4517 | O17: 176.69238 | P17: 276.2 | Q17: 779.77861 | R17: 221.99708 | S17: 259.95249 | T17: 295.12288 | U17: 397.36756 | V17: 1174.44 | W17: 311.36407 | X17: 304.65869 | Y17: 331.53106 | Z17: 501.40634 | AA17: 1448.9602 | AB17: 381.07751 | AC17: 426.87638 | AD17: 552.16405 | AE17: 818.15864 | AF17: 2178.2766 | AG17: 654.915 | AH17: 628.02448 | AI17: 618.43583 | AJ17: 1017.664 | AK17: 2919.0393 | AL17: 721.20768 | AM17: 666.87161 | AN17: 676.4 | AO17: 976.6 | AP17: =AO17+AN17+AM17+AL17 -> 3041.0793 | AQ17: 785 | AR17: 758.93 | AS17: 0 | AT17: 0 | AU17: =AT17+AS17+AR17+AQ17 -> 1543.93
A18: % receita bruta | B18: % gross revenues | C18: =C17/C6 -> 0.033118393 | D18: =D17/D6 -> 0.034808195 | E18: =E17/E6 -> 0.043321576 | F18: =F17/F6 -> 0.058589487 | G18: =G17/G6 -> 0.043682644 | H18: =H17/H6 -> 0.061858396 | I18: =I17/I6 -> 0.049426629 | J18: =J17/J6 -> 0.054551615 | ... AU18: =AU17/AU6 -> 0.037124084
A19: % variação anual | B19: % YoY growth | C19: - | D19: - | E19: - | F19: - | G19: - | H19: =H17/C17-1 -> 0.96448461 | I19: =I17/D17-1 -> 0.51589217 | J19: =J17/E17-1 -> 0.21052632 | K19: =K17/F17-1 -> 0.13221824 | L19: =L17/G17-1 -> 0.3554873 | M19: =M17/H17-1 -> 0.11093981 | N19: =N17/I17-1 -> 0.20331288 | O19: =O17/J17-1 -> 0.21940908 | ... AU19: =AU17/AP17-1 -> -0.49230853
A20: Corporativo & Outros | B20: Holding & Others | AV20: 4 | AW20: 3.3 | AX20: 0.7 | AY20: 0 | AZ20: =AY20+AX20+AW20+AV20 -> 8 | BA20: 0 | BB20: 0
A23: Impostos e deduções | B23: Taxes and deductions | C23: =C35-C6 -> -564.03993 | D23: =D35-D6 -> -708.40998 | E23: =E35-E6 -> -767.15737 | F23: =F35-F6 -> -867.83281 | G23: =G35-G6 -> -2907.4401 | H23: =H35-H6 -> -630.32713 | I23: =I35-I6 -> -789.80616 | J23: =J35-J6 -> -753.6 | ... AO23: =AO35-AO6 -> -3111.8 | AP23: =AO23+AN23+AM23+AL23 -> -10759.408 | AQ23: =AQ35-AQ6 -> -2320.9 | AR23: =AR35-AR6 -> -2492.64 | AS23: =AS35-AS6 -> -2305.175 | AT23: =AT35-AT6 -> -2593 | AU23: =AT23+AS23+AR23+AQ23 -> -9711.715 | AV23: =AV35-AV6 -> -1645.5 | AW23: =AW35-AW6 -> -1998.1 | AX23: =AX35-AX6 -> -1925.1 | AY23: =AY35-AY6 -> -2393 | AZ23: =AZ35-AZ6 -> -7961.8 | BA23: =BA35-BA6 -> -1676.9002 | BB23: =BB35-BB6 -> -1858.5
A24: % receita bruta | B24: % gross revenues | C24: =C23/C6 -> -0.25570302 | D24: =D23/D6 -> -0.26861081 | E24: =E23/E6 -> -0.27764801 | F24: =F23/F6 -> -0.27117803 | G24: =G23/G6 -> -0.26904698 | H24: =H23/H6 -> -0.27168945 | I24: =I23/I6 -> -0.28052432 | J24: =J23/J6 -> -0.28371358 | ... BB24: =BB23/BB6 -> -0.24629269
A25: Natura & Co América Latina | B25: Natura & Co Latam | C25: =C37-C8 -> -557.16401 | D25: =D37-D8 -> -701.12481 | E25: =E37-E8 -> -756.91355 | F25: =F37-F8 -> -851.71692 | G25: =G37-G8 -> -2866.9193 | H25: =H37-H8 -> -616.83689 | I25: =I37-I8 -> -776.72522 | J25: =J37-J8 -> -740 | ... AO25: =AO37-AO8 -> -1943.7 | AP25: =AL25+AM25+AN25+AO25 -> -7130.7657 | AQ25: =AQ37-AQ8 -> -1581.6 | AR25: =AR37-AR8 -> -1811.1 | AS25: =AS37-AS8 -> -1698.18 | AT25: =AT37-AT8 -> -1689.1 | AU25: =AT25+AS25+AR25+AQ25 -> -6779.98 | AV25: =AV37-AV8 -> -1645.5 | AW25: =AW37-AW8 -> -1998.1 | AX25: =AX37-AX8 -> -1925.1 | AY25: =AY37-AY8 -> -2279 | AZ25: =AZ37-AZ8 -> -7847.8 | BA25: =BA37-BA8 -> -1676.9002 | BB25: =BB37-BB8 -> -1858.5
A26: % receita bruta | B26: % gross revenues | C26: =C25/C8 -> -0.26123765 | D26: =D25/D8 -> -0.27543589 | E26: =E25/E8 -> -0.28634552 | F26: =F25/F8 -> -0.28270576 | G26: =G25/G8 -> -0.27741554 | H26: =H25/H8 -> -0.28340579 | I26: =I25/I8 -> -0.29022296 | J26: =J25/J8 -> -0.2946681 | ... BB26: =BB25/BB8 -> -0.24629269
A27: Avon International | B27: Avon International | C27: - | D27: - | E27: - | F27: - | G27: - | H27: - | I27: - | J27: - | K27: - | L27: - | M27: - | N27: - | O27: - | P27: - | Q27: - | R27: - | S27: - | T27: - | U27: - | V27: - | W27: - | X27: - | Y27: - | Z27: - | AA27: - | AB27: =AB40-AB11 -> -409.88054 | AC27: =AC40-AC11 -> -345.63338 | AD27: =AD40-AD11 -> -500.91094 | AE27: =AE40-AE11 -> -537.65816 | AF27: =AF40-AF11 -> -1794.083 | AG27: =AG40-AG11 -> -472.43437 | AH27: =AH40-AH11 -> -440.64635 | AI27: =AI40-AI11 -> -406.3121 | ... AO27: =AO40-AO11 -> -393.8 | AP27: =AL27+AM27+AN27+AO27 -> -1532.6538 | AQ27: =AQ40-AQ11 -> -314.4 | AR27: =AR40-AR11 -> -284.8 | AS27: =AS40-AS11 -> -277.522 | AT27: =AT40-AT11 -> -324.5 | AU27: =AT27+AS27+AR27+AQ27 -> -1201.222 | AV27: =AV40-AV11 -> 0 | AW27: =AW40-AW11 -> 0 | AX27: =AX40-AX11 -> 0 | AY27: =AY40-AY11 -> -114 | AZ27: =AZ40-AZ11 -> -114 | BA27: =BA40-BA11 -> 0
A28: % receita bruta | B28: % gross revenues | C28: - | D28: - | E28: - | F28: - | G28: - | H28: - | I28: - | J28: - | K28: - | L28: - | M28: - | N28: - | O28: - | P28: - | Q28: - | R28: - | S28: - | T28: - | U28: - | V28: - | W28: - | X28: - | Y28: - | Z28: - | AA28: - | AB28: =AB27/AB11 -> -0.16191865 | AC28: =AC27/AC11 -> -0.1731933 | AD28: =AD27/AD11 -> -0.16932694 | AE28: =AE27/AE11 -> -0.15784867 | AF28: =AF27/AF11 -> -0.16472386 | AG28: =AG27/AG11 -> -0.16659018 | AH28: =AH27/AH11 -> -0.16661795 | AI28: =AI27/AI11 -> -0.1651653 | ... BA28: =BA27/BA11 -> #DIV/0!
A29: The Body Shop | B29: The Body Shop | C29: - | D29: - | E29: - | F29: - | G29: - | H29: - | I29: - | J29: - | K29: - | L29: - | M29: - | N29: - | O29: =O43-O14 -> -109.3564 | P29: =P43-P14 -> -689.1 | Q29: =Q43-Q14 -> -798.4564 | R29: =R43-R14 -> -351.61709 | S29: =S43-S14 -> -383.98965 | T29: =T43-T14 -> -381.88416 | U29: =U43-U14 -> -736.74823 | V29: =V43-V14 -> -1854.2391 | ... AO29: =AO43-AO14 -> -677.3 | AP29: =AL29+AM29+AN29+AO29 -> -1773.609 | AQ29: =AQ43-AQ14 -> -341.2 | AR29: =AR43-AR14 -> -316.3 | AS29: =AS43-AS14 -> -329.473 | AT29: =AT43-AT14 -> -579.4 | AU29: =AT29+AS29+AR29+AQ29 -> -1566.373 | AV29: =AV43-AV14 -> 0 | AW29: =AW43-AW14 -> 0 | AX29: =AX43-AX14 -> 0 | AY29: =AY43-AY14 -> 0 | AZ29: =AZ43-AZ14 -> 0 | BA29: =BA43-BA14 -> 0
A30: % receita bruta | B30: % gross revenues | C30: - | D30: - | E30: - | F30: - | G30: - | H30: - | I30: - | J30: - | K30: - | L30: - | M30: - | N30: - | O30: =O29/O14 -> -0.30815678 | P30: =P29/P14 -> -0.36266512 | Q30: =Q29/Q14 -> -0.35408696 | R30: =R29/R14 -> -0.3034129 | S30: =S29/S14 -> -0.32249599 | T30: =T29/T14 -> -0.29202036 | U30: =U29/U14 -> -0.35370313 | V30: =V29/V14 -> -0.32302459 | ... BA30: =BA29/BA14 -> #DIV/0!
A31: Aesop | B31: Aesop | C31: =C46-C17 -> -6.875917 | D31: =D46-D17 -> -7.2851704 | E31: =E46-E17 -> -10.243822 | F31: =F46-F17 -> -16.115897 | G31: =G46-G17 -> -40.520807 | H31: =H46-H17 -> -13.490242 | I31: =I46-I17 -> -13.080937 | J31: =J46-J17 -> -13.6 | ... AO31: =AO46-AO17 -> -97 | AP31: =AL31+AM31+AN31+AO31 -> -322.32256 | AQ31: =AQ46-AQ17 -> -83.7 | AR31: =AR46-AR17 -> -80.44 | AS31: 0 | AT31: 0 | AU31: =AT31+AS31+AR31+AQ31 -> -164.14 | AV31: =AV46-AV17 -> 0 | AW31: =AW46-AW17 -> 0 | AX31: =AX46-AX17 -> 0 | AY31: =AY46-AY17 -> 0 | AZ31: =AZ46-AZ17 -> 0 | BA31: =BA46-BA17 -> 0
A32: % receita bruta | B32: % gross revenues | C32: =C31/C17 -> -0.094121182 | D32: =D31/D17 -> -0.079359155 | E32: =E31/E17 -> -0.085579135 | F32: =F31/F17 -> -0.085951452 | G32: =G31/G17 -> -0.08583937 | H32: =H31/H17 -> -0.094 | I32: =I31/I17 -> -0.094 | J32: =J31/J17 -> -0.093857833 | ... AR32: =AR31/AR17 -> -0.10599133 | AS32: - | AT32: - | AU32: - | AV32: =AV31/AV17 -> #DIV/0! | AW32: =AW31/AW17 -> #DIV/0! | AX32: =AX31/AX17 -> #DIV/0! | AY32: =AY31/AY17 -> #DIV/0! | AZ32: =AZ31/AZ17 -> #DIV/0! | BA32: =BA31/BA17 -> #DIV/0!
A35: Receita Líquida | B35: Net Revenues | C35: 1641.8 | D35: 1928.9 | E35: 1995.9 | F35: 2332.4 | G35: =F35+E35+D35+C35 -> 7899 | H35: 1689.7009 | I35: 2025.658 | J35: 1902.6 | K35: 2294.7123 | L35: =K35+J35+I35+H35 -> 7912.6711 | M35: =M37+M40+M43+M46 -> 1728.607 | N35: =N37+N40+N43+N46 -> 2025.8189 | O35: =O37+O40+O43+O46 -> 2365.4217 | P35: =P37+P40+P43+P46 -> 3732.816 | Q35: =Q37+Q40+Q43+Q46 -> 9852.6636 | R35: =R37+R40+R43+R46 -> 2687.6263 | S35: =S37+S40+S43+S46 -> 3100.0425 | T35: =T37+T40+T43+T46 -> 3241.9013 | ... AK35: =AK37+AK40+AK43+AK46 -> 40164.687 | AL35: =AL37+AL40+AL43+AL46+0.1 -> 8253.3959 | AM35: =AM37+AM40+AM43+AM46 -> 8702.4135 | AN35: =AN37+AN40+AN43+AN46-0.157 -> 9003.603 | AO35: =AO37+AO40+AO43+AO46 -> 10389.8 | AP35: =AP37+AP40+AP43+AP46 -> 36349.269 | AQ35: =AQ37+AQ40+AQ43+AQ46 -> 8021.5 | AR35: =AR37+AR40+AR43+AR46 -> 8451.99 | AS35: =AS37+AS40+AS43+AS46 -> 7517.261 | AT35: =AT37+AT40+AT43+AT46 -> 7885.9 | AU35: =AU37+AU40+AU43+AU46 -> 31876.651 | AV35: =AV37+AV40+AV43+AV46+AV49 -> 4582.6 | AW35: =AW37+AW40+AW43+AW46+AW49 -> 5784 | AX35: =AX37+AX40+AX43+AX46+AX49 -> 5976.3 | AY35: =AY37+AY40+AY43+AY46+AY49 -> 7747.3 | AZ35: =AZ37+AZ40+AZ43+AZ46+AZ49 -> 24089.6 | BA35: =BA37+BA40+BA43+BA46+BA49 -> 5142.9998 | BB35: =BB37+BB40+BB43+BB46+BB49 -> 5687.4
A36: % variação anual | B36: % YoY growth | C36: - | D36: - | E36: - | F36: - | G36: - | H36: =H35/C35-1 -> 0.029175821 | I36: =I35/D35-1 -> 0.050162255 | J36: =J35/E35-1 -> -0.046745829 | K36: =K35/F35-1 -> -0.016158335 | L36: =L35/G35-1 -> 0.0017307428 | M36: =M35/H35-1 -> 0.023025468 | N36: =N35/I35-1 -> 7.9422867e-05 | O36: =O35/J35-1 -> 0.24325751 | ... BB36: =BB35/AW35-1 -> -0.016701245
A37: Natura & Co América Latina | B37: Natura & Co Latam | C37: =C35-C46 -> 1575.622 | D37: =D35-D46 -> 1844.3852 | E37: =E35-E46 -> 1886.4438 | F37: =F35-F46 -> 2161.0159 | G37: =G35-G46 -> 7467.4669 | H37: =H35-H46 -> 1559.6779 | I37: =I35-I46 -> 1899.58 | J37: =J35-J46 -> 1771.3 | ... L37: =L35-L46 -> 7332.9346 | M37: 1584.1593 | N37: 1874.1076 | O37: 1959.8222 | P37: 2271.616 | Q37: =P37+O37+N37+M37 -> 7689.7052 | R37: 1679.2408 | S37: 2057.8348 | T37: 2048.6728 | U37: 2629.3372 | V37: 8447.3733 | W37: 1755.994 | X37: 2252.0018 | Y37: 2241.817 | Z37: 2762.5192 | AA37: =Z37+Y37+X37+W37 -> 9012.332 | AB37: 4162.3357 | AC37: 3975.7474 | AD37: 6083.6203 | AE37: 6320.6409 | AF37: =AE37+AD37+AC37+AB37 -> 20542.344 | AG37: 5185.9449 | AH37: 5533.671 | AI37: 5551.4876 | AJ37: 6142.2974 | AK37: =AJ37+AI37+AH37+AG37 -> 22413.401 | AL37: 4751.5204 | AM37: 5555.0449 | AN37: 5777.533 | AO37: 5943.2 | AP37: =AO37+AN37+AM37+AL37 -> 22027.298 | AQ37: 4863.7 | AR37: 5462.9 | AS37: 5232.034 | AT37: 4882.2 | AU37: =AT37+AS37+AR37+AQ37 -> 20440.834 | AV37: 4578.6 | AW37: 5780.7 | AX37: 5975.6 | AY37: 7090.6 | AZ37: 23424.9 | BA37: 5142.9998 | BB37: 5687.4
A38: % receita Líquida | B38: % net revenues | C38: =C37/C35 -> 0.95969183 | D38: =D37/D35 -> 0.95618496 | E38: =E37/E35 -> 0.94515949 | F38: =F37/F35 -> 0.92652028 | G38: =G37/G35 -> 0.94536865 | H38: =H37/H35 -> 0.92304971 | I38: =I37/I35 -> 0.9377595 | J38: =J37/J35 -> 0.93098917 | ... BB38: =BB37/BB35 -> 1
A39: % variação anual | B39: % YoY growth | C39: - | D39: - | E39: - | F39: - | G39: - | H39: =H37/C37-1 -> -0.010119273 | I39: =I37/D37-1 -> 0.029925874 | J39: =J37/E37-1 -> -0.061037504 | K39: =K37/F37-1 -> -0.027135002 | L39: =L37/G37-1 -> -0.018015788 | M39: =M37/H37-1 -> 0.015696466 | N39: =N37/I37-1 -> -0.013409486 | O39: =O37/J37-1 -> 0.10643156 | ... BB39: =BB37/AW37-1 -> -0.016139914
A40: Avon International | B40: Avon International | AB40: 2121.5174 | AC40: 1650.0176 | AD40: 2457.3363 | AE40: 2868.5041 | AF40: =AE40+AD40+AC40+AB40 -> 9097.3753 | AG40: 2363.4733 | AH40: 2204.0048 | AI40: 2053.721 | AJ40: 2708.1258 | AK40: =AJ40+AI40+AH40+AG40 -> 9329.3249 | AL40: 1841.9755 | AM40: 1643.7729 | AN40: 1647.592 | AO40: 2062.6 | AP40: =AO40+AN40+AM40+AL40 -> 7195.9404 | AQ40: 1606.6 | AR40: 1510.3 | AS40: 1455.786 | AT40: 1714.1 | AU40: =AT40+AS40+AR40+AQ40 -> 6286.786 | AV40: 0 | AW40: 0 | AY40: 656.7 | AZ40: =AY40 -> 656.7 | BA40: 0 | BB40: 0
A41: % receita Líquida | B41: % net revenues | C41: - | D41: - | E41: - | F41: - | G41: - | H41: - | I41: - | J41: - | K41: - | L41: - | M41: - | N41: - | O41: - | P41: - | Q41: - | R41: - | S41: - | T41: - | U41: - | V41: - | W41: - | X41: - | Y41: - | Z41: - | AA41: - | AB41: =AB40/AB35 -> 0.28219198 | AC41: =AC40/AC35 -> 0.23614923 | AD41: =AD40/AD35 -> 0.23583948 | AE41: =AE40/AE35 -> 0.2390963 | AF41: =AF40/AF35 -> 0.24639457 | AG41: =AG40/AG35 -> 0.24996879 | AH41: =AH40/AH35 -> 0.23158205 | AI41: =AI40/AI35 -> 0.21506679 | ... AZ41: =AZ40/AZ35 -> 0.027260727
A42: % variação anual | B42: % YoY growth | C42: - | D42: - | E42: - | F42: - | G42: - | H42: - | I42: - | J42: - | K42: - | L42: - | M42: - | N42: - | O42: - | P42: - | Q42: - | R42: - | S42: - | T42: - | U42: - | V42: - | W42: - | X42: - | Y42: - | Z42: - | AA42: - | AB42: - | AC42: - | AD42: - | AE42: - | AF42: - | AG42: =AG40/AB40-1 -> 0.11404853 | AH42: =AH40/AC40-1 -> 0.3357462 | AI42: =AI40/AD40-1 -> -0.1642491 | AJ42: =AJ40/AE40-1 -> -0.055910069 | AK42: =AK40/AF40-1 -> 0.025496317 | AL42: =AL40/AG40-1 -> -0.2206489 | AM42: =AM40/AH40-1 -> -0.25418814 | AN42: =AN40/AI40-1 -> -0.19775276 | ... AZ42: =AZ40/AU40-1 -> -0.89554281
A43: The Body Shop | B43: The Body Shop | O43: 245.51622 | P43: 1211 | Q43: =P43+O43+N43+M43 -> 1456.5162 | R43: 807.25615 | S43: 806.69075 | T43: 925.84714 | U43: 1346.2082 | V43: =U43+T43+S43+R43 -> 3886.0023 | W43: 889.31654 | X43: 867.45611 | Y43: 935.70065 | Z43: 1436.8352 | AA43: =Z43+Y43+X43+W43 -> 4129.3085 | AB43: 893.24157 | AC43: 979.19455 | AD43: 1384.6085 | AE43: 2075.8775 | AF43: =AE43+AD43+AC43+AB43 -> 5332.9222 | AG43: 1319.7313 | AH43: 1217.5649 | AI43: 1390.5863 | AJ43: 1893.8932 | AK43: =AJ43+AI43+AH43+AG43 -> 5821.7757 | AL43: 1017.4059 | AM43: 909.43307 | AN43: 976.035 | AO43: 1504.4 | AP43: =AO43+AN43+AM43+AL43 -> 4407.274 | AQ43: 849.9 | AR43: 800.3 | AS43: 829.441 | AT43: 1289.6 | AU43: =AT43+AS43+AR43+AQ43 -> 3769.241
A44: % receita Líquida | B44: % net revenues | C44: - | D44: - | E44: - | F44: - | G44: - | H44: - | I44: - | J44: - | K44: - | L44: - | M44: - | N44: - | O44: =O43/O35 -> 0.10379385 | P44: =P43/P35 -> 0.32441996 | Q44: =Q43/Q35 -> 0.14782969 | R44: =R43/R35 -> 0.30036027 | S44: =S43/S35 -> 0.26021926 | T44: =T43/T35 -> 0.28558771 | U44: =U43/U35 -> 0.31050386 | V44: =V43/V35 -> 0.29005606 | ... AU44: =AU43/AU35 -> 0.11824457
A45: % variação anual | B45: % YoY growth | C45: - | D45: - | E45: - | F45: - | G45: - | H45: - | I45: - | J45: - | K45: - | L45: - | M45: - | N45: - | O45: - | P45: - | Q45: - | R45: - | S45: - | T45: =T43/O43-1 -> 2.7710223 | U45: =U43/P43-1 -> 0.11165007 | V45: =V43/Q43-1 -> 1.6680117 | W45: =W43/R43-1 -> 0.10165347 | X45: =X43/S43-1 -> 0.075326703 | Y45: =Y43/T43-1 -> 0.010642693 | Z45: =Z43/U43-1 -> 0.067320158 | AA45: =AA43/V43-1 -> 0.062610925 | ... AU45: =AU43/AP43-1 -> -0.14476816
A46: Aesop | B46: Aesop | C46: 66.177957 | D46: 84.51483 | E46: 109.45618 | F46: 171.3841 | G46: =F46+E46+D46+C46 -> 431.53307 | H46: 130.02297 | I46: 126.07796 | J46: 131.3 | K46: 192.33557 | L46: =K46+J46+I46+H46 -> 579.73651 | M46: 144.44769 | N46: 151.71124 | O46: 160.08329 | P46: 250.2 | Q46: =P46+O46+N46+M46 -> 706.44222 | R46: 201.12935 | S46: 235.51695 | T46: 267.38133 | U46: 360.01501 | V46: =U46+T46+S46+R46 -> 1064.0426 | W46: 269.83945 | X46: 284.2504 | Y46: 296.27807 | Z46: 452.68203 | AA46: =Z46+Y46+X46+W46 -> 1303.0499 | AB46: 340.89858 | AC46: 382.22243 | AD46: 493.96385 | AE46: 732.25271 | AF46: =AE46+AD46+AC46+AB46 -> 1949.3376 | AG46: 585.92399 | AH46: 561.92519 | AI46: 553.42947 | AJ46: 898.90666 | AK46: =AJ46+AI46+AH46+AG46 -> 2600.1853 | AL46: 642.39412 | AM46: 594.16261 | AN46: 602.6 | AO46: 879.6 | AP46: =AO46+AN46+AM46+AL46 -> 2718.7567 | AQ46: 701.3 | AR46: 678.49 | AS46: 0 | AT46: 0 | AU46: =AT46+AS46+AR46+AQ46 -> 1379.79
A47: % receita Líquida | B47: % net revenues | C47: =C46/C35 -> 0.040308172 | D47: =D46/D35 -> 0.043815039 | E47: =E46/E35 -> 0.054840512 | F47: =F46/F35 -> 0.073479722 | G47: =G46/G35 -> 0.054631354 | H47: =H46/H35 -> 0.076950288 | I47: =I46/I35 -> 0.0622405 | J47: =J46/J35 -> 0.069010827 | ... AR47: =AR46/AR35 -> 0.080275769 | AS47: - | AT47: - | AU47: =AU46/AU35 -> 0.043285287
A48: % variação anual | B48: % YoY growth | C48: - | D48: - | E48: - | F48: - | G48: - | H48: =H46/C46-1 -> 0.96474741 | I48: =I46/D46-1 -> 0.49178511 | J48: =J46/E46-1 -> 0.19956683 | K48: =K46/F46-1 -> 0.12224862 | L48: =L46/G46-1 -> 0.34343472 | M48: =M46/H46-1 -> 0.11093981 | N48: =N46/I46-1 -> 0.20331288 | O48: =O46/J46-1 -> 0.21921777 | ... AR48: =AR46/AM46-1 -> 0.14192645 | AS48: - | AT48: - | AU48: =AU46/AP46-1 -> -0.49249229
A49: Corporativo & Outros | B49: Holding & Others | AV49: 4 | AW49: 3.3 | AX49: 0.7 | AY49: 0 | AZ49: =AY49+AX49+AW49+AV49 -> 8 | BA49: 0 | BB49: 0
A51: CMV | B51: COGS | C51: =C68-C35 -> -495.1671 | D51: =D68-D35 -> -589.63978 | E51: =E68-E35 -> -618.31485 | F51: =F68-F35 -> -712.90224 | G51: =G68-G35 -> -2416.024 | H51: =H68-H35 -> -521.07206 | I51: =I68-I35 -> -638.23244 | J51: =J68-J35 -> -566.8 | ... BB51: =BB68-BB35 -> -1909.1
A52: % receita Líquida | B52: % net revenues | C52: =C51/C35 -> -0.30160013 | D52: =D51/D35 -> -0.30568706 | E52: =E51/E35 -> -0.3097925 | F52: =F51/F35 -> -0.30565179 | G52: =G51/G35 -> -0.30586454 | H52: =H51/H35 -> -0.30838125 | I52: =I51/I35 -> -0.31507414 | J52: =J51/J35 -> -0.29790813 | ... BB52: =BB51/BB35 -> -0.33567184
A53: % variação anual | B53: % YoY growth | C53: - | D53: - | E53: - | F53: - | G53: - | H53: =H51/C51-1 -> 0.0523156 | I53: =I51/D51-1 -> 0.082410768 | J53: =J51/E51-1 -> -0.08331491 | K53: =K51/F51-1 -> 0.011098017 | L53: =L51/G51-1 -> 0.012787367 | M53: =M51/H51-1 -> -0.0021763549 | N53: =N51/I51-1 -> -0.051594452 | O53: =O51/J51-1 -> 0.21615944 | ... BB53: =BB51/AW51-1 -> -0.041712679
A54: Natura & Co América Latina | B54: Natura & Co Latam | C54: =C71-C37 -> -486.88031 | D54: =D71-D37 -> -580.58408 | E54: =E71-E37 -> -606.63658 | F54: =F71-F37 -> -692.17947 | G54: =G71-G37 -> -2366.2804 | H54: =H71-H37 -> -506.26318 | I54: =I71-I37 -> -624.90214 | J54: =J71-J37 -> -562.6 | ... BB54: =BB71-BB37 -> -1909.1
A55: % receita Líquida | B55: % net revenues | C55: =C54/C37 -> -0.30900831 | D55: =D54/D37 -> -0.31478462 | E55: =E54/E37 -> -0.32157681 | F55: =F54/F37 -> -0.32030281 | G55: =G54/G37 -> -0.3168786 | H55: =H54/H37 -> -0.3245947 | I55: =I54/I37 -> -0.32896858 | J55: =J54/J37 -> -0.31761983 | ... BB55: =BB54/BB37 -> -0.33567184
A56: % variação anual | B56: % YoY growth | C56: - | D56: - | E56: - | F56: - | G56: - | H56: =H54/C54-1 -> 0.039810333 | I56: =I54/D54-1 -> 0.076333578 | J56: =J54/E54-1 -> -0.072591367 | K56: =K54/F54-1 -> 0.010808481 | L56: =L54/G54-1 -> 0.011471911 | M56: =M54/H54-1 -> -0.0040365316 | N56: =N54/I54-1 -> -0.055952901 | O56: =O54/J54-1 -> 0.089750876 | ... BB56: =BB54/AW54-1 -> -0.040363929
A57: Avon International | B57: Avon International | AB57: =AB74-AB40 -> -927.20321 | AC57: =AC74-AC40 -> -632.53004 | AD57: =AD74-AD40 -> -978.18466 | AE57: =AE74-AE40 -> -1284.0465 | AF57: =AF74-AF40 -> -3821.9644 | AG57: =AG74-AG40 -> -946.15995 | AH57: =AH74-AH40 -> -842.2626 | AI57: =AI74-AI40 -> -794.25034 | ... BA57: =BA74-BA40 -> 0 | BB57: 0
A58: % receita Líquida | B58: % net revenues | C58: - | D58: - | E58: - | F58: - | G58: - | H58: - | I58: - | J58: - | K58: - | L58: - | M58: - | N58: - | O58: - | P58: - | Q58: - | R58: - | S58: - | T58: - | U58: - | V58: - | W58: - | X58: - | Y58: - | Z58: - | AA58: - | AB58: =AB57/AB40 -> -0.4370472 | AC58: =AC57/AC40 -> -0.38334744 | AD58: =AD57/AD40 -> -0.39806708 | AE58: =AE57/AE40 -> -0.44763629 | AF58: =AF57/AF40 -> -0.42011726 | AG58: =AG57/AG40 -> -0.40032606 | AH58: =AH57/AH40 -> -0.38215098 | AI58: =AI57/AI40 -> -0.38673721 | ... AZ58: =AZ57/AZ40 -> -0.40201005
A59: % variação anual | B59: % YoY growth | C59: - | D59: - | E59: - | F59: - | G59: - | H59: - | I59: - | J59: - | K59: - | L59: - | M59: - | N59: - | O59: - | P59: - | Q59: - | R59: - | S59: - | T59: - | U59: - | V59: - | W59: - | X59: - | Y59: - | Z59: - | AA59: - | AB59: - | AC59: - | AD59: - | AE59: - | AF59: - | AG59: =AG57/AB57-1 -> 0.020445079 | AH59: =AH57/AC57-1 -> 0.33157723 | AI59: =AI57/AD57-1 -> -0.1880364 | AJ59: =AJ57/AE57-1 -> -0.13123025 | AK59: =AK57/AF57-1 -> -0.032378839 | AL59: =AL57/AG57-1 -> -0.21307557 | AM59: =AM57/AH57-1 -> -0.19473442 | AN59: =AN57/AI57-1 -> -0.16201735 | ... AZ59: =AZ57/AU57-1 -> -0.8845828
A60: The Body Shop | B60: The Body Shop | O60: =O77-O43 -> -59.609499 | P60: =P77-P43 -> -310.9 | Q60: =Q77-Q43 -> -370.5095 | R60: =R77-R43 -> -193.62695 | S60: =S77-S43 -> -188.87295 | T60: =T77-T43 -> -223.73426 | U60: =U77-U43 -> -337.21866 | V60: =V77-V43 -> -943.45282 | ... AU60: =AU77-AU43 -> -873.976
A61: % receita Líquida | B61: % net revenues | C61: - | D61: - | E61: - | F61: - | G61: - | H61: - | I61: - | J61: - | K61: - | L61: - | M61: - | N61: - | O61: =O60/O43 -> -0.24279251 | P61: =P60/P43 -> -0.25672998 | Q61: =Q60/Q43 -> -0.25438062 | R61: =R60/R43 -> -0.23985813 | S61: =S60/S43 -> -0.23413303 | T61: =T60/T43 -> -0.24165356 | U61: =U60/U43 -> -0.25049517 | V61: =V60/V43 -> -0.24278236 | ... AU61: =AU60/AU43 -> -0.23187055
A62: % variação anual | B62: % YoY growth | C62: - | D62: - | E62: - | F62: - | G62: - | H62: - | I62: - | J62: - | K62: - | L62: - | M62: - | N62: - | O62: - | P62: - | Q62: - | R62: - | S62: - | T62: =T60/O60-1 -> 2.7533324 | U62: =U60/P60-1 -> 0.084653133 | V62: =V60/Q60-1 -> 1.5463661 | W62: =W60/R60-1 -> 0.088785995 | X62: =X60/S60-1 -> 0.085981348 | Y62: =Y60/T60-1 -> -0.0039164393 | Z62: =Z60/U60-1 -> -0.018767239 | AA62: =AA60/V60-1 -> 0.0277979 | ... AU62: =AU60/AP60-1 -> -0.15356529
A63: Aesop | B63: Aesop | C63: =C80-C46 -> -8.2867873 | D63: =D80-D46 -> -9.0556927 | E63: =E80-E46 -> -11.678267 | F63: =F80-F46 -> -20.722778 | G63: =G80-G46 -> -49.743525 | H63: =H80-H46 -> -14.808884 | I63: =I80-I46 -> -13.330299 | J63: =J80-J46 -> -4.2 | ... AR63: =AR80-AR46 -> -95.02 | AS63: 0 | AT63: 0 | AU63: =AU80-AU46 -> -193.22
A64: % receita Líquida | B64: % net revenues | C64: =C63/C46 -> -0.12521975 | D64: =D63/D46 -> -0.10714916 | E64: =E63/E46 -> -0.10669354 | F64: =F63/F46 -> -0.12091423 | G64: =G63/G46 -> -0.11527164 | H64: =H63/H46 -> -0.11389437 | I64: =I63/I46 -> -0.1057306 | J64: =J63/J46 -> -0.031987814 | ... AR64: =AR63/AR46 -> -0.14004628 | AS64: - | AT64: - | AU64: =AU63/AU46 -> -0.1400358
A65: % variação anual | B65: % YoY growth | C65: - | D65: - | E65: - | F65: - | G65: - | H65: =H63/C63-1 -> 0.78704771 | I65: =I63/D63-1 -> 0.47203524 | J65: =J63/E63-1 -> -0.6403576 | K65: =K63/F63-1 -> 0.020769038 | L65: =L63/G63-1 -> 0.075363136 | M65: =M63/H63-1 -> 0.061416486 | N65: =N63/I63-1 -> 0.15272236 | O65: =O63/J63-1 -> 2.9561491 | ... AR65: =AR63/AM63-1 -> 0.58389572 | AS65: - | AT65: - | AU65: =AU63/AP63-1 -> -0.45063229
A66: Corporativo & Outros | B66: Holding & Others | AV66: =AV83-AV49 -> -3.3 | AW66: =AW83-AW49 -> -2.8 | AX66: =AX83-AX49 -> -0.7 | AY66: =AY83-AY49 -> 0 | AZ66: =AZ83-AZ49 -> -6.8 | BA66: =BA83-BA49 -> 0 | BB66: 0
A68: Lucro Bruto | B68: Gross Profit | C68: 1146.6329 | D68: 1339.2602 | E68: 1377.5852 | F68: 1619.4978 | G68: =F68+E68+D68+C68 -> 5482.976 | H68: 1168.6288 | I68: 1387.4255 | J68: 1335.8 | K68: 1573.8983 | L68: =K68+J68+I68+H68 -> 5465.7526 | M68: =M71+M74+M77+M80 -> 1208.669 | N68: =N71+N74+N77+N80 -> 1420.5157 | O68: =O71+O74+O77+O80 -> 1676.1026 | P68: =P71+P74+P77+P80 -> 2636.305 | Q68: =Q71+Q74+Q77+Q80 -> 6941.5922 | R68: =R71+R74+R77+R80 -> 1951.6802 | S68: =S71+S74+S77+S80 -> 2205.1535 | T68: =T71+T74+T77+T80 -> 2374.8145 | ... AK68: =AK71+AK74+AK77+AK80 -> 26153.162 | AL68: =AL71+AL74+AL77+AL80-0.1 -> 5307.5874 | AM68: =AM71+AM74+AM77+AM80 -> 5485.5726 | AN68: =AN71+AN74+AN77+AN80+0.11 -> 5774.24 | AO68: =AO71+AO74+AO77+AO80 -> 6626.9 | AP68: =AP71+AP74+AP77+AP80 -> 23194.29 | AQ68: =AQ71+AQ74+AQ77+AQ80 -> 5428.6 | AR68: =AR71+AR74+AR77+AR80+0.1 -> 5669.07 | AS68: =AS71+AS74+AS77+AS80 -> 4906.268 | AT68: =AT71+AT74+AT77+AT80 -> 5123 | AU68: =AU71+AU74+AU77+AU80 -> 21126.838 | AV68: =AV71+AV74+AV77+AV80+AV83 -> 3030.2 | AW68: =AW71+AW74+AW77+AW80+AW83 -> 3791.8 | AX68: =AX71+AX74+AX77+AX80+AX83 -> 4022.3 | AY68: =AY71+AY74+AY77+AY80+AY83 -> 4872.4 | AZ68: =AZ71+AZ74+AZ77+AZ80+AZ83 -> 15717.2 | BA68: =BA71+BA74+BA77+BA80+BA83 -> 3467.1867 | BB68: =BB71+BB74+BB77+BB80+BB83 -> 3778.3
A69: % margem bruta | B69: % gross margin | C69: =C68/C35 -> 0.69839987 | D69: =D68/D35 -> 0.69431294 | E69: =E68/E35 -> 0.6902075 | F69: =F68/F35 -> 0.69434821 | G69: =G68/G35 -> 0.69413546 | H69: =H68/H35 -> 0.69161875 | I69: =I68/I35 -> 0.68492586 | J69: =J68/J35 -> 0.70209187 | ... BB69: =BB68/BB35 -> 0.66432816
A70: % variação anual | B70: % YoY growth | C70: - | D70: - | E70: - | F70: - | G70: - | H70: =H68/C68-1 -> 0.019183035 | I70: =I68/D68-1 -> 0.035964114 | J70: =J68/E68-1 -> -0.030332175 | K70: =K68/F68-1 -> -0.028156569 | L70: =L68/G68-1 -> -0.0031412591 | M70: =M68/H68-1 -> 0.03426254 | N70: =N68/I68-1 -> 0.023850027 | O70: =O68/J68-1 -> 0.25475563 | ... BB70: =BB68/AW68-1 -> -0.0035603144
A71: Natura & Co América Latina | B71: Natura & Co Latam | C71: =C68-C80 -> 1088.7417 | D71: =D68-D80 -> 1263.8011 | E71: =E68-E80 -> 1279.8072 | F71: =F68-F80 -> 1468.8364 | G71: =G68-G80 -> 5101.1865 | H71: =H68-H80 -> 1053.4147 | I71: =I68-I80 -> 1274.6779 | J71: =J68-J80 -> 1208.7 | ... L71: =L68-L80 -> 4939.5084 | M71: 1079.9397 | N71: 1284.1706 | O71: 1346.7284 | P71: 1518.405 | Q71: =P71+O71+N71+M71 -> 5229.2436 | R71: 1159.6583 | S71: 1375.197 | T71: 1433.6963 | U71: 1744.1433 | V71: 5724.0368 | W71: 1181.6256 | X71: 1519.1158 | Y71: 1525.0875 | Z71: 1845.6943 | AA71: =Z71+Y71+X71+W71 -> 6071.5232 | AB71: 2444.2423 | AC71: 2467.2486 | AD71: 3699.6064 | AE71: 3868.49 | AF71: =AE71+AD71+AC71+AB71 -> 12479.587 | AG71: 3138.9145 | AH71: 3356.2382 | AI71: 3392.5785 | AJ71: 3692.5805 | AK71: =AJ71+AI71+AH71+AG71 -> 13580.312 | AL71: 2836.4588 | AM71: 3280.998 | AN71: 3496.783 | AO71: 3532.9 | AP71: =AO71+AN71+AM71+AL71 -> 13147.14 | AQ71: 3121.9 | AR71: 3506 | AS71: 3332.871 | AT71: 3084.8 | AU71: =AT71+AS71+AR71+AQ71 -> 13045.571 | AV71: 3029.5 | AW71: 3791.3 | AX71: 4022.3 | AY71: 4479.7 | AZ71: 15323.3 | BA71: 3467.1867 | BB71: 3778.3
A72: % margem bruta | B72: % gross margin | C72: =C71/C37 -> 0.69099169 | D72: =D71/D37 -> 0.68521538 | E72: =E71/E37 -> 0.67842319 | F72: =F71/F37 -> 0.67969719 | G72: =G71/G37 -> 0.6831214 | H72: =H71/H37 -> 0.6754053 | I72: =I71/I37 -> 0.67103142 | J72: =J71/J37 -> 0.68238017 | ... BB72: =BB71/BB37 -> 0.66432816
A73: % variação anual | B73: % YoY growth | C73: - | D73: - | E73: - | F73: - | G73: - | H73: =H71/C71-1 -> -0.032447563 | I73: =I71/D71-1 -> 0.0086064007 | J73: =J71/E71-1 -> -0.055560901 | K73: =K71/F71-1 -> -0.045015617 | L73: =L71/G71-1 -> -0.031694207 | M73: =M71/H71-1 -> 0.025179995 | N73: =N71/I71-1 -> 0.0074471342 | O73: =O71/J71-1 -> 0.11419574 | ... BB73: =BB71/AW71-1 -> -0.003428903
A74: Avon International | B74: Avon International | AB74: 1194.3141 | AC74: 1017.4876 | AD74: 1479.1516 | AE74: 1584.4576 | AF74: =AE74+AD74+AC74+AB74 -> 5275.4109 | AG74: 1417.3133 | AH74: 1361.7422 | AI74: 1259.4707 | AJ74: 1592.585 | AK74: =AJ74+AI74+AH74+AG74 -> 5631.1112 | AL74: 1097.4191 | AM74: 965.52783 | AN74: 982.024 | AO74: 1260.4 | AP74: =AO74+AN74+AM74+AL74 -> 4305.371 | AQ74: 1035.4 | AR74: 956.7 | AS74: 938.332 | AT74: 1069 | AU74: =AT74+AS74+AR74+AQ74 -> 3999.432 | AV74: 0 | AW74: 0 | AY74: 392.7 | AZ74: =AY74 -> 392.7 | BA74: 0 | BB74: 0
A75: % margem bruta | B75: % gross margin | C75: - | D75: - | E75: - | F75: - | G75: - | H75: - | I75: - | J75: - | K75: - | L75: - | M75: - | N75: - | O75: - | P75: - | Q75: - | R75: - | S75: - | T75: - | U75: - | V75: - | W75: - | X75: - | Y75: - | Z75: - | AA75: - | AB75: =AB74/AB40 -> 0.5629528 | AC75: =AC74/AC40 -> 0.61665256 | AD75: =AD74/AD40 -> 0.60193292 | AE75: =AE74/AE40 -> 0.55236371 | AF75: =AF74/AF40 -> 0.57988274 | AG75: =AG74/AG40 -> 0.59967394 | AH75: =AH74/AH40 -> 0.61784902 | AI75: =AI74/AI40 -> 0.61326279 | ... AZ75: =AZ74/AZ40 -> 0.59798995
A76: % variação anual | B76: % YoY growth | C76: - | D76: - | E76: - | F76: - | G76: - | H76: - | I76: - | J76: - | K76: - | L76: - | M76: - | N76: - | O76: - | P76: - | Q76: - | R76: - | S76: - | T76: - | U76: - | V76: - | W76: - | X76: - | Y76: - | Z76: - | AA76: - | AB76: - | AC76: - | AD76: - | AE76: - | AF76: - | AG76: =AG74/AB74-1 -> 0.18671737 | AH76: =AH74/AC74-1 -> 0.33833787 | AI76: =AI74/AD74-1 -> -0.1485182 | AJ76: =AJ74/AE74-1 -> 0.0051295082 | AK76: =AK74/AF74-1 -> 0.067426091 | AL76: =AL74/AG74-1 -> -0.22570466 | AM76: =AM74/AH74-1 -> -0.29096136 | AN76: =AN74/AI74-1 -> -0.22028831 | ... AZ76: =AZ74/AU74-1 -> -0.90181106
A77: The Body Shop | B77: The Body Shop | O77: 185.90672 | P77: 900.1 | Q77: =P77+O77+N77+M77 -> 1086.0067 | R77: 613.6292 | S77: 617.8178 | T77: 702.11288 | U77: 1008.9896 | V77: =U77+T77+S77+R77 -> 2942.5495 | W77: 678.49823 | X77: 662.34361 | Y77: 712.84263 | Z77: 1105.9452 | AA77: =Z77+Y77+X77+W77 -> 3159.6297 | AB77: 691.99336 | AC77: 780.18072 | AD77: 1099.5526 | AE77: 1604.1522 | AF77: =AE77+AD77+AC77+AB77 -> 4175.8789 | AG77: 1040.682 | AH77: 973.52202 | AI77: 1081.1081 | AJ77: 1489.799 | AK77: =AJ77+AI77+AH77+AG77 -> 4585.111 | AL77: 794.23749 | AM77: 704.87546 | AN77: 745.023 | AO77: 1130.6 | AP77: =AO77+AN77+AM77+AL77 -> 3374.7359 | AQ77: 668.2 | AR77: 622.8 | AS77: 635.065 | AT77: 969.2 | AU77: =AT77+AS77+AR77+AQ77 -> 2895.265
A78: % margem bruta | B78: % gross margin | C78: - | D78: - | E78: - | F78: - | G78: - | H78: - | I78: - | J78: - | K78: - | L78: - | M78: - | N78: - | O78: =O77/O43 -> 0.75720749 | P78: =P77/P43 -> 0.74327002 | Q78: =Q77/Q43 -> 0.74561938 | R78: =R77/R43 -> 0.76014187 | S78: =S77/S43 -> 0.76586697 | T78: =T77/T43 -> 0.75834644 | U78: =U77/U43 -> 0.74950483 | V78: =V77/V43 -> 0.75721764 | ... AU78: =AU77/AU43 -> 0.76812945
A79: % variação anual | B79: % YoY growth | C79: - | D79: - | E79: - | F79: - | G79: - | H79: - | I79: - | J79: - | K79: - | L79: - | M79: - | N79: - | O79: - | P79: - | Q79: - | R79: - | S79: - | T79: =T77/O77-1 -> 2.7766945 | U79: =U77/P77-1 -> 0.12097497 | V79: =V77/Q77-1 -> 1.7095131 | W79: =W77/R77-1 -> 0.10571372 | X79: =X77/S77-1 -> 0.072069473 | Y79: =Y77/T77-1 -> 0.015282085 | Z79: =Z77/U77-1 -> 0.09609179 | AA79: =AA77/V77-1 -> 0.073772826 | ... AU79: =AU77/AP77-1 -> -0.14207658
A80: Aesop | B80: Aesop | C80: 57.891169 | D80: 75.459137 | E80: 97.77791 | F80: 150.66133 | G80: =F80+E80+D80+C80 -> 381.78954 | H80: 115.21408 | I80: 112.74767 | J80: 127.1 | K80: 171.1824 | L80: =K80+J80+I80+H80 -> 526.24415 | M80: 128.7293 | N80: 136.34511 | O80: 143.46747 | P80: 217.8 | Q80: =P80+O80+N80+M80 -> 626.34187 | R80: 178.39266 | S80: 212.13869 | T80: 239.00536 | U80: 318.45223 | V80: =U80+T80+S80+R80 -> 947.98893 | W80: 245.85428 | X80: 257.69401 | Y80: 268.72602 | Z80: 407.80907 | AA80: =Z80+Y80+X80+W80 -> 1180.0834 | AB80: 308.72142 | AC80: 346.75775 | AD80: 445.77897 | AE80: 660.12919 | AF80: =AE80+AD80+AC80+AB80 -> 1761.3873 | AG80: 533.77494 | AH80: 509.29773 | AI80: 502.99781 | AJ80: 810.55744 | AK80: =AJ80+AI80+AH80+AG80 -> 2356.6279 | AL80: 579.57201 | AM80: 534.17129 | AN80: 550.3 | AO80: 703 | AP80: =AO80+AN80+AM80+AL80 -> 2367.0433 | AQ80: 603.1 | AR80: 583.47 | AS80: 0 | AT80: 0 | AU80: =AT80+AS80+AR80+AQ80 -> 1186.57
A81: % margem bruta | B81: % gross margin | C81: =C80/C46 -> 0.87478025 | D81: =D80/D46 -> 0.89285084 | E81: =E80/E46 -> 0.89330646 | F81: =F80/F46 -> 0.87908577 | G81: =G80/G46 -> 0.88472836 | H81: =H80/H46 -> 0.88610563 | I81: =I80/I46 -> 0.8942694 | J81: =J80/J46 -> 0.96801219 | ... AR81: =AR80/AR46 -> 0.85995372 | AS81: - | AT81: - | AU81: =AU80/AU46 -> 0.8599642
A82: % variação anual | B82: % YoY growth | C82: - | D82: - | E82: - | F82: - | G82: - | H82: =H80/C80-1 -> 0.9901841 | I82: =I80/D80-1 -> 0.49415525 | J82: =J80/E80-1 -> 0.2998846 | K82: =K80/F80-1 -> 0.13620667 | L82: =L80/G80-1 -> 0.37836189 | M82: =M80/H80-1 -> 0.11730522 | N82: =N80/I80-1 -> 0.20929426 | O82: =O80/J80-1 -> 0.12877629 | ... AR82: =AR80/AM80-1 -> 0.092290086 | AS82: - | AT82: - | AU82: =AU80/AP80-1 -> -0.49871217
A83: Corporativo & Outros | B83: Holding & Others | AV83: 0.7 | AW83: 0.5 | AX83: 0 | AY83: 0 | AZ83: =AY83+AX83+AW83+AV83 -> 1.2 | BA83: 0 | BB83: 0
A85: Despesas Operacionais | B85: Operating expenses | C85: =C104+C120+C139+C158+C162+C166 -> -917.9 | D85: =D104+D120+D139+D158+D162+D166 -> -1035 | E85: =E104+E120+E139+E158+E162+E166 -> -1040.5 | F85: =F104+F120+F139+F158+F162+F166 -> -1233.1 | G85: =G104+G120+G139+G158+G162+G166 -> -4226.5 | H85: =H104+H120+H139+H158+H162+H166 -> -1014.7051 | I85: =I104+I120+I139+I158+I162+I166 -> -1107.0744 | J85: =J104+J120+J139+J158+J162+J166 -> -1084.3755 | ... BB85: =BB104+BB120+BB139+BB158+BB162+BB166 -> -3331.8
A86: % receita líquida | B86: % net revenues | C86: =C85/C35 -> -0.5590815 | D86: =D85/D35 -> -0.53657525 | E86: =E85/E35 -> -0.5213187 | F86: =F85/F35 -> -0.5286829 | G86: =G85/G35 -> -0.53506773 | H86: =H85/H35 -> -0.60052354 | I86: =I85/I35 -> -0.54652581 | J86: =J85/J35 -> -0.56994403 | ... BB86: =BB85/BB35 -> -0.58582129
A87: % variação anual | B87: % YoY growth | C87: - | D87: - | E87: - | F87: - | G87: - | H87: =H85/C85-1 -> 0.10546371 | I87: =I85/D85-1 -> 0.069637077 | J87: =J85/E85-1 -> 0.042167712 | K87: =K85/F85-1 -> -0.045721879 | L87: =L85/G85-1 -> 0.036998787 | M87: =M85/H85-1 -> -0.10177186 | N87: =N85/I85-1 -> 0.073557786 | O87: =O85/J85-1 -> 0.20695023 | ... BB87: =BB85/AW85-1 -> 0.0024370431
A88: Natura & Co América Latina | B88: Natura & Co Latam | C88: =C107+C123+C142+C169 -> -860.7184 | D88: =D107+D123+D142+D169 -> -968.38132 | E88: =E107+E123+E142+E169 -> -948.95325 | F88: =F107+F123+F142+F169 -> -1130.0301 | G88: =G107+G123+G142+G169 -> -3908.0831 | H88: =H107+H123+H142+H169 -> -906.84382 | I88: =I107+I123+I142+I169 -> -1005.1762 | J88: =J107+J123+J142+J169 -> -969.1755 | ... BB88: =BB107+BB123+BB142+BB169 -> -3245.4
A89: % receita líquida | B89: % net revenues | C89: =C88/C37 -> -0.54627213 | D89: =D88/D37 -> -0.52504289 | E89: =E88/E37 -> -0.50303817 | F89: =F88/F37 -> -0.52291614 | G89: =G88/G37 -> -0.52334789 | H89: =H88/H37 -> -0.58143019 | I89: =I88/I37 -> -0.52915708 | J89: =J88/J37 -> -0.54715492 | ... BB89: =BB88/BB37 -> -0.57062981
A90: % variação anual | B90: % YoY growth | C90: - | D90: - | E90: - | F90: - | G90: - | H90: =H88/C88-1 -> 0.053589436 | I90: =I88/D88-1 -> 0.037996273 | J90: =J88/E88-1 -> 0.021310067 | K90: =K88/F88-1 -> -0.069035489 | L90: =L88/G88-1 -> 0.0064303579 | M90: =M88/H88-1 -> -0.13524464 | N90: =N88/I88-1 -> 0.05094394 | O90: =O88/J88-1 -> -0.019094053 | ... BB90: =BB88/AW88-1 -> 0.012384191
A91: Avon International | B91: Avon International | AB91: =AB110+AB126+AB145+AB172 -> -1350.4918 | AC91: =AC110+AC126+AC145+AC172 -> -1170.7869 | AD91: =AD110+AD126+AD145+AD172 -> -1542.2061 | AE91: =AE110+AE126+AE145+AE172 -> -1711.0621 | AF91: =AF110+AF126+AF145+AF172 -> -5774.5469 | AG91: =AG110+AG126+AG145+AG172 -> -1613.97 | AH91: =AH110+AH126+AH145+AH172 -> -1616.301 | AI91: =AI110+AI126+AI145+AI172 -> -1417.4799 | ... BB91: =BB110+BB126+BB145+BB172 -> 0
A92: % receita líquida | B92: % net revenues | C92: - | D92: - | E92: - | F92: - | G92: - | H92: - | I92: - | J92: - | K92: - | L92: - | M92: - | N92: - | O92: - | P92: - | Q92: - | R92: - | S92: - | T92: - | U92: - | V92: - | W92: - | X92: - | Y92: - | Z92: - | AA92: - | AB92: =AB91/AB40 -> -0.63656884 | AC92: =AC91/AC40 -> -0.70956023 | AD92: =AD91/AD40 -> -0.62759262 | AE92: =AE91/AE40 -> -0.59649978 | AF92: =AF91/AF40 -> -0.63474867 | AG92: =AG91/AG40 -> -0.68288058 | AH92: =AH91/AH40 -> -0.73334733 | AI92: =AI91/AI40 -> -0.69020082 | ... AZ92: =AZ91/AZ40 -> -0.58824425
A93: % variação anual | B93: % YoY growth | C93: - | D93: - | E93: - | F93: - | G93: - | H93: - | I93: - | J93: - | K93: - | L93: - | M93: - | N93: - | O93: - | P93: - | Q93: - | R93: - | S93: - | T93: - | U93: - | V93: - | W93: - | X93: - | Y93: - | Z93: - | AA93: - | AB93: - | AC93: - | AD93: - | AE93: - | AF93: - | AG93: =AG91/AB91-1 -> 0.19509792 | AH93: =AH91/AC91-1 -> 0.38052538 | AI93: =AI91/AD91-1 -> -0.080875179 | AJ93: =AJ91/AE91-1 -> -0.09983513 | AK93: =AK91/AF91-1 -> 0.071597304 | AL93: =AL91/AG91-1 -> -0.2348034 | AM93: =AM91/AH91-1 -> -0.38630993 | AN93: =AN91/AI91-1 -> -0.17297029 | ... AZ93: =AZ91/AU91-1 -> -0.92511456
A94: The Body Shop | B94: The Body Shop | O94: =O113+O129+O148+O175 -> -187.29223 | P94: =P113+P129+P148+P175 -> -735.26468 | Q94: =Q113+Q129+Q148+Q175 -> -922.55691 | R94: =R113+R129+R148+R175 -> -604.72272 | S94: =S113+S129+S148+S175 -> -682.06167 | T94: =T113+T129+T148+T175 -> -705.99533 | U94: =U113+U129+U148+U175 -> -861.48745 | V94: =V113+V129+V148+V175 -> -2854.2672 | ... AU94: =AU113+AU129+AU148+AU175 -> -3259.265
A95: % receita líquida | B95: % net revenues | C95: - | D95: - | E95: - | F95: - | G95: - | H95: - | I95: - | J95: - | K95: - | L95: - | M95: - | N95: - | O95: =O94/O43 -> -0.76285074 | P95: =P94/P43 -> -0.60715498 | Q95: =Q94/Q43 -> -0.63339968 | R95: =R94/R43 -> -0.74910884 | S95: =S94/S43 -> -0.84550575 | T95: =T94/T43 -> -0.76253984 | U95: =U94/U43 -> -0.63993625 | V95: =V94/V43 -> -0.73449961 | ... AU95: =AU94/AU43 -> -0.86470061
A96: % variação anual | B96: % YoY growth | C96: - | D96: - | E96: - | F96: - | G96: - | H96: - | I96: - | J96: - | K96: - | L96: - | M96: - | N96: - | O96: - | P96: - | Q96: - | R96: - | S96: - | T96: =T94/O94-1 -> 2.7694855 | U96: =U94/P94-1 -> 0.17166984 | V96: =V94/Q94-1 -> 2.0938657 | W96: =W94/R94-1 -> 0.086875521 | X96: =X94/S94-1 -> 0.015544111 | Y96: =Y94/T94-1 -> 0.0052293913 | Z96: =Z94/U94-1 -> 0.046648067 | AA96: =AA94/V94-1 -> 0.034896318 | ... AU96: =AU94/AP94-1 -> -0.11989069
A97: Aesop | B97: Aesop | C97: =C116+C132+C151+C178 -> -57.181598 | D97: =D116+D132+D151+D178 -> -66.618675 | E97: =E116+E132+E151+E178 -> -91.546753 | F97: =F116+F132+F151+F178 -> -103.06991 | G97: =G116+G132+G151+G178 -> -318.41694 | H97: =H116+H132+H151+H178 -> -107.86133 | I97: =I116+I132+I151+I178 -> -101.89817 | J97: =J116+J132+J151+J178 -> -115.2 | ... AU97: =AU116+AU132+AU151+AU178 -> -1140
A98: % receita líquida | B98: % net revenues | C98: =C97/C46 -> -0.86405808 | D98: =D97/D46 -> -0.78824836 | E98: =E97/E46 -> -0.83637813 | F98: =F97/F46 -> -0.60139715 | G98: =G97/G46 -> -0.73787379 | H98: =H97/H46 -> -0.82955595 | I98: =I97/I46 -> -0.80821553 | J98: =J97/J46 -> -0.87738005 | ... AR98: =AR97/AR46 -> -0.85955578 | AS98: - | AT98: - | AU98: =AU97/AU46 -> -0.82621268
A99: % variação anual | B99: % YoY growth | C99: - | D99: - | E99: - | F99: - | G99: - | H99: =H97/C97-1 -> 0.88629438 | I99: =I97/D97-1 -> 0.52957362 | J99: =J97/E97-1 -> 0.25837341 | K99: =K97/F97-1 -> 0.20988211 | L99: =L97/G97-1 -> 0.41217971 | M99: =M97/H97-1 -> 0.17965045 | N99: =N97/I97-1 -> 0.29663246 | O99: =O97/J97-1 -> 0.22984396 | ... AU99: =AU97/AP97-1 -> -0.46567211
A100: Holding | B100: Holding | C100: - | D100: - | E100: - | F100: - | G100: - | H100: - | I100: - | J100: - | K100: - | L100: - | M100: - | N100: - | O100: - | P100: - | Q100: - | R100: - | S100: - | T100: - | U100: - | V100: - | W100: - | X100: - | Y100: - | Z100: - | AA100: - | AB100: - | AC100: - | AD100: - | AE100: - | AF100: - | AG100: =AG158+AG162+AG181+AG135+AG154 -> -118.41415 | AH100: =AH158+AH162+AH181+AH135+AH154 -> -173.31541 | AI100: =AI158+AI162+AI181+AI135+AI154 -> -161.01577 | AJ100: =AJ158+AJ162+AJ181+AJ135+AJ154 -> -155.0123 | AK100: =AK158+AK162+AK181+AK135+AK154 -> -607.67228 | AL100: =AL158+AL162+AL181+AL135+AL154 -> -123.69289 | AM100: =AM158+AM162+AM181+AM135+AM154 -> -244.83166 | AN100: =AN158+AN162+AN181+AN135+AN154 -> -112.101 | ... BB100: =BB158+BB162+BB181+BB135+BB154 -> -86.4
A101: % receita líquida | B101: % net revenues | C101: - | D101: - | E101: - | F101: - | G101: - | H101: - | I101: - | J101: - | K101: - | L101: - | M101: - | N101: - | O101: - | P101: - | Q101: - | R101: - | S101: - | T101: - | U101: - | V101: - | W101: - | X101: - | Y101: - | Z101: - | AA101: - | AB101: - | AC101: - | AD101: - | AE101: - | AF101: - | AG101: =AG100/AG35 -> -0.012523874 | AH101: =AH100/AH35 -> -0.018210822 | AI101: =AI100/AI35 -> -0.016861659 | AJ101: =AJ100/AJ35 -> -0.013313522 | AK101: =AK100/AK35 -> -0.015129516 | AL101: =AL100/AL35 -> -0.014986908 | AM101: =AM100/AM35 -> -0.028133766 | AN101: =AN100/AN35 -> -0.012450682 | ... BB101: =BB100/BB35 -> -0.015191476
A102: % variação anual | B102: % YoY growth | C102: - | D102: - | E102: - | F102: - | G102: - | H102: - | I102: - | J102: - | K102: - | L102: - | M102: - | N102: - | O102: - | P102: - | Q102: - | R102: - | S102: - | T102: - | U102: - | V102: - | W102: - | X102: - | Y102: - | Z102: - | AA102: - | AB102: - | AC102: - | AD102: - | AE102: - | AF102: - | AG102: - | AH102: - | AI102: - | AJ102: - | AK102: - | AL102: =AL100/AG100-1 -> 0.04457857 | AM102: =AM100/AH100-1 -> 0.41263641 | AN102: =AN100/AI100-1 -> -0.30378868 | AO102: =AO100/AJ100-1 -> -0.17941998 | AP102: =AP100/AK100-1 -> 0.00025223163 | AQ102: =AQ100/AL100-1 -> -0.42155121 | AR102: =AR100/AM100-1 -> -0.61308109 | AS102: =AS100/AN100-1 -> -0.33863213 | ... BB102: =BB100/AW100-1 -> -0.26655348
A104: Despesas de Vendas | B104: Selling expenses | C104: -648 | D104: -745.8 | E104: -762.9 | F104: -842.1 | G104: =F104+E104+D104+C104 -> -2998.8 | H104: -694.86438 | I104: -780.86445 | J104: -770.98339 | K104: -863.45687 | L104: =K104+J104+I104+H104 -> -3110.1691 | M104: =M107+M110+M113+M116 -> -736.02438 | N104: =N107+N110+N113+N116 -> -809.65348 | O104: =O107+O110+O113+O116 -> -985.0653 | P104: =P107+P110+P113+P116 -> -1534.559 | Q104: =Q107+Q110+Q113+Q116 -> -4198.6839 | R104: =R107+R110+R113+R116 -> -1282.9865 | S104: =S107+S110+S113+S116 -> -1449.616 | T104: =T107+T110+T113+T116 -> -1534.3647 | ... AK104: =AK107+AK110+AK113+AK116 -> -17837.047 | AL104: =AL107+AL110+AL113+AL116-0.2 -> -3849.4059 | AM104: =AM107+AM110+AM113+AM116 -> -3856.744 | AN104: =AN107+AN110+AN113+AN116-0.33 -> -4120.086 | AO104: =AO107+AO110+AO113+AO116 -> -4334.8 | AP104: =AP107+AP110+AP113+AP116 -> -16160.506 | AQ104: =AQ107+AQ110+AQ113+AQ116-0.1 -> -3690.5 | AR104: =AR107+AR110+AR113+AR116+0.1 -> -3869.6 | AS104: =AS107+AS110+AS113+AS116 -> -3394.732 | AT104: -3647 | AU104: =AU107+AU110+AU113+AU116 -> -14601.732 | AV104: =AV107+AV110+AV113+AV116 -> -1954.2 | AW104: =AW107+AW110+AW113+AW116 -> -2447.2 | AX104: =AX107+AX110+AX113+AX116 -> -2623.9 | AY104: =AY107+AY110+AY113+AY116 -> -3423.7 | AZ104: =AZ107+AZ110+AZ113+AZ116 -> -10449.1 | BA104: =BA107+BA110+BA113+BA116 -> -2244.4 | BB104: =BB107+BB110+BB113+BB116 -> -2344.4
A105: % receita líquida | B105: % net revenues | C105: =C104/C35 -> -0.39468876 | D105: =D104/D35 -> -0.38664524 | E105: =E104/E35 -> -0.38223358 | F105: =F104/F35 -> -0.36104442 | G105: =G104/G35 -> -0.37964299 | H105: =H104/H35 -> -0.41123514 | I105: =I104/I35 -> -0.38548682 | J105: =J104/J35 -> -0.40522621 | ... BB105: =BB104/BB35 -> -0.41220945
A106: % variação anual | B106: % YoY growth | C106: - | D106: - | E106: - | F106: - | G106: - | H106: =H104/C104-1 -> 0.072321568 | I106: =I104/D104-1 -> 0.047015895 | J106: =J104/E104-1 -> 0.010595607 | K106: =K104/F104-1 -> 0.025361438 | L106: =L104/G104-1 -> 0.037137884 | M106: =M104/H104-1 -> 0.059234589 | N106: =N104/I104-1 -> 0.03686815 | O106: =O104/J104-1 -> 0.27767383 | ... BB106: =BB104/AW104-1 -> -0.042007192
A107: Natura & Co América Latina | B107: Natura & Co Latam | C107: =C104-C116 -> -640.34495 | D107: =D104-D116 -> -735.3 | E107: =E104-E116 -> -747.7 | F107: =F104-F116 -> -825.2 | G107: =G104-G116 -> -2948.545 | H107: =H104-H116 -> -678.74249 | I107: =I104-I116 -> -764.69336 | J107: =J104-J116 -> -754.98339 | ... L107: =L104-L116 -> -3042.0711 | M107: -716.94309 | N107: -792.1327 | O107: -758.98127 | P107: -870.259 | Q107: =P107+O107+N107+M107 -> -3138.3161 | R107: -716.69719 | S107: -833.99459 | T107: -886.03335 | U107: -1042.0171 | V107: -3492.4982 | W107: -754.68764 | X107: -935.62032 | Y107: -931.08906 | Z107: -1114.2504 | AA107: =Z107+Y107+X107+W107 -> -3735.6474 | AB107: -1852.4341 | AC107: -1722.9066 | AD107: -2216.171 | AE107: -2540.6158 | AF107: =AE107+AD107+AC107+AB107 -> -8332.1274 | AG107: -2089.8651 | AH107: -2226.4837 | AI107: -2293.6703 | AJ107: -2449.4912 | AK107: -9062.8391 | AL107: -1992.1573 | AM107: -2167.3267 | AN107: -2406.713 | AO107: -2384.2 | AP107: =AO107+AN107+AM107+AL107 -> -8950.3969 | AQ107: -2004 | AR107: -2259.5 | AS107: -2279.05 | AT107: -2341.7 | AU107: =AT107+AS107+AR107+AQ107 -> -8884.25 | AV107: -1954.2 | AW107: -2447.2 | AX107: -2623.9 | AY107: -3188.2 | AZ107: -10213.6 | BA107: -2244.4 | BB107: -2344.4
A108: % receita líquida | B108: % net revenues | C108: =C107/C37 -> -0.40640772 | D108: =D107/D37 -> -0.39866944 | E108: =E107/E37 -> -0.39635424 | F108: =F107/F37 -> -0.38185744 | G108: =G107/G37 -> -0.39485209 | H108: =H107/H37 -> -0.43518119 | I108: =I107/I37 -> -0.40255917 | J108: =J107/J37 -> -0.42623124 | ... BB108: =BB107/BB37 -> -0.41220945
...

Sheet Natura Avon desde l since 2020
C1: IFRS-16 | D1: IFRS-16 | E1: IFRS-16 | F1: IFRS-16 | G1: IFRS-16 | H1: IFRS-16 | I1: IFRS-16 | J1: IFRS-16 | K1: IFRS-16 | L1: IFRS-16 | M1: IFRS-16 | N1: IFRS-16 | O1: IFRS-16 | P1: IFRS-16 | Q1: IFRS-16 | R1: IFRS-16 | S1: IFRS-16 | T1: IFRS-16 | U1: IFRS-16 | V1: IFRS-16 | W1: IFRS-16 | X1: IFRS-16 | Y1: Pro-forma | Z1: Pro-forma | AA1: Pro-forma
C2: 1Q20 | D2: 2Q20 | E2: 3Q20 | F2: 4Q20 | G2: 2020 | H2: 1Q21 | I2: 2Q21 | J2: 3Q21 | K2: 4Q21 | L2: 2021 | M2: 1Q22 | N2: 2Q22 | O2: 3Q22 | P2: 4Q22 | Q2: 2022 | R2: 1Q23 | S2: 2Q23 | T2: 3Q23 | U2: 4Q23 | V2: 2023 | W2: 1Q24 | X2: 2Q24 | Y2: 3Q24 | Z2: 4Q24 | AA2: 2024 | AB2: 1Q25
A3: Demonstração de Resultados | B3: Income Statements | T3: API e suas subsidiárias foram desconsolidadas e estão sendo apresentadas na linha de operações descontinuadas
T4: API and its subsidiaries were deconsolidated and are being presented under the discontinued operations line.
A5: Receita Bruta | B5: Gross Revenues | C5: =C7+C10 -> 8124.6062 | D5: =D7+D10 -> 7416.3224 | E5: =E7+E10 -> 11234.154 | F5: =F7+F10 -> 11700.909 | G5: =G7+G10 -> 38475.992 | H5: =H7+H10 -> 9693.0951 | I5: =I7+I10 -> 9992.5879 | J5: =J7+J10 -> 9869.1941 | ... O5: =O7+O10 -> 9665.137 | P5: =P7+P10+P13 -> 10343.107 | Q5: =Q7+Q10+Q13 -> 37886.365 | R5: =R7+R10+R13 -> 8367.5872 | S5: =S7+S10+S13 -> 9069.6489 | T5: 6764.4 | U5: =U7+U10+U13 -> 8626.9832 | V5: =V7+V10+V13 -> 34718.6 | W5: =W7+W10+W13 -> 8038.9594 | X5: =X7+X10+X13 -> 9648.9983 | Y5: =Y7+Y10+Y13 -> 9833.1205 | Z5: =Z7+Z10+Z13 -> 11636.6 | AA5: =AA7+AA10+AA13 -> 39157.678 | AB5: =AB7+AB10+AB13 -> 8646.4
A6: % variação anual | B6: % YoY growth | C6: - | D6: - | E6: - | F6: - | G6: - | H6: =H5/C5-1 -> 0.19305414 | I6: =I5/D5-1 -> 0.34737777 | J6: =J5/E5-1 -> -0.12150091 | K6: =K5/F5-1 -> -0.031909726 | L6: =L5/G5-1 -> 0.062543462 | M6: =M5/H5-1 -> -0.12369816 | N6: =N5/I5-1 -> -0.060889516 | O6: =O5/J5-1 -> -0.020676162 | ... AA6: =AA5/V5-1 -> 0.12785879
A7: Natura & Co América Latina | B7: Natura & Co Latam | C7: 5593.2083 | D7: 5420.6714 | E7: 8275.9068 | F7: 8294.7467 | G7: 27584.533 | H7: 6857.1875 | I7: 7347.9368 | J7: 7409.161 | K7: 8079.1461 | L7: 29693.431 | M7: 6286.722 | N7: 7284.4 | O7: 7700.042 | P7: 7886.9483 | Q7: 29158.112 | R7: 6444.3922 | S7: 7272.7127 | T7: 6762.7 | U7: 6571.2565 | V7: 27220.754 | W7: 6371.9325 | X7: 7944.6426 | Y7: =AA7-Z7-X7-W7 -> 8045.9249 | Z7: 9454.9 | AA7: 31817.4 | AB7: 6986.1
A8: % receita bruta | B8: % gross revenues | C8: =C7/C5 -> 0.68842824 | D8: =D7/D5 -> 0.73091097 | E8: =E7/E5 -> 0.73667379 | F8: =F7/F5 -> 0.70889764 | G8: =G7/G5 -> 0.71692846 | H8: =H7/H5 -> 0.70743012 | I8: =I7/I5 -> 0.73533872 | J8: =J7/J5 -> 0.75073617 | ... AB8: =AB7/AB5 -> 0.80797789
A9: % variação anual | B9: % YoY growth | C9: - | D9: - | E9: - | F9: - | G9: - | H9: =H7/C7-1 -> 0.22598463 | I9: =I7/D7-1 -> 0.35553998 | J9: =J7/E7-1 -> -0.10473122 | K9: =K7/F7-1 -> -0.025992424 | L9: =L7/G7-1 -> 0.076452196 | M9: =M7/H7-1 -> -0.083192339 | N9: =N7/I7-1 -> -0.0086468927 | O9: =O7/J7-1 -> 0.039259647 | ... AB9: =AB7/W7-1 -> 0.096386383
A10: Avon International | B10: Avon International | C10: 2531.3979 | D10: 1995.651 | E10: 2958.2472 | F10: 3406.1622 | G10: 10891.458 | H10: 2835.9077 | I10: 2644.6511 | J10: 2460.0331 | K10: 3248.39 | L10: 11188.982 | M10: 2207.3551 | N10: 2099.7441 | O10: 1965.095 | P10: 2456.4587 | Q10: 8728.6529 | R10: 1921.0335 | S10: 1795.1244 | T10: 0 | U10: 2038.6266 | V10: 7488.0681 | W10: 1662.9955 | X10: 1701.0089 | Y10: =AA10-Z10-X10-W10 -> 1786.4956 | Z10: 2181.7 | AA10: 7332.2 | AB10: 1660.3
A11: % receita bruta | B11: % gross revenues | C11: =C10/C5 -> 0.31157176 | D11: =D10/D5 -> 0.26908903 | E11: =E10/E5 -> 0.26332621 | F11: =F10/F5 -> 0.29110236 | G11: =G10/G5 -> 0.28307154 | H11: =H10/H5 -> 0.29256988 | I11: =I10/I5 -> 0.26466128 | J11: =J10/J5 -> 0.24926383 | ... AB11: =AB10/AB5 -> 0.19202211
A12: % variação anual | B12: % YoY growth | C12: - | D12: - | E12: - | F12: - | G12: - | H12: =H10/C10-1 -> 0.12029313 | I12: =I10/D10-1 -> 0.32520722 | J12: =J10/E10-1 -> -0.1684153 | K12: =K10/F10-1 -> -0.046319644 | L12: =L10/G10-1 -> 0.027317146 | M12: =M10/H10-1 -> -0.22164071 | N12: =N10/I10-1 -> -0.20604117 | O12: =O10/J10-1 -> -0.20119164 | ... AB12: =AB10/W10-1 -> -0.0016208413
A13: Corporativo | B13: Corporate | C13: 0 | D13: 0 | E13: 0 | F13: 0 | G13: 0 | H13: 0 | I13: 0 | J13: 0 | K13: 0 | L13: 0 | M13: 0 | N13: 0 | O13: 0 | P13: -0.3 | Q13: -0.4 | R13: 2.1615664 | S13: 1.8117957 | T13: 0.7 | U13: 17.1 | V13: 9.777954 | W13: 4.0315118 | X13: 3.3467597 | Y13: ='Histórico | Historic data'!AX20 -> 0.7 | Z13: ='Histórico | Historic data'!AY20 -> 0 | AA13: =Z13+Y13+X13+W13 -> 8.0782715 | AB13: 0
A15: Impostos e deduções | B15: Taxes and deductions | C15: =C23-C5 -> -1840.7531 | D15: =D23-D5 -> -1790.5574 | E15: =E23-E5 -> -2693.1975 | F15: =F23-F5 -> -2511.7639 | G15: =G23-G5 -> -8836.2719 | H15: =H23-H5 -> -2143.6769 | I15: =I23-I5 -> -2254.9122 | J15: =J23-J5 -> -2263.9855 | ... AB15: =AB23-AB5 -> -1967
A16: % receita bruta | B16: % gross revenues | C16: =C15/C5 -> -0.22656521 | D16: =D15/D5 -> -0.24143467 | E16: =E15/E5 -> -0.239733 | F16: =F15/F5 -> -0.214664 | G16: =G15/G5 -> -0.22965677 | H16: =H15/H5 -> -0.22115505 | I16: =I15/I5 -> -0.22565848 | J16: =J15/J5 -> -0.22939923 | ... AB16: =AB15/AB5 -> -0.22749352
A17: Natura & Co América Latina | B17: Natura & Co Latam | C17: =C25-C7 -> -1430.8726 | D17: =D25-D7 -> -1444.924 | E17: =E25-E7 -> -2192.2865 | F17: =F25-F7 -> -1974.1057 | G17: =G25-G7 -> -7042.1888 | H17: =H25-H7 -> -1671.2425 | I17: =I25-I7 -> -1814.2658 | J17: =J25-J7 -> -1857.6734 | ... P17: =P25-P7 -> -1943.7483 | Q17: =M17+N17+O17+P17 -> -7130.8141 | R17: =R25-R7 -> -1580.6922 | S17: =S25-S7 -> -1810.8795 | T17: =T25-T7 -> -1673.5 | U17: =U25-U7 -> -1689.0457 | V17: =U17+T17+S17+R17 -> -6754.1174 | W17: =W25-W7 -> -1667.3786 | X17: =X25-X7 -> -2022.2002 | Y17: =Y25-Y7 -> -1949.5212 | Z17: =Z25-Z7 -> -2294.8 | AA17: =AA25-AA7 -> -7933.9 | AB17: =AB25-AB7 -> -1701
A18: % receita bruta | B18: % gross revenues | C18: =C17/C7 -> -0.25582323 | D18: =D17/D7 -> -0.26655812 | E18: =E17/E7 -> -0.26489986 | F18: =F17/F7 -> -0.2379947 | G18: =G17/G7 -> -0.25529483 | H18: =H17/H7 -> -0.24372129 | I18: =I17/I7 -> -0.2469082 | J18: =J17/J7 -> -0.25072655 | ... AB18: =AB17/AB7 -> -0.24348349
A19: Avon International | B19: Avon International | C19: =C28-C10 -> -409.88054 | D19: =D28-D10 -> -345.63338 | E19: =E28-E10 -> -500.91094 | F19: =F28-F10 -> -537.65816 | G19: =G28-G10 -> -1794.083 | H19: =H28-H10 -> -472.43437 | I19: =I28-I10 -> -440.64635 | J19: =J28-J10 -> -406.3121 | ... P19: =P28-P10 -> -393.85869 | Q19: =M19+N19+O19+P19 -> -1532.7125 | R19: =R28-R10 -> -314.43346 | S19: =S28-S10 -> -284.8049 | T19: =T28-T10 -> 0 | U19: =U28-U10 -> -324.56786 | V19: =V28-V10 -> -1201.3233 | W19: =W28-W10 -> -266.32818 | X19: =X28-X10 -> -274.16613 | Y19: =Y28-Y10 -> -290.80569 | ... AB19: =AB28-AB10 -> -266
A20: % receita bruta | B20: % gross revenues | C20: =C19/C10 -> -0.16191865 | D20: =D19/D10 -> -0.1731933 | E20: =E19/E10 -> -0.16932694 | F20: =F19/F10 -> -0.15784867 | G20: =G19/G10 -> -0.16472386 | H20: =H19/H10 -> -0.16659018 | I20: =I19/I10 -> -0.16661795 | J20: =J19/J10 -> -0.1651653 | ... S20: =S19/S10 -> -0.15865468 | T20: 0 | U20: =U19/U10 -> -0.15920908 | V20: =V19/V10 -> -0.16043168 | W20: =W19/W10 -> -0.16014967 | X20: =X19/X10 -> -0.16117854 | Y20: =Y19/Y10 -> -0.16277996 | Z20: =Z19/Z10 -> -0.15410001 | AA20: =AA19/AA10 -> -0.15922915 | AB20: =AB19/AB10 -> -0.16021201
A21: Corporativo | B21: Corporate | C21: 0 | D21: 0 | E21: 0 | F21: 0 | G21: 0 | H21: 0 | I21: 0 | J21: 0 | K21: 0 | L21: 0 | M21: 0 | N21: 0 | O21: 0 | P21: =P30-P12 -> 0.0054256904 | Q21: =Q30-Q12 -> -0.0087865662 | R21: =R30-R12 -> 0.0019282583 | S21: 0 | T21: 0 | U21: =U13-U31 -> 0 | V21: =V13-V31 -> 0.067575588 | W21: =W13-W31 -> -9.094947e-13 | X21: =X13-X31 -> 4.5474735e-13 | Y21: =Y13-Y31 -> 0 | Z21: =Z13-Z31 -> 0 | AA21: =AA13-AA31 -> -4.5474735e-13 | AB21: =AB13-AB31 -> 0
A23: Receita Líquida | B23: Net Revenues | C23: =C25+C28 -> 6283.8531 | D23: =D25+D28 -> 5625.7651 | E23: =E25+E28 -> 8540.9565 | F23: =F25+F28 -> 9189.145 | G23: =G25+G28 -> 29639.72 | H23: =H25+H28 -> 7549.4182 | I23: =I25+I28 -> 7737.6758 | J23: =J25+J28 -> 7605.2086 | ... O23: =O25+O28 -> 7425.125 | P23: =P25+P28+P31 -> 8005.9 | Q23: =Q25+Q28+Q31 -> 29223.339 | R23: =R25+R28+R31 -> 6472.4155 | S23: =S25+S28+S31 -> 6973.7485 | T23: 5090 | U23: =U25+U28+U31 -> 6613.3696 | V23: =V25+V28+V31 -> 26737.3 | W23: =W25+W28+W31 -> 6105.2526 | X23: =X25+X28+X31 -> 7352.632 | Y23: =Y25+Y28+Y31 -> 7592.7937 | Z23: =Z25+Z28+Z31 -> 9005.6 | AA23: =AA25+AA28+AA31 -> 30056.278 | AB23: =AB25+AB28+AB31 -> 6679.4
A24: % variação anual | B24: % YoY growth | C24: - | D24: - | E24: - | F24: - | G24: - | H24: =H23/C23-1 -> 0.20139954 | I24: =I23/D23-1 -> 0.37539974 | J24: =J23/E23-1 -> -0.10956009 | K24: =K23/F23-1 -> -0.036861076 | L24: =L23/G23-1 -> 0.070952295 | M24: =M23/H23-1 -> -0.12662199 | N24: =N23/I23-1 -> -0.069640805 | O24: =O23/J23-1 -> -0.02367898 | ... T24: =T23/O23-1 -> -0.31448966 | U24: -0.24099598 | V24: =V23/Q23-1 -> -0.085070317 | W24: =W23/R23-1 -> -0.056727335 | X24: =X23/S23-1 -> 0.054329959 | Y24: =Y23/T23-1 -> 0.49170799 | Z24: =Z23/U23-1 -> 0.3617264 | AA24: =AA23/V23-1 -> 0.12413289 | AB24: =AB23/W23-1 -> 0.094041543
A25: Natura & Co América Latina | B25: Natura & Co Latam | C25: 4162.3357 | D25: 3975.7474 | E25: 6083.6203 | F25: 6320.6409 | G25: =F25+E25+D25+C25 -> 20542.344 | H25: 5185.9449 | I25: 5533.671 | J25: 5551.4876 | K25: 6142.2974 | L25: =K25+J25+I25+H25 -> 22413.401 | M25: 4751.5204 | N25: 5555.0449 | O25: 5777.533 | P25: 5943.2 | Q25: =P25+O25+N25+M25 -> 22027.298 | R25: 4863.7 | S25: 5461.8332 | T25: 5089.2 | U25: 4882.2109 | V25: 20440.845 | W25: 4704.5538 | X25: 5922.4425 | Y25: =AA25-Z25-X25-W25 -> 6096.4037 | Z25: 7160.1 | AA25: 23883.5 | AB25: 5285.1
A26: % receita Líquida | B26: % net revenues | C26: =C25/C23 -> 0.66238591 | D26: =D25/D23 -> 0.70670342 | E26: =E25/E23 -> 0.71228793 | F26: =F25/F23 -> 0.68783776 | G26: =G25/G23 -> 0.69306811 | H26: =H25/H23 -> 0.68693306 | I26: =I25/I23 -> 0.71515933 | J26: =J25/J23 -> 0.72995862 | ... T26: =T25/T23 -> 0.99984283 | U26: 0.61910498 | V26: =V25/V23 -> 0.7645067 | W26: =W25/W23 -> 0.7705748 | X26: =X25/X23 -> 0.80548604 | Y26: =Y25/Y23 -> 0.80291971 | Z26: =Z25/Z23 -> 0.79507196 | AA26: =AA25/AA23 -> 0.79462599 | AB26: =AB25/AB23 -> 0.79125371
A27: % variação anual | B27: % YoY growth | C27: - | D27: - | E27: - | F27: - | G27: - | H27: =H25/C25-1 -> 0.24592183 | I27: =I25/D25-1 -> 0.39185678 | J27: =J25/E25-1 -> -0.08746974 | K27: =K25/F25-1 -> -0.028216049 | L27: =L25/G25-1 -> 0.091082914 | M27: =M25/H25-1 -> -0.083769603 | N27: =N25/I25-1 -> 0.0038625183 | O27: =O25/J25-1 -> 0.040717989 | ... T27: =T25/O25-1 -> -0.11913961 | U27: -0.17852335 | V27: =V25/Q25-1 -> -0.072022152 | W27: =W25/R25-1 -> -0.032721213 | X27: =X25/S25-1 -> 0.084332351 | Y27: =Y25/T25-1 -> 0.19791003 | Z27: =Z25/U25-1 -> 0.46656918 | AA27: =AA25/V25-1 -> 0.16842039 | AB27: =AB25/W25-1 -> 0.1234009
A28: Avon International | B28: Avon International | C28: 2121.5174 | D28: 1650.0176 | E28: 2457.3363 | F28: 2868.5041 | G28: =F28+E28+D28+C28 -> 9097.3753 | H28: 2363.4733 | I28: 2204.0048 | J28: 2053.721 | K28: 2708.1258 | L28: =K28+J28+I28+H28 -> 9329.3249 | M28: 1841.9755 | N28: 1643.7729 | O28: 1647.592 | P28: 2062.6 | Q28: =P28+O28+N28+M28 -> 7195.9404 | R28: 1606.6 | S28: 1510.3195 | T28: 0 | U28: 1714.0588 | V28: 6286.7448 | W28: 1396.6673 | X28: 1426.8428 | Y28: =AA28-Z28-X28-W28 -> 1495.6899 | Z28: 1845.5 | AA28: 6164.7 | AB28: 1394.3
A29: % receita Líquida | B29: % net revenues | C29: =C28/C23 -> 0.33761409 | D29: =D28/D23 -> 0.29329658 | E29: =E28/E23 -> 0.28771207 | F29: =F28/F23 -> 0.31216224 | G29: =G28/G23 -> 0.30693189 | H29: =H28/H23 -> 0.31306694 | I29: =I28/I23 -> 0.28484067 | J29: =J28/J23 -> 0.27004138 | ... T29: =T28/T23 -> 0 | U29: 0.21736263 | V29: =V28/V23 -> 0.23513013 | W29: =W28/W23 -> 0.22876486 | X29: =X28/X23 -> 0.19405878 | Y29: =Y28/Y23 -> 0.19698809 | Z29: =Z28/Z23 -> 0.20492804 | AA29: =AA28/AA23 -> 0.20510523 | AB29: =AB28/AB23 -> 0.20874629
A30: % variação anual | B30: % YoY growth | C30: - | D30: - | E30: - | F30: - | G30: - | H30: =H28/C28-1 -> 0.11404853 | I30: =I28/D28-1 -> 0.3357462 | J30: =J28/E28-1 -> -0.1642491 | K30: =K28/F28-1 -> -0.055910069 | L30: =L28/G28-1 -> 0.025496317 | M30: =M28/H28-1 -> -0.2206489 | N30: =N28/I28-1 -> -0.25418814 | O30: =O28/J28-1 -> -0.19775276 | ... T30: =T28/O28-1 -> -1 | U30: -0.1689615 | V30: =V28/Q28-1 -> -0.12634841 | W30: =W28/R28-1 -> -0.13066894 | X30: =X28/S28-1 -> -0.055270914 | Y30: =Y28/T28-1 -> #DIV/0! | Z30: =Z28/U28-1 -> 0.07668421 | AA30: =AA28/V28-1 -> -0.019413029 | AB30: =AB28/W28-1 -> -0.0016949452
A31: Corporativo | B31: Corporate | C31: 0 | D31: 0 | E31: 0 | F31: 0 | G31: 0 | H31: 0 | I31: 0 | J31: 0 | K31: 0 | L31: 0 | M31: 0 | N31: 0 | O31: 0 | P31: 0.1 | Q31: 0.1 | R31: 2.1155004 | S31: 1.5957851 | T31: 0.7 | U31: 17.1 | V31: 9.7103784 | W31: 4.0315118 | X31: 3.3467597 | Y31: ='Histórico | Historic data'!AX49 -> 0.7 | Z31: ='Histórico | Historic data'!AY49 -> 0 | AA31: =Z31+Y31+X31+W31 -> 8.0782715 | AB31: 0
A33: CMV | B33: COGS | C33: =C44-C23 -> -2645.2966 | D33: =D44-D23 -> -2141.0289 | E33: =E44-E23 -> -3362.1985 | F33: =F44-F23 -> -3736.1974 | G33: =G44-G23 -> -11884.721 | H33: =H44-H23 -> -2993.1904 | I33: =I44-I23 -> -3019.6954 | J33: =J44-J23 -> -2953.1594 | ... AB33: =AB44-AB23 -> -2253.3
A34: % receita Líquida | B34: % net revenues | C34: =C33/C23 -> -0.42096729 | D34: =D33/D23 -> -0.3805756 | E34: =E33/E23 -> -0.39365597 | F34: =F33/F23 -> -0.40658815 | G34: =G33/G23 -> -0.4009728 | H34: =H33/H23 -> -0.39647961 | I34: =I33/I23 -> -0.39025872 | J34: =J33/J23 -> -0.38830748 | ... AB34: =AB33/AB23 -> -0.33735066
A35: % variação anual | B35: % YoY growth | C35: - | D35: - | E35: - | F35: - | G35: - | H35: =H33/C33-1 -> 0.13151409 | I35: =I33/D33-1 -> 0.41039452 | J35: =J33/E33-1 -> -0.12165823 | K35: =K33/F33-1 -> -0.045752342 | L35: =L33/G33-1 -> 0.054404422 | M35: =M33/H33-1 -> -0.11144375 | N35: =N33/I33-1 -> -0.022321271 | O35: =O33/J33-1 -> -0.0023166383 | ... AB35: =AB33/W33-1 -> 0.05933965
A36: Natura & Co América Latina | B36: Natura & Co Latam | C36: =C47-C25 -> -1718.0934 | D36: =D47-D25 -> -1508.4989 | E36: =E47-E25 -> -2384.0139 | F36: =F47-F25 -> -2452.1509 | G36: =G47-G25 -> -8062.757 | H36: =H47-H25 -> -2047.0304 | I36: =I47-I25 -> -2177.4328 | J36: =J47-J25 -> -2158.9091 | ... T36: =T47-T25 -> -1839.1 | U36: -1797.4193 | V36: =R36+S36+T36+U36 -> -7335.1971 | W36: -1603.9854 | X36: -2052.7109 | Y36: =Y47-Y25 -> -1987.0038 | Z36: =Z47-Z25 -> -2623.2 | AA36: =AA47-AA25 -> -8266.9 | AB36: =AB47-AB25 -> -1739.3
A37: % receita Líquida | B37: % net revenues | C37: =C36/C25 -> -0.41277146 | D37: =D36/D25 -> -0.37942523 | E37: =E36/E25 -> -0.39187421 | F37: =F36/F25 -> -0.38795922 | G37: =G36/G25 -> -0.39249449 | H37: =H36/H25 -> -0.3947266 | I37: =I36/I25 -> -0.39348795 | J37: =J36/J25 -> -0.38888839 | ... AB37: =AB36/AB25 -> -0.329095
A38: % variação anual | B38: % YoY growth | C38: - | D38: - | E38: - | F38: - | G38: - | H38: =H36/C36-1 -> 0.19145469 | I38: =I36/D36-1 -> 0.44344347 | J38: =J36/E36-1 -> -0.094422605 | K38: =K36/F36-1 -> -0.00099261205 | L38: =L36/G36-1 -> 0.09554203 | M38: =M36/H36-1 -> -0.06446841 | N38: =N36/I36-1 -> 0.044370636 | O38: =O36/J36-1 -> 0.056436344 | ... AB38: =AB36/W36-1 -> 0.084361518
A39: Avon International | B39: Avon International | C39: =C50-C28 -> -927.20321 | D39: =D50-D28 -> -632.53004 | E39: =E50-E28 -> -978.18466 | F39: =F50-F28 -> -1284.0465 | G39: =G50-G28 -> -3821.9644 | H39: =H50-H28 -> -946.15995 | I39: =I50-I28 -> -842.2626 | J39: =J50-J28 -> -794.25034 | ... S39: =S50-S28 -> -553.58818 | T39: 0 | U39: -645.03125 | V39: =R39+S39+T39+U39 -> -1769.8392 | W39: -519.79901 | X39: -555.37952 | Y39: =Y50-Y28 -> -547.22147 | Z39: =Z50-Z28 -> -748.6 | AA39: =AA50-AA28 -> -2371 | AB39: =AB50-AB28 -> -514
A40: % receita Líquida | B40: % net revenues | C40: =C39/C28 -> -0.4370472 | D40: =D39/D28 -> -0.38334744 | E40: =E39/E28 -> -0.39806708 | F40: =F39/F28 -> -0.44763629 | G40: =G39/G28 -> -0.42011726 | H40: =H39/H28 -> -0.40032606 | I40: =I39/I28 -> -0.38215098 | J40: =J39/J28 -> -0.38673721 | ... S40: =S39/S28 -> -0.36653713 | T40: 0 | U40: =U39/U28 -> -0.37631805 | V40: =V39/V28 -> -0.28151918 | W40: =W39/W28 -> -0.37217097 | X40: =X39/X28 -> -0.38923666 | Y40: =Y39/Y28 -> -0.36586558 | Z40: =Z39/Z28 -> -0.40563533 | AA40: =AA39/AA28 -> -0.38460915 | AB40: =AB39/AB28 -> -0.36864376
A41: % variação anual | B41: % YoY growth | C41: - | D41: - | E41: - | F41: - | G41: - | H41: =H39/C39-1 -> 0.020445079 | I41: =I39/D39-1 -> 0.33157723 | J41: =J39/E39-1 -> -0.1880364 | K41: =K39/F39-1 -> -0.13123025 | L41: =L39/G39-1 -> -0.032378839 | M41: =M39/H39-1 -> -0.21307557 | N41: =N39/I39-1 -> -0.19473442 | O41: =O39/J39-1 -> -0.16201735 | ... AB41: =AB39/W39-1 -> -0.011156251
A42: Corporativo | B42: Corporate | C42: 0 | D42: 0 | E42: 0 | F42: 0 | G42: 0 | H42: 0 | I42: 0 | J42: 0 | K42: 0 | L42: 0 | M42: 0 | N42: 0 | O42: 0 | P42: 0 | Q42: 0 | R42: =R33-R36-R39 -> -0.65771298 | S42: =S33-S36-S39 -> -0.53782895 | T42: 0 | U42: =U33-U36-U39 -> -2.1 | V42: =V33-V36-V39 -> -1592.3776 | W42: =W33-W36-W39 -> -3.2954593 | X42: =X33-X36-X39 -> -2.8814657 | Y42: =Y33-Y36-Y39 -> -0.7 | Z42: =Z33-Z36-Z39 -> 0 | AA42: =AA33-AA36-AA39 -> -6.8769249 | AB42: =AB33-AB36-AB39 -> 0
A44: Lucro Bruto | B44: Gross Profit | C44: =C47+C50 -> 3638.5565 | D44: =D47+D50 -> 3484.7362 | E44: =E47+E50 -> 5178.758 | F44: =F47+F50 -> 5452.9476 | G44: =G47+G50 -> 17754.998 | H44: =H47+H50 -> 4556.2279 | I44: =I47+I50 -> 4717.9803 | J44: =J47+J50 -> 4652.0492 | ... N44: =N47+N50 -> 4246.5258 | O44: =O47+O50+O53 -> 4478.807 | P44: =P47+P50+P53 -> 4793.4 | Q44: =Q47+Q50+Q53 -> 17452.611 | R44: =R47+R50+R53 -> 4158.3448 | S44: =S47+S50+S53 -> 4463.1378 | T44: =T47+T50+T53 -> 3250.6 | U44: =U47+U50+U53 -> 4168.8191 | V44: =V47+V50+V53 -> 16039.886 | ... AB44: =AB47+AB50+AB53 -> 4426.1
A45: % margem bruta | B45: % gross margin | C45: =C44/C23 -> 0.57903271 | D45: =D44/D23 -> 0.6194244 | E45: =E44/E23 -> 0.60634403 | F45: =F44/F23 -> 0.59341185 | G45: =G44/G23 -> 0.5990272 | H45: =H44/H23 -> 0.60352039 | I45: =I44/I23 -> 0.60974128 | J45: =J44/J23 -> 0.61169252 | ... AB45: =AB44/AB23 -> 0.66264934
A46: % variação anual | B46: % YoY growth | C46: - | D46: - | E46: - | F46: - | G46: - | H46: =H44/C44-1 -> 0.25220754 | I46: =I44/D44-1 -> 0.35389887 | J46: =J44/E44-1 -> -0.10170563 | K46: =K44/F44-1 -> -0.030769045 | L46: =L44/G44-1 -> 0.082028999 | M46: =M44/H44-1 -> -0.13659325 | N46: =N44/I44-1 -> -0.099927192 | O46: =O44/J44-1 -> -0.037239972 | ... AB46: =AB44/W44-1 -> 0.11259622
A47: Natura & Co América Latina | B47: Natura & Co Latam | C47: 2444.2423 | D47: 2467.2486 | E47: 3699.6064 | F47: 3868.49 | G47: =F47+E47+D47+C47 -> 12479.587 | H47: 3138.9145 | I47: 3356.2382 | J47: 3392.5785 | K47: 3692.5805 | L47: =K47+J47+I47+H47 -> 13580.312 | M47: 2836.4588 | N47: 3280.998 | O47: 3496.783 | P47: 3532.9 | Q47: =P47+O47+N47+M47 -> 13147.14 | R47: 3121.5068 | S47: 3505.3485 | T47: 3250.1 | U47: 3084.7916 | V47: =R47+S47+T47+U47 -> 12961.747 | W47: 3100.5685 | X47: 3869.7316 | Y47: =AA47-Z47-X47-W47 -> 4109.3999 | Z47: 4536.9 | AA47: 15616.6 | AB47: 3545.8
A48: % margem bruta | B48: % gross margin | C48: =C47/C25 -> 0.58722854 | D48: =D47/D25 -> 0.62057477 | E48: =E47/E25 -> 0.60812579 | F48: =F47/F25 -> 0.61204078 | G48: =G47/G25 -> 0.60750551 | H48: =H47/H25 -> 0.6052734 | I48: =I47/I25 -> 0.60651205 | J48: =J47/J25 -> 0.61111161 | ... AB48: =AB47/AB25 -> 0.670905
A49: % variação anual | B49: % YoY growth | C49: - | D49: - | E49: - | F49: - | G49: - | H49: =H47/C47-1 -> 0.28420757 | I49: =I47/D47-1 -> 0.36031619 | J49: =J47/E47-1 -> -0.082989337 | K49: =K47/F47-1 -> -0.045472388 | L49: =L47/G47-1 -> 0.088201987 | M49: =M47/H47-1 -> -0.096356797 | N49: =N47/I47-1 -> -0.022418008 | O49: =O47/J47-1 -> 0.030715421 | ... AB49: =AB47/W47-1 -> 0.14359674
A50: Avon International | B50: Avon International | C50: 1194.3141 | D50: 1017.4876 | E50: 1479.1516 | F50: 1584.4576 | G50: =F50+E50+D50+C50 -> 5275.4109 | H50: 1417.3133 | I50: 1361.7422 | J50: 1259.4707 | K50: 1592.585 | L50: =K50+J50+I50+H50 -> 5631.1112 | M50: 1097.4191 | N50: 965.52783 | O50: 982.024 | P50: 1260.4 | Q50: =P50+O50+N50+M50 -> 4305.371 | R50: 1035.3802 | S50: 956.73134 | T50: 0 | U50: 1069.0275 | V50: =R50+S50+T50+U50 -> 3061.1391 | W50: 876.86827 | X50: 871.46326 | Y50: =AA50-Z50-X50-W50 -> 948.46848 | Z50: 1096.9 | AA50: 3793.7 | AB50: 880.3
A51: % margem bruta | B51: % gross margin | C51: =C50/C28 -> 0.5629528 | D51: =D50/D28 -> 0.61665256 | E51: =E50/E28 -> 0.60193292 | F51: =F50/F28 -> 0.55236371 | G51: =G50/G28 -> 0.57988274 | H51: =H50/H28 -> 0.59967394 | I51: =I50/I28 -> 0.61784902 | J51: =J50/J28 -> 0.61326279 | ... S51: =S50/S28 -> 0.63346287 | T51: 0 | U51: =U50/U28 -> 0.62368195 | V51: =V50/V28 -> 0.48691957 | W51: =W50/W28 -> 0.62782903 | X51: =X50/X28 -> 0.61076334 | Y51: =Y50/Y28 -> 0.63413442 | Z51: =Z50/Z28 -> 0.59436467 | AA51: =AA50/AA28 -> 0.61539085 | AB51: =AB50/AB28 -> 0.63135624
A52: % variação anual | B52: % YoY growth | C52: - | D52: - | E52: - | F52: - | G52: - | H52: =H50/C50-1 -> 0.18671737 | I52: =I50/D50-1 -> 0.33833787 | J52: =J50/E50-1 -> -0.1485182 | K52: =K50/F50-1 -> 0.0051295082 | L52: =L50/G50-1 -> 0.067426091 | M52: =M50/H50-1 -> -0.22570466 | N52: =N50/I50-1 -> -0.29096136 | O52: =O50/J50-1 -> -0.22028831 | ... AB52: =AB50/W50-1 -> 0.003913625
A53: Corporativo | B53: Corporate | C53: 0 | D53: 0 | E53: 0 | F53: 0 | G53: 0 | H53: 0 | I53: 0 | J53: 0 | K53: 0 | L53: 0 | M53: 0 | N53: 0 | O53: 0 | P53: 0.1 | Q53: 0.1 | R53: 1.4577874 | S53: 1.0579561 | T53: 0.5 | U53: 15 | V53: 17 | W53: 0.73605254 | X53: 0.46529406 | Y53: ='Histórico | Historic data'!AX83 -> 0 | Z53: ='Histórico | Historic data'!AY83 -> 0 | AA53: =Z53+Y53+X53+W53 -> 1.2013466 | AB53: ='Histórico | Historic data'!BA83 -> 0
A55: Despesas Operacionais | B55: Operating expenses | C55: =C68+C79+C92+C105+C109+C113 -> -4110.3346 | D55: =D68+D79+D92+D105+D109+D113 -> -3512.9153 | E55: =E68+E79+E92+E105+E109+E113 -> -4610.6434 | F55: =F68+F79+F92+F105+F109+F113 -> -5208.8796 | G55: =G68+G79+G92+G105+G109+G113 -> -17442.773 | H55: =H68+H79+H92+H105+H109+H113 -> -4899.9666 | I55: =I68+I79+I92+I105+I109+I113 -> -5233.702 | J55: =J68+J79+J92+J105+J109+J113 -> -4900.6264 | ... AB55: =AB68+AB79+AB92+AB105+AB109+AB113 -> -4167.1
A56: % receita líquida | B56: % net revenues | C56: =C55/C23 -> -0.65411055 | D56: =D55/D23 -> -0.62443335 | E56: =E55/E23 -> -0.53982752 | F56: =F55/F23 -> -0.56685139 | G56: =G55/G23 -> -0.58849318 | H56: =H55/H23 -> -0.64905222 | I56: =I55/I23 -> -0.676392 | J56: =J55/J23 -> -0.64437765 | ... AB56: =AB55/AB23 -> -0.6238734
A57: % variação anual | B57: % YoY growth | C57: - | D57: - | E57: - | F57: - | G57: - | H57: =H55/C55-1 -> 0.19210896 | I57: =I55/D55-1 -> 0.48984574 | J57: =J55/E55-1 -> 0.062894274 | K57: =K55/F55-1 -> 0.028533258 | L57: =L55/G55-1 -> 0.06816309 | M57: =M55/H55-1 -> -0.17948441 | N57: =N55/I55-1 -> -0.1896909 | O57: =O55/J55-1 -> -0.1005307 | ... AB57: =AB55/W55-1 -> 0.090019728
A58: Natura & Co América Latina | B58: Natura & Co Latam | C58: =C71+C82+C95+C116 -> -2431.3807 | D58: =D71+D82+D95+D116 -> -2258.3919 | E58: =E71+E82+E95+E116 -> -2968.6082 | F58: =F71+F82+F95+F116 -> -3326.4841 | G58: =G71+G82+G95+G116 -> -10984.865 | H58: =H71+H82+H95+H116 -> -2777.8625 | I58: =I71+I82+I95+I116 -> -3012.0812 | J58: =J71+J82+J95+J116 -> -2882.5231 | ... AB58: =AB71+AB82+AB95+AB116 -> -3103.8
A59: % receita líquida | B59: % net revenues | C59: =C58/C25 -> -0.58413855 | D59: =D58/D25 -> -0.56804209 | E59: =E58/E25 -> -0.48796737 | F59: =F58/F25 -> -0.52628904 | G59: =G58/G25 -> -0.53474251 | H59: =H58/H25 -> -0.53565214 | I59: =I58/I25 -> -0.54431881 | J59: =J58/J25 -> -0.51923437 | ... AB59: =AB58/AB25 -> -0.58727366
A60: % variação anual | B60: % YoY growth | C60: - | D60: - | E60: - | F60: - | G60: - | H60: =H58/C58-1 -> 0.1425041 | I60: =I58/D58-1 -> 0.33372833 | J60: =J58/E58-1 -> -0.028998458 | K60: =K58/F58-1 -> -0.042910987 | L60: =L58/G58-1 -> 0.079240909 | M60: =M58/H58-1 -> -0.041420594 | N60: =N58/I58-1 -> -0.002292237 | O60: =O58/J58-1 -> 0.083621484 | ... AB60: =AB58/W58-1 -> 0.19543785
A61: Avon International | B61: Avon International | C61: =C74+C85+C98+C119 -> -1350.4918 | D61: =D74+D85+D98+D119 -> -1170.7869 | E61: =E74+E85+E98+E119 -> -1542.2061 | F61: =F74+F85+F98+F119 -> -1711.0621 | G61: =G74+G85+G98+G119 -> -5774.5469 | H61: =H74+H85+H98+H119 -> -1613.97 | I61: =I74+I85+I98+I119 -> -1616.301 | J61: =J74+J85+J98+J119 -> -1417.4799 | ... AB61: =AB74+AB85+AB98+AB119 -> -1031.8
A62: % receita líquida | B62: % net revenues | C62: =C61/C28 -> -0.63656884 | D62: =D61/D28 -> -0.70956023 | E62: =E61/E28 -> -0.62759262 | F62: =F61/F28 -> -0.59649978 | G62: =G61/G28 -> -0.63474867 | H62: =H61/H28 -> -0.68288058 | I62: =I61/I28 -> -0.73334733 | J62: =J61/J28 -> -0.69020082 | ... S62: =S61/S28 -> -0.81675899 | T62: 0 | U62: =U61/U28 -> -1.0229404 | V62: =V61/V28 -> -0.81822615 | W62: =W61/W28 -> -0.82603942 | X62: =X61/X28 -> -0.75397125 | Y62: =Y61/Y28 -> -0.73056542 | Z62: =Z61/Z28 -> -0.63814684 | AA62: =AA61/AA28 -> -0.72994631 | AB62: =AB61/AB28 -> -0.74001291
A63: % variação anual | B63: % YoY growth | C63: - | D63: - | E63: - | F63: - | G63: - | H63: =H61/C61-1 -> 0.19509792 | I63: =I61/D61-1 -> 0.38052538 | J63: =J61/E61-1 -> -0.080875179 | K63: =K61/F61-1 -> -0.09983513 | L63: =L61/G61-1 -> 0.071597304 | M63: =M61/H61-1 -> -0.2348034 | N63: =N61/I61-1 -> -0.38630993 | O63: =O61/J61-1 -> -0.17297029 | ... AB63: =AB61/W61-1 -> -0.10566177
A64: Corporativo | B64: Corporate | C64: - | D64: - | E64: - | F64: - | G64: - | H64: =H105+H109+H122+H88+H101 -> -118.41415 | I64: =I105+I109+I122+I88+I101 -> -173.31541 | J64: =J105+J109+J122+J88+J101 -> -161.01577 | K64: =K105+K109+K122+K88+K101 -> -155.0123 | L64: =L105+L109+L122+L88+L101 -> -607.67228 | M64: =M105+M109+M122+M88+M101 -> -122.69289 | N64: =N105+N109+N122+N88+N101 -> -243.83166 | O64: =O105+O109+O122+O88+O101 -> -112.101 | ... AB64: =AB105+AB109+AB122+AB88+AB101 -> -31.5
A65: % receita líquida | B65: % net revenues | C65: - | D65: - | E65: - | F65: - | G65: - | H65: =H64/H23 -> -0.015685202 | I65: =I64/I23 -> -0.022398898 | J65: =J64/J23 -> -0.021171775 | K65: =K64/K23 -> -0.017514677 | L65: =L64/L23 -> -0.01914367 | M65: =M64/M23 -> -0.018608169 | N65: =N64/N23 -> -0.03387107 | O65: =O64/O23 -> -0.015097524 | ... AB65: =AB64/AB23 -> -0.0047159925
A66: % variação anual | B66: % YoY growth | C66: - | D66: - | E66: - | F66: - | G66: - | H66: - | I66: - | J66: - | K66: - | L66: - | M66: =M64/H64-1 -> 0.036133633 | N66: =N64/I64-1 -> 0.40686659 | O66: =O64/J64-1 -> -0.30378868 | P66: =P64/K64-1 -> -0.11426386 | Q66: =Q64/L64-1 -> 0.029449037 | R66: =R64/M64-1 -> -0.37615894 | S66: =S64/N64-1 -> -0.6301566 | T66: =T64/O64-1 -> -0.30865024 | ... AB66: =AB64/W64-1 -> -0.56781376
A68: Despesas de Vendas | B68: Selling expenses | C68: =C71+C74 -> -2787.7057 | D68: =D71+D74 -> -2513.5943 | E68: =E71+E74 -> -3255.5636 | F68: =F71+F74 -> -3725.0159 | G68: =G71+G74 -> -12281.88 | H68: =H71+H74 -> -3158.7638 | I68: =I71+I74 -> -3227.3523 | J68: =J71+J74 -> -3239.5417 | ... O68: =O71+O74 -> -3155.62 | P68: =P71+P74+P77 -> -3237.7 | Q68: =Q71+Q74+Q77 -> -12163.684 | R68: =R71+R74+R77 -> -2759.3974 | S68: =S71+S74+S77 -> -2962.4242 | T68: =T71+T74 -> -2216 | U68: =U71+U74+U77 -> -3023.2429 | V68: =V71+V74+V77 -> -11621.8 | W68: =W71+W74+W77 -> -2640.5272 | X68: =X71+X74+X77 -> -3150.0094 | Y68: =Y71+Y74+Y77 -> -3398.7634 | Z68: =Z71+Z74+Z77 -> -3973.2 | AA68: =AA71+AA74+AA77 -> -13162.5 | AB68: =AB71+AB74+AB77 -> -2956.2
A69: % receita líquida | B69: % net revenues | C69: =C68/C23 -> -0.44363 | D69: =D68/D23 -> -0.44680043 | E69: =E68/E23 -> -0.38117085 | F69: =F68/F23 -> -0.40537133 | G69: =G68/G23 -> -0.41437232 | H69: =H68/H23 -> -0.41841155 | I69: =I68/I23 -> -0.41709582 | J69: =J68/J23 -> -0.42596356 | ... AB69: =AB68/AB23 -> -0.44258466
A70: % variação anual | B70: % YoY growth | C70: - | D70: - | E70: - | F70: - | G70: - | H70: =H68/C68-1 -> 0.13310519 | I70: =I68/D68-1 -> 0.28395911 | J70: =J68/E68-1 -> -0.0049213898 | K70: =K68/F68-1 -> -0.03448367 | L70: =L68/G68-1 -> 0.0768344 | M70: =M68/H68-1 -> -0.10071244 | N70: =N68/I68-1 -> -0.092219579 | O70: =O68/J68-1 -> -0.025905431 | ... AB70: =AB68/W68-1 -> 0.11954917
A71: Natura & Co América Latina | B71: Natura & Co Latam | C71: -1852.4341 | D71: -1722.9066 | E71: -2216.171 | F71: -2540.6158 | G71: =F71+E71+D71+C71 -> -8332.1274 | H71: -2089.8651 | I71: -2226.4837 | J71: -2293.6703 | K71: -2449.4912 | L71: -9062.8391 | M71: -1992.1573 | N71: -2167.3267 | O71: -2406.713 | P71: -2384.2 | Q71: =P71+O71+N71+M71 -> -8950.3969 | R71: -2004 | S71: -2258.8428 | T71: -2216 | U71: -2341.7412 | V71: -8884.2912 | W71: -2009.9 | X71: -2510.9078 | Y71: =AA71-Z71-X71-W71 -> -2708.5922 | Z71: -3236.7 | AA71: -10466.1 | AB71: -2318.7
A72: % receita líquida | B72: % net revenues | C72: =C71/C25 -> -0.44504678 | D72: =D71/D25 -> -0.43335414 | E72: =E71/E25 -> -0.36428489 | F72: =F71/F25 -> -0.4019554 | G72: =G71/G25 -> -0.40560743 | H72: =H71/H25 -> -0.40298636 | I72: =I71/I25 -> -0.40235202 | J72: =J71/J25 -> -0.41316319 | ... AB72: =AB71/AB25 -> -0.43872396
A73: % variação anual | B73: % YoY growth | C73: - | D73: - | E73: - | F73: - | G73: - | H73: =H71/C71-1 -> 0.12817241 | I73: =I71/D71-1 -> 0.29228347 | J73: =J71/E71-1 -> 0.034969936 | K73: =K71/F71-1 -> -0.035867132 | L73: =L71/G71-1 -> 0.087698095 | M73: =M71/H71-1 -> -0.046753166 | N73: =N71/I71-1 -> -0.026569706 | O73: =O71/J71-1 -> 0.049284622 | ... AB73: =AB71/W71-1 -> 0.15363951
A74: Avon International | B74: Avon International | C74: -935.2716 | D74: -790.68767 | E74: -1039.3927 | F74: -1184.4002 | G74: =F74+E74+D74+C74 -> -3949.7521 | H74: -1068.8988 | I74: -1000.8685 | J74: -945.8714 | K74: -1147.0725 | L74: =K74+J74+I74+H74 -> -4162.7112 | M74: -848.47975 | N74: -762.4005 | O74: -748.907 | P74: -853.5 | Q74: =P74+O74+N74+M74 -> -3213.2872 | R74: -754.8 | S74: -701.76704 | T74: 0 | U74: -683.61164 | V74: -2738.0486 | W74: -630.62721 | X74: -639.10164 | Y74: =AA74-Z74-X74-W74 -> -690.17115 | Z74: -736.5 | AA74: -2696.4 | AB74: -637.5
A75: % receita líquida | B75: % net revenues | C75: =C74/C28 -> -0.44085032 | D75: =D74/D28 -> -0.47919953 | E75: =E74/E28 -> -0.42297535 | F75: =F74/F28 -> -0.41289819 | G75: =G74/G28 -> -0.43416391 | H75: =H74/H28 -> -0.4522576 | I75: =I74/I28 -> -0.4541136 | J75: =J74/J28 -> -0.4605647 | ... S75: =S74/S28 -> -0.46464806 | T75: 0 | U75: =U74/U28 -> -0.39882626 | V75: =V74/V28 -> -0.43552725 | W75: -0.45152287 | X75: -0.45152287 | Y75: -0.45152287 | Z75: -0.45152287 | AA75: -0.45152287 | AB75: -0.45152287
A76: % variação anual | B76: % YoY growth | C76: - | D76: - | E76: - | F76: - | G76: - | H76: =H74/C74-1 -> 0.14287523 | I76: =I74/D74-1 -> 0.26582036 | J76: =J74/E74-1 -> -0.089976828 | K76: =K74/F74-1 -> -0.031516055 | L76: =L74/G74-1 -> 0.053917093 | M76: =M74/H74-1 -> -0.2062113 | N76: =N74/I74-1 -> -0.23826111 | O76: =O74/J74-1 -> -0.20823592 | ... V76: =V74/Q74-1 -> -0.14789795 | W76: -0.16451085 | X76: -0.16451085 | Y76: -0.16451085 | Z76: -0.16451085 | AA76: -0.16451085 | AB76: -0.16451085
A77: Corporativo | B77: Corporate | C77: - | D77: - | E77: - | F77: - | P77: 0 | Q77: 0 | R77: -0.59739981 | S77: -1.8143467 | T77: 0 | U77: 2.1099387 | V77: 0.53982392 | W77: 0 | X77: 0 | Y77: 0 | Z77: 0 | AA77: =Z77+Y77+X77+W77 -> 0 | AB77: 0
A79: Despesas Gerais e Administrativas | B79: G&A expenses | C79: =C82+C85 -> -959.78456 | D79: =D82+D85 -> -983.37785 | E79: =E82+E85 -> -1153.1137 | F79: =F82+F85 -> -1219.7146 | G79: =G82+G85 -> -4315.9907 | H79: -1506.6186 | I79: -1671.4217 | J79: -1655.4272 | K79: -1566.0595 | L79: =L82+L85 -> -4640.4303 | M79: =M82+M85+M88 -> -1017.5856 | N79: =N82+N85+N88 -> -1070.6756 | O79: =O82+O85+O88 -> -1055.454 | P79: =P82+P85+P88 -> -1318.4 | Q79: =Q82+Q85+Q88 -> -4473.1 | R79: =R82+R85+R88 -> -1091.8974 | S79: =S82+S85+S88 -> -1108.9495 | T79: =T82+T85+T88 -> -616.6 | ... AB79: =AB82+AB85+AB88 -> -1024.8
A80: % receita líquida | B80: % net revenues | C80: =C79/C23 -> -0.15273822 | D80: =D79/D23 -> -0.17479895 | E80: =E79/E23 -> -0.1350099 | F80: =F79/F23 -> -0.13273428 | G80: =G79/G23 -> -0.1456151 | H80: =H79/H23 -> -0.19956751 | I80: =I79/I23 -> -0.21601082 | J80: =J79/J23 -> -0.21767019 | ... AB80: =AB79/AB23 -> -0.15342695
A81: % variação anual | B81: % YoY growth | C81: - | D81: - | E81: - | F81: - | G81: - | H81: =H79/C79-1 -> 0.56974668 | I81: =I79/D79-1 -> 0.69967395 | J81: =J79/E79-1 -> 0.43561489 | K81: =K79/F79-1 -> 0.28395573 | L81: =L79/G79-1 -> 0.07517152 | M81: =M79/H79-1 -> -0.32458978 | N81: =N79/I79-1 -> -0.35942221 | O81: =O79/J79-1 -> -0.36242802 | ... AB81: =AB79/W79-1 -> 0.037465573
A82: Natura & Co América Latina | B82: Natura & Co Latam | C82: -571.11748 | D82: -621.51857 | E82: -695.69588 | F82: -717.62976 | G82: =F82+E82+D82+C82 -> -2605.9617 | H82: -642.61165 | I82: -741.20512 | J82: -784.92308 | K82: -736.91636 | L82: =K82+J82+I82+H82 -> -2905.6562 | M82: -672.41999 | N82: -756.62371 | O82: -710.836 | P82: -874.7 | Q82: -3011 | R82: -715.1 | S82: -757.4 | T82: -613.5 | U82: -349.90082 | V82: -2456.8548 | W82: -647.47107 | X82: -762.90743 | Y82: =AA82-Z82-X82-W82 -> -719.8215 | Z82: -863.7 | AA82: -2993.9 | AB82: -680.1
A83: % receita líquida | B83: % net revenues | C83: =C82/C25 -> -0.13721082 | D83: =D82/D25 -> -0.15632748 | E83: =E82/E25 -> -0.11435557 | F83: =F82/F25 -> -0.1135375 | G83: =G82/G25 -> -0.12685805 | H83: =H82/H25 -> -0.12391409 | I83: =I82/I25 -> -0.13394456 | J83: =J82/J25 -> -0.14138969 | ... V83: =V82/V25 -> -0.12019341 | W83: -0.13762646 | X83: -0.13762646 | Y83: -0.13762646 | Z83: -0.13762646 | AA83: -0.13762646 | AB83: -0.13762646
A84: % variação anual | B84: % YoY growth | C84: - | D84: - | E84: - | F84: - | G84: - | H84: =H82/C82-1 -> 0.12518296 | I84: =I82/D82-1 -> 0.19257116 | J84: =J82/E82-1 -> 0.12825604 | K84: =K82/F82-1 -> 0.026875412 | L84: =L82/G82-1 -> 0.11500343 | M84: =M82/H82-1 -> 0.04638623 | N84: =N82/I82-1 -> 0.020802049 | O84: =O82/J82-1 -> -0.094387697 | ... V84: =V82/Q82-1 -> -0.18404025 | W84: -0.094572683 | X84: -0.094572683 | Y84: -0.094572683 | Z84: -0.094572683 | AA84: -0.094572683 | AB84: -0.094572683
A85: Avon International | B85: Avon International | C85: -388.66708 | D85: -361.85928 | E85: -457.41782 | F85: -502.08483 | G85: =F85+E85+D85+C85 -> -1710.029 | H85: -469.95161 | I85: -489.40377 | J85: -420.10573 | K85: -355.31295 | L85: =K85+J85+I85+H85 -> -1734.7741 | M85: -346.16563 | N85: -315.05191 | O85: -314.618 | P85: -430.3 | Q85: -1410.6 | R85: -372.2 | S85: -346.6 | T85: 0 | U85: -344.86303 | V85: -1438.925 | W85: -336.43078 | X85: -359.03082 | Y85: =AA85-Z85-X85-W85 -> -409.83839 | Z85: -420.6 | AA85: -1525.9 | AB85: -338.6
A86: % receita líquida | B86: % net revenues | C86: =C85/C28 -> -0.18320241 | D86: =D85/D28 -> -0.21930631 | E86: =E85/E28 -> -0.18614376 | F86: =F85/F28 -> -0.17503368 | G86: =G85/G28 -> -0.18796949 | H86: =H85/H28 -> -0.1988394 | I86: =I85/I28 -> -0.22205205 | J86: =J85/J28 -> -0.20455832 | ... S86: =S85/S28 -> -0.22948786 | T86: 0 | U86: =U85/U28 -> -0.20119674 | V86: =V85/V28 -> -0.22888237 | W86: -0.24088112 | X86: -0.24088112 | Y86: -0.24088112 | Z86: -0.24088112 | AA86: -0.24088112 | AB86: -0.24088112
A87: % variação anual | B87: % YoY growth | C87: - | D87: - | E87: - | F87: - | G87: - | H87: =H85/C85-1 -> 0.20913665 | I87: =I85/D85-1 -> 0.35246986 | J87: =J85/E85-1 -> -0.081571135 | K87: =K85/F85-1 -> -0.29232485 | L87: =L85/G85-1 -> 0.014470549 | M87: =M85/H85-1 -> -0.26340155 | N87: =N85/I85-1 -> -0.35625361 | O87: =O85/J85-1 -> -0.25109804 | ... V87: =V85/Q85-1 -> 0.020080128 | W87: -0.096102145 | X87: -0.096102145 | Y87: -0.096102145 | Z87: -0.096102145 | AA87: -0.096102145 | AB87: -0.096102145
A88: Corporativo | B88: Corporate | C88: 0 | D88: 0 | E88: 0 | F88: 0 | G88: 0 | H88: -4.3353514 | I88: -8.8084932 | J88: -10.790781 | K88: 4.6840519 | L88: -19.250573 | M88: 1 | N88: 1 | O88: -30 | P88: -13.4 | Q88: -51.5 | R88: -4.5973631 | S88: -4.9495322 | T88: -3.1 | U88: -4.3288641 | V88: -6.0201516 | W88: -3.8899574 | X88: -3.8694768 | Y88: =AA88-Z88-W88-X88 -> -0.24056581 | Z88: -30.2 | AA88: -38.2 | AB88: -6.1
A89: % receita líquida | B89: % net revenues | C89: - | D89: - | E89: - | F89: - | G89: - | H89: =H88/H23 -> -0.00057426297 | I89: =I88/I23 -> -0.0011383901 | J89: =J88/J23 -> -0.0014188671 | K89: =K88/K23 -> 0.0005292461 | L89: =L88/L23 -> -0.00060645621 | M89: =M88/M23 -> 0.00015166461 | N89: =N88/N23 -> 0.0001389117 | O89: =O88/O23 -> -0.004040336 | ... AB89: =AB88/AB23 -> -0.00091325568
A90: % variação anual | B90: % YoY growth | C90: - | D90: - | E90: - | F90: - | G90: - | H90: - | I90: - | J90: - | K90: - | L90: - | M90: =M88/H88-1 -> -1.2306618 | N90: =N88/I88-1 -> -1.1135268 | O90: =O88/J88-1 -> 1.780151 | P90: =P88/K88-1 -> -3.860771 | Q90: =Q88/L88-1 -> 1.675245 | R90: - | S90: - | T90: - | U90: - | V90: =V88/Q88-1 -> -0.88310385 | W90: - | X90: - | Y90: - | Z90: - | AA90: - | AB90: -
A92: Outras despesas/receitas | B92: Other expenses / revenues | C92: =C95+C98+C101 -> -9.3106851 | D92: =D95+D98+D101 -> 111.01986 | E92: =E95+E98+E101 -> -24.40501 | F92: =F95+F98+F101 -> -14.670696 | G92: =G95+G98+G101 -> 62.633473 | H92: =H95+H98+H101 -> 10.505764 | I92: =I95+I98+I101 -> -5.2517821 | J92: =J95+J98+J101 -> 241.81011 | ... AB92: =AB95+AB98+AB101 -> 27.7
A93: % receita líquida | B93: % net revenues | C93: =C92/C23 -> -0.0014816841 | D93: =D92/D23 -> 0.019734181 | E93: =E92/E23 -> -0.0028574095 | F93: =F92/F23 -> -0.0015965246 | G93: =G92/G23 -> 0.0021131601 | H93: =H92/H23 -> 0.0013915991 | I93: =I92/I23 -> -0.00067872863 | J93: =J92/J23 -> 0.031795329 | ... AB93: =AB92/AB23 -> 0.0041470791
A94: % variação anual | B94: % YoY growth | C94: - | D94: - | E94: - | F94: - | G94: - | H94: =H92/C92-1 -> -2.1283556 | I94: =I92/D92-1 -> -1.0473049 | J94: =J92/E92-1 -> -10.908216 | K94: =K92/F92-1 -> -4.5583921 | L94: =L92/G92-1 -> 3.8468501 | M94: =M92/H92-1 -> 1.6414322 | N94: =N92/I92-1 -> -25.713864 | O94: =O92/J92-1 -> -0.84205375 | ... AB94: =AB92/W92-1 -> -1.5500531
A95: Natura & Co América Latina | B95: Natura & Co Latam | C95: 2.7091927 | D95: 110.35735 | E95: -26.088811 | F95: -10.773325 | G95: =F95+E95+D95+C95 -> 76.204409 | H95: 10.56285 | I95: -6.5487557 | J95: 247.73032 | K95: 45.247818 | L95: 301.21374 | M95: 37.001479 | N95: 18.715234 | O95: 58.079 | P95: -43.4 | Q95: 70.395713 | R95: 34 | S95: -4.5 | T95: -26.2 | U95: 118.17976 | V95: =U95+T95+S95+R95 -> 121.47976 | W95: 103.11408 | X95: 56.062148 | Y95: =AA95-Z95-X95-W95 -> 4.6237686 | Z95: 14.8 | AA95: 178.6 | AB95: 20.7
A96: % receita líquida | B96: % net revenues | C96: =C95/C25 -> 0.00065088281 | D96: =D95/D25 -> 0.027757637 | E96: =E95/E25 -> -0.0042883695 | F96: =F95/F25 -> -0.0017044672 | G96: =G95/G25 -> 0.0037096257 | H96: =H95/H25 -> 0.0020368226 | I96: =I95/I25 -> -0.0011834378 | J96: =J95/J25 -> 0.044624133 | ... AB96: =AB95/AB25 -> 0.0039166714
A97: % variação anual | B97: % YoY growth | C97: - | D97: - | E97: - | F97: - | G97: - | H97: =H95/C95-1 -> 2.898892 | I97: =I95/D95-1 -> -1.0593414 | J97: =J95/E95-1 -> -10.495654 | K97: =K95/F95-1 -> -5.1999862 | L97: =L95/G95-1 -> 2.9527076 | M97: =M95/H95-1 -> 2.5029825 | N97: =N95/I95-1 -> -3.8578306 | O97: =O95/J95-1 -> -0.76555554 | ... AB97: =AB95/W95-1 -> -0.79925148
A98: Avon International | B98: Avon International | C98: -12.019878 | D98: 0.66251114 | E98: 1.6838015 | F98: -3.8973708 | G98: =F98+E98+D98+C98 -> -13.570936 | H98: -0.057086245 | I98: 1.2969736 | J98: -7.4098773 | K98: 5.0461916 | L98: =K98+J98+I98+H98 -> -1.1237983 | M98: -0.037031174 | N98: 111.07659 | O98: -19.886 | P98: -316.9 | Q98: -225.74644 | R98: 0.6 | S98: -46.4 | T98: 0 | U98: -663.95917 | V98: =U98+T98+S98+R98 -> -709.75917 | W98: -139.92862 | X98: 1.064673 | Y98: =AA98-Z98-X98-W98 -> 46.363947 | Z98: -16.8 | AA98: -109.3 | AB98: 7.9
A99: % receita líquida | B99: % net revenues | C99: =C98/C28 -> -0.0056656986 | D99: =D98/D28 -> 0.00040151761 | E99: =E98/E28 -> 0.00068521413 | F99: =F98/F28 -> -0.0013586771 | G99: =G98/G28 -> -0.0014917419 | H99: =H98/H28 -> -2.4153539e-05 | I99: =I98/I28 -> 0.00058846223 | J99: =J98/J28 -> -0.0036080253 | ... S99: =S98/S28 -> -0.030721976 | T99: 0 | U99: =U98/U28 -> -0.3873608 | V99: =V98/V28 -> -0.11289772 | W99: =W98/W28 -> -0.10018751 | X99: =X98/X28 -> 0.00074617404 | Y99: =Y98/Y28 -> 0.030998368 | Z99: =Z98/Z28 -> -0.0091032241 | AA99: =AA98/AA28 -> -0.017729979 | AB99: =AB98/AB28 -> 0.0056659256
A100: % variação anual | B100: % YoY growth | C100: - | D100: - | E100: - | F100: - | G100: - | H100: =H98/C98-1 -> -0.99525068 | I100: =I98/D98-1 -> 0.95766305 | J100: =J98/E98-1 -> -5.4006833 | K100: =K98/F98-1 -> -2.2947682 | L100: =L98/G98-1 -> -0.9171908 | M100: =M98/H98-1 -> -0.35131179 | N100: =N98/I98-1 -> 84.642911 | O100: =O98/J98-1 -> 1.6837151 | ... AB100: =AB98/W98-1 -> -1.0564574
A101: Holding | B101: Holding | C101: 0 | D101: 1.2434498e-14 | E101: -1.7763568e-15 | F101: 8.8817842e-16 | G101: 0 | H101: 0 | I101: 3.5527137e-15 | J101: 1.4896641 | K101: 1.91008 | L101: 3.4851055 | M101: -9.2141849 | N101: -1.2434498e-14 | O101: 0 | P101: -2.3 | Q101: -11.056274 | R101: -0.5134964 | S101: 0 | T101: -0.3 | U101: 1 | V101: -1 | W101: -13.544241 | X101: -30.779176 | Y101: =AA101-Z101-X101-W101 -> -62.776584 | Z101: -434 | AA101: -541.1 | AB101: -0.9
A102: % receita líquida | B102: % net revenues | C102: =C101/C23 -> 0 | D102: =D101/D23 -> 2.2102768e-18 | E102: =E101/E23 -> -2.0798102e-19 | F102: =F101/F23 -> 9.6655175e-20 | G102: =G101/G23 -> 0 | H102: =H101/H23 -> 0 | I102: =I101/I23 -> 4.5914481e-19 | J102: =J101/J23 -> 0.00019587419 | ... AB102: =AB101/AB23 -> -0.00013474264
A103: % variação anual | B103: % YoY growth | C103: - | D103: - | E103: - | F103: - | G103: - | H103: - | I103: =I101/D101-1 -> -0.71428571 | J103: - | K103: - | L103: - | M103: - | N103: - | O103: =O101/J101-1 -> -1 | P103: =P101/K101-1 -> -2.204138 | Q103: =Q101/L101-1 -> -4.172436 | R103: =R101/M101-1 -> -0.9442711 | S103: - | T103: - | U103: - | V103: =V101/Q101-1 -> -0.90955362 | W103: =W101/R101-1 -> 25.376505 | X103: - | Y103: - | Z103: - | AA103: - | AB103: -
A105: Custos de Aquisições | B105: Acquisition costs | C105: -298.2846 | D105: -5.6318795 | E105: 0 | F105: 0 | G105: =F105+E105+D105+C105 -> -303.91648 | H105: 0 | I105: 0 | J105: 0 | K105: 0 | L105: =K105+J105+I105+H105 -> 0 | M105: 0 | N105: 0 | O105: 0 | P105: 0 | Q105: =P105+O105+N105+M105 -> 0 | R105: 0 | S105: 0 | T105: 0 | U105: =T105+S105+R105+Q105 -> 0 | V105: =U105+T105+S105+R105 -> 0 | W105: 0 | X105: 0 | Y105: 0 | Z105: 0 | AA105: 0 | AB105: 0
A106: % receita líquida | B106: % net revenues | C106: =C105/C23 -> -0.047468424 | D106: =D105/D23 -> -0.0010010869 | E106: =E105/E23 -> 0 | F106: =F105/F23 -> 0 | G106: =G105/G23 -> -0.01025369 | H106: =H105/H23 -> 0 | I106: =I105/I23 -> 0 | J106: =J105/J23 -> 0 | ... AB106: =AB105/AB23 -> 0
A107: % variação anual | B107: % YoY growth | C107: - | D107: - | E107: - | F107: - | G107: - | H107: =H105/C105-1 -> -1 | I107: =I105/D105-1 -> -1 | J107: - | K107: - | L107: =L105/G105-1 -> -1 | M107: - | N107: - | O107: - | P107: - | Q107: - | R107: - | S107: - | T107: - | U107: - | V107: - | W107: - | X107: - | Y107: - | Z107: - | AA107: - | AB107: -
A109: Despesas da Holding | B109: Holding expenses | C109: -30.177365 | D109: -78.104703 | E109: -99.829055 | F109: -171.33346 | G109: =F109+E109+D109+C109 -> -379.44459 | H109: -110.9478 | I109: -148.41167 | J109: -142.34098 | K109: -157.42943 | L109: =K109+J109+I109+H109 -> -559.12988 | M109: -109.90764 | N109: -88.695383 | O109: -72.503 | P109: -121 | Q109: =P109+O109+N109+M109 -> -392.10602 | R109: -70.13 | S109: -83.63 | T109: -74.701 | U109: -94.798023 | V109: =U109+T109+S109+R109 -> -323.25902 | W109: -55.251047 | X109: -82.025487 | Y109: =AA109-Z109-X109-W109 -> -42.823466 | Z109: -60.4 | AA109: -240.5 | AB109: -24.7
A110: % receita líquida | B110: % net revenues | C110: =C109/C23 -> -0.0048023664 | D110: =D109/D23 -> -0.013883392 | E110: =E109/E23 -> -0.011688276 | F110: =F109/F23 -> -0.018645202 | G110: =G109/G23 -> -0.012801895 | H110: =H109/H23 -> -0.014696205 | I110: =I109/I23 -> -0.019180394 | J110: =J109/J23 -> -0.018716249 | ... AB110: =AB109/AB23 -> -0.0036979369
...

Sheet Graphs (2)
B2: Revenue
B4: Consolidated Net Revenue Growth | I4: Net Revenue by Geography
C5: 2T-22 | D5: 2T-23 | J5: 2T-23 | K5: 2T-22
C6: Net Revenue | J6: Net Revenue
C7: Q2-22 | D7: Q2-23 | E7: Δ% RC | F7: Δ% CC | J7: Q2-23 | K7: Q2-22 | L7: Δ% RC
B8: Natura & Co Latam | C8: 5555.0449 | D8: 5462.9 | E8: =#REF! -> #REF! | F8: =#REF! -> #REF! | H8: Brasil | I8: Brazil | J8: 30.5 | K8: 30.5
B9: Avon International | C9: 1643.7729 | D9: 1510.3 | E9: =#REF! -> #REF! | F9: =#REF! -> #REF! | H9: Latam Hispânica | I9: Hispanic Latam | J9: 28.7 | K9: 28.7
B10: The Body Shop | C10: 909.43307 | D10: 800.3 | E10: =#REF! -> #REF! | F10: =#REF! -> #REF! | H10: EMEA | I10: EMEA | J10: 23.3 | K10: 23.3
B11: Consolidated | C11: 8108.2509 | D11: 7773.5 | E11: =#REF! -> #REF! | F11: =#REF! -> #REF! | H11: Ásia Pacífico | I11: Asia Pacific | J11: 11.9 | K11: 11.9
H12: América do Norte | I12: North America | J12: 5.7 | K12: 5.7
I13: Consolidated | J13: =SUM(J8:J10) -> 82.5 | K13: =SUM(K8:K10) -> 82.5
C19: Q2-23
B24: Underlying Net Income
C26: Q2-23
A27: Lucro Líquido 2T-23 | B27: Net income Q2-23 | C27: =#REF! -> #REF!
A28: (-) Custos de Transformação / Integração | B28: (-) Transformation / Integration Cost | C28: =#REF! -> #REF!
A29: (-) Custos de Reestruturação / Operações Descontinuadas e outros efeitos | B29: (-) Reestructuring Costs / Descontinued Operations and other effects | C29: =SUM(C30:C33) -> #REF!
A30: Restructuring Cost | B30: Restructuring Cost | C30: =#REF! -> #REF!
A31: Net Non Recurring Items | B31: Net Non Recurring Items | C31: =#REF! -> #REF!
A32: Discontinued Operations | B32: Discontinued Operations | C32: =-#REF! -> #REF!
A33: Non Controlling Interest | B33: Non Controlling Interest | C33: =#REF! -> #REF!
A34: (-) PPA | B34: (-) PPA | C34: =SUM(C35:C38) -> 120.10545
A35: PPA financial result | B35: PPA financial result | C35: 5.0421244
A36: PPA Depreciation | B36: PPA Depreciation | C36: 136.12051
A37: PPA taxes | B37: PPA taxes | C37: -15.574796
A38: PPA EBITDA | B38: PPA EBITDA | C38: -5.4823851
A39: (=) Lucro Líquido Underlying | B39: (=) Underlying Net Income | C39: =C27+C28+C29+C34-0.1 -> #REF!
B45: Net Debt/EBITDA ratio
B58: Natura Brand
C60: 2T-21 | D60: 2T-22 | E60: Var. % | F60: 3T-21 | G60: 3T-22 | H60: Var. % | I60: 4T-21 | J60: 4T-22 | K60: Var. % | L60: 1T-22 | M60: 1T-23 | N60: Var. % | O60: 2T-22 | P60: 2T-23 | Q60: Var. %
C61: Q2-21 | D61: Q2-22 | E61: Ch. % | F61: Q3-21 | G61: Q3-22 | H61: Ch. % | I61: Q4-21 | J61: Q4-22 | K61: Ch. % | L61: Q1-22 | M61: Q1-23 | N61: Ch. % | O61: Q2-22 | P61: Q2-23 | Q61: Ch. %
B62: Gross Revenue Brazil | C62: 2539.3429 | D62: 2852.5751 | E62: =D62/C62-1 -> 0.12335169 | F62: 2367.1755 | G62: 2775 | H62: =G62/F62-1 -> 0.17228318 | I62: 2918.5073 | J62: 3409.6 | K62: =J62/I62-1 -> 0.16826844 | L62: 2074.0596 | M62: 2587.7 | N62: =M62/L62-1 -> 0.24764979 | O62: =D62 -> 2852.5751 | P62: 3270.7 | Q62: =P62/O62-1 -> 0.14657806
B63: Total consultants Brazil - average of the period | C63: 1175.5014 | D63: 1123.6727 | E63: =D63/C63-1 -> -0.044090746 | F63: 1186.9536 | G63: 1146.5805 | H63: =G63/F63-1 -> -0.034014051 | I63: 1137.0372 | J63: 1156.336 | K63: =J63/I63-1 -> 0.016972913 | L63: 1091.3664 | M63: 1130.9144 | N63: =M63/L63-1 -> 0.036237143 | O63: =D63 -> 1123.6727 | P63: =#REF! -> #REF! | Q63: =P63/O63-1 -> #REF!
B64: Productivity | C64: 2.160221 | D64: 2.5386175 | E64: =D64/C64-1 -> 0.17516562 | F64: 1.9943286 | G64: 2.42024 | H64: =G64/F64-1 -> 0.21356131 | I64: 2.5667651 | J64: 2.9486239 | K64: =J64/I64-1 -> 0.14877046 | L64: 1.9004246 | M64: 2.2881484 | N64: =M64/L64-1 -> 0.20401956 | O64: =O62/O63 -> 2.5386175 | P64: =P62/P63 -> #REF! | Q64: =P64/O64-1 -> #REF!
A66: Crescimento da produtividade | B66: Productivity growth | C66: Published
A67: 2T-22 | B67: Q2-22 | C67: =E64 -> 0.17516562
A68: 3T-22 | B68: Q3-22 | C68: =H64 -> 0.21356131
A69: 4T-22 | B69: Q4-22 | C69: =K64 -> 0.14877046
A70: 1T-23 | B70: Q1-23 | C70: =N64 -> 0.20401956
A71: 2T-23 | B71: Q2-23 | C71: =Q64 -> #REF!
E77: a) Gross revenue divided by average number of consultants | J77: a) Receita bruta dividade pelo número médio de consultora
