Workbook

Sheet 2011
B2: 2011 | H2: Pro-Forma
B3: (R$ million) | C3: Consolidated | H3: Brazil | M3: Latam | R3: Aesop
C4: 1Q16 | D4: 2Q16 | E4: 3Q16 | F4: 4Q16 | G4: 2016 | H4: 1Q16 | I4: 2Q16 | J4: 3Q16 | K4: 4Q16 | L4: 2016 | M4: 1Q16 | N4: 2Q16 | O4: 3Q16 | P4: 4Q16 | Q4: 2016 | R4: 1Q16 | S4: 2Q16 | T4: 3Q16 | U4: 4Q16 | V4: 2016
B5: Total Consultants - end of period ('000)2 | C5: 1230.203 | D5: 1296.068 | E5: 1361.622 | F5: 1421.137 | G5: 1421.137 | H5: 1032.703 | I5: 1079.09 | J5: 1131.381 | K5: 1175.471 | L5: 1175.471 | M5: 200.73 | N5: 216.978 | O5: 230.241 | P5: 245.666 | Q5: 245.666 | R5: 0 | S5: 0 | T5: 0 | U5: 0 | V5: 0
B6: Total Consultants - average of period ('000) | C6: 1224.075 | D6: 1278.2551 | E6: 1331.7338 | F6: 1400.3214 | G6: 1313.4067 | H6: 1027.1592 | I6: 1065.6626 | J6: 1106.162 | K6: 1160.4164 | L6: 1093.1687 | M6: 196.91575 | N6: 212.5925 | O6: 225.57175 | P6: 239.905 | Q6: 220.23794 | R6: 0 | S6: 0 | T6: 0 | U6: 0 | V6: 2.8117647
B7: Units sold – items for resale (in million) | C7: 100.04548 | D7: 109.05143 | E7: 118.33295 | F7: 131.11265 | G7: 458.6425 | H7: 90.138928 | I7: 97.589054 | J7: 104.98966 | K7: 117.8009 | L7: 410.51854 | M7: 9.9065488 | N7: 11.762371 | O7: 13.343293 | P7: 14.011742 | Q7: 49.023955 | R7: 0 | S7: 0 | T7: 0 | U7: 0 | V7: 0
B8: Gross Revenue | C8: 1556.0408 | D8: 1885.14 | E8: 1862.033 | F8: 2232.5505 | G8: 7535.7644 | H8: 1438.6805 | I8: 1735.4978 | J8: 1693.8738 | K8: 2030.8336 | L8: 6898.8858 | M8: 114.14621 | N8: 145.1292 | O8: 164.65121 | P8: 195.21775 | Q8: 619.14437 | R8: 0 | S8: 0 | T8: 0 | U8: 0 | V8: 0
B9: Net Revenue | C9: 1145.8458 | D9: 1393.6157 | E9: 1381.4341 | F9: 1670.4781 | G9: 5591.3737 | H9: 1052.4712 | I9: 1274.8356 | J9: 1249.3315 | K9: 1510.9831 | L9: 5087.6214 | M9: 90.687387 | N9: 115.00673 | O9: 129.16957 | P9: 154.06088 | Q9: 488.92457 | R9: 0 | S9: 0 | T9: 0 | U9: 0 | V9: 0
B10: Gross Profit | C10: 802.6242 | D10: 980.5712 | E10: 967.6474 | F10: 1174.231 | G10: 3925.0738 | H10: 747.25816 | I10: 907.51096 | J10: 884.14609 | K10: 1072.3465 | L10: 3611.2617 | M10: 53.404121 | N10: 70.992005 | O10: 82.011998 | P10: 99.702193 | Q10: 306.11032 | R10: 0 | S10: 0 | T10: 0 | U10: 0 | V10: 0
B11: Selling, Marketing and Logistics Expenses | C11: -422.91433 | D11: -486.37843 | E11: -500.2152 | F11: -543.23171 | G11: -1952.7397 | H11: -368.89844 | I11: -422.6431 | J11: -426.31034 | K11: -468.67585 | L11: -1686.5277 | M11: -50.283491 | N11: -60.096632 | O11: -69.555041 | P11: -68.726791 | Q11: -248.66195 | R11: 0 | S11: 0 | T11: 0 | U11: 0 | V11: 0
B12: Administrative, R&D, IT and Projects Expenses | C12: -133.08488 | D12: -170.97857 | E12: -177.90611 | F12: -198.76389 | G12: -680.73345 | H12: -107.46669 | I12: -147.24085 | J12: -152.52419 | K12: -170.66229 | L12: -577.89402 | M12: -24.005328 | N12: -21.492179 | O12: -24.07874 | P12: -26.553767 | Q12: -96.130015 | R12: 0 | S12: 0 | T12: 0 | U12: 0 | V12: 0
B13: Employee profit sharing | C13: -17.90767 | D13: -21.32938 | E13: 14.198864 | F13: -5.1298083 | G13: -30.167993 | H13: -17.90767 | I13: -21.32938 | J13: 14.198864 | K13: -5.1298083 | L13: -30.167993 | M13: 0 | N13: 0 | O13: 0 | P13: 0 | Q13: 0 | R13: 0 | S13: 0 | T13: 0 | U13: 0 | V13: 0
B14: Management compensation | C14: -3.221523 | D14: -3.669664 | E14: -2.8198158 | F14: 0.26755978 | G14: -9.443443 | H14: -3.221523 | I14: -3.669664 | J14: -2.8208158 | K14: 0.26755978 | L14: -9.444443 | M14: 0 | N14: 0 | O14: 0 | P14: 0 | Q14: 0 | R14: 0 | S14: 0 | T14: 0 | U14: 0 | V14: 0
B15: Other Operating Income / (Expenses), net | C15: 13.796681 | D15: 2.9949368 | E15: 4.2173332 | F15: 42.07007 | G15: 63.079021 | H15: 14.683209 | I15: 3.7351698 | J15: 5.0128209 | K15: 42.225394 | L15: 65.656594 | M15: -0.8865281 | N15: -0.74023307 | O15: -0.79587818 | P15: 0.17124048 | Q15: -2.2513989 | R15: 0 | S15: 0 | T15: 0 | U15: 0 | V15: 0
B16: Financial Income / (Expenses), net | C16: -10.196478 | D16: -21.077064 | E16: -4.444381 | F16: -41.605239 | G16: -77.323162 | H16: -9.8355022 | I16: -21.909656 | J16: -1.7224324 | K16: -40.00168 | L16: -73.46927 | M16: -0.36097581 | N16: 0.8325917 | O16: -2.7219486 | P16: -1.6035588 | Q16: -3.8538915 | R16: 0 | S16: 0 | T16: 0 | U16: 0 | V16: 0
... B27: EBITDA Margin | C27: 0.23049876 | D27: 0.23487488 | E27: 0.24125476 | F27: 0.29953743 | G27: 0.25485502 | H27: 0.27325653 | I27: 0.26746727 | J27: 0.2786022 | K27: 0.33052377 | L27: 0.29012649 | M27: -0.22310863 | N27: -0.086616598 | O27: -0.082937321 | P27: 0.041436086 | Q27: -0.070611975 | R27: 0 | S27: 0 | T27: 0 | U27: 0 | V27: 0
B29: (*) EBITDA = Income from operations before financial effects + depreciation & amortization.

Sheet 2012
B2: 2012 | H2: Pro-Forma
B3: (R$ million) | C3: Consolidated | H3: Brazil | M3: Latam | R3: Aesop
C4: 1Q16 | D4: 2Q16 | E4: 3Q16 | F4: 4Q16 | G4: 2016 | H4: 1Q16 | I4: 2Q16 | J4: 3Q16 | K4: 4Q16 | L4: 2016 | M4: 1Q16 | N4: 2Q16 | O4: 3Q16 | P4: 4Q16 | Q4: 2016 | R4: 1Q16 | S4: 2Q16 | T4: 3Q16 | U4: 4Q16 | V4: 2016
B5: Total Consultants - end of period ('000)2 | C5: 1434.832 | D5: 1505.543 | E5: 1518.032 | F5: 1572.811 | G5: 1572.811 | H5: 1178.6 | I5: 1226.01 | J5: 1226.611 | K5: 1268.422 | L5: 1268.422 | M5: 256.232 | N5: 279.533 | O5: 291.421 | P5: 304.389 | Q5: 304.389 | R5: 0 | S5: 0 | T5: 0 | U5: 0 | V5: 0
B6: Total Consultants - average of period ('000) | C6: 1418.7711 | D6: 1487.7993 | E6: 1513.0603 | F6: 1555.7809 | G6: 1497.7119 | H6: 1165.403 | I6: 1215.0522 | J6: 1226.0178 | K6: 1253.791 | L6: 1216.7734 | M6: 253.36805 | N6: 272.74713 | O6: 287.04245 | P6: 301.98985 | Q6: 280.9385 | R6: 0 | S6: 0 | T6: 0 | U6: 0 | V6: 2.7427647
B7: Units sold – items for resale (in million) | C7: 112.48091 | D7: 120.87453 | E7: 128.92689 | F7: 140.17584 | G7: 499.45816 | H7: 100.64471 | I7: 108.22248 | J7: 111.78118 | K7: 125.1509 | L7: 445.79927 | M7: 11.836199 | N7: 12.652046 | O7: 14.145708 | P7: 15.024936 | Q7: 53.658889 | R7: 0 | S7: 0 | T7: 0 | U7: 0 | V7: 0
B8: Gross Revenue | C8: 1712.0708 | D8: 2148.6894 | E8: 2154.1686 | F8: 2551.1652 | G8: 8566.094 | H8: 1540.0606 | I8: 1928.0387 | J8: 1903.5776 | K8: 2257.7688 | L8: 7629.4457 | M8: 167.90557 | N8: 216.18091 | O8: 247.48391 | P8: 287.52178 | Q8: 919.09216 | R8: 0 | S8: 0 | T8: 0 | U8: 0 | V8: 0
B9: Net Revenue | C9: 1275.8349 | D9: 1608.2831 | E9: 1586.5325 | F9: 1875.019 | G9: 6345.6696 | H9: 1140.2118 | I9: 1434.2918 | J9: 1391.7752 | K9: 1644.9524 | L9: 5611.2312 | M9: 132.19128 | N9: 170.254 | O9: 192.15941 | P9: 225.15474 | Q9: 719.75943 | R9: 0 | S9: 0 | T9: 0 | U9: 0 | V9: 0
B10: Gross Profit | C10: 910.50349 | D10: 1136.9716 | E10: 1131.5235 | F10: 1298.6258 | G10: 4477.6243 | H10: 820.10542 | I10: 1016.8144 | J10: 994.93044 | K10: 1139.8719 | L10: 3971.7222 | M10: 87.856218 | N10: 117.7409 | O10: 134.74557 | P10: 155.27134 | Q10: 495.61402 | R10: 0 | S10: 0 | T10: 0 | U10: 0 | V10: 0
B11: Selling, Marketing and Logistics Expenses | C11: -488.2704 | D11: -550.58603 | E11: -535.2573 | F11: -638.09129 | G11: -2212.205 | H11: -412.95987 | I11: -453.07171 | J11: -435.55655 | K11: -533.69935 | L11: -1835.2875 | M11: -71.836019 | N11: -93.752908 | O11: -96.338146 | P11: -99.726016 | Q11: -361.65309 | R11: 0 | S11: 0 | T11: 0 | U11: 0 | V11: 0
B12: Administrative, R&D, IT and Projects Expenses | C12: -164.97596 | D12: -194.40926 | E12: -203.84506 | F12: -208.30805 | G12: -771.53833 | H12: -140.1127 | I12: -164.42147 | J12: -170.94036 | K12: -168.99045 | L12: -644.46497 | M12: -24.777252 | N12: -29.832986 | O12: -32.634344 | P12: -36.320645 | Q12: -123.56523 | R12: 0 | S12: 0 | T12: 0 | U12: 0 | V12: 0
B13: Employee profit sharing | C13: -12.56845 | D13: -29.040665 | E13: -28.106121 | F13: -21.083202 | G13: -90.798438 | H13: -8.4594952 | I13: -24.931711 | J13: -23.997166 | K13: -16.974248 | L13: -74.36262 | M13: -2.5421652 | N13: -2.5421652 | O13: -2.5421652 | P13: -5.3785326 | Q13: -13.005028 | R13: 0 | S13: 0 | T13: 0 | U13: 0 | V13: 0
B14: Management compensation | C14: -3.978 | D14: -6.3500359 | E14: -5.2265271 | F14: -5.184854 | G14: -20.739417 | H14: -3.978 | I14: -6.3500359 | J14: -5.2265271 | K14: -5.184854 | L14: -20.739417 | M14: 0 | N14: 0 | O14: 0 | P14: 0 | Q14: 0 | R14: 0 | S14: 0 | T14: 0 | U14: 0 | V14: 0
B15: Other Operating Income / (Expenses), net | C15: -2.0620274 | D15: 0.42265731 | E15: -9.4938804 | F15: -0.50348582 | G15: -11.636736 | H15: -1.2861846 | I15: 1.15831 | J15: -8.5175542 | K15: 2.7464708 | L15: -5.898958 | M15: -0.77584283 | N15: -0.73165271 | O15: -0.776645 | P15: -2.2626764 | Q15: -4.5468169 | R15: 0 | S15: 0 | T15: 0 | U15: 0 | V15: 0
B16: Financial Income / (Expenses), net | C16: -15.215829 | D16: -39.759813 | E16: 0.42453376 | F16: -17.797014 | G16: -72.348121 | H16: -16.405593 | I16: -40.824182 | J16: -0.91572749 | K16: -11.672277 | L16: -69.817779 | M16: 1.1897639 | N16: 1.064369 | O16: 1.3402613 | P16: -6.1247364 | Q16: -2.5303422 | R16: 0 | S16: 0 | T16: 0 | U16: 0 | V16: 0
... B27: EBITDA Margin | C27: 0.21330265 | D27: 0.24348687 | E27: 0.24267486 | F27: 0.24700638 | G27: 0.23825508 | H27: 0.24981783 | I27: 0.28021947 | J27: 0.27578294 | K27: 0.27547111 | L27: 0.27154939 | M27: -0.077235118 | N27: -0.04314244 | O27: 0.023994376 | P27: 0.06117868 | Q27: 0.0011537648 | R27: 0 | S27: 0 | T27: 0 | U27: 0 | V27: 0
B29: (*) EBITDA = Income from operations before financial effects + depreciation & amortization.

Sheet 2013
B2: 2013 | H2: Pro-Forma
B3: (R$ million) | C3: Consolidated | H3: Brazil | M3: Latam | R3: Aesop
C4: 1Q16 | D4: 2Q16 | E4: 3Q16 | F4: 4Q16 | G4: 2016 | H4: 1Q16 | I4: 2Q16 | J4: 3Q16 | K4: 4Q16 | L4: 2016 | M4: 1Q16 | N4: 2Q16 | O4: 3Q16 | P4: 4Q16 | Q4: 2016 | R4: 1Q16 | S4: 2Q16 | T4: 3Q16 | U4: 4Q16 | V4: 2016
B5: Total Consultants - end of period ('000)2 | C5: 1556.835 | D5: 1574.791 | E5: 1604.078 | F5: 1656.483 | G5: 1656.483 | H5: 1257.566 | I5: 1248.887 | J5: 1257.722 | K5: 1289.93 | L5: 1289.93 | M5: 299.269 | N5: 325.904 | O5: 346.356 | P5: 366.553 | Q5: 366.553 | R5: 0 | S5: 0 | T5: 0 | U5: 0 | V5: 0
B6: Total Consultants - average of period ('000) | C6: 1557.1759 | D6: 1571.114 | E6: 1596.7398 | F6: 1642.8992 | G6: 1596.1532 | H6: 1256.2262 | I6: 1256.337 | J6: 1256.3708 | K6: 1283.1928 | L6: 1264.8023 | M6: 300.94967 | N6: 314.77705 | O6: 340.369 | P6: 359.7064 | Q6: 331.3509 | R6: 0 | S6: 0 | T6: 0 | U6: 0 | V6: 0
B7: Units sold – items for resale (in million) | C7: 111.59892 | D7: 128.31231 | E7: 146.38114 | F7: 170.03848 | G7: 556.33085 | H7: 98.207473 | I7: 111.3823 | J7: 126.24715 | K7: 144.0599 | L7: 479.89683 | M7: 13.391449 | N7: 16.930006 | O7: 20.133987 | P7: 25.978573 | Q7: 76.434015 | R7: 0 | S7: 0 | T7: 0 | U7: 2.0268502 | V7: 2.0268502
B8: Gross Revenue | C8: 1832.3545 | D8: 2313.3312 | E8: 2396.4113 | F8: 2909.6027 | G8: 9451.6997 | H8: 1596.6526 | I8: 1981.9082 | J8: 2007.536 | K8: 2454.1797 | L8: 8040.2765 | M8: 222.10012 | N8: 298.85379 | O8: 347.20753 | P8: 389.53321 | Q8: 1257.6947 | R8: 10.513517 | S8: 28.550824 | T8: 38.623227 | U8: 60.21951 | V8: 137.90708
B9: Net Revenue | C9: 1351.2634 | D9: 1715.8385 | E9: 1777.7223 | F9: 2165.5837 | G9: 7010.308 | H9: 1164.5173 | I9: 1450.6913 | J9: 1467.3405 | K9: 1797.6754 | L9: 5880.2245 | M9: 173.64954 | N9: 233.23654 | O9: 269.11295 | P9: 302.94781 | Q9: 978.94684 | R9: 10.513517 | S9: 28.550824 | T9: 38.623227 | U9: 60.21951 | V9: 137.90708
B10: Gross Profit | C10: 947.32441 | D10: 1212.2225 | E10: 1257.5222 | F10: 1482.2189 | G10: 4899.188 | H10: 816.47574 | I10: 1019.1694 | J10: 1033.0735 | K10: 1213.2122 | L10: 4081.9308 | M10: 120.17965 | N10: 165.84472 | O10: 189.11371 | P10: 214.25959 | Q10: 689.39767 | R10: 8.8554993 | S10: 24.842629 | T10: 33.300237 | U10: 51.156044 | V10: 118.15441
B11: Selling, Marketing and Logistics Expenses | C11: -503.45677 | D11: -616.99934 | E11: -619.97796 | F11: -710.42831 | G11: -2434.2024 | H11: -414.59097 | I11: -500.14298 | J11: -484.13011 | K11: -548.52584 | L11: -1934.3551 | M11: -84.531347 | N11: -109.56809 | O11: -127.57069 | P11: -149.32082 | Q11: -470.99094 | R11: -1.2090002 | S11: -3.7453251 | T11: -4.9810945 | U11: -6.9178933 | V11: -16.853313
B12: Administrative, R&D, IT and Projects Expenses | C12: -223.75708 | D12: -250.04311 | E12: -289.05882 | F12: -284.74426 | G12: -978.30328 | H12: -171.42178 | I12: -185.04052 | J12: -208.67036 | K12: -202.07751 | L12: -702.66358 | M12: -36.669531 | N12: -39.408857 | O12: -46.620373 | P12: -48.573016 | Q12: -171.27178 | R12: -12.174848 | S12: -20.424501 | T12: -30.421113 | U12: -32.189123 | V12: -95.209585
B13: Employee profit sharing | C13: n/a | D13: n/a | E13: n/a | F13: 7.7561933 | G13: -61 | H13: n/a | I13: n/a | J13: n/a | K13: 6.4222787 | L13: -53.981121 | M13: -1.785 | N13: -3.2059812 | O13: -0.97332866 | P13: 1.102172 | Q13: -4.8621379 | R13: 0 | S13: 0 | T13: 0 | U13: 0 | V13: 0
B14: Management compensation | C14: n/a | D14: n/a | E14: n/a | F14: -1.376 | G14: -18.6 | H14: n/a | I14: n/a | J14: n/a | K14: -1.376 | L14: -18.554 | M14: 0 | N14: 0 | O14: 0 | P14: 0 | Q14: 0 | R14: 0 | S14: 0 | T14: 0 | U14: 0 | V14: 0
B15: Other Operating Income / (Expenses), net | C15: -0.30969414 | D15: 17.600429 | E15: -3.1248175 | F15: -5.5050107 | G15: 8.8609066 | H15: -0.33128979 | I15: 17.76247 | J15: -2.8601476 | K15: -2.9391877 | L15: 11.631845 | M15: 0.66628165 | N15: -0.40178625 | O15: 0.57821055 | P15: -1.7148108 | Q15: -0.8721049 | R15: -0.32634875 | S15: 0.68142964 | T15: -0.28913036 | U15: 0.06046266 | V15: 0.12641318
B16: Financial Income / (Expenses), net | C16: -37.792542 | D16: -11.410723 | E16: -84.982842 | F16: -24.066619 | G16: -158.25273 | H16: -37.282343 | I16: -8.0486679 | J16: -83.699852 | K16: -19.315627 | L16: -148.34649 | M16: -0.43947605 | N16: -3.6655009 | O16: -1.8746974 | P16: -6.7992183 | Q16: -12.778893 | R16: -0.07072364 | S16: 0.30344543 | T16: 0.59170775 | U16: 2.0482261 | V16: 2.8726557
B17: Income Tax and Social Contribution | C17: -57.395621 | D17: -110.66879 | E17: -77.22227 | F17: -164.64174 | G17: -409.92843 | H17: -55.84857 | I17: -102.68201 | J17: -70.356545 | K17: -154.67364 | L17: -383.56077 | M17: -1.4845131 | N17: -7.650724 | O17: -6.5065539 | P17: -9.1455334 | Q17: -24.787324 | R17: -0.062537854 | S17: -0.33605658 | T17: -0.35917156 | U17: -0.8225697 | V17: -1.5803357
B18: Noncontrolling shareholders | C18: -0.17875649 | D18: -0.48652279 | E18: 0.63278314 | F18: -5.1656754 | G18: -5.1981716 | H18: 0 | I18: 0 | J18: 0 | K18: 0 | L18: 0 | M18: 0 | N18: 0 | O18: 0 | P18: 0 | Q18: 0 | R18: -0.17875649 | S18: -0.48652279 | T18: 0.63278314 | U18: -5.1656754 | V18: -5.1981716
B19: Net Income** | C19: 124.63394 | D19: 240.21443 | E19: 183.6633 | F19: 294.04743 | G19: 842.58411 | H19: 137.00079 | I19: 241.0177 | J19: 183.35651 | K19: 290.72664 | L19: 852.10164 | M19: -4.0639315 | N19: 1.9437844 | O19: 6.1462804 | P19: -0.19163931 | Q19: 3.834494 | R19: -5.1667152 | S19: 0.83509922 | T19: -1.5257822 | U19: 8.169471 | V19: 2.3120727
B20: EBITDA* | C20: 262.06915 | D20: 409.8839 | E20: 398.31688 | F20: 538.66685 | G20: 1608.9618 | H20: 269.5405 | I20: 395.60355 | J20: 385.9065 | K20: 506.03283 | L20: 1557.0834 | M20: -0.059402655 | N20: 15.533353 | O20: 17.2029 | P20: 20.388062 | Q20: 53.064913 | R20: -4.4033439 | S20: 2.1893324 | T20: -0.65219016 | U20: 16.617837 | V20: 13.751635
B23: Gross Margin | C23: 0.70106569 | D23: 0.70648986 | E23: 0.70737831 | F23: 0.6844431 | G23: 0.69885489 | H23: 0.70112804 | I23: 0.70254051 | J23: 0.70404485 | K23: 0.67487834 | L23: 0.69417942 | M23: 0.6920816 | N23: 0.71105806 | O23: 0.70272988 | P23: 0.70724917 | Q23: 0.70422381 | R23: 0.84229656 | S23: 0.87011953 | T23: 0.86218162 | U23: 0.84949286 | V23: 0.85676827
B24: Selling, Marketing and Logistics Expenses/Net Revenue | C24: 0.37258226 | D24: 0.35959057 | E24: 0.34874848 | F24: 0.32805396 | G24: 0.34723187 | H24: 0.35601958 | I24: 0.34476183 | J24: 0.32993713 | K24: 0.30513064 | L24: 0.32895939 | M24: 0.4867928 | N24: 0.4697724 | O24: 0.47404143 | P24: 0.49289288 | Q24: 0.48112004 | R24: 0.11499483 | S24: 0.13118098 | T24: 0.12896629 | U24: 0.11487794 | V24: 0.12220775
B25: Administrative, R&D, IT and Projects Expenses/Net Revenue | C25: 0.16559102 | D25: 0.14572648 | E25: 0.16260066 | F25: 0.13148615 | G25: 0.13955211 | H25: 0.14720415 | I25: 0.12755334 | J25: 0.14220991 | K25: 0.11241046 | L25: 0.11949605 | M25: 0.21116975 | N25: 0.16896519 | O25: 0.1732372 | P25: 0.1603346 | Q25: 0.17495513 | R25: 1.1580185 | S25: 0.71537343 | T25: 0.78763779 | U25: 0.53452981 | V25: 0.6903894
B26: Net Margin | C26: 0.092235121 | D26: 0.13999828 | E26: 0.10331383 | F26: 0.13578207 | G26: 0.12019217 | H26: 0.11764599 | I26: 0.16613989 | J26: 0.12495839 | K26: 0.16172366 | L26: 0.14490971 | M26: -0.023403065 | N26: 0.0083339616 | O26: 0.022839036 | P26: -0.00063258193 | Q26: 0.0039169583 | R26: -0.49143547 | S26: 0.029249567 | T26: -0.039504266 | U26: 0.13566153 | V26: 0.016765439
B27: EBITDA Margin | C27: 0.19394379 | D27: 0.23888256 | E27: 0.22406023 | F27: 0.24873979 | G27: 0.22951371 | H27: 0.23146114 | I27: 0.27270002 | J27: 0.26299724 | K27: 0.28149289 | L27: 0.26479999 | M27: -0.00034208357 | N27: 0.066599139 | O27: 0.063924461 | P27: 0.067298925 | Q27: 0.054206123 | R27: -0.41882691 | S27: 0.076681934 | T27: -0.016885957 | U27: 0.27595437 | V27: 0.099716673
B29: (*) EBITDA = Income from operations before financial effects + depreciation & amortization.

Sheet 2014
B2: 2014 | H2: Pro-Forma
B3: (R$ million) | C3: Consolidated | H3: Brazil | M3: Latam | R3: Aesop
C4: 1Q16 | D4: 2Q16 | E4: 3Q16 | F4: 4Q16 | G4: 2016 | H4: 1Q16 | I4: 2Q16 | J4: 3Q16 | K4: 4Q16 | L4: 2016 | M4: 1Q16 | N4: 2Q16 | O4: 3Q16 | P4: 4Q16 | Q4: 2016 | R4: 1Q16 | S4: 2Q16 | T4: 3Q16 | U4: 4Q16 | V4: 2016
B5: Total Consultants - end of period ('000)2 | C5: 1650.518 | D5: 1698.971 | E5: 1728.761 | F5: 1742.8 | G5: =F5 -> 1742.8 | H5: 1276.356 | I5: 1300.685 | J5: 1314.237 | K5: 1318.531 | L5: =K5 -> 1318.531 | M5: 374.162 | N5: 396.7 | O5: 413 | P5: 422.5 | Q5: =P5 -> 422.5 | R5: 0 | S5: 0 | T5: 0 | U5: 0 | V5: =U5 -> 0
B6: Total Consultants - average of period ('000) | C6: 1636.6418 | D6: 1691.9816 | E6: 1712.273 | F6: 1745.5 | G6: 1699.3 | H6: 1261.0715 | I6: 1303.1762 | J6: 1303.3878 | K6: 1323.8388 | L6: 1299.6 | M6: 375.57025 | N6: 387.2 | O6: 407.4 | P6: 421.6 | Q6: 399.7 | R6: 0 | S6: 0 | T6: 0 | U6: 0 | V6: =AVERAGE(R6:U6) -> 0
B7: Units sold – items for resale (in million) | C7: 129.12184 | D7: 131.56056 | E7: 130.6423 | F7: 143.4 | G7: =SUM(C7:F7) -> 534.7247 | H7: 110.17118 | I7: 111.54147 | J7: 107.58417 | K7: 117.57353 | L7: =SUM(H7:K7) -> 446.87035 | M7: 18.17 | N7: 19 | O7: 22.06 | P7: 24.3 | Q7: =SUM(M7:P7) -> 83.53 | R7: 0.62674495 | S7: 0.80099796 | T7: 0.75173918 | U7: 1.2 | V7: =SUM(R7:U7) -> 3.3794821
B8: Gross Revenue | C8: 2085.3 | D8: 2421.55 | E8: 2512.47 | F8: 2931.0015 | G8: =SUM(C8:F8) -> 9950.3215 | H8: 1734.7385 | I8: 2017.3875 | J8: 2059.6295 | K8: 2373.8574 | L8: =SUM(H8:K8) -> 8185.6129 | M8: 296.79435 | N8: 343.86012 | O8: 387.10748 | P8: 456.37059 | Q8: =SUM(M8:P8) -> 1484.1325 | R8: 50.63114 | S8: 56.12109 | T8: 62.581744 | U8: 95.835562 | V8: =SUM(R8:U8) -> 265.16954
B9: Net Revenue | C9: 1556.19 | D9: 1802.64 | E9: 1867.4 | F9: 2182.2 | G9: =SUM(C9:F9) -> 7408.43 | H9: 1270.496 | I9: 1476.8052 | J9: 1506.8768 | K9: 1735.0197 | L9: =SUM(H9:K9) -> 5989.1977 | M9: 236.86053 | N9: 271.04631 | O9: 300.59187 | P9: 355.5 | Q9: =SUM(M9:P9) -> 1163.9987 | R9: 46.28075 | S9: 51.298986 | T9: 57.220766 | U9: 87.6 | V9: =SUM(R9:U9) -> 242.4005
B10: Gross Profit | C10: 1082.4 | D10: 1230.5 | E10: 1316.6 | F10: 1504.5 | G10: =SUM(C10:F10) -> 5134 | H10: 873.7 | I10: 992.1 | J10: 1062.4 | K10: 1185.6 | L10: =SUM(H10:K10) -> 4113.8 | M10: 165.11703 | N10: 190.95031 | O10: 202.4 | P10: 240.9 | Q10: =SUM(M10:P10) -> 799.36734 | R10: 41.766173 | S10: 44.760879 | T10: 49.858352 | U10: 75.051006 | V10: =SUM(R10:U10) -> 211.43641
B11: Selling, Marketing and Logistics Expenses | C11: -602.73527 | D11: -660.66729 | E11: -664.64799 | F11: -752.49336 | G11: =SUM(C11:F11) -> -2680.5439 | H11: -471.20817 | I11: -517.35994 | J11: -508.64119 | K11: -579.75959 | L11: =SUM(H11:K11) -> -2076.9689 | M11: -120.71837 | N11: -134.77989 | O11: -145.86781 | P11: -160.7 | Q11: =SUM(M11:P11) -> -562.06607 | R11: -7.2241904 | S11: -4.5633139 | T11: -6.2205077 | U11: -8.4 | V11: =SUM(R11:U11) -> -26.408012
B12: Administrative, R&D, IT and Projects Expenses | C12: -263.77685 | D12: -257.97478 | E12: -278.06645 | F12: -308.78423 | G12: =SUM(C12:F12) -> -1108.6023 | H12: -189.15368 | I12: -176.95675 | J12: -190.37872 | K12: -208.21675 | L12: =SUM(H12:K12) -> -764.7059 | M12: -40.434628 | N12: -42.338498 | O12: -43.656053 | P12: -55.8 | Q12: =SUM(M12:P12) -> -182.22918 | R12: -31.745609 | S12: -35.991579 | T12: -41.505644 | U12: -41.8 | V12: =SUM(R12:U12) -> -151.04283
B13: Other Operating Income / (Expenses), net | C13: 11.258362 | D13: 4.1977652 | E13: 1.509271 | F13: 2.8206388 | G13: =SUM(C13:F13) -> 19.786037 | H13: 5.5853201 | I13: 4.3584763 | J13: 1.3565188 | K13: 3.1057729 | L13: =SUM(H13:K13) -> 14.406088 | M13: -0.55882832 | N13: -0.21365088 | O13: 0.33860043 | P13: -0.33815707 | Q13: =SUM(M13:P13) -> -0.77203585 | R13: 6.2318701 | S13: 0.052939786 | T13: -0.18584826 | U13: 0.1 | V13: =SUM(R13:U13) -> 6.1989616
B14: Financial Income / (Expenses), net | C14: -51.892256 | D14: -61.170013 | E14: -63.657058 | F14: -91.559809 | G14: =SUM(C14:F14) -> -268.27914 | H14: -51.914331 | I14: -58.973704 | J14: -61.947636 | K14: -94.221378 | L14: =SUM(H14:K14) -> -267.05705 | M14: 0.11957006 | N14: -0.39196334 | O14: -0.21102199 | P14: -0.8 | Q14: =SUM(M14:P14) -> -1.2834153 | R14: -0.097494573 | S14: -1.8043453 | T14: -1.4983996 | U14: 3.5 | V14: =SUM(R14:U14) -> 0.099760461
B15: Income Tax and Social Contribution | C15: -57.125354 | D15: -78.369559 | E15: -98.210926 | F15: -121.46628 | G15: =SUM(C15:F15) -> -355.17212 | H15: -52.205817 | I15: -70.717839 | J15: -81.525933 | K15: -101.79073 | L15: =SUM(H15:K15) -> -306.24032 | M15: -4.6579893 | N15: -5.0994366 | O15: -12.971037 | P15: -13.4 | Q15: =SUM(M15:P15) -> -36.128463 | R15: -0.26154851 | S15: -2.5522838 | T15: -3.7139555 | U15: -6.3 | V15: =SUM(R15:U15) -> -12.827788
B16: Noncontrolling shareholders | C16: -0.94616339 | D16: -0.69445523 | E16: 1.0596154 | F16: -7.8212299 | G16: =SUM(C16:F16) -> -8.4022331 | H16: 0 | I16: 0 | J16: 0 | K16: 0 | L16: =SUM(H16:K16) -> 0 | M16: 0 | N16: 0 | O16: 0 | P16: 0 | Q16: =SUM(M16:P16) -> 0 | R16: -0.94616339 | S16: -0.69445523 | T16: 1.0596154 | U16: -7.8 | V16: =SUM(R16:U16) -> -8.3810032
B17: Net Income** | C17: 117.2 | D17: 175.84876 | E17: 214.63335 | F17: 225.18015 | G17: =SUM(C17:F17) -> 732.86226 | H17: 114.8 | I17: 172.5 | J17: 221.2 | K17: 204.8 | L17: =SUM(H17:K17) -> 713.3 | M17: -1.1332195 | N17: 8.1268727 | O17: 0.059586019 | P17: 9.7960988 | Q17: =SUM(M17:P17) -> 16.849338 | R17: 7.7230378 | S17: -0.79215891 | T17: -2.2063876 | U17: 14.4 | V17: =SUM(R17:U17) -> 19.124491
B18: EBITDA* | C18: 283.61593 | D18: 352.33377 | E18: 427.09048 | F18: 491.42663 | G18: =SUM(C18:F18) -> 1554.4668 | H18: 269.9 | I18: 331.94 | J18: 409.14 | K18: 440.74 | L18: =SUM(H18:K18) -> 1451.72 | M18: 5.8439602 | N18: 16.388381 | O18: 15.814939 | P18: 26.631277 | Q18: =SUM(M18:P18) -> 64.678557 | R18: 11.766065 | S18: 7.6566219 | T18: 6.2309026 | U18: 27.4 | V18: =SUM(R18:U18) -> 53.053589
B21: Gross Margin | C21: 0.696 | D21: 0.683 | E21: 0.70850731 | F21: 0.689 | G21: 0.693 | H21: 0.688 | I21: 0.672 | J21: 0.705 | K21: 0.683 | L21: 0.687 | M21: 0.69710657 | N21: 0.70449332 | O21: 0.673 | P21: 0.678 | Q21: 0.687 | R21: 0.90245239 | S21: 0.87254901 | T21: 0.87133318 | U21: 0.857 | V21: 0.872
B22: Selling, Marketing and Logistics Expenses/Net Revenue | C22: 0.38725625 | D22: 0.367 | E22: 0.35601579 | F22: 0.345 | G22: 0.362 | H22: 0.37081311 | I22: 0.35 | J22: 0.33769927 | K22: 0.334 | L22: 0.347 | M22: 0.50966016 | N22: 0.4972578 | O22: 0.485 | P22: 0.452 | Q22: 0.483 | R22: 0.15609493 | S22: 0.088955246 | T22: 0.10871067 | U22: 0.095 | V22: 0.109
B23: Administrative, R&D, IT and Projects Expenses/Net Revenue | C23: 0.17 | D23: 0.143 | E23: 0.149 | F23: 0.141 | G23: 0.15 | H23: 0.149 | I23: 0.12 | J23: 0.126 | K23: 0.12 | L23: 0.128 | M23: 0.17071071 | N23: 0.15620393 | O23: 0.145 | P23: 0.157 | Q23: 0.15722866 | R23: 0.68593549 | S23: 0.70160411 | T23: 0.72535981 | U23: 0.477 | V23: 0.623
B24: Net Margin | C24: 0.075274046 | D24: 0.097550725 | E24: 0.11494493 | F24: 0.10318775 | G24: 0.099 | H24: 0.09 | I24: 0.117 | J24: 0.147 | K24: 0.118 | L24: 0.119 | M24: -0.0047843325 | N24: 0.029983337 | O24: 0 | P24: 0.028 | Q24: 0.014 | R24: 0.16687365 | S24: -0.015441999 | T24: -0.038559211 | U24: 0.164 | V24: 0.079
B25: EBITDA Margin | C25: 0.18225038 | D25: 0.1954544 | E25: 0.22872441 | F25: 0.22519395 | G25: 0.21 | H25: 0.212 | I25: 0.225 | J25: 0.272 | K25: 0.254 | L25: 0.242 | M25: 0.02467258 | N25: 0.0604634 | O25: 0.053 | P25: 0.075 | Q25: 0.056 | R25: 0.25423237 | S25: 0.14925484 | T25: 0.10889233 | U25: 0.313 | V25: 0.219
B27: (*) EBITDA = Income from operations before financial effects + depreciation & amortization.

Sheet VP
B1: FATOR | C1: HOJE | D1: PROJ | E1: DIAS | L1: Preço Gmat3 | M1: {=+_FV(H11,"Price")} -> 10.52 | O1: CAGR
B2: =(1+WACC!E8)^(E2/360) -> 1.1115876 | C2: =+TODAY() -> 46118 | D2: 46387 | E2: =+DAYS360(C2,D2) -> 265 | L2: Mkt Cap | M2: {=+_FV(H11,"Market cap",TRUE)/1000000} -> 14460.35
C3: FCF | L3: LL 26 | M3: =+Resumo!Q38 -> 1022.7266
B4: Soma dos FCF | C4: =+SUM(WACC!F16:I16) -> 3455.7632 | D4: GR% | L4: P/E 2026 hj | M4: =+M2/M3 -> 14.139018
B5: (+) Perpetuidade | C5: =+C31 -> 3039.735 | D5: =+I15 -> 0.0675 | L5: Upside | M5: =+M7/M4-1 -> -0.47938661
B6: EV | C6: =+C4+C5 -> 6495.4982
B7: (-) Total Debt | C7: =+PROJ!BO157 -> 6357.221 | L7: P/E tgt | M7: =+M9*M27+P9*P27 -> 7.3609622
B8: (+) Caixa | C8: =+PROJ!BO155 -> 2654.1155
B9: (+) VP Outros Ativos Fin Líquidos | C9: =+PROJ!BO156 -> 1180.547 | L9: Lula | M9: 0.5 | O9: Not Lula | P9: =1-M9 -> 0.5
B10: (+) Investimentos | C10: 0
B11: (+) Outros Ativos Não Oper. | C11: 0 | H11: #VALUE! | I11: 2025
B12: (-) Opções | C12: 0 | H12: ROE1 | I12: 0.12 | L12: ROE1 | M12: =+I12 -> 0.12 | O12: ROE1 | P12: =+M12 -> 0.12
B13: (+) Ajuste Dividendos | C13: =+PROJ!BO233 -> 0 | H13: ROE2 | I13: 0.15 | L13: ROE2 | M13: =+I13 -> 0.15 | O13: ROE2 | P13: =+M13 -> 0.15
B14: (-) Minoritários | C14: 0 | H14: G1 | I14: =+Resumo!V38 -> 0.11561801 | L14: G1 | M14: =+I14 -> 0.11561801 | O14: G1 | P14: =+M14 -> 0.11561801
B15: Valor de Mercado Proj | C15: =+C6-C7+C8+C9+C10+C11-C12+C13-C14 -> 3972.9397 | H15: G2 | I15: =+I19+I20+I21 -> 0.0675 | L15: G2 | M15: =+M19+M20+M21 -> 0.07 | O15: G2 | P15: =+P19+P20+P21 -> 0.075
B16: Num Ações | C16: {=+_FV(H11,"Shares outstanding",TRUE)/1000000} -> 1374.558 | H16: Ke | I16: =+(I22+I19)+(I24*I23) -> 0.1525 | L16: Ke | M16: =+(M22+M19)+(M24*M23) -> 0.16 | O16: Ke | P16: =+(P22+P19)+(P24*P23) -> 0.13
B17: Cot R$ DEZ/2026 PROJ | C17: =+C15/C16 -> 2.8903398 | H17: N (moat) | I17: 5 | L17: N (moat) | M17: =+I17 -> 5 | O17: N (moat) | P17: =+M17 -> 5
B18: Cot R$ HOJE PROJ | C18: =+C17/B2 -> 2.6001907
B19: Cot R$ 12m | C19: =+C18*(1+WACC!F8) -> 3.0097207 | H19: INFL | I19: =+MACRO!$BP$8 -> 0.0425 | L19: INFL | M19: 0.045 | O19: INFL | P19: 0.04
H20: GDP Perp | I20: 0.025 | L20: GDP Perp | M20: 0.025 | O20: GDP Perp | P20: 0.035
B21: Cot R$ HJ | C21: {=+_FV(H11,"Price")} -> 10.52 | H21: Aj. G2 | I21: 0 | L21: Aj. G2 | M21: 0 | O21: Aj. G2 | P21: =+M21 -> 0
B22: var% | C22: =+C17/C21-1 -> -0.72525287 | H22: BNTNB | I22: 0.065 | L22: BNTNB | M22: =+[1]BRASIL!$P$3 -> 0.07 | O22: BNTNB | P22: =+[1]BRASIL!$R$3 -> 0.045
H23: ERP | I23: 0.045 | L23: ERP | M23: 0.045 | O23: ERP | P23: =+M23 -> 0.045
B24: Valor de Mercado hj | C24: =+C21*C16 -> 14460.35 | H24: Beta | I24: 1 | L24: Beta | M24: =+I24 -> 1 | O24: Beta | P24: =+M24 -> 1
H26: P/E Target | I26: =+(((1-I14/I12)*(1+I14)*(1-(((1+I14)^I17)/((1+I16)^I17))))/(I16-I14))+(((1-I15/I13)*((1+I14)^I17)*(1+I15))/((I16-I15)*((1+I16)^I17))) -> 6.0364122
B27: Noplat 2030 | C27: =+PROJ!BS62 -> 1355.8745 | H27: UPSIDE 2026 | L27: P/E Target 2026 | M27: =+(((1-M14/M12)*(1+M14)*(1-(((1+M14)^M17)/((1+M16)^M17))))/(M16-M14))+(((1-M15/M13)*((1+M14)^M17)*(1+M15))/((M16-M15)*((1+M16)^M17))) -> 5.3797464 | O27: P/E Target 2026 | P27: =+(((1-P14/P12)*(1+P14)*(1-(((1+P14)^P17)/((1+P16)^P17))))/(P16-P14))+(((1-P15/P13)*((1+P14)^P17)*(1+P15))/((P16-P15)*((1+P16)^P17))) -> 9.3421781
B28: ROIC | C28: 0.1
B29: G | C29: =D5 -> 0.0675
B30: Wacc | C30: =WACC!I3 -> 0.155 | H30: =22*8 -> 176
B31: Perp | C31: =(C27*(1+C29)*(1-C29/C28)/(C30-C29))/WACC!I15 -> 3039.735 | H31: =8/H30 -> 0.045454545

Sheet WACC
B1: DRE | D1: 2025 | E1: =+D1+1 -> 2026 | F1: =+E1+1 -> 2027 | G1: =+F1+1 -> 2028 | H1: =+G1+1 -> 2029 | I1: =+H1+1 -> 2030
B3: WACC % | E3: =+E4*E5+(1-E4)*(E8) -> 0.14615487 | F3: =+F4*F5+(1-F4)*(F8) -> 0.1504099 | G3: =+G4*G5+(1-G4)*(G8) -> 0.15241889 | H3: =+H4*H5+(1-H4)*(H8) -> 0.155 | I3: =+H3 -> 0.155
B4: Alavancagem | E4: =+IF(Resumo!Q70/Resumo!Q71>0,Resumo!Q70/Resumo!Q71,0) -> 0.14853513 | F4: =+IF(Resumo!R70/Resumo!R71>0,Resumo!R70/Resumo!R71,0) -> 0.095799238 | G4: =+IF(Resumo!S70/Resumo!S71>0,Resumo!S70/Resumo!S71,0) -> 0.034350734 | H4: =+IF(Resumo!T70/Resumo!T71>0,Resumo!T70/Resumo!T71,0) -> 0 | I4: =+IF(Resumo!U70/Resumo!U71>0,Resumo!U70/Resumo!U71,0) -> 0
B5: Rdebt % | E5: =+(E6)*(1-E7) -> 0.09801 | F5: =+(F6)*(1-F7) -> 0.08349 | G5: =+(G6)*(1-G7) -> 0.07986 | H5: =+(H6)*(1-H7) -> 0.0726 | I5: =+(I6)*(1-I7) -> 0.06534
B6: Debt Bruto % | E6: =110%*MACRO!BO6 -> 0.1485 | F6: =110%*MACRO!BP6 -> 0.1265 | G6: =110%*MACRO!BQ6 -> 0.121 | H6: =110%*MACRO!BR6 -> 0.11 | I6: =110%*MACRO!BS6 -> 0.099
B7: IR % | E7: 0.34 | F7: 0.34 | G7: 0.34 | H7: 0.34 | I7: 0.34
B8: Requity % | E8: =+E9+E10*E12+E11 -> 0.15455358 | F8: =+F9+F10*F12+F11 -> 0.1575 | G8: =+G9+G10*G12+G11 -> 0.155 | H8: =+H9+H10*H12+H11 -> 0.155 | I8: =+I9+I10*I12+I11 -> 0.155
B9: Juros Real | E9: 0.07 | F9: =+E9 -> 0.07 | G9: =+F9 -> 0.07 | H9: =+G9 -> 0.07 | I9: =+H9 -> 0.07
B10: Equity risk premium | E10: 0.045 | F10: 0.045 | G10: 0.045 | H10: 0.045 | I10: 0.045
B11: IPCA | E11: =+MACRO!BO8 -> 0.039553578 | F11: =+MACRO!BP8 -> 0.0425 | G11: =+MACRO!BQ8 -> 0.04 | H11: =+MACRO!BR8 -> 0.04 | I11: =+MACRO!BS8 -> 0.04
B12: Beta | E12: 1 | F12: =+E12 -> 1 | G12: =+F12 -> 1 | H12: =+G12 -> 1 | I12: =+H12 -> 1
B14: FCFF | C14: =-VP!C24 -> -14460.35 | E14: =+PROJ!BO68 -> 1106.8179 | F14: =+PROJ!BP68 -> 1263.7787 | G14: =+PROJ!BQ68 -> 1172.0042 | H14: =+PROJ!BR68 -> 1190.0232 | I14: =+PROJ!BS68 -> 1230.9881 | J14: =+I14*(1+VP!D5)/(WACC!I3-VP!D5) -> 15018.055
B15: FD | E15: 1 | F15: =+E15*(1+F3) -> 1.1504099 | G15: =+F15*(1+G3) -> 1.3257541 | H15: =+G15*(1+H3) -> 1.531246 | I15: =+H15*(1+I3) -> 1.7685891
B16: VP | E16: =+E14/E15 -> 1106.8179 | F16: =+F14/F15 -> 1098.5464 | G16: =+G14/G15 -> 884.02834 | H16: =+H14/H15 -> 777.16007 | I16: =+I14/I15 -> 696.02834 | J16: =+I16*(1+VP!D5)/(WACC!I3-VP!D5) -> 8491.5457
C17: IRR | D17: =+IRR(C14:J14,0) -> 0.076282772
B19: Yield | D19: =+D14/VP!$C$24 -> 0 | E19: =+E14/VP!$C$24 -> 0.076541569 | F19: =+F14/VP!$C$24 -> 0.087396132 | G19: =+G14/VP!$C$24 -> 0.081049503 | H19: =+H14/VP!$C$24 -> 0.082295602 | I19: =+I14/VP!$C$24 -> 0.085128515

Sheet Resumo
B1: NATURA | N1: Preço: | O1: =+VP!C21 -> 10.52 | X1: BBG
B2: DRE - MILLONES BRL | C2: 2015 | G2: =+C2+1 -> 2016 | H2: =+G2+1 -> 2017 | I2: =+H2+1 -> 2018 | J2: =+I2+1 -> 2019 | K2: =+J2+1 -> 2020 | L2: =+K2+1 -> 2021 | M2: =+L2+1 -> 2022 | N2: =+M2+1 -> 2023 | O2: =+N2+1 -> 2024 | ... U2: =+T2+1 -> 2030 | X2: 2026 | Y2: 2027
B3: Receita Bruta | C3: =+PROJ!BD5 -> 7899 | G3: =+PROJ!BE5 -> 7912.6711 | H3: =+PROJ!BF5 -> 9852.7476 | I3: =+FAT!BH8 -> 18514.468 | J3: =+FAT!BJ8 -> 19708.1 | K3: =+FAT!BK8 -> 47697 | L3: =+FAT!BL8 -> 51644.2 | M3: =+FAT!BM8 -> 47108.6 | N3: =+FAT!BN8 -> 38175.466 | O3: =+FAT!BO8 -> 31586.823 | P3: =+FAT!BP8 -> 29494.8 | Q3: =+FAT!BQ8 -> 30341.943 | ... U3: =+FAT!BU8 -> 35383.328 | AD3: BRL | AE3: 5.5
B4: y-o-y | G4: =+G3/C3-1 -> 0.0017307428 | H4: =+H3/G3-1 -> 0.24518604 | I4: =+I3/H3-1 -> 0.87911727 | J4: =+J3/I3-1 -> 0.064470219 | K4: =+K3/J3-1 -> 1.4201724 | L4: =+L3/K3-1 -> 0.082755729 | M4: =+M3/L3-1 -> -0.087823996 | N4: =+N3/M3-1 -> -0.18962852 | O4: =+O3/N3-1 -> -0.17258842 | ... U4: =+U3/T3-1 -> 0.035344534 | AD4: Interest | AE4: 0.06
B6: Natura & co Latam | J6: =+FAT!BJ36 -> 25344 | K6: =+FAT!BK36 -> 27584.5 | L6: =+FAT!BL36 -> 29693.4 | M6: =+FAT!BM36 -> 29158 | N6: =+FAT!BN36 -> 27220.844 | O6: =+FAT!BO36 -> 31586.823 | P6: =+FAT!BP36 -> 29494.8 | Q6: =+FAT!BQ36 -> 30341.943 | ... U6: =+FAT!BU36 -> 35383.328 | V6: =+O69-700 -> 13760.35
B7: yoy | K7: =+K6/J6-1 -> 0.088403567 | L7: =+L6/K6-1 -> 0.076452355 | M7: =+M6/L6-1 -> -0.018030943 | N7: =+N6/M6-1 -> -0.066436516 | O7: =+O6/N6-1 -> 0.16039102 | P7: =+P6/O6-1 -> -0.066230874 | Q7: =+Q6/P6-1 -> 0.028721766 | R7: =+R6/Q6-1 -> 0.044724877 | ... U7: =+U6/T6-1 -> 0.035344534 | V7: =+V6/O6 -> 0.43563578
B8: %RB | J8: =+J6/J$3 -> 1.2859687 | K8: =+K6/K$3 -> 0.57832778 | L8: =+L6/L$3 -> 0.57496098 | M8: =+M6/M$3 -> 0.6189528 | N8: =+N6/N$3 -> 0.71304549 | O8: =+O6/O$3 -> 1 | P8: =+P6/P$3 -> 1 | Q8: =+Q6/Q$3 -> 1 | ... U8: =+U6/U$3 -> 1
B9: Avon Int | J9: =+FAT!BJ40 -> 10926.2 | K9: =+FAT!BK40 -> 10891.5 | L9: =+FAT!BL40 -> 11189 | M9: =+FAT!BM40 -> 8728.6 | N9: =+FAT!BN40 -> 7488.008 | O9: =+FAT!BO40 -> 0 | V9: =(300*20*5.5)/2 -> 16500 | AE9: 2024
B10: yoy | K10: =+K9/J9-1 -> -0.0031758525 | L10: =+L9/K9-1 -> 0.027314879 | M10: =+M9/L9-1 -> -0.21989454 | N10: =+N9/M9-1 -> -0.14212955 | O10: =+O9/N9-1 -> -1 | AD10: Net Rev 2024 | AE10: 49000 | AF10: =+AE10*0.47*0.1 -> 2303 | AG10: =+AF10+AE10 -> 51303
B11: %RB | K11: =+K9/K$3 -> 0.22834769 | L11: =+L9/L$3 -> 0.2166555 | M11: =+M9/M$3 -> 0.18528676 | N11: =+N9/N$3 -> 0.19614713 | O11: =+O9/O$3 -> 0 | Q11: =+Q12-Q14 -> 1584.0686
P12: 23195 | Q12: 23271 | R12: 24342 | AB12: =+O9*0.1 -> 0
Q13: =+Q12/P14-1 -> 0.047420115 | R13: =+R12/Q12-1 -> 0.046022947
B14: Receita Líquida | C14: =+PROJ!BD5 -> 7899 | G14: =+PROJ!BE5 -> 7912.6711 | H14: =+PROJ!BF5 -> 9852.7476 | I14: =+PROJ!BG5 -> 13365.13 | J14: =+PROJ!BH5 -> 19447.159 | K14: =+PROJ!BI5 -> 36921.9 | L14: =+PROJ!BJ5 -> 40164.6 | M14: =+PROJ!BK5 -> 36349.2 | N14: =+PROJ!BL5 -> 29224.396 | ... U14: =+PROJ!BS5 -> 25310.623 | X14: 23271 | Y14: 24342 | AB14: =+O6*1 -> 31586.823 | AD14: EBITDA mrgn | AE14: 0.14 | AF14: 0.16
B15: y-o-y | J15: =+J14/I14-1 -> 0.4550669 | K15: =+K14/J14-1 -> 0.89857552 | L15: =+L14/K14-1 -> 0.087825924 | M15: =+M14/L14-1 -> -0.094994099 | N15: =+N14/M14-1 -> -0.19600993 | O15: =+O14/N14-1 -> -0.19817405 | P15: =+P14/O14-1 -> -0.051868691 | Q15: =+Q14/P14-1 -> -0.023878295 | ... U15: =+U14/T14-1 -> 0.03565074 | AB15: =+AB14+AB12 -> 31586.823 | AD15: EBITDA | AE15: =+AE14*AE10 -> 6860 | AF15: =+AF14*AE10 -> 7840 | AG15: =+AG10*AE14 -> 7182.42
B17: CPV | C17: =+PROJ!BD7 -> -2416.024 | G17: =+PROJ!BE7 -> -2446.9186 | H17: =+PROJ!BF7 -> -2911.0774 | I17: =+PROJ!BG7 -> -3761.8972 | J17: =+PROJ!BH7 -> -6191.727 | K17: =+PROJ!BI7 -> -13229.4 | L17: =+PROJ!BJ7 -> -14011.4 | M17: =+PROJ!BK7 -> -13155.3 | N17: =+PROJ!BL7 -> -10238.485 | ... U17: =+PROJ!BS7 -> -8536.7894
B18: Lucro Bruto | C18: =+PROJ!BD8 -> 5482.976 | G18: =+PROJ!BE8 -> 5465.7526 | H18: =+PROJ!BF8 -> 6941.6308 | I18: =+PROJ!BG8 -> 9603.2333 | J18: =+PROJ!BH8 -> 13255.432 | K18: =+PROJ!BI8 -> 23692.5 | L18: =+PROJ!BJ8 -> 26153.2 | M18: =+PROJ!BK8 -> 23193.9 | N18: =+PROJ!BL8 -> 18985.911 | ... U18: =+PROJ!BS8 -> 16773.834 | X18: =+X19*X14 -> 15505.467 | Y18: =+Y19*Y14 -> 16219.075 | AD18: EBITDA ex Brasil | AE18: =+AE15*0.47 -> 3224.2 | AF18: =+AF15*0.47 -> 3684.8
B19: mg Bruta | C19: =+C18/C3 -> 0.69413546 | G19: =+G18/G3 -> 0.69075948 | H19: =+H18/H3 -> 0.70453756 | I19: =+I18/I14 -> 0.71852896 | J19: =+J18/J14 -> 0.68161277 | K19: =+K18/K14 -> 0.64169233 | L19: =+L18/L14 -> 0.65115052 | M19: =+M18/M14 -> 0.63808557 | N19: =+N18/N14 -> 0.64965965 | O19: =+O18/O14 -> 0.65396864 | P19: =+P18/P14 -> 0.66314943 | ... U19: =+U18/U14 -> 0.66271911 | X19: 0.6663 | Y19: 0.6663
AD20: Upside x FX | AE20: =+AE18*0.1 -> 322.42 | AF20: =+AF18*0.1 -> 368.48
B21: SG&A | C21: =+PROJ!BD11 -> -4226.5 | G21: =+PROJ!BE11 -> -4382.8754 | H21: =+PROJ!BF11 -> -5582.9717 | I21: =+PROJ!BG11 -> -8339.3549 | J21: =+PROJ!BH11 -> -9059.9 | K21: =+PROJ!BI11 -> -22902.7 | L21: =+PROJ!BJ11 -> -25034.9 | M21: =+PROJ!BK11 -> -23652.3 | N21: =+PROJ!BL11 -> -19559.341 | ... U21: =+PROJ!BS11 -> -14610.249 | X21: =+X27-X18 -> -13325.467 | Y21: =+Y27-Y18 -> -13732.075 | AD21: EBITDA Final | AE21: =+AE15+AE20 -> 7182.42 | AF21: =+AF15+AF20 -> 8208.48
B22: % Net Rev | C22: =+C21/C3 -> -0.53506773 | G22: =+G21/G3 -> -0.55390592 | H22: =+H21/H3 -> -0.5666411 | I22: =+I21/I14 -> -0.6239636 | J22: =+J21/J14 -> -0.46587268 | K22: =+K21/K14 -> -0.62030123 | L22: =+L21/L14 -> -0.62330759 | M22: =+M21/M14 -> -0.65069658 | N22: =+N21/N14 -> -0.66928128 | O22: =+O21/O14 -> -0.61549484 | P22: =+P21/P14 -> -0.60434039 | ... U22: =+U21/U14 -> -0.57723783
B23: Vendas | K23: =+FAT!BK70 -> -16426.3 | L23: =+FAT!BL70 -> -17833.8 | M23: =+FAT!BM70 -> -16160.6 | N23: =+FAT!BN70 -> -13235.732 | O23: =+FAT!BO70 -> -10213.499 | P23: =+FAT!BP70 -> -9409.8 | Q23: =+FAT!BQ70 -> -9433.8152 | R23: =+FAT!BR70 -> -9742.7696 | ... U23: =+FAT!BU70 -> -10883.568
B24: G&A | K24: =+FAT!BK74 -> -5582.5 | L24: =+FAT!BL74 -> -6399.5 | M24: =+FAT!BM74 -> -6160.9 | N24: =+FAT!BN74 -> -4528.033 | O24: =+FAT!BO74 -> -2974.0579 | P24: =+FAT!BP74 -> -3085.3 | Q24: =+FAT!BQ74 -> -3085.728 | R24: =+FAT!BR74 -> -3240.0144 | ... U24: =+FAT!BU74 -> -3540.4512
B25: Outras | K25: =+FAT!BK80+FAT!BK81+FAT!BK83+FAT!BK79 -> -893.9 | L25: =+FAT!BL80+FAT!BL81+FAT!BL83+FAT!BL79 -> -801.6 | M25: =+FAT!BM80+FAT!BM81+FAT!BM83+FAT!BM79 -> -1330.8 | N25: =+FAT!BN80+FAT!BN81+FAT!BN83+FAT!BN79 -> -1795.576 | O25: =+FAT!BO80+FAT!BO81+FAT!BO83+FAT!BO79 -> -1235.2587 | P25: =+FAT!BP80+FAT!BP81+FAT!BP83+FAT!BP79 -> -931.8 | Q25: =+FAT!BQ80+FAT!BQ81+FAT!BQ83+FAT!BQ79 -> -136.23 | R25: =+FAT!BR80+FAT!BR81+FAT!BR83+FAT!BR79 -> -136.23 | ... U25: =+FAT!BU80+FAT!BU81+FAT!BU83+FAT!BU79 -> -186.23
B27: EBIT | C27: =+PROJ!BD21 -> 1256.476 | G27: =+PROJ!BE21 -> 1082.8772 | H27: =+PROJ!BF21 -> 1358.6591 | I27: =+PROJ!BG21 -> 1263.8784 | J27: =+PROJ!BH21 -> 4195.532 | K27: =+PROJ!BI21 -> 789.8 | L27: =+PROJ!BJ21 -> 1118.3 | M27: =+PROJ!BK21 -> -458.4 | N27: =+PROJ!BL21 -> -573.43029 | ... U27: =+PROJ!BS21 -> 2163.5845 | X27: 2180 | Y27: 2487
B28: Resultado Financeiro | C28: =+PROJ!BD26 -> -381.5 | G28: =+PROJ!BE26 -> -655.9 | H28: =+PROJ!BF26 -> -387.4 | I28: =+PROJ!BG26 -> -583.3 | J28: =+PROJ!BH26 -> -840.0928 | K28: =+PROJ!BI26 -> -1035.4 | L28: =+PROJ!BJ26 -> #REF! | M28: =+PROJ!BK26 -> -1900.9 | N28: =+PROJ!BL26 -> -2573.204 | ... U28: =+PROJ!BS26 -> -343.41379 | X28: =+X29-X27 -> -850 | Y28: =+Y29-Y27 -> -945
B29: EBT | C29: =+PROJ!BD32 -> 874.97604 | G29: =+PROJ!BE32 -> 426.97721 | H29: =+PROJ!BF32 -> 971.25905 | I29: =+PROJ!BG32 -> 680.57842 | J29: =+PROJ!BH32 -> 3355.4392 | K29: =+PROJ!BI32 -> -245.6 | L29: =+PROJ!BJ32 -> #REF! | M29: =+PROJ!BK32 -> -2359.3 | N29: =+PROJ!BL32 -> -3146.6343 | ... U29: =+PROJ!BS32 -> 1820.1707 | X29: 1330 | Y29: 1542 | AA29: =+X29*-0.34 -> -452.2
B30: Res Não Operacional e Descontinuadas | G30: =+PROJ!BE40 -> 0 | H30: =+PROJ!BF40 -> 0 | I30: =+PROJ!BG40 -> 0 | J30: =+PROJ!BH40 -> 0 | K30: =+PROJ!BI40 -> -143.1 | L30: =+PROJ!BJ40 -> -98.6 | M30: =+PROJ!BK40 -> -380.4 | N30: =+PROJ!BL40 -> 5924.492 | ... U30: =+PROJ!BS40 -> 0
B31: IR & CS | C31: =+PROJ!BD34 -> #REF! | G31: =+PROJ!BE34 -> #REF! | H31: =+PROJ!BF34 -> #REF! | I31: =+PROJ!BG34 -> #REF! | J31: =+PROJ!BH34 -> #REF! | K31: =+PROJ!BI34 -> -274.8 | L31: =+PROJ!BJ34 -> 1048 | M31: =+PROJ!BK34 -> -119.6 | N31: =+PROJ!BL34 -> 200.252 | ... U31: =+PROJ!BS34 -> -235.92839
B32: taxa efectiva | K32: =+K31/#REF! -> #REF! | L32: =+L31/#REF! -> #REF! | M32: =+M31/#REF! -> #REF! | N32: =+N31/#REF! -> #REF! | O32: =+O31/#REF! -> #REF! | P32: =+P31/#REF! -> #REF! | Q32: =+Q31/#REF! -> #REF! | R32: =+R31/#REF! -> #REF! | ... U32: =+U31/#REF! -> #REF!
B34: Participações | C34: =+PROJ!BD35 -> #REF! | G34: =+PROJ!BE35 -> #REF! | H34: =+PROJ!BF35 -> #REF! | I34: =+PROJ!BG35 -> #REF! | J34: =+PROJ!BH35 -> #REF! | K34: =+PROJ!BI35 -> 1.1188925 | L34: =+PROJ!BJ35 -> #REF! | M34: =+PROJ!BK35 -> 0.050693002 | N34: =+PROJ!BL35 -> -0.063640062 | ... U34: =+PROJ!BS35 -> -0.12961882
B35: Minoritários | C35: =+PROJ!BD41 -> -9.2 | G35: =+PROJ!BE41 -> -11.539987 | H35: =+PROJ!BF41 -> 0 | I35: =+PROJ!BG41 -> 0 | J35: =+PROJ!BH41 -> 0 | K35: =+PROJ!BI41 -> -13.4 | L35: =+PROJ!BJ41 -> -7.3009 | M35: =+PROJ!BK41 -> 1 | N35: =+PROJ!BL41 -> 0.923 | ... U35: =+PROJ!BS41 -> 0
B36: Tax | O36: =+PROJ!BM34 -> -957.5 | P36: =+PROJ!BN34 -> 42.5 | Q36: =+PROJ!BO34 -> -8.8737041 | R36: =+PROJ!BP34 -> 28.389143 | S36: =+PROJ!BQ34 -> -2.7376295 | T36: =+PROJ!BR34 -> -55.125261 | U36: =+PROJ!BS34 -> -235.92839 | X36: =+X38-X29 -> -90 | Y36: =+Y38-Y29 -> -42 | AA36: 200 | AD36: =2533-580 -> 1953
B37: rate | O37: =+O36/O29 -> -5.0360824 | P37: =+P36/P29 -> 0.10114551 | Q37: =+Q36/Q29 -> -0.008601882 | R37: =+R36/R29 -> 0.022371528 | S37: =+S36/S29 -> -0.0019333148 | T37: =+T36/T29 -> -0.033617665 | U37: =+U36/U29 -> -0.12961882 | X37: =+X36/X29 -> -0.067669173 | Y37: =+Y36/Y29 -> -0.027237354 | AA37: 140
B38: Lucro Líquido Op. Cont. | C38: =+PROJ!BD42 -> #REF! | G38: =+PROJ!BE42 -> #REF! | H38: =+PROJ!BF42 -> #REF! | I38: =+PROJ!BG42 -> #REF! | J38: =+PROJ!BH42 -> #REF! | K38: =+PROJ!BI42 -> -676.9 | L38: =+PROJ!BJ42 -> #REF! | M38: =+PROJ!BK42 -> -2858.3 | N38: =+PROJ!BL42 -> 2979.0327 | O38: =+PROJ!BM37 -> -767.37205 | P38: =+PROJ!BN42 -> -2202.7133 | Q38: =+PROJ!BO42 -> 1022.7266 | R38: =+PROJ!BP42 -> 1297.3746 | S38: =+PROJ!BQ42 -> 1413.2912 | T38: =+PROJ!BR42 -> 1584.6454 | U38: =+PROJ!BS42 -> 1584.2423 | V38: =(+U38/Q38)^(1/4)-1 -> 0.11561801 | X38: 1240 | Y38: 1500 | AA38: =+AA37+AA36+AA29 -> -112.2 | AD38: =+AD36*0.7 -> 1367.1
B39: y-o-y | G39: =+G38/C38-1 -> #REF! | H39: =+H38/G38-1 -> #REF! | I39: =+I38/H38-1 -> #REF! | J39: =+J38/I38-1 -> #REF! | K39: =+K38/J38-1 -> #REF! | L39: =+L38/K38-1 -> #REF! | M39: =+M38/L38-1 -> #REF! | N39: =+N38/M38-1 -> -2.0422393 | O39: =+O38/N38-1 -> -1.257591 | ... U39: =+U38/T38-1 -> -0.00025435973 | AA39: =+AA38/X29 -> -0.084360902 | AD39: =+AD38+700 -> 2067.1
B41: Op. Descontinuadas | O41: =+PROJ!BM40 -> -8163.4 | P41: =+PROJ!BN40 -> -2665.4 | Q41: =+PROJ!BO40 -> 0 | R41: =+PROJ!BP40 -> 0 | S41: =+PROJ!BQ40 -> 0 | T41: =+PROJ!BR40 -> 0 | U41: =+PROJ!BS40 -> 0
B42: Minoritarios | O42: =+PROJ!BM41 -> 0.2 | P42: =+PROJ!BN41 -> 0 | Q42: =+PROJ!BO41 -> 0 | R42: =+PROJ!BP41 -> 0 | S42: =+PROJ!BQ41 -> 0 | T42: =+PROJ!BR41 -> 0 | U42: =+PROJ!BS41 -> 0
B43: LL Reportado | O43: =+PROJ!BM42 -> -8930.5721 | P43: =+PROJ!BN42 -> -2202.7133 | Q43: =+PROJ!BO42 -> 1022.7266 | R43: =+PROJ!BP42 -> 1297.3746 | S43: =+PROJ!BQ42 -> 1413.2912 | T43: =+PROJ!BR42 -> 1584.6454 | U43: =+PROJ!BS42 -> 1584.2423
B46: FLUXO DE CAIXA FIRMA | C46: 2015 | G46: =+C46+1 -> 2016 | H46: =+G46+1 -> 2017 | I46: =+H46+1 -> 2018 | J46: =+I46+1 -> 2019 | K46: =+J46+1 -> 2020 | L46: =+K46+1 -> 2021 | M46: =+L46+1 -> 2022 | N46: =+M46+1 -> 2023 | O46: =+N46+1 -> 2024 | ... U46: =+T46+1 -> 2030
B47: EBITDA | C47: =+FAT!BE115 -> 1495.9 | G47: =+FAT!BF115 -> 1372.7955 | H47: =+FAT!BG115 -> 1741.9646 | I47: =+FAT!BH115 -> 1850.9154 | J47: =+FAT!BJ115 -> 5312.832 | K47: =+FAT!BK115 -> 3508.6 | L47: =+FAT!BL115 -> 3909.9 | M47: =+FAT!BM115 -> 2133.5 | N47: =+FAT!BN115 -> 1521.4556 | O47: =+FAT!BO115 -> 1850.5519 | P47: =+FAT!BP115 -> 2215.8867 | Q47: =+FAT!BQ115 -> 2605.4186 | ... U47: =+FAT!BU115 -> 2876.1208 | X47: 3081 | Y47: 3307
B48: y-o-y | G48: =+G47/C47-1 -> -0.082294611 | H48: =+H47/G47-1 -> 0.26891776 | I48: =+I47/H47-1 -> 0.062544796 | J48: =+J47/I47-1 -> 1.8703808 | K48: =+K47/J47-1 -> -0.33959892 | L48: =+L47/K47-1 -> 0.1143761 | M48: =+M47/L47-1 -> -0.45433387 | N48: =+N47/M47-1 -> -0.28687339 | O48: =+O47/N47-1 -> 0.2163036 | ... U48: =+U47/T47-1 -> 0.032135745
B49: margem EBITDA | C49: =+C47/C$3 -> 0.1893784 | G49: =+G47/G$3 -> 0.17349331 | H49: =+H47/H$3 -> 0.17679988 | I49: =+I47/I$14 -> 0.13848839 | J49: =+J47/J$14 -> 0.27319322 | K49: =+K47/K$14 -> 0.095027612 | L49: =+L47/L$14 -> 0.097346917 | M49: =+M47/M$14 -> 0.058694552 | N49: =+N47/N$14 -> 0.052061149 | O49: =+O47/O$14 -> 0.078972454 | P49: =+P47/P$14 -> 0.099736338 | ... U49: =+U47/U$14 -> 0.11363295
B51: EBITDA Adj | C51: =+FAT!BE121 -> #REF! | G51: =+FAT!BF121 -> #REF! | H51: =+FAT!BG121 -> #REF! | K51: =+FAT!BK121 -> 4219.7 | L51: =+FAT!BL121 -> 4136.5 | M51: =+FAT!BM121 -> 3158.7 | N51: =+FAT!BN121 -> 3016.9506 | O51: =+FAT!BO121 -> 2862 | P51: =+FAT!BP121 -> 3132 | Q51: =+FAT!BQ121 -> 2605.4186 | R51: =+FAT!BR121 -> 2684.439 | ... U51: =+FAT!BU121 -> 2926.1208
B52: y-o-y | G52: =+G51/C51-1 -> #REF! | H52: =+H51/G51-1 -> #REF! | L52: =+L51/K51-1 -> -0.019717041 | M52: =+M51/L51-1 -> -0.23638342 | N52: =+N51/M51-1 -> -0.044875875 | O52: =+O51/N51-1 -> -0.051359998 | P52: =+P51/O51-1 -> 0.094339623 | Q52: =+Q51/P51-1 -> -0.16812945 | R52: =+R51/Q51-1 -> 0.030329286 | S52: =+S51/R51-1 -> 0.023258228 | ... U52: =+U51/T51-1 -> 0.031569291
B53: margem EBITDA | C53: =+C51/C$3 -> #REF! | G53: =+G51/G$3 -> #REF! | H53: =+H51/H$3 -> #REF! | K53: =+K51/K$14 -> 0.11428718 | L53: =+L51/L$14 -> 0.1029887 | M53: =+M51/M$14 -> 0.086898749 | N53: =+N51/N$14 -> 0.10323398 | O53: =+O51/O$14 -> 0.12213608 | P53: =+P51/P$14 -> 0.1409703 | Q53: =+Q51/Q$14 -> 0.12013772 | R53: =+R51/R$14 -> 0.11847851 | ... U53: =+U51/U$14 -> 0.11560841
AD54: =49000*0.015 -> 735
AD55: =+AD54*0.7 -> 514.5
B56: EBITDA Latam | K56: =+FAT!BK238 -> 2293.1199 | L56: =+FAT!BL238 -> 2298.9661 | M56: =+FAT!BM238 -> 1838.3324 | N56: =+FAT!BN238 -> 2128.6403 | O56: =+FAT!BO238 -> 2602.5774 | P56: =+FAT!BP238 -> 2743.1723 | Q56: =+FAT!BQ238 -> 2741.6486 | R56: =+FAT!BR238 -> 2820.669 | ... U56: =+FAT!BU238 -> 3012.3508
B57: mrgn | K57: =+FAT!BK240 -> 0.11162971 | L57: =+FAT!BL240 -> 0.10257105 | M57: =+FAT!BM240 -> 0.083457378 | N57: =+FAT!BN240 -> 0.099279575 | O57: =+FAT!BO240 -> 0.10984458 | P57: =+FAT!BP240 -> 0.12346929 | Q57: =+FAT!BQ240 -> 0.12641939 | R57: =+FAT!BR240 -> 0.12449106 | ... U57: =+FAT!BU240 -> 0.11901527
B58: % do total | K58: =+K56/K$51 -> 0.54343196 | L58: =+L56/L$51 -> 0.55577567 | M58: =+M56/M$51 -> 0.58199017 | N58: =+N56/N$51 -> 0.70556023 | O58: =+O56/O$51 -> 0.9093562 | P58: =+P56/P$51 -> 0.87585322 | Q58: =+Q56/Q$51 -> 1.0522872 | R58: =+R56/R$51 -> 1.050748 | ... U58: =+U56/U$51 -> 1.0294691
B60: EBITDA INT | J60: =+FAT!BJ503 -> 0 | K60: =+FAT!BK503 -> 329.10512 | L60: =+FAT!BL503 -> 275.1202 | M60: =+FAT!BM503 -> 155.44598 | N60: =+FAT!BN503 -> 217.51581 | O60: =+FAT!BO503 -> 4.293688 | P60: =+FAT!BP503 -> -409.66482 | Q60: =+FAT!BQ503 -> -550.32109 | ... U60: =+FAT!BU503 -> -242.71822
B61: mrgn | K61: =+FAT!BK505 -> 0.036176132 | L61: =+FAT!BL505 -> 0.029489908 | M61: =+FAT!BM505 -> 0.02160172 | N61: =+FAT!BN505 -> 0.03459889 | O61: =+FAT!BO505 -> 0.0006465029 | P61: =+FAT!BP505 -> -0.07051475 | Q61: =+FAT!BQ505 -> -0.11677948 | R61: =+FAT!BR505 -> -0.070963631 | ... U61: =+FAT!BU505 -> -0.044739476
B62: % do total | K62: =+K60/K$51 -> 0.07799254 | L62: =+L60/L$51 -> 0.066510384 | M62: =+M60/M$51 -> 0.049212011 | N62: =+N60/N$51 -> 0.072097905 | O62: =+O60/O$51 -> 0.0015002404 | P62: =+P60/P$51 -> -0.13079975 | Q62: =+Q60/Q$51 -> -0.21122176 | R62: =+R60/R$51 -> -0.12908187 | ... U62: =+U60/U$51 -> -0.082948804
B65: Depreciacion | C65: =-FAT!BE89 -> -239.42396 | G65: =-FAT!BF89 -> -289.91828 | H65: =-FAT!BG89 -> -383.30552 | I65: =-FAT!BH89 -> -587.03697 | J65: =-FAT!BJ89 -> -1117.3 | K65: =-FAT!BK89 -> -2718.8 | L65: =-FAT!BL89 -> -2791.6 | M65: =-FAT!BM89 -> -2591.9 | N65: =-FAT!BN89 -> -2094.8859 | O65: =-FAT!BO89 -> -949 | P65: =-FAT!BP89 -> -909.3 | Q65: =-FAT!BQ89 -> -888.8478 | ... U65: =-FAT!BU89 -> -712.53625
B66: Capex | C66: =+PROJ!BD207 -> 383 | G66: =+PROJ!BE207 -> 306 | H66: =+PROJ!BF207 -> 362.5 | I66: =+PROJ!BG207 -> 491.9 | J66: =+PROJ!BH207 -> 571.3 | K66: =+PROJ!BI207 -> 790.7 | L66: =+PROJ!BJ207 -> 1513 | M66: =+PROJ!BK207 -> 1102.8 | N66: =+PROJ!BL207 -> 1032.8 | ... U66: =+PROJ!BS207 -> 636.8999 | AC66: =+N51+N65 -> 922.06467
B68: Múltiplos | C68: 2015 | G68: =+C68+1 -> 2016 | H68: =+G68+1 -> 2017 | I68: =+H68+1 -> 2018 | J68: =+I68+1 -> 2019 | K68: =+J68+1 -> 2020 | L68: =+K68+1 -> 2021 | M68: =+L68+1 -> 2022 | N68: =+M68+1 -> 2023 | O68: =+N68+1 -> 2024 | ... U68: =+T68+1 -> 2030 | AC68: =74500/2400 -> 31.041667
B69: Mkt Cap | C69: =+VP!$C$24 -> 14460.35 | G69: =+C69 -> 14460.35 | H69: =+G69 -> 14460.35 | I69: =+H69 -> 14460.35 | J69: =+I69 -> 14460.35 | K69: =+J69 -> 14460.35 | L69: =+K69 -> 14460.35 | M69: =+L69 -> 14460.35 | N69: =+M69 -> 14460.35 | O69: =+VP!$C$24 -> 14460.35 | P69: =+VP!$C$24 -> 14460.35 | Q69: =+VP!$C$24 -> 14460.35 | R69: =+VP!$C$24 -> 14460.35 | S69: =+VP!$C$24 -> 14460.35 | T69: =+VP!$C$24 -> 14460.35 | U69: =+VP!$C$24 -> 14460.35
B70: Net Debt | C70: =+PROJ!BD153 -> 2752.201 | G70: =+PROJ!BE153 -> 2091.242 | H70: =+PROJ!BF153 -> 5661.464 | I70: =+PROJ!BG153 -> 5563.72 | J70: =+PROJ!BH153 -> 5247 | K70: =+PROJ!BI153 -> 5480.6 | L70: =+PROJ!BJ153 -> 6730.9 | M70: =+PROJ!BK153 -> 7596.2 | N70: =+PROJ!BL153 -> -1663.3 | ... U70: =+PROJ!BS153 -> -1619.3701
B71: EV | C71: =+C69+C70 -> 17212.551 | G71: =+G69+G70 -> 16551.592 | H71: =+H69+H70 -> 20121.814 | I71: =+I69+I70 -> 20024.07 | J71: =+J69+J70 -> 19707.35 | K71: =+K69+K70 -> 19940.95 | L71: =+L69+L70 -> 21191.25 | M71: =+M69+M70 -> 22056.55 | N71: =+N69+N70 -> 12797.05 | ... U71: =+U69+U70 -> 12840.98
C72: =+C69*0.9 -> 13014.315
B73: Cash & Ativos Fin | J73: =+PROJ!BH155+PROJ!BH156 -> 5539.4 | K73: =+PROJ!BI155+PROJ!BI156 -> 8342.3 | L73: =+PROJ!BJ155+PROJ!BJ156 -> 5986 | M73: =+PROJ!BK155+PROJ!BK156 -> 5996.1 | N73: =+PROJ!BL155+PROJ!BL156 -> 7775 | O73: =+PROJ!BM155+PROJ!BM156 -> 3407.969 | P73: =+PROJ!BN155+PROJ!BN156 -> 2671.253 | Q73: =+PROJ!BO155+PROJ!BO156 -> 3834.6625 | ... U73: =+PROJ!BS155+PROJ!BS156 -> 6579.8911
B74: Deuda | J74: =+PROJ!BH157 -> 10786.4 | K74: =+PROJ!BI157 -> 13822.9 | L74: =+PROJ!BJ157 -> 12716.9 | M74: =+PROJ!BK157 -> 13592.3 | N74: =+PROJ!BL157 -> 6111.7 | O74: =+PROJ!BM157 -> 2389.399 | P74: =+PROJ!BN157 -> 6175.382 | Q74: =+PROJ!BO157 -> 6357.221 | ... U74: =+PROJ!BS157 -> 4960.521
B76: Net Debt / EBITDA | J76: =+J70/J47 -> 0.98760887 | K76: =+K70/K47 -> 1.5620475 | L76: =+L70/L47 -> 1.7215018 | M76: =+M70/M47 -> 3.5604406 | N76: =+N70/N47 -> -1.0932294 | O76: =+O70/O47 -> -0.55041416 | P76: =+P70/P47 -> 1.5813665 | Q76: =+Q70/Q47 -> 0.96819702 | ... U76: =+U70/U47 -> -0.56303969
B78: Capex | J78: =+PROJ!BH207 -> 571.3 | K78: =+PROJ!BI207 -> 790.7 | L78: =+PROJ!BJ207 -> 1513 | M78: =+PROJ!BK207 -> 1102.8 | N78: =+PROJ!BL207 -> 1032.8 | O78: =+PROJ!BM207 -> 634.11283 | P78: =+PROJ!BN207 -> 529.328 | Q78: =+PROJ!BO207 -> 515.81303 | ... U78: =+PROJ!BS207 -> 636.8999
B79: CG | J79: =+PROJ!BH146 -> 526.2 | K79: =+PROJ!BI146 -> -128.5 | L79: =+PROJ!BJ146 -> 1259.8 | M79: =+PROJ!BK146 -> 575.5 | N79: =+PROJ!BL146 -> -446.6 | O79: =+PROJ!BM146 -> 1914.905 | P79: =+PROJ!BN146 -> 2892.56 | Q79: =+PROJ!BO146 -> 3127.3978 | ... U79: =+PROJ!BS146 -> 3547.205
B80: Days | J80: =+PROJ!BH168 -> 8.5405773 | K80: =+PROJ!BI168 -> -16.053364 | L80: =+PROJ!BJ168 -> -21.853604 | M80: =+PROJ!BK168 -> -17.718771 | N80: =+PROJ!BL168 -> -38.918942 | O80: =+PROJ!BM168 -> -48.81365 | P80: =+PROJ!BN168 -> -39.738727 | Q80: =+PROJ!BO168 -> -35.034342 | ... U80: =+PROJ!BS168 -> -35.034342
B82: EPS | G82: =+G38/VP!$C$16 -> #REF! | H82: =+H38/VP!$C$16 -> #REF! | I82: =+I38/VP!$C$16 -> #REF! | J82: =+J38/VP!$C$16 -> #REF! | K82: =+K38/VP!$C$16 -> -0.49244921 | L82: =+L38/VP!$C$16 -> #REF! | M82: =+M38/VP!$C$16 -> -2.0794321 | N82: =+N38/VP!$C$16 -> 2.1672659 | ... U82: =+U38/VP!$C$16 -> 1.1525467
B84: P/E | C84: =C69/C38 -> #REF! | G84: =G69/G38 -> #REF! | H84: =H69/H38 -> #REF! | I84: =I69/I38 -> #REF! | J84: =J69/J38 -> #REF! | K84: =K69/K38 -> -21.362609 | L84: =L69/L38 -> #REF! | M84: =M69/M38 -> -5.0590736 | N84: =N69/N38 -> 4.8540421 | ... U84: =U69/U38 -> 9.1276125 | AC84: Paula Mansenaqui.. Trabajaba en banco do brasil.
B86: Yield | O86: =1/O84 -> -0.053067322 | P86: =1/P84 -> -0.1523278 | Q86: =1/Q84 -> 0.070726268 | R86: =1/R84 -> 0.089719444 | S86: =1/S84 -> 0.097735611 | T86: =1/T84 -> 0.10958555 | U86: =1/U84 -> 0.10955767
B88: # Shares Natura | C88: =+VP!$C$16 -> 1374.558 | G88: =+C88 -> 1374.558 | H88: =+G88 -> 1374.558 | I88: =+VP!$C$16 -> 1374.558 | J88: =+VP!$C$16 -> 1374.558 | K88: =+VP!$C$16 -> 1374.558 | L88: =+VP!$C$16 -> 1374.558 | M88: =+VP!$C$16 -> 1374.558 | N88: =+VP!$C$16 -> 1374.558 | O88: =+VP!$C$16 -> 1374.558 | P88: =+VP!$C$16 -> 1374.558 | ... U88: =+VP!$C$16 -> 1374.558
B90: NetDebt/EBITDA | J90: =+J70/J47 -> 0.98760887 | K90: =+K70/K47 -> 1.5620475 | L90: =+L70/L47 -> 1.7215018 | M90: =+M70/M47 -> 3.5604406 | N90: =+N70/N47 -> -1.0932294 | O90: =+O70/O47 -> -0.55041416 | P90: =+P70/P47 -> 1.5813665 | Q90: =+Q70/Q47 -> 0.96819702 | ... U90: =+U70/U47 -> -0.56303969
B91: P/BV | C91: =C69/PROJ!BD140 -> 14.063944 | G91: =G69/PROJ!BE140 -> 14.512814 | H91: =H69/PROJ!BF140 -> 8.845625 | I91: =I69/PROJ!BG140 -> 5.617629 | J91: =J69/PROJ!BH140 -> 4.3007317 | K91: =K69/PROJ!BI140 -> 0.52843852 | L91: =L69/PROJ!BJ140 -> 0.5065702 | M91: =M69/PROJ!BK140 -> 0.64749673 | N91: =N69/PROJ!BL140 -> 0.62590248 | ... U91: =U69/PROJ!BS140 -> 0.78689347
B92: EV/EBITDA | C92: =C71/C47 -> 11.506485 | G92: =G71/G47 -> 12.056852 | H92: =H71/H47 -> 11.551219 | I92: =I71/I47 -> 10.818469 | J92: =J71/J47 -> 3.709387 | K92: =K71/K47 -> 5.6834493 | L92: =L71/L47 -> 5.4198957 | M92: =M71/M47 -> 10.3382 | N92: =N71/N47 -> 8.4110572 | ... U92: =U71/U47 -> 4.4646874
B93: EV/Sales | C93: =+C71/C3 -> 2.1790798 | G93: =+G71/G3 -> 2.0917832 | H93: =+H71/H3 -> 2.0422541 | I93: =+I71/I3 -> 1.0815363 | J93: =+J71/J3 -> 0.99996195 | K93: =+K71/K3 -> 0.41807556 | L93: =+L71/L3 -> 0.41033166 | M93: =+M71/M3 -> 0.46820645 | N93: =+N71/N3 -> 0.33521661 | ... U93: =+U71/U3 -> 0.36291047
B94: ROE | C94: =+PROJ!BD271 -> #REF! | G94: =+PROJ!BE271 -> #REF! | H94: =+PROJ!BF271 -> #REF! | I94: =+PROJ!BG271 -> #REF! | J94: =+PROJ!BH271 -> #REF! | K94: =+PROJ!BI271 -> -0.044059544 | L94: =+PROJ!BJ271 -> #REF! | M94: =+PROJ!BK271 -> -0.11235831 | N94: =+PROJ!BL271 -> 0.13113123 | ... U94: =+PROJ!BS271 -> 0.088996949
B95: ROIC | C95: =+PROJ!BD272 -> #REF! | G95: =+PROJ!BE272 -> #REF! | H95: =+PROJ!BF272 -> #REF! | I95: =+PROJ!BG272 -> #REF! | J95: =+PROJ!BH272 -> #REF! | K95: =+PROJ!BI272 -> #REF! | L95: =+PROJ!BJ272 -> #REF! | M95: =+PROJ!BK272 -> #REF! | N95: =+PROJ!BL272 -> #REF! | ... U95: =+PROJ!BS272 -> 0.085650762
P97: =145*5.5 -> 797.5 | Q97: =+P71-P97 -> 17166.979
P98: =+P71/P6 -> 0.60907276 | Q98: =+Q97/P6 -> 0.58203409
P99: =+P97/P9 -> #DIV/0!
I100: DATOS AESOP 2023 | M100: DATOS TBS
I101: Sales 2023 | J101: =+FAT!BN541 -> 2893.2052 | K101: =+$J$107/J101 -> 4.3636725 | M101: Sales 2023 | N101: =+FAT!BN609 -> 3871.8523 | O101: =+N101*K101 -> 16895.495 | P101: =+O101*0.3+O102*0.7 -> 8419.0885 | Q101: =+$P$101/N101 -> 2.1744343
I102: EBITDA 2023 | J102: =+FAT!BN573 -> 515.32838 | K102: =+$J$107/J102 -> 24.498942 | M102: EBITDA 2023 | N102: =+FAT!BN641 -> 195.36937 | O102: =+N102*K102 -> 4786.3428 | P102: =+N102*17 -> 3321.2793 | Q102: =+$P$101/N102 -> 43.093186
I103: mrgn | J103: =+J102/J101 -> 0.17811677 | M103: mrgn | N103: =+N102/N101 -> 0.050458891
I105: Venta Aesop | M105: Transaccion vs Loreal 2017
I106: EV | J106: 2525 | K106: mln USD | M106: Loreal Compra en 2006 | N106: 740 | O106: euros
J107: =+J106*5 -> 12625 | K107: mln BRL | M107: Natura compro en 2017 | N107: 1000 | O107: euros
M109: Sales 2017 | N109: 921 | O109: euros | P109: =+N107/N109 -> 1.0857763
M110: Ebitda 2017 | N110: =+N109*N111 -> 77.364 | O110: euros | P110: =+N107/N110 -> 12.925909 | Q110: =+N110*2 -> 154.728
M111: mrgn | N111: 0.084 | Q111: =+Q110*5 -> 773.64
I112: Pago na compra 2012 | J112: 50 | K112: mln USD | M112: https://www.ft.com/content/12dc9e7c-400a-3b68-9de0-96f91b11edaa
J113: =+J112*2 -> 100 | K113: mln BRL
J114: =+J107-J113 -> 12525 | K114: =+J114*0.34 -> 4258.5
I115: Ganho de Capital | J115: =+(J106-J112) -> 2475 | K115: =+J114*0.25 -> 3131.25
I116: tax rate | J116: 0.12 | K116: =+J107-K115 -> 9493.75
I118: Tax paid | J118: -908
I119: Cash Neto | J119: =+J120/5 -> 2323.4 | K119: mln USD
J120: =+J114+J118 -> 11617 | K120: mln BRL
I121: Use of cash
I122: Bono 2043 | J122: =-JUROS!C29*1.27 -> -274.447 | K122: mln USD
J123: =+J122*5*1.27 -> -1742.7385 | K123: mln BRL
...

Sheet FAT
AM1: ---> Proforma sin Int. | BO1: ---> Proforma sin Int.
B2: Inflação IPC-A | C2: =+MACRO!C8 -> 0.013475174 | D2: =+MACRO!D8 -> 0.013475174 | E2: =+MACRO!E8 -> 0.013475174 | F2: =+MACRO!F8 -> 0.013475174 | G2: =+MACRO!G8 -> 0.026 | H2: =+MACRO!H8 -> 0.017496397 | I2: =+MACRO!I8 -> 0.010430578 | J2: =+MACRO!J8 -> 0.007417894 | ... AX2: =+MACRO!AX8 -> 0.0115 | BB2: 0.0060105353 | BE2: =+MACRO!BD8 -> 0.1067 | BF2: =+MACRO!BE8 -> 0.062665012 | BG2: =+MACRO!BF8 -> 0.029473499 | BH2: =+MACRO!BG8 -> 0.030601831 | BJ2: =+MACRO!BH8 -> 0.042901847 | BK2: =+MACRO!BI8 -> 0.044908326 | BL2: =+MACRO!BJ8 -> 0.099766039 | BM2: =+MACRO!BK8 -> 0.057740344 | BN2: =+MACRO!BL8 -> 0.047250272 | BO2: =+MACRO!BM8 -> 0.046425617 | BP2: =+MACRO!BN8 -> 0.042643849 | BQ2: =+MACRO!BO8 -> 0.039553578 | ... BU2: =+MACRO!BS8 -> 0.04
B3: R$ million | C3: 1Q15 | D3: 2Q15 | E3: 3Q15 | F3: 4Q15 | G3: 1Q16 | H3: 2Q16 | I3: 3Q16 | J3: 4Q16 | K3: Q1-17 | L3: Q2-17 | M3: Q3-17(a) | N3: Q4-17(a) | O3: Q1-18(a) | P3: Q2-18 | Q3: Q3-18 | R3: Q4-18 | S3: Q1-19 | T3: Q2-19 | U3: Q3-19 | V3: Q4-19 | W3: Q1-20 | X3: Q2-20 | Y3: Q3-20 | Z3: Q4-20 | AA3: Q1-21 | AB3: Q2-21 | AC3: Q3-21 | AD3: Q4-21 | AE3: Q1-22 | AF3: Q2-22 | AG3: Q3-22 | AH3: Q4-22 | AI3: Q1-23 | AJ3: Q2-23 | AK3: Q3-23 | AL3: Q4-23 | AM3: Q1-24 | AN3: Q2-24 | AO3: Q3-24 | AP3: Q4-24 | AQ3: Q1-25 | AR3: Q2-25 | AS3: Q3-25 | AT3: Q4-25 | AU3: Q1-26 | AV3: Q2-26 | AW3: Q3-26 | AX3: Q4-26 | BB3: Q4-25 | BE3: 2015 | BF3: =+BE3+1 -> 2016 | BG3: =+BF3+1 -> 2017 | BH3: 2018 | BI3: 2019 | BJ3: 2019 PROFORMA | BK3: 2020 | BL3: =+BK3+1 -> 2021 | BM3: =+BL3+1 -> 2022 | BN3: =+BM3+1 -> 2023 | BO3: =+BN3+1 -> 2024 | BP3: =+BO3+1 -> 2025 | BQ3: =+BP3+1 -> 2026 | BR3: =+BQ3+1 -> 2027 | BS3: =+BR3+1 -> 2028 | ... BU3: =+BT3+1 -> 2030
B4: Total Consultants - end of period ('000) | C4: 1714.9 | D4: 1810.6 | E4: 1835 | F4: 1883 | G4: 1824.125 | H4: 1863.799 | I4: 1820.9 | J4: 1800.067 | K4: 1838.32 | L4: 1775.372 | M4: 1745.209 | N4: 1718.756 | O4: 1643.342 | P4: 1684.523 | Q4: =636.8+1082.1 -> 1718.9 | R4: =644.8+1058.7 -> 1703.5 | S4: =634.4+1036.1 -> 1670.5 | T4: =1049.8+659.2 -> 1709 | U4: =628.1+1056.4 -> 1684.5 | V4: =+#REF!+V339 -> #REF! | W4: =+#REF!+W339 -> #REF! | X4: =+#REF!+X339 -> #REF! | Y4: =+#REF!+Y339 -> #REF! | Z4: =+#REF!+Z339 -> #REF! | AA4: =+#REF!+AA339 -> #REF! | AB4: =+#REF!+AB339 -> #REF! | AC4: =+#REF!+AC339 -> #REF! | ... AX4: =+#REF!+AX339 -> #REF! | BB4: #REF! | BE4: =+F4 -> 1883 | BF4: =+J4 -> 1800.067 | BG4: =+N4 -> 1718.756 | BH4: =+R4 -> 1703.5 | BJ4: =+V4 -> #REF! | BK4: =+Z4 -> #REF! | BL4: =+AA4 -> #REF! | BM4: =+AH4 -> #REF! | BN4: =+AI4 -> #REF! | BO4: =+AM4 -> #REF! | BP4: =+AQ4 -> #REF! | BQ4: =+AU4 -> #REF! | BR4: =+#REF!+BR339 -> #REF! | BS4: =+#REF!+BS339 -> #REF! | BT4: =+#REF!+BT339 -> #REF! | BU4: =+#REF!+BU339 -> #REF!
B5: Total Consultants - average of period ('000) | C5: 1713 | D5: 1781.4 | E5: 1825.9 | F5: 1871.4 | G5: 1848.0495 | H5: 1855.3599 | I5: 1832.6 | J5: 1812.5381 | K5: 1822.9274 | L5: 1794.3739 | M5: 1747.6962 | N5: 1734.5326 | O5: 1633.1827 | P5: 1666.2007 | Q5: =633.8+1061.9 -> 1695.7 | R5: =644.4+1068.4 -> 1712.8 | S5: =636.6+1018.2 -> 1654.8 | T5: =1039.1+650.2 -> 1689.3 | U5: =+#REF!+U342 -> #REF! | V5: =+#REF!+V342 -> #REF! | W5: =+#REF!+W342 -> #REF! | X5: =+#REF!+X342 -> #REF! | Y5: =+#REF!+Y342 -> #REF! | Z5: =+#REF!+Z342 -> #REF! | AA5: =+#REF!+AA342 -> #REF! | AB5: =+#REF!+AB342 -> #REF! | ... AX5: =+#REF!+AX342 -> #REF! | BB5: #REF! | BE5: =+F5 -> 1871.4 | BF5: =+J5 -> 1812.5381 | BG5: =+N5 -> 1734.5326 | BH5: =+R5 -> 1712.8 | BJ5: =+V5 -> #REF! | BK5: =+Z5 -> #REF! | BL5: =+AA5 -> #REF! | BM5: =+AH5 -> #REF! | BN5: =+AI5 -> #REF! | BO5: =+AM5 -> #REF! | BP5: =+AQ5 -> #REF! | BQ5: =+AU5 -> #REF! | BR5: =+#REF!+BR342 -> #REF! | BS5: =+#REF!+BS342 -> #REF! | BT5: =+#REF!+BT342 -> #REF! | BU5: =+#REF!+BU342 -> #REF!
B6: Units sold – items for resale (in million) | C6: 114.81 | D6: 120.42 | E6: 129.66 | F6: 139.62 | G6: 109.1861 | H6: 116.89729 | I6: 112.8 | J6: 128.46677 | K6: 101.83594 | L6: 107.58112 | M6: 116.21644 | N6: 134.05381 | O6: 104.67395 | P6: 122.16681 | Q6: =35.4+89.6 -> 125 | R6: =40.4+99.4 -> 139.8 | S6: =33.5+73.4 -> 106.9 | T6: =81.8+38.5 -> 120.3 | U6: =+#REF!+U344 -> #REF! | V6: =+#REF!+V344 -> #REF! | W6: =+#REF!+W344 -> #REF! | X6: =+#REF!+X344 -> #REF! | Y6: =+#REF!+Y344 -> #REF! | Z6: =+#REF!+Z344 -> #REF! | AA6: =+#REF!+AA344 -> #REF! | AB6: =+#REF!+AB344 -> #REF! | ... AX6: =+#REF!+AX344 -> #REF! | BB6: #REF! | BE6: =+SUM(C6:F6) -> 504.51 | BF6: =+SUM(G6:J6) -> 467.35016 | BG6: =+SUM(K6:N6) -> 459.68731 | BH6: =+SUM(O6:R6) -> 491.64076 | BJ6: =+SUM(S6:V6) -> #REF! | BK6: =+SUM(W6:Z6) -> #REF! | BL6: =+SUM(AA6:AD6) -> #REF! | BM6: =+SUM(AE6:AH6) -> #REF! | BN6: =+SUM(AI6:AL6) -> #REF! | BO6: =+SUM(AM6:AP6) -> #REF! | BP6: =+SUM(AQ6:AT6) -> #REF! | BQ6: =+SUM(AU6:AX6) -> #REF! | BR6: =+#REF!+BR344 -> #REF! | BS6: =+#REF!+BS344 -> #REF! | BT6: =+#REF!+BT344 -> #REF! | BU6: =+#REF!+BU344 -> #REF!
B8: Gross Revenue | C8: 2205.8399 | D8: 2637.31 | E8: 2763.0574 | F8: 3200.2328 | G8: 2320.028 | H8: 2815.4641 | I8: 2656.2 | J8: 3198.6641 | K8: 2395.9488 | L8: 2801.6006 | M8: 3203.2068 | N8: 5350.1 | O8: 3708.4434 | P8: 4301.1209 | Q8: 4392.9386 | R8: 6111.9653 | S8: 3940.6 | T8: 4629.9 | U8: 4705 | V8: 6432.6 | W8: =+W36+W40+W44+W48 -> 9719.1 | X8: =+X36+X40+X44+X48 -> 9115.8 | Y8: =+Y36+Y40+Y44+Y48 -> 13601.3 | Z8: =+Z36+Z40+Z44+Z48 -> 15260.8 | AA8: =+AA36+AA40+AA44+AA48 -> 12059.1 | AB8: =+AB36+AB40+AB44+AB48 -> 12233 | AC8: =+AC36+AC40+AC44+AC48 -> 12329.1 | AD8: =+AD36+AD40+AD44+AD48 -> 15023 | ... AX8: =+AX36+AX40+AX44+AX48 -> 9319.9503 | BB8: 8402.5252 | BC8: =+AT8/BB8-1 -> -0.016724167 | BE8: =+SUM(C8:F8) -> 10806.44 | BF8: =+SUM(G8:J8) -> 10990.356 | BG8: =+SUM(K8:N8) -> 13750.856 | BH8: =+SUM(O8:R8) -> 18514.468 | BJ8: =+SUM(S8:V8) -> 19708.1 | BK8: =+SUM(W8:Z8) -> 47697 | BL8: =+SUM(AA8:AD8) -> 51644.2 | BM8: =+SUM(AE8:AH8) -> 47108.6 | BN8: =+SUM(AI8:AL8) -> 38175.466 | BO8: =+SUM(AM8:AP8) -> 31586.823 | BP8: =+SUM(AQ8:AT8) -> 29494.8 | BQ8: =+SUM(AU8:AX8) -> 30341.943 | BR8: =+BR36+BR40+BR44+BR48 -> 31698.982 | BS8: =+BS36+BS40+BS44+BS48 -> 32921.722 | BT8: =+BT36+BT40+BT44+BT48 -> 34175.414 | BU8: =+BU36+BU40+BU44+BU48 -> 35383.328
G9: =+G8/C8-1 -> 0.051766254 | H9: =+H8/D8-1 -> 0.067551467 | I9: =+I8/E8-1 -> -0.038673598 | J9: =+J8/F8-1 -> -0.00049018569 | K9: =+K8/G8-1 -> 0.032724096 | L9: =+L8/H8-1 -> -0.0049240771 | M9: =+M8/I8-1 -> 0.20593587 | N9: =+N8/J8-1 -> 0.67260451 | ... AX9: =+AX8/AT8-1 -> 0.12805014 | BB9: -0.10321409 | BF9: =+BF8/BE8-1 -> 0.017019124 | BG9: =+BG8/BF8-1 -> 0.25117475 | BH9: =+BH8/BG8-1 -> 0.34642293 | BJ9: =+BJ8/BH8-1 -> 0.064470219 | BK9: =+BK8/BJ8-1 -> 1.4201724 | BL9: =+BL8/BK8-1 -> 0.082755729 | BM9: =+BM8/BL8-1 -> -0.087823996 | BN9: =+BN8/BM8-1 -> -0.18962852 | BO9: =+BO8/BN8-1 -> -0.17258842 | BP9: =+BP8/BO8-1 -> -0.066230874 | BQ9: =+BQ8/BP8-1 -> 0.028721766 | BR9: =+BR8/BQ8-1 -> 0.044724877 | ... BU9: =+BU8/BT8-1 -> 0.035344534
B11: Natura Brasil | C11: 1703.7 | D11: 1979.2 | E11: 1952.8 | F11: 2256.3 | G11: 1611.7 | H11: 2003.5 | I11: 1849.5 | J11: 2293.1 | K11: 1682.7651 | L11: 1943.7478 | M11: 1931.4179 | N11: 2389.5056 | O11: 1663.6544 | P11: 2045.3235 | Q11: 2158.1 | R11: 2673.7 | S11: 1686.9 | T11: 2224.5 | U11: 2219.5 | V11: 2734 | BE11: =+SUM(C11:F11) -> 7892 | BF11: =+SUM(G11:J11) -> 7757.8 | BG11: =+SUM(K11:N11) -> 7947.4365 | BH11: =+SUM(O11:R11) -> 8540.7779 | BJ11: =+SUM(S11:V11) -> 8864.9
B12: % Sales | C12: 0.77235261 | D12: 0.75047225 | E12: 0.70677004 | F12: 0.70505202 | G12: 0.69468418 | H12: 0.71160404 | I12: 0.69629546 | J12: 0.71688888 | K12: 0.70233768 | L12: 0.69379905 | M12: 0.60296384 | N12: 0.44662822 | O12: 0.44862489 | P12: 0.4755272 | Q12: 0.49126569 | R12: 0.4374534 | S12: 0.42808202 | T12: 0.48046394 | U12: =+U11/U$8 -> 0.4717322 | V12: =+V11/V$8 -> 0.42502254 | BE12: =+BE11/BE$8 -> 0.73030526 | BF12: =+BF11/BF$8 -> 0.70587339 | BG12: =+BG11/BG$8 -> 0.57795939 | BH12: =+BH11/BH$8 -> 0.4613029 | BJ12: =+BJ11/BJ$8 -> 0.44980998
B13: yoy | G13: -0.054000243 | H13: 0.012261191 | I13: -0.05292079 | J13: 0.016290228 | K13: 0.044101865 | L13: -0.029821795 | M13: 0.044291916 | N13: 0.042047645 | O13: -0.011329649 | P13: 0.052245557 | Q13: 0.11736564 | R13: 0.11893438 | S13: 0.013944822 | T13: 0.087615509 | U13: =+U11/Q11-1 -> 0.028450952 | V13: =+V11/R11-1 -> 0.022553016 | BF13: =+BF11/BE11-1 -> -0.017004562 | BG13: =+BG11/BF11-1 -> 0.024444622 | BH13: =+BH11/BG11-1 -> 0.074658208 | BJ13: =+BJ11/BH11-1 -> 0.037949956
B15: Natura Latam | C15: 425.6 | D15: 561.6 | E15: 686.9 | F15: 750.5 | G15: 560.8 | H15: 668.2 | I15: 658.6 | J15: 687.7 | K15: 551.79426 | L15: 688.29958 | M15: 738.92014 | N15: 782.04328 | O15: 661.76527 | P15: 802.82208 | Q15: 629.6 | R15: 954 | S15: 720.2 | T15: 880.4 | U15: 863.2 | V15: 1048.5 | BE15: =+SUM(C15:F15) -> 2424.6 | BF15: =+SUM(G15:J15) -> 2575.3 | BG15: =+SUM(K15:N15) -> 2761.0573 | BH15: =+SUM(O15:R15) -> 3048.1873 | BJ15: =+SUM(S15:V15) -> 3512.3
B16: % Sales | C16: 0.1929294 | D16: 0.21296182 | E16: 0.24859978 | F16: 0.23452909 | G16: 0.24170145 | H16: 0.23734405 | I16: 0.2479482 | J16: 0.21499415 | K16: 0.23030302 | L16: 0.24568084 | M16: 0.23068137 | N16: 0.14617358 | O16: 0.17845762 | P16: 0.18664902 | Q16: 0.14332092 | R16: 0.15608727 | S16: 0.18276405 | T16: 0.19015529 | U16: =+U15/U$8 -> 0.1834644 | V16: =+V15/V$8 -> 0.16299785 | BE16: =+BE15/BE$8 -> 0.22436621 | BF16: =+BF15/BF$8 -> 0.23432361 | BG16: =+BG15/BG$8 -> 0.20079166 | BH16: =+BH15/BH$8 -> 0.16463813 | BJ16: =+BJ15/BJ$8 -> 0.17821606
B17: yoy | G17: 0.31765005 | H17: 0.1897766 | I17: -0.041193262 | J17: -0.083743673 | K17: -0.015978259 | L17: 0.030028316 | M17: 0.12195587 | N17: 0.13719647 | O17: 0.19936007 | P17: 0.16635259 | Q17: -0.14794581 | R17: 0.21988133 | S17: 0.088244183 | T17: 0.096661684 | U17: =+U15/Q15-1 -> 0.37102922 | V17: =+V15/R15-1 -> 0.099056604 | BF17: =+BF15/BE15-1 -> 0.062154582 | BG17: =+BG15/BF15-1 -> 0.072130339 | BH17: =+BH15/BG15-1 -> 0.1039928 | BJ17: =+BJ15/BH15-1 -> 0.15225857
B19: Aesop | C19: 73.053874 | D19: 91.8 | E19: 119.7 | F19: 187.5 | G19: 143.51321 | H19: 139.1589 | I19: 144.9 | J19: 212.29092 | K19: 159.43454 | L19: 167.4517 | M19: 176.69238 | N19: 276.16212 | O19: 221.99708 | P19: 259.95249 | Q19: 295.12288 | R19: 397.36756 | S19: 297.79249 | T19: 313.79691 | U19: 331.5 | V19: 501.4 | BE19: =+SUM(C19:F19) -> 472.05387 | BF19: =+SUM(G19:J19) -> 639.86303 | BG19: =+SUM(K19:N19) -> 779.74073 | BH19: =+SUM(O19:R19) -> 1174.44 | BJ19: =+SUM(S19:V19) -> 1444.4894
B20: % Sales | C20: 0.033118393 | D20: 0.034808195 | E20: 0.043321576 | F20: 0.058589487 | G20: 0.061858396 | H20: 0.049426629 | I20: 0.054551615 | J20: 0.066368619 | K20: 0.066543383 | L20: 0.059770012 | M20: 0.055161088 | N20: 0.051618122 | O20: 0.059862603 | P20: 0.060438312 | Q20: 0.067181198 | R20: 0.065014695 | S20: 0.075570343 | T20: 0.067776174 | U20: =+U19/U$8 -> 0.070456961 | V20: =+V19/V$8 -> 0.077946709 | BE20: =+BE19/BE$8 -> 0.043682644 | BF20: =+BF19/BF$8 -> 0.058220409 | BG20: =+BG19/BG$8 -> 0.056704886 | BH20: =+BH19/BH$8 -> 0.063433634 | BJ20: =+BJ19/BJ$8 -> 0.073294199
B21: yoy | G21: 0.96448461 | H21: 0.51589217 | I21: 0.21052632 | J21: 0.13221824 | K21: 0.11093981 | L21: 0.20331288 | M21: 0.21940908 | N21: 0.30086637 | O21: 0.39240266 | P21: 0.55240282 | Q21: 0.67026379 | R21: 0.43889236 | S21: 0.3414253 | T21: 0.20713178 | U21: =+U19/Q19-1 -> 0.12326094 | V21: =+V19/R19-1 -> 0.26180406 | BF21: =+BF19/BE19-1 -> 0.3554873 | BG21: =+BG19/BF19-1 -> 0.21860569 | BH21: =+BH19/BG19-1 -> 0.50619297 | BJ21: =+BJ19/BH19-1 -> 0.22993886
B24: The body Shop | M24: 354.87262 | N24: 1900.0621 | O24: 1158.8732 | P24: 1190.6804 | Q24: 1307.7313 | R24: 2082.9565 | S24: 1231.7175 | T24: 1208.288 | U24: 1288.6 | V24: 2145.4 | BE24: =+SUM(C24:F24) -> 0 | BF24: =+SUM(G24:J24) -> 0 | BG24: =+SUM(K24:N24) -> 2254.9347 | BH24: =+SUM(O24:R24) -> 5740.2414 | BJ24: =+SUM(S24:V24) -> 5874.0055
B25: % Sales | M25: 0.11078667 | N25: 0.35514516 | O25: 0.31249587 | P25: 0.27683026 | Q25: 0.29768941 | R25: 0.34079979 | S25: 0.31257104 | T25: 0.26097498 | U25: =+U24/U$8 -> 0.27387885 | V25: =+V24/V$8 -> 0.33351988 | BE25: =+BE24/BE$8 -> 0 | BF25: =+BF24/BF$8 -> 0 | BG25: =+BG24/BG$8 -> 0.16398504 | BH25: =+BH24/BH$8 -> 0.31004085 | BJ25: =+BJ24/BJ$8 -> 0.29805032
B26: yoy | Q26: 2.6850724 | R26: 0.096257041 | S26: 0.062857789 | T26: 0.01478788 | U26: =+U24/Q24-1 -> -0.014629386 | V26: =+V24/R24-1 -> 0.029978323 | BH26: =+BH24/BG24-1 -> 1.5456353 | BJ26: =+BJ24/BH24-1 -> 0.023302867
B29: Others | C29: 3.5284691 | D29: 4.6356993 | E29: 3.6157452 | F29: 5.8545154 | G29: 4.0739035 | H29: 4.5759303 | I29: 3.2 | J29: 5.5923698 | K29: 1.9548775 | L29: 2.1014764 | M29: 1.3038131 | N29: 2.3268632 | O29: 2.0730762 | P29: 2.3880338 | Q29: 2.3844217 | R29: 3.9412434 | S29: 3.990054 | T29: 2.915047 | U29: =+U8-U11-U15-U19-U24 -> 2.2 | V29: =+V8-V11-V15-V19-V24 -> 3.3 | BE29: =+SUM(C29:F29) -> 17.634429 | BF29: =+SUM(G29:J29) -> 17.442204 | BG29: =+SUM(K29:N29) -> 7.6870302 | BH29: =+SUM(O29:R29) -> 10.786775 | BJ29: =+SUM(S29:V29) -> 12.405101
B30: % Sales | C30: 0.0015996034 | D30: 0.0017577377 | E30: 0.001308603 | F30: 0.001829403 | G30: 0.0017559717 | H30: 0.0016252845 | I30: 0.0012047286 | J30: 0.0017483454 | K30: 0.00081590954 | L30: 0.00075009852 | M30: 0.00040703368 | N30: 0.00043491957 | O30: 0.00055901519 | P30: 0.00055521198 | Q30: 0.00054278512 | R30: 0.00064484061 | S30: 0.0010125499 | T30: 0.00062961339 | U30: =+U29/U$8 -> 0.00046758767 | V30: =+V29/V$8 -> 0.00051301185 | BE30: =+BE29/BE$8 -> 0.0016318444 | BF30: =+BF29/BF$8 -> 0.0015870462 | BG30: =+BG29/BG$8 -> 0.00055902193 | BH30: =+BH29/BH$8 -> 0.00058261329 | BJ30: =+BJ29/BJ$8 -> 0.00062944175
B31: yoy | G31: 0.15458103 | H31: -0.012893193 | I31: -0.11498189 | J31: -0.044776663 | K31: -0.52014634 | L31: -0.54075427 | M31: -0.59255842 | N31: -0.58392179 | O31: 0.060463481 | P31: 0.13636004 | Q31: 0.82880642 | R31: 0.69380108 | S31: 0.92470205 | T31: 0.22068916 | U31: =+U29/Q29-1 -> -0.077344416 | V31: =+V29/R29-1 -> -0.16270079 | BF31: =+BF29/BE29-1 -> -0.010900576 | BG31: =+BG29/BF29-1 -> -0.5592856 | BH31: =+BH29/BG29-1 -> 0.4032435 | BJ31: =+BJ29/BH29-1 -> 0.1500287
B33: Gross Revenue | S33: =+S36+S40+S44+S48 -> 9683.3099 | T33: =+T36+T40+T44+T48 -> 10531.185 | U33: =+U36+U40+U44+U48 -> 10458.9 | V33: =+V36+V40+V44+V48 -> 12915.3 | W33: =+W36+W40+W44+W48 -> 9719.1 | X33: =+X36+X40+X44+X48 -> 9115.8 | Y33: =+Y36+Y40+Y44+Y48 -> 13601.3 | Z33: =+Z36+Z40+Z44+Z48 -> 15260.8 | ... AL33: =+AL36+AL40+AL44+AL48 -> 8609.9 | AM33: 6231.5 | AN33: 7778.8 | AO33: 7900.7339 | AP33: 9369.6 | AQ33: 6819.9 | AR33: 7545.9 | AS33: 6866.6 | AT33: =+AT36 -> 8262 | AU33: =+AU36 -> 6020.787 | AV33: =+AV36 -> 7623.5828 | AW33: =+AW36 -> 7377.6227 | AX33: =+AX36 -> 9319.9503 | BB33: 8402.5252 | BC33: =+AT33/BB33-1 -> -0.016724167 | BJ33: =+BJ36+BJ40+BJ44+BJ48 -> 43588.695 | BK33: =+BK36+BK40+BK44+BK48 -> 47697 | BL33: =+BL36+BL40+BL44+BL48 -> 51644.2 | BM33: =+BM36+BM40+BM44+BM48 -> 47108.6 | BN33: =+BN36+BN40+BN44+BN48 -> 38175.466 | BO33: =+BO36 -> 31586.823 | BP33: =+BP36 -> 29494.8 | BQ33: =+BQ36 -> 30341.943 | BR33: =+BR36 -> 31698.982 | BS33: =+BS36 -> 32921.722 | BT33: =+BT36 -> 34175.414 | BU33: =+BU36 -> 35383.328
W34: =+W33/S33-1 -> 0.0036960558 | X34: =+X33/T33-1 -> -0.1343994 | Y34: =+Y33/U33-1 -> 0.30045225 | Z34: =+Z33/V33-1 -> 0.18160631 | AA34: =+AA33/W33-1 -> 0.24076303 | AB34: =+AB33/X33-1 -> 0.34195573 | AC34: =+AC33/Y33-1 -> -0.093535177 | AD34: =+AD33/Z33-1 -> -0.015582407 | ... AX34: =+AX33/AT33-1 -> 0.12805014 | BB34: -0.10321409 | BK34: =+BK33/BJ33-1 -> 0.09425162 | BL34: =+BL33/BK33-1 -> 0.082755729 | BM34: =+BM33/BL33-1 -> -0.087823996 | BN34: =+BN33/BM33-1 -> -0.18962852 | BO34: =+BO33/BN33-1 -> -0.17258842 | BP34: =+BP33/BO33-1 -> -0.066230874 | BQ34: =+BQ33/BP33-1 -> 0.028721766 | BR34: =+BR33/BQ33-1 -> 0.044724877 | ... BU34: =+BU33/BT33-1 -> 0.035344534
B36: Natura & Co Latam | S36: =+S138 -> 5463.3 | T36: =+T138 -> 6410.1 | U36: =+U138 -> 6353.1 | V36: =+V138 -> 7117.5 | W36: 5593.2 | X36: =+X138 -> 5420.7 | Y36: =+Y138 -> 8275.9 | Z36: =+Z138 -> 8294.7 | AA36: =+AA138 -> 6857.2 | AB36: =+AB138 -> 7347.9 | AC36: =+AC138 -> 7409.2 | AD36: =+AD138 -> 8079.1 | AE36: =+AE138 -> 6286.7 | ... AX36: =+AX138 -> 9319.9503 | BB36: 8402.5252 | BC36: =+AT36/BB36-1 -> -0.016724167 | BJ36: =+SUM(S36:V36) -> 25344 | BK36: =+SUM(W36:Z36) -> 27584.5 | BL36: =+SUM(AA36:AD36) -> 29693.4 | BM36: =+SUM(AE36:AH36) -> 29158 | BN36: =+SUM(AI36:AL36) -> 27220.844 | BO36: =+SUM(AM36:AP36) -> 31586.823 | BP36: =+SUM(AQ36:AT36) -> 29494.8 | BQ36: =+SUM(AU36:AX36) -> 30341.943 | BR36: =+BR138 -> 31698.982 | BS36: =+BS138 -> 32921.722 | BT36: =+BT138 -> 34175.414 | BU36: =+BU138 -> 35383.328
B37: % Sales | S37: =+S36/S$8 -> 1.3864132 | T37: =+T36/T$8 -> 1.3845007 | U37: =+U36/U$8 -> 1.3502869 | V37: =+V36/V$8 -> 1.1064733 | W37: =+W36/W$8 -> 0.57548538 | X37: =+X36/X$8 -> 0.59464885 | Y37: =+Y36/Y$8 -> 0.6084639 | Z37: =+Z36/Z$8 -> 0.54352983 | ... AX37: =+AX36/AX$8 -> 1 | BB37: 1 | BJ37: =+BJ36/BJ$8 -> 1.2859687 | BK37: =+BK36/BK$8 -> 0.57832778 | BL37: =+BL36/BL$8 -> 0.57496098 | BM37: =+BM36/BM$8 -> 0.6189528 | BN37: =+BN36/BN$8 -> 0.71304549 | BO37: =+BO36/BO$8 -> 1 | BP37: =+BP36/BP$8 -> 1 | BQ37: =+BQ36/BQ$8 -> 1 | ... BU37: =+BU36/BU$8 -> 1
B38: yoy | W38: =+W36/S36-1 -> 0.023776838 | X38: =+X36/T36-1 -> -0.15435017 | Y38: =+Y36/U36-1 -> 0.3026554 | Z38: =+Z36/V36-1 -> 0.16539515 | AA38: =+AA36/W36-1 -> 0.2259887 | AB38: =+AB36/X36-1 -> 0.35552604 | AC38: =+AC36/Y36-1 -> -0.10472577 | AD38: =+AD36/Z36-1 -> -0.025992501 | ... AX38: =+AX36/AT36-1 -> 0.12805014 | BB38: -0.10321409 | BK38: =+BK36/BJ36-1 -> 0.088403567 | BL38: =+BL36/BK36-1 -> 0.076452355 | BM38: =+BM36/BL36-1 -> -0.018030943 | BN38: =+BN36/BM36-1 -> -0.066436516 | BO38: =+BO36/BN36-1 -> 0.16039102 | BP38: =+BP36/BO36-1 -> -0.066230874 | BQ38: =+BQ36/BP36-1 -> 0.028721766 | BR38: =+BR36/BQ36-1 -> 0.044724877 | ... BU38: =+BU36/BT36-1 -> 0.035344534
B40: Avon International | S40: =+S455 -> 2690.5 | T40: =+T455 -> 2599 | U40: =+U455 -> 2485.7 | V40: =+V455 -> 3151 | W40: 2531.4 | X40: =+X455 -> 1995.7 | Y40: =+Y455 -> 2958.2 | Z40: =+Z455 -> 3406.2 | AA40: =+AA455 -> 2835.9 | AB40: =+AB455 -> 2644.7 | AC40: =+AC455 -> 2460 | AD40: =+AD455 -> 3248.4 | AE40: =+AE455 -> 2207.4 | ... AL40: =+AL455 -> 2038.6 | BC40: =+AT40/BB40-1 -> #DIV/0! | BJ40: =+SUM(S40:V40) -> 10926.2 | BK40: =+SUM(W40:Z40) -> 10891.5 | BL40: =+SUM(AA40:AD40) -> 11189 | BM40: =+SUM(AE40:AH40) -> 8728.6 | BN40: =+SUM(AI40:AL40) -> 7488.008
B41: % Sales | S41: =+S40/S$8 -> 0.68276405 | T41: =+T40/T$8 -> 0.56135122 | U41: =+U40/U$8 -> 0.52831031 | V41: =+V40/V$8 -> 0.48984858 | W41: =+W40/W$8 -> 0.26045622 | X41: =+X40/X$8 -> 0.21892758 | Y41: =+Y40/Y$8 -> 0.21749392 | Z41: =+Z40/Z$8 -> 0.22319931 | ... AL41: =+AL40/AL$8 -> 0.23677395 | BJ41: =+BJ40/BJ$8 -> 0.55440149 | BK41: =+BK40/BK$8 -> 0.22834769 | BL41: =+BL40/BL$8 -> 0.2166555 | BM41: =+BM40/BM$8 -> 0.18528676 | BN41: =+BN40/BN$8 -> 0.19614713
B42: yoy | W42: =+W40/S40-1 -> -0.05913399 | X42: =+X40/T40-1 -> -0.23212774 | Y42: =+Y40/U40-1 -> 0.1900873 | Z42: =+Z40/V40-1 -> 0.080990162 | AA42: =+AA40/W40-1 -> 0.12028917 | AB42: =+AB40/X40-1 -> 0.32519918 | AC42: =+AC40/Y40-1 -> -0.16841322 | AD42: =+AD40/Z40-1 -> -0.046327286 | ... AL42: =+AL40/AH40-1 -> -0.17008631 | BK42: =+BK40/BJ40-1 -> -0.0031758525 | BL42: =+BL40/BK40-1 -> 0.027314879 | BM42: =+BM40/BL40-1 -> -0.21989454 | BN42: =+BN40/BM40-1 -> -0.14212955
B44: TBS (ex latam) | S44: =+S603 -> 1231.7175 | T44: =+T603 -> 1208.288 | U44: =+U603 -> 1288.6 | V44: =+V603 -> 2145.4 | W44: 1213.4 | X44: =+X603 -> 1272.5 | Y44: =+Y603 -> 1815 | Z44: =+Z603 -> 2741.7 | AA44: =+AA603 -> 1711.1 | AB44: =+AB603 -> 1612.4 | AC44: =+AC603 -> 1841.5 | AD44: =+AD603 -> 2677.8 | AE44: =+AE603 -> 1426.7 | ... AK44: =+AK603 -> 1158.914 | BC44: =+AT44/BB44-1 -> #DIV/0! | BJ44: =+SUM(S44:V44) -> 5874.0055 | BK44: =+SUM(W44:Z44) -> 7042.6 | BL44: =+SUM(AA44:AD44) -> 7842.8 | BM44: =+SUM(AE44:AH44) -> 6180.9 | BN44: =+SUM(AI44:AL44) -> 3466.614
B45: % Sales | S45: =+S44/S$8 -> 0.31257104 | T45: =+T44/T$8 -> 0.26097498 | U45: =+U44/U$8 -> 0.27387885 | V45: =+V44/V$8 -> 0.33351988 | W45: =+W44/W$8 -> 0.12484695 | X45: =+X44/X$8 -> 0.13959279 | Y45: =+Y44/Y$8 -> 0.13344313 | Z45: =+Z44/Z$8 -> 0.17965637 | ... AK45: =+AK44/AK$8 -> 0.11798641 | BJ45: =+BJ44/BJ$8 -> 0.29805032 | BK45: =+BK44/BK$8 -> 0.14765289 | BL45: =+BL44/BL$8 -> 0.15186216 | BM45: =+BM44/BM$8 -> 0.13120534 | BN45: =+BN44/BN$8 -> 0.090807379
B46: yoy | W46: =+W44/S44-1 -> -0.014871472 | X46: =+X44/T44-1 -> 0.053142921 | Y46: =+Y44/U44-1 -> 0.40850535 | Z46: =+Z44/V44-1 -> 0.27794351 | AA46: =+AA44/W44-1 -> 0.41016977 | AB46: =+AB44/X44-1 -> 0.26711198 | AC46: =+AC44/Y44-1 -> 0.014600551 | AD46: =+AD44/Z44-1 -> -0.023306708 | ... AK46: =+AK44/AG44-1 -> -0.14268827 | BK46: =+BK44/BJ44-1 -> 0.19894338 | BL46: =+BL44/BK44-1 -> 0.11362281 | BM46: =+BM44/BL44-1 -> -0.21190136 | BN46: =+BN44/BM44-1 -> -0.4391409
B48: Aesop (ex latam) | S48: =+S535 -> 297.79249 | T48: =+T535 -> 313.79691 | U48: =+U535 -> 331.5 | V48: =+V535 -> 501.4 | W48: 381.1 | X48: =+X535 -> 426.9 | Y48: =+Y535 -> 552.2 | Z48: =+Z535 -> 818.2 | AA48: =+AA535 -> 654.9 | AB48: =+AB535 -> 628 | AC48: =+AC535 -> 618.4 | AD48: =+AD535 -> 1017.7 | AE48: =+AE535 -> 721.2 | ... AH48: =+AH535 -> 976.6 | BC48: =+AT48/BB48-1 -> #DIV/0! | BJ48: =+SUM(S48:V48) -> 1444.4894 | BK48: =+SUM(W48:Z48) -> 2178.4 | BL48: =+SUM(AA48:AD48) -> 2919 | BM48: =+SUM(AE48:AH48) -> 3041.1
B49: % Sales | S49: =+S48/S$8 -> 0.075570343 | T49: =+T48/T$8 -> 0.067776174 | U49: =+U48/U$8 -> 0.070456961 | V49: =+V48/V$8 -> 0.077946709 | W49: =+W48/W$8 -> 0.03921145 | X49: =+X48/X$8 -> 0.046830777 | Y49: =+Y48/Y$8 -> 0.04059906 | Z49: =+Z48/Z$8 -> 0.053614489 | ... AH49: =+AH48/AH$8 -> 0.072332168 | BJ49: =+BJ48/BJ$8 -> 0.073294199 | BK49: =+BK48/BK$8 -> 0.045671636 | BL49: =+BL48/BL$8 -> 0.056521352 | BM49: =+BM48/BM$8 -> 0.064555092
B50: yoy | W50: =+W48/S48-1 -> 0.27975019 | X50: =+X48/T48-1 -> 0.36043405 | Y50: =+Y48/U48-1 -> 0.66576169 | Z50: =+Z48/V48-1 -> 0.63183087 | AA50: =+AA48/W48-1 -> 0.7184466 | AB50: =+AB48/X48-1 -> 0.47107051 | AC50: =+AC48/Y48-1 -> 0.1198841 | AD50: =+AD48/Z48-1 -> 0.24382791 | ... AH50: =+AH48/AD48-1 -> -0.040385182 | BK50: =+BK48/BJ48-1 -> 0.50807614 | BL50: =+BL48/BK48-1 -> 0.33997429 | BM50: =+BM48/BL48-1 -> 0.041829394
B54: Impostos | C54: =+C57-C8 -> -564.03993 | D54: =+D57-D8 -> -708.40998 | E54: =+E57-E8 -> -767.15737 | F54: =+F57-F8 -> -867.83281 | G54: =+G57-G8 -> -630.32713 | H54: =+H57-H8 -> -789.80616 | I54: =+I57-I8 -> -753.6 | J54: =+J57-J8 -> -903.95181 | K54: =+K57-K8 -> -667.3418 | M54: =+M57-M8 -> -837.78511 | N54: =+N57-N8 -> -1617.2 | O54: =+O57-O8 -> -1020.8171 | P54: =+P57-P8 -> -1201.0784 | Q54: =+Q57-Q8 -> -1151.0373 | R54: =+R57-R8 -> -1776.4048 | S54: =+S57-S8 -> -1025.45 | T54: =+T57-T8 -> -1226.191 | ... AL54: =+AL57-AL8 -> -1996.5 | AM54: =+AM57-AM33 -> -1654.5 | AN54: =+AN57-AN33 -> -1989.1 | AO54: =+AO57-AO33 -> -1925.155 | AP54: =+AP57-AP33 -> -2279 | AQ54: =+AQ57-AQ33 -> -1676.8539 | AR54: =+AR57-AR33 -> -1858.5 | AS54: =+AS57-AS33 -> -1672.6 | AT54: =+AT57-AT33 -> -2069 | ... AX54: =+AX57-AX33 -> -2964.8489 | BB54: -2056.5846 | BE54: =+SUM(C54:F54) -> -2907.4401 | BF54: =+SUM(G54:J54) -> -3077.6851 | BG54: =+SUM(K54:N54) -> -3122.3269 | BH54: =+SUM(O54:R54) -> -5149.3377 | BJ54: =+SUM(S54:V54) -> -260.941 | BK54: =+SUM(W54:Z54) -> -10775.1 | BL54: =+SUM(AA54:AD54) -> -11479.6 | BM54: =+SUM(AE54:AH54) -> -10759.4 | BN54: =+SUM(AI54:AL54) -> -8951.0703 | BO54: =+SUM(AM54:AP54) -> -7847.755 | BP54: =+SUM(AQ54:AT54) -> -7276.9539 | BQ54: =+SUM(AU54:AX54) -> -8655.0113 | BR54: =+BR57-BR33 -> -9041.3787 | BS54: =+BS57-BS33 -> -9386.3588 | BT54: =+BT57-BT33 -> -9736.0712 | BU54: =+BU57-BU33 -> -10072.705
B55: % Revs | C55: =+C54/C33 -> #DIV/0! | D55: =+D54/D33 -> #DIV/0! | E55: =+E54/E33 -> #DIV/0! | F55: =+F54/F33 -> #DIV/0! | G55: =+G54/G33 -> #DIV/0! | H55: =+H54/H33 -> #DIV/0! | I55: =+I54/I33 -> #DIV/0! | J55: =+J54/J33 -> #DIV/0! | ... AX55: =+AX54/AX33 -> -0.31811853 | BB55: -0.24475792 | BE55: =+BE54/BE33 -> #DIV/0! | BF55: =+BF54/BF33 -> #DIV/0! | BG55: =+BG54/BG33 -> #DIV/0! | BH55: =+BH54/BH33 -> #DIV/0! | BJ55: =+BJ54/BJ33 -> -0.0059864376 | BK55: =+BK54/BK33 -> -0.22590729 | BL55: =+BL54/BL33 -> -0.22228246 | BM55: =+BM54/BM33 -> -0.22839566 | BN55: =+BN54/BN33 -> -0.2344718 | BO55: =+BO54/BO33 -> -0.24845028 | BP55: =+BP54/BP33 -> -0.24671989 | BQ55: =+BQ54/BQ33 -> -0.28524908 | ... BU55: =+BU54/BU33 -> -0.28467375
B57: Net Revenue | C57: 1641.8 | D57: 1928.9 | E57: 1995.9 | F57: 2332.4 | G57: 1689.7009 | H57: 2025.658 | I57: 1902.6 | J57: 2294.7123 | K57: 1728.607 | L57: 2025.8189 | M57: 2365.4217 | N57: 3732.9 | O57: 2687.6263 | P57: 3100.0425 | Q57: 3241.9013 | R57: 4335.5604 | S57: 2915.15 | T57: 3403.709 | U57: 3473.8 | V57: 9654.5 | W57: 7518 | X57: =+X144+X470+X541+X609 -> 6987.1 | Y57: =+Y144+Y470+Y541+Y609 -> 10419.5 | Z57: =+Z144+Z470+Z541+Z609 -> 11997.3 | AA57: =+AA144+AA470+AA541+AA609 -> 9455 | AB57: =+AB144+AB470+AB541+AB609 -> 9517.2 | AC57: =+AC144+AC470+AC541+AC609 -> 9549.2 | AD57: =+AD144+AD470+AD541+AD609 -> 11643.2 | AE57: =+AE144+AE470+AE541+AE609 -> 8253.3 | ... AH57: =+AH144+AH470+AH541+AH609 -> 10389.8 | AI57: =+AI144+AI470+AI609 -> 7320.2 | AJ57: =+AJ144+AJ470+AJ609 -> 7773.5348 | AK57: =+AK144+AK470+AK609 -> 7517.261 | AL57: 6613.4 | AM57: 4577 | AN57: 5789.7 | AO57: 5975.5789 | AP57: 7090.6 | AQ57: =+AQ144 -> 5143.0461 | AR57: =+AR144 -> 5687.4 | AS57: =+AS144 -> 5194 | AT57: =+AT144 -> 6193 | AU57: =+AU144 -> 4671.1848 | AV57: =+AV144 -> 5589.1976 | AW57: =+AW144 -> 5071.4476 | AX57: =+AX144 -> 6355.1014 | BB57: 6345.9406 | BC57: =+AT57/BB57-1 -> -0.024100547 | BE57: =+SUM(C57:F57) -> 7899 | BF57: =+SUM(G57:J57) -> 7912.6711 | BG57: =+SUM(K57:N57) -> 9852.7476 | BH57: =+SUM(O57:R57) -> 13365.13 | BJ57: =+SUM(S57:V57) -> 19447.159 | BK57: =+SUM(W57:Z57) -> 36921.9 | BL57: =+SUM(AA57:AD57) -> 40164.6 | BM57: =+SUM(AE57:AH57) -> 36349.2 | BN57: =+SUM(AI57:AL57) -> 29224.396 | BO57: =+SUM(AM57:AP57) -> 23432.879 | BP57: =+SUM(AQ57:AT57) -> 22217.446 | BQ57: =+SUM(AU57:AX57) -> 21686.931 | BR57: =+BR144 -> 22657.604 | BS57: =+BS144 -> 23535.363 | BT57: =+BT144 -> 24439.342 | BU57: =+BU144 -> 25310.623
B58: yoy | G58: =+G57/C57-1 -> 0.029175821 | H58: =+H57/D57-1 -> 0.050162255 | I58: =+I57/E57-1 -> -0.046745829 | J58: =+J57/F57-1 -> -0.016158335 | K58: =+K57/G57-1 -> 0.023025468 | L58: =+L57/H57-1 -> 7.9422867e-05 | M58: =+M57/I57-1 -> 0.24325751 | N58: =+N57/J57-1 -> 0.62673987 | ... AX58: =+AX57/AT57-1 -> 0.026174938 | BB58: -0.10502064 | BF58: =+BF57/BE57-1 -> 0.0017307428 | BG58: =+BG57/BF57-1 -> 0.24518604 | BH58: =+BH57/BG57-1 -> 0.35648765 | BJ58: =+BJ57/BH57-1 -> 0.4550669 | BK58: =+BK57/BJ57-1 -> 0.89857552 | BL58: =+BL57/BK57-1 -> 0.087825924 | BM58: =+BM57/BL57-1 -> -0.094994099 | BN58: =+BN57/BM57-1 -> -0.19600993 | BO58: =+BO57/BN57-1 -> -0.19817405 | BP58: =+BP57/BO57-1 -> -0.051868691 | BQ58: =+BQ57/BP57-1 -> -0.023878295 | BR58: =+BR57/BQ57-1 -> 0.044758396 | ... BU58: =+BU57/BT57-1 -> 0.03565074
B59: COGS | C59: =+C61-C57 -> -495.1671 | D59: =+D61-D57 -> -589.63978 | E59: =+E61-E57 -> -618.31485 | F59: =+F61-F57 -> -712.90224 | G59: =+G61-G57 -> -521.07206 | H59: =+H61-H57 -> -638.23244 | I59: =+I61-I57 -> -566.8 | J59: =+J61-J57 -> -720.81404 | K59: -519.93802 | L59: -605.30319 | M59: -689.31917 | N59: -1096.517 | O59: -735.94613 | P59: -894.88899 | Q59: -867.08677 | R59: -1263.9753 | S59: =+S61-S57 -> -809.172 | T59: =+T61-T57 -> -964.555 | U59: =+U61-U57 -> -967.1 | V59: =+V61-V57 -> -3450.9 | W59: =+W61-W57 -> -2878.7 | X59: =+X61-X57 -> -2375.4 | Y59: =+Y61-Y57 -> -3695.3 | Z59: =+Z61-Z57 -> -4280 | ... AX59: =+AX61-AX57 -> -2254.5063 | BB59: -2174.6637 | BE59: =+SUM(C59:F59) -> -2416.024 | BF59: =+SUM(G59:J59) -> -2446.9186 | BG59: =+SUM(K59:N59) -> -2911.0774 | BH59: =+SUM(O59:R59) -> -3761.8972 | BJ59: =+SUM(S59:V59) -> -6191.727 | BK59: =+SUM(W59:Z59) -> -13229.4 | BL59: =+SUM(AA59:AD59) -> -14011.4 | BM59: =+SUM(AE59:AH59) -> -13155.3 | BN59: =+SUM(AI59:AL59) -> -10238.485 | BO59: =+SUM(AM59:AP59) -> -8108.5109 | BP59: =+SUM(AQ59:AT59) -> -7483.9594 | BQ59: =+SUM(AU59:AX59) -> -7314.5875 | BR59: =+BR61-BR57 -> -7641.9767 | BS59: =+BS61-BS57 -> -7938.0283 | BT59: =+BT61-BT57 -> -8242.9231 | BU59: =+BU61-BU57 -> -8536.7894
B61: Gross Profit | C61: 1146.6329 | D61: 1339.2602 | E61: 1377.5852 | F61: 1619.4978 | G61: 1168.6288 | H61: 1387.4255 | I61: 1335.8 | J61: 1573.8983 | K61: 1208.669 | L61: 1420.5157 | M61: 1676.1026 | N61: 2636.3435 | O61: 1951.6802 | P61: 2205.1535 | Q61: 2374.8145 | R61: 3071.5851 | S61: 2105.978 | T61: 2439.154 | U61: 2506.7 | V61: 6203.6 | W61: 4639.3 | X61: =+X207+X473+X547+X615 -> 4611.7 | Y61: =+Y207+Y473+Y547+Y615 -> 6724.2 | Z61: =+Z207+Z473+Z547+Z615 -> 7717.3 | AA61: =+AA207+AA473+AA547+AA615 -> 6130.7 | AB61: =+AB207+AB473+AB547+AB615 -> 6200.7 | AC61: =+AC207+AC473+AC547+AC615 -> 6236.2 | AD61: =+AD207+AD473+AD547+AD615 -> 7585.6 | AE61: =+AE207+AE473+AE547+AE615 -> 5307.7 | ... AH61: =+AH207+AH473+AH547+AH615 -> 6626.7 | AI61: =+AI207+AI473+AI615 -> 4825.5 | AJ61: =+AJ207+AJ473+AJ615 -> 5085.5427 | AK61: =+AK207+AK473+AK615 -> 4906.268 | AL61: 4168.6 | AM61: 3030.7 | AN61: 3791.3 | AO61: 4022.668 | AP61: 4479.7 | AQ61: =+AQ207 -> 3467.1867 | AR61: =+AR207 -> 3778.3 | AS61: =+AS207 -> 3492 | AT61: =+AT207 -> 3996 | AU61: =+AU207 -> 3149.0812 | AV61: =+AV207 -> 3713.0614 | AW61: =+AW207 -> 3409.6063 | AX61: =+AX207 -> 4100.5951 | BB61: 4171.277 | BC61: =+AT61/BB61-1 -> -0.042019974 | BE61: =+SUM(C61:F61) -> 5482.976 | BF61: =+SUM(G61:J61) -> 5465.7526 | BG61: =+SUM(K61:N61) -> 6941.6308 | BH61: =+SUM(O61:R61) -> 9603.2333 | BJ61: =+SUM(S61:V61) -> 13255.432 | BK61: =+SUM(W61:Z61) -> 23692.5 | BL61: =+SUM(AA61:AD61) -> 26153.2 | BM61: =+SUM(AE61:AH61) -> 23193.9 | BN61: =+SUM(AI61:AL61) -> 18985.911 | BO61: =+SUM(AM61:AP61) -> 15324.368 | BP61: =+SUM(AQ61:AT61) -> 14733.487 | BQ61: =+SUM(AU61:AX61) -> 14372.344 | BR61: =+BR207 -> 15015.627 | BS61: =+BS207 -> 15597.335 | BT61: =+BT207 -> 16196.419 | BU61: =+BU207 -> 16773.834
B62: Gross Margin | C62: =+C61/C$57 -> 0.69839987 | D62: =+D61/D$57 -> 0.69431294 | E62: =+E61/E$57 -> 0.6902075 | F62: =+F61/F$57 -> 0.69434821 | G62: =+G61/G$57 -> 0.69161875 | H62: =+H61/H$57 -> 0.68492586 | I62: =+I61/I$57 -> 0.70209187 | J62: =+J61/J$57 -> 0.68588043 | ... AX62: =+AX61/AX$57 -> 0.64524463 | BB62: 0.65731421 | BC62: =+AT62-BB62 -> -0.012069578 | BE62: =+BE61/BE$57 -> 0.69413546 | BF62: =+BF61/BF$57 -> 0.69075948 | BG62: =+BG61/BG$57 -> 0.70453756 | BH62: =+BH61/BH$57 -> 0.71852896 | BJ62: =+BJ61/BJ$57 -> 0.68161277 | BK62: =+BK61/BK$57 -> 0.64169233 | BL62: =+BL61/BL$57 -> 0.65115052 | BM62: =+BM61/BM$57 -> 0.63808557 | BN62: =+BN61/BN$57 -> 0.64965965 | BO62: =+BO61/BO$57 -> 0.65396864 | BP62: =+BP61/BP$57 -> 0.66314943 | BQ62: =+BQ61/BQ$57 -> 0.66271911 | ... BU62: =+BU61/BU$57 -> 0.66271911
B63: yoy | G63: =+G61/C61-1 -> 0.019183035 | H63: =+H61/D61-1 -> 0.035964114 | I63: =+I61/E61-1 -> -0.030332175 | J63: =+J61/F61-1 -> -0.028156569 | K63: =+K61/G61-1 -> 0.03426254 | L63: =+L61/H61-1 -> 0.023850027 | M63: =+M61/I61-1 -> 0.25475563 | N63: =+N61/J61-1 -> 0.67504064 | ... AX63: =+AX61/AT61-1 -> 0.026174938 | BB63: -0.068849041 | BF63: =+BF61/BE61-1 -> -0.0031412591 | BG63: =+BG61/BF61-1 -> 0.27002287 | BH63: =+BH61/BG61-1 -> 0.38342611 | BJ63: =+BJ61/BH61-1 -> 0.38030928 | BK63: =+BK61/BJ61-1 -> 0.78738045 | BL63: =+BL61/BK61-1 -> 0.10385987 | BM63: =+BM61/BL61-1 -> -0.1131525 | BN63: =+BN61/BM61-1 -> -0.18142655 | BO63: =+BO61/BN61-1 -> -0.19285579 | BP63: =+BP61/BO61-1 -> -0.038558278 | BQ63: =+BQ61/BP61-1 -> -0.024511699 | BR63: =+BR61/BQ61-1 -> 0.044758396 | ... BU63: =+BU61/BT61-1 -> 0.03565074
B65: SG&A | C65: =+C70+C74+C79+C80+C81+C83+C89 -> -860.7329 | D65: =+D70+D74+D79+D80+D81+D83+D89 -> -982.06022 | E65: =+E70+E74+E79+E80+E81+E83+E89 -> -977.98515 | F65: =+F70+F74+F79+F80+F81+F83+F89 -> -1166.2978 | G65: =+G70+G74+G79+G80+G81+G83+G89 -> -951.63184 | H65: =+H70+H74+H79+H80+H81+H83+H89 -> -1042.6997 | I65: =+I70+I74+I79+I80+I81+I83+I89 -> -986.853 | J65: =+J70+J74+J79+J80+J81+J83+J89 -> -1111.7725 | ... AL65: =+AL70+AL74+AL79+AL80+AL81+AL83+AL89 -> -4224.3 | AM65: =+AM70+AM74+AM79+AM80+AM81+AM83 -> -2595.2 | AN65: =+AN70+AN74+AN79+AN80+AN81+AN83 -> -3323.5 | AO65: =+AO70+AO74+AO79+AO80+AO81+AO83 -> -3591.716 | AP65: =+AP70+AP74+AP79+AP80+AP81+AP83 -> -4912.4 | AQ65: =+AQ70+AQ74+AQ79+AQ80+AQ81+AQ83 -> -3035 | AR65: =+AR70+AR74+AR79+AR80+AR81+AR83 -> -3331.8 | AS65: =+AS70+AS74+AS79+AS80+AS81+AS83 -> -3267.1 | AT65: =+AT70+AT74+AT79+AT80+AT81+AT83 -> -3793 | ... AX65: =+AX70+AX74+AX79+AX80+AX81+AX83 -> -3513.2291 | BB65: -3834.2686 | BC65: =+AT65/BB65-1 -> -0.010763092 | BE65: =+SUM(C65:F65) -> -3987.076 | BF65: =+SUM(G65:J65) -> -4092.9571 | BG65: =+SUM(K65:N65) -> -5199.6662 | BH65: =+SUM(O65:R65) -> -7752.3179 | BJ65: =+SUM(S65:V65) -> -7942.6 | BK65: =+SUM(W65:Z65) -> -20183.9 | BL65: =+SUM(AA65:AD65) -> -22243.3 | BM65: =+SUM(AE65:AH65) -> -21060.4 | BN65: =+SUM(AI65:AL65) -> -17464.455 | BO65: =+SUM(AM65:AP65) -> -14422.816 | BP65: =+SUM(AQ65:AT65) -> -13426.9 | BQ65: =+BQ70+BQ74+BQ79+BQ80+BQ81+BQ83 -> -12655.773 | BR65: =+BR70+BR74+BR79+BR80+BR81+BR83 -> -13119.014 | BS65: =+BS70+BS74+BS79+BS80+BS81+BS83 -> -13643.651 | BT65: =+BT70+BT74+BT79+BT80+BT81+BT83 -> -14132.479 | BU65: =+BU70+BU74+BU79+BU80+BU81+BU83 -> -14610.249
B66: % Revs | C66: =+C65/C$57 -> -0.52426173 | D66: =+D65/D$57 -> -0.50912967 | E66: =+E65/E$57 -> -0.48999707 | F66: =+F65/F$57 -> -0.50004191 | G66: =+G65/G$57 -> -0.56319545 | H66: =+H65/H$57 -> -0.51474619 | I66: =+I65/I$57 -> -0.51868653 | J66: =+J65/J$57 -> -0.48449321 | ... AX66: =+AX65/AX$57 -> -0.55282031 | BB66: -0.60420808 | BC66: =+AT66-BB66 -> -0.008257611 | BE66: =+BE65/BE$57 -> -0.50475706 | BF66: =+BF65/BF$57 -> -0.51726617 | BG66: =+BG65/BG$57 -> -0.52773768 | BH66: =+BH65/BH$57 -> -0.58004057 | BJ66: =+BJ65/BJ$57 -> -0.40841955 | BK66: =+BK65/BK$57 -> -0.54666472 | BL66: =+BL65/BL$57 -> -0.5538036 | BM66: =+BM65/BM$57 -> -0.57939102 | BN66: =+BN65/BN$57 -> -0.5975985 | BO66: =+BO65/BO$57 -> -0.61549484 | BP66: =+BP65/BP$57 -> -0.60434039 | BQ66: =+BQ65/BQ$57 -> -0.5835668 | ... BU66: =+BU65/BU$57 -> -0.57723783
B67: yoy | G67: =+G65/C65-1 -> 0.10560644 | H67: =+H65/D65-1 -> 0.061747227 | I67: =+I65/E65-1 -> 0.0090674643 | J67: =+J65/F65-1 -> -0.046750686 | K67: =+K65/G65-1 -> -0.11299284 | L67: =+L65/H65-1 -> 0.075944853 | M67: =+M65/I65-1 -> 0.24205823 | N67: =+N65/J65-1 -> 0.80607597 | ... AX67: =+AX65/AT65-1 -> -0.073759793 | BB67: -0.21947142 | BF67: =+BF65/BE65-1 -> 0.026556067 | BG67: =+BG65/BF65-1 -> 0.27039353 | BH67: =+BH65/BG65-1 -> 0.49092607 | BJ67: =+BJ65/BH65-1 -> 0.024545187 | BK67: =+BK65/BJ65-1 -> 1.5412208 | BL67: =+BL65/BK65-1 -> 0.10203182 | BM67: =+BM65/BL65-1 -> -0.053180059 | BN67: =+BN65/BM65-1 -> -0.17074438 | BO67: =+BO65/BN65-1 -> -0.17416169 | BP67: =+BP65/BO65-1 -> -0.069051426 | BQ67: =+BQ65/BP65-1 -> -0.057431487 | BR67: =+BR65/BQ65-1 -> 0.036603123 | ... BU67: =+BU65/BT65-1 -> 0.03380657
T68: =+T66-P66 -> 0.050638424 | U68: =+U66-Q66 -> 0.01978513 | V68: =+V66-R66 -> 0.29031614 | W68: =+W66-S66 -> -0.029403109 | X68: =+X66-T66 -> -0.013921401 | Y68: =+Y66-U66 -> 0.058258923 | Z68: =+Z66-V66 -> -0.28537392 | AA68: =+AA66-W66 -> 0.037070045 | ... AX68: =+AX66-AT66 -> 0.05964538 | BB68: 0.088596482
B70: Selling, Marketing and Logistics Expenses | C70: -648 | D70: -745.8 | E70: -762.9 | F70: -842.1 | G70: -694.86438 | H70: -780.86445 | I70: -770.98339 | J70: -863.45687 | K70: -736.02438 | L70: -809.65348 | M70: -985.0653 | N70: -1534.606 | O70: -1282.9865 | P70: -1449.616 | Q70: -1534.3647 | R70: -1785.8739 | S70: -1398.5 | T70: -1594.9 | U70: -1613.7 | V70: -1998 | W70: -3523.2 | X70: -3378.1 | Y70: -4280.3 | Z70: -5244.7 | AA70: -4255 | AB70: -4248.1 | AC70: =+AC211+AC477+AC552+AC620 -> -4288.4 | AD70: -5042.3 | AE70: -3849.2 | AF70: =+AF211+AF477+AF552+AF620 -> -3856.7 | AG70: -4119.9 | AH70: =+AH211+AH477+AH552+AH620 -> -4334.8 | AI70: -3320.4 | AJ70: -3497.4 | AK70: -3394.732 | AL70: -3023.2 | AM70: -1954.2 | AN70: -2447.2 | AO70: -2623.8994 | AP70: -3188.2 | AQ70: =+AQ211 -> -2244.4 | AR70: =+AR211 -> -2344.4 | AS70: =+AS211 -> -2308 | AT70: =+AT211 -> -2513 | AU70: =+AU211 -> -2031.9654 | AV70: =+AV211 -> -2431.301 | AW70: =+AW211 -> -2206.0797 | AX70: =+AX211 -> -2764.4691 | BB70: -2823.9436 | BC70: =+AT70/BB70-1 -> -0.1101097 | BE70: =+SUM(C70:F70) -> -2998.8 | BF70: =+SUM(G70:J70) -> -3110.1691 | BG70: =+SUM(K70:N70) -> -4065.3492 | BH70: =+SUM(O70:R70) -> -6052.8411 | BJ70: =+SUM(S70:V70) -> -6605.1 | BK70: =+SUM(W70:Z70) -> -16426.3 | BL70: =+SUM(AA70:AD70) -> -17833.8 | BM70: =+SUM(AE70:AH70) -> -16160.6 | BN70: =+SUM(AI70:AL70) -> -13235.732 | BO70: =+SUM(AM70:AP70) -> -10213.499 | BP70: =+SUM(AQ70:AT70) -> -9409.8 | BQ70: =+SUM(AU70:AX70) -> -9433.8152 | BR70: =+BR211 -> -9742.7696 | BS70: =+BS211 -> -10120.206 | BT70: =+BT211 -> -10508.917 | BU70: =+BU211 -> -10883.568
B71: % Revs | C71: =+C70/C$57 -> -0.39468876 | D71: =+D70/D$57 -> -0.38664524 | E71: =+E70/E$57 -> -0.38223358 | F71: =+F70/F$57 -> -0.36104442 | G71: =+G70/G$57 -> -0.41123514 | H71: =+H70/H$57 -> -0.38548682 | I71: =+I70/I$57 -> -0.40522621 | J71: =+J70/J$57 -> -0.3762811 | ... AX71: =+AX70/AX$57 -> -0.435 | BB71: -0.445 | BC71: =+AT71-BB71 -> 0.03921928 | BE71: =+BE70/BE$57 -> -0.37964299 | BF71: =+BF70/BF$57 -> -0.39306184 | BG71: =+BG70/BG$57 -> -0.41261071 | BH71: =+BH70/BH$57 -> -0.45288305 | BJ71: =+BJ70/BJ$57 -> -0.33964344 | BK71: =+BK70/BK$57 -> -0.44489314 | BL71: =+BL70/BL$57 -> -0.44401787 | BM71: =+BM70/BM$57 -> -0.444593 | BN71: =+BN70/BN$57 -> -0.45290011 | BO71: =+BO70/BO$57 -> -0.43586191 | BP71: =+BP70/BP$57 -> -0.42353203 | BQ71: =+BQ70/BQ$57 -> -0.435 | ... BU71: =+BU70/BU$57 -> -0.43
B72: yoy | G72: =+G70/C70-1 -> 0.072321568 | H72: =+H70/D70-1 -> 0.047015895 | I72: =+I70/E70-1 -> 0.010595607 | J72: =+J70/F70-1 -> 0.025361438 | K72: =+K70/G70-1 -> 0.059234589 | L72: =+L70/H70-1 -> 0.03686815 | M72: =+M70/I70-1 -> 0.27767383 | N72: =+N70/J70-1 -> 0.7772816 | ... AX72: =+AX70/AT70-1 -> 0.10006729 | BB72: -0.11425143 | BF72: =+BF70/BE70-1 -> 0.037137884 | BG72: =+BG70/BF70-1 -> 0.30711516 | BH72: =+BH70/BG70-1 -> 0.4888859 | BJ72: =+BJ70/BH70-1 -> 0.091239624 | BK72: =+BK70/BJ70-1 -> 1.4869116 | BL72: =+BL70/BK70-1 -> 0.08568576 | BM72: =+BM70/BL70-1 -> -0.093821844 | BN72: =+BN70/BM70-1 -> -0.18098759 | BO72: =+BO70/BN70-1 -> -0.22833891 | BP72: =+BP70/BO70-1 -> -0.078689919 | BQ72: =+BQ70/BP70-1 -> 0.0025521442 | BR72: =+BR70/BQ70-1 -> 0.032749679 | ... BU72: =+BU70/BT70-1 -> 0.03565074
B74: Administrative, R&D, IT and Projects Expenses | C74: -278.4 | D74: -299.1 | E74: -314.2 | F74: -401.8 | G74: -327.58135 | H74: -321.79427 | I74: -320.89212 | J74: -356.82517 | K74: -355.47476 | L74: -356.2054 | M74: -384.02428 | N74: -562.1246 | O74: -448.80933 | P74: -503.51077 | Q74: -488.96383 | R74: -703.59363 | S74: -498.4 | T74: -531.4 | U74: -569.3 | V74: -652.5 | W74: -1228 | X74: -1266.2 | Y74: -1469.2 | Z74: -1619.1 | AA74: -1506.6 | AB74: -1671.4 | AC74: -1655.4 | AD74: -1566.1 | AE74: -1423.4 | AF74: -1491.1 | AG74: -1474.7 | AH74: -1771.7 | AI74: -1310.9 | AJ74: -1317.3 | AK74: -1200.733 | AL74: -699.1 | AM74: -629.1 | AN74: -748.1 | AO74: -733.35786 | AP74: -863.5 | AQ74: -653.7 | AR74: -834.5 | AS74: -831.1 | AT74: -766 | AU74: =+AU214 -> -654.848 | AV74: =+AV214 -> -842.88 | AW74: =+AW214 -> -839.24 | AX74: =+AX214 -> -748.76 | BB74: -820.325 | BC74: =+AT74/BB74-1 -> -0.066223753 | BE74: =+SUM(C74:F74) -> -1293.5 | BF74: =+SUM(G74:J74) -> -1327.0929 | BG74: =+SUM(K74:N74) -> -1657.829 | BH74: =+SUM(O74:R74) -> -2144.8776 | BJ74: =+SUM(S74:V74) -> -2251.6 | BK74: =+SUM(W74:Z74) -> -5582.5 | BL74: =+SUM(AA74:AD74) -> -6399.5 | BM74: =+SUM(AE74:AH74) -> -6160.9 | BN74: =+SUM(AI74:AL74) -> -4528.033 | BO74: =+SUM(AM74:AP74) -> -2974.0579 | BP74: =+SUM(AQ74:AT74) -> -3085.3 | BQ74: =+SUM(AU74:AX74) -> -3085.728 | BR74: =+BR214 -> -3240.0144 | BS74: =+BS214 -> -3337.2148 | BT74: =+BT214 -> -3437.3313 | BU74: =+BU214 -> -3540.4512
B75: % Revs | C75: =+C74/C$57 -> -0.16956998 | D75: =+D74/D$57 -> -0.15506247 | E75: =+E74/E$57 -> -0.15742272 | F75: =+F74/F$57 -> -0.17226891 | G75: =+G74/G$57 -> -0.19386943 | H75: =+H74/H$57 -> -0.15885913 | I75: =+I74/I$57 -> -0.16865979 | J75: =+J74/J$57 -> -0.15549887 | ... AX75: =+AX74/AX$57 -> -0.11782031 | BB75: -0.12926768 | BC75: =+AT75-BB75 -> 0.0055796414 | BE75: =+BE74/BE$57 -> -0.16375491 | BF75: =+BF74/BF$57 -> -0.16771744 | BG75: =+BG74/BG$57 -> -0.16826058 | BH75: =+BH74/BH$57 -> -0.1604831 | BJ75: =+BJ74/BJ$57 -> -0.11578041 | BK75: =+BK74/BK$57 -> -0.15119753 | BL75: =+BL74/BL$57 -> -0.15933185 | BM75: =+BM74/BM$57 -> -0.16949204 | BN75: =+BN74/BN$57 -> -0.15494018 | BO75: =+BO74/BO$57 -> -0.12691816 | BP75: =+BP74/BP$57 -> -0.13886835 | BQ75: =+BQ74/BQ$57 -> -0.14228514 | ... BU75: =+BU74/BU$57 -> -0.13988005
B76: yoy | G76: =+G74/C74-1 -> 0.17665715 | H76: =+H74/D74-1 -> 0.075875194 | I76: =+I74/E74-1 -> 0.021298903 | J76: =+J74/F74-1 -> -0.11193337 | K76: =+K74/G74-1 -> 0.085149549 | L76: =+L74/H74-1 -> 0.10693519 | M76: =+M74/I74-1 -> 0.19673953 | N76: =+N74/J74-1 -> 0.57535018 | ... AX76: =+AX74/AT74-1 -> -0.022506527 | BB76: -0.05 | BF76: =+BF74/BE74-1 -> 0.025970552 | BG76: =+BG74/BF74-1 -> 0.24921852 | BH76: =+BH74/BG74-1 -> 0.29378694 | BJ76: =+BJ74/BH74-1 -> 0.049756892 | BK76: =+BK74/BJ74-1 -> 1.479348 | BL76: =+BL74/BK74-1 -> 0.1463502 | BM76: =+BM74/BL74-1 -> -0.037284163 | BN76: =+BN74/BM74-1 -> -0.26503709 | BO76: =+BO74/BN74-1 -> -0.34318989 | BP76: =+BP74/BO74-1 -> 0.03740416 | BQ76: =+BQ74/BP74-1 -> 0.00013872233 | BR76: =+BR74/BQ74-1 -> 0.05 | ... BU76: =+BU74/BT74-1 -> 0.03
B79: Other Operating Income / (Expenses) net | C79: 8.5 | D79: 9.9 | E79: 36.6 | F79: 10.8 | G79: 7.7405845 | H79: -4.4156493 | I79: 7.5 | J79: 43.561688 | K79: 180.06243 | L79: -22.649431 | M79: 89.449309 | N79: -42.423781 | O79: -13.162213 | P79: -3.2399167 | Q79: 38.003935 | R79: 37.266905 | S79: 21.1 | T79: 80.3 | U79: 13 | V79: 2 | W79: -15.1 | X79: =119.1-0.2 -> 118.9 | Y79: -38.6 | Z79: -18.8 | AA79: 8.7 | AB79: -20.6 | AC79: 244.6 | AD79: 34.9 | AE79: 21.4 | AF79: 93.6 | AG79: 22.6 | AH79: -435.2 | AI79: -11.7 | AJ79: -80.2 | AK79: -65.464 | AL79: -544.8 | AM79: 89.6 | AN79: 25.3 | AO79: -58.665199 | AP79: -511 | AQ79: 19.7 | AR79: 26.5 | AS79: 2.1 | AT79: -409 | AU79: =+AU217 -> 0 | AV79: =+AV217 -> 0 | AW79: =+AW217 -> 0 | AX79: =+AX217 -> 0 | BB79: 0 | BE79: =+SUM(C79:F79) -> 65.8 | BF79: =+SUM(G79:J79) -> 54.386623 | BG79: =+SUM(K79:N79) -> 204.43853 | BH79: =+SUM(O79:R79) -> 58.868711 | BJ79: =+SUM(S79:V79) -> 116.4 | BK79: =+SUM(W79:Z79) -> 46.4 | BL79: =+SUM(AA79:AD79) -> 267.6 | BM79: =+SUM(AE79:AH79) -> -297.6 | BN79: =+SUM(AI79:AL79) -> -702.164 | BO79: =+SUM(AM79:AP79) -> -454.7652 | BP79: =+SUM(AQ79:AT79) -> -360.7 | BQ79: =+SUM(AU79:AX79) -> 0 | BR79: =+BR217 -> 0 | BS79: =+BS217 -> 0 | BT79: =+BT217 -> 0 | BU79: =+BU217 -> 0
B80: Acquisition related expenses(c) | C80: 0 | D80: 0 | E80: 0 | F80: 0 | G80: 0 | H80: 0 | I80: 0 | J80: 0 | K80: 0 | L80: 0 | M80: -29.147 | N80: -22.485058 | O80: -0.1 | P80: 0 | Q80: 0 | R80: 0 | S80: 0 | T80: -55.6 | U80: -32 | V80: -37.5 | W80: -298.3 | X80: -5.6 | Y80: 0 | Z80: 0 | AA80: 0 | AB80: 0 | AC80: 0 | AD80: 0 | AE80: 0 | AF80: 0 | AG80: 0 | AH80: 0 | AI80: 0 | AJ80: 0 | AK80: 0 | AL80: 0 | AM80: 0 | AN80: 0 | AO80: 0 | AP80: 0 | AQ80: 0 | AR80: 0 | AS80: 0 | AT80: 0 | AU80: 0 | AV80: 0 | AW80: 0 | AX80: 0 | BB80: 0 | BE80: =+SUM(C80:F80) -> 0 | BF80: =+SUM(G80:J80) -> 0 | BG80: =+SUM(K80:N80) -> -51.632058 | BH80: =+SUM(O80:R80) -> -0.1 | BJ80: =+SUM(S80:V80) -> -125.1 | BK80: =+SUM(W80:Z80) -> -303.9 | BL80: =+SUM(AA80:AD80) -> 0 | BM80: =+SUM(AE80:AH80) -> 0 | BN80: =+SUM(AI80:AL80) -> 0 | BO80: =+SUM(AM80:AP80) -> 0 | BP80: =+SUM(AQ80:AT80) -> 0 | BQ80: =+SUM(AU80:AX80) -> 0 | BR80: 0 | BS80: 0 | BT80: 0 | BU80: 0
B81: Corporate Expenses(d) | C81: 0 | D81: 0 | E81: 0 | F81: 0 | G81: 0 | H81: 0 | I81: 0 | J81: 0 | K81: 0 | L81: 0 | M81: 0 | N81: -12.6 | O81: -15.811331 | P81: -21.556616 | Q81: -24.871848 | R81: -39.699382 | S81: -38.6 | T81: -32.9 | U81: -32.8 | V81: -38.8 | W81: -30.2 | X81: -78.1 | Y81: -99.8 | Z81: -171.3 | AA81: -110.9 | AB81: -148.4 | AC81: -142.3 | AD81: -157.4 | AE81: -109.9 | AF81: -88.7 | AG81: -72.5 | AH81: -121 | AI81: -70.1 | AJ81: -83.63 | AK81: -74.701 | AL81: -94.8 | AM81: -59.2 | AN81: -85.9 | AO81: -43.7 | AP81: -90 | AQ81: =-42.9-68.5-AR81 -> -30.7 | AR81: =-36.9-43.8 -> -80.7 | AS81: -32 | AT81: 0 | AU81: =+AQ81*0.95 -> -29.165 | AV81: =+AR81*0.95 -> -76.665 | AW81: =+AS81*0.95 -> -30.4 | AX81: =+AT81*0.95 -> 0 | BB81: -90 | BE81: =+SUM(C81:F81) -> 0 | BF81: =+SUM(G81:J81) -> 0 | BG81: =+SUM(K81:N81) -> -12.6 | BH81: =+SUM(O81:R81) -> -101.93918 | BJ81: =+SUM(S81:V81) -> -143.1 | BK81: =+SUM(W81:Z81) -> -379.4 | BL81: =+SUM(AA81:AD81) -> -559 | BM81: =+SUM(AE81:AH81) -> -392.1 | BN81: =+SUM(AI81:AL81) -> -323.231 | BO81: =+SUM(AM81:AP81) -> -278.8 | BP81: =+SUM(AQ81:AT81) -> -143.4 | BQ81: =+SUM(AU81:AX81) -> -136.23 | BR81: =+BQ81 -> -136.23 | BS81: =+BR81 -> -136.23 | BT81: =+BS81 -> -136.23 | BU81: =+BT81 -> -136.23
B82: % Revs | C82: =+C81/C$57 -> 0 | D82: =+D81/D$57 -> 0 | E82: =+E81/E$57 -> 0 | F82: =+F81/F$57 -> 0 | G82: =+G81/G$57 -> 0 | H82: =+H81/H$57 -> 0 | I82: =+I81/I$57 -> 0 | J82: =+J81/J$57 -> 0 | ... AX82: =+AX81/AX$57 -> 0 | BB82: -0.014182295 | BC82: =+AT82-BB82 -> 0.014182295 | BE82: =+BE81/BE$57 -> 0 | BF82: =+BF81/BF$57 -> 0 | BG82: =+BG81/BG$57 -> -0.0012788311 | BH82: =+BH81/BH$57 -> -0.0076272489 | BJ82: =+BJ81/BJ$57 -> -0.0073584013 | BK82: =+BK81/BK$57 -> -0.010275744 | BL82: =+BL81/BL$57 -> -0.013917729 | BM82: =+BM81/BM$57 -> -0.010787032 | BN82: =+BN81/BN$57 -> -0.011060314 | BO82: =+BO81/BO$57 -> -0.011897813 | BP82: =+BP81/BP$57 -> -0.0064543872 | BQ82: =+BQ81/BQ$57 -> -0.0062816632 | ... BU82: =+BU81/BU$57 -> -0.005382325
B83: Transformation Costs | O83: -0.2156283 | P83: -37.452319 | Q83: -24.693321 | R83: -36.10453 | S83: -6.8 | T83: -19.5 | U83: -6.4 | V83: -18.7 | W83: -25.1 | X83: -54.6 | Y83: -90.3 | Z83: -87 | AA83: -134.1 | AB83: -181.3 | AC83: -105.1 | AD83: -89.7 | AE83: -80.1 | AF83: -281.6 | AG83: -162.4 | AH83: -117 | AI83: -85 | AJ83: -239.1 | AK83: -219.281 | AL83: -226.8 | AM83: -42.3 | AN83: -67.6 | AO83: -132.09351 | AP83: -259.7 | AQ83: -125.9 | AR83: -98.7 | AS83: -98.1 | AT83: -105 | AU83: =+AU218 -> 0 | AV83: =+AV218 -> 0 | AW83: =+AW218 -> 0 | AX83: =+AX218 -> 0 | BB83: -100 | BE83: =+SUM(C83:F83) -> 0 | BF83: =+SUM(G83:J83) -> 0 | BG83: =+SUM(K83:N83) -> 0 | BH83: =+SUM(O83:R83) -> -98.465799 | BJ83: =+SUM(S83:V83) -> -51.4 | BK83: =+SUM(W83:Z83) -> -257 | BL83: =+SUM(AA83:AD83) -> -510.2 | BM83: =+SUM(AE83:AH83) -> -641.1 | BN83: =+SUM(AI83:AL83) -> -770.181 | BO83: =+SUM(AM83:AP83) -> -501.69351 | BP83: =+SUM(AQ83:AT83) -> -427.7 | BQ83: =+SUM(AU83:AX83) -> 0 | BR83: =+BR218 -> 0 | BS83: =+BS218 -> -50 | BT83: =+BT218 -> -50 | BU83: =+BU218 -> -50
B84: % Revs | O84: =+O83/O$57 -> -8.0230016e-05 | P84: =+P83/P$57 -> -0.012081228 | Q84: =+Q83/Q$57 -> -0.0076169257 | R84: =+R83/R$57 -> -0.0083275348 | S84: =+S83/S$57 -> -0.0023326415 | T84: =+T83/T$57 -> -0.0057290444 | U84: =+U83/U$57 -> -0.0018423628 | V84: =+V83/V$57 -> -0.0019369206 | ... AX84: =+AX83/AX$57 -> 0 | BB84: -0.015758105 | BH84: =+BH83/BH$57 -> -0.0073673653 | BJ84: =+BJ83/BJ$57 -> -0.0026430596 | BK84: =+BK83/BK$57 -> -0.0069606385 | BL84: =+BL83/BL$57 -> -0.012702728 | BM84: =+BM83/BM$57 -> -0.017637252 | BN84: =+BN83/BN$57 -> -0.026354044 | BO84: =+BO83/BO$57 -> -0.021409811 | BP84: =+BP83/BP$57 -> -0.019250637 | BQ84: =+BQ83/BQ$57 -> 0 | ... BU84: =+BU83/BU$57 -> -0.0019754551
B86: EBIT | C86: =+C115+C129 -> 228.7329 | D86: =+D115+D129 -> 304.26022 | E86: =+E115+E129 -> 337.08515 | F86: =+F115+F129 -> 386.39776 | G86: =+G115+G129 -> 153.92366 | H86: =+H115+H129 -> 280.35116 | I86: =+I115+I129 -> 251.4245 | J86: =+J115+J129 -> 397.1779 | ... AL86: =+AL115+AL129 -> -420.1 | AM86: =+AM61+AM65 -> 435.5 | AN86: =+AN61+AN65 -> 467.8 | AO86: =+AO61+AO65 -> 430.95195 | AP86: =+AP61+AP65 -> -432.7 | AQ86: =+AQ61+AQ65 -> 432.18673 | AR86: =+AR61+AR65 -> 446.5 | AS86: =+AS61+AS65 -> 224.9 | AT86: =+AT61+AT65 -> 203 | ... AX86: =+AX61+AX65 -> 587.36595 | BB86: 337.00837 | BE86: =+SUM(C86:F86) -> 1256.476 | BF86: =+SUM(G86:J86) -> 1082.8772 | BG86: =+SUM(K86:N86) -> 1358.6591 | BH86: =+SUM(O86:R86) -> 1263.8784 | BJ86: =+SUM(S86:V86) -> 4195.532 | BK86: =+SUM(W86:Z86) -> 789.8 | BL86: =+SUM(AA86:AD86) -> 1118.3 | BM86: =+SUM(AE86:AH86) -> -458.4 | BN86: =+SUM(AI86:AL86) -> -573.43029 | BO86: =+BO61+BO65 -> 901.55195 | BP86: =+BP61+BP65 -> 1306.5867 | BQ86: =+BQ61+BQ65 -> 1716.5708 | BR86: =+BR61+BR65 -> 1896.613 | BS86: =+BS61+BS65 -> 1953.684 | BT86: =+BT61+BT65 -> 2063.9408 | BU86: =+BU61+BU65 -> 2163.5845
B89: Depreciacion Total | C89: =+C92+C96 -> 57.167098 | D89: =+D92+D96 -> 52.939777 | E89: =+E92+E96 -> 62.514845 | F89: =+F92+F96 -> 66.802244 | G89: =+G92+G96 -> 63.073301 | H89: =+H92+H96 -> 64.374656 | I89: =+I92+I96 -> 97.522504 | J89: =+J92+J96 -> 64.947815 | ... T89: =+T92+T96 -> 272.4 | U89: 282.8 | V89: =+V92+V96 -> 297.8 | W89: 625.8 | X89: 703.9 | Y89: 711.1 | Z89: 678 | AA89: 696.4 | AB89: 698.9 | AC89: 664.4 | AD89: 731.9 | AE89: 649.3 | AF89: 629.7 | AG89: 622.3 | AH89: 690.6 | AI89: 603.5 | AJ89: 587.8 | AK89: 539.1859 | AL89: 364.4 | AM89: 222.1 | AN89: 237.4 | AO89: 227.9 | AP89: 261.6 | AQ89: 218.5 | AR89: 210.6 | AS89: 239.2 | AT89: 241 | AU89: =+AU92+AU96 -> 178.24633 | AV89: =+AV92+AV96 -> 181.452 | AW89: =+AW92+AW96 -> 311.15469 | AX89: =+AX92+AX96 -> 217.99477 | BB89: 239.2 | BE89: =+SUM(C89:F89) -> 239.42396 | BF89: =+SUM(G89:J89) -> 289.91828 | BG89: =+SUM(K89:N89) -> 383.30552 | BH89: =+SUM(O89:R89) -> 587.03697 | BJ89: =+SUM(S89:V89) -> 1117.3 | BK89: =+SUM(W89:Z89) -> 2718.8 | BL89: =+SUM(AA89:AD89) -> 2791.6 | BM89: =+SUM(AE89:AH89) -> 2591.9 | BN89: =+SUM(AI89:AL89) -> 2094.8859 | BO89: =+SUM(AM89:AP89) -> 949 | BP89: =+SUM(AQ89:AT89) -> 909.3 | BQ89: =+SUM(AU89:AX89) -> 888.8478 | BR89: =+BR92+BR96 -> 787.82604 | BS89: =+BS92+BS96 -> 743.19029 | BT89: =+BT92+BT96 -> 722.6314 | BU89: =+BU92+BU96 -> 712.53625
B90: % sales | C90: =+C89/C$57 -> 0.03481977 | D90: =+D89/D$57 -> 0.027445579 | E90: =+E89/E$57 -> 0.031321632 | F90: =+F89/F$57 -> 0.028640989 | G90: =+G89/G$57 -> 0.037328087 | H90: =+H89/H$57 -> 0.031779628 | I90: =+I89/I$57 -> 0.051257492 | J90: =+J89/J$57 -> 0.02830325 | ... AX90: =+AX89/AX$57 -> 0.034302328 | BB90: 0.037693388 | BE90: =+BE89/BE$57 -> 0.030310668 | BF90: =+BF89/BF$57 -> 0.036639748 | BG90: =+BG89/BG$57 -> 0.038903414 | BH90: =+BH89/BH$57 -> 0.043923026 | BJ90: =+BJ89/BJ$57 -> 0.057453122 | BK90: =+BK89/BK$57 -> 0.073636514 | BL90: =+BL89/BL$57 -> 0.069503991 | BM90: =+BM89/BM$57 -> 0.071305558 | BN90: =+BN89/BN$57 -> 0.071682779 | BO90: =+BO89/BO$57 -> 0.040498652 | BP90: =+BP89/BP$57 -> 0.040927296 | BQ90: =+BQ89/BQ$57 -> 0.040985411 | ... BU90: =+BU89/BU$57 -> 0.028151668
B92: Depreciation Imob e Intag | C92: 57.167098 | D92: 52.939777 | E92: 62.514845 | F92: 66.802244 | G92: 63.073301 | H92: 64.374656 | I92: 97.522504 | J92: 64.947815 | K92: 67.332451 | L92: 66.62092 | M92: 83.058378 | N92: 166.29377 | O92: 128.26159 | P92: 144.6639 | Q92: 143.08424 | R92: 171.02724 | S92: =264.3-S96 -> 135.86 | T92: =272.4-T96 -> 130.277 | U92: =282.8-U96 -> 124.594 | V92: 159.5 | W92: =+W89-W96 -> 268.924 | X92: =+X89-X96 -> 378.438 | Y92: =+Y89-Y96 -> 392.889 | Z92: =+Z89-Z96 -> 455.655 | AA92: =+AA89-AA96 -> 440.282 | AB92: =+AB89-AB96 -> 457.604 | AC92: =+AC89-AC96 -> 422.77 | AD92: =+AD89-AD96 -> 472.935 | ... AK92: =+AK89-AK96 -> 366.3029 | AL92: =565.035+1015.809-AK92-AJ92-AI92 -> 365.2641 | AM92: =+AM89-AM96 -> 144.234 | AN92: =+AN89-AN96 -> 153.269 | AO92: =+AO89-AO96 -> 228.433 | AP92: =+AP89-AP96 -> 806.41 | AQ92: =+AQ89-AQ96 -> 130.199 | AR92: =+AR89-AR96 -> 132.715 | AS92: =+AS89-AS96 -> 236.592 | AT92: =+AT89-AT96 -> 214.227 | AU92: =+AT93*AU94 -> 156.17858 | AV92: =+AU93*AV94 -> 159.38425 | AW92: =+AV93*AW94 -> 289.08694 | AX92: =+AW93*AX94 -> 195.92702 | BB92: 191.57278 | BE92: =+SUM(C92:F92) -> 239.42396 | BF92: =+SUM(G92:J92) -> 289.91828 | BG92: =+SUM(K92:N92) -> 383.30552 | BH92: =+SUM(O92:R92) -> 587.03697 | BJ92: =+SUM(S92:V92) -> 550.231 | BK92: =+SUM(W92:Z92) -> 1495.906 | BL92: =+SUM(AA92:AD92) -> 1793.591 | BM92: =+SUM(AE92:AH92) -> 1664.034 | BN92: =+SUM(AI92:AL92) -> 1580.844 | BO92: =+SUM(AM92:AP92) -> 1332.346 | BP92: =+SUM(AQ92:AT92) -> 713.733 | BQ92: =+SUM(AU92:AX92) -> 800.5768 | BR92: =+BQ93*BR94 -> 708.2463 | BS92: =+BR93*BS94 -> 663.61055 | BT92: =+BS93*BT94 -> 640.5835 | BU92: =+BT93*BU94 -> 632.33947
B93: Inmob | C93: =+PROJ!C112 -> 1759.945 | D93: =+PROJ!D112 -> 1727.015 | E93: =+PROJ!E112 -> 1761.819 | F93: =+PROJ!F112 -> 1752.35 | G93: =+PROJ!G112 -> 1739.664 | H93: =+PROJ!H112 -> 1717.734 | I93: =+PROJ!I112 -> 1707.288 | J93: =+PROJ!J112 -> 1734.688 | ... AX93: =+PROJ!AX112 -> 2184.3582 | BB93: 2405.8487 | BE93: =+F93 -> 1752.35 | BF93: =+J93 -> 1734.688 | BG93: =+N93 -> 2276.674 | BH93: =+R93 -> 2236.714 | BJ93: =+V93 -> 1773.9 | BK93: =+PROJ!BI112 -> 5235.1 | BL93: =+PROJ!BJ112 -> 5377.4 | BM93: =+PROJ!BK112 -> 4966.2 | BN93: =+PROJ!BL112 -> 3457.6 | BO93: =+PROJ!BM112 -> 2058.395 | BP93: =+PROJ!BN112 -> 2469.122 | BQ93: =+PROJ!BO112 -> 2184.3582 | BR93: =+PROJ!BP112 -> 2046.6936 | ... BU93: =+PROJ!BS112 -> 1954.8084
B94: Taxa | C94: =+C92/B93 -> #VALUE! | D94: =+D92/C93 -> 0.030080359 | E94: =+E92/D93 -> 0.036198206 | F94: =+F92/E93 -> 0.037916633 | G94: =+G92/F93 -> 0.035993552 | H94: =+H92/G93 -> 0.037004075 | I94: =+I92/H93 -> 0.056773926 | J94: =+J92/I93 -> 0.038041511 | ... AT94: =+AT92/AS93 -> 0.088182085 | AU94: =+AQ94 -> 0.06325268 | AV94: =+AR94 -> 0.06598951 | AW94: =+AS94 -> 0.12118437 | AX94: =+AT94 -> 0.088182085 | BB94: 0.078856945 | BE94: =+BE92/BE93 -> 0.13663022 | BF94: =+BF92/BE93 -> 0.16544542 | BG94: =+BG92/BF93 -> 0.22096511 | BH94: =+BH92/BG93 -> 0.2578485 | BJ94: =+BJ92/BH93 -> 0.24599971 | BK94: =+BK92/BK93 -> 0.28574545 | BL94: =+BL92/BK93 -> 0.34260874 | BM94: =+BM92/BL93 -> 0.30944955 | BN94: =+BN92/BM93 -> 0.31832065 | BO94: =+BO92/BN93 -> 0.38533839 | BP94: =+BP92/BO93 -> 0.34674249 | BQ94: =+BQ92/BP93 -> 0.32423542 | BR94: =+BQ94 -> 0.32423542 | BS94: =+BR94 -> 0.32423542 | BT94: =+BS94 -> 0.32423542 | BU94: =+BT94 -> 0.32423542
B96: Arrendamento | S96: 128.44 | T96: =270.563-S96 -> 142.123 | U96: =428.769-T96-S96 -> 158.206 | V96: 138.3 | W96: =930.974-574.098 -> 356.876 | X96: =1256.436-574.098-W96 -> 325.462 | Y96: =1574.647-574.098-X96-W96 -> 318.211 | Z96: =1796.992-574.098-Y96-X96-W96 -> 222.345 | AA96: 256.118 | AB96: =497.414-AA96 -> 241.296 | AC96: =739.044-AB96-AA96 -> 241.63 | AD96: =998.009-AC96-AB96-AA96 -> 258.965 | AE96: 247.152 | AF96: =458.833-AE96 -> 211.681 | AG96: =704.501-AF96-AE96 -> 245.668 | AH96: =927.866-AG96-AF96-AE96 -> 223.365 | AI96: 171.198 | AJ96: =342.023-AI96 -> 170.825 | AK96: =514.906-AJ96-AI96 -> 172.883 | AL96: =694.835-AK96-AJ96-AI96 -> 179.929 | AM96: 77.866 | AN96: =161.997-AM96 -> 84.131 | AO96: =161.464-AN96-AM96 -> -0.533 | AP96: =-383.346-AO96-AN96-AM96 -> -544.81 | AQ96: 88.301 | AR96: =166.186-AQ96 -> 77.885 | AS96: =168.794-AR96-AQ96 -> 2.608 | AT96: =195.567-AS96-AR96-AQ96 -> 26.773 | AU96: =+$BP$96/4 -> 22.06775 | AV96: =+$BP$96/4 -> 22.06775 | AW96: =+$BP$96/4 -> 22.06775 | AX96: =+$BP$96/4 -> 22.06775 | BB96: 47.627224 | BE96: =+SUM(C96:F96) -> 0 | BF96: =+SUM(G96:J96) -> 0 | BG96: =+SUM(K96:N96) -> 0 | BH96: =+SUM(O96:R96) -> 0 | BJ96: =+SUM(S96:V96) -> 567.069 | BK96: =+SUM(W96:Z96) -> 1222.894 | BL96: =+SUM(AA96:AD96) -> 998.009 | BM96: =+SUM(AE96:AH96) -> 927.866 | BN96: =+SUM(AI96:AL96) -> 694.835 | BO96: =719.586-527.575 -> 192.011 | BP96: =807.857-719.586 -> 88.271 | BQ96: =+BQ98*BP97 -> 79.579739 | BR96: =+BR98*BQ97 -> 79.579739 | BS96: =+BS98*BR97 -> 79.579739 | BT96: =+BT98*BS97 -> 82.047901 | BU96: =+BU98*BT97 -> 80.196779
B97: Leases Activo | S97: =+PROJ!S114 -> 2408.249 | T97: =+PROJ!T114 -> 2419.4 | U97: =+PROJ!U114 -> 2685.6 | V97: =+PROJ!V114 -> 2619.9 | W97: =+PROJ!W114 -> 3736.5 | X97: =+PROJ!X114 -> 3810 | Y97: =+PROJ!Y114 -> 3846.4 | Z97: =+PROJ!Z114 -> 3402 | ... AT97: =+PROJ!AT114 -> 666.743 | AU97: =+AU100+AU105 -> 666.743 | AV97: =+AV100+AV105 -> 666.743 | AW97: =+AW100+AW105 -> 666.743 | AX97: =+AX100+AX105 -> 666.743 | BB97: 649.872 | BJ97: =+V97 -> 2619.9 | BK97: =+Z97 -> 3402 | BL97: =+AD97 -> 3096 | BM97: =+AH97 -> 2941.9 | BN97: =+AL97 -> 1050.8 | BO97: =+AP97 -> 739.561 | BP97: =+AT97 -> 666.743 | BQ97: =+BQ100+BQ105 -> 666.743 | BR97: =+BR100+BR105 -> 666.743 | BS97: =+BS100+BS105 -> 687.422 | BT97: =+BT100+BT105 -> 671.91275 | BU97: =+BU100+BU105 -> 673.20519
B98: taxa | S98: =+S96/S97 -> 0.053333355 | T98: =+T96/S97 -> 0.059015077 | U98: =+U96/T97 -> 0.065390593 | V98: =+V96/U97 -> 0.051496872 | W98: =+W96/W97 -> 0.095510772 | X98: =+X96/X97 -> 0.085423097 | Y98: =+Y96/Y97 -> 0.082729565 | Z98: =+Z96/Z97 -> 0.065357143 | AA98: =+AA96/AA97 -> 0.075595632 | AB98: =+AB96/AB97 -> 0.081678966 | AC98: =+AC96/AC97 -> 0.079596139 | AD98: =+AD96/AD97 -> 0.083645026 | ... AJ98: =+AJ96/AJ97 -> 0.08616211 | AK98: =+AK96/AJ97 -> 0.087200141 | AL98: =+AL96/AK97 -> 0.091177156 | AM98: =+AM96/AL97 -> 0.074101637 | AN98: =+AN96/AM97 -> 0.1193026 | AO98: =+AO96/AN97 -> -0.00073735498 | AP98: =+AP96/AO97 -> -0.7486235 | AQ98: =+AQ96/AP97 -> 0.11939651 | AR98: =+AR96/AQ97 -> 0.11462796 | ... AX98: =+AX96/AW97 -> 0.033097835 | BB98: 0.073287084 | BJ98: =+BJ96/BJ97 -> 0.21644681 | BK98: =+BK96/BK97 -> 0.35946326 | BL98: =+BL96/BL97 -> 0.32235433 | BM98: =+BM96/BM97 -> 0.31539685 | BN98: =+BN96/BM97 -> 0.2361858 | BO98: =+BO96/BN97 -> 0.1827284 | BP98: =+BP96/BO97 -> 0.11935594 | BQ98: =+BP98 -> 0.11935594 | BR98: =+BQ98 -> 0.11935594 | BS98: =+BR98 -> 0.11935594 | BT98: =+BS98 -> 0.11935594 | BU98: =+BT98 -> 0.11935594
B100: Lojas de varejo | AD100: =3417.595-1458.512 -> 1959.083 | AE100: =2953.335-1284.856 -> 1668.479 | AF100: =3269.893-1379.514 -> 1890.379 | AG100: =3281.02-1396.978 -> 1884.042 | AH100: =3361.432-1525.308 -> 1836.124 | AI100: =1912.89-929.712 -> 983.178 | AJ100: =1831.753-874.46 -> 957.293 | AK100: =1904.281-966.948 -> 937.333 | AL100: =146.994-90.804 -> 56.19 | AM100: =151.694-93.137 -> 58.557 | AN100: =165.16-99.365 -> 65.795 | AO100: =167.82-105.179 -> 62.641 | AP100: =167.971-109.769 -> 58.202 | AQ100: =130.986-78.153 -> 52.833 | AR100: =123.374-78.847 -> 44.527 | AS100: =167.971-81.76 -> 86.211 | AT100: =+BP100 -> 96.109 | AU100: =+AT100 -> 96.109 | AV100: =+AU100 -> 96.109 | AW100: =+AV100 -> 96.109 | AX100: =+AW100 -> 96.109 | BB100: 86.211 | BJ100: =2350.377-463.332 -> 1887.045 | BK100: =3338.104-1291.346 -> 2046.758 | BL100: =+AD100 -> 1959.083 | BM100: =+AH100 -> 1836.124 | BN100: =+AL100 -> 56.19 | BO100: =167.971-81.76 -> 86.211 | BP100: =148.653-52.544 -> 96.109 | BQ100: =+AX100 -> 96.109 | BR100: =+BQ100 -> 96.109 | BS100: =+BR100 -> 96.109 | BT100: =+BS100 -> 96.109 | BU100: =+BT100 -> 96.109
B101: Dep | AE101: -164.748 | AF101: =-293.566-AE101 -> -128.818 | AG101: =-438.675-AF101-AE101 -> -145.109 | AH101: =-611.862-AG101-AF101-AE101 -> -173.187 | AI101: -97.093 | AJ101: =-187.207-AI101 -> -90.114 | AK101: =-285.042-AJ101-AI101 -> -97.835 | AL101: =-390.499-AK101-AJ101-AI101 -> -105.457 | AM101: -5.592 | AN101: =-12.129-AM101 -> -6.537 | AO101: =-17.691-AN101-AM101 -> -5.562 | AP101: =-23.076-AO101-AN101-AM101 -> -5.385 | AQ101: -5.107 | AR101: =-9.746-AQ101 -> -4.639 | AS101: =-14.363-AR101-AQ101 -> -4.617 | AT101: =+BP101-AS101-AR101-AQ101 -> -11.934 | AU101: =+AU102*AT100 -> -11.934 | AV101: =+AV102*AU100 -> -11.934 | AW101: =+AW102*AV100 -> -11.934 | AX101: =+AX102*AW100 -> -11.934 | BB101: -4.6201089 | BJ101: -466.59 | BK101: -643.441 | BL101: -659.109 | BM101: =+SUM(AE101:AH101) -> -611.862 | BN101: =+SUM(AI101:AL101) -> -390.499 | BO101: =+SUM(AM101:AP101) -> -23.076 | BP101: -26.297 | BQ101: =+SUM(AU101:AX101) -> -47.736 | BR101: =+BR102*BQ100 -> -47.736 | BS101: =+BS102*BR100 -> -47.736 | BT101: =+BT102*BS100 -> -47.736 | BU101: =+BU102*BT100 -> -47.736
B102: tasa | AE102: =+AE101/AD100 -> -0.084094446 | AF102: =+AF101/AE100 -> -0.077206845 | AG102: =+AG101/AF100 -> -0.076761856 | AH102: =+AH101/AG100 -> -0.09192311 | AI102: =+AI101/AH100 -> -0.052879326 | AJ102: =+AJ101/AI100 -> -0.091655834 | AK102: =+AK101/AJ100 -> -0.10219964 | AL102: =+AL101/AK100 -> -0.11250751 | ... AR102: =+AR101/AQ100 -> -0.08780497 | AS102: =+AS101/AS100 -> -0.053554651 | AT102: =+AT101/AT100 -> -0.12417151 | AU102: =+AT102 -> -0.12417151 | AV102: =+AU102 -> -0.12417151 | AW102: =+AV102 -> -0.12417151 | AX102: =+AW102 -> -0.12417151 | BB102: -0.053590713 | BK102: =+BK101/BJ100 -> -0.34097809 | BL102: =+BL101/BK100 -> -0.32202586 | BM102: =+BM101/BL100 -> -0.31232061 | BN102: =+BN101/BM100 -> -0.21267572 | BO102: =+BO101/BN100 -> -0.41067806 | BP102: =+BP101/BO100 -> -0.30503068 | BQ102: =+BQ101/BP100 -> -0.49668605 | BR102: =+BQ102 -> -0.49668605 | BS102: =+BR102 -> -0.49668605 | BT102: =+BS102 -> -0.49668605 | BU102: =+BT102 -> -0.49668605
B105: Others | AD105: =+AD97-AD100 -> 1136.917 | AE105: =+AE97-AE100 -> 1108.821 | AF105: =+AF97-AF100 -> 1136.621 | AG105: =+AG97-AG100 -> 1104.058 | AH105: =+AH97-AH100 -> 1105.776 | AI105: =+AI97-AI100 -> 1111.122 | AJ105: =+AJ97-AJ100 -> 1025.307 | AK105: =+AK97-AK100 -> 1036.067 | ... AT105: =+AT97-AT100 -> 570.634 | AU105: =+AT105 -> 570.634 | AV105: =+AU105 -> 570.634 | AW105: =+AV105 -> 570.634 | AX105: =+AW105 -> 570.634 | BB105: 563.661 | BJ105: =+BJ97-BJ100 -> 732.855 | BK105: =+BK97-BK100 -> 1355.242 | BL105: =+AD105 -> 1136.917 | BM105: =+AH105 -> 1105.776 | BN105: =+AL105 -> 994.61 | BO105: =+BO97-BO100 -> 653.35 | BP105: =+BP97-BP100 -> 570.634 | BQ105: =+AX105 -> 570.634 | BR105: =+AVERAGE(BP105:BQ105) -> 570.634 | BS105: =+AVERAGE(BO105:BR105) -> 591.313 | BT105: =+AVERAGE(BP105:BS105) -> 575.80375 | BU105: =+AVERAGE(BQ105:BT105) -> 577.09619
B106: Dep | AD106: =-AD96-AD101 -> -258.965 | AE106: =-AE96-AE101 -> -82.404 | AF106: =-AF96-AF101 -> -82.863 | AG106: =-AG96-AG101 -> -100.559 | AH106: =-AH96-AH101 -> -50.178 | AI106: =-AI96-AI101 -> -74.105 | AJ106: =-AJ96-AJ101 -> -80.711 | AK106: =-AK96-AK101 -> -75.048 | ... AT106: =-AT96-AT101 -> -14.839 | AU106: =+AU107*AT105 -> -14.839 | AV106: =+AV107*AU105 -> -14.839 | AW106: =+AW107*AV105 -> -14.839 | AX106: =+AX107*AW105 -> -14.839 | BB106: -43.007115 | BJ106: =-BJ96-BJ101 -> -100.479 | BK106: =-BK96-BK101+564.67-148.05 -> -162.833 | BL106: =-BL96-BL101 -> -338.9 | BM106: =+SUM(AE106:AH106) -> -316.004 | BN106: =+SUM(AI106:AL106) -> -304.336 | BO106: =+SUM(AM106:AP106) -> 406.422 | BP106: =+SUM(AQ106:AT106) -> -169.27 | BQ106: =+SUM(AU106:AX106) -> -59.356 | BR106: =+BR107*BQ105 -> -59.356 | BS106: =+BS107*BR105 -> -59.356 | BT106: =+BT107*BS105 -> -61.506981 | BU106: =+BU107*BT105 -> -59.893745
B107: tasa | AE107: =+AE106/AD105 -> -0.072480225 | AF107: =+AF106/AE105 -> -0.074730728 | AG107: =+AG106/AF105 -> -0.088471883 | AH107: =+AH106/AG105 -> -0.045448699 | AI107: =+AI106/AH105 -> -0.067016285 | AJ107: =+AJ106/AI105 -> -0.072639188 | AK107: =+AK106/AJ105 -> -0.073195638 | AL107: =+AL106/AK105 -> -0.071879521 | ... AR107: =+AR106/AQ105 -> -0.1168895 | AS107: =+AS106/AS105 -> 0.003564199 | AT107: =+AT106/AT105 -> -0.026004409 | AU107: =+AT107 -> -0.026004409 | AV107: =+AU107 -> -0.026004409 | AW107: =+AV107 -> -0.026004409 | AX107: =+AW107 -> -0.026004409 | BB107: -0.076299611 | BK107: =+BK106/BJ105 -> -0.22218993 | BL107: =+BL106/BK105 -> -0.25006604 | BM107: =+BM106/BL105 -> -0.27794817 | BN107: =+BN106/BM105 -> -0.27522392 | BO107: =+BO106/BN105 -> 0.40862449 | BP107: =+BP106/BO105 -> -0.25908013 | BQ107: =+BQ106/BP105 -> -0.10401764 | BR107: =+BQ107 -> -0.10401764 | BS107: =+BR107 -> -0.10401764 | BT107: =+BS107 -> -0.10401764 | BU107: =+BT107 -> -0.10401764
B110: Leases Pasivo | S110: =+S112+S113 -> 2248.2 | T110: =+T112+T113 -> 2271.821 | U110: =+U112+U113 -> 2545.4 | V110: =+V112+V113 -> 2517.6 | W110: =+W112+W113 -> 3928 | X110: =+X112+X113 -> 4107.2 | Y110: =+Y112+Y113 -> 4181.8 | Z110: =+Z112+Z113 -> 3858.5 | ... AT110: =+AT112+AT113 -> 593.882 | AU110: =+AU111*AU97 -> 593.882 | AV110: =+AV111*AV97 -> 593.882 | AW110: =+AW111*AW97 -> 593.882 | AX110: =+AX111*AX97 -> 593.882 | BB110: 557.041 | BJ110: =+V110 -> 2517.6 | BK110: =+Z110 -> 3858.5 | BL110: =+AD110 -> 3547.8 | BM110: =+AH110 -> 3270.7 | BN110: =+AI110 -> 2279.7 | BO110: =+AM110 -> 642.304 | BP110: =+AQ110 -> 590.545 | BQ110: =+AU110 -> 593.882 | BR110: =+BR111*BR97 -> 593.882 | BS110: =+BS111*BS97 -> 612.30122 | BT110: =+BT111*BT97 -> 598.4868 | BU110: =+BU111*BU97 -> 599.63801
S111: =+S110/S97 -> 0.93354134 | T111: =+T110/T97 -> 0.93900182 | U111: =+U110/U97 -> 0.94779565 | V111: =+V110/V97 -> 0.96095271 | W111: =+W110/W97 -> 1.0512512 | X111: =+X110/X97 -> 1.0780052 | Y111: =+Y110/Y97 -> 1.0871984 | Z111: =+Z110/Z97 -> 1.1341858 | ... AT111: =+AT110/AT97 -> 0.89072101 | AU111: =+AT111 -> 0.89072101 | AV111: =+AU111 -> 0.89072101 | AW111: =+AV111 -> 0.89072101 | AX111: =+AW111 -> 0.89072101 | BB111: 0.85715495 | BJ111: =+BJ110/BJ97 -> 0.96095271 | BK111: =+BK110/BK97 -> 1.1341858 | BL111: =+BL110/BL97 -> 1.1459302 | BM111: =+BM110/BM97 -> 1.1117645 | BN111: =+BN110/BN97 -> 2.1694899 | BO111: =+BO110/BO97 -> 0.86849361 | BP111: =+BP110/BP97 -> 0.88571609 | BQ111: =+BQ110/BQ97 -> 0.89072101 | BR111: =+BQ111 -> 0.89072101 | BS111: =+BR111 -> 0.89072101 | BT111: =+BS111 -> 0.89072101 | BU111: =+BT111 -> 0.89072101
B112: CP | S112: =+PROJ!S118 -> 451.6 | T112: =+PROJ!T118 -> 456.134 | U112: =+PROJ!U118 -> 504.2 | V112: =+PROJ!V118 -> 542.1 | W112: =+PROJ!W118 -> 956.4 | X112: =+PROJ!X118 -> 1081.1 | Y112: =+PROJ!Y118 -> 1129.2 | Z112: =+PROJ!Z118 -> 1059.7 | ... AT112: =+PROJ!AT118 -> 192.427 | AU112: =+AT112*AU$110/AT$110 -> 192.427 | AV112: =+AU112*AV$110/AU$110 -> 192.427 | AW112: =+AV112*AW$110/AV$110 -> 192.427 | AX112: =+AW112*AX$110/AW$110 -> 192.427 | BB112: 180.266 | BJ112: =+V112 -> 542.1 | BK112: =+Z112 -> 1059.7 | BL112: =+AD112 -> 1005.5 | BM112: =+AH112 -> 878.4 | BN112: =+AI112 -> 635 | BO112: =+AM112 -> 155.353 | BP112: =+AQ112 -> 175.591 | BQ112: =+AU112 -> 192.427 | BR112: =+BQ112*BR$110/BQ$110 -> 192.427 | BS112: =+BR112*BS$110/BR$110 -> 198.39511 | BT112: =+BS112*BT$110/BS$110 -> 193.91903 | BU112: =+BT112*BU$110/BT$110 -> 194.29204
B113: LP | S113: =+PROJ!S132 -> 1796.6 | T113: =+PROJ!T132 -> 1815.687 | U113: =+PROJ!U132 -> 2041.2 | V113: =+PROJ!V132 -> 1975.5 | W113: =+PROJ!W132 -> 2971.6 | X113: =+PROJ!X132 -> 3026.1 | Y113: =+PROJ!Y132 -> 3052.6 | Z113: =+PROJ!Z132 -> 2798.8 | ... AT113: =+PROJ!AT132 -> 401.455 | AU113: =+AT113*AU$110/AT$110 -> 401.455 | AV113: =+AU113*AV$110/AU$110 -> 401.455 | AW113: =+AV113*AW$110/AV$110 -> 401.455 | AX113: =+AW113*AX$110/AW$110 -> 401.455 | BB113: 376.775 | BJ113: =+V113 -> 1975.5 | BK113: =+Z113 -> 2798.8 | BL113: =+AD113 -> 2542.3 | BM113: =+AH113 -> 2392.3 | BN113: =+AI113 -> 1644.7 | BO113: =+AM113 -> 486.951 | BP113: =+AQ113 -> 414.954 | BQ113: =+AU113 -> 401.455 | BR113: =+BQ113*BR$110/BQ$110 -> 401.455 | BS113: =+BR113*BS$110/BR$110 -> 413.90611 | BT113: =+BS113*BT$110/BS$110 -> 404.56778 | BU113: =+BT113*BU$110/BT$110 -> 405.34597
B115: EBITDA | C115: =+C61+C65 -> 285.9 | D115: =+D61+D65 -> 357.2 | E115: =+E61+E65 -> 399.6 | F115: =+F61+F65 -> 453.2 | G115: =+G61+G65 -> 216.99696 | H115: =+H61+H65 -> 344.72581 | I115: =+I61+I65 -> 348.947 | J115: =+J61+J65 -> 462.12572 | ... AL115: =+AL61+AL65 -> -55.7 | AM115: =+AM86+AM89 -> 657.6 | AN115: =+AN86+AN89 -> 705.2 | AO115: =+AO86+AO89 -> 658.85195 | AP115: =+AP86+AP89 -> -171.1 | AQ115: =+AQ86+AQ89 -> 650.68673 | AR115: =+AR86+AR89 -> 657.1 | AS115: =+AS86+AS89 -> 464.1 | AT115: =+AT86+AT89 -> 444 | ... AX115: =+AX86+AX89 -> 805.36072 | BB115: 576.20837 | BC115: =+AT115/BB115-1 -> -0.22944541 | BE115: =+SUM(C115:F115) -> 1495.9 | BF115: =+SUM(G115:J115) -> 1372.7955 | BG115: =+SUM(K115:N115) -> 1741.9646 | BH115: =+SUM(O115:R115) -> 1850.9154 | BJ115: =+BJ61+BJ65 -> 5312.832 | BK115: =+BK61+BK65 -> 3508.6 | BL115: =+BL61+BL65 -> 3909.9 | BM115: =+BM61+BM65 -> 2133.5 | BN115: =+BN61+BN65 -> 1521.4556 | BO115: =+BO86+BO89 -> 1850.5519 | BP115: =+BP86+BP89 -> 2215.8867 | BQ115: =+BQ86+BQ89 -> 2605.4186 | BR115: =+BR86+BR89 -> 2684.439 | BS115: =+BS86+BS89 -> 2696.8743 | BT115: =+BT86+BT89 -> 2786.5722 | BU115: =+BU86+BU89 -> 2876.1208
B116: EBITDA Margin | C116: =+C115/C$57 -> 0.17413814 | D116: =+D115/D$57 -> 0.18518327 | E116: =+E115/E$57 -> 0.20021043 | F116: =+F115/F$57 -> 0.19430629 | G116: =+G115/G$57 -> 0.1284233 | H116: =+H115/H$57 -> 0.17017967 | I116: =+I115/I$57 -> 0.18340534 | J116: =+J115/J$57 -> 0.20138722 | ... AX116: =+AX115/AX$57 -> 0.12672665 | BB116: 0.09079952 | BC116: =+AT116-BB116 -> -0.019105672 | BE116: =+BE115/BE$57 -> 0.1893784 | BF116: =+BF115/BF$57 -> 0.17349331 | BG116: =+BG115/BG$57 -> 0.17679988 | BH116: =+BH115/BH$57 -> 0.13848839 | BJ116: =+BJ115/BJ$57 -> 0.27319322 | BK116: =+BK115/BK$57 -> 0.095027612 | BL116: =+BL115/BL$57 -> 0.097346917 | BM116: =+BM115/BM$57 -> 0.058694552 | BN116: =+BN115/BN$57 -> 0.052061149 | BO116: =+BO115/BO$57 -> 0.078972454 | BP116: =+BP115/BP$57 -> 0.099736338 | BQ116: =+BQ115/BQ$57 -> 0.12013772 | ... BU116: =+BU115/BU$57 -> 0.11363295
B117: yoy | G117: =+G116-C116 -> -0.045714842 | H117: =+H116-D116 -> -0.015003592 | I117: =+I116-E116 -> -0.016805091 | J117: =+J116-F116 -> 0.0070809212 | K117: =+K116-G116 -> 0.082477577 | L117: =+L116-H116 -> -0.022768531 | M117: =+M116-I116 -> 0.0069935539 | N117: =+N116-J116 -> -0.033046814 | ... AX117: =+AX116-AT116 -> 0.055032803 | BB117: 0.11493006 | BF117: =+BF115/BE115-1 -> -0.082294611 | BG117: =+BG115/BF115-1 -> 0.26891776 | BH117: =+BH115/BG115-1 -> 0.062544796 | BJ117: =+BJ115/BH115-1 -> 1.8703808 | BK117: =+BK115/BJ115-1 -> -0.33959892 | BL117: =+BL115/BK115-1 -> 0.1143761 | BM117: =+BM115/BL115-1 -> -0.45433387 | BN117: =+BN115/BM115-1 -> -0.28687339 | BO117: =+BO115/BN115-1 -> 0.2163036 | BP117: =+BP115/BO115-1 -> 0.19741936 | BQ117: =+BQ115/BP115-1 -> 0.1757905 | BR117: =+BR115/BQ115-1 -> 0.030329286 | ... BU117: =+BU115/BT115-1 -> 0.032135745
AG118: =+AG233+AG498+AG573+AG641 -> 701.2
B119: Ajustes | N119: =+N121-N115 -> #REF! | O119: =+O121-O115 -> #REF! | P119: =+P121-P115 -> #REF! | Q119: =+Q121-Q115 -> #REF! | R119: =+R121-R115 -> #REF! | S119: =+S121-S115 -> #REF! | T119: =+T121-T115 -> -5.2 | U119: =+U121-U115 -> 25.4 | ... AT119: =+AT121-AT115 -> 534 | AU119: =-AU83 -> 0 | AV119: =-AV83 -> 0 | AW119: =-AW83 -> 0 | AX119: =-AX83 -> 0 | BB119: 100 | BE119: =+BE121-BE115 -> #REF! | BF119: =+BF121-BF115 -> #REF! | BG119: =+BG121-BG115 -> #REF! | BH119: =+BH121-BH115 -> #REF! | BJ119: =+BJ121-BJ115 -> #REF! | BK119: =+BK121-BK115 -> 711.1 | BL119: =+BL121-BL115 -> 226.6 | BM119: =+BM121-BM115 -> 1025.2 | BN119: =+BN121-BN115 -> 1495.495 | BO119: =+BO121-BO115 -> 1011.4481 | BP119: =+BP121-BP115 -> 916.11327 | BQ119: =+BQ121-BQ115 -> 0 | BR119: =-BR83 -> 0 | BS119: =-BS83 -> 50 | BT119: =-BT83 -> 50 | BU119: =-BU83 -> 50
B121: EBITDA Adj | N121: =+#REF!-N83-N79 -> #REF! | O121: =+#REF!-O83-O79 -> #REF! | P121: =+#REF!-P83-P79 -> #REF! | Q121: =+#REF!-Q83-Q79 -> #REF! | R121: =+#REF!-57.2+34.2-R83 -> #REF! | S121: =+#REF!-S83-S79-S80 -> #REF! | T121: =+T115-T83-T79-T80 -> 552.354 | U121: =+U115-U83-U79-U80 -> 573.7 | V121: =+V115-V83-V79-V80 -> 3812.1 | W121: 571.5 | X121: 615.2 | Y121: 1547.3 | Z121: 1485.7 | AA121: 963.2 | AB121: 811.2 | AC121: 819.1 | AD121: 1543 | AE121: 595.9 | AF121: 694.9 | AG121: 772.5 | AH121: 1095.4 | AI121: 841.71757 | AJ121: 753.1 | AK121: 751.433 | AL121: 670.7 | AM121: 607 | AN121: 761.3 | AO121: 870.1 | AP121: 623.6 | AQ121: 781.5 | AR121: 795.6 | AS121: 576.9 | AT121: 978 | AU121: =+AU115+AU119 -> 611.34915 | AV121: =+AV115+AV119 -> 543.66743 | AW121: =+AW115+AW119 -> 645.04127 | AX121: =+AX115+AX119 -> 805.36072 | BB121: 676.20837 | BC121: =+AT121/BB121-1 -> 0.44629977 | BE121: =+#REF!-BE83-BE79-BE80 -> #REF! | BF121: =+#REF!-BF83-BF79-BF80 -> #REF! | BG121: =+#REF!-BG83-BG79-BG80 -> #REF! | BH121: =+#REF!-BH83-BH79-BH80 -> #REF! | BJ121: =+SUM(S121:V121) -> #REF! | BK121: =+SUM(W121:Z121) -> 4219.7 | BL121: =+SUM(AA121:AD121) -> 4136.5 | BM121: =+SUM(AE121:AH121) -> 3158.7 | BN121: =+SUM(AI121:AL121) -> 3016.9506 | BO121: =+SUM(AM121:AP121) -> 2862 | BP121: =+SUM(AQ121:AT121) -> 3132 | BQ121: =+SUM(AU121:AX121) -> 2605.4186 | BR121: =+BR115+BR119 -> 2684.439 | BS121: =+BS115+BS119 -> 2746.8743 | BT121: =+BT115+BT119 -> 2836.5722 | BU121: =+BU115+BU119 -> 2926.1208
B122: mrgn | N122: =+N121/N$57 -> #REF! | O122: =+O121/O$57 -> #REF! | P122: =+P121/P$57 -> #REF! | Q122: =+Q121/Q$57 -> #REF! | R122: =+R121/R$57 -> #REF! | S122: =+S121/S$57 -> #REF! | T122: =+T121/T$57 -> 0.16228003 | U122: =+U121/U$57 -> 0.16515056 | ... AX122: =+AX121/AX$57 -> 0.12672665 | BB122: 0.10655763 | BC122: =+AT122-BB122 -> 0.051362607 | BE122: =+BE121/BE$57 -> #REF! | BF122: =+BF121/BF$57 -> #REF! | BG122: =+BG121/BG$57 -> #REF! | BH122: =+BH121/BH$57 -> #REF! | BJ122: =+BJ121/BJ$57 -> #REF! | BK122: =+BK121/BK$57 -> 0.11428718 | BL122: =+BL121/BL$57 -> 0.1029887 | BM122: =+BM121/BM$57 -> 0.086898749 | BN122: =+BN121/BN$57 -> 0.10323398 | BO122: =+BO121/BO$57 -> 0.12213608 | BP122: =+BP121/BP$57 -> 0.1409703 | BQ122: =+BQ121/BQ$57 -> 0.12013772 | ... BU122: =+BU121/BU$57 -> 0.11560841
B123: dif | R123: =+R122-N122 -> #REF! | S123: =+S122-O122 -> #REF! | T123: =+T122-P122 -> #REF! | U123: =+U122-Q122 -> #REF! | V123: =+V122-R122 -> #REF! | W123: =+W122-S122 -> #REF! | X123: =+X122-T122 -> -0.074232056 | Y123: =+Y122-U122 -> -0.016650148 | ... AX123: =+AX122-AT122 -> -0.031193581 | BB123: 0.018610202 | BF123: =+BF122-BE122 -> #REF! | BG123: =+BG122-BF122 -> #REF! | BH123: =+BH122-BG122 -> #REF! | BJ123: =+BJ122-BH122 -> #REF! | BK123: =+BK122-BJ122 -> #REF! | BL123: =+BL122-BK122 -> -0.011298483 | BM123: =+BM122-BL122 -> -0.016089953 | BN123: =+BN122-BM122 -> 0.016335227 | BO123: =+BO122-BN122 -> 0.018902105 | BP123: =+BP122-BO122 -> 0.018834217 | BQ123: =+BQ122-BP122 -> -0.020832575 | BR123: =+BR122-BQ122 -> -0.0016592166 | ... BU123: =+BU122-BT122 -> -0.00045740976
B129: Depreciation | C129: =-C89 -> -57.167098 | D129: =-D89 -> -52.939777 | E129: =-E89 -> -62.514845 | F129: =-F89 -> -66.802244 | G129: =-G89 -> -63.073301 | H129: =-H89 -> -64.374656 | I129: =-I89 -> -97.522504 | J129: =-J89 -> -64.947815 | ... AX129: =-AX89 -> -217.99477 | BB129: -239.2 | BE129: =+SUM(C129:F129) -> -239.42396 | BF129: =+SUM(G129:J129) -> -289.91828 | BG129: =+SUM(K129:N129) -> -383.30552 | BH129: =+SUM(O129:R129) -> -587.03697 | BJ129: =+SUM(S129:V129) -> -1117.3 | BK129: =+SUM(W129:Z129) -> -2718.8 | BL129: =+SUM(AA129:AD129) -> -2791.6 | BM129: =+SUM(AE129:AH129) -> -2591.9 | BN129: =+SUM(AI129:AL129) -> -2094.8859 | BO129: =+SUM(AM129:AP129) -> -949 | BP129: =+SUM(AQ129:AT129) -> -909.3 | BQ129: =+SUM(AU129:AX129) -> -888.8478 | BR129: =-BR89 -> -787.82604 | BS129: =-BS89 -> -743.19029 | BT129: =-BT89 -> -722.6314 | BU129: =-BU89 -> -712.53625
BF130: =+BF129/BE129-1 -> 0.21089916 | BG130: =+BG129/BF129-1 -> 0.32211575 | BH130: =+BH129/BG129-1 -> 0.53151192 | BJ130: =+BJ129/BH129-1 -> 0.90328728 | BK130: =+BK129/BJ129-1 -> 1.4333662 | BL130: =+BL129/BK129-1 -> 0.026776519 | BM130: =+BM129/BL129-1 -> -0.071536037 | BN130: =+BN129/BM129-1 -> -0.19175666 | BO130: =+BO129/BN129-1 -> -0.54699204 | BP130: =+BP129/BO129-1 -> -0.041833509 | BQ130: =+BQ129/BP129-1 -> -0.022492249 | BR130: =+BR129/BQ129-1 -> -0.11365473 | ... BU130: =+BU129/BT129-1 -> -0.013969983
S131: =+S129/S$57 -> -0.090664288 | T131: =+T129/T$57 -> -0.080030343 | U131: =+U129/U$57 -> -0.081409408 | V131: =+V129/V$57 -> -0.03084572 | W131: =+W129/W$57 -> -0.083240223 | X131: =+X129/X$57 -> -0.1007428 | Y131: =+Y129/Y$57 -> -0.068247037 | Z131: =+Z129/Z$57 -> -0.056512715 | ... AX131: =+AX129/AX$57 -> -0.034302328 | BB131: -0.037693388 | BF131: =+BF129/BF$57 -> -0.036639748 | BG131: =+BG129/BG$57 -> -0.038903414 | BH131: =+BH129/BH$57 -> -0.043923026 | BJ131: =+BJ129/BJ$57 -> -0.057453122 | BK131: =+BK129/BK$57 -> -0.073636514 | BL131: =+BL129/BL$57 -> -0.069503991 | BM131: =+BM129/BM$57 -> -0.071305558 | BN131: =+BN129/BN$57 -> -0.071682779 | BO131: =+BO129/BO$57 -> -0.040498652 | BP131: =+BP129/BP$57 -> -0.040927296 | BQ131: =+BQ129/BQ$57 -> -0.040985411 | ... BU131: =+BU129/BU$57 -> -0.028151668
BF133: =+BF86/BE86-1 -> -0.13816326 | BG133: =+BG86/BF86-1 -> 0.25467508 | BH133: =+BH86/BG86-1 -> -0.069760427 | BJ133: =+BJ86/BH86-1 -> 2.3195693 | BK133: =+BK86/BJ86-1 -> -0.81175212 | BL133: =+BL86/BK86-1 -> 0.41592808 | BM133: =+BM86/BL86-1 -> -1.4099079 | BN133: =+BN86/BM86-1 -> 0.25093867 | BO133: =+BO86/BN86-1 -> -2.5722085 | BP133: =+BP86/BO86-1 -> 0.44926394 | BQ133: =+BQ86/BP86-1 -> 0.31378249 | BR133: =+BR86/BQ86-1 -> 0.10488484 | ... BU133: =+BU86/BT86-1 -> 0.048278382
B136: NATURA LATAM & CO
S137: PRO FORMA | BJ137: PRO FORMA
B138: Total Gross Revs | S138: 5463.3 | T138: 6410.1 | U138: 6353.1 | V138: 7117.5 | W138: 5662.9932 | X138: 5420.7 | Y138: 8275.9 | Z138: 8294.7 | AA138: 6857.2 | AB138: 7347.9 | AC138: 7409.2 | AD138: 8079.1 | AE138: 6286.7 | AF138: 7284.4 | AG138: 7700 | AH138: 7886.9 | AI138: 6445.3 | AJ138: 7274.0301 | AK138: 6930.214 | AL138: 6571.3 | AM138: 6371.9 | AN138: 7944.6426 | AO138: 7900.6803 | AP138: 9369.6 | AQ138: 6819.9 | AR138: 7545.9 | AS138: 6867 | AT138: 8262 | AU138: 6020.787 | AV138: 7623.5828 | AW138: 7377.6227 | AX138: 9319.9503 | BB138: 8402.5252 | BC138: -0.016724167 | BH138: 11647.3 | BI138: 12387.5 | BJ138: 25344 | BK138: 27654.293 | BL138: 28848.5 | BM138: 29158 | BN138: 27220.844 | BO138: 31586.823 | BP138: 29494.8 | BQ138: 30341.943 | BR138: 31698.982 | BS138: 32921.722 | BT138: 34175.414 | BU138: 35383.328
B139: yoy | W139: =+W138/S138-1 -> 0.036551754 | X139: =+X138/T138-1 -> -0.15435017 | Y139: =+Y138/U138-1 -> 0.3026554 | Z139: =+Z138/V138-1 -> 0.16539515 | AA139: =+AA138/W138-1 -> 0.21087908 | AB139: =+AB138/X138-1 -> 0.35552604 | AC139: =+AC138/Y138-1 -> -0.10472577 | AD139: =+AD138/Z138-1 -> -0.025992501 | ... AX139: =+AX138/AT138-1 -> 0.12805014 | BB139: -0.10321409 | BJ139: =+BJ138-BI138 -> 12956.5 | BK139: =+BK138/BJ138-1 -> 0.091157402 | BL139: =+BL138/BK138-1 -> 0.043183414 | BM139: =+BM138/BL138-1 -> 0.010728461 | BN139: =+BN138/BM138-1 -> -0.066436516 | BO139: =+BO138/BN138-1 -> 0.16039102 | BP139: =+BP138/BO138-1 -> -0.066230874 | BQ139: =+BQ138/BP138-1 -> 0.028721766 | BR139: =+BR138/BQ138-1 -> 0.044724877 | ... BU139: =+BU138/BT138-1 -> 0.035344534
B141: Impostos | S141: =+S144-S138 -> -1400 | T141: =+T144-T138 -> -1646.1 | U141: =+U144-U138 -> -1655.3 | V141: =+V144-V138 -> -1872.7 | W141: =+W144-W138 -> -1500.6932 | X141: =+X144-X138 -> -1445 | Y141: =+Y144-Y138 -> -2192.3 | Z141: =+Z144-Z138 -> -1974.1 | ... AX141: =+AX144-AX138 -> -2964.8489 | BB141: -2056.5846 | BH141: =+BH144-BH138 -> -3241.8537 | BI141: =+BI144-BI138 -> -3384.1 | BJ141: =+SUM(S141:V141) -> -6574.1 | BK141: =+SUM(W141:Z141) -> -7112.0932 | BL141: =+SUM(AA141:AD141) -> -7280 | BM141: =+SUM(AE141:AH141) -> -7130.8 | BN141: =+SUM(AI141:AL141) -> -5779.9753 | BO141: =+SUM(AM141:AP141) -> -7893.5513 | BP141: =+SUM(AQ141:AT141) -> -7277.3539 | BQ141: =+SUM(AU141:AX141) -> -8655.0113 | BR141: =+BR144-BR138 -> -9041.3787 | BS141: =+BS144-BS138 -> -9386.3588 | BT141: =+BT144-BT138 -> -9736.0712 | BU141: =+BU144-BU138 -> -10072.705
B142: % revs | S142: =+S141/S138 -> -0.25625538 | T142: =+T141/T138 -> -0.25679787 | U142: =+U141/U138 -> -0.26054997 | V142: =+V141/V138 -> -0.26311205 | W142: -0.265 | X142: =+X141/X138 -> -0.26657074 | Y142: =+Y141/Y138 -> -0.2649017 | Z142: =+Z141/Z138 -> -0.23799535 | AA142: =+AA141/AA138 -> -0.24372922 | AB142: =+AB141/AB138 -> -0.24690047 | AC142: =+AC141/AC138 -> -0.25072882 | AD142: =+AD141/AD138 -> -0.23972967 | AE142: =+AE141/AE138 -> -0.24419807 | ... AT142: =+AT141/AT138 -> -0.25042363 | AU142: =+AVERAGE(AQ142:AT142) -> -0.24655547 | AV142: =+AVERAGE(AR142:AU142) -> -0.24672518 | AW142: =+AVERAGE(AS142:AV142) -> -0.24683331 | AX142: =+AVERAGE(AT142:AW142) -> -0.2476344 | BB142: -0.24475792 | BH142: =+BH141/BH138 -> -0.27833521 | BI142: =+BI141/BI138 -> -0.27318668 | BJ142: =+BJ141/BJ138 -> -0.25939473 | BK142: =+BK141/BK138 -> -0.25717863 | BL142: =+BL141/BL138 -> -0.25235281 | BM142: =+BM141/BM138 -> -0.24455724 | BN142: =+BN141/BN138 -> -0.21233637 | BO142: =+BO141/BO138 -> -0.24990014 | ... BQ142: =+BQ141/BQ138 -> -0.28524908 | BR142: =+AVERAGE(BP142:BQ142) -> -0.26599127 | BS142: =+AVERAGE(BQ142:BR142) -> -0.27562018 | BT142: =+AVERAGE(BR142:BS142) -> -0.27080572 | BU142: =+AVERAGE(BS142:BT142) -> -0.27321295
B144: Total Net Revs | S144: =8827.3-T144 -> 4063.3 | T144: 4764 | U144: 4697.8 | V144: 5244.8 | W144: 4162.3 | X144: 3975.7 | Y144: 6083.6 | Z144: 6320.6 | AA144: 5185.9 | AB144: 5533.7 | AC144: 5551.5 | AD144: 6142.3 | AE144: 4751.5 | AF144: 5555 | AG144: 5777.5 | AH144: 5943.2 | AI144: 4863.7 | AJ144: 5462.9348 | AK144: 5232.034 | AL144: =4882.2+1000 -> 5882.2 | AM144: 4704.6 | AN144: 5922.4425 | AO144: 5975.6291 | AP144: 7090.6 | AQ144: 5143.0461 | AR144: 5687.4 | AS144: 5194 | AT144: 6193 | AU144: =+AU161+AU152+AU179+AU170 -> 4671.1848 | AV144: =+AV161+AV152+AV179+AV170 -> 5589.1976 | AW144: =+AW161+AW152+AW179+AW170 -> 5071.4476 | AX144: =+AX161+AX152+AX179+AX170 -> 6355.1014 | BB144: 6345.9406 | BC144: =+AT144/BB144-1 -> -0.024100547 | BE144: =+BE152 -> 7452.8 | BF144: =+BF152 -> 7318.4 | BG144: =+BG152 -> 7683.0983 | BH144: =+BH152 -> 8405.4463 | BI144: =+BI152 -> 9003.4 | BJ144: =+SUM(S144:V144) -> 18769.9 | BK144: =+SUM(W144:Z144) -> 20542.2 | BL144: =+SUM(AA144:AD144) -> 22413.4 | BM144: =+SUM(AE144:AH144) -> 22027.2 | BN144: =+SUM(AI144:AL144) -> 21440.869 | BO144: =+SUM(AM144:AP144) -> 23693.272 | BP144: =+SUM(AQ144:AT144) -> 22217.446 | BQ144: =+SUM(AU144:AX144) -> 21686.931 | BR144: =+BR161+BR152+BR179+BR170 -> 22657.604 | BS144: =+BS161+BS152+BS179+BS170 -> 23535.363 | BT144: =+BT161+BT152+BT179+BT170 -> 24439.342 | BU144: =+BU161+BU152+BU179+BU170 -> 25310.623
B145: yoy | W145: =+W144/S144-1 -> 0.024364433 | X145: =+X144/T144-1 -> -0.16547019 | Y145: =+Y144/U144-1 -> 0.29498914 | Z145: =+Z144/V144-1 -> 0.20511745 | AA145: =+AA144/W144-1 -> 0.24592173 | AB145: =+AB144/X144-1 -> 0.39188068 | AC145: =+AC144/Y144-1 -> -0.087464659 | AD145: =+AD144/Z144-1 -> -0.028209347 | ... AX145: =+AX144/AT144-1 -> 0.026174938 | BB145: -0.10502064 | BK145: =+BK144/BJ144-1 -> 0.094422453 | BL145: =+BL144/BK144-1 -> 0.091090536 | BM145: =+BM144/BL144-1 -> -0.017230764 | BN145: =+BN144/BM144-1 -> -0.026618508 | BO145: =+BO144/BN144-1 -> 0.10505184 | BP145: =+BP144/BO144-1 -> -0.062288799 | BQ145: =+BQ144/BP144-1 -> -0.023878295 | BR145: =+BR144/BQ144-1 -> 0.044758396 | ... BU145: =+BU144/BT144-1 -> 0.03565074
...

Sheet Sheet2
K3: =+K6/13000000 -> 0.26557862
G5: 9M24 | H5: 2024 | J5: 9M25 | K5: 2025 | M5: 2026 | N5: 2026 ajustando folha | P5: 2027
G6: =+G8+G20+G23 -> 2254320 | H6: =+H8+H20+H23 -> 3297302 | J6: =+J8+J20+J23 -> 2636562 | K6: =+K8+K20+K23 -> 3452522 | M6: =+M8+M20+M23 -> 4562934.3 | N6: =+M28*N27 -> 3422200.8 | O6: =+N6-M6 -> -1140733.6
J7: =+J6/G6-1 -> 0.16955978 | K7: =+K6/H6-1 -> 0.047074851
E8: Custos pessoal | G8: 230176 | H8: 321015 | J8: 303740 | K8: 427603 | M8: =+K8*1.15 -> 491743.45 | N8: =+M8*N$6/M$6 -> 368807.59 | P8: =+N8*1.15 -> 424128.73
E9: qoq | H9: =+H8/G8-1 -> 0.39465018 | K9: =+K8/J8-1 -> 0.40779285
E10: yoy | J10: =+J8/G8-1 -> 0.31959892 | K10: =+K8/H8-1 -> 0.33203433
H12: =+H18/(8609117+2536438) -> 0.26703803 | K12: =+K18/(8612735+3096489) -> 0.25833642 | N12: =+N18/0.27 -> 12679234
E14: SG&A total | H14: =10188000+2978000 -> 13166000 | K14: =9410000+3064000 -> 12474000 | M14: =+M15+M18 -> 13520272 | N14: =+N15+N18 -> 12872474 | P14: =+P15+P18 -> 13432937 | Q14: =+P14/13700000-1 -> -0.019493635
H15: =+H14-H18 -> 10189713 | K15: =+K14-K18 -> 9449081 | M15: =+N15 -> 9449081 | N15: =+K15*(1+N16) -> 9449081 | P15: =+N15*(1+P16) -> 9921535.1
K16: =+K15/H15-1 -> -0.072684285 | N16: 0 | P16: 0.05
H17: =+H18/H14 -> 0.22605856 | K17: =+K18/K14 -> 0.24249792 | N17: 0.23
E18: SG&A pessoal | G18: =+G20+G23 -> 2024144 | H18: =+H20+H23 -> 2976287 | J18: =+J20+J23 -> 2332822 | K18: =+K20+K23 -> 3024919 | M18: =+M20+M23 -> 4071190.9 | N18: =+N20+N23 -> 3423393.2 | P18: =+(N18-370000)*(1+P19) -> 3511402.2
J19: =+J18/G18-1 -> 0.15249804 | K19: =+K18/H18-1 -> 0.016339822 | M19: =+M18/K18-1 -> 0.34588427 | N19: =+N18/K18-1 -> 0.13173053 | P19: 0.15
E20: pessoal selling | G20: 1014913 | H20: 1764250 | J20: 1324237 | K20: 1778278 | L20: =+H20*1.3 -> 2293525 | M20: =+L20*1.15 -> 2637553.8 | N20: =+M20*N$6/M$6+370000 -> 2348165.3
E21: qoq | H21: =+H20/G20-1 -> 0.73832634 | K21: =+K20/J20-1 -> 0.34286989 | L21: =+L20/J20-1 -> 0.73195961
E22: yoy | J22: =+J20/G20-1 -> 0.30477883 | K22: =+K20/H20-1 -> 0.0079512541
E23: pessoal G&A | G23: 1009231 | H23: 1212037 | J23: 1008585 | K23: 1246641 | M23: =+K23*1.15 -> 1433637.1 | N23: =+M23*N$6/M$6 -> 1075227.9
E24: qoq | H24: =+H23/G23-1 -> 0.20095102 | K24: =+K23/J23-1 -> 0.23602969
E25: yoy | J25: =+J23/G23-1 -> -0.00064009132 | K25: =+K23/H23-1 -> 0.028550284
M27: =1400/0.25 -> 5600 | N27: =+M27-1400 -> 4200
M28: =+M6/M27 -> 814.80971

Sheet PROJ
B1: 0.39966709
B2: DRE | C2: 1T15 | D2: 2T15 | E2: 3T15 | F2: 4T15 | G2: 1T16 | H2: 2T16 | I2: 3T16 | J2: 4T16 | K2: 1T17 | L2: 2T17 | M2: 3T17 | N2: 4T17 | O2: 1T18 | P2: 2T18 | Q2: 3T18 | R2: 4T18 | S2: 1T19 | T2: 2T19 | U2: 3T19 | V2: 4T19 | W2: 1T20 | X2: 2T20 | Y2: 3T20 | Z2: 4T20 | AA2: 1T21 | AB2: 2T21 | AC2: 3T21 | AD2: 4T21 | AE2: 1T22 | AF2: 2T22 | AG2: 3T22 | AH2: 4T22 | AI2: 1T23 | AJ2: 2T23 | AK2: 3T23 | AL2: 4T23 | AM2: 1T24 | AN2: 2T24 | AO2: 3T24 | AP2: 4T24 | AQ2: 1T25 | AR2: 2T25 | AS2: 3T25 | AT2: 4T25 | AU2: 1T26 | AV2: 2T26 | AW2: 3T26 | AX2: 4T26 | AZ2: 4T25 | BA2: dif | BD2: 2015 | BE2: =+BD2+1 -> 2016 | BF2: =+BE2+1 -> 2017 | BG2: 2018 | BH2: 2019 | BI2: =+BH2+1 -> 2020 | BJ2: =+BI2+1 -> 2021 | BK2: =+BJ2+1 -> 2022 | BL2: =+BK2+1 -> 2023 | BM2: =+BL2+1 -> 2024 | BN2: =+BM2+1 -> 2025 | BO2: =+BN2+1 -> 2026 | BP2: =+BO2+1 -> 2027 | ... BS2: =+BR2+1 -> 2030
B3: Receita Bruta | C3: =+FAT!C8 -> 2205.8399 | D3: =+FAT!D8 -> 2637.31 | E3: =+FAT!E8 -> 2763.0574 | F3: =+FAT!F8 -> 3200.2328 | G3: =+FAT!G8 -> 2320.028 | H3: =+FAT!H8 -> 2815.4641 | I3: =+FAT!I8 -> 2656.2 | J3: =+FAT!J8 -> 3198.6641 | ... AX3: =+FAT!AX8 -> 9319.9503 | AZ3: 8402.5252 | BA3: =+AT3/AZ3-1 -> -0.016724167 | BD3: =+SUM(C3:F3) -> 10806.44 | BE3: =+SUM(G3:J3) -> 10990.356 | BF3: =+SUM(K3:N3) -> 13750.856 | BG3: =+SUM(O3:R3) -> 18514.468 | BH3: =+SUM(S3:V3) -> 19708.1 | BI3: =+SUM(W3:Z3) -> 47697 | BJ3: =+SUM(AA3:AD3) -> 51644.2 | BK3: =+SUM(AE3:AH3) -> 47108.6 | BL3: =+SUM(AI3:AL3) -> 38175.466 | BM3: =+SUM(AM3:AP3) -> 31586.823 | BN3: =+SUM(AQ3:AT3) -> 29494.8 | BO3: =+SUM(AU3:AX3) -> 30341.943 | BP3: =+FAT!BR8 -> 31698.982 | BQ3: =+FAT!BS8 -> 32921.722 | BR3: =+FAT!BT8 -> 34175.414 | BS3: =+FAT!BU8 -> 35383.328
B4: Impostos e Ajustes | C4: =+FAT!C54 -> -564.03993 | D4: =+FAT!D54 -> -708.40998 | E4: =+FAT!E54 -> -767.15737 | F4: =+FAT!F54 -> -867.83281 | G4: =+FAT!G54 -> -630.32713 | H4: =+FAT!H54 -> -789.80616 | I4: =+FAT!I54 -> -753.6 | J4: =+FAT!J54 -> -903.95181 | ... AX4: =+FAT!AX54 -> -2964.8489 | AZ4: -2056.5846 | BD4: =+SUM(C4:F4) -> -2907.4401 | BE4: =+SUM(G4:J4) -> -3077.6851 | BF4: =+SUM(K4:N4) -> -3122.3269 | BG4: =+SUM(O4:R4) -> -5149.3377 | BH4: =+SUM(S4:V4) -> -260.941 | BI4: =+SUM(W4:Z4) -> -10775.1 | BJ4: =+SUM(AA4:AD4) -> -11479.6 | BK4: =+SUM(AE4:AH4) -> -10759.4 | BL4: =+SUM(AI4:AL4) -> -8951.0703 | BM4: =+SUM(AM4:AP4) -> -7847.755 | BN4: =+SUM(AQ4:AT4) -> -7276.9539 | BO4: =+SUM(AU4:AX4) -> -8655.0113 | BP4: =+FAT!BR54 -> -9041.3787 | BQ4: =+FAT!BS54 -> -9386.3588 | BR4: =+FAT!BT54 -> -9736.0712 | BS4: =+FAT!BU54 -> -10072.705
B5: Receita Líquida | C5: =+FAT!C57 -> 1641.8 | D5: =+FAT!D57 -> 1928.9 | E5: =+FAT!E57 -> 1995.9 | F5: =+FAT!F57 -> 2332.4 | G5: =+FAT!G57 -> 1689.7009 | H5: =+FAT!H57 -> 2025.658 | I5: =+FAT!I57 -> 1902.6 | J5: =+FAT!J57 -> 2294.7123 | ... AX5: =+FAT!AX57 -> 6355.1014 | AZ5: 6345.9406 | BA5: =+AT5/AZ5-1 -> -0.024100547 | BD5: =+SUM(C5:F5) -> 7899 | BE5: =+SUM(G5:J5) -> 7912.6711 | BF5: =+SUM(K5:N5) -> 9852.7476 | BG5: =+SUM(O5:R5) -> 13365.13 | BH5: =+SUM(S5:V5) -> 19447.159 | BI5: =+SUM(W5:Z5) -> 36921.9 | BJ5: =+SUM(AA5:AD5) -> 40164.6 | BK5: =+SUM(AE5:AH5) -> 36349.2 | BL5: =+SUM(AI5:AL5) -> 29224.396 | BM5: =+SUM(AM5:AP5) -> 23432.879 | BN5: =+SUM(AQ5:AT5) -> 22217.446 | BO5: =+SUM(AU5:AX5) -> 21686.931 | BP5: =+FAT!BR57 -> 22657.604 | BQ5: =+FAT!BS57 -> 23535.363 | BR5: =+FAT!BT57 -> 24439.342 | BS5: =+FAT!BU57 -> 25310.623
BE6: =+BE5/BD5-1 -> 0.0017307428 | BF6: =+BF5/BE5-1 -> 0.24518604 | BG6: =+BG5/BF5-1 -> 0.35648765 | BH6: =+BH5/BG5-1 -> 0.4550669 | BI6: =+BI5/BH5-1 -> 0.89857552 | BJ6: =+BJ5/BI5-1 -> 0.087825924 | BK6: =+BK5/BJ5-1 -> -0.094994099 | BL6: =+BL5/BK5-1 -> -0.19600993 | ... BS6: =+BS5/BR5-1 -> 0.03565074
B7: CPV | C7: =+FAT!C59 -> -495.1671 | D7: =+FAT!D59 -> -589.63978 | E7: =+FAT!E59 -> -618.31485 | F7: =+FAT!F59 -> -712.90224 | G7: =+FAT!G59 -> -521.07206 | H7: =+FAT!H59 -> -638.23244 | I7: =+FAT!I59 -> -566.8 | J7: =+FAT!J59 -> -720.81404 | ... AX7: =+FAT!AX59 -> -2254.5063 | AZ7: -2174.6637 | BD7: =+SUM(C7:F7) -> -2416.024 | BE7: =+SUM(G7:J7) -> -2446.9186 | BF7: =+SUM(K7:N7) -> -2911.0774 | BG7: =+SUM(O7:R7) -> -3761.8972 | BH7: =+SUM(S7:V7) -> -6191.727 | BI7: =+SUM(W7:Z7) -> -13229.4 | BJ7: =+SUM(AA7:AD7) -> -14011.4 | BK7: =+SUM(AE7:AH7) -> -13155.3 | BL7: =+SUM(AI7:AL7) -> -10238.485 | BM7: =+SUM(AM7:AP7) -> -8108.5109 | BN7: =+SUM(AQ7:AT7) -> -7483.9594 | BO7: =+SUM(AU7:AX7) -> -7314.5875 | BP7: =+FAT!BR59 -> -7641.9767 | BQ7: =+FAT!BS59 -> -7938.0283 | BR7: =+FAT!BT59 -> -8242.9231 | BS7: =+FAT!BU59 -> -8536.7894
B8: Lucro Bruto | C8: =+FAT!C61 -> 1146.6329 | D8: =+FAT!D61 -> 1339.2602 | E8: =+FAT!E61 -> 1377.5852 | F8: =+FAT!F61 -> 1619.4978 | G8: =+FAT!G61 -> 1168.6288 | H8: =+FAT!H61 -> 1387.4255 | I8: =+FAT!I61 -> 1335.8 | J8: =+FAT!J61 -> 1573.8983 | ... AX8: =+FAT!AX61 -> 4100.5951 | AZ8: 4171.277 | BA8: =+AT8/AZ8-1 -> -0.042019974 | BD8: =+SUM(C8:F8) -> 5482.976 | BE8: =+SUM(G8:J8) -> 5465.7526 | BF8: =+SUM(K8:N8) -> 6941.6308 | BG8: =+SUM(O8:R8) -> 9603.2333 | BH8: =+SUM(S8:V8) -> 13255.432 | BI8: =+SUM(W8:Z8) -> 23692.5 | BJ8: =+SUM(AA8:AD8) -> 26153.2 | BK8: =+SUM(AE8:AH8) -> 23193.9 | BL8: =+SUM(AI8:AL8) -> 18985.911 | BM8: =+SUM(AM8:AP8) -> 15324.368 | BN8: =+SUM(AQ8:AT8) -> 14733.487 | BO8: =+SUM(AU8:AX8) -> 14372.344 | BP8: =+FAT!BR61 -> 15015.627 | BQ8: =+FAT!BS61 -> 15597.335 | BR8: =+FAT!BT61 -> 16196.419 | BS8: =+FAT!BU61 -> 16773.834
B9: mrgn | T9: =+T8/T$5 -> 0.71661649 | U9: =+U8/U$5 -> 0.7216017 | V9: =+V8/V$5 -> 0.64256046 | W9: =+W8/W$5 -> 0.61709231 | X9: =+X8/X$5 -> 0.66003063 | Y9: =+Y8/Y$5 -> 0.64534767 | Z9: =+Z8/Z$5 -> 0.64325307 | AA9: =+AA8/AA$5 -> 0.64840825 | ... AX9: =+AX8/AX$5 -> 0.64524463 | AZ9: 0.65731421 | BA9: =+AT9-AZ9 -> -0.012069578 | BE9: =+BE8/BE$5 -> 0.69075948 | BF9: =+BF8/BF$5 -> 0.70453756 | BG9: =+BG8/BG$5 -> 0.71852896 | BH9: =+BH8/BH$5 -> 0.68161277 | BI9: =+BI8/BI$5 -> 0.64169233 | BJ9: =+BJ8/BJ$5 -> 0.65115052 | BK9: =+BK8/BK$5 -> 0.63808557 | BL9: =+BL8/BL$5 -> 0.64965965 | ... BS9: =+BS8/BS$5 -> 0.66271911
B11: SG&A | C11: =+C13+C15+C19 -> -917.9 | D11: =+D13+D15+D19 -> -1035 | E11: =+E13+E15+E19 -> -1040.5 | F11: =+F13+F15+F19 -> -1233.1 | G11: =+G13+G15+G19 -> -1014.7051 | H11: =+H13+H15+H19 -> -1107.0744 | I11: =+I13+I15+I19 -> -1084.3755 | J11: =+J13+J15+J19 -> -1176.7204 | ... AX11: =+AX13+AX15+AX19 -> -3513.2291 | AZ11: -3834.2686 | BA11: =+AT11/AZ11-1 -> -0.010763092 | BD11: =+SUM(C11:F11) -> -4226.5 | BE11: =+SUM(G11:J11) -> -4382.8754 | BF11: =+SUM(K11:N11) -> -5582.9717 | BG11: =+SUM(O11:R11) -> -8339.3549 | BH11: =+SUM(S11:V11) -> -9059.9 | BI11: =+BI13+BI15+BI19 -> -22902.7 | BJ11: =+BJ13+BJ15+BJ19 -> -25034.9 | BK11: =+BK13+BK15+BK19 -> -23652.3 | BL11: =+BL13+BL15+BL19 -> -19559.341 | BM11: =+BM13+BM15+BM19 -> -14422.816 | BN11: =+BN13+BN15+BN19 -> -13426.9 | BO11: =+BO13+BO15+BO19 -> -12655.773 | BP11: =+BP13+BP15+BP19 -> -13119.014 | ... BS11: =+BS13+BS15+BS19 -> -14610.249
B12: % sales | T12: =+T11/T$5 -> -0.63283906 | U12: =+U11/U$5 -> -0.64517243 | V12: =+V11/V$5 -> -0.284168 | W12: =+W11/W$5 -> -0.68101889 | X12: =+X11/X$5 -> -0.66747291 | Y12: =+Y11/Y$5 -> -0.57375114 | Z12: =+Z11/Z$5 -> -0.59520892 | AA12: =+AA11/AA$5 -> -0.63436277 | ... AX12: =+AX11/AX$5 -> -0.55282031 | AZ12: -0.60420808 | BA12: =+AT12-AZ12 -> -0.008257611 | BE12: =+BE11/BE$5 -> -0.55390592 | BF12: =+BF11/BF$5 -> -0.5666411 | BG12: =+BG11/BG$5 -> -0.6239636 | BH12: =+BH11/BH$5 -> -0.46587268 | BI12: =+BI11/BI$5 -> -0.62030123 | BJ12: =+BJ11/BJ$5 -> -0.62330759 | BK12: =+BK11/BK$5 -> -0.65069658 | BL12: =+BL11/BL$5 -> -0.66928128 | ... BS12: =+BS11/BS$5 -> -0.57723783
B13: Desp Vendas | C13: =+FAT!C70 -> -648 | D13: =+FAT!D70 -> -745.8 | E13: =+FAT!E70 -> -762.9 | F13: =+FAT!F70 -> -842.1 | G13: =+FAT!G70 -> -694.86438 | H13: =+FAT!H70 -> -780.86445 | I13: =+FAT!I70 -> -770.98339 | J13: =+FAT!J70 -> -863.45687 | ... AX13: =+FAT!AX70 -> -2764.4691 | AZ13: -2823.9436 | BA13: =+AT13/AZ13-1 -> -0.1101097 | BD13: =+SUM(C13:F13) -> -2998.8 | BE13: =+SUM(G13:J13) -> -3110.1691 | BF13: =+SUM(K13:N13) -> -4065.3492 | BG13: =+SUM(O13:R13) -> -6052.8411 | BH13: =+SUM(S13:V13) -> -6605.1 | BI13: =+SUM(W13:Z13) -> -16426.3 | BJ13: =+SUM(AA13:AD13) -> -17833.8 | BK13: =+SUM(AE13:AH13) -> -16160.6 | BL13: =+SUM(AI13:AL13) -> -13235.732 | BM13: =+SUM(AM13:AP13) -> -10213.499 | BN13: =+SUM(AQ13:AT13) -> -9409.8 | BO13: =+SUM(AU13:AX13) -> -9433.8152 | BP13: =+FAT!BR70 -> -9742.7696 | BQ13: =+FAT!BS70 -> -10120.206 | BR13: =+FAT!BT70 -> -10508.917 | BS13: =+FAT!BU70 -> -10883.568
BE14: =+BE13/BE$5 -> -0.39306184 | BF14: =+BF13/BF$5 -> -0.41261071 | BG14: =+BG13/BG$5 -> -0.45288305 | BH14: =+BH13/BH$5 -> -0.33964344 | BI14: =+BI13/BI$5 -> -0.44489314 | BJ14: =+BJ13/BJ$5 -> -0.44401787 | BK14: =+BK13/BK$5 -> -0.444593 | BL14: =+BL13/BL$5 -> -0.45290011 | ... BO14: =+BO13/BO$5 -> -0.435
B15: Desp Administrativas | C15: =+FAT!C74 -> -278.4 | D15: =+FAT!D74 -> -299.1 | E15: =+FAT!E74 -> -314.2 | F15: =+FAT!F74 -> -401.8 | G15: =+FAT!G74 -> -327.58135 | H15: =+FAT!H74 -> -321.79427 | I15: =+FAT!I74 -> -320.89212 | J15: =+FAT!J74 -> -356.82517 | ... AX15: =+FAT!AX74 -> -748.76 | AZ15: -820.325 | BA15: =+AT15/AZ15-1 -> -0.066223753 | BD15: =+SUM(C15:F15) -> -1293.5 | BE15: =+SUM(G15:J15) -> -1327.0929 | BF15: =+SUM(K15:N15) -> -1657.829 | BG15: =+SUM(O15:R15) -> -2144.8776 | BH15: =+SUM(S15:V15) -> -2251.6 | BI15: =+SUM(W15:Z15) -> -5582.5 | BJ15: =+SUM(AA15:AD15) -> -6399.5 | BK15: =+SUM(AE15:AH15) -> -6160.9 | BL15: =+SUM(AI15:AL15) -> -4528.033 | BM15: =+SUM(AM15:AP15) -> -2974.0579 | BN15: =+SUM(AQ15:AT15) -> -3085.3 | BO15: =+SUM(AU15:AX15) -> -3085.728 | BP15: =+FAT!BR74 -> -3240.0144 | BQ15: =+FAT!BS74 -> -3337.2148 | BR15: =+FAT!BT74 -> -3437.3313 | BS15: =+FAT!BU74 -> -3540.4512
BE16: =+BE15/BE$5 -> -0.16771744 | BF16: =+BF15/BF$5 -> -0.16826058 | BG16: =+BG15/BG$5 -> -0.1604831 | BH16: =+BH15/BH$5 -> -0.11578041 | BI16: =+BI15/BI$5 -> -0.15119753 | BJ16: =+BJ15/BJ$5 -> -0.15933185 | BK16: =+BK15/BK$5 -> -0.16949204 | BL16: =+BL15/BL$5 -> -0.15494018 | ... BO16: =+BO15/BO$5 -> -0.14228514
B17: Depreciação | C17: =FAT!C129 -> -57.167098 | D17: =FAT!D129 -> -52.939777 | E17: =FAT!E129 -> -62.514845 | F17: =FAT!F129 -> -66.802244 | G17: =FAT!G129 -> -63.073301 | H17: =FAT!H129 -> -64.374656 | I17: =FAT!I129 -> -97.522504 | J17: =FAT!J129 -> -64.947815 | ... AX17: =FAT!AX129 -> -217.99477 | AZ17: -239.2 | BD17: =+SUM(C17:F17) -> -239.42396 | BE17: =+SUM(G17:J17) -> -289.91828 | BF17: =+SUM(K17:N17) -> -383.30552 | BG17: =+SUM(O17:R17) -> -587.03697 | BH17: =+SUM(S17:V17) -> -1117.3 | BI17: =+SUM(W17:Z17) -> -2718.8 | BJ17: =+SUM(AA17:AD17) -> -2791.6 | BK17: =+SUM(AE17:AH17) -> -2591.9 | BL17: =+SUM(AI17:AL17) -> -2094.8859 | BM17: =+SUM(AM17:AP17) -> -949 | BN17: =+SUM(AQ17:AT17) -> -909.3 | BO17: =+SUM(AU17:AX17) -> -888.8478 | BP17: =FAT!BR129 -> -787.82604 | BQ17: =FAT!BS129 -> -743.19029 | BR17: =FAT!BT129 -> -722.6314 | BS17: =FAT!BU129 -> -712.53625
BE18: =+BE17/BE$5 -> -0.036639748 | BF18: =+BF17/BF$5 -> -0.038903414 | BG18: =+BG17/BG$5 -> -0.043923026 | BH18: =+BH17/BH$5 -> -0.057453122 | BI18: =+BI17/BI$5 -> -0.073636514 | BJ18: =+BJ17/BJ$5 -> -0.069503991 | BK18: =+BK17/BK$5 -> -0.071305558 | BL18: =+BL17/BL$5 -> -0.071682779 | ... BO18: =+BO17/BO$5 -> -0.040985411
B19: Outras Receitas (Despesas) | C19: =+FAT!C79+FAT!C80+FAT!C81+FAT!C83 -> 8.5 | D19: =+FAT!D79+FAT!D80+FAT!D81+FAT!D83 -> 9.9 | E19: =+FAT!E79+FAT!E80+FAT!E81+FAT!E83 -> 36.6 | F19: =+FAT!F79+FAT!F80+FAT!F81+FAT!F83 -> 10.8 | G19: =+FAT!G79+FAT!G80+FAT!G81+FAT!G83 -> 7.7405845 | H19: =+FAT!H79+FAT!H80+FAT!H81+FAT!H83 -> -4.4156493 | I19: =+FAT!I79+FAT!I80+FAT!I81+FAT!I83 -> 7.5 | J19: =+FAT!J79+FAT!J80+FAT!J81+FAT!J83 -> 43.561688 | ... AX19: =+FAT!AX79+FAT!AX80+FAT!AX81+FAT!AX83 -> 0 | AZ19: -190 | BA19: =+AT19/AZ19-1 -> 1.7052632 | BD19: =+SUM(C19:F19) -> 65.8 | BE19: =+SUM(G19:J19) -> 54.386623 | BF19: =+SUM(K19:N19) -> 140.20647 | BG19: =+SUM(O19:R19) -> -141.63626 | BH19: =+SUM(S19:V19) -> -203.2 | BI19: =+SUM(W19:Z19) -> -893.9 | BJ19: =+SUM(AA19:AD19) -> -801.6 | BK19: =+SUM(AE19:AH19) -> -1330.8 | BL19: =+SUM(AI19:AL19) -> -1795.576 | BM19: =+SUM(AM19:AP19) -> -1235.2587 | BN19: =+SUM(AQ19:AT19) -> -931.8 | BO19: =+SUM(AU19:AX19) -> -136.23 | BP19: =+FAT!BR79+FAT!BR80+FAT!BR81+FAT!BR83 -> -136.23 | BQ19: =+FAT!BS79+FAT!BS80+FAT!BS81+FAT!BS83 -> -186.23 | BR19: =+FAT!BT79+FAT!BT80+FAT!BT81+FAT!BT83 -> -186.23 | BS19: =+FAT!BU79+FAT!BU80+FAT!BU81+FAT!BU83 -> -186.23
BE20: =+BE19/BE$5 -> 0.0068733583
B21: EBIT | C21: =+C8+C11 -> 228.7329 | D21: =+D8+D11 -> 304.26022 | E21: =+E8+E11 -> 337.08515 | F21: =+F8+F11 -> 386.39776 | G21: =+G8+G11 -> 153.92366 | H21: =+H8+H11 -> 280.35116 | I21: =+I8+I11 -> 251.4245 | J21: =+J8+J11 -> 397.1779 | ... AX21: =+AX8+AX11 -> 587.36595 | AZ21: 337.00837 | BA21: =+AT21/AZ21-1 -> -0.39764107 | BD21: =+BD8+BD11 -> 1256.476 | BE21: =+BE8+BE11 -> 1082.8772 | BF21: =+BF8+BF11 -> 1358.6591 | BG21: =+BG8+BG11 -> 1263.8784 | BH21: =+BH8+BH11 -> 4195.532 | BI21: =+BI8+BI11 -> 789.8 | BJ21: =+BJ8+BJ11 -> 1118.3 | BK21: =+BK8+BK11 -> -458.4 | ... BS21: =+BS8+BS11 -> 2163.5845
B23: EBITDA | S23: =+FAT!S115 -> 449.078 | T23: =+FAT!T115 -> 557.554 | U23: =+FAT!U115 -> 548.3 | V23: =+FAT!V115 -> 3757.9 | W23: =+FAT!W115 -> 145.2 | X23: =+FAT!X115 -> 651.9 | Y23: =+FAT!Y115 -> 1457.1 | Z23: =+FAT!Z115 -> 1254.4 | ... AX23: =+FAT!AX115 -> 805.36072 | AZ23: 576.20837 | BA23: =+AT23/AZ23-1 -> -0.22944541 | BF23: =+FAT!BG115 -> 1741.9646 | BG23: =+FAT!BH115 -> 1850.9154 | BH23: =+FAT!BJ115 -> 5312.832 | BI23: =+FAT!BK115 -> 3508.6 | BJ23: =+FAT!BL115 -> 3909.9 | BK23: =+FAT!BM115 -> 2133.5 | BL23: =+FAT!BN115 -> 1521.4556 | BM23: =+FAT!BO115 -> 1850.5519 | BN23: =+FAT!BP115 -> 2215.8867 | BO23: =+FAT!BQ115 -> 2605.4186 | ... BS23: =+FAT!BU115 -> 2876.1208
B24: mrgn | T24: =+T23/T$5 -> 0.16380778 | U24: =+U23/U$5 -> 0.15783868 | V24: =+V23/V$5 -> 0.38923818 | W24: =+W23/W$5 -> 0.019313647 | X24: =+X23/X$5 -> 0.093300511 | Y24: =+Y23/Y$5 -> 0.13984356 | Z24: =+Z23/Z$5 -> 0.10455686 | AA24: =+AA23/AA$5 -> 0.08769963 | ... AX24: =+AX23/AX$5 -> 0.12672665 | AZ24: 0.09079952 | BA24: =+AT24-AZ24 -> -0.019105672 | BE24: =+BE23/BE$5 -> 0 | BF24: =+BF23/BF$5 -> 0.17679988 | BG24: =+BG23/BG$5 -> 0.13848839 | BH24: =+BH23/BH$5 -> 0.27319322 | BI24: =+BI23/BI$5 -> 0.095027612 | BJ24: =+BJ23/BJ$5 -> 0.097346917 | BK24: =+BK23/BK$5 -> 0.058694552 | BL24: =+BL23/BL$5 -> 0.052061149 | ... BS24: =+BS23/BS$5 -> 0.11363295
B26: Resultado Financeiro | C26: =+C27+C28 -> -54.7 | D26: =+D27+D28 -> -129.1 | E26: =+E27+E28 -> -131.5 | F26: =+F27+F28 -> -66.2 | G26: =+G27+G28 -> -217.8 | H26: =+H27+H28 -> -178.9 | I26: =+I27+I28 -> -128.3 | J26: =+J27+J28 -> -130.9 | ... AE26: =+AE27+AE28 -> -386.6 | AF26: -426.8 | AG26: -563.9 | AH26: -523.6 | AI26: -476.3 | AJ26: -402.1 | AK26: -1064.904 | AL26: -629.9 | AM26: -84.359 | AN26: -390.778 | AO26: -170.387 | AP26: -65.9 | AQ26: -351.6 | AR26: 23.8 | AS26: -430.6 | AT26: -128 | AU26: =+SUM(AU27:AU30) -> -187.19807 | AV26: =+SUM(AV27:AV30) -> -170.50333 | AW26: =+SUM(AW27:AW30) -> -166.50512 | AX26: =+SUM(AX27:AX30) -> -160.76395 | AZ26: -205.81195 | BA26: =+AT26/AZ26-1 -> -0.37807304 | BD26: =+SUM(C26:F26) -> -381.5 | BE26: =+SUM(G26:J26) -> -655.9 | BF26: =+SUM(K26:N26) -> -387.4 | BG26: =+SUM(O26:R26) -> -583.3 | BH26: =+SUM(S26:V26) -> -840.0928 | BI26: =+SUM(W26:Z26) -> -1035.4 | BJ26: =+SUM(AA26:AD26) -> #REF! | BK26: =+SUM(AE26:AH26) -> -1900.9 | BL26: =+SUM(AI26:AL26) -> -2573.204 | BM26: =+SUM(AM26:AP26) -> -711.424 | BN26: =+SUM(AQ26:AT26) -> -886.4 | BO26: =+SUM(AU26:AX26) -> -684.97046 | BP26: =+SUM(BP27:BP30) -> -627.62757 | BQ26: =+SUM(BQ27:BQ30) -> -537.65526 | BR26: =+SUM(BR27:BR30) -> -424.17012 | BS26: =+SUM(BS27:BS30) -> -343.41379
B27: Receitas Financeiras | C27: 565.1 | D27: 305.4 | E27: 776.8 | F27: 215.9 | G27: 404.5 | H27: 381.1 | I27: 106.6 | J27: =1073.3-I27-H27-G27 -> 181.1 | K27: 273.3 | L27: 126.8 | M27: 76 | N27: =604.4-M27-L27-K27 -> 128.3 | O27: =837.461-P27 -> 263.069 | P27: 574.392 | Q27: 484.2 | R27: =2056.4-Q27-P27-O27 -> 734.739 | S27: =792.159-T27 -> 378.102 | T27: 414.057 | U27: 481.5 | V27: 682.121 | W27: =2225.7-X27 -> 1560.2 | X27: 665.5 | Y27: 1328.8 | Z27: 1183.9 | AA27: 1038.9 | AB27: 1225.5 | AC27: =+AC280 -> #REF! | AD27: 867.6 | AE27: 1354.3 | AF27: =+AF280 -> #REF! | AG27: =+AG280 -> #REF! | AH27: =+AH280 -> #REF! | AI27: 1005.7 | AJ27: =+AJ280 -> #REF! | AK27: =+AK280 -> #REF! | AL27: =+AL280 -> #REF! | AM27: 129.38 | AN27: 88.578 | AO27: 54.929 | AP27: 68.6 | AQ27: 41.4 | AR27: 22.5 | AS27: 37.328 | AT27: 32.294 | AU27: =+AU280 -> 64.766194 | AV27: =+AV280 -> 64.675901 | AW27: =+AW280 -> 59.970724 | AX27: =+AX280 -> 57.12781 | AZ27: 46.013331 | BD27: =+SUM(C27:F27) -> 1863.2 | BE27: =+SUM(G27:J27) -> 1073.3 | BF27: =+SUM(K27:N27) -> 604.4 | BG27: =+SUM(O27:R27) -> 2056.4 | BH27: =+SUM(S27:V27) -> 1955.78 | BI27: =+SUM(W27:Z27) -> 4738.4 | BJ27: =+SUM(AA27:AD27) -> #REF! | BK27: =+SUM(AE27:AH27) -> #REF! | BL27: =+SUM(AI27:AL27) -> #REF! | BM27: =+SUM(AM27:AP27) -> 341.487 | BN27: =+SUM(AQ27:AT27) -> 133.522 | BO27: =+SUM(AU27:AX27) -> 246.54063 | BP27: =+BP280 -> 218.4955 | BQ27: =+BQ280 -> 188.86808 | BR27: =+BR280 -> 182.00866 | BS27: =+BS280 -> 212.26237
B28: Despesas Financeiras | C28: -619.8 | D28: -434.5 | E28: -908.3 | F28: -282.1 | G28: -622.3 | H28: -560 | I28: -234.9 | J28: =-1729.2-I28-H28-G28 -> -312 | K28: -285.9 | L28: -112.6 | M28: -351.5 | N28: =-991.8-M28-L28-K28 -> -241.8 | O28: =-1138.694-P28 -> -419.316 | P28: -719.378 | Q28: -648.2 | R28: =-2639.7-Q28-P28-O28 -> -852.806 | S28: =-1161.816-T28 -> -543.357 | T28: -618.459 | U28: -677 | V28: -957.0568 | W28: =-2721.9-X28 -> -1787.8 | X28: -934.1 | Y28: -1619.1 | Z28: -1432.8 | AA28: -1266.9 | AB28: -1431 | AC28: =+AC300 -> #REF! | AD28: -1168.2 | AE28: -1740.9 | AF28: =+AF300 -> #REF! | AG28: =+AG300 -> #REF! | AH28: =+AH300 -> #REF! | AI28: -1482.1 | AJ28: =+AJ300 -> #REF! | AK28: =+AK300 -> #REF! | AL28: =+AL300 -> #REF! | AM28: -97.209 | AN28: -248.101 | AO28: -107.5 | AP28: -128.4 | AQ28: -130 | AR28: -137.2 | AS28: -144.806 | AT28: -156.279 | AU28: =+AU300 -> -223.33381 | AV28: =+AV300 -> -206.968 | AW28: =+AW300 -> -196.39163 | AX28: =+AX300 -> -189.59833 | AZ28: -227.20572 | BD28: =+SUM(C28:F28) -> -2244.7 | BE28: =+SUM(G28:J28) -> -1729.2 | BF28: =+SUM(K28:N28) -> -991.8 | BG28: =+SUM(O28:R28) -> -2639.7 | BH28: =+SUM(S28:V28) -> -2795.8728 | BI28: =+SUM(W28:Z28) -> -5773.8 | BJ28: =+SUM(AA28:AD28) -> #REF! | BK28: =+SUM(AE28:AH28) -> #REF! | BL28: =+SUM(AI28:AL28) -> #REF! | BM28: =+SUM(AM28:AP28) -> -581.21 | BN28: =+SUM(AQ28:AT28) -> -568.285 | BO28: =+SUM(AU28:AX28) -> -816.29177 | BP28: =+BP300 -> -735.00147 | BQ28: =+BQ300 -> -626.22638 | BR28: =+BR300 -> -496.0521 | BS28: =+BS300 -> -446.44689
B29: Leases | AM29: -33.3 | AN29: -21.241 | AO29: -21.7 | AP29: -19 | AQ29: -32.5 | AR29: -19.8 | AS29: -34.544 | AT29: -28.223407 | AU29: =+AU362 -> -28.630455 | AV29: =+AV362 -> -28.211229 | AW29: =+AW362 -> -30.084208 | AX29: =+AX362 -> -28.29343 | AZ29: -24.619565 | BM29: =+SUM(AM29:AP29) -> -95.241 | BN29: =+SUM(AQ29:AT29) -> -115.06741 | BO29: =+SUM(AU29:AX29) -> -115.21932 | BP29: =+BP362 -> -111.1216 | BQ29: =+BQ362 -> -100.29696 | BR29: =+BR362 -> -110.12668 | BS29: =+BS362 -> -109.22927
B30: Others | AM30: =+AM26-AM27-AM28-AM29 -> -83.23 | AN30: =+AN26-AN27-AN28-AN29 -> -210.014 | AO30: =+AO26-AO27-AO28-AO29 -> -96.116 | AP30: =+AP26-AP27-AP28-AP29 -> 12.9 | AQ30: =+AQ26-AQ27-AQ28-AQ29 -> -230.5 | AR30: =+AR26-AR27-AR28-AR29 -> 158.3 | AS30: =+AS26-AS27-AS28-AS29 -> -288.578 | AT30: =+AT26-AT27-AT28-AT29 -> 24.208407 | BM30: =+SUM(AM30:AP30) -> -376.46 | BN30: =+SUM(AQ30:AT30) -> -336.56959 | BO30: =+SUM(AU30:AX30) -> 0
B32: EBT | C32: =+C21+C26 -> 174.0329 | D32: =+D21+D26 -> 175.16022 | E32: =+E21+E26 -> 205.58515 | F32: =+F21+F26 -> 320.19776 | G32: =+G21+G26 -> -63.876342 | H32: =+H21+H26 -> 101.45116 | I32: =+I21+I26 -> 123.1245 | J32: =+J21+J26 -> 266.2779 | ... AX32: =+AX21+AX26 -> 426.602 | AZ32: 131.19642 | BA32: =+AT32/AZ32-1 -> -0.42833804 | BD32: =+SUM(C32:F32) -> 874.97604 | BE32: =+SUM(G32:J32) -> 426.97721 | BF32: =+SUM(K32:N32) -> 971.25905 | BG32: =+SUM(O32:R32) -> 680.57842 | BH32: =+SUM(S32:V32) -> 3355.4392 | BI32: =+SUM(W32:Z32) -> -245.6 | BJ32: =+SUM(AA32:AD32) -> #REF! | BK32: =+SUM(AE32:AH32) -> -2359.3 | BL32: =+SUM(AI32:AL32) -> -3146.6343 | BM32: =+SUM(AM32:AP32) -> 190.12795 | BN32: =+SUM(AQ32:AT32) -> 420.18673 | BO32: =+SUM(AU32:AX32) -> 1031.6003 | BP32: =+BP21+BP26 -> 1268.9854 | BQ32: =+BQ21+BQ26 -> 1416.0288 | BR32: =+BR21+BR26 -> 1639.7707 | BS32: =+BS21+BS26 -> 1820.1707
B34: IR & CS | C34: =+FAT!#REF! -> #REF! | D34: =+FAT!#REF! -> #REF! | E34: =+FAT!#REF! -> #REF! | F34: =+FAT!#REF! -> #REF! | G34: =+FAT!#REF! -> #REF! | H34: =+FAT!#REF! -> #REF! | I34: =+FAT!#REF! -> #REF! | J34: =+FAT!#REF! -> #REF! | ... T34: =+FAT!#REF! -> #REF! | U34: -6.2 | V34: =-112.2-206.6 -> -318.8 | W34: -94.8 | X34: -44.9 | Y34: -53.1 | Z34: -82 | AA34: -90.1 | AB34: 527.4 | AC34: 312 | AD34: 298.7 | AE34: -82.5 | AF34: -135.1 | AG34: 112.8 | AH34: -14.8 | AI34: -82.8 | AJ34: -98.6 | AK34: 961.952 | AL34: -580.3 | AM34: -216.2 | AN34: -950.2 | AO34: 40.9 | AP34: 168 | AQ34: -129.6 | AR34: -25.4 | AS34: 86.5 | AT34: 111 | AU34: =+AU35*AU32 -> -2.1152436 | AV34: =+AV35*AV32 -> -1.6490848 | AW34: =+AW35*AW32 -> -1.4397956 | AX34: =+AX35*AX32 -> -3.6695801 | AZ34: -44.606781 | BA34: =+AT34/AZ34-1 -> -3.4884109 | BD34: =+SUM(C34:F34) -> #REF! | BE34: =+SUM(G34:J34) -> #REF! | BF34: =+SUM(K34:N34) -> #REF! | BG34: =+SUM(O34:R34) -> #REF! | BH34: =+SUM(S34:V34) -> #REF! | BI34: =+SUM(W34:Z34) -> -274.8 | BJ34: =+SUM(AA34:AD34) -> 1048 | BK34: =+SUM(AE34:AH34) -> -119.6 | BL34: =+SUM(AI34:AL34) -> 200.252 | BM34: =+SUM(AM34:AP34) -> -957.5 | BN34: =+SUM(AQ34:AT34) -> 42.5 | BO34: =+BO256 -> -8.8737041 | BP34: =+BP256 -> 28.389143 | BQ34: =+BQ256 -> -2.7376295 | BR34: =+BR256 -> -55.125261 | BS34: =+BS256 -> -235.92839
B35: % Taxa | C35: =+C34/C32 -> #REF! | D35: =+D34/D32 -> #REF! | E35: =+E34/E32 -> #REF! | F35: =+F34/F32 -> #REF! | G35: =+G34/G32 -> #REF! | H35: =+H34/H32 -> #REF! | I35: =+I34/I32 -> #REF! | J35: =+J34/J32 -> #REF! | ... AT35: =+AT34/AT32 -> 1.48 | AU35: =+$BO$35 -> -0.008601882 | AV35: =+$BO$35 -> -0.008601882 | AW35: =+$BO$35 -> -0.008601882 | AX35: =+$BO$35 -> -0.008601882 | AZ35: -0.34 | BD35: =+BD34/#REF! -> #REF! | BE35: =+BE34/#REF! -> #REF! | BF35: =+BF34/#REF! -> #REF! | BG35: =+BG34/#REF! -> #REF! | BH35: =+BH34/BH32 -> #REF! | BI35: =+BI34/BI32 -> 1.1188925 | BJ35: =+BJ34/BJ32 -> #REF! | BK35: =+BK34/BK32 -> 0.050693002 | BL35: =+BL34/BL32 -> -0.063640062 | BM35: =+BM34/BM32 -> -5.0360824 | BN35: =+BN34/BN32 -> 0.10114551 | BO35: =+BO34/BO32 -> -0.008601882 | ... BS35: =+BS34/BS32 -> -0.12961882
B37: Lucro Líquido Op. Continuadas | C37: =+C32+C34 -> #REF! | D37: =+D32+D34 -> #REF! | E37: =+E32+E34 -> #REF! | F37: =+F32+F34 -> #REF! | G37: =+G32+G34 -> #REF! | H37: =+H32+H34 -> #REF! | I37: =+I32+I34 -> #REF! | J37: =+J32+J34 -> #REF! | ... AX37: =+AX32+AX34 -> 422.93242 | AZ37: 86.589635 | BA37: =+AT37/AZ37-1 -> 1.1480631 | BD37: =+SUM(C37:F37) -> #REF! | BE37: =+SUM(G37:J37) -> #REF! | BF37: =+SUM(K37:N37) -> #REF! | BG37: =+SUM(O37:R37) -> #REF! | BH37: =+BH32+BH34 -> #REF! | BI37: =+BI32+BI34 -> -520.4 | BJ37: =+BJ32+BJ34 -> #REF! | BK37: =+BK32+BK34 -> -2478.9 | BL37: =+BL32+BL34 -> -2946.3823 | BM37: =+BM32+BM34 -> -767.37205 | BN37: =+BN32+BN34 -> 462.68673 | BO37: =+BO32+BO34 -> 1022.7266 | ... BS37: =+BS32+BS34 -> 1584.2423
B38: y-o-y | G38: =+G37/C37-1 -> #REF! | H38: =+H37/D37-1 -> #REF! | I38: =+I37/E37-1 -> #REF! | J38: =+J37/F37-1 -> #REF! | K38: =+K37/G37-1 -> #REF! | L38: =+L37/H37-1 -> #REF! | M38: =+M37/I37-1 -> #REF! | N38: =+N37/J37-1 -> #REF! | ... AX38: =+AX37/AT37-1 -> 1.2738302 | AZ38: -1.2619166 | BE38: =+BE37/BD37-1 -> #REF! | BF38: =+BF37/BE37-1 -> #REF! | BG38: =+BG37/BF37-1 -> #REF! | BH38: =+BH37/BG37-1 -> #REF! | BI38: =+BI37/BH37-1 -> #REF! | BJ38: =+BJ37/BI37-1 -> #REF! | BK38: =+BK37/BJ37-1 -> #REF! | BL38: =+BL37/BK37-1 -> 0.18858457 | ... BS38: =+BS37/BR37-1 -> -0.00025435973
B40: Res Não Operacional e Descontinuadas | W40: =-48.7-X40 -> -22 | X40: -26.7 | Y40: -24.7 | Z40: -69.7 | AA40: 28.7 | AB40: -20.8 | AC40: -38.9 | AD40: -67.6 | AE40: -39.6 | AF40: -66.1 | AG40: -75.5 | AH40: -199.2 | AI40: -120.5 | AJ40: -99.1 | AK40: 7175.592 | AL40: -1031.5 | AM40: -1073.7 | AN40: 13.8 | AO40: -6995.4 | AP40: -108.1 | AQ40: -101.7 | AR40: -249.7 | AS40: -1807 | AT40: -507 | BD40: =+SUM(C40:F40) -> 0 | BE40: =+SUM(G40:J40) -> 0 | BF40: =+SUM(K40:N40) -> 0 | BG40: =+SUM(O40:R40) -> 0 | BH40: =+SUM(S40:V40) -> 0 | BI40: =+SUM(W40:Z40) -> -143.1 | BJ40: =+SUM(AA40:AD40) -> -98.6 | BK40: =+SUM(AE40:AH40) -> -380.4 | BL40: =+SUM(AI40:AL40) -> 5924.492 | BM40: =+SUM(AM40:AP40) -> -8163.4 | BN40: =+SUM(AQ40:AT40) -> -2665.4 | BO40: =+SUM(AU40:AX40) -> 0
B41: Minoritários | C41: 0.4 | D41: -1.7 | E41: 1.5 | F41: -9.4 | G41: -0.79271504 | H41: -0.61550502 | I41: -3.1 | J41: -7.0317671 | K41: 0 | L41: 0 | M41: 0 | N41: 0 | O41: 0 | P41: 0 | Q41: 0 | R41: 0 | S41: 0 | T41: 0 | U41: 0 | V41: 0 | W41: =-7.7-X41 -> -4.1 | X41: -3.6 | Y41: -4 | Z41: -1.7 | AA41: -1.4 | AB41: -2.6 | AC41: -3.3 | AD41: -0.0009 | AE41: 0.9 | AF41: -0.2 | AG41: 0.3 | AH41: 0 | AI41: 0.3 | AJ41: 0.06 | AK41: -0.437 | AL41: 1 | AM41: 0 | AN41: 0.2 | AO41: 0.2 | AP41: -0.2 | AQ41: 0 | AR41: 0 | AS41: 0 | AT41: 0 | AU41: 0 | AV41: 0 | AW41: 0 | AX41: 0 | AZ41: 0 | BD41: =+SUM(C41:F41) -> -9.2 | BE41: =+SUM(G41:J41) -> -11.539987 | BF41: =+SUM(K41:N41) -> 0 | BG41: =+SUM(O41:R41) -> 0 | BH41: =+SUM(S41:V41) -> 0 | BI41: =+SUM(W41:Z41) -> -13.4 | BJ41: =+SUM(AA41:AD41) -> -7.3009 | BK41: =+SUM(AE41:AH41) -> 1 | BL41: =+SUM(AI41:AL41) -> 0.923 | BM41: =+SUM(AM41:AP41) -> 0.2 | BN41: =+SUM(AQ41:AT41) -> 0 | BO41: =+SUM(AU41:AX41) -> 0 | BP41: 0 | BQ41: 0 | BR41: 0 | BS41: 0
B42: Lucro Líquido Reportado | C42: =+C37+C40+C41 -> #REF! | D42: =+D37+D40+D41 -> #REF! | E42: =+E37+E40+E41 -> #REF! | F42: =+F37+F40+F41 -> #REF! | G42: =+G37+G40+G41 -> #REF! | H42: =+H37+H40+H41 -> #REF! | I42: =+I37+I40+I41 -> #REF! | J42: =+J37+J40+J41 -> #REF! | ... AX42: =+AX37+AX40+AX41 -> 422.93242 | AZ42: 86.589635 | BA42: =+AT42/AZ42-1 -> -4.7071412 | BD42: =+SUM(C42:F42) -> #REF! | BE42: =+SUM(G42:J42) -> #REF! | BF42: =+SUM(K42:N42) -> #REF! | BG42: =+SUM(O42:R42) -> #REF! | BH42: =+BH37+BH40+BH41 -> #REF! | BI42: =+BI37+BI40+BI41 -> -676.9 | BJ42: =+BJ37+BJ40+BJ41 -> #REF! | BK42: =+BK37+BK40+BK41 -> -2858.3 | BL42: =+BL37+BL40+BL41 -> 2979.0327 | BM42: =+BM37+BM40+BM41 -> -8930.5721 | BN42: =+BN37+BN40+BN41 -> -2202.7133 | BO42: =+BO37+BO40+BO41 -> 1022.7266 | ... BS42: =+BS37+BS40+BS41 -> 1584.2423
B43: y-o-y | G43: =+G42/C42-1 -> #REF! | H43: =+H42/D42-1 -> #REF! | I43: =+I42/E42-1 -> #REF! | J43: =+J42/F42-1 -> #REF! | K43: =+K42/G42-1 -> #REF! | L43: =+L42/H42-1 -> #REF! | M43: =+M42/I42-1 -> #REF! | N43: =+N42/J42-1 -> #REF! | ... AX43: =+AX42/AT42-1 -> -2.3175465 | AZ43: -1.1972878 | BE43: =+BE42/BD42-1 -> #REF! | BF43: =+BF42/BE42-1 -> #REF! | BG43: =+BG42/BF42-1 -> #REF! | BH43: =+BH42/BG42-1 -> #REF! | BI43: =+BI42/BH42-1 -> #REF! | BJ43: =+BJ42/BI42-1 -> #REF! | BK43: =+BK42/BJ42-1 -> #REF! | BL43: =+BL42/BK42-1 -> -2.0422393 | ... BS43: =+BS42/BR42-1 -> -0.00025435973
B45: Subv investimento | AT45: =978-241 -> 737 | BK45: 200 | BL45: 400 | BM45: 200 | BN45: 200 | BO45: 200 | BP45: =+BP48*0.25 -> 141.61002 | BQ45: =+BQ48*0.25 -> 147.09602 | BR45: =+BR48*0.25 -> 152.74589 | BS45: =+BS48*0.25 -> 158.19139
B46: LL Ajustado | BK46: =+BK42-BK45 -> -3058.3 | BL46: =+BL42-BL45 -> 2579.0327 | BM46: =+BM42-BM45 -> -9130.5721 | BN46: =+BN42-BN45 -> -2402.7133 | BO46: =+BO42-BO45 -> 822.7266 | BP46: =+BP42-BP45 -> 1155.7646 | BQ46: =+BQ42-BQ45 -> 1266.1951 | BR46: =+BR42-BR45 -> 1431.8995 | BS46: =+BS42-BS45 -> 1426.0509
BN47: =+BN46+FAT!AS242-FAT!BP243 -> -2790.5133 | BO47: =+BO46+FAT!AT242-FAT!BQ243 -> -1918.922 | BP47: =+VP!$C$24/BP46 -> 12.511502 | BQ47: =+VP!$C$24/BQ46 -> 11.420317
BJ48: Subv invst | BK48: =+BK45/0.25 -> 800 | BL48: =+BL45/0.25 -> 1600 | BM48: =+BM45/0.25 -> 800 | BN48: =+BN45/0.25 -> 800 | BO48: =+BO45/0.25 -> 800 | BP48: =+BP49*BP5 -> 566.44009 | BQ48: =+BQ49*BQ5 -> 588.38409 | BR48: =+BR49*BR5 -> 610.98356 | BS48: =+BS49*BS5 -> 632.76558
BJ49: % RL | BK49: =+BK48/BK5 -> 0.022008737 | BL49: =+BL48/BL5 -> 0.054748779 | BM49: =+BM48/BM5 -> 0.034140065 | BN49: =+BN48/BN5 -> 0.036007739 | BO49: =+BO48/BO5 -> 0.036888575 | BP49: 0.025 | BQ49: 0.025 | BR49: 0.025 | BS49: 0.025
B51: FLUXO DE CAIXA FIRMA | C51: 1T15 | D51: 2T15 | E51: 3T15 | F51: 4T15 | G51: 1T16 | H51: 2T16 | I51: 3T16 | J51: 4T16 | K51: 1T17 | L51: 2T17 | M51: 3T17 | N51: 4T17 | O51: 1T18 | P51: 2T18 | Q51: 3T18 | R51: 4T18 | S51: 1T19 | T51: 2T19 | U51: 3T19 | V51: 4T19 | W51: 1T20 | X51: 2T20 | Y51: 3T20 | Z51: 4T20 | AA51: 1T21 | AB51: 2T21 | AC51: 3T21 | AD51: 4T21 | AE51: 1T22 | AF51: 2T22 | AG51: 3T22 | AH51: 4T22 | AI51: 1T23 | AJ51: 2T23 | AK51: 3T23 | AL51: 4T23 | AM51: 1T24 | AN51: 2T24 | AO51: 3T24 | AP51: 4T24 | AQ51: 4T24 | AR51: 4T24 | AS51: 4T24 | AT51: 4T24 | AU51: 4T24 | AV51: 4T24 | AW51: 4T24 | AX51: 4T24 | AZ51: 4T24
B52: EBITDA | C52: =+C56+C53 -> 285.9 | D52: =+D56+D53 -> 357.2 | E52: =+E56+E53 -> 399.6 | F52: =+F56+F53 -> 453.2 | G52: =+G56+G53 -> 216.99696 | H52: =+H56+H53 -> 344.72581 | I52: =+I56+I53 -> 348.947 | J52: =+J56+J53 -> 462.12572 | ... AX52: =+AX56+AX53 -> 805.36072 | AZ52: 576.20837 | BD52: =+BD56+BD53 -> 1495.9 | BE52: =+BE56+BE53 -> 1372.8321 | BF52: =+BF56+BF53 -> 1742.0035 | BG52: =+BG56+BG53 -> 1850.9593 | BH52: =+BH56+BH53 -> 5312.8895 | BI52: =+BI56+BI53 -> 3508.6736 | BJ52: =+BJ56+BJ53 -> 3909.9695 | BK52: =+BK56+BK53 -> 2133.5713 | ... BS52: =+BS56+BS53 -> 2876.1208
B53: (-) Deprec & Amort | C53: =-(+C54+C55) -> 57.167098 | D53: =-(+D54+D55) -> 52.939777 | E53: =-(+E54+E55) -> 62.514845 | F53: =-(+F54+F55) -> 66.802244 | G53: =-(+G54+G55) -> 63.073301 | H53: =-(+H54+H55) -> 64.374656 | I53: =-(+I54+I55) -> 97.522504 | J53: =-(+J54+J55) -> 64.947815 | ... AX53: =-(+AX54+AX55) -> 217.99477 | AZ53: 239.2 | BD53: =-(+BD54+BD55) -> 239.42396 | BE53: =-(+BE54+BE55) -> 289.95492 | BF53: =-(+BF54+BF55) -> 383.34442 | BG53: =-(+BG54+BG55) -> 587.0809 | BH53: =-(+BH54+BH55) -> 1117.3575 | BI53: =-(+BI54+BI55) -> 2718.8736 | BJ53: =-(+BJ54+BJ55) -> 2791.6695 | BK53: =-(+BK54+BK55) -> 2591.9713 | ... BS53: =-(+BS54+BS55) -> 712.53625
B54: (-) Amort | C54: =C18 -> 0 | D54: =D18 -> 0 | E54: =E18 -> 0 | F54: =F18 -> 0 | G54: =G18 -> 0 | H54: =H18 -> 0 | I54: =I18 -> 0 | J54: =J18 -> 0 | ... AX54: =AX18 -> 0 | AZ54: 0 | BD54: =BD18 -> 0 | BE54: =BE18 -> -0.036639748 | BF54: =BF18 -> -0.038903414 | BG54: =BG18 -> -0.043923026 | BH54: =BH18 -> -0.057453122 | BI54: =BI18 -> -0.073636514 | BJ54: =BJ18 -> -0.069503991 | BK54: =BK18 -> -0.071305558 | ... BS54: =BS18 -> 0
B55: (-) Depreciação | C55: =C17 -> -57.167098 | D55: =D17 -> -52.939777 | E55: =E17 -> -62.514845 | F55: =F17 -> -66.802244 | G55: =G17 -> -63.073301 | H55: =H17 -> -64.374656 | I55: =I17 -> -97.522504 | J55: =J17 -> -64.947815 | ... AY55: =AY17 -> 0 | AZ55: -239.2 | BD55: =BD17 -> -239.42396 | BE55: =BE17 -> -289.91828 | BF55: =BF17 -> -383.30552 | BG55: =BG17 -> -587.03697 | BH55: =BH17 -> -1117.3 | BI55: =BI17 -> -2718.8 | BJ55: =BJ17 -> -2791.6 | BK55: =BK17 -> -2591.9 | ... BS55: =BS17 -> -712.53625
B56: EBIT IFRS | C56: =+C21 -> 228.7329 | D56: =+D21 -> 304.26022 | E56: =+E21 -> 337.08515 | F56: =+F21 -> 386.39776 | G56: =+G21 -> 153.92366 | H56: =+H21 -> 280.35116 | I56: =+I21 -> 251.4245 | J56: =+J21 -> 397.1779 | ... AX56: =+AX21 -> 587.36595 | AZ56: 337.00837 | BD56: =+BD21 -> 1256.476 | BE56: =+BE21 -> 1082.8772 | BF56: =+BF21 -> 1358.6591 | BG56: =+BG21 -> 1263.8784 | BH56: =+BH21 -> 4195.532 | BI56: =+BI21 -> 789.8 | BJ56: =+BJ21 -> 1118.3 | BK56: =+BK21 -> -458.4 | ... BS56: =+BS21 -> 2163.5845
B57: (-) Juros con arrendamentos | C57: =+#REF! -> #REF! | D57: =+#REF! -> #REF! | E57: =+#REF! -> #REF! | F57: =+#REF! -> #REF! | G57: =+#REF! -> #REF! | H57: =+#REF! -> #REF! | I57: =+#REF! -> #REF! | J57: =+#REF! -> #REF! | ... AL57: =+#REF! -> #REF! | AM57: =+AM29 -> -33.3 | AN57: =+AN29 -> -21.241 | AO57: =+AO29 -> -21.7 | AP57: =+AP29 -> -19 | AQ57: =+AQ29 -> -32.5 | AR57: =+AR29 -> -19.8 | AS57: =+AS29 -> -34.544 | AT57: =+AT29 -> -28.223407 | ... AX57: =+AX29 -> -28.29343 | AZ57: -24.619565 | BD57: =+#REF! -> #REF! | BE57: =+#REF! -> #REF! | BF57: =+#REF! -> #REF! | BG57: =+#REF! -> #REF! | BH57: =+#REF! -> #REF! | BI57: =+#REF! -> #REF! | BJ57: =+#REF! -> #REF! | BK57: =+#REF! -> #REF! | BL57: =+#REF! -> #REF! | BM57: =+BM29 -> -95.241 | BN57: =+BN29 -> -115.06741 | BO57: =+BO29 -> -115.21932 | BP57: =+BP29 -> -111.1216 | BQ57: =+BQ29 -> -100.29696 | BR57: =+BR29 -> -110.12668 | BS57: =+BS29 -> -109.22927
B58: EBIT IAS | C58: =+C56+C57 -> #REF! | D58: =+D56+D57 -> #REF! | E58: =+E56+E57 -> #REF! | F58: =+F56+F57 -> #REF! | G58: =+G56+G57 -> #REF! | H58: =+H56+H57 -> #REF! | I58: =+I56+I57 -> #REF! | J58: =+J56+J57 -> #REF! | ... AX58: =+AX56+AX57 -> 559.07252 | AZ58: 312.3888 | BD58: =+BD56+BD57 -> #REF! | BE58: =+BE56+BE57 -> #REF! | BF58: =+BF56+BF57 -> #REF! | BG58: =+BG56+BG57 -> #REF! | BH58: =+BH56+BH57 -> #REF! | BI58: =+BI56+BI57 -> #REF! | BJ58: =+BJ56+BJ57 -> #REF! | BK58: =+BK56+BK57 -> #REF! | ... BS58: =+BS56+BS57 -> 2054.3552
B59: (-) Provisão de IR & CS | C59: =-0.34*C58 -> #REF! | D59: =-0.34*D58 -> #REF! | E59: =-0.34*E58 -> #REF! | F59: =-0.34*F58 -> #REF! | G59: =-0.34*G58 -> #REF! | H59: =-0.34*H58 -> #REF! | I59: =-0.34*I58 -> #REF! | J59: =-0.34*J58 -> #REF! | ... AX59: =-0.34*AX58 -> -190.08466 | AZ59: -106.21219 | BD59: =+BD35*BD58 -> #REF! | BE59: =+BE35*BE58 -> #REF! | BF59: =+BF35*BF58 -> #REF! | BG59: =+BG35*BG58 -> #REF! | BH59: =-0.34*BH58 -> #REF! | BI59: =-0.34*BI58 -> #REF! | BJ59: =-0.34*BJ58 -> #REF! | BK59: =-0.34*BK58 -> #REF! | BL59: =-0.34*BL58 -> #REF! | BM59: =-0.34*BM58 -> -274.14572 | BN59: =-0.34*BN58 -> -405.11657 | BO59: =-0.34*BO58 -> -544.45949 | ... BS59: =-0.34*BS58 -> -698.48078
B60: (+) Ajustes Fiscais | C60: 0 | D60: 0 | E60: 0 | F60: 0 | G60: 0 | H60: 0 | I60: 0 | J60: 0 | K60: 0 | L60: 0 | M60: 0 | N60: 0 | O60: 0 | P60: 0 | Q60: 0 | R60: 0 | S60: 0 | T60: 0 | U60: 0 | V60: 0 | W60: 0 | X60: 0 | Y60: 0 | Z60: 0 | AA60: 0 | AB60: 0 | AC60: 0 | AD60: 0 | AE60: 0 | AF60: 0 | AG60: 0 | AH60: 0 | AI60: 0 | AJ60: 0 | AK60: 0 | AL60: 0 | AM60: 0 | AN60: 0 | AO60: 0 | AP60: 0 | AQ60: 0 | AR60: 0 | AS60: 0 | AT60: 0 | AU60: 0 | AV60: 0 | AW60: 0 | AX60: 0 | AZ60: 0 | BD60: 0 | BE60: 0 | BF60: 0 | BG60: 0 | BH60: 0 | BI60: 0 | BJ60: 0 | BK60: 0 | BL60: 0 | BM60: 0 | BN60: 0 | BO60: 0 | BP60: 0 | BQ60: 0 | BR60: 0 | BS60: 0
B61: (-) Part | C61: 0 | D61: 0 | E61: 0 | F61: 0 | G61: 0 | H61: 0 | I61: 0 | J61: 0 | K61: 0 | L61: 0 | M61: 0 | N61: 0 | O61: 0 | P61: 0 | Q61: 0 | R61: 0 | S61: 0 | T61: 0 | U61: 0 | V61: 0 | W61: 0 | X61: 0 | Y61: 0 | Z61: 0 | AA61: 0 | AB61: 0 | AC61: 0 | AD61: 0 | AE61: 0 | AF61: 0 | AG61: 0 | AH61: 0 | AI61: 0 | AJ61: 0 | AK61: 0 | AL61: 0 | AM61: 0 | AN61: 0 | AO61: 0 | AP61: 0 | AQ61: 0 | AR61: 0 | AS61: 0 | AT61: 0 | AU61: 0 | AV61: 0 | AW61: 0 | AX61: 0 | AZ61: 0 | BD61: 0 | BE61: 0 | BF61: 0 | BG61: 0 | BH61: 0 | BI61: 0 | BJ61: 0 | BK61: 0 | BL61: 0 | BM61: 0 | BN61: 0 | BO61: 0 | BP61: 0 | BQ61: 0 | BR61: 0 | BS61: 0
B62: NOPLAT | C62: =+C58+C59+C60+C61 -> #REF! | D62: =+D58+D59+D60+D61 -> #REF! | E62: =+E58+E59+E60+E61 -> #REF! | F62: =+F58+F59+F60+F61 -> #REF! | G62: =+G58+G59+G60+G61 -> #REF! | H62: =+H58+H59+H60+H61 -> #REF! | I62: =+I58+I59+I60+I61 -> #REF! | J62: =+J58+J59+J60+J61 -> #REF! | ... AX62: =+AX58+AX59+AX60+AX61 -> 368.98786 | AZ62: 206.17661 | BD62: =+BD58+BD59+BD60+BD61 -> #REF! | BE62: =+BE58+BE59+BE60+BE61 -> #REF! | BF62: =+BF58+BF59+BF60+BF61 -> #REF! | BG62: =+BG58+BG59+BG60+BG61 -> #REF! | BH62: =+BH58+BH59+BH60+BH61 -> #REF! | BI62: =+BI58+BI59+BI60+BI61 -> #REF! | BJ62: =+BJ58+BJ59+BJ60+BJ61 -> #REF! | BK62: =+BK58+BK59+BK60+BK61 -> #REF! | ... BS62: =+BS58+BS59+BS60+BS61 -> 1355.8745
B63: (+) Deprec & Amort Imob | C63: =+FAT!C92 -> 57.167098 | D63: =+FAT!D92 -> 52.939777 | E63: =+FAT!E92 -> 62.514845 | F63: =+FAT!F92 -> 66.802244 | G63: =+FAT!G92 -> 63.073301 | H63: =+FAT!H92 -> 64.374656 | I63: =+FAT!I92 -> 97.522504 | J63: =+FAT!J92 -> 64.947815 | ... AX63: =+FAT!AX92 -> 195.92702 | AZ63: 191.57278 | BD63: =+FAT!BE92 -> 239.42396 | BE63: =+FAT!BF92 -> 289.91828 | BF63: =+FAT!BG92 -> 383.30552 | BG63: =+FAT!BH92 -> 587.03697 | BH63: =+FAT!BJ92 -> 550.231 | BI63: =+FAT!BK92 -> 1495.906 | BJ63: =+FAT!BL92 -> 1793.591 | BK63: =+FAT!BM92 -> 1664.034 | BL63: =+FAT!BN92 -> 1580.844 | BM63: =+FAT!BO92 -> 1332.346 | BN63: =+FAT!BP92 -> 713.733 | BO63: =+FAT!BQ92 -> 800.5768 | ... BS63: =+FAT!BU92 -> 632.33947
B64: (+) Impostos Diferidos | C64: =C162-B162 -> #VALUE! | D64: =D162-C162 -> -58.202 | E64: =E162-D162 -> -59.052 | F64: =F162-E162 -> 69.19 | G64: =G162-F162 -> -74.647 | H64: =H162-G162 -> -127.561 | I64: =I162-H162 -> -37.257 | J64: =J162-I162 -> -51.221 | ... AX64: =AX162-AW162 -> 0 | AZ64: 0 | BD64: =BD162-BB162 -> -178.535 | BE64: =BE162-BD162 -> -290.686 | BF64: =BF162-BE162 -> 547.437 | BG64: =BG162-BF162 -> -45.082 | BH64: =BH162-BG162 -> 43.018 | BI64: =BI162-BH162 -> -127.852 | BJ64: =BJ162-BI162 -> -1908.4 | BK64: =BK162-BJ162 -> -625 | BL64: =BL162-BK162 -> 712.5 | ... BS64: =BS162-BR162 -> 0
B65: (-) Inv Cap Giro | C65: =C146-B146 -> #VALUE! | D65: =D146-C146 -> -71.1 | E65: =E146-D146 -> -76.3 | F65: =F146-E146 -> -166.96 | G65: =G146-F146 -> 137.366 | H65: =H146-G146 -> 113.254 | I65: =I146-H146 -> -25.895 | J65: =J146-I146 -> -247.009 | ... AX65: =AX146-AW146 -> 314.00911 | AZ65: 46.313009 | BD65: =BD146-BB146 -> 141.032 | BE65: =BE146-BD146 -> -22.284 | BF65: =BF146-BE146 -> 703.556 | BG65: =BG146-BF146 -> 135.71 | BH65: =BH146-BG146 -> -431.814 | BI65: =BI146-BH146 -> -654.7 | BJ65: =BJ146-BI146 -> 1388.3 | BK65: =BK146-BJ146 -> -684.3 | BL65: =BL146-BK146 -> -1022.1 | ... BS65: =BS146-BR146 -> 120.3259
B66: (-) Capex | C66: =+C207 -> 50.2 | D66: =+D207 -> 90.8 | E66: =+E207 -> 97.8 | F66: =+F207 -> 144.2 | G66: =+G207 -> 47.9 | H66: =+H207 -> 62.7 | I66: =+I207 -> 65 | J66: =+J207 -> 130.4 | ... AX66: =+AX207 -> 158.43916 | AZ66: 168.0505 | BD66: =+BD207 -> 383 | BE66: =+BE207 -> 306 | BF66: =+BF207 -> 362.5 | BG66: =+BG207 -> 491.9 | BH66: =+BH207 -> 571.3 | BI66: =+BI207 -> 790.7 | BJ66: =+BJ207 -> 1513 | BK66: =+BK207 -> 1102.8 | ... BS66: =+BS207 -> 636.8999
B67: (+) Venda de Ativos | AL67: =+Resumo!$J$120 -> 11617 | AM67: 260 | BI67: =+SUM(W67:Z67) -> 0 | BJ67: =+SUM(AA67:AD67) -> 0 | BK67: =+SUM(AE67:AH67) -> 0 | BL67: =+SUM(AI67:AK67) -> 0 | BM67: =+SUM(AM67:AP67) -> 260 | BN67: =+SUM(AQ67:AT67) -> 0 | BO67: =+SUM(AU67:AX67) -> 0 | BP67: =+BO67*(1+MACRO!BP5) -> 0 | BQ67: =+BP67*(1+MACRO!BQ5) -> 0
B68: FCF Firm | C68: =C62+C63+C64-C65-C66+C67 -> #REF! | D68: =D62+D63+D64-D65-D66+D67 -> #REF! | E68: =E62+E63+E64-E65-E66+E67 -> #REF! | F68: =F62+F63+F64-F65-F66+F67 -> #REF! | G68: =G62+G63+G64-G65-G66+G67 -> #REF! | H68: =H62+H63+H64-H65-H66+H67 -> #REF! | I68: =I62+I63+I64-I65-I66+I67 -> #REF! | J68: =J62+J63+J64-J65-J66+J67 -> #REF! | ... AX68: =AX62+AX63+AX64-AX65-AX66+AX67 -> 92.466621 | AZ68: 183.38587 | BD68: =BD62+BD63+BD64-BD65-BD66+BD67 -> #REF! | BE68: =BE62+BE63+BE64-BE65-BE66+BE67 -> #REF! | BF68: =BF62+BF63+BF64-BF65-BF66+BF67 -> #REF! | BG68: =BG62+BG63+BG64-BG65-BG66+BG67 -> #REF! | BH68: =BH62+BH63+BH64-BH65-BH66+BH67 -> #REF! | BI68: =BI62+BI63+BI64-BI65-BI66+BI67 -> #REF! | BJ68: =BJ62+BJ63+BJ64-BJ65-BJ66+BJ67 -> #REF! | BK68: =BK62+BK63+BK64-BK65-BK66+BK67 -> #REF! | ... BS68: =BS62+BS63+BS64-BS65-BS66+BS67 -> 1230.9881
B69: (-) Outros Ativos Não Oper. | C69: =C165-B165 -> #VALUE! | D69: =D165-C165 -> -338.499 | E69: =E165-D165 -> 250.919 | F69: =F165-E165 -> 95.795 | G69: =G165-F165 -> -308.519 | H69: =H165-G165 -> -576.121 | I69: =I165-H165 -> -105.068 | J69: =J165-I165 -> 28.854 | ... AX69: =AX165-AW165 -> -40.662384 | AZ69: -529.1635 | BD69: =BD165-BB165 -> 941.57 | BE69: =BE165-BD165 -> -960.854 | BF69: =BF165-BE165 -> 20.823 | BG69: =BG165-BF165 -> 623.358 | BH69: =BH165-BG165 -> 677.559 | BI69: =BI165-BH165 -> -53.856 | BJ69: =BJ165-BI165 -> -773.2 | BK69: =BK165-BJ165 -> -1586.7 | BL69: =BL165-BK165 -> 1508.7 | ... BS69: =BS165-BR165 -> -9.1053945
B70: (+) Outras Rec (Desp) Não Oper | C70: =C19 -> 8.5 | D70: =D19 -> 9.9 | E70: =E19 -> 36.6 | F70: =F19 -> 10.8 | G70: =G19 -> 7.7405845 | H70: =H19 -> -4.4156493 | I70: =I19 -> 7.5 | J70: =J19 -> 43.561688 | ... AF70: =AF19 -> -276.7 | AG70: =+AG40 -> -75.5 | AH70: =+AH40 -> -199.2 | AI70: =+AI40 -> -120.5 | AJ70: =+AJ40 -> -99.1 | AK70: =+AK40 -> 7175.592 | AL70: =+AL40 -> -1031.5 | AM70: =+AM40 -> -1073.7 | AN70: =+AN40 -> 13.8 | ... AY70: =+AY40 -> 0 | AZ70: 0 | BA70: =+BA40 -> 0 | BB70: =+BB40 -> 0 | BD70: =+BD40 -> 0 | BE70: =+BE40 -> 0 | BF70: =+BF40 -> 0 | BG70: =+BG40 -> 0 | BH70: =+BH40 -> 0 | BI70: =+BI40 -> -143.1 | BJ70: =+BJ40 -> -98.6 | BK70: =+BK40 -> -380.4 | ... BS70: =+BS40 -> 0
B71: (+) Resultado Financeiro Bruto | C71: =C26-C57 -> #REF! | D71: =D26-D57 -> #REF! | E71: =E26-E57 -> #REF! | F71: =F26-F57 -> #REF! | G71: =G26-G57 -> #REF! | H71: =H26-H57 -> #REF! | I71: =I26-I57 -> #REF! | J71: =J26-J57 -> #REF! | ... AX71: =AX26-AX57 -> -132.47052 | AZ71: -181.19238 | BD71: =BD26-BD57 -> #REF! | BE71: =BE26-BE57 -> #REF! | BF71: =BF26-BF57 -> #REF! | BG71: =BG26-BG57 -> #REF! | BH71: =BH26-BH57 -> #REF! | BI71: =BI26-BI57 -> #REF! | BJ71: =BJ26-BJ57 -> #REF! | BK71: =BK26-BK57 -> #REF! | ... BS71: =BS26-BS57 -> -234.18452
B72: (+) Ajustes IR | C72: =+C34-C59 -> #REF! | D72: =+D34-D59 -> #REF! | E72: =+E34-E59 -> #REF! | F72: =+F34-F59 -> #REF! | G72: =+G34-G59 -> #REF! | H72: =+H34-H59 -> #REF! | I72: =+I34-I59 -> #REF! | J72: =+J34-J59 -> #REF! | ... AX72: =+AX34-AX59 -> 186.41508 | AZ72: 61.605411 | BD72: =+BD34-BD59 -> #REF! | BE72: =+BE34-BE59 -> #REF! | BF72: =+BF34-BF59 -> #REF! | BG72: =+BG34-BG59 -> #REF! | BH72: =+BH34-BH59 -> #REF! | BI72: =+BI34-BI59 -> #REF! | BJ72: =+BJ34-BJ59 -> #REF! | BK72: =+BK34-BK59 -> #REF! | ... BS72: =+BS34-BS59 -> 462.55239
B73: (+) Divid. Recebidos Líquidos
B74: FCFequity | C74: =C68-C69+C70+C71+C72+C73 -> #REF! | D74: =D68-D69+D70+D71+D72+D73 -> #REF! | E74: =E68-E69+E70+E71+E72+E73 -> #REF! | F74: =F68-F69+F70+F71+F72+F73 -> #REF! | G74: =G68-G69+G70+G71+G72+G73 -> #REF! | H74: =H68-H69+H70+H71+H72+H73 -> #REF! | I74: =I68-I69+I70+I71+I72+I73 -> #REF! | J74: =J68-J69+J70+J71+J72+J73 -> #REF! | ... AX74: =AX68-AX69+AX70+AX71+AX72+AX73 -> 187.07356 | AZ74: 592.9624 | BD74: =BD68-BD69+BD70+BD71+BD72+BD73 -> #REF! | BE74: =BE68-BE69+BE70+BE71+BE72+BE73 -> #REF! | BF74: =BF68-BF69+BF70+BF71+BF72+BF73 -> #REF! | BG74: =BG68-BG69+BG70+BG71+BG72+BG73 -> #REF! | BH74: =BH68-BH69+BH70+BH71+BH72+BH73 -> #REF! | BI74: =BI68-BI69+BI70+BI71+BI72+BI73 -> #REF! | BJ74: =BJ68-BJ69+BJ70+BJ71+BJ72+BJ73 -> #REF! | BK74: =BK68-BK69+BK70+BK71+BK72+BK73 -> #REF! | ... BS74: =BS68-BS69+BS70+BS71+BS72+BS73 -> 1468.4614
B75: (-) Dividendos Pagos no Período | C75: =+C233-(C121-B121) -> #VALUE! | D75: =+D233-(D121-C121) -> 0 | E75: =+E233-(E121-D121) -> 236.326 | F75: =+F233-(F121-E121) -> 0 | G75: =+G233-(G121-F121) -> 0 | H75: =+H233-(H121-G121) -> 123.132 | I75: =+I233-(I121-H121) -> 0 | J75: =+J233-(J121-I121) -> 0 | ... AX75: =+AX233-(AX121-AW121) -> 0 | AZ75: 0 | BD75: =+BD233-(BD121-BB121) -> 207.29 | BE75: =+BE233-(BE121-BD121) -> 105.732 | BF75: =+BF233-(BF121-BE121) -> -99.15 | BG75: =+BG233-(BG121-BF121) -> 177.462 | BH75: =+BH233-(BH121-BG121) -> 224.44 | BI75: =+BI233-(BI121-BH121) -> 95.9 | BJ75: =+BJ233-(BJ121-BI121) -> -180.8 | BK75: =+BK233-(BK121-BJ121) -> 180.5 | BL75: =+BL233-(BL121-BK121) -> -293.9 | ... BS75: =+BS233-(BS121-BR121) -> 433.40845
B76: (+) Aumento Dívidas CP | C76: =+C117-B117 -> #VALUE! | D76: =+D117-C117 -> 50.148 | E76: =+E117-D117 -> 459.983 | F76: =+F117-E117 -> 275.623 | G76: =+G117-F117 -> 40.384 | H76: =+H117-G117 -> -68.411 | I76: =+I117-H117 -> -182.675 | J76: =+J117-I117 -> -186.193 | ... AX76: =+AX117-AW117 -> 0 | AZ76: 0 | BD76: =+BD117-BB117 -> 2161.383 | BE76: =+BE117-BD117 -> -396.895 | BF76: =+BF117-BE117 -> 2312.181 | BG76: =+BG117-BF117 -> -2963.574 | BH76: =+BH117-BG117 -> 2241.305 | BI76: =+BI117-BH117 -> 451.2 | BJ76: =+BJ117-BI117 -> -2860.5 | BK76: =+BK117-BJ117 -> -613.9 | BL76: =+BL117-BK117 -> -167.4 | ... BS76: =+BS117-BR117 -> 0
B77: (+) Aumento Dívidas LP | C77: =C130-B130 -> #VALUE! | D77: =D130-C130 -> -79.043 | E77: =E130-D130 -> 208.659 | F77: =F130-E130 -> -670.985 | G77: =G130-F130 -> -391.101 | H77: =H130-G130 -> -381.671 | I77: =I130-H130 -> -477.51 | J77: =J130-I130 -> 501.468 | ... AX77: =AX130-AW130 -> 25.307557 | AZ77: 111.99946 | BD77: =BD130-BB130 -> 3374.497 | BE77: =BE130-BD130 -> -748.814 | BF77: =BF130-BE130 -> 2629.548 | BG77: =BG130-BF130 -> 1625.819 | BH77: =BH130-BG130 -> 550.95 | BI77: =BI130-BH130 -> 2585.3 | BJ77: =BJ130-BI130 -> 1754.5 | BK77: =BK130-BJ130 -> 1489.3 | BL77: =BL130-BK130 -> -7313.2 | ... BS77: =BS130-BR130 -> 0
B78: (+) Subscrição de Ações
B79: (-) Outros Ativos Finan | C79: =+C99-B99+C110-B110 -> #VALUE! | D79: =+D99-C99+D110-C110 -> 125.091 | E79: =+E99-D99+E110-D110 -> 439.347 | F79: =+F99-E99+F110-E110 -> 4.826 | G79: =+G99-F99+G110-F110 -> -110.642 | H79: =+H99-G99+H110-G110 -> -1.146 | I79: =+I99-H99+I110-H110 -> -49.523 | J79: =+J99-I99+J110-I110 -> 188.839 | ... AX79: =+AX99-AW99+AX110-AW110 -> 25.604869 | AZ79: 35.88824 | BD79: =+BD99-BB99+BD110-BB110 -> 1786.672 | BE79: =+BE99-BD99+BE110-BD110 -> 27.528 | BF79: =+BF99-BE99+BF110-BE110 -> 967.822 | BG79: =+BG99-BF99+BG110-BF110 -> -228.514 | BH79: =+BH99-BG99+BH110-BG110 -> 382.048 | BI79: =+BI99-BH99+BI110-BH110 -> 4873.844 | BJ79: =+BJ99-BI99+BJ110-BI110 -> -1117.1 | BK79: =+BK99-BJ99+BK110-BJ110 -> -1016.5 | BL79: =+BL99-BK99+BL110-BK110 -> 1829.1 | ... BS79: =+BS99-BR99+BS110-BR110 -> 0
B80: (+) Outros Ajustes | C80: =C81-(C74-C75+C76+C77+C78-C79) -> #VALUE! | D80: =D81-(D74-D75+D76+D77+D78-D79) -> #REF! | E80: =E81-(E74-E75+E76+E77+E78-E79) -> #REF! | F80: =F81-(F74-F75+F76+F77+F78-F79) -> #REF! | G80: =G81-(G74-G75+G76+G77+G78-G79) -> #REF! | H80: =H81-(H74-H75+H76+H77+H78-H79) -> #REF! | I80: =I81-(I74-I75+I76+I77+I78-I79) -> #REF! | J80: =J81-(J74-J75+J76+J77+J78-J79) -> #REF! | ... AX80: =AX81-(AX74-AX75+AX76+AX77+AX78-AX79) -> 25.604869 | AZ80: 35.88824 | BD80: =BD81-(BD74-BD75+BD76+BD77+BD78-BD79) -> #REF! | BE80: =BE81-(BE74-BE75+BE76+BE77+BE78-BE79) -> #REF! | BF80: =BF81-(BF74-BF75+BF76+BF77+BF78-BF79) -> #REF! | BG80: =BG81-(BG74-BG75+BG76+BG77+BG78-BG79) -> #REF! | BH80: =BH81-(BH74-BH75+BH76+BH77+BH78-BH79) -> #REF! | BI80: =BI81-(BI74-BI75+BI76+BI77+BI78-BI79) -> #REF! | BJ80: =BJ81-(BJ74-BJ75+BJ76+BJ77+BJ78-BJ79) -> #REF! | BK80: =BK81-(BK74-BK75+BK76+BK77+BK78-BK79) -> #REF! | ... BS80: =BS81-(BS74-BS75+BS76+BS77+BS78-BS79) -> -0.14123626
B81: Aumento No Caixa | C81: =C98-B98 -> #VALUE! | D81: =D98-C98 -> -152.761 | E81: =E98-D98 -> -189.697 | F81: =F98-E98 -> -31.421 | G81: =G98-F98 -> -239.821 | H81: =H98-G98 -> -155.207 | I81: =I98-H98 -> -411.803 | J81: =J98-I98 -> 306.458 | ... AX81: =AX98-AW98 -> 212.38112 | AZ81: 704.96186 | BD81: =BD98-BB98 -> 1591.843 | BE81: =BE98-BD98 -> -500.373 | BF81: =BF98-BE98 -> 601.661 | BG81: =BG98-BF98 -> -478.083 | BH81: =BH98-BG98 -> 3298.552 | BI81: =BI98-BH98 -> 1308.1 | BJ81: =BJ98-BI98 -> -1814.4 | BK81: =BK98-BJ98 -> 188.4 | BL81: =BL98-BK98 -> -444.8 | ... BS81: =BS98-BR98 -> 1034.9117
B83: Net Income
AU87: total | AV87: x dia
AU88: 960 | AV88: =+AU88/10 -> 96 | AW88: 1 dia 4 | AX88: =+AV88 -> 96 | AY88: =+AX88/4 -> 24
AW89: 5 dias todos: | AX89: =+AV88*5 -> 480 | AY89: =+AX89/6 -> 80
AW90: 4 dias ellos 4: | AX90: =+AU88-AX88-AX89 -> 384 | AY90: =+AX90/4 -> 96
AF95: =+AF100-AD100 -> -224.7 | BI95: =+BI74/Resumo!K69 -> #REF! | BJ95: =+BJ74/Resumo!L69 -> #REF! | BK95: =+BK74/Resumo!M69 -> #REF! | BL95: =+BL74/Resumo!N69 -> #REF! | BM95: =+BM74/Resumo!O69 -> -0.80156108 | BN95: =+BN74/Resumo!P69 -> -0.0086274725 | BO95: =+BO74/Resumo!Q69 -> 0.067880412 | BP95: =+BP68/Resumo!R69 -> 0.087396132 | BQ95: =+BQ68/Resumo!S69 -> 0.081049503 | BR95: =+BR68/Resumo!T69 -> 0.082295602 | BS95: =+BS68/Resumo!U69 -> 0.085128515
B96: BALANÇO | C96: =+C$2 -> 1T15 | D96: =+D$2 -> 2T15 | E96: =+E$2 -> 3T15 | F96: =+F$2 -> 4T15 | G96: =+G$2 -> 1T16 | H96: =+H$2 -> 2T16 | I96: =+I$2 -> 3T16 | J96: =+J$2 -> 4T16 | ... AX96: =+AX$2 -> 4T26 | AZ96: 4T25 | BD96: =+BD$2 -> 2015 | BE96: =+BE$2 -> 2016 | BF96: =+BF$2 -> 2017 | BG96: =+BG$2 -> 2018 | BH96: =+BH$2 -> 2019 | BI96: =+BI$2 -> 2020 | BJ96: =+BJ$2 -> 2021 | BK96: =+BK$2 -> 2022 | ... BS96: =+BS$2 -> 2030
B97: ATIVO CIRCULANTE | C97: =+C98+C99+C100+C102+C103+C107 -> 5771.416 | D97: =+D98+D99+D100+D102+D103+D107 -> 5401.154 | E97: =+E98+E99+E100+E102+E103+E107 -> 6459.548 | F97: =+F98+F99+F100+F102+F103+F107 -> 6018.706 | G97: =+G98+G99+G100+G102+G103+G107 -> 5427.96 | H97: =+H98+H99+H100+H102+H103+H107 -> 5000.876 | I97: =+I98+I99+I100+I102+I103+I107 -> 4436.879 | J97: =+J98+J99+J100+J102+J103+J107 -> 4802.9 | ... AL97: =+AL98+AL99+AL100+AL102+AL103+AL107 -> 15987.2 | AM97: =+SUM(AM98:AM107) -> 12558.697 | AN97: =+SUM(AN98:AN107) -> 11697.885 | AO97: =+SUM(AO98:AO107) -> 12762.525 | AP97: =+SUM(AP98:AP107) -> 13380.033 | AQ97: =+SUM(AQ98:AQ107) -> 13132.931 | AR97: =+SUM(AR98:AR107) -> 13576.947 | AS97: =+SUM(AS98:AS107) -> 12210.956 | AT97: =+SUM(AT98:AT107) -> 12214.288 | ... AX97: =+SUM(AX98:AX107) -> 13597.531 | AZ97: 12224.168 | BD97: =+F97 -> 6018.706 | BE97: =+J97 -> 4802.9 | BF97: =+N97 -> 7056.309 | BG97: =+R97 -> 6455.759 | BH97: =+V97 -> 9430.1 | BI97: =+Z97 -> 18734.8 | BJ97: =+AD97 -> 17449.9 | BK97: =+AH97 -> 16121.5 | BL97: =+AL97 -> 15987.2 | BM97: =+AP97 -> 13380.033 | BN97: =+AT97 -> 12214.288 | BO97: =+AX97 -> 13597.531 | BP97: =+SUM(BP98:BP107) -> 15149.527 | BQ97: =+SUM(BQ98:BQ107) -> 15090.856 | BR97: =+SUM(BR98:BR107) -> 16589.977 | BS97: =+SUM(BS98:BS107) -> 18009.967
B98: Dispon. + Aplic.Fin. | C98: 1965.722 | D98: 1812.961 | E98: 1623.264 | F98: 1591.843 | G98: 1352.022 | H98: 1196.815 | I98: 785.012 | J98: 1091.47 | K98: 617.367 | L98: 649.817 | M98: 2210.412 | N98: 1693.131 | O98: 798.628 | P98: 643.563 | Q98: 586.752 | R98: 1215.048 | S98: 866.906 | T98: 882.675 | U98: 910.7 | V98: 4513.6 | W98: 3150.1 | X98: 4820.1 | Y98: 5059.9 | Z98: 5821.7 | AA98: 4326.4 | AB98: 4504.8 | AC98: 3054.4 | AD98: 4007.3 | AE98: 3038.5 | AF98: 3043.8 | AG98: 3252.3 | AH98: 4195.7 | AI98: 2224.5 | AJ98: 2275.1 | AK98: 3292.5 | AL98: 3750.9 | AM98: 3146.926 | AN98: 643.2 | AO98: 1159.17 | AP98: 1741.187 | AQ98: 1563.367 | AR98: 1259.449 | AS98: 1315.03 | AT98: 1490.706 | AU98: =+AU142-AU111-AU108-AU107-AU103-AU102-AU100-AU99-AU106-AU105-AU104-AU101 -> 2355.0115 | AV98: =+AV142-AV111-AV108-AV107-AV103-AV102-AV100-AV99-AV106-AV105-AV104-AV101 -> 2485.4549 | AW98: =+AW142-AW111-AW108-AW107-AW103-AW102-AW100-AW99-AW106-AW105-AW104-AW101 -> 2441.7344 | AX98: =+AX142-AX111-AX108-AX107-AX103-AX102-AX100-AX99-AX106-AX105-AX104-AX101 -> 2654.1155 | AZ98: 2019.9919 | BD98: =+F98 -> 1591.843 | BE98: =+J98 -> 1091.47 | BF98: =+N98 -> 1693.131 | BG98: =+R98 -> 1215.048 | BH98: =+V98 -> 4513.6 | BI98: =+Z98 -> 5821.7 | BJ98: =+AD98 -> 4007.3 | BK98: =+AH98 -> 4195.7 | BL98: =+AL98 -> 3750.9 | BM98: =+AP98 -> 1741.187 | BN98: =+AT98 -> 1490.706 | BO98: =+AX98 -> 2654.1155 | BP98: =+BP142-BP111-BP108-BP107-BP103-BP102-BP100-BP99-BP106-BP105-BP104-BP101 -> 3693.3524 | BQ98: =+BQ142-BQ111-BQ108-BQ107-BQ103-BQ102-BQ100-BQ99-BQ106-BQ105-BQ104-BQ101 -> 3246.1276 | BR98: =+BR142-BR111-BR108-BR107-BR103-BR102-BR100-BR99-BR106-BR105-BR104-BR101 -> 4344.9794 | BS98: =+BS142-BS111-BS108-BS107-BS103-BS102-BS100-BS99-BS106-BS105-BS104-BS101 -> 5379.8911
B99: Outros Ativos Financeiros CP | C99: 713.642 | D99: 824.225 | E99: 1284.607 | F99: 1191.836 | G99: 1072.098 | H99: 1075.361 | I99: 1034.969 | J99: 1207.459 | K99: 1171.066 | L99: 974.193 | M99: 1491.155 | N99: 1977.305 | O99: 1856.46 | P99: 1299.54 | Q99: 1179.398 | R99: 1215.377 | S99: 502.241 | T99: 717.782 | U99: 749.9 | V99: 1025.8 | W99: 1416.2 | X99: 2570.2 | Y99: 2891 | Z99: 2520.6 | AA99: 2249.7 | AB99: 3484.6 | AC99: 2304.5 | AD99: 1978.7 | AE99: 1498.2 | AF99: 1231.8 | AG99: 1377.2 | AH99: 1800.4 | AI99: 1587.5 | AJ99: 1180.4 | AK99: 3480.9 | AL99: 4024.1 | AM99: 1510.284 | AN99: 1885.284 | AO99: 2078.766 | AP99: 1666.782 | AQ99: 1391.832 | AR99: 1007.323 | AS99: 938.43 | AT99: 1180.547 | AU99: =+AT99 -> 1180.547 | AV99: =+AU99 -> 1180.547 | AW99: =+AV99 -> 1180.547 | AX99: =+AW99 -> 1180.547 | AZ99: 938.43 | BD99: =+F99 -> 1191.836 | BE99: =+J99 -> 1207.459 | BF99: =+N99 -> 1977.305 | BG99: =+R99 -> 1215.377 | BH99: =+V99 -> 1025.8 | BI99: =+Z99 -> 2520.6 | BJ99: =+AD99 -> 1978.7 | BK99: =+AH99 -> 1800.4 | BL99: =+AL99 -> 4024.1 | BM99: =+AP99 -> 1666.782 | BN99: =+AT99 -> 1180.547 | BO99: =+AX99 -> 1180.547 | BP99: 1200 | BQ99: 1200 | BR99: 1200 | BS99: 1200
B100: Clientes | C100: 798.941 | D100: 886.832 | E100: 905.635 | F100: 909.013 | G100: 791.098 | H100: 957.865 | I100: 947.165 | J100: 1051.901 | K100: 948.879 | L100: 939.884 | M100: 1269.715 | N100: 1507.921 | O100: 1371.903 | P100: 1353.288 | Q100: 1499.83 | R100: 1691.581 | S100: 1439.205 | T100: 1536.365 | U100: 1577 | V100: 1685.8 | W100: 2774.6 | X100: 2644.6 | Y100: 3617.4 | Z100: 3597.5 | AA100: 3370.1 | AB100: 3106.9 | AC100: 3246.5 | AD100: 3476.4 | AE100: 2893.5 | AF100: 3251.7 | AG100: 3368.2 | AH100: 3502.4 | AI100: 3327.9 | AJ100: 3452.6 | AK100: 3406.6 | AL100: =3524.4+22.9 -> 3547.3 | AM100: 3065.215 | AN100: 3825.967 | AO100: 4051.791 | AP100: 4659.505 | AQ100: 4101.28 | AR100: 4515.261 | AS100: 4291.014 | AT100: 4680.026 | AU100: =SUM(AR3:AU3)/365*AU170 -> 3923.8042 | AV100: =SUM(AS3:AV3)/365*AV170 -> 3918.4203 | AW100: =SUM(AT3:AW3)/365*AW170 -> 4213.4423 | AX100: =SUM(AU3:AX3)/365*AX170 -> 4614.3521 | AZ100: 4263.9928 | BD100: =+F100 -> 909.013 | BE100: =+J100 -> 1051.901 | BF100: =+N100 -> 1507.921 | BG100: =+R100 -> 1691.581 | BH100: =+V100 -> 1685.8 | BI100: =+Z100 -> 3597.5 | BJ100: =+AD100 -> 3476.4 | BK100: =+AH100 -> 3502.4 | BL100: =+AL100 -> 3547.3 | BM100: =+AP100 -> 4659.505 | BN100: =+AT100 -> 4680.026 | BO100: =+AX100 -> 4614.3521 | BP100: =SUM(BP3)/365*BP170 -> 4855.034 | BQ100: =SUM(BQ3)/365*BQ170 -> 5042.3095 | BR100: =SUM(BR3)/365*BR170 -> 5234.3256 | BS100: =SUM(BS3)/365*BS170 -> 5419.3304
B101: Accounts receivable - sale of subsidiary | AM101: 0 | AN101: 0 | AO101: 0 | AP101: 1864.702 | AQ101: 1971.545 | AR101: 2513.056 | AS101: 0 | AT101: 169.1 | AU101: =+AT101 -> 169.1 | AV101: =+AU101 -> 169.1 | AW101: =+AV101 -> 169.1 | AX101: =+AW101 -> 169.1 | AZ101: 0 | BM101: =+AP101 -> 1864.702 | BN101: =+AT101 -> 169.1 | BO101: =+AX101 -> 169.1 | BP101: =+BO101 -> 169.1 | BQ101: =+BP101 -> 169.1 | BR101: =+BQ101 -> 169.1 | BS101: =+BR101 -> 169.1
B102: Estoques | C102: 979.315 | D102: 866.982 | E102: 1080.685 | F102: 963.675 | G102: 1082.982 | H102: 1039.286 | I102: 1024.286 | J102: 835.922 | K102: 847.929 | L102: 860.721 | M102: 1458.856 | N102: 1243.925 | O102: 1455.113 | P102: 1522.843 | Q102: 1616.847 | R102: 1364.672 | S102: 1535.41 | T102: 1621.098 | U102: 1781.9 | V102: 1430.6 | W102: 4040.7 | X102: 4481.3 | Y102: 5135.8 | Z102: 4544.3 | AA102: 5342.7 | AB102: 5243.3 | AC102: 5948 | AD102: 5403.5 | AE102: 5117.8 | AF102: 5367.4 | AG102: 5410.5 | AH102: 4516.9 | AI102: 4382.4 | AJ102: 4207.4 | AK102: 4362.9 | AL102: 3087.4 | AM102: 2275.127 | AN102: 2448.53 | AO102: 3013.297 | AP102: 2386.616 | AQ102: 2697.27 | AR102: 2844.981 | AS102: 3319.026 | AT102: 2965.607 | AU102: =-SUM(AR7:AU7)/365*AU171 -> 2261.8112 | AV102: =-SUM(AS7:AV7)/365*AV171 -> 2481.5483 | AW102: =-SUM(AT7:AW7)/365*AW171 -> 2831.9508 | AX102: =-SUM(AU7:AX7)/365*AX171 -> 3071.2017 | AZ102: 2911.7698 | BD102: =+F102 -> 963.675 | BE102: =+J102 -> 835.922 | BF102: =+N102 -> 1243.925 | BG102: =+R102 -> 1364.672 | BH102: =+V102 -> 1430.6 | BI102: =+Z102 -> 4544.3 | BJ102: =+AD102 -> 5403.5 | BK102: =+AH102 -> 4516.9 | BL102: =+AL102 -> 3087.4 | BM102: =+AP102 -> 2386.616 | BN102: =+AT102 -> 2965.607 | BO102: =+AX102 -> 3071.2017 | BP102: =-SUM(BP7)/365*BP171 -> 3153.5033 | BQ102: =-SUM(BQ7)/365*BQ171 -> 3275.6706 | BR102: =-SUM(BR7)/365*BR171 -> 3401.4871 | BS102: =-SUM(BS7)/365*BS171 -> 3522.7526
