Workbook

Sheet RESUMO
O2: =+TODAY() -> 46071
B3: REGIONAL (mln MXN) | C3: 2020 | D3: =+C3+1 -> 2021 | E3: =+D3+1 -> 2022 | F3: =+E3+1 -> 2023 | G3: =+F3+1 -> 2024 | H3: =+G3+1 -> 2025 | I3: =+H3+1 -> 2026 | J3: =+I3+1 -> 2027 | K3: =+J3+1 -> 2028 | ... R3: =+Q3+1 -> 2035 | T3: #VALUE!
B5: Gross Loan | C5: =+FAT!AM7 -> 110416 | D5: =+FAT!AN7 -> 117952 | E5: =+FAT!AO7 -> 136876 | F5: =+FAT!AP7 -> 155301 | G5: =+FAT!AQ7 -> 177176 | H5: =+FAT!AR7 -> 190842 | I5: =+FAT!AS7 -> 206164.96 | J5: =+FAT!AT7 -> 226042.93 | ... R5: =+FAT!BB7 -> 350896.08
B6: yoy | D6: =+D5/C5-1 -> 0.068250978 | E6: =+E5/D5-1 -> 0.16043814 | F6: =+F5/E5-1 -> 0.13461089 | G6: =+G5/F5-1 -> 0.1408555 | H6: =+H5/G5-1 -> 0.077132343 | I6: =+I5/H5-1 -> 0.080291332 | J6: =+J5/I5-1 -> 0.096417803 | K6: =+K5/J5-1 -> 0.062909369 | ... R6: =+R5/Q5-1 -> 0.05035676
B7: A Vencer | C7: =+FAT!AM9 -> 108864 | D7: =+FAT!AN9 -> 115817 | E7: =+FAT!AO9 -> 135100 | F7: =+FAT!AP9 -> 153248 | G7: =+FAT!AQ9 -> 174951 | H7: =+FAT!AR9 -> 188396 | I7: =+FAT!AS9 -> 203501.18 | J7: =+FAT!AT9 -> 222959.31 | ... R7: =+FAT!BB9 -> 344805.56
B8: Vencidos (NPL) | C8: =+FAT!AM10 -> 1552 | D8: =+FAT!AN10 -> 2135 | E8: =+FAT!AO10 -> 1776 | F8: =+FAT!AP10 -> 2053 | G8: =+FAT!AQ10 -> 2225 | H8: =+FAT!AR10 -> 2446 | I8: =+FAT!AS10 -> 2663.7783 | J8: =+FAT!AT10 -> 3083.6166 | ... R8: =+FAT!BB10 -> 6090.5186
B9: % portfolio | C9: =+C8/AVERAGE(B5:C5) -> 0.014055934 | D9: =+D8/AVERAGE(C5:D5) -> 0.018697891 | E9: =+E8/AVERAGE(D5:E5) -> 0.013938814 | F9: =+F8/AVERAGE(E5:F5) -> 0.014053125 | G9: =+G8/AVERAGE(F5:G5) -> 0.013384384 | H9: =+H8/AVERAGE(G5:H5) -> 0.013292828 | I9: =+I8/AVERAGE(H5:I5) -> 0.013419303 | J9: =+J8/AVERAGE(I5:J5) -> 0.014269136 | ... R9: =+R8/AVERAGE(Q5:R5) -> 0.017783333
B11: Net Interest Rev | C11: =+FAT!AM137 -> 7512 | D11: =+FAT!AN137 -> 7568 | E11: =+FAT!AO137 -> 10361 | F11: =+FAT!AP137 -> 12386 | G11: =+FAT!AQ137 -> 14377 | H11: =+FAT!AR137 -> 15465 | I11: =+FAT!AS137 -> 15792.26 | J11: =+FAT!AT137 -> 16840.707 | ... R11: =+FAT!BB137 -> 27721.717 | T11: share price | U11: {=+_FV(T3,"Price")} -> 162.48
B12: yoy | D12: =+D11/C11-1 -> 0.0074547391 | E12: =+E11/D11-1 -> 0.36905391 | F12: =+F11/E11-1 -> 0.19544446 | G12: =+G11/F11-1 -> 0.160746 | H12: =+H11/G11-1 -> 0.075676428 | I12: =+I11/H11-1 -> 0.021161322 | J12: =+J11/I11-1 -> 0.06638997 | K12: =+K11/J11-1 -> 0.086613231 | ... R12: =+R11/Q11-1 -> 0.054268164 | T12: Shares | U12: {=+_FV(T3,"Shares outstanding",TRUE)/1000000} -> 327.9313 | V12: =+U12*U11 -> 53282.278
B13: NIM | C13: =+FAT!AM142 -> 0.056879466 | D13: =+FAT!AN142 -> 0.052181048 | E13: =+FAT!AO142 -> 0.060077177 | F13: =+FAT!AP142 -> 0.058380743 | G13: =+FAT!AQ142 -> 0.06576973 | H13: =+FAT!AR142 -> 0.064616569 | I13: =+FAT!AS142 -> 0.061138133 | J13: =+FAT!AT142 -> 0.06042198 | ... R13: =+FAT!BB142 -> 0.058370491 | T13: TP price | U13: =8*H35/H41 -> 161.43625
B15: Var yoy | D15: =+(D13/C13-1)*10000 -> -826.03067 | E15: =+(E13/D13-1)*10000 -> 1513.2178 | F15: =+(F13/E13-1)*10000 -> -282.37577 | G15: =+(G13/F13-1)*10000 -> 1265.655 | H15: =+(H13/G13-1)*10000 -> -175.33308 | I15: =+(I13/H13-1)*10000 -> -538.31956
B16: TIIE | D16: =+macro!DI51 -> 0.0571 | E16: =+macro!DJ51 -> 0.105 | F16: =+macro!DK51 -> 0.115025 | G16: =+macro!DL51 -> 0.10245 | H16: =+macro!DM51 -> 0.075 | I16: =+macro!DN51 -> 0.068
B17: Var yoy | D17: =+(D16/C16-1)*10000 -> #DIV/0! | E17: =+(E16/D16-1)*10000 -> 8388.7916 | F17: =+(F16/E16-1)*10000 -> 954.7619 | G17: =+(G16/F16-1)*10000 -> -1093.2406 | H17: =+(H16/G16-1)*10000 -> -2679.3558 | I17: =+(I16/H16-1)*10000 -> -933.33333
B18: dif | D18: =+D15/D17*100 -> #DIV/0! | E18: =+E15/E17*100 -> 18.038567 | F18: =+F15/F17*100 -> -29.575517 | G18: =+G15/G17*100 -> -115.77094 | H18: =+H15/H17*100 -> 6.5438523 | I18: =+I15/I17*100 -> 57.677096
B20: Other Revenues | C20: =+FAT!AM164 -> 2649 | D20: =+FAT!AN164 -> 3092 | E20: =+FAT!AO164 -> 2851 | F20: =+FAT!AP164 -> 2613 | G20: =+FAT!AQ164 -> 3041 | H20: =+FAT!AR164 -> 3231 | I20: =+FAT!AS164 -> 3563.0088 | J20: =+FAT!AT164 -> 3869.2195 | ... R20: =+FAT!BB164 -> 5841.1515
B21: yoy | D21: =+D20/C20-1 -> 0.16723292 | E21: =+E20/D20-1 -> -0.077943079 | F21: =+F20/E20-1 -> -0.083479481 | G21: =+G20/F20-1 -> 0.1637964 | H21: =+H20/G20-1 -> 0.062479448 | I21: =+I20/H20-1 -> 0.10275728 | J21: =+J20/I20-1 -> 0.085941608 | K21: =+K20/J20-1 -> 0.059442913 | ... R21: =+R20/Q20-1 -> 0.051940993 | T21: ROE1 | U21: =+AVERAGE(H48:R48) -> 0.1465045
B23: Provisions | C23: =+FAT!AM160 -> -1064 | D23: =+FAT!AN160 -> -853 | E23: =+FAT!AO160 -> -444 | F23: =+FAT!AP160 -> -1270 | G23: =+FAT!AQ160 -> -1648 | H23: =+FAT!AR160 -> -1757 | I23: =+FAT!AS160 -> -1959.5548 | J23: =+FAT!AT160 -> -2014.9948 | ... R23: =+FAT!BB160 -> -3251.4327 | T23: ROE2 | U23: 0.15
B24: % portfolio | C24: =+C23/AVERAGE(B5:C5) -> -0.0096362846 | D24: =+D23/AVERAGE(C5:D5) -> -0.0074703987 | E24: =+E23/AVERAGE(D5:E5) -> -0.0034847034 | F24: =+F23/AVERAGE(E5:F5) -> -0.0086933605 | G24: =+G23/AVERAGE(F5:G5) -> -0.0099134677 | H24: =+H23/AVERAGE(G5:H5) -> -0.009548446 | I24: =+I23/AVERAGE(H5:I5) -> -0.0098716396 | J24: =+J23/AVERAGE(I5:J5) -> -0.0093241928 | ... R24: =+R23/AVERAGE(Q5:R5) -> -0.0094936593
B26: Other Expenses | C26: =+FAT!AM183 -> -4747 | D26: =+FAT!AN183 -> -4857 | E26: =+FAT!AO183 -> -5369.5 | F26: =+FAT!AP183 -> -6139 | G26: =+FAT!AQ183 -> -6910 | H26: =+FAT!AR183 -> -7896.5 | I26: =+FAT!AS183 -> -8578.7002 | J26: =+FAT!AT183 -> -8698.0681 | ... R26: =+FAT!BB183 -> -11281.06 | T26: G1 | U26: 0.02
B27: yoy | D27: =+D26/C26-1 -> 0.02317253 | E27: =+E26/D26-1 -> 0.10551781 | F27: =+F26/E26-1 -> 0.14330943 | G27: =+G26/F26-1 -> 0.12559049 | H27: =+H26/G26-1 -> 0.14276411 | I27: =+I26/H26-1 -> 0.086392736 | J27: =+J26/I26-1 -> 0.013914446 | K27: =+K26/J26-1 -> 0.034460836 | ... R27: =+R26/Q26-1 -> 0.032970452 | T27: ROE1 | U27: =+AVERAGE(H54:R54) -> #DIV/0!
B28: Ratio eficiencia | C28: =+C26/(C11+C20) -> -0.46717843 | D28: =+D26/(D11+D20) -> -0.45562852 | E28: =+E26/(E11+E20) -> -0.40641084 | F28: =+F26/(F11+F20) -> -0.40929395 | G28: =+G26/(G11+G20) -> -0.39671604 | H28: =+H26/(H11+H20) -> -0.42236307 | I28: =+I26/(I11+I20) -> -0.443223 | J28: =+J26/(J11+J20) -> -0.41999511 | ... R28: =+R26/(R11+R20) -> -0.33611727 | T28: G2 | U28: 0.02
B30: EBT | C30: =+FAT!AM210 -> 4780 | D30: =+FAT!AN210 -> 5390 | E30: =+FAT!AO210 -> 7398.5 | F30: =+FAT!AP210 -> 7590 | G30: =+FAT!AQ210 -> 8860 | H30: =+FAT!AR210 -> 9042.5 | I30: =+FAT!AS210 -> 8817.0136 | J30: =+FAT!AT210 -> 9996.864 | ... R30: =+FAT!BB210 -> 19030.376 | T30: Ke | U30: =+(U36+U33)+(U38*U37) -> 0.135
T31: N (moat) | U31: 5
B32: Tax | C32: =+FAT!AM212 -> -1180 | D32: =+FAT!AN212 -> -1206 | E32: =+FAT!AO212 -> -1571 | F32: =+FAT!AP212 -> -1918 | G32: =+FAT!AQ212 -> -2310 | H32: =+FAT!AR212 -> -2425 | I32: =+FAT!AS212 -> -2424.6787 | J32: =+FAT!AT212 -> -2749.1376 | ... R32: =+FAT!BB212 -> -5233.3535
B33: rate | C33: =+C32/C30 -> -0.24686192 | D33: =+D32/D30 -> -0.22374768 | E33: =+E32/E30 -> -0.21234034 | F33: =+F32/F30 -> -0.25270092 | G33: =+G32/G30 -> -0.26072235 | H33: =+H32/H30 -> -0.26817805 | I33: =+I32/I30 -> -0.275 | J33: =+J32/J30 -> -0.275 | ... R33: =+R32/R30 -> -0.275 | T33: INFL | U33: 0.04
T34: GDP Perp | U34: 0.02
B35: Net Income | C35: =+FAT!AM217 -> 3619 | D35: =+FAT!AN217 -> 4202 | E35: =+FAT!AO217 -> 5820.5 | F35: =+FAT!AP217 -> 5673 | G35: =+FAT!AQ217 -> 6519 | H35: =+FAT!AR217 -> 6617.5 | I35: =+FAT!AS217 -> 6392.3348 | J35: =+FAT!AT217 -> 7247.7264 | ... R35: =+FAT!BB217 -> 13797.023 | T35: Aj. G2 | U35: 0
B36: yoy | D36: =+D35/C35-1 -> 0.16109422 | E36: =+E35/D35-1 -> 0.38517373 | F36: =+F35/E35-1 -> -0.025341466 | G36: =+G35/F35-1 -> 0.14912745 | H36: =+H35/G35-1 -> 0.015109679 | I36: =+I35/H35-1 -> -0.034025716 | J36: =+J35/I35-1 -> 0.1338152 | K36: =+K35/J35-1 -> 0.11965909 | ... R36: =+R35/Q35-1 -> 0.06737007 | T36: BNTNB | U36: 0.05
T37: ERP | U37: 0.045
B38: MULTIPLOS | C38: =+C$3 -> 2020 | D38: =+D$3 -> 2021 | E38: =+E$3 -> 2022 | F38: =+F$3 -> 2023 | G38: =+G$3 -> 2024 | H38: =+H$3 -> 2025 | I38: =+I$3 -> 2026 | J38: =+J$3 -> 2027 | ... R38: =+R$3 -> 2035 | T38: Beta | U38: 1
B39: Mkt Cap | C39: {=+_FV($T$3,"Market cap",TRUE)/1000000} -> 53282.278 | D39: {=+_FV($T$3,"Market cap",TRUE)/1000000} -> 53282.278 | E39: {=+_FV($T$3,"Market cap",TRUE)/1000000} -> 53282.278 | F39: {=+_FV($T$3,"Market cap",TRUE)/1000000} -> 53282.278 | G39: {=+_FV($T$3,"Market cap",TRUE)/1000000} -> 53282.278 | H39: {=+_FV($T$3,"Market cap",TRUE)/1000000} -> 53282.278 | I39: {=+_FV($T$3,"Market cap",TRUE)/1000000} -> 53282.278 | J39: {=+_FV($T$3,"Market cap",TRUE)/1000000} -> 53282.278 | ... R39: {=+_FV($T$3,"Market cap",TRUE)/1000000} -> 53282.278
T40: P/E Target | U40: =+(((1-U26/U21)*(1+U26)*(1-(((1+U26)^U31)/((1+U30)^U31))))/(U30-U26))+(((1-U28/U23)*((1+U26)^U31)*(1+U28))/((U30-U28)*((1+U30)^U31))) -> 7.6752797
B41: Shares | C41: {=+_FV($T$3,"Shares outstanding",TRUE)/1000000} -> 327.9313 | D41: {=+_FV($T$3,"Shares outstanding",TRUE)/1000000} -> 327.9313 | E41: {=+_FV($T$3,"Shares outstanding",TRUE)/1000000} -> 327.9313 | F41: {=+_FV($T$3,"Shares outstanding",TRUE)/1000000} -> 327.9313 | G41: {=+_FV($T$3,"Shares outstanding",TRUE)/1000000} -> 327.9313 | H41: {=+_FV($T$3,"Shares outstanding",TRUE)/1000000} -> 327.9313 | I41: {=+_FV($T$3,"Shares outstanding",TRUE)/1000000} -> 327.9313 | J41: {=+_FV($T$3,"Shares outstanding",TRUE)/1000000} -> 327.9313 | ... R41: {=+_FV($T$3,"Shares outstanding",TRUE)/1000000} -> 327.9313 | T41: vs 2025 | U41: =+U40/H46-1 -> -0.046753147
B43: EPS | C43: =+C35/C41 -> 11.035848 | D43: =+D35/D41 -> 12.813659 | E43: =+E35/E41 -> 17.749144 | F43: =+F35/F41 -> 17.299355 | G43: =+G35/G41 -> 19.879164 | H43: =+H35/H41 -> 20.179532 | I43: =+I35/I41 -> 19.492908 | J43: =+J35/J41 -> 22.101356 | ... R43: =+R35/R41 -> 42.072906
B45: P/BV | C45: =+C39/PROJ!AM67 -> 2.4011842 | D45: =+D39/PROJ!AN67 -> 2.1829842 | E45: =+E39/PROJ!AO67 -> 2.1111926 | F45: =+F39/PROJ!AP67 -> 1.8828991 | G45: =+G39/PROJ!AQ67 -> 1.6441088 | H45: =+H39/PROJ!AR67 -> 1.4189215 | I45: =+I39/PROJ!AS67 -> 1.2698854 | J45: =+J39/PROJ!AT67 -> 1.1267525 | ... R45: =+R39/PROJ!BB67 -> 0.48247619
B46: P/E | C46: =+C39/C35 -> 14.722928 | D46: =+D39/D35 -> 12.680218 | E46: =+E39/E35 -> 9.1542441 | F46: =+F39/F35 -> 9.3922576 | G46: =+G39/G35 -> 8.1733821 | H46: =+H39/H35 -> 8.0517231 | I46: =+I39/I35 -> 8.335339 | J46: =+J39/J35 -> 7.3515851 | ... R46: =+R39/R35 -> 3.8618678
B48: ROE | C48: =+PROJ!AM75 -> 0.16937135 | D48: =+PROJ!AN75 -> 0.17947103 | E48: =+PROJ!AO75 -> 0.24941348 | F48: =+PROJ!AP75 -> 0.20827903 | G48: =+PROJ!AQ75 -> 0.2094256 | H48: =+PROJ!AR75 -> 0.18682321 | I48: =+PROJ!AS75 -> 0.15935678 | J48: =+PROJ!AT75 -> 0.1532666 | ... R48: =+PROJ!BB75 -> 0.12493338
B50: div yield | G50: =+PROJ!AQ72/RESUMO!G39 -> 0.023387496 | H50: =+PROJ!AR72/RESUMO!H39 -> 0.030587093 | I50: =+PROJ!AS72/RESUMO!I39 -> 0.037259105 | J50: =+PROJ!AT72/RESUMO!J39 -> 0.035991338 | K50: =+PROJ!AU72/RESUMO!K39 -> 0.040807526 | L50: =+PROJ!AV72/RESUMO!L39 -> 0.045690517 | M50: =+PROJ!AW72/RESUMO!M39 -> 0.04987724 | N50: =+PROJ!AX72/RESUMO!N39 -> 0.054470668 | ... R50: =+PROJ!BB72/RESUMO!R39 -> 0.072779461

Sheet FAT
A1: IPC | B1: =+PROJ!B1 -> 0.004426325 | C1: =+PROJ!C1 -> -0.0017105416 | D1: =+PROJ!D1 -> 0.0062246488 | E1: =+PROJ!E1 -> 0.019164534 | F1: =+PROJ!F1 -> 0.0085336153 | G1: =+PROJ!G1 -> -0.00088919673 | H1: =+PROJ!H1 -> 0.012843934 | I1: =+PROJ!I1 -> 0.010701667 | ... AG1: =+PROJ!AG1 -> 0.013734568 | AI1: 0.013734568 | AL1: =+PROJ!AL1 -> 0.02828577 | AM1: =+PROJ!AM1 -> 0.031500746 | AN1: =+PROJ!AN1 -> 0.073551079 | AO1: =+PROJ!AO1 -> 0.078170287 | AP1: =+PROJ!AP1 -> 0.046608896 | AQ1: =+PROJ!AQ1 -> 0.042123394 | AR1: =+PROJ!AR1 -> 0.035 | AS1: =+PROJ!AS1 -> 0.035 | ... BA1: =+PROJ!BA1 -> 0.035 | BB1: =+BA1 -> 0.035
A2: MX POLICY RATE | B2: =+PROJ!B2 -> 0.08515 | C2: =+PROJ!C2 -> 0.084887 | D2: =+PROJ!D2 -> 0.080275 | E2: =+PROJ!E2 -> #VALUE! | F2: =+PROJ!F2 -> #VALUE! | G2: =+PROJ!G2 -> 0.052843 | H2: =+PROJ!H2 -> 0.0475 | I2: =+PROJ!I2 -> 0.0425 | ... AG2: =+PROJ!AG2 -> 0.068 | AI2: 0.075 | AL2: =+PROJ!AL2 -> #VALUE! | AM2: =+PROJ!AM2 -> 0.0425 | AN2: =+PROJ!AN2 -> 0.0571 | AO2: =+PROJ!AO2 -> 0.105 | AP2: =+PROJ!AP2 -> 0.115025 | AQ2: =+PROJ!AQ2 -> 0.10245 | AR2: =+PROJ!AR2 -> 0.075 | AS2: =+PROJ!AS2 -> 0.068 | ... BA2: =+PROJ!BA2 -> 0.068 | BB2: =+BA2 -> 0.068
AL3: 43830 | AM3: =+EOMONTH(AL3,12) -> 44196 | AN3: =+EOMONTH(AM3,12) -> 44561 | AO3: =+EOMONTH(AN3,12) -> 44926 | AP3: =+EOMONTH(AO3,12) -> 45291 | AQ3: =+EOMONTH(AP3,12) -> 45657 | AR3: =+EOMONTH(AQ3,12) -> 46022 | AS3: =+EOMONTH(AR3,12) -> 46387
A4: REGIONAL (mln mex) | B4: 43555 | C4: =+EOMONTH(B4,3) -> 43646 | D4: =+EOMONTH(C4,3) -> 43738 | E4: =+EOMONTH(D4,3) -> 43830 | F4: =+EOMONTH(E4,3) -> 43921 | G4: =+EOMONTH(F4,3) -> 44012 | H4: =+EOMONTH(G4,3) -> 44104 | I4: =+EOMONTH(H4,3) -> 44196 | J4: =+EOMONTH(I4,3) -> 44286 | ... AG4: =+EOMONTH(AF4,3) -> 46387 | AI4: 46022 | AL4: 2019 | AM4: =+AL4+1 -> 2020 | AN4: =+AM4+1 -> 2021 | AO4: =+AN4+1 -> 2022 | AP4: =+AO4+1 -> 2023 | AQ4: =+AP4+1 -> 2024 | AR4: =+AQ4+1 -> 2025 | AS4: =+AR4+1 -> 2026 | AT4: =+AS4+1 -> 2027 | ... BB4: =+BA4+1 -> 2035
A5: NET LOAN PORTFOLIO | B5: =+B7+B12+B13+B14 -> 100362 | C5: =+C7+C12+C13+C14 -> 104484 | D5: =+D7+D12+D13+D14 -> 105991 | E5: =+E7+E12+E13+E14 -> 105777 | F5: =+F7+F12+F13+F14 -> 111108 | G5: =+G7+G12+G13+G14 -> 109380 | H5: =+H7+H12+H13+H14 -> 109040 | I5: =+I7+I12+I13+I14 -> 107985 | ... AH5: =+AH7+AH12+AH13+AH14 -> 0 | AI5: 189518.56 | AJ5: =+AB5/AI5-1 -> -0.024797364 | AL5: =+AL7+AL12+AL13+AL14 -> 105777 | AM5: =+AM7+AM12+AM13+AM14 -> 107985 | AN5: =+AN7+AN12+AN13+AN14 -> 115218 | AO5: =+AO7+AO12+AO13+AO14 -> 134094 | AP5: =+AP7+AP12+AP13+AP14 -> 152171 | AQ5: =+AQ7+AQ12+AQ13+AQ14 -> 174115 | AR5: =+AR7+AR12+AR13+AR14 -> 187878 | AS5: =+AS7+AS12+AS13+AS14 -> 202742.41 | ... BB5: =+BB7+BB12+BB13+BB14 -> 348403.06
A7: Total Gross Loans | B7: =+B9+B10 -> 102244 | C7: =+C9+C10 -> 106344 | D7: =+D9+D10 -> 107965 | E7: =+E9+E10 -> 107933 | F7: =+F9+F10 -> 113373 | G7: =+G9+G10 -> 111569 | H7: =+H9+H10 -> 111149 | I7: =+I9+I10 -> 110416 | ... AG7: =+AG9+AG10 -> 206164.96 | AI7: 192858.96 | AJ7: =+AB7/AI7-1 -> -0.024675836 | AL7: =+AL9+AL10 -> 107933 | AM7: =+AM9+AM10 -> 110416 | AN7: =+AN9+AN10 -> 117952 | AO7: =+AO9+AO10 -> 136876 | AP7: =+AP9+AP10 -> 155301 | AQ7: =+AQ9+AQ10 -> 177176 | AR7: =+AR9+AR10 -> 190842 | AS7: =+AS9+AS10 -> 206164.96 | ... BB7: =+BB9+BB10 -> 350896.08
A8: yoy | F8: =+F7/B7-1 -> 0.10884746 | G8: =+G7/C7-1 -> 0.049133002 | H8: =+H7/D7-1 -> 0.029491039 | I8: =+I7/E7-1 -> 0.023005012 | J8: =+J7/F7-1 -> -0.0051334974 | K8: =+K7/G7-1 -> 0.025992883 | L8: =+L7/H7-1 -> 0.037031372 | M8: =+M7/I7-1 -> 0.068250978 | ... AG8: =+AG7/AC7-1 -> 0.080291332 | AI8: 0.088516255 | AM8: =+AM7/AL7-1 -> 0.023005012 | AN8: =+AN7/AM7-1 -> 0.068250978 | AO8: =+AO7/AN7-1 -> 0.16043814 | AP8: =+AP7/AO7-1 -> 0.13461089 | AQ8: =+AQ7/AP7-1 -> 0.1408555 | AR8: =+AR7/AQ7-1 -> 0.077132343 | AS8: =+AS7/AR7-1 -> 0.080291332 | AT8: =+AT7/AS7-1 -> 0.096417803 | ... BB8: =+BB7/BA7-1 -> 0.05035676
A9: STAGE 1 & 2 | B9: =+B19+B28 -> 100438 | C9: =+C19+C28 -> 104573 | D9: =+D19+D28 -> 106243 | E9: =+E19+E28 -> 106015 | F9: =+F19+F28 -> 111306 | G9: =+G19+G28 -> 109850 | H9: =+H19+H28 -> 109787 | I9: =+I19+I28 -> 108864 | ... AG9: =+AG19+AG28 -> 203501.18 | AI9: 189560.97 | AL9: =+SUMIFS($B9:AF9,$B$4:AF$4,"="&AL$3) -> 106015 | AM9: =+SUMIFS($B9:AG9,$B$4:AG$4,"="&AM$3) -> 108864 | AN9: =+SUMIFS($B9:AG9,$B$4:AG$4,"="&AN$3) -> 115817 | AO9: =+SUMIFS($B9:AG9,$B$4:AG$4,"="&AO$3) -> 135100 | AP9: =+SUMIFS($B9:AG9,$B$4:AG$4,"="&AP$3) -> 153248 | AQ9: =+SUMIFS($B9:AG9,$B$4:AG$4,"="&AQ$3) -> 174951 | AR9: =+SUMIFS($B9:AG9,$B$4:AG$4,"="&AR$3) -> 188396 | AS9: =+SUMIFS($B9:$AG9,$B$4:$AG$4,"="&AS$3) -> 203501.18 | AT9: =+AT19+AT28 -> 222959.31 | AU9: =+AU19+AU28 -> 236823.55 | AV9: =+AV19+AV28 -> 251586.53 | AW9: =+AW19+AW28 -> 267308.86 | AX9: =+AX19+AX28 -> 284055.45 | AY9: =+AY19+AY28 -> 298047.8 | AZ9: =+AZ19+AZ28 -> 312804.44 | BA9: =+BA19+BA28 -> 328373.24 | BB9: =+BB19+BB28 -> 344805.56
A10: STAGE 3 | B10: =+B42+B45 -> 1806 | C10: =+C42+C45 -> 1771 | D10: =+D42+D45 -> 1722 | E10: =+E42+E45 -> 1918 | F10: =+F42+F45 -> 2067 | G10: =+G42+G45 -> 1719 | H10: =+H42+H45 -> 1362 | I10: =+I42+I45 -> 1552 | ... AB10: =+AB42+AB45 -> 3064 | AC10: =+AC56 -> 2446 | AD10: =+AD56 -> 2498.1249 | AE10: =+AE56 -> 2579.6557 | AF10: =+AF56 -> 2622.3429 | AG10: =+AG56 -> 2663.7783 | AI10: 3297.986 | AL10: =+SUMIFS($B10:AF10,$B$4:AF$4,"="&AL$3) -> 1918 | AM10: =+SUMIFS($B10:AG10,$B$4:AG$4,"="&AM$3) -> 1552 | AN10: =+SUMIFS($B10:AG10,$B$4:AG$4,"="&AN$3) -> 2135 | AO10: =+SUMIFS($B10:AG10,$B$4:AG$4,"="&AO$3) -> 1776 | AP10: =+SUMIFS($B10:AG10,$B$4:AG$4,"="&AP$3) -> 2053 | AQ10: =+SUMIFS($B10:AG10,$B$4:AG$4,"="&AQ$3) -> 2225 | AR10: =+SUMIFS($B10:AG10,$B$4:AG$4,"="&AR$3) -> 2446 | AS10: =+SUMIFS($B10:$AG10,$B$4:$AG$4,"="&AS$3) -> 2663.7783 | AT10: =+AT56 -> 3083.6166 | AU10: =+AU56 -> 3439.5962 | AV10: =+AV56 -> 3700.1881 | AW10: =+AW56 -> 4127.4541 | AX10: =+AX56 -> 4549.1772 | AY10: =+AY56 -> 4942.4458 | AZ10: =+AZ56 -> 5306.8873 | BA10: =+BA56 -> 5699.9949 | BB10: =+BB56 -> 6090.5186
A12: Allowances | B12: =-B69 -> -2187 | C12: =-C69 -> -2319 | D12: =-D69 -> -2231 | E12: =-E69 -> -2342 | F12: =-F69 -> -2447 | G12: =-G69 -> -2369 | H12: =-H69 -> -2307 | I12: =-I69 -> -2626 | ... AG12: =-AG69 -> -4189.545 | AI12: -4049.3953 | AJ12: =+AB12/AI12-1 -> -0.014667707 | AL12: =+SUMIFS($B12:AF12,$B$4:AF$4,"="&AL$3) -> -2342 | AM12: =+SUMIFS($B12:AG12,$B$4:AG$4,"="&AM$3) -> -2626 | AN12: =+SUMIFS($B12:AG12,$B$4:AG$4,"="&AN$3) -> -2827 | AO12: =+SUMIFS($B12:AG12,$B$4:AG$4,"="&AO$3) -> -3055 | AP12: =+SUMIFS($B12:AG12,$B$4:AG$4,"="&AP$3) -> -3426 | AQ12: =+SUMIFS($B12:AG12,$B$4:AG$4,"="&AQ$3) -> -3653 | AR12: =+SUMIFS($B12:AG12,$B$4:AG$4,"="&AR$3) -> -3731 | AS12: =+SUMIFS($B12:$AG12,$B$4:$AG$4,"="&AS$3) -> -4189.545 | AT12: =-AT69 -> -4435.9287 | AU12: =-AU69 -> -4541.193 | AV12: =-AV69 -> -4543.139 | AW12: =-AW69 -> -4591.5907 | AX12: =-AX69 -> -4465.6921 | AY12: =-AY69 -> -4213.418 | AZ12: =-AZ69 -> -3844.7111 | BA12: =-BA69 -> -3389.8961 | BB12: =-BB69 -> -2813.0216
A13: Other receivables | B13: 305 | C13: 459 | D13: 257 | E13: 186 | F13: 182 | G13: 180 | H13: 198 | I13: 195 | J13: 188 | K13: 182 | L13: 174 | M13: 93 | N13: 91 | O13: 89 | P13: 53 | Q13: 52 | R13: 51 | S13: 46 | T13: 45 | U13: 44 | V13: 43 | W13: 42 | X13: 41 | Y13: 40 | Z13: 39 | AA13: 38 | AB13: 38 | AC13: 36 | AD13: =+AC13 -> 36 | AE13: =+AD13 -> 36 | AF13: =+AE13 -> 36 | AG13: =+AF13 -> 36 | AI13: 38 | AL13: =+SUMIFS($B13:AF13,$B$4:AF$4,"="&AL$3) -> 186 | AM13: =+SUMIFS($B13:AG13,$B$4:AG$4,"="&AM$3) -> 195 | AN13: =+SUMIFS($B13:AG13,$B$4:AG$4,"="&AN$3) -> 93 | AO13: =+SUMIFS($B13:AG13,$B$4:AG$4,"="&AO$3) -> 52 | AP13: =+SUMIFS($B13:AG13,$B$4:AG$4,"="&AP$3) -> 44 | AQ13: =+SUMIFS($B13:AG13,$B$4:AG$4,"="&AQ$3) -> 40 | AR13: =+SUMIFS($B13:AG13,$B$4:AG$4,"="&AR$3) -> 36 | AS13: =+SUMIFS($B13:$AG13,$B$4:$AG$4,"="&AS$3) -> 36 | AT13: 45 | AU13: 45 | AV13: 45 | AW13: 45 | AX13: 45 | AY13: 45 | AZ13: 45 | BA13: 45 | BB13: 45
A14: Deferred Items | N14: 240 | O14: 229 | P14: 252 | Q14: 221 | R14: 114 | S14: 170 | T14: 238 | U14: 252 | V14: 280 | W14: 313 | X14: 332 | Y14: 552 | Z14: 597 | AA14: 634 | AB14: 671 | AC14: 731 | AD14: =+AC14 -> 731 | AE14: =+AD14 -> 731 | AF14: =+AE14 -> 731 | AG14: =+AF14 -> 731 | AI14: 671 | AL14: =+SUMIFS($B14:AF14,$B$4:AF$4,"="&AL$3) -> 0 | AM14: =+SUMIFS($B14:AG14,$B$4:AG$4,"="&AM$3) -> 0 | AN14: =+SUMIFS($B14:AG14,$B$4:AG$4,"="&AN$3) -> 0 | AO14: =+SUMIFS($B14:AG14,$B$4:AG$4,"="&AO$3) -> 221 | AP14: =+SUMIFS($B14:AG14,$B$4:AG$4,"="&AP$3) -> 252 | AQ14: =+SUMIFS($B14:AG14,$B$4:AG$4,"="&AQ$3) -> 552 | AR14: =+SUMIFS($B14:AG14,$B$4:AG$4,"="&AR$3) -> 731 | AS14: =+SUMIFS($B14:$AG14,$B$4:$AG$4,"="&AS$3) -> 731 | AT14: 275 | AU14: 275 | AV14: 275 | AW14: 275 | AX14: 275 | AY14: 275 | AZ14: 275 | BA14: 275 | BB14: 275
AQ15: =+AQ5/AP5-1 -> 0.14420619 | AR15: =+AR5/AQ5-1 -> 0.079045458 | AS15: =+AS5/AR5-1 -> 0.079117371
A16: LOAN BREAKDOWN STAGE 1&2
A17: MORTGAGE | B17: 10648 | C17: 10920 | D17: 10998 | E17: 11144 | F17: 11061 | G17: 11046 | H17: 11272 | I17: 11218 | J17: 11186 | K17: 11319 | L17: 11382 | M17: 11513 | N17: 11647 | O17: 11814 | P17: 12255 | Q17: 12778 | R17: 13139 | S17: 13678 | T17: 14056 | U17: 14526 | V17: =14270+516 -> 14786 | W17: =14842+517 -> 15359 | X17: =488+15236 -> 15724 | Y17: =15585+533 -> 16118 | Z17: =15844+543 -> 16387 | AA17: =16086+589 -> 16675 | AB17: =16515+566 -> 17081 | AC17: =16802+532 -> 17334 | AD17: =+Z17*(1+AD21) -> 17697.96 | AE17: =+AA17*(1+AE21) -> 18009 | AF17: =+AB17*(1+AF21) -> 18447.48 | AG17: =+AC17*(1+AG21) -> 18720.72 | AI17: 17407.44 | AL17: =+SUMIFS($B17:AF17,$B$4:AF$4,"="&AL$3) -> 11144 | AM17: =+SUMIFS($B17:AG17,$B$4:AG$4,"="&AM$3) -> 11218 | AN17: =+SUMIFS($B17:AG17,$B$4:AG$4,"="&AN$3) -> 11513 | AO17: =+SUMIFS($B17:AG17,$B$4:AG$4,"="&AO$3) -> 12778 | AP17: =+SUMIFS($B17:AG17,$B$4:AG$4,"="&AP$3) -> 14526 | AQ17: =+SUMIFS($B17:AG17,$B$4:AG$4,"="&AQ$3) -> 16118 | AR17: =+SUMIFS($B17:AG17,$B$4:AG$4,"="&AR$3) -> 17334 | AS17: =+SUMIFS($B17:$AG17,$B$4:$AG$4,"="&AS$3) -> 18720.72 | AT17: =+AS17*(1+AT21) -> 20218.378 | AU17: =+AT17*(1+AU21) -> 21431.48 | AV17: =+AU17*(1+AV21) -> 22717.369 | AW17: =+AV17*(1+AW21) -> 24080.411 | AX17: =+AW17*(1+AX21) -> 25525.236 | AY17: =+AX17*(1+AY21) -> 26673.872 | AZ17: =+AY17*(1+AZ21) -> 27874.196 | BA17: =+AZ17*(1+BA21) -> 29128.535 | BB17: =+BA17*(1+BB21) -> 30439.319
A18: CONSUMER | B18: 3785 | C18: 4148 | D18: 4415 | E18: 4609 | F18: 4757 | G18: 4668 | H18: 5001 | I18: 5229 | J18: 5353 | K18: 5637 | L18: 5978 | M18: 6412 | N18: 6861 | O18: 7423 | P18: 8101 | Q18: 9472 | R18: 10147 | S18: 11076 | T18: 11500 | U18: 11801 | V18: =11355+328 -> 11683 | W18: =338+11478 -> 11816 | X18: =316+11699 -> 12015 | Y18: =12069+314 -> 12383 | Z18: =12129+331 -> 12460 | AA18: =12599+326 -> 12925 | AB18: =12935+341 -> 13276 | AC18: =13475+344 -> 13819 | AD18: =+Z18*(1+AD22) -> 13332.2 | AE18: =+AA18*(1+AE22) -> 13959 | AF18: =+AB18*(1+AF22) -> 14603.6 | AG18: =+AC18*(1+AG22) -> 15200.9 | AI18: 13373.64 | AL18: =+SUMIFS($B18:AF18,$B$4:AF$4,"="&AL$3) -> 4609 | AM18: =+SUMIFS($B18:AG18,$B$4:AG$4,"="&AM$3) -> 5229 | AN18: =+SUMIFS($B18:AG18,$B$4:AG$4,"="&AN$3) -> 6412 | AO18: =+SUMIFS($B18:AG18,$B$4:AG$4,"="&AO$3) -> 9472 | AP18: =+SUMIFS($B18:AG18,$B$4:AG$4,"="&AP$3) -> 11801 | AQ18: =+SUMIFS($B18:AG18,$B$4:AG$4,"="&AQ$3) -> 12383 | AR18: =+SUMIFS($B18:AG18,$B$4:AG$4,"="&AR$3) -> 13819 | AS18: =+SUMIFS($B18:$AG18,$B$4:$AG$4,"="&AS$3) -> 15200.9 | AT18: =+AS18*(1+AT22) -> 16720.99 | AU18: =+AT18*(1+AU22) -> 18393.089 | AV18: =+AU18*(1+AV22) -> 20232.398 | AW18: =+AV18*(1+AW22) -> 22255.638 | AX18: =+AW18*(1+AX22) -> 24481.201 | AY18: =+AX18*(1+AY22) -> 26929.322 | AZ18: =+AY18*(1+AZ22) -> 29622.254 | BA18: =+AZ18*(1+BA22) -> 32584.479 | BB18: =+BA18*(1+BB22) -> 35842.927
A19: TOTAL INDIVUDUALS | B19: =+B17+B18 -> 14433 | C19: =+C17+C18 -> 15068 | D19: =+D17+D18 -> 15413 | E19: =+E17+E18 -> 15753 | F19: =+F17+F18 -> 15818 | G19: =+G17+G18 -> 15714 | H19: =+H17+H18 -> 16273 | I19: =+I17+I18 -> 16447 | ... AG19: =+AG17+AG18 -> 33921.62 | AI19: 30781.08 | AL19: =+SUMIFS($B19:AF19,$B$4:AF$4,"="&AL$3) -> 15753 | AM19: =+SUMIFS($B19:AG19,$B$4:AG$4,"="&AM$3) -> 16447 | AN19: =+SUMIFS($B19:AG19,$B$4:AG$4,"="&AN$3) -> 17925 | AO19: =+SUMIFS($B19:AG19,$B$4:AG$4,"="&AO$3) -> 22250 | AP19: =+SUMIFS($B19:AG19,$B$4:AG$4,"="&AP$3) -> 26327 | AQ19: =+SUMIFS($B19:AG19,$B$4:AG$4,"="&AQ$3) -> 28501 | AR19: =+SUMIFS($B19:AG19,$B$4:AG$4,"="&AR$3) -> 31153 | AS19: =+SUMIFS($B19:$AG19,$B$4:$AG$4,"="&AS$3) -> 33921.62 | AT19: =+AT17+AT18 -> 36939.368 | AU19: =+AU17+AU18 -> 39824.569 | AV19: =+AV17+AV18 -> 42949.767 | AW19: =+AW17+AW18 -> 46336.049 | AX19: =+AX17+AX18 -> 50006.437 | AY19: =+AY17+AY18 -> 53603.193 | AZ19: =+AZ17+AZ18 -> 57496.449 | BA19: =+BA17+BA18 -> 61713.014 | BB19: =+BB17+BB18 -> 66282.246
A21: MORTGAGE | F21: =+F17/B17-1 -> 0.038786627 | G21: =+G17/C17-1 -> 0.011538462 | H21: =+H17/D17-1 -> 0.024913621 | I21: =+I17/E17-1 -> 0.0066403446 | J21: =+J17/F17-1 -> 0.011300967 | K21: =+K17/G17-1 -> 0.024714829 | L21: =+L17/H17-1 -> 0.0097586941 | M21: =+M17/I17-1 -> 0.026297023 | ... AC21: =+AC17/Y17-1 -> 0.075443603 | AD21: 0.08 | AE21: =+AD21 -> 0.08 | AF21: =+AE21 -> 0.08 | AG21: =+AF21 -> 0.08 | AI21: 0.08 | AM21: =+AM17/AL17-1 -> 0.0066403446 | AN21: =+AN17/AM17-1 -> 0.026297023 | AO21: =+AO17/AN17-1 -> 0.10987579 | AP21: =+AP17/AO17-1 -> 0.13679762 | AQ21: =+AQ17/AP17-1 -> 0.10959659 | AR21: =+AR17/AQ17-1 -> 0.075443603 | AS21: =+AS17/AR17-1 -> 0.08 | AT21: 0.08 | AU21: 0.06 | AV21: =+AU21 -> 0.06 | AW21: =+AV21 -> 0.06 | AX21: =+AW21 -> 0.06 | AY21: 0.045 | AZ21: =+AY21 -> 0.045 | BA21: =+AZ21 -> 0.045 | BB21: =+BA21 -> 0.045
A22: CONSUMER | F22: =+F18/B18-1 -> 0.25680317 | G22: =+G18/C18-1 -> 0.12536162 | H22: =+H18/D18-1 -> 0.13272933 | I22: =+I18/E18-1 -> 0.13451942 | J22: =+J18/F18-1 -> 0.12528905 | K22: =+K18/G18-1 -> 0.20758355 | L22: =+L18/H18-1 -> 0.19536093 | M22: =+M18/I18-1 -> 0.22623829 | ... AC22: =+AC18/Y18-1 -> 0.11596544 | AD22: 0.07 | AE22: 0.08 | AF22: 0.1 | AG22: 0.1 | AI22: 0.08 | AM22: =+AM18/AL18-1 -> 0.13451942 | AN22: =+AN18/AM18-1 -> 0.22623829 | AO22: =+AO18/AN18-1 -> 0.47723019 | AP22: =+AP18/AO18-1 -> 0.2458826 | AQ22: =+AQ18/AP18-1 -> 0.049317854 | AR22: =+AR18/AQ18-1 -> 0.11596544 | AS22: =+AS18/AR18-1 -> 0.1 | AT22: =+AS22 -> 0.1 | AU22: =+AT22 -> 0.1 | AV22: =+AU22 -> 0.1 | AW22: =+AV22 -> 0.1 | AX22: =+AW22 -> 0.1 | AY22: =+AX22 -> 0.1 | AZ22: =+AY22 -> 0.1 | BA22: =+AZ22 -> 0.1 | BB22: =+BA22 -> 0.1
A23: TOTAL INDIVUDUALS | F23: =+F19/B19-1 -> 0.095960646 | G23: =+G19/C19-1 -> 0.042872312 | H23: =+H19/D19-1 -> 0.055797054 | I23: =+I19/E19-1 -> 0.044055101 | J23: =+J19/F19-1 -> 0.045580984 | K23: =+K19/G19-1 -> 0.079037801 | L23: =+L19/H19-1 -> 0.066797763 | M23: =+M19/I19-1 -> 0.089864413 | ... AG23: =+AG19/AC19-1 -> 0.088871698 | AI23: 0.08 | AM23: =+AM19/AL19-1 -> 0.044055101 | AN23: =+AN19/AM19-1 -> 0.089864413 | AO23: =+AO19/AN19-1 -> 0.24128312 | AP23: =+AP19/AO19-1 -> 0.18323596 | AQ23: =+AQ19/AP19-1 -> 0.082576822 | AR23: =+AR19/AQ19-1 -> 0.093049367 | AS23: =+AS19/AR19-1 -> 0.088871698 | AT23: =+AT19/AS19-1 -> 0.088962367 | ... BB23: =+BB19/BA19-1 -> 0.074040007
A25: BUSINESS LOANS | B25: 83810 | C25: 87155 | D25: 89002 | E25: 89415 | F25: 94760 | G25: 93438 | H25: 92866 | I25: 91665 | J25: 93575 | K25: 92751 | L25: 93179 | M25: 96398 | N25: 98858 | O25: 100619 | P25: 101940 | Q25: 111004 | R25: 115885 | S25: 117884 | T25: 121957 | U25: 123970 | V25: =126661+1956 -> 128617 | W25: =2014+130405 -> 132419 | X25: =1983+134954 -> 136937 | Y25: =139487+2339 -> 141826 | Z25: =141603+2134 -> 143737 | AA25: =143596+2002 -> 145598 | AB25: =146603+2446 -> 149049 | AC25: =146415+2839 -> 149254 | AD25: =+Z25*(1+AD30) -> 150923.85 | AE25: =+AA25*(1+AE30) -> 152877.9 | AF25: =+AB25*(1+AF30) -> 160972.92 | AG25: =+AC25*(1+AG30) -> 161194.32 | AI25: 153172.08 | AL25: =+SUMIFS($B25:AF25,$B$4:AF$4,"="&AL$3) -> 89415 | AM25: =+SUMIFS($B25:AG25,$B$4:AG$4,"="&AM$3) -> 91665 | AN25: =+SUMIFS($B25:AG25,$B$4:AG$4,"="&AN$3) -> 96398 | AO25: =+SUMIFS($B25:AG25,$B$4:AG$4,"="&AO$3) -> 111004 | AP25: =+SUMIFS($B25:AG25,$B$4:AG$4,"="&AP$3) -> 123970 | AQ25: =+SUMIFS($B25:AG25,$B$4:AG$4,"="&AQ$3) -> 141826 | AR25: =+SUMIFS($B25:AG25,$B$4:AG$4,"="&AR$3) -> 149254 | AS25: =+SUMIFS($B25:$AG25,$B$4:$AG$4,"="&AS$3) -> 161194.32 | AT25: =+AS25*(1+AT30) -> 177313.75 | AU25: =+AT25*(1+AU30) -> 187952.58 | AV25: =+AU25*(1+AV30) -> 199229.73 | AW25: =+AV25*(1+AW30) -> 211183.52 | AX25: =+AW25*(1+AX30) -> 223854.53 | AY25: =+AX25*(1+AY30) -> 233927.98 | AZ25: =+AY25*(1+AZ30) -> 244454.74 | BA25: =+AZ25*(1+BA30) -> 255455.2 | BB25: =+BA25*(1+BB30) -> 266950.69
A26: FINANCIAL ENTITIES | B26: 2137 | C26: 2342 | D26: 1821 | E26: 760 | F26: 711 | G26: 681 | H26: 633 | I26: 689 | J26: 684 | K26: 2926 | L26: 2813 | M26: 1494 | N26: 1990 | O26: 2053 | P26: 2056 | Q26: 1846 | R26: 2271 | S26: 2208 | T26: 2133 | U26: 2673 | V26: =3263+3 -> 3266 | W26: 4307 | X26: 4244 | Y26: 4447 | Z26: 5756 | AA26: 5581 | AB26: 5492 | AC26: 4953 | AD26: =+Z26*(1+AD31) -> 6216.48 | AE26: =+AA26*(1+AE31) -> 6027.48 | AF26: =+AB26*(1+AF31) -> 5931.36 | AG26: =+AC26*(1+AG31) -> 5349.24 | AI26: 5469.81 | AL26: =+SUMIFS($B26:AF26,$B$4:AF$4,"="&AL$3) -> 760 | AM26: =+SUMIFS($B26:AG26,$B$4:AG$4,"="&AM$3) -> 689 | AN26: =+SUMIFS($B26:AG26,$B$4:AG$4,"="&AN$3) -> 1494 | AO26: =+SUMIFS($B26:AG26,$B$4:AG$4,"="&AO$3) -> 1846 | AP26: =+SUMIFS($B26:AG26,$B$4:AG$4,"="&AP$3) -> 2673 | AQ26: =+SUMIFS($B26:AG26,$B$4:AG$4,"="&AQ$3) -> 4447 | AR26: =+SUMIFS($B26:AG26,$B$4:AG$4,"="&AR$3) -> 4953 | AS26: =+SUMIFS($B26:$AG26,$B$4:$AG$4,"="&AS$3) -> 5349.24 | AT26: =+AS26*(1+AT31) -> 5670.1944 | AU26: =+AT26*(1+AU31) -> 6010.4061 | AV26: =+AU26*(1+AV31) -> 6371.0304 | AW26: =+AV26*(1+AW31) -> 6753.2923 | AX26: =+AW26*(1+AX31) -> 7158.4898 | AY26: =+AX26*(1+AY31) -> 7480.6218 | AZ26: =+AY26*(1+AZ31) -> 7817.2498 | BA26: =+AZ26*(1+BA31) -> 8169.0261 | BB26: =+BA26*(1+BB31) -> 8536.6322
A27: GOVERNMENT ENTITIES | B27: 58 | C27: 8 | D27: 7 | E27: 87 | F27: 17 | G27: 17 | H27: 15 | I27: 63 | J27: 49 | K27: 0 | L27: 0 | M27: 0 | N27: 0 | O27: 0 | P27: 0 | Q27: 0 | R27: 90 | S27: 71 | T27: 103 | U27: 278 | V27: 257 | W27: =49+177 -> 226 | X27: 196 | Y27: 177 | Z27: 166 | AA27: 153 | AB27: 138 | AC27: 3036 | AD27: =+AC27 -> 3036 | AE27: =+AD27 -> 3036 | AF27: =+AE27 -> 3036 | AG27: =+AF27 -> 3036 | AI27: 138 | AL27: =+SUMIFS($B27:AF27,$B$4:AF$4,"="&AL$3) -> 87 | AM27: =+SUMIFS($B27:AG27,$B$4:AG$4,"="&AM$3) -> 63 | AN27: =+SUMIFS($B27:AG27,$B$4:AG$4,"="&AN$3) -> 0 | AO27: =+SUMIFS($B27:AG27,$B$4:AG$4,"="&AO$3) -> 0 | AP27: =+SUMIFS($B27:AG27,$B$4:AG$4,"="&AP$3) -> 278 | AQ27: =+SUMIFS($B27:AG27,$B$4:AG$4,"="&AQ$3) -> 177 | AR27: =+SUMIFS($B27:AG27,$B$4:AG$4,"="&AR$3) -> 3036 | AS27: =+SUMIFS($B27:$AG27,$B$4:$AG$4,"="&AS$3) -> 3036 | AT27: =+AS27 -> 3036 | AU27: =+AT27 -> 3036 | AV27: =+AU27 -> 3036 | AW27: =+AV27 -> 3036 | AX27: =+AW27 -> 3036 | AY27: =+AX27 -> 3036 | AZ27: =+AY27 -> 3036 | BA27: =+AZ27 -> 3036 | BB27: =+BA27 -> 3036
A28: TOTAL COMMERCIAL | B28: =+SUM(B25:B27) -> 86005 | C28: =+SUM(C25:C27) -> 89505 | D28: =+SUM(D25:D27) -> 90830 | E28: =+SUM(E25:E27) -> 90262 | F28: =+SUM(F25:F27) -> 95488 | G28: =+SUM(G25:G27) -> 94136 | H28: =+SUM(H25:H27) -> 93514 | I28: =+SUM(I25:I27) -> 92417 | ... AG28: =+SUM(AG25:AG27) -> 169579.56 | AI28: 158779.89 | AL28: =+SUMIFS($B28:AF28,$B$4:AF$4,"="&AL$3) -> 90262 | AM28: =+SUMIFS($B28:AG28,$B$4:AG$4,"="&AM$3) -> 92417 | AN28: =+SUMIFS($B28:AG28,$B$4:AG$4,"="&AN$3) -> 97892 | AO28: =+SUMIFS($B28:AG28,$B$4:AG$4,"="&AO$3) -> 112850 | AP28: =+SUMIFS($B28:AG28,$B$4:AG$4,"="&AP$3) -> 126921 | AQ28: =+SUMIFS($B28:AG28,$B$4:AG$4,"="&AQ$3) -> 146450 | AR28: =+SUMIFS($B28:AG28,$B$4:AG$4,"="&AR$3) -> 157243 | AS28: =+SUMIFS($B28:$AG28,$B$4:$AG$4,"="&AS$3) -> 169579.56 | AT28: =+SUM(AT25:AT27) -> 186019.95 | AU28: =+SUM(AU25:AU27) -> 196998.98 | AV28: =+SUM(AV25:AV27) -> 208636.76 | AW28: =+SUM(AW25:AW27) -> 220972.81 | AX28: =+SUM(AX25:AX27) -> 234049.02 | AY28: =+SUM(AY25:AY27) -> 244444.6 | AZ28: =+SUM(AZ25:AZ27) -> 255307.99 | BA28: =+SUM(BA25:BA27) -> 266660.23 | BB28: =+SUM(BB25:BB27) -> 278523.32
A30: BUSINESS LOANS | I30: =+I25/E25-1 -> 0.025163563 | J30: =+J25/F25-1 -> -0.012505276 | K30: =+K25/G25-1 -> -0.007352469 | L30: =+L25/H25-1 -> 0.0033704477 | M30: =+M25/I25-1 -> 0.051633666 | N30: =+N25/J25-1 -> 0.056457387 | O30: =+O25/K25-1 -> 0.084829274 | P30: =+P25/L25-1 -> 0.094023331 | ... AC30: =+AC25/Y25-1 -> 0.052374036 | AD30: 0.05 | AE30: 0.05 | AF30: 0.08 | AG30: 0.08 | AI30: 0.08 | AM30: =+AM25/AL25-1 -> 0.025163563 | AN30: =+AN25/AM25-1 -> 0.051633666 | AO30: =+AO25/AN25-1 -> 0.15151767 | AP30: =+AP25/AO25-1 -> 0.1168066 | AQ30: =+AQ25/AP25-1 -> 0.14403485 | AR30: =+AR25/AQ25-1 -> 0.052374036 | AS30: =+AS25/AR25-1 -> 0.08 | AT30: 0.1 | AU30: 0.06 | AV30: 0.06 | AW30: 0.06 | AX30: 0.06 | AY30: 0.045 | AZ30: =+AY30 -> 0.045 | BA30: =+AZ30 -> 0.045 | BB30: =+BA30 -> 0.045
A31: FINANCIAL ENTITIES | I31: =+I26/E26-1 -> -0.093421053 | J31: =+J26/F26-1 -> -0.037974684 | K31: =+K26/G26-1 -> 3.2966226 | L31: =+L26/H26-1 -> 3.4439179 | M31: =+M26/I26-1 -> 1.1683599 | N31: =+N26/J26-1 -> 1.9093567 | O31: =+O26/K26-1 -> -0.29835954 | P31: =+P26/L26-1 -> -0.26910771 | ... AC31: =+AC26/Y26-1 -> 0.11378457 | AD31: 0.08 | AE31: 0.08 | AF31: 0.08 | AG31: 0.08 | AI31: 0.23 | AM31: =+AM26/AL26-1 -> -0.093421053 | AN31: =+AN26/AM26-1 -> 1.1683599 | AO31: =+AO26/AN26-1 -> 0.2356091 | AP31: =+AP26/AO26-1 -> 0.44799567 | AQ31: =+AQ26/AP26-1 -> 0.66367377 | AR31: =+AR26/AQ26-1 -> 0.11378457 | AS31: =+AS26/AR26-1 -> 0.08 | AT31: 0.06 | AU31: 0.06 | AV31: 0.06 | AW31: 0.06 | AX31: 0.06 | AY31: 0.045 | AZ31: =+AY31 -> 0.045 | BA31: =+AZ31 -> 0.045 | BB31: =+BA31 -> 0.045
A32: GOVERNMENT ENTITIES | V32: =+V27/R27-1 -> 1.8555556 | W32: =+W27/S27-1 -> 2.1830986 | X32: =+X27/T27-1 -> 0.90291262 | Y32: =+Y27/U27-1 -> -0.36330935 | Z32: =+Z27/V27-1 -> -0.3540856 | AA32: =+AA27/W27-1 -> -0.32300885 | AB32: =+AB27/X27-1 -> -0.29591837 | AC32: =+AC27/Y27-1 -> 16.152542 | AM32: =+AM27/AL27-1 -> -0.27586207 | AN32: =+AN27/AM27-1 -> -1 | AO32: =+AO27/AN27-1 -> #DIV/0! | AP32: =+AP27/AO27-1 -> #DIV/0! | AQ32: =+AQ27/AP27-1 -> -0.36330935 | AR32: =+AR27/AQ27-1 -> 16.152542 | AS32: =+AS27/AR27-1 -> 0 | AT32: =+AT27/AS27-1 -> 0 | ... BB32: =+BB27/BA27-1 -> 0
A33: TOTAL COMMERCIAL | I33: =+I28/E28-1 -> 0.023874942 | J33: =+J28/F28-1 -> -0.012357574 | K33: =+K28/G28-1 -> 0.016369933 | L33: =+L28/H28-1 -> 0.026498706 | M33: =+M28/I28-1 -> 0.059242347 | N33: =+N28/J28-1 -> 0.069347245 | O33: =+O28/K28-1 -> 0.07311057 | P33: =+P28/L28-1 -> 0.083381948 | ... AG33: =+AG28/AC28-1 -> 0.078455384 | AI33: 0.084191806 | AM33: =+AM28/AL28-1 -> 0.023874942 | AN33: =+AN28/AM28-1 -> 0.059242347 | AO33: =+AO28/AN28-1 -> 0.15280105 | AP33: =+AP28/AO28-1 -> 0.12468764 | AQ33: =+AQ28/AP28-1 -> 0.15386737 | AR33: =+AR28/AQ28-1 -> 0.073697508 | AS33: =+AS28/AR28-1 -> 0.078455384 | AT33: =+AT28/AS28-1 -> 0.096947925 | ... BB33: =+BB28/BA28-1 -> 0.044487663
A35: TOTAL STAGE 1&2 | I35: =+I28+I19 -> 108864 | J35: =+J28+J19 -> 110847 | K35: =+K28+K19 -> 112633 | L35: =+L28+L19 -> 113352 | M35: =+M28+M19 -> 115817 | N35: =+N28+N19 -> 119356 | O35: =+O28+O19 -> 121909 | P35: =+P28+P19 -> 124352 | ... AG35: =+AG28+AG19 -> 203501.18 | AI35: 189560.97 | AL35: =+SUMIFS($B35:AF35,$B$4:AF$4,"="&AL$3) -> 0 | AM35: =+SUMIFS($B35:AG35,$B$4:AG$4,"="&AM$3) -> 108864 | AN35: =+SUMIFS($B35:AG35,$B$4:AG$4,"="&AN$3) -> 115817 | AO35: =+SUMIFS($B35:AG35,$B$4:AG$4,"="&AO$3) -> 135100 | AP35: =+SUMIFS($B35:AG35,$B$4:AG$4,"="&AP$3) -> 153248 | AQ35: =+SUMIFS($B35:AG35,$B$4:AG$4,"="&AQ$3) -> 174951 | AR35: =+SUMIFS($B35:AG35,$B$4:AG$4,"="&AR$3) -> 188396 | AS35: =+SUMIFS($B35:$AG35,$B$4:$AG$4,"="&AS$3) -> 203501.18 | AT35: =+AT28+AT19 -> 222959.31 | AU35: =+AU28+AU19 -> 236823.55 | AV35: =+AV28+AV19 -> 251586.53 | AW35: =+AW28+AW19 -> 267308.86 | AX35: =+AX28+AX19 -> 284055.45 | AY35: =+AY28+AY19 -> 298047.8 | AZ35: =+AZ28+AZ19 -> 312804.44 | BA35: =+BA28+BA19 -> 328373.24 | BB35: =+BB28+BB19 -> 344805.56
A36: YOY | M36: =+M35/I35-1 -> 0.06386868 | N36: =+N35/J35-1 -> 0.076763467 | O36: =+O35/K35-1 -> 0.08235597 | P36: =+P35/L35-1 -> 0.09704284 | Q36: =+Q35/M35-1 -> 0.16649542 | R36: =+R35/N35-1 -> 0.18579711 | S36: =+S35/O35-1 -> 0.18873094 | T36: =+T35/P35-1 -> 0.20423475 | ... AG36: =+AG35/AC35-1 -> 0.080177817 | AI36: 0.083508925 | AM36: =+AM35/AL35-1 -> #DIV/0! | AN36: =+AN35/AM35-1 -> 0.06386868 | AO36: =+AO35/AN35-1 -> 0.16649542 | AP36: =+AP35/AO35-1 -> 0.13433013 | AQ36: =+AQ35/AP35-1 -> 0.14162012 | AR36: =+AR35/AQ35-1 -> 0.076850089 | AS36: =+AS35/AR35-1 -> 0.080177817 | AT36: =+AT35/AS35-1 -> 0.095616812 | ... BB36: =+BB35/BA35-1 -> 0.050041599
A38: LOAN BREAKDOWN STAGE 3 | B38: =+B42+B45 -> 1806 | C38: =+C42+C45 -> 1771 | D38: =+D42+D45 -> 1722 | E38: =+E42+E45 -> 1918 | F38: =+F42+F45 -> 2067 | G38: =+G42+G45 -> 1719 | H38: =+H42+H45 -> 1362 | I38: =+I42+I45 -> 1552 | ... AC38: =+AC42+AC45 -> 2446 | AD38: =+AD56 -> 2498.1249 | AE38: =+AE56 -> 2579.6557 | AF38: =+AF56 -> 2622.3429 | AG38: =+AG56 -> 2663.7783 | AI38: 3297.986 | AM38: =+SUMIFS($B38:AG38,$B$4:AG$4,"="&AM$3) -> 1552 | AN38: =+SUMIFS($B38:AG38,$B$4:AG$4,"="&AN$3) -> 2135 | AO38: =+SUMIFS($B38:AG38,$B$4:AG$4,"="&AO$3) -> 1776 | AP38: =+SUMIFS($B38:AG38,$B$4:AG$4,"="&AP$3) -> 2053 | AQ38: =+SUMIFS($B38:AG38,$B$4:AG$4,"="&AQ$3) -> 2225 | AR38: =+SUMIFS($B38:AG38,$B$4:AG$4,"="&AR$3) -> 2446 | AS38: =+SUMIFS($B38:$AG38,$B$4:$AG$4,"="&AS$3) -> 2663.7783
A39: % total gross loan | B39: =+B38/AVERAGE(A7:B7) -> 0.017663628 | C39: =+C38/AVERAGE(B7:C7) -> 0.016980843 | D39: =+D38/AVERAGE(C7:D7) -> 0.016070254 | E39: =+E38/AVERAGE(D7:E7) -> 0.01776765 | F39: =+F38/AVERAGE(E7:F7) -> 0.018680018 | G39: =+G38/AVERAGE(F7:G7) -> 0.01528394 | H39: =+H38/AVERAGE(G7:H7) -> 0.012230713 | I39: =+I38/AVERAGE(H7:I7) -> 0.014009433 | ... AG39: =+AG38/AVERAGE(AF7:AG7) -> 0.012937913 | AI39: 0.017314128 | AM39: =+AM38/AVERAGEIFS($B$7:$AG$7,$B$4:$AG$4,">"&AL$3,$B$4:$AG$4,"<="&AM$3) -> 0.013903477 | AN39: =+AN38/AVERAGEIFS($B$7:$AG$7,$B$4:$AG$4,">"&AM$3,$B$4:$AG$4,"<="&AN$3) -> 0.018545986 | AO39: =+AO38/AVERAGEIFS($B$7:$AG$7,$B$4:$AG$4,">"&AN$3,$B$4:$AG$4,"<="&AO$3) -> 0.013993645 | AP39: =+AP38/AVERAGEIFS($B$7:$AG$7,$B$4:$AG$4,">"&AO$3,$B$4:$AG$4,"<="&AP$3) -> 0.013750515 | AQ39: =+AQ38/AVERAGEIFS($B$7:$AG$7,$B$4:$AG$4,">"&AP$3,$B$4:$AG$4,"<="&AQ$3) -> 0.013178606 | AR39: =+AR38/AVERAGEIFS($B$7:$AG$7,$B$4:$AG$4,">"&AQ$3,$B$4:$AG$4,"<="&AR$3) -> 0.013156727 | AS39: =+AS38/AVERAGEIFS($B$7:$AG$7,$B$4:$AG$4,">"&AR$3,$B$4:$AG$4,"<="&AS$3) -> 0.013286136
A40: MORTGAGE | B40: 217 | C40: 217 | D40: 222 | E40: 252 | F40: 293 | G40: 268 | H40: 264 | I40: 306 | J40: 333 | K40: 330 | L40: 318 | M40: 319 | N40: 290 | O40: 290 | P40: 274 | Q40: 272 | R40: 265 | S40: 246 | T40: 230 | U40: 230 | V40: 232 | W40: 226 | X40: 223 | Y40: 219 | Z40: 224 | AA40: 221 | AB40: 230 | AC40: 218 | AM40: =+SUMIFS($B40:AG40,$B$4:AG$4,"="&AM$3) -> 306 | AN40: =+SUMIFS($B40:AG40,$B$4:AG$4,"="&AN$3) -> 319 | AO40: =+SUMIFS($B40:AG40,$B$4:AG$4,"="&AO$3) -> 272 | AP40: =+SUMIFS($B40:AG40,$B$4:AG$4,"="&AP$3) -> 230 | AQ40: =+SUMIFS($B40:AG40,$B$4:AG$4,"="&AQ$3) -> 219 | AR40: =+SUMIFS($B40:AG40,$B$4:AG$4,"="&AR$3) -> 218 | AS40: =+SUMIFS($B40:$AG40,$B$4:$AG$4,"="&AS$3) -> 0
A41: CONSUMER | B41: 68 | C41: 79 | D41: 91 | E41: 104 | F41: 107 | G41: 84 | H41: 64 | I41: 150 | J41: 213 | K41: 142 | L41: 122 | M41: 109 | N41: 106 | O41: 106 | P41: 128 | Q41: 146 | R41: 175 | S41: 264 | T41: 335 | U41: 361 | V41: 308 | W41: 318 | X41: 227 | Y41: 213 | Z41: 293 | AA41: 324 | AB41: 319 | AC41: 348 | AM41: =+SUMIFS($B41:AG41,$B$4:AG$4,"="&AM$3) -> 150 | AN41: =+SUMIFS($B41:AG41,$B$4:AG$4,"="&AN$3) -> 109 | AO41: =+SUMIFS($B41:AG41,$B$4:AG$4,"="&AO$3) -> 146 | AP41: =+SUMIFS($B41:AG41,$B$4:AG$4,"="&AP$3) -> 361 | AQ41: =+SUMIFS($B41:AG41,$B$4:AG$4,"="&AQ$3) -> 213 | AR41: =+SUMIFS($B41:AG41,$B$4:AG$4,"="&AR$3) -> 348 | AS41: =+SUMIFS($B41:$AG41,$B$4:$AG$4,"="&AS$3) -> 0
A42: TOTAL INDIVUDUALS | B42: =+B40+B41 -> 285 | C42: =+C40+C41 -> 296 | D42: =+D40+D41 -> 313 | E42: =+E40+E41 -> 356 | F42: =+F40+F41 -> 400 | G42: =+G40+G41 -> 352 | H42: =+H40+H41 -> 328 | I42: =+I40+I41 -> 456 | ... AC42: =+AC40+AC41 -> 566 | AM42: =+SUMIFS($B42:AG42,$B$4:AG$4,"="&AM$3) -> 456 | AN42: =+SUMIFS($B42:AG42,$B$4:AG$4,"="&AN$3) -> 428 | AO42: =+SUMIFS($B42:AG42,$B$4:AG$4,"="&AO$3) -> 418 | AP42: =+SUMIFS($B42:AG42,$B$4:AG$4,"="&AP$3) -> 591 | AQ42: =+SUMIFS($B42:AG42,$B$4:AG$4,"="&AQ$3) -> 432 | AR42: =+SUMIFS($B42:AG42,$B$4:AG$4,"="&AR$3) -> 566 | AS42: =+SUMIFS($B42:$AG42,$B$4:$AG$4,"="&AS$3) -> 0
AM43: =+SUMIFS($B43:AG43,$B$4:AG$4,"="&AM$3) -> 0 | AN43: =+SUMIFS($B43:AG43,$B$4:AG$4,"="&AN$3) -> 0 | AO43: =+SUMIFS($B43:AG43,$B$4:AG$4,"="&AO$3) -> 0 | AP43: =+SUMIFS($B43:AG43,$B$4:AG$4,"="&AP$3) -> 0 | AQ43: =+SUMIFS($B43:AG43,$B$4:AG$4,"="&AQ$3) -> 0 | AR43: =+SUMIFS($B43:AG43,$B$4:AG$4,"="&AR$3) -> 0 | AS43: =+SUMIFS($B43:$AG43,$B$4:$AG$4,"="&AS$3) -> 0
A44: BUSINESS LOANS | B44: 1521 | C44: 1475 | D44: 1409 | E44: 1562 | F44: 1667 | G44: 1367 | H44: 1034 | I44: 1096 | J44: 1398 | K44: 1364 | L44: 1473 | M44: 1707 | N44: 1474 | O44: 1246 | P44: 1252 | Q44: 1358 | R44: 1326 | S44: 1413 | T44: 1461 | U44: 1462 | V44: 1497 | W44: 1611 | X44: 1667 | Y44: 1793 | Z44: 1963 | AA44: 2245 | AB44: 2515 | AC44: 1880 | AM44: =+SUMIFS($B44:AG44,$B$4:AG$4,"="&AM$3) -> 1096 | AN44: =+SUMIFS($B44:AG44,$B$4:AG$4,"="&AN$3) -> 1707 | AO44: =+SUMIFS($B44:AG44,$B$4:AG$4,"="&AO$3) -> 1358 | AP44: =+SUMIFS($B44:AG44,$B$4:AG$4,"="&AP$3) -> 1462 | AQ44: =+SUMIFS($B44:AG44,$B$4:AG$4,"="&AQ$3) -> 1793 | AR44: =+SUMIFS($B44:AG44,$B$4:AG$4,"="&AR$3) -> 1880 | AS44: =+SUMIFS($B44:$AG44,$B$4:$AG$4,"="&AS$3) -> 0
A45: TOTAL COMMERCIAL | B45: =+B44 -> 1521 | C45: =+C44 -> 1475 | D45: =+D44 -> 1409 | E45: =+E44 -> 1562 | F45: =+F44 -> 1667 | G45: =+G44 -> 1367 | H45: =+H44 -> 1034 | I45: =+I44 -> 1096 | ... AC45: =+AC44 -> 1880 | AM45: =+SUMIFS($B45:AG45,$B$4:AG$4,"="&AM$3) -> 1096 | AN45: =+SUMIFS($B45:AG45,$B$4:AG$4,"="&AN$3) -> 1707 | AO45: =+SUMIFS($B45:AG45,$B$4:AG$4,"="&AO$3) -> 1358 | AP45: =+SUMIFS($B45:AG45,$B$4:AG$4,"="&AP$3) -> 1462 | AQ45: =+SUMIFS($B45:AG45,$B$4:AG$4,"="&AQ$3) -> 1793 | AR45: =+SUMIFS($B45:AG45,$B$4:AG$4,"="&AR$3) -> 1880 | AS45: =+SUMIFS($B45:$AG45,$B$4:$AG$4,"="&AS$3) -> 0
A47: NON PERFORMING LOANS
A48: Balance ate beginning of period | J48: =+I56 -> 1552 | K48: =+J56 -> 1944 | L48: =+K56 -> 1836 | M48: =+L56 -> 1913 | N48: =+M56 -> 2135 | O48: =+N56 -> 1870 | P48: =+O56 -> 1642 | Q48: =+P56 -> 1654 | ... AG48: =+AF56 -> 2622.3429 | AI48: 3064 | AM48: =+AL56 -> 0 | AN48: =+AM56 -> 1552 | AO48: =+AN56 -> 2135 | AP48: =+AO56 -> 1845 | AQ48: =+AP56 -> 2053 | AR48: =+AQ56 -> 2250 | AS48: =+AR56 -> 2446 | AT48: =+AS56 -> 2663.7783 | ... BB48: =+BA56 -> 5699.9949
A49: Transfer of perf loans to NPL | J49: 749 | K49: 422 | L49: 487 | M49: 692 | N49: 600 | O49: 357 | P49: 431 | Q49: 523 | R49: 511 | S49: 575 | T49: 594 | U49: 765 | V49: 647 | W49: 611 | X49: 756 | Y49: =38+701 -> 739 | Z49: 885 | AA49: 841 | AB49: 974 | AC49: 849 | AD49: =+AD59 -> 864.41668 | AE49: =+AE59 -> 877.31204 | AF49: =+AF59 -> 889.7137 | AG49: =+AG59 -> 931.38451 | AI49: 647.626 | AM49: =+SUMIFS($B49:AG49,$B$4:AG$4,"<="&AM$3,$B$4:AG$4,">"&AL$3) -> 0 | AN49: =+SUMIFS($B49:AG49,$B$4:AG$4,"<="&AN$3,$B$4:AG$4,">"&AM$3) -> 2350 | AO49: =+SUMIFS($B49:AG49,$B$4:AG$4,"<="&AO$3,$B$4:AG$4,">"&AN$3) -> 1911 | AP49: =+SUMIFS($B49:AG49,$B$4:AG$4,"<="&AP$3,$B$4:AG$4,">"&AO$3) -> 2445 | AQ49: =+SUMIFS($B49:AG49,$B$4:AG$4,"<="&AQ$3,$B$4:AG$4,">"&AP$3) -> 2753 | AR49: =+SUMIFS($B49:AG49,$B$4:AG$4,"<="&AR$3,$B$4:AG$4,">"&AQ$3) -> 3549 | AS49: =+SUMIFS($B49:$AG49,$B$4:$AG$4,"<="&AS$3,$B$4:$AG$4,">"&AR$3) -> 3562.8269 | AT49: =+AT59 -> 3663.627 | AU49: =+AU59 -> 4013.9313 | AV49: =+AV59 -> 4263.5289 | AW49: =+AW59 -> 4529.3064 | AX49: =+AX59 -> 4812.3551 | AY49: =+AY59 -> 5113.8437 | AZ49: =+AZ59 -> 5365.7475 | BA49: =+BA59 -> 5631.411 | BB49: =+BB59 -> 5911.6958
A50: Accured interests not charged | J50: 64 | K50: 90 | L50: 81 | M50: 394 | N50: 96 | O50: 85 | P50: 64 | Q50: 99 | R50: 189 | S50: 71 | T50: 204 | U50: 70 | V50: 132 | W50: 102 | X50: 180 | Y50: 164 | Z50: 73 | AA50: 208 | AB50: 86 | AC50: 398 | AD50: =+AVERAGE(Z50:AC50) -> 191.25 | AE50: =+AVERAGE(AA50:AD50) -> 220.8125 | AF50: =+AVERAGE(AB50:AE50) -> 224.01562 | AG50: =+AVERAGE(AC50:AF50) -> 258.51953 | AM50: =+SUMIFS($B50:AG50,$B$4:AG$4,"<="&AM$3,$B$4:AG$4,">"&AL$3) -> 0 | AN50: =+SUMIFS($B50:AG50,$B$4:AG$4,"<="&AN$3,$B$4:AG$4,">"&AM$3) -> 629 | AO50: =+SUMIFS($B50:AG50,$B$4:AG$4,"<="&AO$3,$B$4:AG$4,">"&AN$3) -> 344 | AP50: =+SUMIFS($B50:AG50,$B$4:AG$4,"<="&AP$3,$B$4:AG$4,">"&AO$3) -> 534 | AQ50: =+SUMIFS($B50:AG50,$B$4:AG$4,"<="&AQ$3,$B$4:AG$4,">"&AP$3) -> 578 | AR50: =+SUMIFS($B50:AG50,$B$4:AG$4,"<="&AR$3,$B$4:AG$4,">"&AQ$3) -> 765 | AS50: =+SUMIFS($B50:$AG50,$B$4:$AG$4,"<="&AS$3,$B$4:$AG$4,">"&AR$3) -> 894.59766 | AT50: =+AVERAGE(AP50:AS50) -> 692.89941 | AU50: =+AVERAGE(AQ50:AT50) -> 732.62427 | AV50: =+AVERAGE(AR50:AU50) -> 771.28033 | AW50: =+AVERAGE(AS50:AV50) -> 772.85042 | AX50: =+AVERAGE(AT50:AW50) -> 742.41361 | AY50: =+AVERAGE(AU50:AX50) -> 754.79216 | AZ50: =+AVERAGE(AV50:AY50) -> 760.33413 | BA50: =+AVERAGE(AW50:AZ50) -> 757.59758 | BB50: =+AVERAGE(AX50:BA50) -> 753.78437
A52: NPL Reversals
A53: Paid credits | J53: -132 | K53: -250 | L53: -197 | M53: -556 | N53: -167 | O53: -139 | P53: -205 | Q53: -128 | R53: -346 | S53: -215 | T53: -313 | U53: -213 | V53: -249 | W53: -249 | X53: -385 | Y53: -359 | Z53: -263 | AA53: -308 | AB53: -272 | AC53: -777 | AD53: =+AVERAGE(Z53:AC53) -> -405 | AE53: =+AVERAGE(AA53:AD53) -> -440.5 | AF53: =+AVERAGE(AB53:AE53) -> -473.625 | AG53: =+AVERAGE(AC53:AF53) -> -524.03125 | AM53: =+SUMIFS($B53:AG53,$B$4:AG$4,"<="&AM$3,$B$4:AG$4,">"&AL$3) -> 0 | AN53: =+SUMIFS($B53:AG53,$B$4:AG$4,"<="&AN$3,$B$4:AG$4,">"&AM$3) -> -1135 | AO53: =+SUMIFS($B53:AG53,$B$4:AG$4,"<="&AO$3,$B$4:AG$4,">"&AN$3) -> -639 | AP53: =+SUMIFS($B53:AG53,$B$4:AG$4,"<="&AP$3,$B$4:AG$4,">"&AO$3) -> -1087 | AQ53: =+SUMIFS($B53:AG53,$B$4:AG$4,"<="&AQ$3,$B$4:AG$4,">"&AP$3) -> -1242 | AR53: =+SUMIFS($B53:AG53,$B$4:AG$4,"<="&AR$3,$B$4:AG$4,">"&AQ$3) -> -1620 | AS53: =+SUMIFS($B53:$AG53,$B$4:$AG$4,"<="&AS$3,$B$4:$AG$4,">"&AR$3) -> -1843.1562 | AT53: =+AVERAGE(AP53:AS53) -> -1448.0391 | AU53: =+AVERAGE(AQ53:AT53) -> -1538.2988 | AV53: =+AVERAGE(AR53:AU53) -> -1612.3735 | AW53: =+AVERAGE(AS53:AV53) -> -1610.4669 | AX53: =+AVERAGE(AT53:AW53) -> -1552.2946 | AY53: =+AVERAGE(AU53:AX53) -> -1578.3585 | AZ53: =+AVERAGE(AV53:AY53) -> -1588.3734 | BA53: =+AVERAGE(AW53:AZ53) -> -1582.3733 | BB53: =+AVERAGE(AX53:BA53) -> -1575.3499
A54: W-O | J54: -98 | K54: -231 | L54: -165 | M54: -204 | N54: -136 | O54: -320 | P54: -179 | Q54: -212 | R54: -252 | S54: -205 | T54: -256 | U54: -392 | V54: -276 | W54: -364 | X54: -468 | Y54: -367 | Z54: -383 | AA54: -266 | AB54: -386 | AC54: -753 | AD54: =+AD64*AC10 -> -421.0418 | AE54: =+AE64*AD10 -> -374.71873 | AF54: =+AF64*AE10 -> -386.94835 | AG54: =+AG64*AF10 -> -393.35144 | AI54: -413.64 | AM54: =+SUMIFS($B54:AG54,$B$4:AG$4,"<="&AM$3,$B$4:AG$4,">"&AL$3) -> 0 | AN54: =+SUMIFS($B54:AG54,$B$4:AG$4,"<="&AN$3,$B$4:AG$4,">"&AM$3) -> -698 | AO54: =+SUMIFS($B54:AG54,$B$4:AG$4,"<="&AO$3,$B$4:AG$4,">"&AN$3) -> -847 | AP54: =+SUMIFS($B54:AG54,$B$4:AG$4,"<="&AP$3,$B$4:AG$4,">"&AO$3) -> -1105 | AQ54: =+SUMIFS($B54:AG54,$B$4:AG$4,"<="&AQ$3,$B$4:AG$4,">"&AP$3) -> -1475 | AR54: =+SUMIFS($B54:AG54,$B$4:AG$4,"<="&AR$3,$B$4:AG$4,">"&AQ$3) -> -1788 | AS54: =+SUMIFS($B54:$AG54,$B$4:$AG$4,"<="&AS$3,$B$4:$AG$4,">"&AR$3) -> -1576.0603 | AT54: =+AT64*AS10 -> -1857.0417 | AU54: =+AU64*AT10 -> -2207.5179 | AV54: =+AV64*AU10 -> -2460.1446 | AW54: =+AW64*AV10 -> -2564.8001 | AX54: =+AX64*AW10 -> -2911.3286 | AY54: =+AY64*AX10 -> -3218.1326 | AZ54: =+AZ64*AY10 -> -3485.8614 | BA54: =+BA64*AZ10 -> -3729.6957 | BB54: =+BB64*BA10 -> -4019.7225
A55: Transfers of NPL to perf portfolio | J55: -191 | K55: -139 | L55: -129 | M55: -104 | N55: -658 | O55: -211 | P55: -99 | Q55: -91 | R55: -181 | S55: -69 | T55: -89 | U55: -240 | V55: -120 | W55: -106 | X55: -130 | Y55: =-34-27 -> -61 | Z55: -82 | AA55: -165 | AB55: -128 | AC55: -335 | AD55: =+AVERAGE(Z55:AC55) -> -177.5 | AE55: =+AVERAGE(AA55:AD55) -> -201.375 | AF55: =+AVERAGE(AB55:AE55) -> -210.46875 | AG55: =+AVERAGE(AC55:AF55) -> -231.08594 | AM55: =+SUMIFS($B55:AG55,$B$4:AG$4,"<="&AM$3,$B$4:AG$4,">"&AL$3) -> 0 | AN55: =+SUMIFS($B55:AG55,$B$4:AG$4,"<="&AN$3,$B$4:AG$4,">"&AM$3) -> -563 | AO55: =+SUMIFS($B55:AG55,$B$4:AG$4,"<="&AO$3,$B$4:AG$4,">"&AN$3) -> -1059 | AP55: =+SUMIFS($B55:AG55,$B$4:AG$4,"<="&AP$3,$B$4:AG$4,">"&AO$3) -> -579 | AQ55: =+SUMIFS($B55:AG55,$B$4:AG$4,"<="&AQ$3,$B$4:AG$4,">"&AP$3) -> -417 | AR55: =+SUMIFS($B55:AG55,$B$4:AG$4,"<="&AR$3,$B$4:AG$4,">"&AQ$3) -> -710 | AS55: =+SUMIFS($B55:$AG55,$B$4:$AG$4,"<="&AS$3,$B$4:$AG$4,">"&AR$3) -> -820.42969 | AT55: =+AVERAGE(AP55:AS55) -> -631.60742 | AU55: =+AVERAGE(AQ55:AT55) -> -644.75928 | AV55: =+AVERAGE(AR55:AU55) -> -701.6991 | AW55: =+AVERAGE(AS55:AV55) -> -699.62387 | AX55: =+AVERAGE(AT55:AW55) -> -669.42242 | AY55: =+AVERAGE(AU55:AX55) -> -678.87617 | AZ55: =+AVERAGE(AV55:AY55) -> -687.40539 | BA55: =+AVERAGE(AW55:AZ55) -> -683.83196 | BB55: =+AVERAGE(AX55:BA55) -> -679.88398
A56: Balance at the end of the period | I56: =+I10 -> 1552 | J56: =+J48+J49+J50+J53+J54+J55 -> 1944 | K56: =+K48+K49+K50+K53+K54+K55 -> 1836 | L56: =+L48+L49+L50+L53+L54+L55 -> 1913 | M56: =+M48+M49+M50+M53+M54+M55 -> 2135 | N56: =+N48+N49+N50+N53+N54+N55 -> 1870 | O56: =+O48+O49+O50+O53+O54+O55 -> 1642 | P56: =+P48+P49+P50+P53+P54+P55 -> 1654 | Q56: =+Q48+Q49+Q50+Q53+Q54+Q55 -> 1845 | ... AG56: =+AG48+AG49+AG50+AG53+AG54+AG55 -> 2663.7783 | AI56: 3297.986 | AJ56: =+AB56/AI56-1 -> -0.070948148 | AM56: =+I56 -> 1552 | AN56: =+AN48+AN49+AN50+AN53+AN54+AN55 -> 2135 | AO56: =+AO48+AO49+AO50+AO53+AO54+AO55 -> 1845 | AP56: =+AP48+AP49+AP50+AP53+AP54+AP55 -> 2053 | AQ56: =+AQ48+AQ49+AQ50+AQ53+AQ54+AQ55 -> 2250 | AR56: =+AR48+AR49+AR50+AR53+AR54+AR55 -> 2446 | AS56: =+AS48+AS49+AS50+AS53+AS54+AS55 -> 2663.7783 | AT56: =+AT48+AT49+AT50+AT53+AT54+AT55 -> 3083.6166 | AU56: =+AU48+AU49+AU50+AU53+AU54+AU55 -> 3439.5962 | ... BB56: =+BB48+BB49+BB50+BB53+BB54+BB55 -> 6090.5186
A57: NPL/Total loan | B57: =+B56/B5 -> 0 | C57: =+C56/C5 -> 0 | D57: =+D56/D5 -> 0 | E57: =+E56/E5 -> 0 | F57: =+F56/F5 -> 0 | G57: =+G56/G5 -> 0 | H57: =+H56/H5 -> 0 | I57: =+I56/I5 -> 0.014372367 | ... AC57: =+AC56/AC5 -> 0.013019087 | AN57: =+AN56/AN5 -> 0.018530091 | AO57: =+AO56/AO5 -> 0.013759005 | AP57: =+AP56/AP5 -> 0.013491401 | AQ57: =+AQ56/AQ5 -> 0.012922494 | AR57: =+AR56/AR5 -> 0.013019087 | AS57: =+AS56/AS5 -> 0.013138732 | AT57: =+AT56/AT5 -> 0.013894734 | AU57: =+AU56/AU5 -> 0.014571969 | ... BB57: =+BB56/BB5 -> 0.017481243
A59: NPL CREATION | I59: =+I49 -> 0 | J59: =+J49 -> 749 | K59: =+K49 -> 422 | L59: =+L49 -> 487 | M59: =+M49 -> 692 | N59: =+N49 -> 600 | O59: =+O49 -> 357 | P59: =+P49 -> 431 | ... AC59: =+AC49 -> 849 | AD59: =+AD60*AC9 -> 864.41668 | AE59: =+AE60*AD9 -> 877.31204 | AF59: =+AF60*AE9 -> 889.7137 | AG59: =+AG60*AF9 -> 931.38451 | AI59: 647.626 | AJ59: =+AB59/AI59-1 -> 0.50395444 | AM59: =+SUMIFS($B59:AG59,$B$4:AG$4,"<="&AM$3,$B$4:AG$4,">"&AL$3) -> 0 | AN59: =+SUMIFS($B59:AG59,$B$4:AG$4,"<="&AN$3,$B$4:AG$4,">"&AM$3) -> 2350 | AO59: =+SUMIFS($B59:AG59,$B$4:AG$4,"<="&AO$3,$B$4:AG$4,">"&AN$3) -> 1911 | AP59: =+SUMIFS($B59:AG59,$B$4:AG$4,"<="&AP$3,$B$4:AG$4,">"&AO$3) -> 2445 | AQ59: =+SUMIFS($B59:AG59,$B$4:AG$4,"<="&AQ$3,$B$4:AG$4,">"&AP$3) -> 2753 | AR59: =+SUMIFS($B59:AG59,$B$4:AG$4,"<="&AR$3,$B$4:AG$4,">"&AQ$3) -> 3549 | AS59: =+SUMIFS($B59:AH59,$B$4:AH$4,"<="&AS$3,$B$4:AH$4,">"&AR$3) -> 3562.8269 | AT59: =+AT60*AS9 -> 3663.627 | AU59: =+AU60*AT9 -> 4013.9313 | AV59: =+AV60*AU9 -> 4263.5289 | AW59: =+AW60*AV9 -> 4529.3064 | AX59: =+AX60*AW9 -> 4812.3551 | AY59: =+AY60*AX9 -> 5113.8437 | AZ59: =+AZ60*AY9 -> 5365.7475 | BA59: =+BA60*AZ9 -> 5631.411 | BB59: =+BB60*BA9 -> 5911.6958
A60: CREATION / STAGE 1&2 t-1 | J60: =+J59/I$9 -> 0.006880144 | K60: =+K59/J$9 -> 0.0038070494 | L60: =+L59/K$9 -> 0.0043237772 | M60: =+M59/L$9 -> 0.0061048768 | N60: =+N59/M$9 -> 0.0051805866 | O60: =+O59/N$9 -> 0.002991052 | P60: =+P59/O$9 -> 0.003535424 | Q60: =+Q59/P$9 -> 0.0042058029 | ... AC60: =+AC59/AB$9 -> 0.0045882963 | AD60: =+AC60 -> 0.0045882963 | AE60: =+AD60 -> 0.0045882963 | AF60: =+AE60 -> 0.0045882963 | AG60: =+AF60 -> 0.0045882963 | AI60: 0.0035 | AM60: =+AM59/AVERAGEIFS($B$9:$AG$9,$B$4:$AG$4,">"&AL$3,$B$4:$AG$4,"<="&AM$3) -> 0 | AN60: =+AN59/AVERAGEIFS($B$9:$AG$9,$B$4:$AG$4,">"&AM$3,$B$4:$AG$4,"<="&AN$3) -> 0.020766643 | AO60: =+AO59/AVERAGEIFS($B$9:$AG$9,$B$4:$AG$4,">"&AN$3,$B$4:$AG$4,"<="&AO$3) -> 0.015266108 | AP60: =+AP59/AVERAGEIFS($B$9:$AG$9,$B$4:$AG$4,">"&AO$3,$B$4:$AG$4,"<="&AP$3) -> 0.016591851 | AQ60: =+AQ59/AVERAGEIFS($B$9:$AG$9,$B$4:$AG$4,">"&AP$3,$B$4:$AG$4,"<="&AQ$3) -> 0.016514623 | AR60: =+AR59/AVERAGEIFS($B$9:$AG$9,$B$4:$AG$4,">"&AQ$3,$B$4:$AG$4,"<="&AR$3) -> 0.01937042 | AS60: =+AS59/AVERAGEIFS($B$9:$AG$9,$B$4:$AG$4,">"&AR$3,$B$4:$AG$4,"<="&AS$3) -> 0.018002977 | AT60: =+AS60 -> 0.018002977 | AU60: =+AT60 -> 0.018002977 | AV60: =+AU60 -> 0.018002977 | AW60: =+AV60 -> 0.018002977 | AX60: =+AW60 -> 0.018002977 | AY60: =+AX60 -> 0.018002977 | AZ60: =+AY60 -> 0.018002977 | BA60: =+AZ60 -> 0.018002977 | BB60: =+BA60 -> 0.018002977
B61: =+SUM(#REF!)/A7 -> #REF! | C61: =+SUM(#REF!)/B7 -> #REF! | D61: =+SUM(A59:D59)/C7 -> 0 | E61: =+SUM(B59:E59)/D7 -> 0 | F61: =+SUM(C59:F59)/E7 -> 0 | G61: =+SUM(D59:G59)/F7 -> 0 | H61: =+SUM(E59:H59)/G7 -> 0 | I61: =+SUM(F59:I59)/H7 -> 0 | J61: =+SUM(G59:J59)/I7 -> 0.0067834372 | K61: =+SUM(H59:K59)/J7 -> 0.010382034 | ... AG61: =+SUM(AD59:AG59)/AF7 -> 0.01732777 | AI61: 0.013272865
A64: W-O / STAGE 3 (T-1) | K64: =+K54/J10 -> -0.11882716 | L64: =+L54/K10 -> -0.089869281 | M64: =+M54/L10 -> -0.10663879 | N64: =+N54/M10 -> -0.063700234 | O64: =+O54/N10 -> -0.17112299 | P64: =+P54/O10 -> -0.1090134 | Q64: =+Q54/P10 -> -0.12817412 | R64: =+R54/Q10 -> -0.14189189 | ... AC64: =+AC54/AB10 -> -0.24575718 | AD64: =+Z64 -> -0.17213483 | AE64: -0.15 | AF64: -0.15 | AG64: -0.15 | AI64: -0.135 | AM64: =+AM54/AL10 -> 0 | AN64: =+AN54/AM10 -> -0.44974227 | AO64: =+AO54/AN10 -> -0.39672131 | AP64: =+AP54/AO10 -> -0.62218468 | AQ64: =+AQ54/AP10 -> -0.71846079 | AR64: =+AR54/AQ10 -> -0.80359551 | AS64: =+AS54/AR10 -> -0.64434191 | AT64: =+AVERAGE(AP64:AS64) -> -0.69714572 | AU64: =+AVERAGE(AQ64:AT64) -> -0.71588598 | AV64: =+AVERAGE(AR64:AU64) -> -0.71524228 | AW64: =+AVERAGE(AS64:AV64) -> -0.69315397 | AX64: =+AVERAGE(AT64:AW64) -> -0.70535699 | AY64: =+AVERAGE(AU64:AX64) -> -0.70740981 | AZ64: =+AVERAGE(AV64:AY64) -> -0.70529076 | BA64: =+AVERAGE(AW64:AZ64) -> -0.70280288 | BB64: =+AVERAGE(AX64:BA64) -> -0.70521511
A66: LOAN LOSSES RESERVES AT T-1 | B66: 2157 | C66: 2187 | D66: 2319 | E66: 2231 | F66: 2342 | G66: 2447 | H66: 2369 | I66: 2307 | J66: 2626 | K66: 2773 | L66: 2643 | M66: 2739 | N66: 2827 | O66: 3051 | P66: 2818 | Q66: 2861 | R66: 3055 | S66: 3219 | T66: 3375 | U66: =+T69 -> 3484 | V66: =+U69 -> 3426 | W66: =+V69 -> 3540 | X66: =+W69 -> 3619 | Y66: =+X69 -> 3593 | Z66: =+Y69 -> 3653 | AA66: =+Z69 -> 3737 | AB66: =+AA69 -> 3906 | ... AG66: =+AF69 -> 4051.9039 | AI66: 3990 | AN66: =+AM69 -> 2626 | AO66: =+AN69 -> 2827 | AP66: =+AO69 -> 3055 | AQ66: =+AP69 -> 3426 | AR66: =+AQ69 -> 3653 | AS66: =+AR69 -> 3731 | AT66: =+AS69 -> 4189.545 | AU66: =+AT69 -> 4435.9287 | ... BB66: =+BA69 -> 3389.8961
A67: PROVISION CHARGE IN THE PERIOD | B67: 154 | C67: 218 | D67: 130 | E67: 229 | F67: 175 | G67: 157 | H67: 260 | I67: 472 | J67: 237 | K67: 118 | L67: 238 | M67: 260 | N67: -49 | O67: 66 | P67: 207 | Q67: 220 | R67: 290 | S67: 339 | T67: 336 | U67: 305 | V67: 375 | W67: 410 | X67: 419 | Y67: 444 | Z67: 413 | AA67: 415 | AB67: 458 | AC67: 471 | AD67: =+AD59*AD73 -> 475.42917 | AE67: =+AE59*AE73 -> 482.52162 | AF67: =+AF59*AF73 -> 489.34253 | AG67: =+AG59*AG73 -> 512.26148 | AI67: 453.3382 | AM67: =+SUMIFS($B67:AG67,$B$4:AG$4,"<="&AM$3,$B$4:AG$4,">"&AL$3) -> 1064 | AN67: =+SUMIFS($B67:AG67,$B$4:AG$4,"<="&AN$3,$B$4:AG$4,">"&AM$3) -> 853 | AO67: =+SUMIFS($B67:AG67,$B$4:AG$4,"<="&AO$3,$B$4:AG$4,">"&AN$3) -> 444 | AP67: =+SUMIFS($B67:AG67,$B$4:AG$4,"<="&AP$3,$B$4:AG$4,">"&AO$3) -> 1270 | AQ67: =+SUMIFS($B67:AG67,$B$4:AG$4,"<="&AQ$3,$B$4:AG$4,">"&AP$3) -> 1648 | AR67: =+SUMIFS($B67:AG67,$B$4:AG$4,"<="&AR$3,$B$4:AG$4,">"&AQ$3) -> 1757 | AS67: =+SUMIFS($B67:$AG67,$B$4:$AG$4,"<="&AS$3,$B$4:$AG$4,">"&AR$3) -> 1959.5548 | AT67: =+AT59*AT73 -> 2014.9948 | AU67: =+AU59*AU73 -> 2207.6622 | AV67: =+AV59*AV73 -> 2344.9409 | AW67: =+AW59*AW73 -> 2491.1185 | AX67: =+AX59*AX73 -> 2646.7953 | AY67: =+AY59*AY73 -> 2812.614 | AZ67: =+AZ59*AZ73 -> 2951.1611 | BA67: =+BA59*BA73 -> 3097.276 | BB67: =+BB59*BB73 -> 3251.4327
A68: WO / REVERSES | B68: =+B69-B67-B66 -> -124 | C68: =+C69-C67-C66 -> -86 | D68: =+D69-D67-D66 -> -218 | E68: =+E69-E67-E66 -> -118 | F68: =+F69-F67-F66 -> -70 | G68: =+G69-G67-G66 -> -235 | H68: =+H69-H67-H66 -> -322 | I68: =+I69-I67-I66 -> -153 | ... AC68: =+AC69-AC67-AC66 -> -730 | AD68: =+AD54/AD77 -> -400.99219 | AE68: =+AE54/AE77 -> -356.87498 | AF68: =+AF54/AF77 -> -368.52224 | AG68: =+AG54/AG77 -> -374.62041 | AI68: -393.94286 | AM68: =+SUMIFS($B68:AG68,$B$4:AG$4,"<="&AM$3,$B$4:AG$4,">"&AL$3) -> -780 | AN68: =+SUMIFS($B68:AG68,$B$4:AG$4,"<="&AN$3,$B$4:AG$4,">"&AM$3) -> -652 | AO68: =+SUMIFS($B68:AG68,$B$4:AG$4,"<="&AO$3,$B$4:AG$4,">"&AN$3) -> -216 | AP68: =+SUMIFS($B68:AG68,$B$4:AG$4,"<="&AP$3,$B$4:AG$4,">"&AO$3) -> -899 | AQ68: =+SUMIFS($B68:AG68,$B$4:AG$4,"<="&AQ$3,$B$4:AG$4,">"&AP$3) -> -1421 | AR68: =+SUMIFS($B68:AG68,$B$4:AG$4,"<="&AR$3,$B$4:AG$4,">"&AQ$3) -> -1679 | AS68: =+SUMIFS($B68:$AG68,$B$4:$AG$4,"<="&AS$3,$B$4:$AG$4,">"&AR$3) -> -1501.0098 | AT68: =+AT54/AT77 -> -1768.6111 | AU68: =+AU54/AU77 -> -2102.398 | AV68: =+AV54/AV77 -> -2342.9949 | AW68: =+AW54/AW77 -> -2442.6668 | AX68: =+AX54/AX77 -> -2772.6939 | AY68: =+AY54/AY77 -> -3064.8881 | AZ68: =+AZ54/AZ77 -> -3319.868 | BA68: =+BA54/BA77 -> -3552.0911 | BB68: =+BB54/BB77 -> -3828.3072
A69: LOAN LOSS RESERVE AT EOP | B69: 2187 | C69: 2319 | D69: 2231 | E69: 2342 | F69: 2447 | G69: 2369 | H69: 2307 | I69: 2626 | J69: 2773 | K69: 2643 | L69: 2739 | M69: 2827 | N69: 3051 | O69: 2818 | P69: 2861 | Q69: 3055 | R69: 3219 | S69: 3375 | T69: 3484 | U69: 3426 | V69: 3540 | W69: 3619 | X69: 3593 | Y69: 3653 | Z69: 3737 | AA69: 3906 | AB69: 3990 | AC69: 3731 | AD69: =+AD66+AD67+AD68 -> 3805.437 | AE69: =+AE66+AE67+AE68 -> 3931.0836 | AF69: =+AF66+AF67+AF68 -> 4051.9039 | AG69: =+AG66+AG67+AG68 -> 4189.545 | AI69: 4049.3953 | AJ69: =+AB69/AI69-1 -> -0.014667707 | AM69: =+I69 -> 2626 | AN69: =+AN66+AN67+AN68 -> 2827 | AO69: =+AO66+AO67+AO68 -> 3055 | AP69: =+AP66+AP67+AP68 -> 3426 | AQ69: =+AQ66+AQ67+AQ68 -> 3653 | AR69: =+AR66+AR67+AR68 -> 3731 | AS69: =+AS66+AS67+AS68 -> 4189.545 | AT69: =+AT66+AT67+AT68 -> 4435.9287 | AU69: =+AU66+AU67+AU68 -> 4541.193 | ... BB69: =+BB66+BB67+BB68 -> 2813.0216
Q70: =+Q67/Q$9 -> 0.0016284234 | R70: =+R67/R$9 -> 0.0020490066 | S70: =+S67/S$9 -> 0.0023392701 | T70: =+T67/T$9 -> 0.0022437545 | U70: =+U67/U$9 -> 0.001990238 | V70: =+V67/V$9 -> 0.0023643047 | W70: =+W67/W$9 -> 0.0024980655 | X70: =+X67/X$9 -> 0.0024775893 | ... AG70: =+AG67/AG$9 -> 0.0025172408 | AI70: 0.0023915166 | AM70: =+AM67/AVERAGEIFS($B$9:$AG$9,$B$4:$AG$4,">"&AL$3,$B$4:$AG$4,"<="&AM$3) -> 0.0096769719 | AN70: =+AN67/AVERAGEIFS($B$9:$AG$9,$B$4:$AG$4,">"&AM$3,$B$4:$AG$4,"<="&AN$3) -> 0.0075378494 | AO70: =+AO67/AVERAGEIFS($B$9:$AG$9,$B$4:$AG$4,">"&AN$3,$B$4:$AG$4,"<="&AO$3) -> 0.0035469137 | AP70: =+AP67/AVERAGEIFS($B$9:$AG$9,$B$4:$AG$4,">"&AO$3,$B$4:$AG$4,"<="&AP$3) -> 0.0086182619 | AQ70: =+AQ67/AVERAGEIFS($B$9:$AG$9,$B$4:$AG$4,">"&AP$3,$B$4:$AG$4,"<="&AQ$3) -> 0.0098859783 | AR70: =+AR67/AVERAGEIFS($B$9:$AG$9,$B$4:$AG$4,">"&AQ$3,$B$4:$AG$4,"<="&AR$3) -> 0.0095896953 | AS70: =+AS67/AVERAGEIFS($B$9:$AG$9,$B$4:$AG$4,">"&AR$3,$B$4:$AG$4,"<="&AS$3) -> 0.0099016371
A72: Coverage Ratio | B72: =+B69/B56 -> #DIV/0! | C72: =+C69/C56 -> #DIV/0! | D72: =+D69/D56 -> #DIV/0! | E72: =+E69/E56 -> #DIV/0! | F72: =+F69/F56 -> #DIV/0! | G72: =+G69/G56 -> #DIV/0! | H72: =+H69/H56 -> #DIV/0! | I72: =+I69/I56 -> 1.6920103 | ... AG72: =+AG69/AG56 -> 1.5727829 | AI72: 1.2278389 | AM72: =+AM69/AM56 -> 1.6920103 | AN72: =+AN69/AN56 -> 1.3241218 | AO72: =+AO69/AO56 -> 1.6558266 | AP72: =+AP69/AP56 -> 1.6687774 | AQ72: =+AQ69/AQ56 -> 1.6235556 | AR72: =+AR69/AR56 -> 1.5253475 | AS72: =+AS69/AS56 -> 1.5727829 | AT72: =+AT69/AT56 -> 1.4385474 | ... BB72: =+BB69/BB56 -> 0.46186897
A73: PROVISIONS / NPL CREATION | B73: =+B67/B59 -> #DIV/0! | C73: =+C67/C59 -> #DIV/0! | D73: =+D67/D59 -> #DIV/0! | E73: =+E67/E59 -> #DIV/0! | F73: =+F67/F59 -> #DIV/0! | G73: =+G67/G59 -> #DIV/0! | H73: =+H67/H59 -> #DIV/0! | I73: =+I67/I59 -> #DIV/0! | ... AC73: =+AC67/AC59 -> 0.55477032 | AD73: 0.55 | AE73: 0.55 | AF73: 0.55 | AG73: 0.55 | AI73: 0.7 | AM73: =+AM67/AM59 -> #DIV/0! | AN73: =+AN67/AN59 -> 0.36297872 | AO73: =+AO67/AO59 -> 0.23233909 | AP73: =+AP67/AP59 -> 0.5194274 | AQ73: =+AQ67/AQ59 -> 0.59861969 | AR73: =+AR67/AR59 -> 0.49506903 | AS73: =+AS67/AS59 -> 0.55 | AT73: =+AS73 -> 0.55 | AU73: =+AT73 -> 0.55 | AV73: =+AU73 -> 0.55 | AW73: =+AV73 -> 0.55 | AX73: =+AW73 -> 0.55 | AY73: =+AX73 -> 0.55 | AZ73: =+AY73 -> 0.55 | BA73: =+AZ73 -> 0.55 | BB73: =+BA73 -> 0.55
Y74: =+Y67/Y49 -> 0.60081191 | Z74: =+Z67/Z49 -> 0.46666667 | AA74: =+AA67/AA49 -> 0.49346017 | AB74: =+AB67/AB49 -> 0.47022587 | AC74: =+AC67/AC49 -> 0.55477032
A77: NPL W-O / LLR W-O | J77: =+J54/J68 -> 1.0888889 | K77: =+K54/K68 -> 0.93145161 | L77: =+L54/L68 -> 1.1619718 | M77: =+M54/M68 -> 1.1860465 | N77: =+N54/N68 -> -0.4981685 | O77: =+O54/O68 -> 1.0702341 | P77: =+P54/P68 -> 1.0914634 | Q77: =+Q54/Q68 -> 8.1538462 | ... AC77: =+AC54/AC68 -> 1.0315068 | AD77: 1.05 | AE77: 1.05 | AF77: 1.05 | AG77: 1.05 | AI77: 1.05 | AM77: =+AM54/AM68 -> 0 | AN77: =+AN54/AN68 -> 1.0705521 | AO77: =+AO54/AO68 -> 3.9212963 | AP77: =+AP54/AP68 -> 1.2291435 | AQ77: =+AQ54/AQ68 -> 1.0380014 | AR77: =+AR54/AR68 -> 1.0649196 | AS77: =+AS54/AS68 -> 1.05 | AT77: 1.05 | AU77: 1.05 | AV77: 1.05 | AW77: 1.05 | AX77: 1.05 | AY77: 1.05 | AZ77: 1.05 | BA77: 1.05 | BB77: 1.05
AR78: =+AR79/AQ79-1 -> 0.0088056144
A79: INTEREST INCOME | B79: 4106 | C79: 4298 | D79: 4337 | E79: 4286 | F79: 4207 | G79: 3924 | H79: 3608 | I79: 3512 | J79: 3235 | K79: 3135 | L79: 3414 | M79: 3778 | N79: 4059 | O79: 4660 | P79: 5428 | Q79: 6869 | R79: 6530 | S79: 7094 | T79: 7630 | U79: 7481 | V79: 7212 | W79: 7362 | X79: 7702 | Y79: 7932 | Z79: 7634 | AA79: 7742 | AB79: 7533 | AC79: 7565 | AD79: =+AD80*AVERAGE(AC5:AD5)/4 -> 7636.3679 | AE79: =+AE80*AVERAGE(AD5:AE5)/4 -> 7650.2515 | AF79: =+AF80*AVERAGE(AE5:AF5)/4 -> 7820.7848 | AG79: =+AG80*AVERAGE(AF5:AG5)/4 -> 7930.9865 | AI79: 7393.1668 | AJ79: =+AB79/AI79-1 -> 0.01891384 | AM79: =+SUMIFS($B79:AG79,$B$4:AG$4,"<="&AM$3,$B$4:AG$4,">"&AL$3) -> 15251 | AN79: =+SUMIFS($B79:AG79,$B$4:AG$4,"<="&AN$3,$B$4:AG$4,">"&AM$3) -> 13562 | AO79: =+SUMIFS($B79:AG79,$B$4:AG$4,"<="&AO$3,$B$4:AG$4,">"&AN$3) -> 21016 | AP79: =+SUMIFS($B79:AG79,$B$4:AG$4,"<="&AP$3,$B$4:AG$4,">"&AO$3) -> 28735 | AQ79: =+SUMIFS($B79:AG79,$B$4:AG$4,"<="&AQ$3,$B$4:AG$4,">"&AP$3) -> 30208 | AR79: =+SUMIFS($B79:AG79,$B$4:AG$4,"<="&AR$3,$B$4:AG$4,">"&AQ$3) -> 30474 | AS79: =+SUMIFS($B79:$AG79,$B$4:$AG$4,"<="&AS$3,$B$4:$AG$4,">"&AR$3) -> 31038.391 | AT79: =+AT80*AVERAGE(AS5:AT5) -> 33186.519 | AU79: =+AU80*AVERAGE(AT5:AU5) -> 35788.769 | AV79: =+AV80*AVERAGE(AU5:AV5) -> 38065.697 | AW79: =+AW80*AVERAGE(AV5:AW5) -> 40497.838 | AX79: =+AX80*AVERAGE(AW5:AX5) -> 43107.576 | AY79: =+AY80*AVERAGE(AX5:AY5) -> 45602.965 | AZ79: =+AZ80*AVERAGE(AY5:AZ5) -> 47957.344 | BA79: =+BA80*AVERAGE(AZ5:BA5) -> 50450.733 | BB79: =+BB80*AVERAGE(BA5:BB5) -> 53093.377
A80: yield | C80: =+C79/AVERAGE(B5:C5)*4 -> 0.16785292 | D80: =+D79/AVERAGE(C5:D5)*4 -> 0.16484618 | E80: =+E79/AVERAGE(D5:E5)*4 -> 0.16191304 | F80: =+F79/AVERAGE(E5:F5)*4 -> 0.15517901 | G80: =+G79/AVERAGE(F5:G5)*4 -> 0.1423751 | H80: =+H79/AVERAGE(G5:H5)*4 -> 0.13214907 | I80: =+I79/AVERAGE(H5:I5)*4 -> 0.12945974 | J80: =+J79/AVERAGE(I5:J5)*4 -> 0.11861168 | ... AC80: =+AC79/AVERAGE(AB5:AC5)*4 -> 0.16238392 | AD80: =+AD82+AVERAGE(AC81:AD81) -> 0.16138392 | AE80: =+AE82+AVERAGE(AD81:AE81) -> 0.15938392 | AF80: =+AF82+AVERAGE(AE81:AF81) -> 0.15813392 | AG80: =+AG82+AVERAGE(AF81:AG81) -> 0.15663392 | AI80: 0.158 | AJ80: =+AB80-AI80 -> 0.0069680953 | AM80: =+AM79/AVERAGE(AL5:AM5) -> 0.1426914 | AN80: =+AN79/AVERAGE(AM5:AN5) -> 0.12152166 | AO80: =+AO79/AVERAGE(AN5:AO5) -> 0.16859197 | AP80: =+AP79/AVERAGE(AO5:AP5) -> 0.20075804 | AQ80: =+AQ79/AVERAGE(AP5:AQ5) -> 0.18516271 | AR80: =+AR79/AVERAGE(AQ5:AR5) -> 0.1683679 | AS80: =+AS79/AVERAGE(AR5:AS5) -> 0.15891843 | AT80: =+AT81+AT82 -> 0.15629343 | AU80: =+AU81+AU82 -> 0.15629343 | AV80: =+AV81+AV82 -> 0.15629343 | AW80: =+AW81+AW82 -> 0.15629343 | AX80: =+AX81+AX82 -> 0.15629343 | AY80: =+AY81+AY82 -> 0.15629343 | AZ80: =+AZ81+AZ82 -> 0.15629343 | BA80: =+BA81+BA82 -> 0.15629343 | BB80: =+BB81+BB82 -> 0.15629343
A81: RFR | C81: =+C2 -> 0.084887 | D81: =+D2 -> 0.080275 | E81: =+E2 -> #VALUE! | F81: =+F2 -> #VALUE! | G81: =+G2 -> 0.052843 | H81: =+H2 -> 0.0475 | I81: =+I2 -> 0.0425 | J81: =+J2 -> 0.042875 | ... AG81: =+AG2 -> 0.068 | AI81: 0.075 | AM81: =+AVERAGEIFS($B81:AG81,$B$4:AG$4,"<="&AM$3,$B$4:AG$4,">"&AL$3) -> #VALUE! | AN81: =+AVERAGEIFS($B81:AG81,$B$4:AG$4,"<="&AN$3,$B$4:AG$4,">"&AM$3) -> 0.04819375 | AO81: =+AVERAGEIFS($B81:AG81,$B$4:AG$4,"<="&AO$3,$B$4:AG$4,">"&AN$3) -> 0.086875 | AP81: =+AVERAGEIFS($B81:AG81,$B$4:AG$4,"<="&AP$3,$B$4:AG$4,">"&AO$3) -> 0.11501325 | AQ81: =+AVERAGEIFS($B81:AG81,$B$4:AG$4,"<="&AQ$3,$B$4:AG$4,">"&AP$3) -> 0.108695 | AR81: =+AVERAGEIFS($B81:AG81,$B$4:AG$4,"<="&AR$3,$B$4:AG$4,">"&AQ$3) -> 0.084477 | AS81: =+AVERAGEIFS($B81:$AG81,$B$4:$AG$4,"<="&AS$3,$B$4:$AG$4,">"&AR$3) -> 0.070625 | AT81: =+AT$2 -> 0.068 | AU81: =+AU$2 -> 0.068 | AV81: =+AV$2 -> 0.068 | AW81: =+AW$2 -> 0.068 | AX81: =+AX$2 -> 0.068 | AY81: =+AY$2 -> 0.068 | AZ81: =+AZ$2 -> 0.068 | BA81: =+BA$2 -> 0.068 | BB81: =+BB$2 -> 0.068
A82: Spread | C82: =+C80-C81 -> 0.082965924 | D82: =+D80-D81 -> 0.084571181 | E82: =+E80-E81 -> #VALUE! | F82: =+F80-F81 -> #VALUE! | G82: =+G80-G81 -> 0.089532095 | H82: =+H80-H81 -> 0.084649071 | I82: =+I80-I81 -> 0.08695974 | J82: =+J80-J81 -> 0.075736675 | ... AC82: =+AC80-AC81 -> 0.08738392 | AD82: =+AC82 -> 0.08738392 | AE82: =+AD82 -> 0.08738392 | AF82: =+AE82 -> 0.08738392 | AG82: =+AF82 -> 0.08738392 | AI82: 0.083 | AJ82: =+AB82-AI82 -> 0.0044680953 | AM82: =+AM80-AM81 -> #VALUE! | AN82: =+AN80-AN81 -> 0.073327914 | AO82: =+AO80-AO81 -> 0.081716965 | AP82: =+AP80-AP81 -> 0.085744789 | AQ82: =+AQ80-AQ81 -> 0.07646771 | AR82: =+AR80-AR81 -> 0.083890897 | AS82: =+AS80-AS81 -> 0.088293427 | AT82: =+AS82 -> 0.088293427 | AU82: =+AT82+(AT81-AU81)*10 -> 0.088293427 | AV82: =+AU82+(AU81-AV81)*10 -> 0.088293427 | AW82: =+AV82+(AV81-AW81)*10 -> 0.088293427 | AX82: =+AW82+(AW81-AX81)*10 -> 0.088293427 | AY82: =+AX82+(AX81-AY81)*10 -> 0.088293427 | AZ82: =+AY82+(AY81-AZ81)*10 -> 0.088293427 | BA82: =+AZ82+(AZ81-BA81)*10 -> 0.088293427 | BB82: =+BA82+(BA81-BB81)*10 -> 0.088293427
Y83: (X73-Y73)*10
A84: Estimated Yields | Y84: =+X81-Y81 -> 0.00495 | AO84: =+AO80-AN80 -> 0.047070301 | AP84: =+AP80-AO80 -> 0.032166074 | AQ84: =+AQ80-AP80 -> -0.015595329 | AR84: =+AR80-AQ80 -> -0.016794813 | AS84: =+AS80-AR80 -> -0.00944947 | AT84: =+AT80-AS80 -> -0.002625
A85: MORTGAGE | Y85: =+Y84*10 -> 0.0495 | AO85: =+AO81-AN81 -> 0.03868125 | AP85: =+AP81-AO81 -> 0.02813825 | AQ85: =+AQ81-AP81 -> -0.00631825 | AR85: =+AR81-AQ81 -> -0.024218 | AS85: =+AS81-AR81 -> -0.013852 | AT85: =+AT81-AS81 -> -0.002625
A86: CONSUMER
A87: TOTAL INDIVUDUALS | AQ87: =+AQ84/AQ85 -> 2.4682988 | AR87: =+AR84/AR85 -> 0.69348474 | AS87: =+AS84/AS85 -> 0.68217369
A89: BUSINESS LOANS
A90: FINANCIAL ENTITIES
A91: GOVERNMENT ENTITIES
A92: TOTAL COMMERCIAL
A100: FUNDING | B100: =+B4 -> 43555 | C100: =+C4 -> 43646 | D100: =+D4 -> 43738 | E100: =+E4 -> 43830 | F100: =+F4 -> 43921 | G100: =+G4 -> 44012 | H100: =+H4 -> 44104 | I100: =+I4 -> 44196 | ... AG100: =+AG4 -> 46387 | AI100: 46022 | AL100: =+AL4 -> 2019 | AM100: =+AM4 -> 2020 | AN100: =+AN4 -> 2021 | AO100: =+AO4 -> 2022 | AP100: =+AP4 -> 2023 | AQ100: =+AQ4 -> 2024 | AR100: =+AR4 -> 2025 | AS100: =+AS4 -> 2026 | ... BB100: =+BB4 -> 2035
A102: TOTAL FUNDING | B102: =+B107+B113+B122+B125 -> 100432 | C102: =+C107+C113+C122+C125 -> 103163 | D102: =+D107+D113+D122+D125 -> 105687 | E102: =+E107+E113+E122+E125 -> 108850 | F102: =+F107+F113+F122+F125 -> 113480 | G102: =+G107+G113+G122+G125 -> 108897 | H102: =+H107+H113+H122+H125 -> 108029 | I102: =+I107+I113+I122+I125 -> 111470 | ... AG102: =+AG107+AG113+AG122+AG125 -> 243821.69 | AI102: 219855.94 | AJ102: =+AB102/AI102-1 -> 0.075977276 | AL102: =+SUMIFS($B102:AF102,$B$4:AF$4,"="&AL$3) -> 108850 | AM102: =+SUMIFS($B102:AG102,$B$4:AG$4,"="&AM$3) -> 111470 | AN102: =+SUMIFS($B102:AG102,$B$4:AG$4,"="&AN$3) -> 118901 | AO102: =+SUMIFS($B102:AG102,$B$4:AG$4,"="&AO$3) -> 181994 | AP102: =+SUMIFS($B102:AG102,$B$4:AG$4,"="&AP$3) -> 200636 | AQ102: =+SUMIFS($B102:AG102,$B$4:AG$4,"="&AQ$3) -> 212483 | AR102: =+SUMIFS($B102:AG102,$B$4:AG$4,"="&AR$3) -> 246304 | AS102: =+SUMIFS($B102:$AG102,$B$4:$AG$4,"="&AS$3) -> 243821.69 | AT102: =+AT107+AT113+AT122 -> 264661.24 | AU102: =+AU107+AU113+AU122 -> 280988 | AV102: =+AV107+AV113+AV122 -> 298182.73 | AW102: =+AW107+AW113+AW122 -> 316679.53 | AX102: =+AX107+AX113+AX122 -> 336420.16 | AY102: =+AY107+AY113+AY122 -> 353612.09 | AZ102: =+AZ107+AZ113+AZ122 -> 371695.95 | BA102: =+BA107+BA113+BA122 -> 390805.74 | BB102: =+BB107+BB113+BB122 -> 410968.28
A103: Funding / loans | B103: =+B102/B5 -> 1.0006975 | C103: =+C102/C5 -> 0.98735692 | D103: =+D102/D5 -> 0.99713183 | E103: =+E102/E5 -> 1.0290517 | F103: =+F102/F5 -> 1.0213486 | G103: =+G102/G5 -> 0.9955842 | H103: =+H102/H5 -> 0.99072817 | I103: =+I102/I5 -> 1.032273 | ... AG103: =+AG102/AG5 -> 1.2026181 | AI103: 1.1600761 | AL103: =+AL102/AL5 -> 1.0290517 | AM103: =+AM102/AM5 -> 1.032273 | AN103: =+AN102/AN5 -> 1.0319655 | AO103: =+AO102/AO5 -> 1.3572121 | AP103: =+AP102/AP5 -> 1.3184904 | AQ103: =+AQ102/AQ5 -> 1.2203601 | AR103: =+AR102/AR5 -> 1.3109784 | AS103: =+AS102/AS5 -> 1.2026181 | ... BB103: =+BB102/BB5 -> 1.1795771
A105: dif | B105: =+B106-B107 -> 0 | C105: =+C106-C107 -> 0 | D105: =+D106-D107 -> 0 | E105: =+E106-E107 -> 0 | F105: =+F106-F107 -> 0 | G105: =+G106-G107 -> 0 | H105: =+H106-H107 -> 0 | I105: =+I106-I107 -> 0 | ... AG105: =+AG106-AG107 -> -23437.527 | AI105: -91.55342 | AL105: =+AL106-AL107 -> 0 | AM105: =+AM106-AM107 -> 0 | AN105: =+AN106-AN107 -> 0 | AO105: =+AO106-AO107 -> 0 | AP105: =+AP106-AP107 -> 0 | AQ105: =+AQ106-AQ107 -> 0 | AR105: =+AR106-AR107 -> -10711.136 | AS105: =+AS106-AS107 -> -4497.4754 | ... BB105: =+BB106-BB107 -> -10578.423
A106: Value | B106: 7803 | C106: 5272 | D106: 7506 | E106: 9132 | F106: 10129 | G106: 9807 | H106: 10419 | I106: 11648 | J106: 11917 | K106: 12008 | L106: 11747 | M106: 12144 | N106: 15074 | O106: 13997 | P106: 12819 | Q106: 12059 | R106: 14362 | S106: 13314 | T106: 11322 | U106: 13805 | V106: 11003 | W106: 13311 | X106: 14786 | Y106: 13001 | Z106: 12531 | AA106: 16631 | AB106: 15956 | AC106: 18233 | AD106: 12361.326 | AE106: 7950.4061 | AF106: 24110.515 | AG106: -10622.453 | AI106: 7564.8766 | AL106: 9132 | AM106: 11648 | AN106: 12144 | AO106: 12059 | AP106: 13805 | AQ106: 13001 | AR106: 7521.8644 | AS106: 8317.5977 | AT106: 7744.8396 | AU106: 8249.8114 | AV106: 8949.5907 | AW106: 9691.1111 | AX106: 10441.208 | AY106: 11357.923 | AZ106: 12285.497 | BA106: 13225.285 | BB106: 14186.449
A107: Disponibilidades Total | B107: 7803 | C107: 5272 | D107: 7506 | E107: 9132 | F107: 10129 | G107: 9807 | H107: 10419 | I107: 11648 | J107: 11917 | K107: 12008 | L107: 11747 | M107: 12144 | N107: 15074 | O107: 13997 | P107: 12819 | Q107: 12059 | R107: 14362 | S107: 13314 | T107: 11322 | U107: 13805 | V107: 11003 | W107: 13311 | X107: 14786 | Y107: 13001 | Z107: 12531 | AA107: 16631 | AB107: 15956 | AC107: 18233 | AD107: =+AD152 -> 11889.419 | AE107: =+AE152 -> 12247.35 | AF107: =+AF152 -> 12306.629 | AG107: =+AG152 -> 12815.073 | AI107: 7656.43 | AL107: =+SUMIFS($B107:AF107,$B$4:AF$4,"="&AL$3) -> 9132 | AM107: =+SUMIFS($B107:AG107,$B$4:AG$4,"="&AM$3) -> 11648 | AN107: =+SUMIFS($B107:AG107,$B$4:AG$4,"="&AN$3) -> 12144 | AO107: =+SUMIFS($B107:AG107,$B$4:AG$4,"="&AO$3) -> 12059 | AP107: =+SUMIFS($B107:AG107,$B$4:AG$4,"="&AP$3) -> 13805 | AQ107: =+SUMIFS($B107:AG107,$B$4:AG$4,"="&AQ$3) -> 13001 | AR107: =+SUMIFS($B107:AG107,$B$4:AG$4,"="&AR$3) -> 18233 | AS107: =+SUMIFS($B107:$AG107,$B$4:$AG$4,"="&AS$3) -> 12815.073 | AT107: =+AT152 -> 13601.676 | AU107: =+AU152 -> 14857.312 | AV107: =+AV152 -> 16044.923 | AW107: =+AW152 -> 17426.115 | AX107: =+AX152 -> 18828.857 | AY107: =+AY152 -> 20270.096 | AZ107: =+AZ152 -> 21715.791 | BA107: =+BA152 -> 23224.149 | BB107: =+BB152 -> 24764.872
A108: Cash del banco | R108: =1944+30 -> 1974 | S108: 1972 | T108: =1972+27 -> 1999 | U108: =2480+41 -> 2521 | V108: =2126+24 -> 2150 | W108: 1632 | X108: 1832 | Y108: 2223 | Z108: 1794 | AA108: 1712 | AB108: 1628 | AC108: 2173 | AL108: =+SUMIFS($B108:AF108,$B$4:AF$4,"="&AL$3) -> 0 | AM108: =+SUMIFS($B108:AG108,$B$4:AG$4,"="&AM$3) -> 0 | AN108: =+SUMIFS($B108:AG108,$B$4:AG$4,"="&AN$3) -> 0 | AO108: =+SUMIFS($B108:AG108,$B$4:AG$4,"="&AO$3) -> 0 | AP108: =+SUMIFS($B108:AG108,$B$4:AG$4,"="&AP$3) -> 2521 | AQ108: =+SUMIFS($B108:AG108,$B$4:AG$4,"="&AQ$3) -> 2223 | AR108: =+SUMIFS($B108:AG108,$B$4:AG$4,"="&AR$3) -> 2173 | AS108: =+SUMIFS($B108:$AG108,$B$4:$AG$4,"="&AS$3) -> 0
A109: Depositos a la visa | R109: =+R107-R108 -> 12388 | S109: =+S107-S108 -> 11342 | T109: =+T107-T108 -> 9323 | U109: =+U107-U108 -> 11284 | V109: =+V107-V108 -> 8853 | W109: =+W107-W108 -> 11679 | X109: =+X107-X108 -> 12954 | Y109: =+Y107-Y108 -> 10778 | ... AC109: =+AC107-AC108 -> 16060 | AL109: =+SUMIFS($B109:AF109,$B$4:AF$4,"="&AL$3) -> 0 | AM109: =+SUMIFS($B109:AG109,$B$4:AG$4,"="&AM$3) -> 0 | AN109: =+SUMIFS($B109:AG109,$B$4:AG$4,"="&AN$3) -> 0 | AO109: =+SUMIFS($B109:AG109,$B$4:AG$4,"="&AO$3) -> 0 | AP109: =+SUMIFS($B109:AG109,$B$4:AG$4,"="&AP$3) -> 11284 | AQ109: =+SUMIFS($B109:AG109,$B$4:AG$4,"="&AQ$3) -> 10778 | AR109: =+SUMIFS($B109:AG109,$B$4:AG$4,"="&AR$3) -> 16060 | AS109: =+SUMIFS($B109:$AG109,$B$4:$AG$4,"="&AS$3) -> 0
A113: Deposits (captacion tradicional) | B113: =+B116+B118 -> 92629 | C113: =+C116+C118 -> 97891 | D113: =+D116+D118 -> 98181 | E113: =+E116+E118 -> 99718 | F113: =+F116+F118 -> 103351 | G113: =+G116+G118 -> 99090 | H113: =+H116+H118 -> 97610 | I113: =+I116+I118 -> 99822 | ... AC113: =+AC116+AC118 -> 190547 | AD113: =+AD115*AD5 -> 188759.52 | AE113: =+AE115*AE5 -> 191391.7 | AF113: =+AF115*AF5 -> 200305.51 | AG113: =+AG115*AG5 -> 200714.99 | AI113: 182932.24 | AL113: =+SUMIFS($B113:AF113,$B$4:AF$4,"="&AL$3) -> 99718 | AM113: =+SUMIFS($B113:AG113,$B$4:AG$4,"="&AM$3) -> 99822 | AN113: =+SUMIFS($B113:AG113,$B$4:AG$4,"="&AN$3) -> 106757 | AO113: =+SUMIFS($B113:AG113,$B$4:AG$4,"="&AO$3) -> 126329 | AP113: =+SUMIFS($B113:AG113,$B$4:AG$4,"="&AP$3) -> 150317 | AQ113: =+SUMIFS($B113:AG113,$B$4:AG$4,"="&AQ$3) -> 168064 | AR113: =+SUMIFS($B113:AG113,$B$4:AG$4,"="&AR$3) -> 190547 | AS113: =+SUMIFS($B113:$AG113,$B$4:$AG$4,"="&AS$3) -> 200714.99 | AT113: =+AT115*AT5 -> 219707.73 | AU113: =+AU115*AU5 -> 233681.54 | AV113: =+AV115*AV5 -> 248552.94 | AW113: =+AW115*AW5 -> 264493.07 | AX113: =+AX115*AX5 -> 281614.35 | AY113: =+AY115*AY5 -> 296105.85 | AZ113: =+AZ115*AZ5 -> 311440.75 | BA113: =+BA115*BA5 -> 327693.31 | BB113: =+BB115*BB5 -> 344919.03
A114: yoy | F114: =+F113/B113-1 -> 0.11575209 | G114: =+G113/C113-1 -> 0.012248317 | H114: =+H113/D113-1 -> -0.0058157892 | I114: =+I113/E113-1 -> 0.0010429411 | J114: =+J113/F113-1 -> -0.01542317 | K114: =+K113/G113-1 -> 0.072398829 | L114: =+L113/H113-1 -> 0.09098453 | M114: =+M113/I113-1 -> 0.069473663 | ... AG114: =+AG113/AC113-1 -> 0.053362106 | AI114: 0.088467741 | AM114: =+AM113/AL113-1 -> 0.0010429411 | AN114: =+AN113/AM113-1 -> 0.069473663 | AO114: =+AO113/AN113-1 -> 0.18333224 | AP114: =+AP113/AO113-1 -> 0.18988514 | AQ114: =+AQ113/AP113-1 -> 0.11806383 | AR114: =+AR113/AQ113-1 -> 0.13377642 | AS114: =+AS113/AR113-1 -> 0.053362106 | AT114: =+AT113/AS113-1 -> 0.094625432 | ... BB114: =+BB113/BA113-1 -> 0.052566601
A115: % net portfolio | B115: =+B113/B5 -> 0.92294892 | C115: =+C113/C5 -> 0.93689943 | D115: =+D113/D5 -> 0.9263145 | E115: =+E113/E5 -> 0.94271912 | F115: =+F113/F5 -> 0.93018505 | G115: =+G113/G5 -> 0.9059243 | H115: =+H113/H5 -> 0.89517608 | I115: =+I113/I5 -> 0.92440617 | ... AC115: =+AC113/AC5 -> 1.014206 | AD115: 0.99 | AE115: 0.99 | AF115: 0.99 | AG115: 0.99 | AI115: 0.96524711 | AL115: =+AL113/AL5 -> 0.94271912 | AM115: =+AM113/AM5 -> 0.92440617 | AN115: =+AN113/AN5 -> 0.92656529 | AO115: =+AO113/AO5 -> 0.94209286 | AP115: =+AP113/AP5 -> 0.98781634 | AQ115: =+AQ113/AQ5 -> 0.96524711 | AR115: =+AR113/AR5 -> 1.014206 | AS115: =+AS113/AS5 -> 0.99 | AT115: =+AS115 -> 0.99 | AU115: =+AT115 -> 0.99 | AV115: =+AU115 -> 0.99 | AW115: =+AV115 -> 0.99 | AX115: =+AW115 -> 0.99 | AY115: =+AX115 -> 0.99 | AZ115: =+AY115 -> 0.99 | BA115: =+AZ115 -> 0.99 | BB115: =+BA115 -> 0.99
A116: Demand Deposits | B116: 37260 | C116: 37663 | D116: 38259 | E116: 39947 | F116: 44895 | G116: 44836 | H116: 46449 | I116: 48159 | J116: 53380 | K116: 58659 | L116: 61079 | M116: 61785 | N116: 70785 | O116: 75949 | P116: 71760 | Q116: 72024 | R116: 74474 | S116: 73829 | T116: 70700 | U116: 74696 | V116: 72629 | W116: 77522 | X116: 75049 | Y116: 76695 | Z116: 79983 | AA116: 82269 | AB116: 81687 | AC116: 87162 | AD116: =+AC116*(1+AD$1) -> 87927.793 | AE116: =+AD116*(1+AE$1) -> 88713.804 | AF116: =+AE116*(1+AF$1) -> 88990.425 | AG116: =+AF116*(1+AG$1) -> 90212.67 | AI116: 92946.281 | AL116: =+SUMIFS($B116:AF116,$B$4:AF$4,"="&AL$3) -> 39947 | AM116: =+SUMIFS($B116:AG116,$B$4:AG$4,"="&AM$3) -> 48159 | AN116: =+SUMIFS($B116:AG116,$B$4:AG$4,"="&AN$3) -> 61785 | AO116: =+SUMIFS($B116:AG116,$B$4:AG$4,"="&AO$3) -> 72024 | AP116: =+SUMIFS($B116:AG116,$B$4:AG$4,"="&AP$3) -> 74696 | AQ116: =+SUMIFS($B116:AG116,$B$4:AG$4,"="&AQ$3) -> 76695 | AR116: =+SUMIFS($B116:AG116,$B$4:AG$4,"="&AR$3) -> 87162 | AS116: =+SUMIFS($B116:$AG116,$B$4:$AG$4,"="&AS$3) -> 90212.67 | AT116: =+AS116*(1+AT$1) -> 93370.113 | AU116: =+AT116*(1+AU$1) -> 96638.067 | AV116: =+AU116*(1+AV$1) -> 100020.4 | AW116: =+AV116*(1+AW$1) -> 103521.11 | AX116: =+AW116*(1+AX$1) -> 107144.35 | AY116: =+AX116*(1+AY$1) -> 110894.41 | AZ116: =+AY116*(1+AZ$1) -> 114775.71 | BA116: =+AZ116*(1+BA$1) -> 118792.86 | BB116: =+BA116*(1+BB$1) -> 122950.61
A117: Avg rate | N117: 0.015 | O117: 0.022 | P117: 0.021 | Q117: 0.02 | R117: 0.023 | S117: 0.026 | T117: 0.024 | U117: 0.016 | V117: 0.021 | W117: 0.02 | X117: 0.02 | Y117: 0.017 | Z117: 0.019 | AA117: 0.017 | AB117: 0.016 | AC117: 0.013 | AD117: 0.01 | AE117: 0.01 | AF117: =+AE117 -> 0.01 | AG117: =+AF117 -> 0.01 | AI117: 0.016 | AJ117: =+AB117-AI117 -> 0 | AM117: =+AVERAGEIFS($B117:AG117,$B$4:AG$4,"<="&AM$3,$B$4:AG$4,">"&AL$3) -> #DIV/0! | AN117: =+AVERAGEIFS($B117:AG117,$B$4:AG$4,"<="&AN$3,$B$4:AG$4,">"&AM$3) -> #DIV/0! | AO117: =+AVERAGEIFS($B117:AG117,$B$4:AG$4,"<="&AO$3,$B$4:AG$4,">"&AN$3) -> 0.0195 | AP117: =+AVERAGEIFS($B117:AG117,$B$4:AG$4,"<="&AP$3,$B$4:AG$4,">"&AO$3) -> 0.02225 | AQ117: =+AVERAGEIFS($B117:AG117,$B$4:AG$4,"<="&AQ$3,$B$4:AG$4,">"&AP$3) -> 0.0195 | AR117: =+AVERAGEIFS($B117:AG117,$B$4:AG$4,"<="&AR$3,$B$4:AG$4,">"&AQ$3) -> 0.01625 | AS117: =+AVERAGEIFS($B117:$AG117,$B$4:$AG$4,"<="&AS$3,$B$4:$AG$4,">"&AR$3) -> 0.01 | AT117: =+AS117 -> 0.01 | AU117: =+AT117 -> 0.01 | AV117: =+AU117 -> 0.01 | AW117: =+AV117 -> 0.01 | AX117: =+AW117 -> 0.01 | AY117: =+AX117 -> 0.01 | AZ117: =+AY117 -> 0.01 | BA117: =+AZ117 -> 0.01 | BB117: =+BA117 -> 0.01
A118: Time Deposits | B118: 55369 | C118: 60228 | D118: 59922 | E118: 59771 | F118: 58456 | G118: 54254 | H118: 51161 | I118: 51663 | J118: 48377 | K118: 47605 | L118: 45412 | M118: 44972 | N118: 44512 | O118: 48308 | P118: 53759 | Q118: 54305 | R118: 62366 | S118: 75137 | T118: 81019 | U118: 75621 | V118: 84880 | W118: 86122 | X118: 93506 | Y118: 91369 | Z118: 96481 | AA118: 92252 | AB118: 101550 | AC118: 103385 | AD118: =+AD113-AD116 -> 100831.72 | AE118: =+AE113-AE116 -> 102677.9 | AF118: =+AF113-AF116 -> 111315.09 | AG118: =+AG113-AG116 -> 110502.32 | AI118: 89985.961 | AL118: =+SUMIFS($B118:AF118,$B$4:AF$4,"="&AL$3) -> 59771 | AM118: =+SUMIFS($B118:AG118,$B$4:AG$4,"="&AM$3) -> 51663 | AN118: =+SUMIFS($B118:AG118,$B$4:AG$4,"="&AN$3) -> 44972 | AO118: =+SUMIFS($B118:AG118,$B$4:AG$4,"="&AO$3) -> 54305 | AP118: =+SUMIFS($B118:AG118,$B$4:AG$4,"="&AP$3) -> 75621 | AQ118: =+SUMIFS($B118:AG118,$B$4:AG$4,"="&AQ$3) -> 91369 | AR118: =+SUMIFS($B118:AG118,$B$4:AG$4,"="&AR$3) -> 103385 | AS118: =+SUMIFS($B118:$AG118,$B$4:$AG$4,"="&AS$3) -> 110502.32 | AT118: =+AT113-AT116 -> 126337.62 | AU118: =+AU113-AU116 -> 137043.47 | AV118: =+AV113-AV116 -> 148532.54 | AW118: =+AW113-AW116 -> 160971.96 | AX118: =+AX113-AX116 -> 174470 | AY118: =+AY113-AY116 -> 185211.45 | AZ118: =+AZ113-AZ116 -> 196665.04 | BA118: =+BA113-BA116 -> 208900.45 | BB118: =+BB113-BB116 -> 221968.42
A119: Avg rate | N119: 0.055 | O119: 0.064 | P119: 0.076 | Q119: 0.088 | R119: 0.098 | S119: 0.103 | T119: 0.102 | U119: 0.101 | V119: 0.101 | W119: 0.099 | X119: 0.099 | Y119: 0.094 | Z119: 0.088 | AA119: 0.08 | AB119: 0.07 | AC119: 0.067 | AD119: =+AD120*AD123 -> 0.062906752 | AE119: =+AE120*AE123 -> 0.06118328 | AF119: =+AF120*AF123 -> 0.060752412 | AG119: =+AG120*AG123 -> 0.058598071 | AI119: 0.069 | AJ119: =+AB119-AI119 -> 0.001 | AM119: =+AVERAGEIFS($B119:AG119,$B$4:AG$4,"<="&AM$3,$B$4:AG$4,">"&AL$3) -> #DIV/0! | AN119: =+AVERAGEIFS($B119:AG119,$B$4:AG$4,"<="&AN$3,$B$4:AG$4,">"&AM$3) -> #DIV/0! | AO119: =+AVERAGEIFS($B119:AG119,$B$4:AG$4,"<="&AO$3,$B$4:AG$4,">"&AN$3) -> 0.07075 | AP119: =+AVERAGEIFS($B119:AG119,$B$4:AG$4,"<="&AP$3,$B$4:AG$4,">"&AO$3) -> 0.101 | AQ119: =+AVERAGEIFS($B119:AG119,$B$4:AG$4,"<="&AQ$3,$B$4:AG$4,">"&AP$3) -> 0.09825 | AR119: =+AVERAGEIFS($B119:AG119,$B$4:AG$4,"<="&AR$3,$B$4:AG$4,">"&AQ$3) -> 0.07625 | AS119: =+AVERAGEIFS($B119:$AG119,$B$4:$AG$4,"<="&AS$3,$B$4:$AG$4,">"&AR$3) -> 0.060860129 | AT119: =+AT120*AT123 -> 0.05916 | AU119: =+AU120*AU123 -> 0.05916 | AV119: =+AV120*AV123 -> 0.05916 | AW119: =+AW120*AW123 -> 0.05916 | AX119: =+AX120*AX123 -> 0.05916 | AY119: =+AY120*AY123 -> 0.05916 | AZ119: =+AZ120*AZ123 -> 0.05916 | BA119: =+BA120*BA123 -> 0.05916 | BB119: =+BB120*BB123 -> 0.05916
N120: =+N119/AVERAGE(M123:N123) -> 0.88495575 | O120: =+O119/AVERAGE(N123:O123) -> 0.86779661 | P120: =+P119/AVERAGE(O123:P123) -> 0.867085 | Q120: =+Q119/AVERAGE(P123:Q123) -> 0.88 | R120: =+R119/AVERAGE(Q123:R123) -> 0.89090909 | S120: =+S119/AVERAGE(R123:S123) -> 0.89565217 | T120: =+T119/AVERAGE(S123:T123) -> 0.88684856 | U120: =+U119/AVERAGE(T123:U123) -> 0.87805853 | ... AC120: =+AC119/AVERAGE(AB123:AC123) -> 0.86173633 | AD120: =+AC120 -> 0.86173633 | AE120: =+AD120 -> 0.86173633 | AF120: =+AE120 -> 0.86173633 | AG120: =+AF120 -> 0.86173633 | AI120: 0.92 | AM120: =+AM119/AM123 -> #DIV/0! | AN120: =+AN119/AN123 -> #DIV/0! | AO120: =+AO119/AO123 -> 0.81438849 | AP120: =+AP119/AP123 -> 0.87815969 | AQ120: =+AQ119/AQ123 -> 0.90390542 | AR120: =+AR119/AR123 -> 0.89466953 | AS120: =+AS119/AS123 -> 0.86173633 | AT120: 0.87 | AU120: 0.87 | AV120: 0.87 | AW120: 0.87 | AX120: 0.87 | AY120: 0.87 | AZ120: 0.87 | BA120: 0.87 | BB120: 0.87
A122: Interbank Loans | N122: =5817 -> 5817 | O122: =5491 -> 5491 | P122: =5056 -> 5056 | Q122: =5367 -> 5367 | R122: =4871 -> 4871 | S122: 4522 | T122: =4387 -> 4387 | U122: 4221 | V122: =3736 -> 3736 | W122: =3785 -> 3785 | X122: =3774 -> 3774 | Y122: =3830 -> 3830 | Z122: =3363 -> 3363 | AA122: =3487 -> 3487 | AB122: 3553 | AC122: 3524 | AD122: =+PROJ!AD61+PROJ!AD58 -> 29524.41 | AE122: =+PROJ!AE61+PROJ!AE58 -> 29788.337 | AF122: =+PROJ!AF61+PROJ!AF58 -> 29881.221 | AG122: =+PROJ!AG61+PROJ!AG58 -> 30291.626 | AI122: 29267.272 | AL122: =+SUMIFS($B122:AF122,$B$4:AF$4,"="&AL$3) -> 0 | AM122: =+SUMIFS($B122:AG122,$B$4:AG$4,"="&AM$3) -> 0 | AN122: =+SUMIFS($B122:AG122,$B$4:AG$4,"="&AN$3) -> 0 | AO122: =+SUMIFS($B122:AG122,$B$4:AG$4,"="&AO$3) -> 5367 | AP122: =+SUMIFS($B122:AG122,$B$4:AG$4,"="&AP$3) -> 4221 | AQ122: =+SUMIFS($B122:AG122,$B$4:AG$4,"="&AQ$3) -> 3830 | AR122: =+SUMIFS($B122:AG122,$B$4:AG$4,"="&AR$3) -> 3524 | AS122: =+SUMIFS($B122:$AG122,$B$4:$AG$4,"="&AS$3) -> 30291.626 | AT122: =+PROJ!AT61+PROJ!AT58 -> 31351.833 | AU122: =+PROJ!AU61+PROJ!AU58 -> 32449.148 | AV122: =+PROJ!AV61+PROJ!AV58 -> 33584.868 | AW122: =+PROJ!AW61+PROJ!AW58 -> 34760.338 | AX122: =+PROJ!AX61+PROJ!AX58 -> 35976.95 | AY122: =+PROJ!AY61+PROJ!AY58 -> 37236.143 | AZ122: =+PROJ!AZ61+PROJ!AZ58 -> 38539.408 | BA122: =+PROJ!BA61+PROJ!BA58 -> 39888.288 | BB122: =+PROJ!BB61+PROJ!BB58 -> 41284.378
A123: tasa ref | B123: =+B2 -> 0.08515 | C123: =+C2 -> 0.084887 | D123: =+D2 -> 0.080275 | E123: =+E2 -> #VALUE! | F123: =+F2 -> #VALUE! | G123: =+G2 -> 0.052843 | H123: =+H2 -> 0.0475 | I123: =+I2 -> 0.0425 | ... AB123: =+AB2 -> 0.0775 | AC123: 0.078 | AD123: =+AD2 -> 0.073 | AE123: =+AE2 -> 0.071 | AF123: =+AF2 -> 0.0705 | AG123: =+AG2 -> 0.068 | AI123: 0.075 | AM123: =+AVERAGEIFS($B123:AG123,$B$4:AG$4,"<="&AM$3,$B$4:AG$4,">"&AL$3) -> #VALUE! | AN123: =+AVERAGEIFS($B123:AG123,$B$4:AG$4,"<="&AN$3,$B$4:AG$4,">"&AM$3) -> 0.04819375 | AO123: =+AVERAGEIFS($B123:AG123,$B$4:AG$4,"<="&AO$3,$B$4:AG$4,">"&AN$3) -> 0.086875 | AP123: =+AVERAGEIFS($B123:AG123,$B$4:AG$4,"<="&AP$3,$B$4:AG$4,">"&AO$3) -> 0.11501325 | AQ123: =+AVERAGEIFS($B123:AG123,$B$4:AG$4,"<="&AQ$3,$B$4:AG$4,">"&AP$3) -> 0.108695 | AR123: =+AVERAGEIFS($B123:AG123,$B$4:AG$4,"<="&AR$3,$B$4:AG$4,">"&AQ$3) -> 0.085227 | AS123: =+AVERAGEIFS($B123:$AG123,$B$4:$AG$4,"<="&AS$3,$B$4:$AG$4,">"&AR$3) -> 0.070625 | AT123: =+AT2 -> 0.068 | AU123: =+AU2 -> 0.068 | AV123: =+AV2 -> 0.068 | AW123: =+AW2 -> 0.068 | AX123: =+AX2 -> 0.068 | AY123: =+AY2 -> 0.068 | AZ123: =+AZ2 -> 0.068 | BA123: =+BA2 -> 0.068 | BB123: =+BB2 -> 0.068
A125: Acreedores por reporto | N125: 21074 | O125: 17545 | P125: 30171 | Q125: 38239 | R125: 38171 | S125: =40582 -> 40582 | T125: 38980 | U125: =32293 -> 32293 | V125: 19097 | W125: 19566 | X125: 22619 | Y125: 27588 | Z125: 25163 | AA125: 36551 | AB125: 33814 | AC125: 34000
A127: Interest Expense - real - | B127: -2230 | C127: -2393 | D127: -2351 | E127: -2352 | F127: -2244 | G127: -2068 | H127: -1790 | I127: -1637 | J127: -1417 | K127: -1294 | L127: -1527 | M127: -1756 | N127: -1969 | O127: -2404 | P127: -2906 | Q127: -3376 | R127: -3709 | S127: -4164 | T127: -4372 | U127: -4104 | V127: -3779 | W127: -3838 | X127: -4050 | Y127: -4164 | Z127: -3911 | AA127: -3927 | AB127: -3628 | AC127: -3543 | AD127: =+AD128+AD129 -> -3624.3772 | AE127: =+AE128+AE129 -> -3816.729 | AF127: =+AF128+AF129 -> -3901.2761 | AG127: =+AG128+AG129 -> -3903.7486 | AI127: -3480.4201 | AJ127: =+AB127/AI127-1 -> 0.042402902 | AL127: =+SUMIFS($B127:AF127,$B$4:AF$4,"<="&AL$3,$B$4:AF$4,">"&AK$3) -> 0 | AM127: =+SUMIFS($B127:AG127,$B$4:AG$4,"<="&AM$3,$B$4:AG$4,">"&AL$3) -> -7739 | AN127: =+SUMIFS($B127:AG127,$B$4:AG$4,"<="&AN$3,$B$4:AG$4,">"&AM$3) -> -5994 | AO127: =+SUMIFS($B127:AG127,$B$4:AG$4,"<="&AO$3,$B$4:AG$4,">"&AN$3) -> -10655 | AP127: =+SUMIFS($B127:AG127,$B$4:AG$4,"<="&AP$3,$B$4:AG$4,">"&AO$3) -> -16349 | AQ127: =+SUMIFS($B127:AG127,$B$4:AG$4,"<="&AQ$3,$B$4:AG$4,">"&AP$3) -> -15831 | AR127: =+SUMIFS($B127:AG127,$B$4:AG$4,"<="&AR$3,$B$4:AG$4,">"&AQ$3) -> -15009 | AS127: =+SUMIFS($B127:$AG127,$B$4:$AG$4,"<="&AS$3,$B$4:$AG$4,">"&AR$3) -> -15246.131 | AT127: =+AT128+AT129 -> -16345.812 | AU127: =+AU128+AU129 -> -17489.433 | AV127: =+AV128+AV129 -> -18518.308 | AW127: =+AW128+AW129 -> -19612.809 | AX127: =+AX128+AX129 -> -20781.638 | AY127: =+AY128+AY129 -> -21915.721 | AZ127: =+AZ128+AZ129 -> -23005.407 | BA127: =+BA128+BA129 -> -24155.984 | BB127: =+BB128+BB129 -> -25371.66
A128: Cost of funding | B128: =-(B117*AVERAGE(A116:B116)+B119*AVERAGE(A118:B118)+B123*AVERAGE(A122:B122))/4 -> #DIV/0! | C128: =-(C117*AVERAGE(B116:C116)+C119*AVERAGE(B118:C118)+C123*AVERAGE(B122:C122))/4 -> #DIV/0! | D128: =-(D117*AVERAGE(C116:D116)+D119*AVERAGE(C118:D118)+D123*AVERAGE(C122:D122))/4 -> #DIV/0! | E128: =-(E117*AVERAGE(D116:E116)+E119*AVERAGE(D118:E118)+E123*AVERAGE(D122:E122))/4 -> #VALUE! | F128: =-(F117*AVERAGE(E116:F116)+F119*AVERAGE(E118:F118)+F123*AVERAGE(E122:F122))/4 -> #VALUE! | G128: =-(G117*AVERAGE(F116:G116)+G119*AVERAGE(F118:G118)+G123*AVERAGE(F122:G122))/4 -> #DIV/0! | H128: =-(H117*AVERAGE(G116:H116)+H119*AVERAGE(G118:H118)+H123*AVERAGE(G122:H122))/4 -> #DIV/0! | I128: =-(I117*AVERAGE(H116:I116)+I119*AVERAGE(H118:I118)+I123*AVERAGE(H122:I122))/4 -> #DIV/0! | ... AG128: =-(AG117*AVERAGE(AF116:AG116)+AG119*AVERAGE(AF118:AG118)+AG123*AVERAGE(AF122:AG122))/4 -> -2360.2321 | AI128: -2645.9605 | AL128: =+SUMIFS($B128:AF128,$B$4:AF$4,"<="&AL$3,$B$4:AF$4,">"&AK$3) -> 0 | AM128: =+SUMIFS($B128:AG128,$B$4:AG$4,"<="&AM$3,$B$4:AG$4,">"&AL$3) -> #VALUE! | AN128: =+SUMIFS($B128:AG128,$B$4:AG$4,"<="&AN$3,$B$4:AG$4,">"&AM$3) -> #DIV/0! | AO128: =+SUMIFS($B128:AG128,$B$4:AG$4,"<="&AO$3,$B$4:AG$4,">"&AN$3) -> -5388.6635 | AP128: =+SUMIFS($B128:AG128,$B$4:AG$4,"<="&AP$3,$B$4:AG$4,">"&AO$3) -> -9329.746 | AQ128: =+SUMIFS($B128:AG128,$B$4:AG$4,"<="&AQ$3,$B$4:AG$4,">"&AP$3) -> -10420.093 | AR128: =+SUMIFS($B128:AG128,$B$4:AG$4,"<="&AR$3,$B$4:AG$4,">"&AQ$3) -> -8984.8965 | AS128: =+SUMIFS($B128:$AG128,$B$4:$AG$4,"<="&AS$3,$B$4:$AG$4,">"&AR$3) -> -9163.1553 | AT128: =-(AT117*AVERAGE(AS116:AT116)+AT119*AVERAGE(AS118:AT118)+AT123*AVERAGE(AS122:AT122)) -> -10019.517 | AU128: =-(AU117*AVERAGE(AT116:AU116)+AU119*AVERAGE(AT118:AU118)+AU123*AVERAGE(AT122:AU122)) -> -10910.087 | AV128: =-(AV117*AVERAGE(AU116:AV116)+AV119*AVERAGE(AU118:AV118)+AV123*AVERAGE(AU122:AV122)) -> -11675.787 | AW128: =-(AW117*AVERAGE(AV116:AW116)+AW119*AVERAGE(AV118:AW118)+AW123*AVERAGE(AV122:AW122)) -> -12496.588 | AX128: =-(AX117*AVERAGE(AW116:AX116)+AX119*AVERAGE(AW118:AX118)+AX123*AVERAGE(AW122:AX122)) -> -13380.768 | AY128: =-(AY117*AVERAGE(AX116:AY116)+AY119*AVERAGE(AX118:AY118)+AY123*AVERAGE(AX122:AY122)) -> -14218.816 | AZ128: =-(AZ117*AVERAGE(AY116:AZ116)+AZ119*AVERAGE(AY118:AZ118)+AZ123*AVERAGE(AY122:AZ122)) -> -15000.626 | BA128: =-(BA117*AVERAGE(AZ116:BA116)+BA119*AVERAGE(AZ118:BA118)+BA123*AVERAGE(AZ122:BA122)) -> -15831.012 | BB128: =-(BB117*AVERAGE(BA116:BB116)+BB119*AVERAGE(BA118:BB118)+BB123*AVERAGE(BA122:BB122)) -> -16713.689
A129: other cost of funding | N129: =+N127-N128 -> -1007.5032 | O129: =+O127-O128 -> -1144.4174 | P129: =+P127-P128 -> -1423.3818 | Q129: =+Q127-Q128 -> -1691.0341 | R129: =+R127-R128 -> -1711.4272 | S129: =+S127-S128 -> -1776.6398 | T129: =+T127-T128 -> -1819.3259 | U129: =+U127-U128 -> -1711.8611 | ... AC129: =+AC127-AC128 -> -1483.289 | AD129: =+AC129*1.01 -> -1498.1219 | AE129: =+AD129*1.01 -> -1513.1031 | AF129: =+AE129*1.01 -> -1528.2341 | AG129: =+AF129*1.01 -> -1543.5165 | AI129: -834.45956 | AL129: =+AL127-AL128 -> 0 | AM129: =+AM127-AM128 -> #VALUE! | AN129: =+AN127-AN128 -> #DIV/0! | AO129: =+AO127-AO128 -> -5266.3365 | AP129: =+AP127-AP128 -> -7019.254 | AQ129: =+AQ127-AQ128 -> -5410.9072 | AR129: =+AR127-AR128 -> -6024.1035 | AS129: =+AS127-AS128 -> -6082.9756 | AT129: =+AS129*1.04 -> -6326.2946 | AU129: =+AT129*1.04 -> -6579.3464 | AV129: =+AU129*1.04 -> -6842.5203 | AW129: =+AV129*1.04 -> -7116.2211 | AX129: =+AW129*1.04 -> -7400.8699 | AY129: =+AX129*1.04 -> -7696.9047 | AZ129: =+AY129*1.04 -> -8004.7809 | BA129: =+AZ129*1.04 -> -8324.9722 | BB129: =+BA129*1.04 -> -8657.9711
A130: % funding | N130: =+N129/N102 -> -0.0064065264 | O130: =+O129/O102 -> -0.0070954024 | P130: =+P129/P102 -> -0.008200857 | Q130: =+Q129/Q102 -> -0.0092917026 | R130: =+R129/R102 -> -0.0088107084 | S130: =+S129/S102 -> -0.0085669085 | T130: =+T129/T102 -> -0.008814222 | U130: =+U129/U102 -> -0.0085321732 | ... AG130: =+AG129/AG102 -> -0.0063305135 | AI130: -0.0037954833 | AO130: =+AO129/AO102 -> -0.028936869 | AP130: =+AP129/AP102 -> -0.034985018 | AQ130: =+AQ129/AQ102 -> -0.02546513 | AR130: =+AR129/AR102 -> -0.024458001 | AS130: =+AS129/AS102 -> -0.02494846 | AT130: =+AT129/AT102 -> -0.023903367 | AU130: =+AU129/AU102 -> -0.023415045 | AV130: =+AV129/AV102 -> -0.022947406 | ... BB130: =+BB129/BB102 -> -0.021067249
A132: Cost of fundaing rate | B132: =-B127/B102*4 -> 0.088816314 | C132: =-C127/C102*4 -> 0.092785204 | D132: =-D127/D102*4 -> 0.088979723 | E132: =-E127/E102*4 -> 0.086430868 | F132: =-F127/F102*4 -> 0.079097638 | G132: =-G127/G102*4 -> 0.075961689 | H132: =-H127/H102*4 -> 0.066278499 | I132: =-I127/I102*4 -> 0.058742262 | ... AG132: =-AG127/AG102*4 -> 0.064042679 | AI132: 0.063321828 | AM132: =-AM127/AVERAGE(AL102:AM102) -> 0.07025236 | AN132: =-AN127/AVERAGE(AM102:AN102) -> 0.0520378 | AO132: =-AO127/AVERAGE(AN102:AO102) -> 0.070822048 | AP132: =-AP127/AVERAGE(AO102:AP102) -> 0.085455923 | AQ132: =-AQ127/AVERAGE(AP102:AQ102) -> 0.076641355 | AR132: =-AR127/AVERAGE(AQ102:AR102) -> 0.065429055 | AS132: =-AS127/AVERAGE(AR102:AS102) -> 0.062213148 | AT132: =-AT127/AVERAGE(AS102:AT102) -> 0.064292469 | ... BB132: =-BB127/AVERAGE(BA102:BB102) -> 0.063288806
A133: % RFR | B133: =+B132/B123 -> 1.0430571 | C133: =+C132/C123 -> 1.0930437 | D133: =+D132/D123 -> 1.1084363 | E133: =+E132/E123 -> #VALUE! | F133: =+F132/F123 -> #VALUE! | G133: =+G132/G123 -> 1.4374977 | H133: =+H132/H123 -> 1.3953368 | I133: =+I132/I123 -> 1.3821709 | ... AG133: =+AG132/AG123 -> 0.94180411 | AI133: 0.84429104 | AM133: =+AM132/AM123 -> #VALUE! | AN133: =+AN132/AN123 -> 1.0797624 | AO133: =+AO132/AO123 -> 0.81521781 | AP133: =+AP132/AP123 -> 0.74300938 | AQ133: =+AQ132/AQ123 -> 0.7051047 | AR133: =+AR132/AR123 -> 0.76770337 | AS133: =+AS132/AS123 -> 0.88089413 | AT133: =+AT132/AT123 -> 0.94547749 | ... BB133: =+BB132/BB123 -> 0.93071773
...

Sheet Graficos
V2: RFR | W2: =+FAT!AQ$2 -> 0.10245 | X2: =+FAT!AR$2 -> 0.075 | Y2: =+FAT!AS$2 -> 0.068
K5: NIM | L5: RFR | W5: 2024 | X5: 2025 | Y5: 2026
K6: =+X23 -> 0.085917318 | L6: =+M6-1% -> 0.0505 | M6: =+N6-1% -> 0.0605 | N6: =+O6-1% -> 0.0705 | O6: 0.0805 | P6: =+O6+1% -> 0.0905 | Q6: =+P6+1% -> 0.1005 | R6: =+Q6+1% -> 0.1105 | S6: =+R6+1% -> 0.1205 | V6: Portfolio | W6: =+FAT!AQ5 -> 174115 | X6: =+W6*(1+X7) -> 187878 | Y6: =+X6*(1+Y7) -> 202742.41
J7: portfolio growth | K7: =+K8-2% -> 0.04 | L7: 0.084314903 | M7: 0.084398865 | N7: 0.084482826 | O7: 0.084566788 | P7: 0.08465075 | Q7: 0.084734711 | R7: 0.084818673 | S7: 0.084902635 | V7: yoy | X7: =+FAT!AR15 -> 0.079045458 | Y7: =+FAT!AS15 -> 0.079117371
K8: =+K9-2% -> 0.06 | L8: 0.084801078 | M8: 0.084981312 | N8: 0.085161545 | O8: 0.085341779 | P8: 0.085522013 | Q8: 0.085702247 | R8: 0.085882481 | S8: 0.086062715
K9: =+K10-2% -> 0.08 | L9: 0.085277903 | M9: 0.085552558 | N9: 0.085827212 | O9: 0.086101867 | P9: 0.086376522 | Q9: 0.086651176 | R9: 0.086925831 | S9: 0.087200486
K10: 0.1 | L10: 0.085745646 | M10: 0.086112923 | N10: 0.0864802 | O10: 0.086847477 | P10: 0.087214754 | Q10: 0.087582031 | R10: 0.087949308 | S10: 0.088316585 | V10: NII | W10: =+FAT!AQ80 -> 0.18516271 | X10: =+X11+X12 -> 0.1588909 | Y10: =+Y11+Y12 -> 0.15629343
K11: =+K10+2% -> 0.12 | L11: 0.086204563 | M11: 0.086662715 | N11: 0.087120867 | O11: 0.087579019 | P11: 0.08803717 | Q11: 0.088495322 | R11: 0.088953474 | S11: 0.089411626 | V11: RFR | W11: =+W$2 -> 0.10245 | X11: =+X$2 -> 0.075 | Y11: =+Y$2 -> 0.068
K12: 0.13 | L12: 0.08643079 | M12: 0.086933739 | N12: 0.087436688 | O12: 0.087939638 | P12: 0.088442587 | Q12: 0.088945536 | R12: 0.089448485 | S12: 0.089951434 | W12: =+FAT!AQ82 -> 0.07646771 | X12: =+FAT!AR82 -> 0.083890897 | Y12: =+FAT!AS82 -> 0.088293427
K13: =+K12+2% -> 0.15 | L13: 0.086876931 | M13: 0.087468224 | N13: 0.088059518 | O13: 0.088650812 | P13: 0.089242106 | Q13: 0.0898334 | R13: 0.090424694 | S13: 0.091015988
V14: Int Income | W14: =+W10*AVERAGE(V6:W6) -> 32239.605 | X14: =+X10*AVERAGE(W6:X6) -> 28758.696 | Y14: =+Y10*AVERAGE(X6:Y6) -> 30525.701
V16: FUNDING | W16: =+FAT!AQ102 -> 212483 | X16: =+FAT!AR102 -> 246304 | Y16: =+FAT!AS102 -> 243821.69
V17: Cost | W17: =+FAT!AQ127 -> -15831 | X17: =-X18*AVERAGE(W16:X16) -> -13207.962 | Y17: =-Y18*AVERAGE(X16:Y16) -> -14679.461
V18: rate | X18: =+X19*X20 -> 0.057577753 | Y18: =+Y19*Y20 -> 0.059900801
V19: RFR | W19: =+W$2 -> 0.10245 | X19: =+X$2 -> 0.075 | Y19: =+Y$2 -> 0.068
V20: dif | X20: =+FAT!AR133 -> 0.76770337 | Y20: =+FAT!AS133 -> 0.88089413
V22: Net Interest earning | W22: =+W14+W17 -> 16408.605 | X22: =+X14+X17 -> 15550.734 | Y22: =+Y14+Y17 -> 15846.241
V23: NIM | W23: =+W22/AVERAGE(W6) -> 0.094240044 | X23: =+X22/AVERAGE(W6:X6) -> 0.085917318 | Y23: =+Y22/AVERAGE(X6:Y6) -> 0.081133706
V25: PDD | X25: =+FAT!AR160 -> -1757 | Y25: =+FAT!AS160 -> -1959.5548
V27: Other Income & Expenses | X27: =+FAT!AR164+FAT!AR183 -> -4665.5 | Y27: =+FAT!AS164+FAT!AS183 -> -5015.6915
V29: EBT | X29: =+X14+X17+X25+X27 -> 9128.2339 | Y29: =+Y14+Y17+Y25+Y27 -> 8870.9946
V31: tax | X31: =+X32*X29 -> -2447.992 | Y31: =+Y32*Y29 -> -2439.5235
V32: rate | X32: =+FAT!AR213 -> -0.26817805 | Y32: =+FAT!AS213 -> -0.275
V34: NI | X34: =+X29+X31 -> 6680.242 | Y34: =+Y29+Y31 -> 6431.4711

Sheet macro
A1: 45909 | B1: 2009 | C1: 2009 | D1: 2009 | E1: 2009 | F1: 2010 | G1: 2010 | H1: 2010 | I1: 2010 | J1: 2011 | K1: 2011 | L1: 2011 | M1: 2011 | N1: 2012 | O1: 2012 | P1: 2012 | Q1: 2012 | R1: 2013 | S1: 2013 | T1: 2013 | U1: 2013 | V1: 2014 | W1: 2014 | X1: 2014 | Y1: 2014 | Z1: 2015 | AA1: 2015 | AB1: 2015 | AC1: 2015 | AD1: 2016 | AE1: 2016 | AF1: 2016 | AG1: 2016 | AH1: 2017 | AI1: 2017 | AJ1: 2017 | AK1: 2017 | AL1: 2018 | AM1: 2018 | AN1: 2018 | AO1: 2018 | AP1: 2019 | AQ1: 2019 | AR1: 2019 | AS1: 2019 | AT1: 2020 | AU1: 2020 | AV1: 2020 | AW1: 2020 | AX1: 2021 | AY1: 2021 | AZ1: 2021 | BA1: 2021 | BB1: 2022 | BC1: 2022 | BD1: 2022 | BE1: 2022 | BF1: 2023 | BG1: 2023 | BH1: 2023 | BI1: 2023 | BJ1: 2024 | BK1: 2024 | BL1: 2024 | BM1: 2024 | BN1: 2025 | BO1: 2025 | BP1: 2025 | BQ1: 2025 | BR1: 2026 | BS1: 2026 | BT1: 2026 | BU1: 2026 | CY1: 2011 | CZ1: 2012 | DA1: 2013 | DB1: 2014 | DC1: 2015 | DD1: 2016 | DE1: 2017 | DF1: 2018 | DG1: 2019 | DH1: 2020 | DI1: 2021 | DJ1: 2022 | DK1: 2023 | DL1: 2024 | DM1: 2025 | DN1: 2026 | DO1: 2027 | DP1: 2028 | DQ1: 2029 | DR1: 2030 | DS1: 2031 | DT1: 2032 | DU1: 2033 | DV1: 2034 | DW1: 2035 | DX1: 2036 | DY1: 2037 | DZ1: 2038 | EA1: 2039 | EB1: 2040
A2: FX Medio | B2: 39903 | C2: 39994 | D2: 40086 | E2: 40178 | F2: 40268 | G2: 40359 | H2: 40451 | I2: 40543 | J2: 40633 | K2: 40724 | L2: 40816 | M2: 40908 | N2: 40999 | O2: 41090 | P2: 41182 | Q2: 41274 | R2: 41364 | S2: 41455 | T2: 41547 | U2: 41639 | V2: 41729 | W2: 41820 | X2: 41912 | Y2: 42004 | Z2: 42094 | AA2: 42185 | AB2: 42277 | AC2: 42369 | AD2: 42460 | AE2: 42551 | AF2: 42643 | AG2: 42735 | AH2: 42825 | AI2: 42916 | AJ2: 43008 | AK2: 43100 | AL2: 43190 | AM2: 43281 | AN2: 43373 | AO2: 43465 | AP2: 43555 | AQ2: 43646 | AR2: 43738 | AS2: 43830 | AT2: 43921 | AU2: 44012 | AV2: 44104 | AW2: 44196 | AX2: 44286 | AY2: 44377 | AZ2: 44469 | BA2: 44561 | BB2: 44651 | BC2: 44742 | BD2: 44834 | BE2: 44926 | BF2: 45016 | BG2: 45107 | BH2: 45199 | BI2: 45291 | BJ2: 45382 | BK2: 45473 | BL2: 45565 | BM2: 45657 | BN2: 45747 | BO2: 45838 | BP2: 45930 | BQ2: 46022 | BR2: 46112 | BS2: 46203 | BT2: 46295 | BU2: 46387 | CY2: 40908 | CZ2: 41274 | DA2: 41639 | DB2: 42004 | DC2: 42369 | DD2: 42735 | DE2: 43100 | DF2: 43465 | DG2: 43830 | DH2: 44196 | DI2: 44561 | DJ2: 44926 | DK2: 45291 | DL2: 45657 | DM2: 46022 | DN2: 46387 | DO2: 46752 | DP2: 47118 | DQ2: 47483 | DR2: 47848 | DS2: 48213 | DT2: 48579 | DU2: 48944 | DV2: 49309 | DW2: 49674 | DX2: 50040 | DY2: 50405 | DZ2: 50770 | EA2: 51135 | EB2: 51501
A3: CLP Medio | B3: 606.59778 | C3: 566.21015 | D3: 545.48909 | E3: 517.95692 | F3: 519.07683 | G3: 530.63538 | H3: 510.71379 | I3: 479.94864 | J3: 481.68391 | K3: 469.22906 | L3: 471.926 | M3: 509.33056 | N3: 495.6692 | O3: 498.04086 | P3: 484.56667 | Q3: 478.17018 | R3: 472.40951 | S3: 484.81083 | T3: 508.39131 | U3: 517.35194 | V3: 552.58476 | W3: 554.67548 | X3: 577.71323 | Y3: 598.60697 | Z3: 624.50937 | AA3: 616.72525 | AB3: 679.16576 | AC3: 698.02887 | AD3: 701.10444 | AE3: 677.39812 | AF3: 661.67106 | AG3: 665.72097 | AH3: 655.33344 | AI3: 664.86758 | AJ3: 642.3659 | AK3: 633.45758 | AL3: 601.95 | AM3: 621.69859 | AN3: 663.30813 | AO3: 679.75 | AP3: 667.58922 | AQ3: 683.62206 | AR3: 706.46062 | AS3: 755.16121 | AT3: 804.15 | AU3: 822.41607 | AV3: 780.83266 | AW3: 760.92806 | AX3: 724.3727 | AY3: 715.49738 | AZ3: 773.73422 | BA3: 826.76571 | BB3: 808.16859 | BC3: 845.12719 | BD3: 927.20625 | BE3: 913.69063 | BF3: 810.09438 | BG3: 801.18231 | BH3: 853.25046 | BI3: 895.51492 | BJ3: 946.47422 | BK3: 934.1581 | BL3: 930.77226 | BM3: 963.48419 | BN3: 963.2173 | BO3: 946.92742 | BP3: 949.1 | BQ3: 967.1535 | BR3: 969.50006 | BS3: 968.10099 | BT3: 967.16756 | BU3: 970.92464 | CY3: 483.04238 | CZ3: 489.11173 | DA3: 495.7409 | DB3: 570.89511 | DC3: 654.60732 | DD3: 676.47365 | DE3: 649.00613 | DF3: 641.67668 | DG3: 703.20828 | DH3: 792.0817 | DI3: 760.0925 | DJ3: 873.54817 | DK3: 840.01052 | DL3: 943.72219 | DM3: 956.59956 | DN3: 968.92331 | DO3: 977.2099 | DP3: 986.79038 | DQ3: 996.4648 | DR3: 1006.2341 | DS3: 1016.0991 | DT3: 1026.0609 | DU3: 1036.1203 | DV3: 1046.2783 | DW3: 1056.536 | DX3: 1066.8941 | DY3: 1077.3539 | DZ3: 1087.9162 | EA3: 1098.582 | EB3: 1109.3524
A4: PEN Medio | B4: 3.1852984 | C4: 3.0233354 | D4: 2.9570773 | E4: 2.8775046 | F4: 2.8492222 | G4: 2.8403477 | H4: 2.8052455 | I4: 2.8042828 | J4: 2.778725 | K4: 2.7841172 | L4: 2.7412569 | M4: 2.7131642 | N4: 2.6816818 | O4: 2.6657377 | P4: 2.6159737 | Q4: 2.5819314 | R4: 2.5692667 | S4: 2.6583 | T4: 2.785637 | U4: 2.7808469 | V4: 2.8097556 | W4: 2.7918758 | X4: 2.8226385 | Y4: 2.9316698 | Z4: 3.060629 | AA4: 3.1437172 | AB4: 3.2135032 | AC4: 3.324 | AD4: 3.4504758 | AE4: 3.3176609 | AF4: 3.3413923 | AG4: 3.3939836 | AH4: 3.2878554 | AI4: 3.2639279 | AJ4: 3.2458097 | AK4: 3.2464145 | AL4: 3.2386934 | AM4: 3.2588952 | AN4: 3.2926565 | AO4: 3.3575127 | AP4: 3.3231698 | AQ4: 3.320454 | AR4: 3.3403484 | AS4: 3.3607344 | AT4: 3.3953895 | AU4: 3.4328016 | AV4: 3.5436682 | AW4: 3.6018156 | AX4: 3.6617603 | AY4: 3.7947613 | AZ4: 4.0495762 | BA4: 4.023073 | BB4: 3.8033031 | BC4: 3.7478113 | BD4: 3.8924 | BE4: 3.8939952 | BF4: 3.8158516 | BG4: 3.6973836 | BH4: 3.677746 | BI4: 3.7821435 | BJ4: 3.7602279 | BK4: 3.7436238 | BL4: 3.7567984 | BM4: 3.755929 | BN4: 3.699819 | BO4: 3.6524661 | BP4: 3.52625 | BQ4: 3.5031389 | BR4: 3.5046621 | BS4: 3.5164007 | BT4: 3.5088907 | BU4: 3.4911886 | CY4: 2.7543158 | CZ4: 2.6363311 | DA4: 2.6985127 | DB4: 2.8389849 | DC4: 3.1854623 | DD4: 3.3758782 | DE4: 3.2610019 | DF4: 3.2869394 | DG4: 3.3361767 | DH4: 3.4934187 | DI4: 3.8822927 | DJ4: 3.8343774 | DK4: 3.7432812 | DL4: 3.7541448 | DM4: 3.5954185 | DN4: 3.5052855 | DO4: 3.488621 | DP4: 3.4971715 | DQ4: 3.505743 | DR4: 3.5143355 | DS4: 3.5229491 | DT4: 3.5315838 | DU4: 3.5402396 | DV4: 3.5489167 | DW4: 3.557615 | DX4: 3.5663347 | DY4: 3.5750757 | DZ4: 3.5838381 | EA4: 3.592622 | EB4: 3.6014275
A5: COP Medio | B5: 2418.3827 | C5: 2228.1545 | D5: 2013.6042 | E5: 1964.8087 | F5: 1942.5883 | G5: 1949.568 | H5: 1831.725 | I5: 1868.0247 | J5: 1877.542 | K5: 1796.3937 | L5: 1796.1932 | M5: 1918.9842 | N5: 1795.6903 | O5: 1785.7197 | P5: 1796.4274 | Q5: 1805.8551 | R5: 1788.4047 | S5: 1860.2492 | T5: 1906.1563 | U5: 1913.1643 | V5: 2006.2579 | W5: 1913.2035 | X5: 1911.1348 | Y5: 2177.52 | Z5: 2474.2625 | AA5: 2499.0377 | AB5: 2947.5812 | AC5: 3062.2818 | AD5: 3251.7006 | AE5: 2992.0048 | AF5: 2947.6774 | AG5: 3019.9071 | AH5: 2922.1529 | AI5: 2925.0843 | AJ5: 2974.5891 | AK5: 2988.1213 | AL5: 2855.7705 | AM5: 2842.0557 | AN5: 2960.7506 | AO5: 3165.4894 | AP5: 3134.0035 | AQ5: 3242.2911 | AR5: 3343.7847 | AS5: 3404.0021 | AT5: 3551.7089 | AU5: 3842.9453 | AV5: 3731.553 | AW5: 3655.2125 | AX5: 3560.9698 | AY5: 3695.246 | AZ5: 3847.7811 | BA5: 3886.9744 | BB5: 3907.8169 | BC5: 3923.7174 | BD5: 4388.037 | BE5: 4820.8119 | BF5: 4756.8162 | BG5: 4406.0674 | BH5: 4044.2606 | BI5: 4072.6468 | BJ5: 3919.6002 | BK5: 3928.7761 | BL5: 4097.1941 | BM5: 4352.0903 | BN5: 4183.6351 | BO5: 4196.3313 | BP5: 4014.4 | BQ5: 3923.8842 | BR5: 3950.7297 | BS5: 3995.0301 | BT5: 3985.4183 | BU5: 3958.3043 | CY5: 1847.2783 | CZ5: 1795.9231 | DA5: 1866.9936 | DB5: 2002.0291 | DC5: 2745.7908 | DD5: 3052.8225 | DE5: 2952.4869 | DF5: 2956.0165 | DG5: 3281.0203 | DH5: 3695.3549 | DI5: 3747.7428 | DJ5: 4260.0958 | DK5: 4319.9477 | DL5: 4074.4152 | DM5: 4079.5627 | DN5: 3972.3706 | DO5: 3981.9162 | DP5: 4040.4738 | DQ5: 4099.8925 | DR5: 4160.185 | DS5: 4221.3642 | DT5: 4283.4431 | DU5: 4346.4349 | DV5: 4410.3531 | DW5: 4475.2112 | DX5: 4541.0231 | DY5: 4607.8029 | DZ5: 4675.5647 | EA5: 4744.323 | EB5: 4814.0925
A6: ARS Medio | B6: 3.5468159 | C6: 3.7285016 | D6: 3.8299703 | E6: 3.8138855 | F6: 3.8389516 | G6: 3.9002217 | H6: 3.9410406 | I6: 3.9677548 | J6: 4.0120367 | K6: 4.0810934 | L6: 4.1662323 | M6: 4.2566983 | N6: 4.3408852 | O6: 4.4511586 | P6: 4.6086984 | Q6: 4.7986885 | R6: 5.0128667 | S6: 5.23905 | T6: 5.5843875 | U6: 6.052065 | V6: 7.5982217 | W6: 8.0574119 | X6: 8.2977031 | Y6: 8.5110082 | Z6: 8.6872441 | AA6: 8.9553656 | AB6: 9.2494297 | AC6: 10.161588 | AD6: 14.475107 | AE6: 14.230345 | AF6: 14.953745 | AG6: 15.451003 | AH6: 15.679418 | AI6: 15.739711 | AJ6: 17.28517 | AK6: 17.549547 | AL6: 19.676355 | AM6: 23.585497 | AN6: 31.999838 | AO6: 37.101193 | AP6: 38.9995 | AQ6: 44.01039 | AR6: 50.524956 | AS6: 59.356035 | AT6: 61.469492 | AU6: 67.704447 | AV6: 73.351394 | AW6: 79.922541 | AX6: 88.652315 | AY6: 94.015784 | AZ6: 97.259108 | BA6: 100.50011 | BB6: 106.59146 | BC6: 118.03298 | BD6: 135.83682 | BE6: 162.69439 | BF6: 192.43875 | BG6: 232.70614 | BH6: 312.9949 | BI6: 445.28678 | BJ6: 833.69708 | BK6: 885.61801 | BL6: 941.26712 | BM6: 999.70919 | BN6: 1055.0398 | BO6: 1150.9686 | BP6: 1320 | BQ6: 1416.6708 | BR6: 1447.927 | BS6: 1499.09 | BT6: 1545.2668 | BU6: 1588.0966 | CY6: 4.1290152 | CZ6: 4.5498577 | DA6: 5.4720923 | DB6: 8.1160862 | DC6: 9.2634069 | DD6: 14.77755 | DE6: 16.563462 | DF6: 28.090721 | DG6: 48.22272 | DH6: 70.611968 | DI6: 95.10683 | DJ6: 130.78891 | DK6: 295.85664 | DL6: 915.07285 | DM6: 1235.6698 | DN6: 1520.0951 | DO6: 1655.1544 | DP6: 1752.5164 | DQ6: 1855.6057 | DR6: 1964.7589 | DS6: 2080.333 | DT6: 2202.7055 | DU6: 2332.2764 | DV6: 2469.4692 | DW6: 2614.732 | DX6: 2768.5398 | DY6: 2931.3951 | DZ6: 3103.8301 | EA6: 3286.4083 | EB6: 3479.7265
A7: BRL Medio | B7: 2.3156937 | C7: 2.0763862 | D7: 1.8667515 | E7: 1.7403045 | F7: 1.8005262 | G7: 1.7937871 | H7: 1.750954 | I7: 1.6974274 | J7: 1.6672532 | K7: 1.5955032 | L7: 1.6363062 | M7: 1.8018852 | N7: 1.7688921 | O7: 1.9657306 | P7: 2.0278078 | Q7: 2.0581984 | R7: 1.9971567 | S7: 2.0685968 | T7: 2.287647 | U7: 2.2741508 | V7: 2.3640328 | W7: 2.2288148 | X7: 2.2749106 | Y7: 2.5455281 | Z7: 2.8724557 | AA7: 3.0698672 | AB7: 3.5365185 | AC7: 3.8447127 | AD7: 3.8989492 | AE7: 3.5001825 | AF7: 3.2465262 | AG7: 3.2940226 | AH7: 3.1442698 | AI7: 3.2176426 | AJ7: 3.1631156 | AK7: 3.2488361 | AL7: 3.2426656 | AM7: 3.6088714 | AN7: 3.9477672 | AO7: 3.8127226 | AP7: 3.7658705 | AQ7: 3.9215968 | AR7: 3.9723576 | AS7: 4.1152754 | AT7: 4.4726371 | AU7: 5.3855984 | AV7: 5.3801877 | AW7: 5.3956413 | AX7: 5.4849459 | AY7: 5.2936492 | AZ7: 5.2323169 | BA7: 5.5865206 | BB7: 5.2249758 | BC7: 4.9274355 | BD7: 5.24656 | BE7: 5.2607887 | BF7: 5.192381 | BG7: 4.9428049 | BH7: 4.8850281 | BI7: 4.957625 | BJ7: 4.951523 | BK7: 5.2154889 | BL7: 5.546103 | BM7: 5.8342016 | BN7: 5.8486541 | BO7: 5.6625197 | BP7: 5.43105 | BQ7: 5.4463357 | BR7: 5.494773 | BS7: 5.533904 | BT7: 5.5349543 | BU7: 5.5456013 | CY7: 1.675237 | CZ7: 1.9551572 | DA7: 2.1568878 | DB7: 2.3533216 | DC7: 3.3308885 | DD7: 3.4849201 | DE7: 3.193466 | DF7: 3.6530067 | DG7: 3.9437751 | DH7: 5.1585161 | DI7: 5.3993582 | DJ7: 5.16494 | DK7: 4.9944597 | DL7: 5.3868291 | DM7: 5.5971399 | DN7: 5.5273081 | DO7: 5.6291691 | DP7: 5.7654833 | DQ7: 5.9050984 | DR7: 6.0480945 | DS7: 6.1945532 | DT7: 6.3445586 | DU7: 6.4981964 | DV7: 6.6555547 | DW7: 6.8167235 | DX7: 6.9817952 | DY7: 7.1508641 | DZ7: 7.3240272 | EA7: 7.5013835 | EB7: 7.6830347
A8: PYG Medio | B8: 5073.9453 | C8: 5043.2538 | D8: 4968.9227 | E8: 4790.553 | F8: 4685.6889 | G8: 4737.8438 | H8: 4781.4773 | I8: 4802.2348 | J8: 4508.3594 | K8: 4027.2692 | L8: 3942.2955 | M8: 4311 | N8: 4450.8769 | O8: 4407.7308 | P8: 4436.0769 | Q8: 4408.4848 | R8: 4089.3203 | S8: 4219.8692 | T8: 4457.0606 | U8: 4467.7303 | V8: 4527.7453 | W8: 4419.9077 | X8: 4292.9742 | Y8: 4615.7258 | Z8: 4760.0297 | AA8: 5052.8492 | AB8: 5308.8212 | AC8: 5698.0258 | AD8: 5791.8031 | AE8: 5611.6815 | AF8: 5551.5121 | AG8: 5737.1846 | AH8: 5664.1308 | AI8: 5579.74 | AJ8: 5602.0385 | AK8: 5641.9077 | AL8: 5578.6246 | AM8: 5619.5815 | AN8: 5782.2723 | AO8: 5939.0939 | AP8: 6069.1556 | AQ8: 6263.8125 | AR8: 6177.6308 | AS8: 6450.3125 | AT8: 6539.9453 | AU8: 6611.1862 | AV8: 6943.6515 | AW8: 6999.8015 | AX8: 6717.3333 | AY8: 6632.0063 | AZ8: 6893.1303 | BA8: 6862.7258 | BB8: 6975.7703 | BC8: 6858.3175 | BD8: 6907.8985 | BE8: 7201.5631 | BF8: 7286.5469 | BG8: 7216.1869 | BH8: 7276.2063 | BI8: 7390.3719 | BJ8: 7296.2125 | BK8: 7479.0046 | BL8: 7632.7273 | BM8: 7829.5152 | BN8: 7916.0625 | BO8: 7989.0262 | BP8: 7550.4 | BQ8: 7189.1682 | BR8: 7253.8919 | BS8: 7308.7723 | BT8: 7326.5325 | BU8: 7352.7429 | CY8: 4197.231 | CZ8: 4425.7924 | DA8: 4308.4951 | DB8: 4464.0883 | DC8: 5204.9315 | DD8: 5673.0453 | DE8: 5621.9542 | DF8: 5729.8931 | DG8: 6240.2278 | DH8: 6773.6461 | DI8: 6776.2989 | DJ8: 6985.8873 | DK8: 7292.328 | DL8: 7559.3649 | DM8: 7661.1642 | DN8: 7310.4849 | DO8: 7473.2924 | DP8: 7686.4386 | DQ8: 7905.664 | DR8: 8131.142 | DS8: 8363.0508 | DT8: 8601.5739 | DU8: 8846.9 | DV8: 9099.223 | DW8: 9358.7425 | DX8: 9625.6638 | DY8: 9900.198 | DZ8: 10182.562 | EA8: 10472.98 | EB8: 10771.68
A9: MXN Medio | B9: 14.371277 | C9: 13.316355 | D9: 13.267964 | E9: 13.066306 | F9: 12.765022 | G9: 12.564428 | H9: 12.798624 | I9: 12.385903 | J9: 12.061261 | K9: 11.722303 | L9: 12.331148 | M9: 13.648677 | N9: 12.976945 | O9: 13.536628 | P9: 13.161551 | Q9: 12.945545 | R9: 12.63973 | S9: 12.474511 | T9: 12.913488 | U9: 13.024082 | V9: 13.229828 | W9: 12.9965 | X9: 13.118111 | Y9: 13.895885 | Z9: 14.956191 | AA9: 15.32064 | AB9: 16.438 | AC9: 16.7702 | AD9: 18.0272 | AE9: 18.1073 | AF9: 18.7626 | AG9: 19.8451 | AH9: 20.29942 | AI9: 18.548848 | AJ9: 17.818892 | AK9: 18.986402 | AL9: 18.718333 | AM9: 19.415462 | AN9: 18.942154 | AO9: 19.83728 | AP9: 19.200492 | AQ9: 19.1074 | AR9: 19.437526 | AS9: 19.244785 | AT9: 20.000129 | AU9: 23.316534 | AV9: 22.082652 | AW9: 20.534918 | AX9: 20.340297 | AY9: 20.020471 | AZ9: 20.033242 | BA9: 20.748074 | BB9: 20.501794 | BC9: 20.030058 | BD9: 20.233745 | BE9: 19.670035 | BF9: 18.651975 | BG9: 17.673632 | BH9: 17.070366 | BI9: 17.553212 | BJ9: 16.977138 | BK9: 17.246688 | BL9: 18.947241 | BM9: 20.084412 | BN9: 20.418702 | BO9: 19.492834 | BP9: 18.692 | BQ9: 18.676296 | BR9: 18.757961 | BS9: 18.851136 | BT9: 18.851209 | BU9: 18.840123 | CY9: 12.440847 | CZ9: 13.155167 | DA9: 12.762953 | DB9: 13.310081 | DC9: 15.871258 | DD9: 18.68555 | DE9: 18.91339 | DF9: 19.228307 | DG9: 19.247551 | DH9: 21.483558 | DI9: 20.285521 | DJ9: 20.108908 | DK9: 17.737297 | DL9: 18.31387 | DM9: 19.319958 | DN9: 18.825107 | DO9: 19.019094 | DP9: 19.298787 | DQ9: 19.582592 | DR9: 19.870572 | DS9: 20.162786 | DT9: 20.459298 | DU9: 20.76017 | DV9: 21.065466 | DW9: 21.375252 | DX9: 21.689594 | DY9: 22.008559 | DZ9: 22.332214 | EA9: 22.660629 | EB9: 22.993874
A10: UYU Medio | B10: 23.495524 | C10: 23.673086 | D10: 22.702439 | E10: 20.257159 | F10: 19.605016 | G10: 19.624208 | H10: 20.809924 | I10: 19.999621 | J10: 19.575625 | K10: 18.743385 | L10: 18.853723 | M10: 19.854822 | N10: 19.517258 | O10: 20.359041 | P10: 21.40904 | Q10: 19.714643 | R10: 19.122619 | S10: 19.59255 | T10: 21.648174 | U10: 21.430036 | V10: 22.174515 | W10: 22.901775 | X10: 23.639127 | Y10: 24.110484 | Z10: 24.764262 | AA10: 26.57455 | AB10: 28.299246 | AC10: 29.490581 | AD10: 31.526966 | AE10: 31.197378 | AF10: 29.176922 | AG10: 28.52273 | AH10: 28.453452 | AI10: 28.285427 | AJ10: 28.721587 | AK10: 29.132177 | AL10: 28.456542 | AM10: 30.098566 | AN10: 31.780156 | AO10: 32.558952 | AP10: 32.819 | AQ10: 34.876875 | AR10: 35.811346 | AS10: 37.507188 | AT10: 39.696822 | AU10: 43.128542 | AV10: 42.739219 | AW10: 42.613625 | AX10: 43.178625 | AY10: 43.887377 | AZ10: 43.2495 | BA10: 43.984153 | BB10: 43.253542 | BC10: 40.498975 | BD10: 40.830352 | BE10: 39.928532 | BF10: 39.191976 | BG10: 38.613432 | BH10: 37.977659 | BI10: 39.540484 | BJ10: 38.89625 | BK10: 38.753024 | BL10: 40.5365 | BM10: 42.634297 | BN10: 43.050792 | BO10: 41.621352 | BP10: 39.925 | BQ10: 40.05837 | BR10: 40.651607 | BS10: 41.509691 | BT10: 41.946686 | BU10: 42.117979 | CY10: 19.256889 | CZ10: 20.249995 | DA10: 20.448345 | DB10: 23.206475 | DC10: 27.28216 | DD10: 30.105999 | DE10: 28.648161 | DF10: 30.723554 | DG10: 35.253602 | DH10: 42.044552 | DI10: 43.574914 | DJ10: 41.12785 | DK10: 38.830888 | DL10: 40.205018 | DM10: 41.163878 | DN10: 41.556491 | DO10: 43.312988 | DP10: 45.807816 | DQ10: 48.446347 | DR10: 51.236856 | DS10: 54.1881 | DT10: 57.309334 | DU10: 60.610352 | DV10: 64.101509 | DW10: 67.793756 | DX10: 71.698677 | DY10: 75.828521 | DZ10: 80.196244 | EA10: 84.815548 | EB10: 89.700924
A11: EUR Medio | B11: 1.3063172 | C11: 1.3630323 | D11: 1.4302455 | E11: 1.4766258 | F11: 1.3836547 | G11: 1.2727785 | H11: 1.2931258 | I11: 1.3579106 | J11: 1.3695734 | K11: 1.4398492 | L11: 1.412903 | M11: 1.3473185 | N11: 1.3118923 | O11: 1.2832123 | P11: 1.2510923 | Q11: 1.2976076 | R11: 1.3200328 | S11: 1.3062154 | T11: 1.3254303 | U11: 1.3615318 | V11: 1.3703984 | W11: 1.3716462 | X11: 1.3252288 | Y11: 1.2488379 | Z11: 1.1268125 | AA11: 1.10686 | AB11: 1.1124636 | AC11: 1.0951909 | AD11: 1.1040631 | AE11: 1.1292492 | AF11: 1.116297 | AG11: 1.0779092 | AH11: 1.0654062 | AI11: 1.1013369 | AJ11: 1.1754108 | AK11: 1.1777708 | AL11: 1.2287754 | AM11: 1.1916123 | AN11: 1.1629077 | AO11: 1.1407712 | AP11: 1.1357219 | AQ11: 1.1234262 | AR11: 1.1117424 | AS11: 1.1072818 | AT11: 1.1029046 | AU11: 1.1013477 | AV11: 1.1691091 | AW11: 1.1930455 | AX11: 1.2050578 | AY11: 1.2051677 | AZ11: 1.1785894 | BA11: 1.143347 | BB11: 1.12175 | BC11: 1.0646569 | BD11: 1.0066985 | BE11: 1.0220354 | BF11: 1.0732015 | BG11: 1.0888338 | BH11: 1.0879523 | BI11: 1.0764246 | BJ11: 1.08588 | BK11: 1.0766646 | BL11: 1.0987242 | BM11: 1.0665742 | BN11: 1.0526828 | BO11: 1.1340923 | BP11: 1.17645 | BQ11: 1.1742 | BR11: 1.1742 | BS11: 1.1742 | BT11: 1.1742 | BU11: 1.1742 | CY11: 1.392411 | CZ11: 1.2859511 | DA11: 1.3283026 | DB11: 1.3290278 | DC11: 1.1103318 | DD11: 1.1068796 | DE11: 1.1299812 | DF11: 1.1810166 | DG11: 1.1195431 | DH11: 1.1416017 | DI11: 1.1830405 | DJ11: 1.0537852 | DK11: 1.0816031 | DL11: 1.0819608 | DM11: 1.1343563 | DN11: 1.1742 | DO11: 1.1742 | DP11: 1.1742 | DQ11: 1.1742 | DR11: 1.1742 | DS11: 1.1742 | DT11: 1.1742 | DU11: 1.1742 | DV11: 1.1742 | DW11: 1.1742 | DX11: 1.1742 | DY11: 1.1742 | DZ11: 1.1742 | EA11: 1.1742 | EB11: 1.1742
A15: CPI QoQ
A16: USA | D16: 0.0049862657 | E16: 0.0068840596 | F16: 2.7605626e-05 | G16: -0.00070852484 | H16: 0.0049539823 | I16: 0.010065285 | J16: 0.011674952 | K16: 0.007890749 | L16: 0.0079668692 | M16: 0.0027626138 | N16: 0.0069711253 | O16: -0.0012368503 | P16: 0.010900387 | Q16: 0.00089171699 | R16: 0.0045886836 | S16: 0.00070173324 | T16: 0.0047280002 | U16: 0.0050311719 | V16: 0.0055768813 | W16: 0.0050968529 | X16: 0.001036964 | Y16: -0.0051583943 | Z16: -0.0011682441 | AA16: 0.0071236058 | AB16: -0.00066903142 | AC16: 0.0011073777 | AD16: 0.0013416835 | AE16: 0.0089969758 | AF16: 0.0039713265 | AG16: 0.0060578167 | AH16: 0.0051723356 | AI16: 0.0011111476 | AJ16: 0.0093052592 | AK16: 0.0055592753 | AL16: 0.0071507839 | AM16: 0.0057737692 | AN16: 0.0046371177 | AO16: 0.0023197532 | AP16: 0.0059738811 | AQ16: 0.003681025 | AR16: 0.0047685659 | AS16: 0.0085793394 | AT16: -0.0021420562 | AU16: -0.0040065717 | AV16: 0.011496176 | AW16: 0.007877014 | AX16: 0.01069282 | AY16: 0.022137309 | AZ16: 0.011938975 | BA16: 0.025056399 | BB16: 0.023721003 | BC16: 0.026455211 | BD16: 0.0045717655 | BE16: 0.0080527358 | BF16: 0.0094876978 | BG16: 0.0081420752 | BH16: 0.010769519 | BI16: 0.0044278306 | BJ16: 0.010921988 | BK16: 0.0032809261 | BL16: 0.0054929087 | BM16: 0.0087406424 | BN16: 0.0063349528 | BO16: 0.0058977207 | BP16: 0.012615658 | BQ16: 0.0094235423 | BR16: 0.0042925217 | BS16: 0.0034623689 | BT16: 0.008585249 | BU16: 0.0094235423 | CZ16: 0.01759505 | DA16: 0.015128384 | DB16: 0.0065312139 | DC16: 0.0063872475 | DD16: 0.020507989 | DE16: 0.021299307 | DF16: 0.020023809 | DG16: 0.023195275 | DH16: 0.013204191 | DI16: 0.071594573 | DJ16: 0.064108317 | DK16: 0.033222002 | DL16: 0.028723663 | DM16: 0.0347 | DN16: 0.026 | DO16: 0.02 | DP16: 0.02 | DQ16: 0.02 | DR16: 0.02 | DS16: 0.02 | DT16: 0.02 | DU16: 0.02 | DV16: 0.02 | DW16: 0.02 | DX16: 0.02 | DY16: 0.02 | DZ16: 0.02 | EA16: 0.02 | EB16: 0.02
A17: Chile | F17: 0.0088989705 | G17: 0.0083016257 | H17: 0.0094339623 | I17: 0.0028887001 | J17: 0.012707557 | K17: 0.0088673247 | L17: 0.007960199 | M17: 0.014149391 | N17: 0.0063270604 | O17: -0.0020957601 | P17: 0.0096930533 | Q17: 0.0008 | R17: 0.0068745004 | S17: 0.0014290251 | T17: 0.010464563 | U17: 0.01114075 | V17: 0.015052762 | W17: 0.010243082 | X17: 0.013922518 | Y17: 0.0064179104 | Z17: 0.01067774 | AA17: 0.012472487 | AB17: 0.016086957 | AC17: 0.0039937241 | AD17: 0.011223185 | AE17: 0.010115201 | AF17: 0.0052851182 | AG17: 0.00013835086 | AH17: 0.011758196 | AI17: -0.00027344818 | AJ17: 0.0028719912 | AK17: 0.0081821901 | AL17: 0.0071689436 | AM17: 0.0069836154 | AN17: 0.0086689784 | AO17: 0.0026444533 | AP17: 0.0063299486 | AQ17: 0.0091731097 | AR17: 0.0041553045 | AS17: 0.0099573257 | AT17: 0.013572343 | AU17: -0.0016422436 | AV17: 0.0087308617 | AW17: 0.0089061716 | AX17: 0.012681835 | AY17: 0.0072437078 | AZ17: 0.023647001 | BA17: 0.026434865 | BB17: 0.033758701 | BC17: 0.035686231 | BD17: 0.034890021 | BE17: 0.017799183 | BF17: 0.018413743 | BG17: 0.0026262626 | BH17: 0.011384243 | BI17: 0.0064747485 | BJ17: 0.016429137 | BK17: 0.0070107108 | BL17: 0.010829627 | BM17: 0.010330974 | BN17: 0.01969324 | BO17: -0.00018570102 | BP17: 0.013265212 | BQ17: 0.010621382 | BR17: 0.007972628 | BS17: -0.0030921379 | BT17: 0.013265212 | BU17: 0.012585661 | CZ17: 0.014763141 | DA17: 0.030215827 | DB17: 0.046399752 | DC17: 0.043897375 | DD17: 0.026992471 | DE17: 0.022686402 | DF17: 0.025699986 | DG17: 0.029935382 | DH17: 0.029833547 | DI17: 0.071739401 | DJ17: 0.12772622 | DK17: 0.039399239 | DL17: 0.045328583 | DM17: 0.044 | DN17: 0.031 | DO17: 0.03 | DP17: 0.03 | DQ17: 0.03 | DR17: 0.03 | DS17: 0.03 | DT17: 0.03 | DU17: 0.03 | DV17: 0.03 | DW17: 0.03 | DX17: 0.03 | DY17: 0.03 | DZ17: 0.03 | EA17: 0.03 | EB17: 0.03
A18: Peru | F18: 0.0089195799 | G18: 0.0052759162 | H18: 0.0059574468 | I18: 0.00042301184 | J18: 0.014799154 | K18: 0.0076388889 | L18: 0.013921433 | M18: 0.010195759 | N18: 0.0099582829 | O18: 0.0053297801 | P18: 0.011398277 | Q18: -0.00039313327 | R18: 0.0093078133 | S18: 0.0071437849 | T18: 0.01199381 | U18: -0.00012743724 | V18: 0.014529697 | W18: 0.0077889447 | X18: 0.0049862877 | Y18: 0.0045894319 | Z18: 0.012470675 | AA18: 0.012926829 | AB18: 0.0085480376 | AC18: 0.0094305837 | AD18: 0.011471145 | AE18: 0.0036244593 | AF18: 0.0064072693 | AG18: 0.010417872 | AH18: 0.018787948 | AI18: -0.0084335995 | AJ18: 0.0086187344 | AK18: -0.0051720261 | AL18: 0.0087025316 | AM18: 0.0021288515 | AN18: 0.0070438283 | AO18: 0.0038858665 | AP18: 0.0091793851 | AQ18: 0.002630137 | AR18: 0.0027325391 | AS18: 0.0043601482 | AT18: 0.0084653788 | AU18: 0.00043047783 | AV18: 0.0048407917 | AW18: 0.0058880206 | AX18: 0.014580673 | AY18: 0.0068184202 | AZ18: 0.024171702 | BA18: 0.017293998 | BB18: 0.0184 | BC18: 0.025530244 | BD18: 0.021447721 | BE18: 0.016685414 | BF18: 0.017794579 | BG18: 0.0072470332 | BH18: 0.0078244446 | BI18: -0.00080314117 | BJ18: 0.015897115 | BK18: -0.00017582418 | BL18: 0.0028136815 | BM18: 0.0010521701 | BN18: 0.0091092231 | BO18: 0.0039059109 | BP18: 0.0038293273 | BQ18: 0.0054772534 | BR18: 0.0091092231 | BS18: 0.0053786336 | BT18: 0.0023588742 | BU18: 0.0054772534 | CZ18: 0.026510564 | DA18: 0.02857892 | DB18: 0.03224573 | DC18: 0.044079516 | DD18: 0.032284768 | DE18: 0.013632719 | DF18: 0.021925859 | DG18: 0.01902234 | DH18: 0.01975255 | DI18: 0.064282673 | DJ18: 0.0846 | DK18: 0.032362161 | DL18: 0.01964812 | DM18: 0.0225 | DN18: 0.0225 | DO18: 0.0225 | DP18: 0.0225 | DQ18: 0.0225 | DR18: 0.0225 | DS18: 0.0225 | DT18: 0.0225 | DU18: 0.0225 | DV18: 0.0225 | DW18: 0.0225 | DX18: 0.0225 | DY18: 0.0225 | DZ18: 0.0225 | EA18: 0.0225 | EB18: 0.0225
A19: Colombia | F19: 0.017696629 | G19: 0.0067623516 | H19: -0.00068540096 | I19: 0.0075445816 | J19: 0.017971409 | K19: 0.0072221479 | L19: 0.0041163192 | M19: 0.0075376884 | N19: 0.014700092 | O19: 0.0053033243 | P19: 0.0030880082 | Q19: 0.0011544382 | R19: 0.0094811019 | S19: 0.0076151796 | T19: 0.0042826552 | U19: -0.0021321962 | V19: 0.015208648 | W19: 0.010399901 | X19: 0.0049013601 | Y19: 0.0056090721 | Z19: 0.02400873 | AA19: 0.0089994079 | AB19: 0.01384814 | AC19: 0.019215187 | AD19: 0.035547984 | AE19: 0.014915552 | AF19: 0.0015128593 | AG19: 0.0046396202 | AH19: 0.025238965 | AI19: 0.0080662057 | AJ19: 0.0013509301 | AK19: 0.0058115401 | AL19: 0.015786215 | AM19: 0.0087353987 | AN19: 0.0016111167 | AO19: 0.0053282397 | AP19: 0.0162 | AQ19: 0.010726235 | AR19: 0.0053548827 | AS19: 0.0052295177 | AT19: 0.016666667 | AU19: -0.0053065479 | AV19: 0.00304849 | AW19: 0.0018045398 | AX19: 0.015547971 | AY19: 0.015496639 | AZ19: 0.011583012 | BA19: 0.012450018 | BB19: 0.043532897 | BC19: 0.026234302 | BD19: 0.02782667 | BE19: 0.027725679 | BF19: 0.045544712 | BG19: 0.015253851 | BH19: 0.017416654 | BI19: 0.011828668 | BJ19: 0.027301772 | BK19: 0.01342946 | BL19: 0.004463663 | BM19: 0.0059713929 | BN19: 0.026228603 | BO19: 0.010895884 | BP19: 9.0978044e-05 | BQ19: 0.0066460886 | BR19: 0.020824297 | BS19: 0.0095336215 | BT19: -0.0023188797 | BU19: 0.0066460886 | CZ19: 0.024412653 | DA19: 0.019346573 | DB19: 0.036576169 | DC19: 0.067660968 | DD19: 0.057467348 | DE19: 0.040919343 | DF19: 0.031778787 | DG19: 0.038 | DH19: 0.016184971 | DI19: 0.056219188 | DJ19: 0.131227 | DK19: 0.092755693 | DL19: 0.051989544 | DM19: 0.0444 | DN19: 0.035 | DO19: 0.035 | DP19: 0.035 | DQ19: 0.035 | DR19: 0.035 | DS19: 0.035 | DT19: 0.035 | DU19: 0.035 | DV19: 0.035 | DW19: 0.035 | DX19: 0.035 | DY19: 0.035 | DZ19: 0.035 | EA19: 0.035 | EB19: 0.035
A20: Argentina | F20: 0.07770674 | G20: 0.037110282 | H20: 0.047694639 | I20: 0.049715337 | J20: 0.056477278 | K20: 0.04615377 | L20: 0.051020923 | M20: 0.043695527 | N20: 0.06217492 | O20: 0.048217585 | P20: 0.056785867 | Q20: 0.052996542 | R20: 0.052678173 | S20: 0.050617317 | T20: 0.068180143 | U20: 0.069969638 | V20: 0.13375468 | W20: 0.081626849 | X20: 0.068998159 | Y20: 0.052983716 | Z20: 0.051579144 | AA20: 0.060467389 | AB20: 0.056307344 | AC20: 0.077499703 | AD20: 0.11863658 | AE20: 0.14461416 | AF20: 0.03328244 | AG20: 0.052868608 | AH20: 0.062232064 | AI20: 0.053874536 | AJ20: 0.050831522 | AK20: 0.06111551 | AL20: 0.066407936 | AM20: 0.087363979 | AN20: 0.14083758 | AO20: 0.11600893 | AP20: 0.11830279 | AQ20: 0.094837458 | AR20: 0.12558992 | AS20: 0.11718103 | AT20: 0.078005927 | AU20: 0.053739159 | AV20: 0.076559928 | AW20: 0.11326525 | AX20: 0.12954805 | AY20: 0.10950513 | AZ20: 0.092845327 | BA20: 0.10210028 | BB20: 0.16069773 | BC20: 0.17301719 | BD20: 0.2197647 | BE20: 0.17293319 | BF20: 0.21732079 | BG20: 0.23780735 | BH20: 0.34821392 | BI20: 0.53289051 | BJ20: 0.51621905 | BK20: 0.18566423 | BL20: 0.12131064 | BM20: 0.080279519 | BN20: 0.085691337 | BO20: 0.060125794 | BP20: 0.0601676 | BQ20: 0.04980232 | BR20: 0.039508184 | BS20: 0.0313211 | BT20: 0.030301 | BU20: 0.025208576 | BV20: ver ARS | CZ20: 0.23897181 | DA20: 0.26402635 | DB20: 0.38036889 | DC20: 0.26924874 | DD20: 0.3929687 | DE20: 0.24825718 | DF20: 0.4763516 | DG20: 0.53961739 | DH20: 0.36141688 | DI20: 0.50943298 | DJ20: 0.94792775 | DK20: 2.1140676 | DL20: 1.1776383 | DM20: 0.28099027 | DN20: 0.13239559 | DO20: 0.08 | DP20: 0.08 | DQ20: 0.08 | DR20: 0.08 | DS20: 0.08 | DT20: 0.08 | DU20: 0.08 | DV20: 0.08 | DW20: 0.08 | DX20: 0.08 | DY20: 0.08 | DZ20: 0.08 | EA20: 0.08 | EB20: 0.08
A21: Brasil | D21: 0.0063125611 | E21: 0.010636908 | F21: 0.020635673 | G21: 0.01002643 | H21: 0.0049988106 | I21: 0.02226281 | J21: 0.02439696 | K21: 0.013956003 | L21: 0.010633971 | M21: 0.014569951 | N21: 0.01224539 | O21: 0.0108289 | P21: 0.014167088 | Q21: 0.019931711 | R21: 0.019420063 | S21: 0.01184505 | T21: 0.0062084221 | U21: 0.020433326 | V21: 0.021751381 | W21: 0.015375618 | X21: 0.0083166596 | Y21: 0.017192652 | Z21: 0.038277182 | AA21: 0.022568003 | AB21: 0.013857215 | AC21: 0.028157122 | AD21: 0.026206442 | AE21: 0.017495424 | AF21: 0.010431432 | AG21: 0.0074190017 | AH21: 0.0096300019 | AI21: 0.0021942514 | AJ21: 0.0059102658 | AK21: 0.011444548 | AL21: 0.0070152101 | AM21: 0.018887284 | AN21: 0.0072098897 | AO21: 0.0038930647 | AP21: 0.015068786 | AQ21: 0.0071077186 | AR21: 0.0026024736 | AS21: 0.017676516 | AT21: 0.0053080212 | AU21: -0.0043058882 | AV21: 0.012447751 | AW21: 0.031314508 | AX21: 0.0205248 | AY21: 0.016786731 | AZ21: 0.030195945 | BA21: 0.029580045 | BB21: 0.032007961 | BC21: 0.022153507 | BD21: -0.013245351 | BE21: 0.016286415 | BF21: 0.020941939 | BG21: 0.0076070364 | BH21: 0.0061126585 | BI21: 0.010836246 | BJ21: 0.014154168 | BK21: 0.010535526 | BL21: 0.008015547 | BM21: 0.014770299 | BN21: 0.020404197 | BO21: 0.0093287033 | BP21: 0.0085773379 | BQ21: 0.015347913 | BR21: 0.01624402 | BS21: 0.0058694655 | BT21: 0.0065540169 | BU21: 0.015347913 | CZ21: 0.058385947 | DA21: 0.059106833 | DB21: 0.064074708 | DC21: 0.10673028 | DD21: 0.062879882 | DE21: 0.029474213 | DF21: 0.037455812 | DG21: 0.043061516 | DH21: 0.045174569 | DI21: 0.10060983 | DJ21: 0.057850929 | DK21: 0.0462119 | DL21: 0.048311967 | DM21: 0.0547 | DN21: 0.0447 | DO21: 0.0447 | DP21: 0.0447 | DQ21: 0.0447 | DR21: 0.0447 | DS21: 0.0447 | DT21: 0.0447 | DU21: 0.0447 | DV21: 0.0447 | DW21: 0.0447 | DX21: 0.0447 | DY21: 0.0447 | DZ21: 0.0447 | EA21: 0.0447 | EB21: 0.0447
A22: Paraguay | D22: 0.011560694 | E22: 0.0085714286 | F22: 0.018413598 | G22: 0.0041724618 | H22: 0.0069252078 | I22: 0.041265475 | J22: 0.047556143 | K22: -0.0088272383 | L22: 0.011450382 | M22: -0.0012578616 | N22: 0.031486146 | O22: -0.0024420024 | P22: 0 | Q22: 0.011015912 | R22: 0.0024213075 | S22: 0.0036231884 | T22: 0.014440433 | U22: 0.016607355 | V22: 0.025670945 | W22: 0.0056882821 | X22: -0.0067873303 | Y22: 0.017084282 | Z22: 0.010078387 | AA22: 0.0044345898 | AB22: 0.0055187638 | AC22: 0.010976948 | AD22: 0.026058632 | AE22: 0.0031746032 | AF22: -0.0052742616 | AG22: 0.014846235 | AH22: 0.014629049 | AI22: 0.0051493306 | AJ22: 0.0071721311 | AK22: 0.017293998 | AL22: 0.011 | AM22: 0.0079129575 | AN22: 0.0029440628 | AO22: 0.0097847358 | AP22: 0.0067829457 | AQ22: 0.0086621752 | AR22: 0.00095419847 | AS22: 0.011439466 | AT22: 0.0037700283 | AU22: -0.011267606 | AV22: 0.012345679 | AW22: 0.016885553 | AX22: 0.0064575646 | AY22: 0.0082493126 | AZ22: 0.030909091 | BA22: 0.021164021 | BB22: 0.037132988 | BC22: 0.021648626 | BD22: 0.010594947 | BE22: 0.0096774194 | BF22: 0.020766773 | BG22: 0.00078247261 | BH22: 0.0031274433 | BI22: 0.011691348 | BJ22: 0.020030817 | BK22: 0.0075528701 | BL22: 0.00074962519 | BM22: 0.008988764 | BN22: 0.025983667 | BO22: 0.003617945 | BP22: 0.011586272 | BQ22: 0.014171562 | BR22: 0.017631634 | BS22: 0.0053931352 | BT22: 0.011545357 | BU22: 0.013681421 | CZ22: 0.040302267 | DA22: 0.037530266 | DB22: 0.042007001 | DC22: 0.031354983 | DD22: 0.039087948 | DE22: 0.044932079 | DF22: 0.032 | DG22: 0.028100775 | DH22: 0.021677663 | DI22: 0.068265683 | DJ22: 0.081174439 | DK22: 0.036741214 | DL22: 0.037750385 | DM22: 0.05638742 | DN22: 0.049091486 | DO22: 0.049091486 | DP22: 0.049091486 | DQ22: 0.049091486 | DR22: 0.049091486 | DS22: 0.049091486 | DT22: 0.049091486 | DU22: 0.049091486 | DV22: 0.049091486 | DW22: 0.049091486 | DX22: 0.049091486 | DY22: 0.049091486 | DZ22: 0.049091486 | EA22: 0.049091486 | EB22: 0.049091486
A23: Mexico | D23: 0.010163951 | E23: 0.012401841 | F23: 0.023934158 | G23: -0.0097768803 | H23: 0.010222451 | I23: 0.019259989 | J23: 0.010576397 | K23: -0.0075009739 | L23: 0.0088563046 | M23: 0.025999359 | N23: 0.0097053183 | O23: -0.0017021569 | P23: 0.013076797 | Q23: 0.014213404 | R23: 0.016373706 | S23: -0.0032752292 | T23: 0.006286511 | U23: 0.019940998 | V23: 0.014267621 | W23: -0.0033331254 | X23: 0.01079567 | Y23: 0.018607113 | Z23: 0.005066006 | AA23: -0.0059066058 | AB23: 0.0073387355 | AC23: 0.014750594 | AD23: 0.009693779 | AE23: -0.0065176287 | AF23: 0.011572478 | AG23: 0.018607158 | AH23: 0.029156119 | AI23: 0.0025453298 | AJ23: 0.011898243 | AK23: 0.022679994 | AL23: 0.012407286 | AM23: -0.0011629052 | AN23: 0.015501653 | AO23: 0.020838907 | AP23: 0.004426325 | AQ23: -0.0017105416 | AR23: 0.0062246488 | AS23: 0.019164534 | AT23: 0.0085336153 | AU23: -0.00088919673 | AV23: 0.012843934 | AW23: 0.010701667 | AX23: 0.02336393 | AY23: 0.010677493 | AZ23: 0.014006618 | BA23: 0.023621085 | BB23: 0.024303543 | BC23: 0.015687547 | BD23: 0.020705647 | BE23: 0.015308539 | BF23: 0.015109347 | BG23: -0.0013630451 | BH23: 0.014865771 | BI23: 0.017314786 | BJ23: 0.012782063 | BK23: 0.0039458472 | BL23: 0.011040611 | BM23: 0.013734568 | BN23: 0.0087858556 | BO23: 0.0089392862 | BP23: 0.0031181226 | BQ23: 0.013734568 | BR23: 0.0087858556 | BS23: 0.0089392862 | BT23: 0.0031181226 | BU23: 0.013734568 | CZ23: 0.035682149 | DA23: 0.039741486 | DB23: 0.040812891 | DC23: 0.021307734 | DD23: 0.033602555 | DE23: 0.067731071 | DF23: 0.04830528 | DG23: 0.02828577 | DH23: 0.031500746 | DI23: 0.073551079 | DJ23: 0.078170287 | DK23: 0.046608896 | DL23: 0.042123394 | DM23: 0.035 | DN23: 0.035 | DO23: 0.035 | DP23: 0.035 | DQ23: 0.035 | DR23: 0.035 | DS23: 0.035 | DT23: 0.035 | DU23: 0.035 | DV23: 0.035 | DW23: 0.035 | DX23: 0.035 | DY23: 0.035 | DZ23: 0.035 | EA23: 0.035 | EB23: 0.035
A24: Uruguay | D24: 0.024733966 | E24: 0.0053325849 | F24: 0.024567281 | G24: 0.0059945504 | H24: 0.026002167 | I24: 0.011087645 | J24: 0.036553525 | K24: 0.010075567 | L24: 0.018453865 | M24: 0.018364349 | N24: 0.025967781 | O24: 0.014998828 | P24: 0.024474717 | Q24: 0.0074374577 | R24: 0.036017897 | S24: 0.012092421 | T24: 0.032003414 | U24: 0.002894356 | V24: 0.047619048 | W24: 0.0059031877 | X24: 0.025234742 | Y24: 0.0020988361 | Z24: 0.040555979 | AA24: 0.015187557 | AB24: 0.031002163 | AC24: 0.0048951049 | AD24: 0.051496173 | AE24: 0.018365321 | AF24: 0.012185215 | AG24: -0.0027287319 | AH24: 0.038145823 | AI24: 0.0049612403 | AJ24: 0.016352977 | AK24: 0.0048573163 | AL24: 0.039123867 | AM24: 0.018752726 | AN24: 0.017836758 | AO24: 0.0019627085 | AP24: 0.037358332 | AQ24: 0.014836795 | AR24: 0.021664009 | AS24: 0.011577989 | AT24: 0.040766461 | AU24: 0.02594835 | AV24: 0.017704444 | AW24: 0.0067455621 | AX24: 0.030798166 | AY24: 0.016307447 | AZ24: 0.018402154 | BA24: 0.012009696 | BB24: 0.044202504 | BC24: 0.015535398 | BD24: 0.024537988 | BE24: -0.0032067341 | BF24: 0.03488489 | BG24: 0.0027200311 | BH24: 0.0042627398 | BI24: 0.0085857611 | BJ24: 0.021999044 | BK24: 0.013944782 | BL24: 0.007661067 | BM24: 0.010259229 | BN24: 0.023846224 | BO24: 0.0034537726 | BP24: 0.018402154 | BQ24: 0.0085857611 | BR24: 0.03488489 | BS24: 0.015535398 | BT24: 0.017704444 | BU24: 0.0085857611 | DB24: 0.082663368 | DC24: 0.094440213 | DD24: 0.080897704 | DE24: 0.065507806 | DF24: 0.079607251 | DG24: 0.088008955 | DH24: 0.094007202 | DI24: 0.079699071 | DJ24: 0.08296135 | DK24: 0.051070675 | DL24: 0.054901961 | DM24: 0.055271587 | DN24: 0.078752004 | DO24: 0.078752004 | DP24: 0.078752004 | DQ24: 0.078752004 | DR24: 0.078752004 | DS24: 0.078752004 | DT24: 0.078752004 | DU24: 0.078752004 | DV24: 0.078752004 | DW24: 0.078752004 | DX24: 0.078752004 | DY24: 0.078752004 | DZ24: 0.078752004 | EA24: 0.078752004 | EB24: 0.078752004
A25: Spain | F25: -0.0045041422 | G25: 0.014704694 | H25: -0.0012739868 | I25: 0.020842587 | J25: 0.0013722931 | K25: 0.010684761 | L25: -0.0016976619 | M25: 0.013284157 | N25: -0.0033129182 | O25: 0.010660631 | P25: 0.013155475 | Q25: 0.0079552371 | R25: -0.0075852279 | S25: 0.0070667606 | T25: -0.0039325843 | U25: 0.0070555183 | V25: -0.01152887 | W25: 0.0094076394 | X25: -0.006322746 | Y25: -0.0018971692 | Z25: -0.0077526002 | AA25: 0.016724064 | AB25: -0.015612761 | AC25: 0.0071398617 | AD25: -0.0162711 | AE25: 0.017191417 | AF25: -0.0059537147 | AG25: 0.021113079 | AH25: -0.00928184 | AI25: 0.0094324608 | AJ25: -0.0031848473 | AK25: 0.014287974 | AL25: -0.0082856846 | AM25: 0.020011951 | AN25: -0.0033298391 | AO25: 0.0036193776 | AP25: -0.0067811238 | AQ25: 0.010861807 | AR25: -0.0067540601 | AS25: 0.010684223 | AT25: -0.014720274 | AU25: 0.0075839093 | AV25: -0.0070339375 | AW25: 0.0090382627 | AX25: 0.0038432369 | AY25: 0.021409101 | AZ25: 0.0052875677 | BA25: 0.033706189 | BB25: 0.034636657 | BC25: 0.025110165 | BD25: -0.0069739813 | BE25: 0.0036621673 | BF25: 0.011028308 | BG25: 0.011187011 | BH25: 0.008847037 | BI25: -0.00035289551 | BJ25: 0.012055636 | BK25: 0.013411933 | BL25: -0.010351771 | BM25: 0.013259832 | BN25: 0.0062299415 | BO25: 0.013704588 | BP25: -0.010202941 | BQ25: 0.013755071 | BR25: 0.0018058724 | BS25: 0.013704588 | BT25: -0.0092315995 | BU25: 0.013755071 | DB25: -0.010419308 | DC25: 0.00018153472 | DD25: 0.015683888 | DE25: 0.011121389 | DF25: 0.011841148 | DG25: 0.0078804878 | DH25: -0.0053213179 | DI25: 0.065499006 | DJ25: 0.057076901 | DK25: 0.031019391 | DL25: 0.02847107 | DM25: 0.0235 | DN25: 0.02 | DO25: 0.02 | DP25: 0.02 | DQ25: 0.02 | DR25: 0.02 | DS25: 0.02 | DT25: 0.02 | DU25: 0.02 | DV25: 0.02 | DW25: 0.02 | DX25: 0.02 | DY25: 0.02 | DZ25: 0.02 | EA25: 0.02 | EB25: 0.02
A27: Costa Rica | F27: 0.018034887 | G27: 0.023620523 | H27: 0.048704369 | I27: 0.0098295608 | J27: -0.0048222897 | K27: -0.0092426418 | L27: -0.0060682909 | M27: -0.0023692364 | N27: -9.1340884e-05 | O27: -0.0033799214 | P27: 0.0055912007 | Q27: -0.003463677 | R27: 0.0096954175 | S27: 0.00027176375 | T27: -0.0086035139 | U27: -0.13172559 | V27: 0.02041031 | W27: 0.020620683 | X27: 0.011112234 | Y27: -0.0016984714 | Z27: 0.00020016013 | AA27: 0.00060036022 | AB27: -0.0078 | AC27: -0.0010078613 | AD27: -0.0026230831 | AE27: 0.0026299818 | AF27: 0.004842615 | AG27: 0.0027108434 | AH27: 0.0055071593 | AI27: 0.0045807608 | AJ27: 0.0035685964 | AK27: 0.011951798 | AL27: 0.0058565154 | AM27: -0.00019408054 | AN27: 0.0043676599 | AO27: 0.010050251 | AP27: -9.5675469e-05 | AQ27: 0.0097598316 | AR27: 0.0053065479 | AS27: 0.00018851918 | AT27: 0.0036754312 | AU27: -0.0060093897 | AV27: 0.0051955413 | AW27: 0.0061084485 | AX27: -0.066411358 | AY27: 0.008104052 | AZ27: 0.007046447 | BA27: 0.018034887 | BB27: 0.023620523 | BC27: 0.048704369 | BD27: 0.0098295608 | BE27: -0.0048222897 | BF27: -0.0092426418 | BG27: 0.048704369 | BH27: 0.0098295608 | BI27: -0.0048222897 | BJ27: -0.0092426418 | BK27: 0.048704369 | BL27: 0.0098295608 | BM27: -0.0048222897 | BN27: -0.0092426418 | BO27: 0.048704369 | BP27: 0.0074415316 | BQ27: 0.0029374551 | BR27: -0.011520138 | BS27: 0.029641554 | BT27: 0.0083461342 | BU27: 0.0019352933 | DB27: 0.051236191 | DC27: -0.0080064051 | DD27: 0.007566586 | DE27: 0.025833584 | DF27: 0.020204978 | DG27: 0.0152124 | DH27: 0.0089529733 | DI27: -0.035120493 | DJ27: 0.078799613 | DK27: 0.044164933 | DL27: 0.044164933 | DM27: 0.04981817 | DN27: 0.028260612 | DO27: 0.028260612 | DP27: 0.028260612 | DQ27: 0.028260612 | DR27: 0.028260612 | DS27: 0.028260612 | DT27: 0.028260612 | DU27: 0.028260612 | DV27: 0.028260612 | DW27: 0.028260612 | DX27: 0.028260612 | DY27: 0.028260612 | DZ27: 0.028260612 | EA27: 0.028260612 | EB27: 0.028260612
A28: El Salvador | F28: 0.0089 | G28: 0.00069382496 | H28: 0.0014857369 | I28: 0.010088023 | J28: 0.014687163 | K28: 0.035317958 | L28: 0.0010252586 | M28: -0.0010242086 | N28: 0.0081088638 | O28: -0.0020340237 | P28: 0.0027793218 | Q28: -0.0010162602 | R28: 0.013039859 | S28: -0.0057513237 | T28: 0.001377284 | U28: -0.00073354117 | V28: 0.0092677556 | W28: 0.0014546777 | X28: 0.0068996823 | Y28: -0.012713011 | Z28: -0.003652968 | AA28: 0.0012832264 | AB28: -0.0075979495 | AC28: 0.020293331 | AD28: -0.0026218244 | AE28: -0.00072516316 | AF28: -0.0066219158 | AG28: 0.00063921103 | AH28: 0.012228509 | AI28: 0.0030652723 | AJ28: -0.00035951825 | AK28: 0.0053048013 | AL28: 0.0010732493 | AM28: 0.0029482712 | AN28: 0.0044539462 | AO28: -0.0040794608 | AP28: 0.0034728406 | AQ28: 0.0014198243 | AR28: -0.0076207355 | AS28: 0.0026788106 | AT28: -0.0017811025 | AU28: 0.0044607012 | AV28: -0.009148237 | AW28: 0.0057368232 | AX28: 0.016755793 | AY28: 0.012535063 | AZ28: 0.013765042 | BA28: 0.016737831 | BB28: 0.022173694 | BC28: 0.023007395 | BD28: 0.01124498 | BE28: 0.014853058 | BF28: 0.010252798 | BG28: 0.00077471336 | BH28: 0.0037931568 | BI28: -0.0025449217 | BJ28: 0.0057213546 | BK28: 0.0077644526 | BL28: -0.0051109924 | BM28: -0.0054439503 | BN28: 0.0042402282 | BO28: 0.0046061723 | BP28: 0.0024068413 | BQ28: 0.0074923202 | BR28: 0.010624507 | BS28: 0.0097084651 | BT28: 0.0029087899 | BU28: 0.005867768 | DB28: 0.0047715177 | DC28: 0.010136986 | DD28: -0.0093119971 | DE28: 0.020350429 | DF28: 0.0043824345 | DG28: -8.9047195e-05 | DH28: -0.00080149613 | DI28: 0.06114082 | DJ28: 0.073156392 | DK28: 0.012287704 | DL28: 0.0028606773 | DM28: 0.018871051 | DN28: 0.029409454 | DO28: 0.029409454 | DP28: 0.029409454 | DQ28: 0.029409454 | DR28: 0.029409454 | DS28: 0.029409454 | DT28: 0.029409454 | DU28: 0.029409454 | DV28: 0.029409454 | DW28: 0.029409454 | DX28: 0.029409454 | DY28: 0.029409454 | DZ28: 0.029409454 | EA28: 0.029409454 | EB28: 0.029409454
A29: Guatemala | F29: -0.69661258 | G29: 0.003071364 | H29: 0.0070244957 | I29: 0.013950993 | J29: 0.023990122 | K29: 0.01791559 | L29: 0.014892537 | M29: 0.003835251 | N29: 0.0093023256 | O29: 0.0062541145 | P29: 0.012921165 | Q29: 0.0056515421 | R29: 0.017822736 | S29: 0.010727244 | T29: 0.0073357265 | U29: 0.0072823055 | V29: 0.0067681895 | W29: 0.0096256684 | X29: 0.010441889 | Y29: 0.0023962858 | Z29: 0.0016435081 | AA29: 0.0090990453 | AB29: 0.0054693274 | AC29: 0.014113496 | AD29: 0.013337199 | AE29: 0.010729614 | AF29: 0.0066525124 | AG29: 0.010967379 | AH29: 0.010987483 | AI29: 0.014307333 | AJ29: 0.0066458701 | AK29: 0.023713285 | AL29: -0.0036851803 | AM29: 0.010964333 | AN29: 0.013981445 | AO29: 0.0018041237 | AP29: 0.014406998 | AQ29: 0.016992138 | AR29: -0.014962594 | AS29: 0.017468354 | AT29: -0.0016173177 | AU29: 0.023302181 | AV29: 0.0097418412 | AW29: 0.016160154 | AX29: 0.0080702587 | AY29: 0.0045914763 | AZ29: 0.007500293 | BA29: 0.010236129 | BB29: 0.018767991 | BC29: 0.037183544 | BD29: 0.021357742 | BE29: 0.012162595 | BF29: 0.013913777 | BG29: 0.00114357 | BH29: 0.019003115 | BI29: 0.0071333945 | BJ29: 0.004755641 | BK29: 0.0048338369 | BL29: 0.0042092604 | BM29: 0.0030938124 | BN29: 0.0034822406 | BO29: 0.0069403133 | BP29: 0.0085280796 | BQ29: 0.012632125 | BR29: 0.0087780699 | BS29: 0.014210922 | BT29: 0.01236245 | BU29: 0.009757217 | DB29: 0.029533918 | DC29: 0.030629015 | DD29: 0.04233111 | DE29: 0.05674548 | DF29: 0.023163991 | DG29: 0.033959352 | DH29: 0.048270714 | DI29: 0.030738191 | DJ29: 0.09234312 | DK29: 0.04174133 | DL29: 0.016998887 | DM29: 0.031936835 | DN29: 0.045868083 | DO29: 0.045868083 | DP29: 0.045868083 | DQ29: 0.045868083 | DR29: 0.045868083 | DS29: 0.045868083 | DT29: 0.045868083 | DU29: 0.045868083 | DV29: 0.045868083 | DW29: 0.045868083 | DX29: 0.045868083 | DY29: 0.045868083 | DZ29: 0.045868083 | EA29: 0.045868083 | EB29: 0.045868083
A30: Honduras | F30: 0.017387218 | G30: 0.01108545 | H30: 0.016902695 | I30: 0.017969452 | J30: 0.018534863 | K30: 0.021663778 | L30: 0.0084817642 | M30: 0.0063078217 | N30: 0.019222733 | O30: 0.012300123 | P30: 0.01417578 | Q30: 0.0071884984 | R30: 0.021015067 | S30: 0.0093203883 | T30: 0.011158138 | U30: 0.0068493151 | V30: 0.029478458 | W30: 0.013582966 | X30: 0.010141253 | Y30: 0.003944066 | Z30: 0.0092857143 | AA30: 0.012384996 | AB30: 0.0017476407 | AC30: 0 | AD30: 0.010467551 | AE30: 0.012085635 | AF30: 0.0061412487 | AG30: 0.004069176 | AH30: 0.016548463 | AI30: 0.0093023256 | AJ30: 0.0062541145 | AK30: 0.014393196 | AL30: 0.012899065 | AM30: 0.0073225088 | AN30: 0.0085335019 | AO30: 0.012848637 | AP30: 0.012066832 | AQ30: 0.013757261 | AR30: 0.0048250905 | AS30: 0.0096038415 | AT30: 0.010107015 | AU30: 0.0017657446 | AV30: 0.012044653 | AW30: 0.015674891 | AX30: 0.0094312661 | AY30: 0.0087768969 | AZ30: 0.011507157 | BA30: 0.022475028 | BB30: 0.025237449 | BC30: 0.039438857 | BD30: 0.0099312452 | BE30: 0.020171457 | BF30: 0.018289669 | BG30: 0.0065533981 | BH30: 0.014950567 | BI30: 0.011166548 | BJ30: 0.014097744 | BK30: 0.0076459685 | BL30: 0.011266958 | BM30: 0.0052296498 | BN30: 0.020131192 | BO30: 0.0093126386 | BP30: 0.010651743 | BQ30: 0.015818353 | BR30: 0.015432629 | BS30: 0.012836173 | BT30: 0.011940116 | BU30: 0.014943515 | DB30: 0.058201058 | DC30: 0.023571429 | DD30: 0.033147244 | DE30: 0.047281324 | DF30: 0.042244437 | DG30: 0.040841584 | DH30: 0.040130797 | DI30: 0.053158045 | DJ30: 0.097964722 | DK30: 0.051903114 | DL30: 0.038768797 | DM30: 0.05705923 | DN30: 0.056299329 | DO30: 0.056299329 | DP30: 0.056299329 | DQ30: 0.056299329 | DR30: 0.056299329 | DS30: 0.056299329 | DT30: 0.056299329 | DU30: 0.056299329 | DV30: 0.056299329 | DW30: 0.056299329 | DX30: 0.056299329 | DY30: 0.056299329 | DZ30: 0.056299329 | EA30: 0.056299329 | EB30: 0.056299329
A31: Nicaragua | F31: -0.013211979 | G31: 0.0026777745 | H31: -0.0082096934 | I31: -0.02463349 | J31: -0.01605317 | K31: -0.020056116 | L31: 0.01028632 | M31: 0.02603128 | N31: -0.0039897698 | O31: 0.0090386196 | P31: -0.0090594463 | Q31: -0.0059578839 | R31: 0.005476904 | S31: 0.0029804728 | T31: 0.00010246952 | U31: -0.011372951 | V31: 0.0014509276 | W31: -0.0057953017 | X31: 0.013011346 | Y31: 0.020961776 | Z31: 0.023953301 | AA31: -0.0029486927 | AB31: 0.0088722397 | AC31: 0.0044948212 | AD31: 0.0094357977 | AE31: -0.016960586 | AF31: -0.0050975395 | AG31: 0.0027588925 | AH31: -0.0030460843 | AI31: -0.025034496 | AJ31: -0.023048928 | AK31: 0.0048634106 | AL31: -0.021419009 | AM31: 0.0051562664 | AN31: 0.0072236181 | AO31: 0.0081072654 | AP31: -0.016290339 | AQ31: 0.0096425951 | AR31: 0.0017647669 | AS31: -0.0070466321 | AT31: -0.0019828846 | AU31: 0.027920109 | AV31: -0.023194303 | AW31: -0.021870444 | AX31: -0.007346678 | AY31: -0.0120133 | AZ31: 0.0070567799 | BA31: 0.013691246 | BB31: 0.0053174519 | BC31: 0.012059664 | BD31: 0.029998955 | BE31: 0.013497057 | BF31: -0.0179233 | BG31: 0.0034665579 | BH31: 0.0048770575 | BI31: 0.0061678463 | BJ31: -0.00040196965 | BK31: 0.014878858 | BL31: 0.0043585934 | BM31: 0.0056218562 | BN31: 0.0083366026 | BO31: -0.021787764 | BP31: 0.01 | BQ31: 0.01 | BR31: 0.01 | BS31: 0.01 | BT31: 0.01 | BU31: 0.01 | DB31: 0.029744015 | DC31: 0.034621578 | DD31: -0.010019455 | DE31: -0.045789525 | DF31: -0.0012357121 | DG31: -0.012063099 | DH31: -0.019828846 | DI31: 0.0011712095 | DJ31: 0.062107838 | DK31: -0.0036046861 | DL31: 0.024620641 | DM31: 0.0061931836 | DN31: 0.04060401 | DO31: 0.04060401 | DP31: 0.04060401 | DQ31: 0.04060401 | DR31: 0.04060401 | DS31: 0.04060401 | DT31: 0.04060401 | DU31: 0.04060401 | DV31: 0.04060401 | DW31: 0.04060401 | DX31: 0.04060401 | DY31: 0.04060401 | DZ31: 0.04060401 | EA31: 0.04060401 | EB31: 0.04060401
A32: CHUF | F32: 0.0026567502 | G32: 0.0096978263 | H32: 0.0065007528 | I32: 0.0054151853 | J32: 0.0057192661 | K32: 0.014441387 | L32: 0.0056103551 | M32: 0.01278081 | N32: 0.010741889 | O32: 0.0041649082 | P32: -0.0016046945 | Q32: 0.01105305 | R32: 0.0012534615 | S32: -0.00073067132 | T32: 0.010430291 | U32: 0.0094638481 | V32: 0.012759143 | W32: 0.017649025 | X32: 0.0060111698 | Y32: 0.01899535 | Z32: -0.00017541651 | AA32: 0.014627918 | AB32: 0.014567129 | AC32: 0.011133516 | AD32: 0.007138763 | AE32: 0.0092987578 | AF32: 0.006610991 | AG32: 0.0047162365 | AH32: 0.004704725 | AI32: 0.0072964052 | AJ32: -0.0003112684 | AK32: 0.0053025889 | AL32: 0.0062970788 | AM32: 0.0071153922 | AN32: 0.0073155007 | AO32: 0.0076154759 | AP32: -1.0883055e-06 | AQ32: 0.012244901 | AR32: 0.0052047607 | AS32: 0.009319918 | AT32: 0.01015615 | AU32: 0.0034604472 | AV32: 0.00039830752 | AW32: 0.012626512 | AX32: 0.01116052 | AY32: 0.010718233 | AZ32: 0.012741237 | BA32: 0.030023893 | BB32: 0.023748263 | BC32: 0.042836017 | BD32: 0.035403815 | BE32: 0.024891829 | BF32: 0.01322948 | BG32: 0.014448154 | BH32: 0.0029939473 | BI32: 0.016350011 | BJ32: 0.0082676078 | BK32: 0.012895514 | BL32: 0.0090109992 | BM32: 0.013354376 | BN32: 0.012427411 | BO32: 0.0095891126 | BP32: 0.0073694626 | BQ32: 0.011766274 | BR32: 0.0091385688 | BS32: 0.0016533344 | BT32: 0.006200202 | BU32: 0.012880082 | DB32: 0.056523589 | DC32: 0.04068648 | DD32: 0.028049767 | DE32: 0.017085181 | DF32: 0.028645645 | DG32: 0.026995417 | DH32: 0.026859471 | DI32: 0.066095225 | DJ32: 0.13291412 | DK32: 0.047802141 | DL32: 0.044233713 | DM32: 0.041783642 | DN32: 0.03017422 | DO32: 0.0305 | DP32: 0.03 | DQ32: 0.03 | DR32: 0.03 | DS32: 0.03 | DT32: 0.03 | DU32: 0.03 | DV32: 0.03 | DW32: 0.03 | DX32: 0.03 | DY32: 0.03 | DZ32: 0.03 | EA32: 0.03 | EB32: 0.03
A35: FX EoP
A36: CLP Curncy | B36: 583.2 | C36: 533.65 | D36: 549.7 | E36: 507.45 | F36: 524.4 | G36: 546.04 | H36: 483.55 | I36: 468 | J36: 477.45 | K36: 467.22 | L36: 519.75 | M36: 519.55 | N36: 488.35 | O36: 501.07 | P36: 474.7 | Q36: 479.2 | R36: 473 | S36: 507.25 | T36: 504.76 | U36: 528.85 | V36: 549.47 | W36: 552.95 | X36: 598.32 | Y36: 606.45 | Z36: 625.29 | AA36: 639.15 | AB36: 696.2 | AC36: 707.8 | AD36: 667.74 | AE36: 663.26 | AF36: 657.32 | AG36: 670.68 | AH36: 660.25 | AI36: 663.8 | AJ36: 639.03 | AK36: 615.44 | AL36: 603.9 | AM36: 654.35 | AN36: 656.85 | AO36: 693.6 | AP36: 679.7 | AQ36: 678.72 | AR36: 728.41 | AS36: 751.75 | AT36: 855.15 | AU36: 821.22 | AV36: 784.33 | AW36: 711.78 | AX36: 719.04 | AY36: 734.38 | AZ36: 810.06 | BA36: 852 | BB36: 786.05 | BC36: 918.08 | BD36: 968.69 | BE36: 851.13 | BF36: 795.47 | BG36: 802.25 | BH36: 891.53 | BI36: 879 | BJ36: 979.36 | BK36: 940.23 | BL36: 898.7 | BM36: 994.92 | BN36: 951.08 | BO36: 931.62 | BP36: 966.58 | BQ36: 967.727 | BR36: 971.27312 | BS36: 964.92887 | BT36: 969.40626 | BU36: 972.44302 | CY36: 519.55 | CZ36: 479.2 | DA36: 528.85 | DB36: 606.45 | DC36: 707.8 | DD36: 670.68 | DE36: 615.44 | DF36: 693.6 | DG36: 751.75 | DH36: 711.78 | DI36: 852 | DJ36: 851.13 | DK36: 879 | DL36: 994.92 | DM36: 967.727 | DN36: 972.44302 | DO36: 981.97677 | DP36: 991.604 | DQ36: 1001.3256 | DR36: 1011.1425 | DS36: 1021.0557 | DT36: 1031.066 | DU36: 1041.1745 | DV36: 1051.3821 | DW36: 1061.6898 | DX36: 1072.0985 | DY36: 1082.6093 | DZ36: 1093.2231 | EA36: 1103.941 | EB36: 1114.7639
A37: PEN Curncy | B37: 3.1527 | C37: 3.0065 | D37: 2.882 | E37: 2.888 | F37: 2.842 | G37: 2.8255 | H37: 2.7861 | I37: 2.8063 | J37: 2.8025 | K37: 2.7495 | L37: 2.774 | M37: 2.6965 | N37: 2.6685 | O37: 2.664 | P37: 2.5975 | Q37: 2.5515 | R37: 2.5895 | S37: 2.7805 | T37: 2.7815 | U37: 2.799 | V37: 2.8085 | W37: 2.7985 | X37: 2.8904 | Y37: 2.9795 | Z37: 3.0965 | AA37: 3.1795 | AB37: 3.2335 | AC37: 3.414 | AD37: 3.313 | AE37: 3.2855 | AF37: 3.3835 | AG37: 3.356 | AH37: 3.2485 | AI37: 3.245 | AJ37: 3.2655 | AK37: 3.2374 | AL37: 3.2298 | AM37: 3.2765 | AN37: 3.304 | AO37: 3.3685 | AP37: 3.3185 | AQ37: 3.294 | AR37: 3.3695 | AS37: 3.313 | AT37: 3.432 | AU37: 3.5415 | AV37: 3.6025 | AW37: 3.618 | AX37: 3.7435 | AY37: 3.8659 | AZ37: 4.1345 | BA37: 4.0015 | BB37: 3.6804 | BC37: 3.8265 | BD37: 3.9832 | BE37: 3.8061 | BF37: 3.7631 | BG37: 3.625 | BH37: 3.7849 | BI37: 3.7042 | BJ37: 3.7176 | BK37: 3.8425 | BL37: 3.704 | BM37: 3.7403 | BN37: 3.677 | BO37: 3.5425 | BP37: 3.51 | BQ37: 3.4962778 | BR37: 3.5130464 | BS37: 3.5197551 | BT37: 3.4980263 | BU37: 3.484351 | CY37: 2.6965 | CZ37: 2.5515 | DA37: 2.799 | DB37: 2.9795 | DC37: 3.414 | DD37: 3.356 | DE37: 3.2374 | DF37: 3.3685 | DG37: 3.313 | DH37: 3.618 | DI37: 4.0015 | DJ37: 3.8061 | DK37: 3.7042 | DL37: 3.7403 | DM37: 3.4962778 | DN37: 3.484351 | DO37: 3.492891 | DP37: 3.501452 | DQ37: 3.510034 | DR37: 3.5186371 | DS37: 3.5272612 | DT37: 3.5359064 | DU37: 3.5445729 | DV37: 3.5532605 | DW37: 3.5619695 | DX37: 3.5706998 | DY37: 3.5794515 | DZ37: 3.5882247 | EA37: 3.5970194 | EB37: 3.6058356
A38: COP Curncy | B38: 2548.3 | C38: 2143.15 | D38: 1919.73 | E38: 2043.79 | F38: 1920.35 | G38: 1900.11 | H38: 1802.18 | I38: 1907.7 | J38: 1871 | K38: 1770.78 | L38: 1931.98 | M38: 1938.5 | N38: 1788.75 | O38: 1783.76 | P38: 1800.53 | Q38: 1767 | R38: 1825 | S38: 1922.77 | T38: 1916.98 | U38: 1929.51 | V38: 1971.2 | W38: 1877.44 | X38: 2024.85 | Y38: 2376.51 | Z38: 2599.62 | AA38: 2606 | AB38: 3087.44 | AC38: 3174.5 | AD38: 3002.2 | AE38: 2920.35 | AF38: 2882.06 | AG38: 3002 | AH38: 2873.98 | AI38: 3045.67 | AJ38: 2937.65 | AK38: 2985.78 | AL38: 2794.06 | AM38: 2931.61 | AN38: 2966.17 | AO38: 3254.25 | AP38: 3188.74 | AQ38: 3211.36 | AR38: 3477.98 | AS38: 3287.23 | AT38: 4065.37 | AU38: 3758.06 | AV38: 3828.4 | AW38: 3428.26 | AX38: 3663.44 | AY38: 3755.08 | AZ38: 3809.13 | BA38: 4064.92 | BB38: 3764.45 | BC38: 4151.66 | BD38: 4606.84 | BE38: 4850.83 | BF38: 4663.25 | BG38: 4171.7 | BH38: 4067.88 | BI38: 3854.92 | BJ38: 3852.31 | BK38: 4153.08 | BL38: 4206.9 | BM38: 4405.77 | BN38: 4182.91 | BO38: 4099.51 | BP38: 3929.29 | BQ38: 3918.4785 | BR38: 3982.981 | BS38: 4007.0792 | BT38: 3963.7575 | BU38: 3952.8511 | CY38: 1938.5 | CZ38: 1767 | DA38: 1929.51 | DB38: 2376.51 | DC38: 3174.5 | DD38: 3002 | DE38: 2985.78 | DF38: 3254.25 | DG38: 3287.23 | DH38: 3428.26 | DI38: 4064.92 | DJ38: 4850.83 | DK38: 3854.92 | DL38: 4405.77 | DM38: 3918.4785 | DN38: 3952.8511 | DO38: 4010.9812 | DP38: 4069.9663 | DQ38: 4129.8187 | DR38: 4190.5513 | DS38: 4252.1771 | DT38: 4314.7091 | DU38: 4378.1607 | DV38: 4442.5454 | DW38: 4507.877 | DX38: 4574.1693 | DY38: 4641.4365 | DZ38: 4709.6929 | EA38: 4778.9531 | EB38: 4849.2318
A39: ARS Curncy | B39: 3.7185 | C39: 3.7956 | D39: 3.8416 | E39: 3.799 | F39: 3.8788 | G39: 3.9305 | H39: 3.9595 | I39: 3.9787 | J39: 4.0517 | K39: 4.1085 | L39: 4.2048 | M39: 4.3 | N39: 4.3788 | O39: 4.526 | P39: 4.6966 | Q39: 4.9155 | R39: 5.1213 | S39: 5.3865 | T39: 5.7915 | U39: 6.5197 | V39: 8.0029 | W39: 8.1323 | X39: 8.4275 | Y39: 8.465 | Z39: 8.819 | AA39: 9.0869 | AB39: 9.4186 | AC39: 12.9315 | AD39: 14.7045 | AE39: 15.045 | AF39: 15.3075 | AG39: 15.88 | AH39: 15.39 | AI39: 16.601 | AJ39: 17.33 | AK39: 18.649 | AL39: 20.149 | AM39: 28.85 | AN39: 41.25 | AO39: 37.7 | AP39: 43.345 | AQ39: 42.45 | AR39: 57.595 | AS39: 59.89 | AT39: 64.469 | AU39: 70.46 | AV39: 76.18 | AW39: 84.15 | AX39: 92 | AY39: 95.72 | AZ39: 98.74 | BA39: 102.72 | BB39: 111.01 | BC39: 125.23 | BD39: 147.32 | BE39: 177.16 | BF39: 209.01 | BG39: 256.7 | BH39: 349.9984 | BI39: 808.475 | BJ39: 857.6721 | BK39: 911.5066 | BL39: 968.7194 | BM39: 1030.985 | BN39: 1073.1025 | BO39: 1203.6274 | BP39: 1413.4629 | BQ39: 1419.8786 | BR39: 1475.9755 | BS39: 1522.2046 | BT39: 1568.329 | BU39: 1607.8643 | BV39: ver ARS | CY39: 4.3 | CZ39: 4.9155 | DA39: 6.5197 | DB39: 8.465 | DC39: 12.9315 | DD39: 15.88 | DE39: 18.649 | DF39: 37.7 | DG39: 59.89 | DH39: 84.15 | DI39: 102.72 | DJ39: 177.16 | DK39: 808.475 | DL39: 1030.985 | DM39: 1419.8786 | DN39: 1607.8643 | DO39: 1702.4446 | DP39: 1802.5883 | DQ39: 1908.623 | DR39: 2020.8949 | DS39: 2139.7711 | DT39: 2265.64 | DU39: 2398.9129 | DV39: 2540.0254 | DW39: 2689.4387 | DX39: 2847.6409 | DY39: 3015.1492 | DZ39: 3192.511 | EA39: 3380.3057 | EB39: 3579.1472
A40: BRL Curncy | B40: 2.3228 | C40: 1.9518 | D40: 1.767 | E40: 1.7445 | F40: 1.779 | G40: 1.8047 | H40: 1.6873 | I40: 1.6613 | J40: 1.6318 | K40: 1.5633 | L40: 1.8793 | M40: 1.8668 | N40: 1.8268 | O40: 2.0094 | P40: 2.0264 | Q40: 2.0516 | R40: 2.0219 | S40: 2.2322 | T40: 2.2169 | U40: 2.3592 | V40: 2.272 | W40: 2.2145 | X40: 2.4461 | Y40: 2.6582 | Z40: 3.1974 | AA40: 3.103 | AB40: 3.9471 | AC40: 3.964 | AD40: 3.5928 | AE40: 3.2126 | AF40: 3.2613 | AG40: 3.25 | AH40: 3.122 | AI40: 3.3082 | AJ40: 3.1625 | AK40: 3.3125 | AL40: 3.3063 | AM40: 3.8769 | AN40: 4.0504 | AO40: 3.8812 | AP40: 3.921 | AQ40: 3.8497 | AR40: 4.157 | AS40: 4.0249 | AT40: 5.2053 | AU40: 5.4659 | AV40: 5.6103 | AW40: 5.1935 | AX40: 5.6344 | AY40: 4.969 | AZ40: 5.443 | BA40: 5.5714 | BB40: 4.7411 | BC40: 5.2559 | BD40: 5.4138 | BE40: 5.286 | BF40: 5.064 | BG40: 4.7854 | BH40: 5.0341 | BI40: 4.8572 | BJ40: 5.0141 | BK40: 5.594 | BL40: 5.4496 | BM40: 6.1774 | BN40: 5.7057 | BO40: 5.4317 | BP40: 5.4304 | BQ40: 5.4622714 | BR40: 5.5272747 | BS40: 5.5405334 | BT40: 5.5293751 | BU40: 5.5618274 | CY40: 1.8668 | CZ40: 2.0516 | DA40: 2.3592 | DB40: 2.6582 | DC40: 3.964 | DD40: 3.25 | DE40: 3.3125 | DF40: 3.8812 | DG40: 4.0249 | DH40: 5.1935 | DI40: 5.5714 | DJ40: 5.286 | DK40: 4.8572 | DL40: 6.1774 | DM40: 5.4622714 | DN40: 5.5618274 | DO40: 5.6965108 | DP40: 5.8344558 | DQ40: 5.9757411 | DR40: 6.1204478 | DS40: 6.2686586 | DT40: 6.4204585 | DU40: 6.5759343 | DV40: 6.7351751 | DW40: 6.898272 | DX40: 7.0653183 | DY40: 7.2364099 | DZ40: 7.4116445 | EA40: 7.5911226 | EB40: 7.7749468
A41: PYG Curncy | B41: 5120 | C41: 5045 | D41: 4895 | E41: 4672.5 | F41: 4745 | G41: 4760 | H41: 4820 | I41: 4645 | J41: 4115 | K41: 4055 | L41: 4180 | M41: 4435 | N41: 4310 | O41: 4540 | P41: 4465 | Q41: 4220 | R41: 4008 | S41: 4452.5 | T41: 4427.5 | U41: 4598.2 | V41: 4442.1 | W41: 4386.9 | X41: 4527.5 | Y41: 4635.7 | Z41: 4798.8 | AA41: 5183.5 | AB41: 5636.1 | AC41: 5782 | AD41: 5628.7 | AE41: 5589 | AF41: 5555.4 | AG41: 5737.5 | AH41: 5638.1 | AI41: 5555 | AJ41: 5667.5 | AK41: 5588 | AL41: 5548.3 | AM41: 5693.2 | AN41: 5892.9 | AO41: 5963.9 | AP41: 6190 | AQ41: 6197.5 | AR41: 6380.1 | AS41: 6465 | AT41: 6563 | AU41: 6817.5 | AV41: 6990.2 | AW41: 6911.6 | AX41: 6311.1 | AY41: 6752.3 | AZ41: 6907 | BA41: 6876.9 | BB41: 6941.9 | BC41: 6849.1 | BD41: 7074.7 | BE41: 7339.5 | BF41: 7181.8 | BG41: 7265.8 | BH41: 7287.5 | BI41: 7275 | BJ41: 7385.5 | BK41: 7538.5 | BL41: 7793.8 | BM41: 7820.2 | BN41: 7987.9 | BO41: 7928.5 | BP41: 7172.3 | BQ41: 7206.0363 | BR41: 7301.7476 | BS41: 7315.7969 | BT41: 7337.2681 | BU41: 7368.2177 | CY41: 4435 | CZ41: 4220 | DA41: 4598.2 | DB41: 4635.7 | DC41: 5782 | DD41: 5737.5 | DE41: 5588 | DF41: 5963.9 | DG41: 6465 | DH41: 6911.6 | DI41: 6876.9 | DJ41: 7339.5 | DK41: 7275 | DL41: 7820.2 | DM41: 7206.0363 | DN41: 7368.2177 | DO41: 7578.3671 | DP41: 7794.5102 | DQ41: 8016.8179 | DR41: 8245.4661 | DS41: 8480.6356 | DT41: 8722.5123 | DU41: 8971.2877 | DV41: 9227.1583 | DW41: 9490.3267 | DX41: 9761.0009 | DY41: 10039.395 | DZ41: 10325.729 | EA41: 10620.23 | EB41: 10923.13
A42: MXN Curncy | B42: 14.1456 | C42: 13.1697 | D42: 13.4885 | E42: 13.0817 | F42: 12.3319 | G42: 12.867 | H42: 12.6005 | I42: 12.3401 | J42: 11.8989 | K42: 11.7141 | L42: 13.8973 | M42: 13.9357 | N42: 12.8107 | O42: 13.3608 | P42: 12.8585 | Q42: 12.9251 | R42: 12.3312 | S42: 12.9308 | T42: 13.1665 | U42: 13.0954 | V42: 13.0543 | W42: 12.9769 | X42: 13.4279 | Y42: 14.7472 | Z42: 15.2707 | AA42: 15.6885 | AB42: 16.9177 | AC42: 17.2075 | AD42: 17.2793 | AE42: 18.4684 | AF42: 19.3852 | AG42: 20.7272 | AH42: 18.7249 | AI42: 18.1203 | AJ42: 18.2545 | AK42: 19.659 | AL42: 18.1812 | AM42: 19.9078 | AN42: 18.7183 | AO42: 19.6504 | AP42: 19.4279 | AQ42: 19.2229 | AR42: 19.7344 | AS42: 18.9265 | AT42: 23.6723 | AU42: 22.9924 | AV42: 22.1146 | AW42: 19.9143 | AX42: 20.4325 | AY42: 19.9365 | AZ42: 20.64 | BA42: 20.5294 | BB42: 19.8699 | BC42: 20.1183 | BD42: 20.1382 | BE42: 19.4999 | BF42: 18.0462 | BG42: 17.1248 | BH42: 17.4227 | BI42: 16.972 | BJ42: 16.5586 | BK42: 18.3183 | BL42: 19.6915 | BM42: 20.8272 | BN42: 20.4711 | BO42: 18.7475 | BP42: 18.6365 | BQ42: 18.716092 | BR42: 18.799831 | BS42: 18.90244 | BT42: 18.799978 | BU42: 18.880269 | CY42: 13.9357 | CZ42: 12.9251 | DA42: 13.0954 | DB42: 14.7472 | DC42: 17.2075 | DD42: 20.7272 | DE42: 19.659 | DF42: 19.6504 | DG42: 18.9265 | DH42: 19.9143 | DI42: 20.5294 | DJ42: 19.4999 | DK42: 16.972 | DL42: 20.8272 | DM42: 18.716092 | DN42: 18.880269 | DO42: 19.15792 | DP42: 19.439654 | DQ42: 19.725531 | DR42: 20.015612 | DS42: 20.30996 | DT42: 20.608635 | DU42: 20.911704 | DV42: 21.219229 | DW42: 21.531276 | DX42: 21.847913 | DY42: 22.169205 | DZ42: 22.495223 | EA42: 22.826035 | EB42: 23.161712
A43: UYU Curncy | B43: 24.05 | C43: 23.522 | D43: 21.45 | E43: 19.5 | F43: 19.45 | G43: 21.12 | H43: 20.3 | I43: 19.9 | J43: 19.25 | K43: 18.4 | L43: 20.3039 | M43: 19.95 | N43: 19.5 | O43: 21.63 | P43: 21 | Q43: 19.18 | R43: 18.945 | S43: 20.555 | T43: 22.05 | U43: 21.3995 | V43: 22.634 | W43: 22.88 | X43: 24.68 | Y43: 24.333 | Z43: 25.735 | AA43: 27.0505 | AB43: 29.097 | AC43: 29.873 | AD43: 31.76 | AE43: 30.5 | AF43: 28.365 | AG43: 29.261 | AH43: 28.52 | AI43: 28.525 | AJ43: 28.99 | AK43: 28.7 | AL43: 28.335 | AM43: 31.485 | AN43: 33.35 | AO43: 32.4 | AP43: 33.47 | AQ43: 35.18 | AR43: 36.96 | AS43: 37.35 | AT43: 43.1 | AU43: 42.2025 | AV43: 42.55 | AW43: 42.3525 | AX43: 44.22 | AY43: 43.6075 | AZ43: 42.9425 | BA43: 44.6875 | BB43: 41.1375 | BC43: 39.7725 | BD43: 41.7125 | BE43: 39.9125 | BF43: 38.665 | BG43: 37.5 | BH43: 38.4925 | BI43: 38.85 | BJ43: 37.55 | BK43: 39.95 | BL43: 41.8 | BM43: 43.95 | BN43: 42.135 | BO43: 39.775 | BP43: 40.075 | BQ43: 40.041739 | BR43: 41.261475 | BS43: 41.757907 | BT43: 42.135464 | BU43: 42.100494 | CY43: 19.95 | CZ43: 19.18 | DA43: 21.3995 | DB43: 24.333 | DC43: 29.873 | DD43: 29.261 | DE43: 28.7 | DF43: 32.4 | DG43: 37.35 | DH43: 42.3525 | DI43: 44.6875 | DJ43: 39.9125 | DK43: 38.85 | DL43: 43.95 | DM43: 40.041739 | DN43: 42.100494 | DO43: 44.525482 | DP43: 47.09015 | DQ43: 49.802543 | DR43: 52.67117 | DS43: 55.705029 | DT43: 58.913639 | DU43: 62.307065 | DV43: 65.895952 | DW43: 69.69156 | DX43: 73.705794 | DY43: 77.951248 | DZ43: 82.44124 | EA43: 87.189856 | EB43: 92.211992
A44: EUR Curncy | F44: 1.3509862 | G44: 1.2236907 | H44: 1.3635124 | I44: 1.3385089 | J44: 1.4156285 | K44: 1.450116 | L44: 1.3390466 | M44: 1.2963443 | N44: 1.3342228 | O44: 1.265983 | P44: 1.2858429 | Q44: 1.3192612 | R44: 1.2817226 | S44: 1.3008976 | T44: 1.3526309 | U44: 1.3741927 | V44: 1.3768415 | W44: 1.3689254 | X44: 1.2631047 | Y44: 1.209775 | Z44: 1.0731917 | AA44: 1.1137098 | AB44: 1.1176931 | AC44: 1.0857763 | AD44: 1.1380448 | AE44: 1.1106175 | AF44: 1.1234693 | AG44: 1.0519672 | AH44: 1.0652 | AI44: 1.1426 | AJ44: 1.1814 | AK44: 1.2005 | AL44: 1.2324 | AM44: 1.1684 | AN44: 1.1604 | AO44: 1.1467 | AP44: 1.1218 | AQ44: 1.1373 | AR44: 1.0899 | AS44: 1.1213 | AT44: 1.1031 | AU44: 1.1234 | AV44: 1.1721 | AW44: 1.2216 | AX44: 1.173 | AY44: 1.1858 | AZ44: 1.158 | BA44: 1.137 | BB44: 1.1067 | BC44: 1.0484 | BD44: 0.9802 | BE44: 1.0705 | BF44: 1.0839 | BG44: 1.0909 | BH44: 1.0573 | BI44: 1.1039 | BJ44: 1.079 | BK44: 1.0713 | BL44: 1.1135 | BM44: 1.0354 | BN44: 1.0816 | BO44: 1.1787 | BP44: 1.1742 | BQ44: 1.1742 | BR44: 1.1742 | BS44: 1.1742 | BT44: 1.1742 | BU44: 1.1742 | CY44: 1.2963443 | CZ44: 1.3192612 | DA44: 1.3741927 | DB44: 1.209775 | DC44: 1.0857763 | DD44: 1.0519672 | DE44: 1.2005 | DF44: 1.1467 | DG44: 1.1213 | DH44: 1.2216 | DI44: 1.137 | DJ44: 1.0705 | DK44: 1.1039 | DL44: 1.0354 | DM44: 1.1742 | DN44: 1.1742 | DO44: 1.1742 | DP44: 1.1742 | DQ44: 1.1742 | DR44: 1.1742 | DS44: 1.1742 | DT44: 1.1742 | DU44: 1.1742 | DV44: 1.1742 | DW44: 1.1742 | DX44: 1.1742 | DY44: 1.1742 | DZ44: 1.1742 | EA44: 1.1742 | EB44: 1.1742
A46: Tasa de interes
A47: TJLP final | AP47: 0.0703 | AQ47: 0.0626 | AR47: 0.0595 | AS47: 0.0557 | AT47: 0.05 | AU47: 0.0494 | AV47: 0.0491 | AW47: 0.0455 | AX47: 0.0439 | AY47: 0.0461 | AZ47: 0.0488 | BA47: 0.0532 | BB47: 0.0608 | BC47: 0.0682 | BD47: 0.0701 | BE47: 0.072 | BF47: 0.0728 | BG47: 0.0728 | BH47: 0.07 | BI47: 0.0655 | BJ47: 0.0653 | BK47: 0.0667 | BL47: 0.0691 | BM47: 0.0743 | BN47: 0.0797 | BO47: 0.0865 | BP47: 0.095 | BQ47: 0.093 | BR47: 0.087 | BS47: 0.0795 | BT47: 0.074 | BU47: 0.0685 | DB47: 0.05 | DC47: 0.0625 | DD47: 0.075 | DE47: 0.07125 | DF47: 0.0675 | DG47: 0.0557 | DH47: 0.0455 | DI47: 0.0532 | DJ47: 0.072 | DK47: 0.0655 | DL47: 0.0743 | DM47: 0.093 | DN47: 0.0685 | DO47: 0.0685 | DP47: 0.0685 | DQ47: 0.0685 | DR47: 0.0685 | DS47: 0.0685 | DT47: 0.0685 | DU47: 0.0685 | DV47: 0.0685 | DW47: 0.0685 | DX47: 0.0685 | DY47: 0.0685 | DZ47: 0.0685 | EA47: 0.0685 | EB47: 0.0685
A48: SOFR/LIBOR 3m Avg | C48: 0.0084042 | D48: 0.0041381 | E48: 0.0026832 | F48: 0.0025693 | G48: 0.0043862 | H48: 0.0038847 | I48: 0.002928 | J48: 0.0030794 | K48: 0.0026219 | L48: 0.0029853 | M48: 0.0047789 | N48: 0.005135 | O48: 0.0046632 | P48: 0.0042513 | Q48: 0.0031756 | R48: 0.0029202 | S48: 0.0027504 | T48: 0.0026158 | U48: 0.0024128 | V48: 0.0023589 | W48: 0.0022822 | X48: 0.0023427 | Y48: 0.0023618 | Z48: 0.002605 | AA48: 0.0027951 | AB48: 0.0031363 | AC48: 0.0040716 | AD48: 0.0062484 | AE48: 0.0064316 | AF48: 0.0078678 | AG48: 0.0091976 | AH48: 0.0107078 | AI48: 0.0120555 | AJ48: 0.0131498 | AK48: 0.014591 | AL48: 0.019251 | AM48: 0.0233826 | AN48: 0.02337 | AO48: 0.0262256 | AP48: 0.0268706 | AQ48: 0.0250666 | AR48: 0.0219759 | AS48: 0.0193177 | AT48: 0.0152913 | AU48: 0.0059578 | AV48: 0.002528 | AW48: 0.0022472 | AX48: 0.0020043 | AY48: 0.001572 | AZ48: 0.001572 | BA48: #VALUE! | BB48: 0.0051787 | BC48: 0.01548 | BD48: 0.03 | BE48: 0.040657143 | BF48: 0.04498871 | BG48: 0.049677419 | BH48: 0.052369841 | BI48: 0.053217742 | BJ48: 0.053144262 | BK48: 0.053185714 | BL48: 0.052778125 | BM48: 0.046787097 | BN48: 0.043281967 | BO48: 0.043564286 | BP48: 0.0401 | BQ48: 0.0377 | BR48: 0.0359 | BS48: 0.0344 | BT48: 0.0337 | BU48: 0.0331 | CZ48: 0.004306275 | DA48: 0.0026748 | DB48: 0.0023364 | DC48: 0.003152 | DD48: 0.00743635 | DE48: 0.012626025 | DF48: 0.0230573 | DG48: 0.0233077 | DH48: 0.006506075 | DI48: #VALUE! | DJ48: 0.022828961 | DK48: 0.053217742 | DL48: 0.046787097 | DM48: 0.0377 | DN48: 0.0331 | DO48: 0.0331 | DP48: 0.0331 | DQ48: 0.0331 | DR48: 0.0331 | DS48: 0.0331 | DT48: 0.0331 | DU48: 0.0331 | DV48: 0.0331 | DW48: 0.0331 | DX48: 0.0331 | DY48: 0.0331 | DZ48: 0.0331 | EA48: 0.0331 | EB48: 0.0331
A49: Taxa de Juros (Chile) - final | C49: 0.0075 | D49: 0.005 | E49: 0.005 | F49: 0.005 | G49: 0.01 | H49: 0.025 | I49: 0.0325 | J49: 0.04 | K49: 0.0525 | L49: 0.0525 | M49: 0.0525 | N49: 0.05 | O49: 0.05 | P49: 0.05 | Q49: 0.05 | R49: 0.05 | S49: 0.05 | T49: 0.05 | U49: 0.045 | V49: 0.04 | W49: 0.04 | X49: 0.0325 | Y49: 0.03 | Z49: 0.03 | AA49: 0.03 | AB49: 0.03 | AC49: 0.035 | AD49: 0.035 | AE49: 0.035 | AF49: 0.035 | AG49: 0.035 | AH49: 0.03 | AI49: 0.025 | AJ49: 0.025 | AK49: 0.025 | AL49: 0.025 | AM49: 0.025 | AN49: 0.025 | AO49: 0.0275 | AP49: 0.03 | AQ49: 0.025 | AR49: 0.02 | AS49: 0.0175 | AT49: 0.005 | AU49: 0.005 | AV49: 0.005 | AW49: 0.005 | AX49: 0.005 | AY49: 0.005 | AZ49: 0.015 | BA49: 0.04 | BB49: 0.07 | BC49: 0.09 | BD49: 0.1075 | BE49: 0.1125 | BF49: 0.1125 | BG49: 0.1125 | BH49: 0.095 | BI49: 0.0825 | BJ49: 0.0725 | BK49: 0.0575 | BL49: 0.055 | BM49: 0.05 | BN49: 0.05 | BO49: 0.05 | BP49: 0.0475 | BQ49: 0.0475 | BR49: 0.0465 | BS49: 0.0455 | BT49: 0.0455 | BU49: 0.0415 | CY49: 0.0525 | CZ49: 0.05 | DA49: 0.045 | DB49: 0.03 | DC49: 0.035 | DD49: 0.035 | DE49: 0.025 | DF49: 0.0275 | DG49: 0.0175 | DH49: 0.005 | DI49: 0.04 | DJ49: 0.1125 | DK49: 0.0825 | DL49: 0.05 | DM49: 0.0475 | DN49: 0.0415 | DO49: 0.0415 | DP49: 0.0415 | DQ49: 0.0415 | DR49: 0.0415 | DS49: 0.0415 | DT49: 0.0415 | DU49: 0.0415 | DV49: 0.0415 | DW49: 0.0415 | DX49: 0.0415 | DY49: 0.0415 | DZ49: 0.0415 | EA49: 0.0415 | EB49: 0.0415
A50: Taxa de Juros (Chile) - avg | B50: 0.054688 | C50: 0.0139 | D50: 0.0052 | E50: 0.005 | F50: 0.005 | G50: 0.0059 | H50: 0.0177 | I50: 0.029 | J50: 0.0346 | K50: 0.0478 | L50: 0.0525 | M50: 0.0525 | N50: 0.0503 | O50: 0.05 | P50: 0.05 | Q50: 0.05 | R50: 0.05 | S50: 0.05 | T50: 0.05 | U50: 0.0468 | V50: 0.0433 | W50: 0.04 | X50: 0.0361 | Y50: 0.0304 | Z50: 0.03 | AA50: 0.03 | AB50: 0.03 | AC50: 0.0325 | AD50: 0.035 | AE50: 0.035 | AF50: 0.035 | AG50: 0.035 | AH50: 0.0325 | AI50: 0.0265 | AJ50: 0.025 | AK50: 0.025 | AL50: 0.025 | AM50: 0.025 | AN50: 0.025 | AO50: 0.027 | AP50: 0.0292 | AQ50: 0.0288 | AR50: 0.0235 | AS50: 0.0181 | AT50: 0.016 | AU50: 0.005 | AV50: 0.005 | AW50: 0.005 | AX50: 0.005 | AY50: 0.005 | AZ50: 0.0097 | BA50: 0.0287 | BB50: 0.051496667 | BC50: 0.078903297 | BD50: 0.09875 | BE50: 0.11 | BF50: 0.1125 | BG50: 0.1125 | BH50: 0.10379167 | BI50: 0.090625 | BJ50: 0.075992063 | BK50: 0.062909836 | BL50: 0.056844262 | BM50: 0.052701613 | BN50: 0.05 | BO50: 0.05 | BP50: 0.04875 | BQ50: 0.0475 | BR50: 0.047 | BS50: 0.046 | BT50: 0.0455 | BU50: 0.0435 | CY50: 0.04685 | CZ50: 0.050075 | DA50: 0.0492 | DB50: 0.03745 | DC50: 0.030625 | DD50: 0.035 | DE50: 0.02725 | DF50: 0.0255 | DG50: 0.0249 | DH50: 0.00775 | DI50: 0.0121 | DJ50: 0.084787491 | DK50: 0.090625 | DL50: 0.052701613 | DM50: 0.0475 | DN50: 0.0435 | DO50: 0.0415 | DP50: 0.0415 | DQ50: 0.0415 | DR50: 0.0415 | DS50: 0.0415 | DT50: 0.0415 | DU50: 0.0415 | DV50: 0.0415 | DW50: 0.0415 | DX50: 0.0415 | DY50: 0.0415 | DZ50: 0.0415 | EA50: 0.0415 | EB50: 0.0415
A51: TIIE 28d Final | C51: 0.050665 | D51: 0.049349 | E51: 0.049231 | F51: 0.049075 | G51: 0.04925 | H51: 0.04895 | I51: 0.04875 | J51: 0.048331 | K51: 0.0485 | L51: 0.047843 | M51: 0.048035 | N51: 0.0477 | O51: 0.0477 | P51: 0.048075 | Q51: 0.048475 | R51: 0.043512 | S51: 0.043137 | T51: 0.040265 | U51: 0.03795 | V51: 0.03815 | W51: 0.033075 | X51: 0.032793 | Y51: 0.033205 | Z51: 0.03299 | AA51: 0.0331 | AB51: 0.033225 | AC51: 0.03555 | AD51: 0.04065 | AE51: 0.041138 | AF51: 0.050725 | AG51: 0.0611 | AH51: 0.06835 | AI51: 0.07365 | AJ51: 0.073725 | AK51: 0.076311 | AL51: 0.078503 | AM51: 0.081004 | AN51: 0.0812 | AO51: 0.085897 | AP51: 0.08515 | AQ51: 0.084887 | AR51: 0.080275 | AS51: #VALUE! | AT51: #VALUE! | AU51: 0.052843 | AV51: 0.0475 | AW51: 0.0425 | AX51: 0.042875 | AY51: 0.0453 | AZ51: 0.0475 | BA51: 0.0571 | BB51: 0.0672 | BC51: 0.0803 | BD51: 0.095 | BE51: 0.105 | BF51: 0.115 | BG51: 0.115 | BH51: 0.115028 | BI51: 0.115025 | BJ51: 0.112485 | BK51: 0.112445 | BL51: 0.1074 | BM51: 0.10245 | BN51: 0.092704 | BO51: 0.092704 | BP51: 0.0775 | BQ51: 0.075 | BR51: 0.073 | BS51: 0.071 | BT51: 0.0705 | BU51: 0.068 | CY51: 0.048035 | CZ51: 0.048475 | DA51: 0.03795 | DB51: 0.033205 | DC51: 0.03555 | DD51: 0.0611 | DE51: 0.076311 | DF51: 0.085897 | DG51: #VALUE! | DH51: 0.0425 | DI51: 0.0571 | DJ51: 0.105 | DK51: 0.115025 | DL51: 0.10245 | DM51: 0.075 | DN51: 0.068 | DO51: 0.068 | DP51: 0.068 | DQ51: 0.068 | DR51: 0.068 | DS51: 0.068 | DT51: 0.068 | DU51: 0.068 | DV51: 0.068 | DW51: 0.068 | DX51: 0.068 | DY51: 0.068 | DZ51: 0.068 | EA51: 0.068 | EB51: 0.068
A52: BZSELICA Index Avg | B52: 0.1254 | C52: 0.1026 | D52: 0.0878 | E52: 0.0865 | F52: 0.0865 | G52: 0.0936 | H52: 0.1054 | I52: 0.1066 | J52: 0.1122 | K52: 0.1192 | L52: 0.122 | M52: 0.1132 | N52: 0.103 | O52: 0.0887 | P52: 0.0779 | Q52: 0.0718 | R52: 0.0713 | S52: 0.0752 | T52: 0.0851 | U52: 0.0952 | V52: 0.104 | W52: 0.1089 | X52: 0.109 | Y52: 0.1122 | Z52: 0.1219 | AA52: 0.1314 | AB52: 0.1399 | AC52: 0.1415 | AD52: 0.1415 | AE52: 0.1415 | AF52: 0.1415 | AG52: 0.1386 | AH52: 0.127 | AI52: 0.1094 | AJ52: 0.0918 | AK52: 0.0748 | AL52: 0.0674 | AM52: 0.064 | AN52: 0.064 | AO52: 0.064 | AP52: 0.064 | AQ52: 0.064 | AR52: 0.0601 | AS52: 0.0497 | AT52: 0.0418 | AU52: 0.0307 | AV52: 0.02 | AW52: 0.019 | AX52: 0.0202 | AY52: 0.0324 | AZ52: 0.0486 | BA52: 0.0763 | BB52: 0.10254667 | BC52: 0.13 | BD52: 0.1375 | BE52: 0.1365 | BF52: 0.1365 | BG52: 0.1365 | BH52: 0.13275 | BI52: 0.12240164 | BJ52: 0.11281148 | BK52: 0.10507143 | BL52: 0.10430303 | BM52: 0.11142063 | BN52: 0.12953279 | BO52: 0.1415 | BP52: 0.15 | BQ52: 0.148 | BR52: 0.142 | BS52: 0.1345 | BT52: 0.129 | BU52: 0.1235 | CY52: 0.11665 | CZ52: 0.08535 | DA52: 0.0817 | DB52: 0.108525 | DC52: 0.133675 | DD52: 0.140775 | DE52: 0.10075 | DF52: 0.06485 | DG52: 0.0497 | DH52: 0.019 | DI52: 0.0763 | DJ52: 0.1365 | DK52: 0.12240164 | DL52: 0.11142063 | DM52: 0.148 | DN52: 0.1235 | DO52: 0.1235 | DP52: 0.1235 | DQ52: 0.1235 | DR52: 0.1235 | DS52: 0.1235 | DT52: 0.1235 | DU52: 0.1235 | DV52: 0.1235 | DW52: 0.1235 | DX52: 0.1235 | DY52: 0.1235 | DZ52: 0.1235 | EA52: 0.1235 | EB52: 0.1235
A53: CPI Index
A54: USA | C54: 214.79 | D54: 215.861 | E54: 217.347 | F54: 217.353 | G54: 217.199 | H54: 218.275 | I54: 220.472 | J54: 223.046 | K54: 224.806 | L54: 226.597 | M54: 227.223 | N54: 228.807 | O54: 228.524 | P54: 231.015 | Q54: 231.221 | R54: 232.282 | S54: 232.445 | T54: 233.544 | U54: 234.719 | V54: 236.028 | W54: 237.231 | X54: 237.477 | Y54: 236.252 | Z54: 235.976 | AA54: 237.657 | AB54: 237.498 | AC54: 237.761 | AD54: 238.08 | AE54: 240.222 | AF54: 241.176 | AG54: 242.637 | AH54: 243.892 | AI54: 244.163 | AJ54: 246.435 | AK54: 247.805 | AL54: 249.577 | AM54: 251.018 | AN54: 252.182 | AO54: 252.767 | AP54: 254.277 | AQ54: 255.213 | AR54: 256.43 | AS54: 258.63 | AT54: 258.076 | AU54: 257.042 | AV54: 259.997 | AW54: 262.045 | AX54: 264.847 | AY54: 270.71 | AZ54: 273.942 | BA54: 280.806 | BB54: 287.467 | BC54: 295.072 | BD54: 296.421 | BE54: 298.808 | BF54: 301.643 | BG54: 304.099 | BH54: 307.374 | BI54: 308.735 | BJ54: 312.107 | BK54: 313.131 | BL54: 314.851 | BM54: 317.603 | BN54: 319.615 | BO54: 321.5 | BP54: 325.55593 | BQ54: 328.62382 | BR54: 330.03445 | BS54: 331.17715 | BT54: 334.02039 | BU54: 337.16804 | CY54: 227.223 | CZ54: 231.221 | DA54: 234.719 | DB54: 236.252 | DC54: 237.761 | DD54: 242.637 | DE54: 247.805 | DF54: 252.767 | DG54: 258.63 | DH54: 262.045 | DI54: 280.806 | DJ54: 298.808 | DK54: 308.735 | DL54: 317.603 | DM54: 328.62382 | DN54: 337.16804 | DO54: 343.9114 | DP54: 350.78963 | DQ54: 357.80543 | DR54: 364.96153 | DS54: 372.26076 | DT54: 379.70598 | DU54: 387.3001 | DV54: 395.0461 | DW54: 402.94702 | DX54: 411.00596 | DY54: 419.22608 | DZ54: 427.6106 | EA54: 436.16282 | EB54: 444.88607
A55: Chile | C55: 0 | D55: 0 | E55: 57.31 | F55: 57.82 | G55: 58.3 | H55: 58.85 | I55: 59.02 | J55: 59.77 | K55: 60.3 | L55: 60.78 | M55: 61.64 | N55: 62.03 | O55: 61.9 | P55: 62.5 | Q55: 62.55 | R55: 62.98 | S55: 63.07 | T55: 63.73 | U55: 64.44 | V55: 65.41 | W55: 66.08 | X55: 67 | Y55: 67.43 | Z55: 68.15 | AA55: 69 | AB55: 70.11 | AC55: 70.39 | AD55: 71.18 | AE55: 71.9 | AF55: 72.28 | AG55: 72.29 | AH55: 73.14 | AI55: 73.12 | AJ55: 73.33 | AK55: 73.93 | AL55: 74.46 | AM55: 74.98 | AN55: 75.63 | AO55: 75.83 | AP55: 76.31 | AQ55: 77.01 | AR55: 77.33 | AS55: 78.1 | AT55: 79.16 | AU55: 79.03 | AV55: 79.72 | AW55: 80.43 | AX55: 81.45 | AY55: 82.04 | AZ55: 83.98 | BA55: 86.2 | BB55: 89.11 | BC55: 92.29 | BD55: 95.51 | BE55: 97.21 | BF55: 99 | BG55: 99.26 | BH55: 100.39 | BI55: 101.04 | BJ55: 102.7 | BK55: 103.42 | BL55: 104.54 | BM55: 105.62 | BN55: 107.7 | BO55: 107.68 | BP55: 109.1084 | BQ55: 110.26728 | BR55: 111.1464 | BS55: 110.80272 | BT55: 112.27254 | BU55: 113.68557 | CY55: 61.64 | CZ55: 62.55 | DA55: 64.44 | DB55: 67.43 | DC55: 70.39 | DD55: 72.29 | DE55: 73.93 | DF55: 75.83 | DG55: 78.1 | DH55: 80.43 | DI55: 86.2 | DJ55: 97.21 | DK55: 101.04 | DL55: 105.62 | DM55: 110.26728 | DN55: 113.68557 | DO55: 117.09613 | DP55: 120.60902 | DQ55: 124.22729 | DR55: 127.95411 | DS55: 131.79273 | DT55: 135.74651 | DU55: 139.81891 | DV55: 144.01347 | DW55: 148.33388 | DX55: 152.78389 | DY55: 157.36741 | DZ55: 162.08843 | EA55: 166.95109 | EB55: 171.95962
A56: Peru | C56: 69.36 | D56: 69.28 | E56: 69.51 | F56: 70.13 | G56: 70.5 | H56: 70.92 | I56: 70.95 | J56: 72 | K56: 72.55 | L56: 73.56 | M56: 74.31 | N56: 75.05 | O56: 75.45 | P56: 76.31 | Q56: 76.28 | R56: 76.99 | S56: 77.54 | T56: 78.47 | U56: 78.46 | V56: 79.6 | W56: 80.22 | X56: 80.62 | Y56: 80.99 | Z56: 82 | AA56: 83.06 | AB56: 83.77 | AC56: 84.56 | AD56: 85.53 | AE56: 85.84 | AF56: 86.39 | AG56: 87.29 | AH56: 88.93 | AI56: 88.18 | AJ56: 88.94 | AK56: 88.48 | AL56: 89.25 | AM56: 89.44 | AN56: 90.07 | AO56: 90.42 | AP56: 91.25 | AQ56: 91.49 | AR56: 91.74 | AS56: 92.14 | AT56: 92.92 | AU56: 92.96 | AV56: 93.41 | AW56: 93.96 | AX56: 95.33 | AY56: 95.98 | AZ56: 98.3 | BA56: 100 | BB56: 101.84 | BC56: 104.44 | BD56: 106.68 | BE56: 108.46 | BF56: 110.39 | BG56: 111.19 | BH56: 112.06 | BI56: 111.97 | BJ56: 113.75 | BK56: 113.73 | BL56: 114.05 | BM56: 114.17 | BN56: 115.21 | BO56: 115.66 | BP56: 116.1029 | BQ56: 116.73882 | BR56: 117.80223 | BS56: 118.43584 | BT56: 118.71522 | BU56: 119.36545 | CY56: 74.31 | CZ56: 76.28 | DA56: 78.46 | DB56: 80.99 | DC56: 84.56 | DD56: 87.29 | DE56: 88.48 | DF56: 90.42 | DG56: 92.14 | DH56: 93.96 | DI56: 100 | DJ56: 108.46 | DK56: 111.97 | DL56: 114.17 | DM56: 116.73882 | DN56: 119.36545 | DO56: 122.05117 | DP56: 124.79732 | DQ56: 127.60526 | DR56: 130.47638 | DS56: 133.4121 | DT56: 136.41387 | DU56: 139.48318 | DV56: 142.62156 | DW56: 145.83054 | DX56: 149.11173 | DY56: 152.46674 | DZ56: 155.89724 | EA56: 159.40493 | EB56: 162.99154
A57: Colombia | C57: 71.35 | D57: 71.28 | E57: 71.2 | F57: 72.46 | G57: 72.95 | H57: 72.9 | I57: 73.45 | J57: 74.77 | K57: 75.31 | L57: 75.62 | M57: 76.19 | N57: 77.31 | O57: 77.72 | P57: 77.96 | Q57: 78.05 | R57: 78.79 | S57: 79.39 | T57: 79.73 | U57: 79.56 | V57: 80.77 | W57: 81.61 | X57: 82.01 | Y57: 82.47 | Z57: 84.45 | AA57: 85.21 | AB57: 86.39 | AC57: 88.05 | AD57: 91.18 | AE57: 92.54 | AF57: 92.68 | AG57: 93.11 | AH57: 95.46 | AI57: 96.23 | AJ57: 96.36 | AK57: 96.92 | AL57: 98.45 | AM57: 99.31 | AN57: 99.47 | AO57: 100 | AP57: 101.62 | AQ57: 102.71 | AR57: 103.26 | AS57: 103.8 | AT57: 105.53 | AU57: 104.97 | AV57: 105.29 | AW57: 105.48 | AX57: 107.12 | AY57: 108.78 | AZ57: 110.04 | BA57: 111.41 | BB57: 116.26 | BC57: 119.31 | BD57: 122.63 | BE57: 126.03 | BF57: 131.77 | BG57: 133.78 | BH57: 136.11 | BI57: 137.72 | BJ57: 141.48 | BK57: 143.38 | BL57: 144.02 | BM57: 144.88 | BN57: 148.68 | BO57: 150.3 | BP57: 150.31367 | BQ57: 151.31267 | BR57: 154.46365 | BS57: 155.93625 | BT57: 155.57465 | BU57: 156.60862 | CY57: 76.19 | CZ57: 78.05 | DA57: 79.56 | DB57: 82.47 | DC57: 88.05 | DD57: 93.11 | DE57: 96.92 | DF57: 100 | DG57: 103.8 | DH57: 105.48 | DI57: 111.41 | DJ57: 126.03 | DK57: 137.72 | DL57: 144.88 | DM57: 151.31267 | DN57: 156.60862 | DO57: 162.08992 | DP57: 167.76306 | DQ57: 173.63477 | DR57: 179.71199 | DS57: 186.00191 | DT57: 192.51197 | DU57: 199.24989 | DV57: 206.22364 | DW57: 213.44147 | DX57: 220.91192 | DY57: 228.64384 | DZ57: 236.64637 | EA57: 244.92899 | EB57: 253.50151
A58: Argentina | C58: 116.14387 | D58: 120.45877 | E58: 126.51374 | F58: 136.34471 | G58: 141.4045 | H58: 148.14874 | I58: 155.51401 | J58: 164.29701 | K58: 171.87994 | L58: 180.64941 | M58: 188.54298 | N58: 200.26563 | O58: 209.92195 | P58: 221.84255 | Q58: 233.59944 | R58: 245.90503 | S58: 258.35209 | T58: 275.96657 | U58: 295.27585 | V58: 334.77038 | W58: 362.09663 | X58: 387.08063 | Y58: 407.5896 | Z58: 428.61272 | AA58: 454.52981 | AB58: 480.12318 | AC58: 517.33258 | AD58: 578.70715 | AE58: 662.3964 | AF58: 684.44257 | AG58: 720.6281 | AH58: 765.47427 | AI58: 806.71384 | AJ58: 847.72033 | AK58: 899.52919 | AL58: 959.26507 | AM58: 1043.0703 | AN58: 1189.9738 | AO58: 1328.0214 | AP58: 1485.13 | AQ58: 1625.976 | AR58: 1830.1822 | AS58: 2044.6448 | AT58: 2204.1392 | AU58: 2322.5878 | AV58: 2500.4049 | AW58: 2783.6139 | AX58: 3144.2257 | AY58: 3488.5345 | AZ58: 3812.4286 | BA58: 4201.6787 | BB58: 4876.8789 | BC58: 5720.6628 | BD58: 6977.8625 | BE58: 8184.5665 | BF58: 9963.243 | BG58: 12332.575 | BH58: 16626.95 | BI58: 25487.294 | BJ58: 38644.32 | BK58: 45819.188 | BL58: 51377.543 | BM58: 55502.108 | BN58: 60258.158 | BO58: 63881.227 | BP58: 67724.807 | BQ58: 71097.66 | BR58: 73906.599 | BS58: 76221.435 | BT58: 78531.021 | BU58: 80510.676 | CY58: 188.54298 | CZ58: 233.59944 | DA58: 295.27585 | DB58: 407.5896 | DC58: 517.33258 | DD58: 720.6281 | DE58: 899.52919 | DF58: 1328.0214 | DG58: 2044.6448 | DH58: 2783.6139 | DI58: 4201.6787 | DJ58: 8184.5665 | DK58: 25487.294 | DL58: 55502.108 | DM58: 71097.66 | DN58: 80510.676 | DO58: 86951.53 | DP58: 93907.653 | DQ58: 101420.27 | DR58: 109533.89 | DS58: 118296.6 | DT58: 127760.32 | DU58: 137981.15 | DV58: 149019.64 | DW58: 160941.21 | DX58: 173816.51 | DY58: 187721.83 | DZ58: 202739.58 | EA58: 218958.75 | EB58: 236475.45
A59: Brasil | C59: 2967.1 | D59: 2985.83 | E59: 3017.59 | F59: 3079.86 | G59: 3110.74 | H59: 3126.29 | I59: 3195.89 | J59: 3273.86 | K59: 3319.55 | L59: 3354.85 | M59: 3403.73 | N59: 3445.41 | O59: 3482.72 | P59: 3532.06 | Q59: 3602.46 | R59: 3672.42 | S59: 3715.92 | T59: 3738.99 | U59: 3815.39 | V59: 3898.38 | W59: 3958.32 | X59: 3991.24 | Y59: 4059.86 | Z59: 4215.26 | AA59: 4310.39 | AB59: 4370.12 | AC59: 4493.17 | AD59: 4610.92 | AE59: 4691.59 | AF59: 4740.53 | AG59: 4775.7 | AH59: 4821.69 | AI59: 4832.27 | AJ59: 4860.83 | AK59: 4916.46 | AL59: 4950.95 | AM59: 5044.46 | AN59: 5080.83 | AO59: 5100.61 | AP59: 5177.47 | AQ59: 5214.27 | AR59: 5227.84 | AS59: 5320.25 | AT59: 5348.49 | AU59: 5325.46 | AV59: 5391.75 | AW59: 5560.59 | AX59: 5674.72 | AY59: 5769.98 | AZ59: 5944.21 | BA59: 6120.04 | BB59: 6315.93 | BC59: 6455.85 | BD59: 6370.34 | BE59: 6474.09 | BF59: 6609.67 | BG59: 6659.95 | BH59: 6700.66 | BI59: 6773.27 | BJ59: 6869.14 | BK59: 6941.51 | BL59: 6997.15 | BM59: 7100.5 | BN59: 7245.38 | BO59: 7312.97 | BP59: 7375.6958 | BQ59: 7488.8973 | BR59: 7610.5472 | BS59: 7655.217 | BT59: 7705.3894 | BU59: 7823.6511 | CY59: 3403.73 | CZ59: 3602.46 | DA59: 3815.39 | DB59: 4059.86 | DC59: 4493.17 | DD59: 4775.7 | DE59: 4916.46 | DF59: 5100.61 | DG59: 5320.25 | DH59: 5560.59 | DI59: 6120.04 | DJ59: 6474.09 | DK59: 6773.27 | DL59: 7100.5 | DM59: 7488.8973 | DN59: 7823.6511 | DO59: 8173.3683 | DP59: 8538.7178 | DQ59: 8920.3985 | DR59: 9319.1403 | DS59: 9735.7059 | DT59: 10170.892 | DU59: 10625.531 | DV59: 11100.492 | DW59: 11596.684 | DX59: 12115.056 | DY59: 12656.599 | DZ59: 13222.349 | EA59: 13813.388 | EB59: 14430.846
A60: Paraguay | C60: 69.2 | D60: 70 | E60: 70.6 | F60: 71.9 | G60: 72.2 | H60: 72.7 | I60: 75.7 | J60: 79.3 | K60: 78.6 | L60: 79.5 | M60: 79.4 | N60: 81.9 | O60: 81.7 | P60: 81.7 | Q60: 82.6 | R60: 82.8 | S60: 83.1 | T60: 84.3 | U60: 85.7 | V60: 87.9 | W60: 88.4 | X60: 87.8 | Y60: 89.3 | Z60: 90.2 | AA60: 90.6 | AB60: 91.1 | AC60: 92.1 | AD60: 94.5 | AE60: 94.8 | AF60: 94.3 | AG60: 95.7 | AH60: 97.1 | AI60: 97.6 | AJ60: 98.3 | AK60: 100 | AL60: 101.1 | AM60: 101.9 | AN60: 102.2 | AO60: 103.2 | AP60: 103.9 | AQ60: 104.8 | AR60: 104.9 | AS60: 106.1 | AT60: 106.5 | AU60: 105.3 | AV60: 106.6 | AW60: 108.4 | AX60: 109.1 | AY60: 110 | AZ60: 113.4 | BA60: 115.8 | BB60: 120.1 | BC60: 122.7 | BD60: 124 | BE60: 125.2 | BF60: 127.8 | BG60: 127.9 | BH60: 128.3 | BI60: 129.8 | BJ60: 132.4 | BK60: 133.4 | BL60: 133.5 | BM60: 134.7 | BN60: 138.2 | BO60: 138.7 | BP60: 140.30702 | BQ60: 142.29539 | BR60: 144.80429 | BS60: 145.58523 | BT60: 147.26607 | BU60: 149.28088 | CY60: 79.4 | CZ60: 82.6 | DA60: 85.7 | DB60: 89.3 | DC60: 92.1 | DD60: 95.7 | DE60: 100 | DF60: 103.2 | DG60: 106.1 | DH60: 108.4 | DI60: 115.8 | DJ60: 125.2 | DK60: 129.8 | DL60: 134.7 | DM60: 142.29539 | DN60: 149.28088 | DO60: 156.6093 | DP60: 164.29748 | DQ60: 172.36309 | DR60: 180.82465 | DS60: 189.7016 | DT60: 199.01433 | DU60: 208.78424 | DV60: 219.03377 | DW60: 229.78646 | DX60: 241.06702 | DY60: 252.90136 | DZ60: 265.31666 | EA60: 278.34145 | EB60: 292.00565
A61: Mexico | C61: 70.1794 | D61: 70.8927 | E61: 71.7719 | F61: 73.4897 | G61: 72.7712 | H61: 73.5151 | I61: 74.931 | J61: 75.7235 | K61: 75.1555 | L61: 75.8211 | M61: 77.7924 | N61: 78.5474 | O61: 78.4137 | P61: 79.4391 | Q61: 80.5682 | R61: 81.8874 | S61: 81.6192 | T61: 82.1323 | U61: 83.7701 | V61: 84.9653 | W61: 84.6821 | X61: 85.5963 | Y61: 87.189 | Z61: 87.6307 | AA61: 87.1131 | AB61: 87.7524 | AC61: 89.0468 | AD61: 89.91 | AE61: 89.324 | AF61: 90.3577 | AG61: 92.039 | AH61: 94.7225 | AI61: 94.9636 | AJ61: 96.0935 | AK61: 98.2729 | AL61: 99.4922 | AM61: 99.3765 | AN61: 100.917 | AO61: 103.02 | AP61: 103.476 | AQ61: 103.299 | AR61: 103.942 | AS61: 105.934 | AT61: 106.838 | AU61: 106.743 | AV61: 108.114 | AW61: 109.271 | AX61: 111.824 | AY61: 113.018 | AZ61: 114.601 | BA61: 117.308 | BB61: 120.159 | BC61: 122.044 | BD61: 124.571 | BE61: 126.478 | BF61: 128.389 | BG61: 128.214 | BH61: 130.12 | BI61: 132.373 | BJ61: 134.065 | BK61: 134.594 | BL61: 136.08 | BM61: 137.949 | BN61: 139.161 | BO61: 140.405 | BP61: 140.8428 | BQ61: 142.77722 | BR61: 144.03164 | BS61: 145.31918 | BT61: 145.7723 | BU61: 147.77442 | CY61: 77.7924 | CZ61: 80.5682 | DA61: 83.7701 | DB61: 87.189 | DC61: 89.0468 | DD61: 92.039 | DE61: 98.2729 | DF61: 103.02 | DG61: 105.934 | DH61: 109.271 | DI61: 117.308 | DJ61: 126.478 | DK61: 132.373 | DL61: 137.949 | DM61: 142.77722 | DN61: 147.77442 | DO61: 152.94652 | DP61: 158.29965 | DQ61: 163.84014 | DR61: 169.57454 | DS61: 175.50965 | DT61: 181.65249 | DU61: 188.01033 | DV61: 194.59069 | DW61: 201.40136 | DX61: 208.45041 | DY61: 215.74617 | DZ61: 223.29729 | EA61: 231.1127 | EB61: 239.20164
A62: Uruguay | C62: 34.77 | D62: 35.63 | E62: 35.82 | F62: 36.7 | G62: 36.92 | H62: 37.88 | I62: 38.3 | J62: 39.7 | K62: 40.1 | L62: 40.84 | M62: 41.59 | N62: 42.67 | O62: 43.31 | P62: 44.37 | Q62: 44.7 | R62: 46.31 | S62: 46.87 | T62: 48.37 | U62: 48.51 | V62: 50.82 | W62: 51.12 | X62: 52.41 | Y62: 52.52 | Z62: 54.65 | AA62: 55.48 | AB62: 57.2 | AC62: 57.48 | AD62: 60.44 | AE62: 61.55 | AF62: 62.3 | AG62: 62.13 | AH62: 64.5 | AI62: 64.82 | AJ62: 65.88 | AK62: 66.2 | AL62: 68.79 | AM62: 70.08 | AN62: 71.33 | AO62: 71.47 | AP62: 74.14 | AQ62: 75.24 | AR62: 76.87 | AS62: 77.76 | AT62: 80.93 | AU62: 83.03 | AV62: 84.5 | AW62: 85.07 | AX62: 87.69 | AY62: 89.12 | AZ62: 90.76 | BA62: 91.85 | BB62: 95.91 | BC62: 97.4 | BD62: 99.79 | BE62: 99.47 | BF62: 102.94 | BG62: 103.22 | BH62: 103.66 | BI62: 104.55 | BJ62: 106.85 | BK62: 108.34 | BL62: 109.17 | BM62: 110.29 | BN62: 112.92 | BO62: 113.31 | BP62: 115.39515 | BQ62: 116.3859 | BR62: 120.44601 | BS62: 122.31719 | BT62: 124.48275 | BU62: 125.55153 | CY62: 41.59 | CZ62: 44.7 | DA62: 48.51 | DB62: 52.52 | DC62: 57.48 | DD62: 62.13 | DE62: 66.2 | DF62: 71.47 | DG62: 77.76 | DH62: 85.07 | DI62: 91.85 | DJ62: 99.47 | DK62: 104.55 | DL62: 110.29 | DM62: 116.3859 | DN62: 125.55153 | DO62: 135.43896 | DP62: 146.10505 | DQ62: 157.61112 | DR62: 170.02331 | DS62: 183.41298 | DT62: 197.85712 | DU62: 213.43877 | DV62: 230.2475 | DW62: 248.37995 | DX62: 267.94037 | DY62: 289.04121 | DZ62: 311.80379 | EA62: 336.35896 | EB62: 362.8479
A63: Spain | C63: 86.614 | D63: 85.971 | E63: 87.031 | F63: 86.639 | G63: 87.913 | H63: 87.801 | I63: 89.631 | J63: 89.754 | K63: 90.713 | L63: 90.559 | M63: 91.762 | N63: 91.458 | O63: 92.433 | P63: 93.649 | Q63: 94.394 | R63: 93.678 | S63: 94.34 | T63: 93.969 | U63: 94.632 | V63: 93.541 | W63: 94.421 | X63: 93.824 | Y63: 93.646 | Z63: 92.92 | AA63: 94.474 | AB63: 92.999 | AC63: 93.663 | AD63: 92.139 | AE63: 93.723 | AF63: 93.165 | AG63: 95.132 | AH63: 94.249 | AI63: 95.138 | AJ63: 94.835 | AK63: 96.19 | AL63: 95.393 | AM63: 97.302 | AN63: 96.978 | AO63: 97.329 | AP63: 96.669 | AQ63: 97.719 | AR63: 97.059 | AS63: 98.096 | AT63: 96.652 | AU63: 97.385 | AV63: 96.7 | AW63: 97.574 | AX63: 97.949 | AY63: 100.046 | AZ63: 100.575 | BA63: 103.965 | BB63: 107.566 | BC63: 110.267 | BD63: 109.498 | BE63: 109.899 | BF63: 111.111 | BG63: 112.354 | BH63: 113.348 | BI63: 113.308 | BJ63: 114.674 | BK63: 116.212 | BL63: 115.009 | BM63: 116.534 | BN63: 117.26 | BO63: 118.867 | BP63: 117.65421 | BQ63: 119.27255 | BR63: 119.48794 | BS63: 121.12547 | BT63: 120.00729 | BU63: 121.658 | CY63: 91.762 | CZ63: 94.394 | DA63: 94.632 | DB63: 93.646 | DC63: 93.663 | DD63: 95.132 | DE63: 96.19 | DF63: 97.329 | DG63: 98.096 | DH63: 97.574 | DI63: 103.965 | DJ63: 109.899 | DK63: 113.308 | DL63: 116.534 | DM63: 119.27255 | DN63: 121.658 | DO63: 124.09116 | DP63: 126.57298 | DQ63: 129.10444 | DR63: 131.68653 | DS63: 134.32026 | DT63: 137.00667 | DU63: 139.7468 | DV63: 142.54174 | DW63: 145.39257 | DX63: 148.30042 | DY63: 151.26643 | DZ63: 154.29176 | EA63: 157.3776 | EB63: 160.52515
A65: Costa Rica | C65: 99.95 | D65: 100.76 | E65: 101.47 | F65: 103.3 | G65: 105.74 | H65: 110.89 | I65: 111.98 | J65: 111.44 | K65: 110.41 | L65: 109.74 | M65: 109.48 | N65: 109.47 | O65: 109.1 | P65: 109.71 | Q65: 109.33 | R65: 110.39 | S65: 110.42 | T65: 109.47 | U65: 95.05 | V65: 96.99 | W65: 98.99 | X65: 100.09 | Y65: 99.92 | Z65: 99.94 | AA65: 100 | AB65: 99.22 | AC65: 99.12 | AD65: 98.86 | AE65: 99.12 | AF65: 99.6 | AG65: 99.87 | AH65: 100.42 | AI65: 100.88 | AJ65: 101.24 | AK65: 102.45 | AL65: 103.05 | AM65: 103.03 | AN65: 103.48 | AO65: 104.52 | AP65: 104.51 | AQ65: 105.53 | AR65: 106.09 | AS65: 106.11 | AT65: 106.5 | AU65: 105.86 | AV65: 106.41 | AW65: 107.06 | AX65: 99.95 | AY65: 100.76 | AZ65: 101.47 | BA65: 103.3 | BB65: 105.74 | BC65: 110.89 | BD65: 111.98 | BE65: 111.44 | BF65: 110.41 | BG65: 115.78745 | BH65: 116.92559 | BI65: 116.36174 | BJ65: 115.28625 | BK65: 120.90119 | BL65: 122.0896 | BM65: 121.50085 | BN65: 120.37786 | BO65: 126.24079 | BP65: 127.18021 | BQ65: 127.5538 | BR65: 126.08436 | BS65: 129.8217 | BT65: 130.90521 | BU65: 131.15855 | CY65: 109.48 | CZ65: 109.33 | DA65: 95.05 | DB65: 99.92 | DC65: 99.12 | DD65: 99.87 | DE65: 102.45 | DF65: 104.52 | DG65: 106.11 | DH65: 107.06 | DI65: 103.3 | DJ65: 111.44 | DK65: 116.36174 | DL65: 121.50085 | DM65: 127.5538 | DN65: 131.15855 | DO65: 134.86517 | DP65: 138.67654 | DQ65: 142.59562 | DR65: 146.62546 | DS65: 150.76919 | DT65: 155.03002 | DU65: 159.41126 | DV65: 163.91632 | DW65: 168.5487 | DX65: 173.31199 | DY65: 178.20989 | DZ65: 183.24621 | EA65: 188.42486 | EB65: 193.74986
A66: El Salvador | C66: 100.4 | D66: 99.73 | E66: 100 | F66: 100.89 | G66: 100.96 | H66: 101.11 | I66: 102.13 | J66: 103.63 | K66: 107.29 | L66: 107.4 | M66: 107.29 | N66: 108.16 | O66: 107.94 | P66: 108.24 | Q66: 108.13 | R66: 109.54 | S66: 108.91 | T66: 109.06 | U66: 108.98 | V66: 109.99 | W66: 110.15 | X66: 110.91 | Y66: 109.5 | Z66: 109.1 | AA66: 109.24 | AB66: 108.41 | AC66: 110.61 | AD66: 110.32 | AE66: 110.24 | AF66: 109.51 | AG66: 109.58 | AH66: 110.92 | AI66: 111.26 | AJ66: 111.22 | AK66: 111.81 | AL66: 111.93 | AM66: 112.26 | AN66: 112.76 | AO66: 112.3 | AP66: 112.69 | AQ66: 112.85 | AR66: 111.99 | AS66: 112.29 | AT66: 112.09 | AU66: 112.59 | AV66: 111.56 | AW66: 112.2 | AX66: 114.08 | AY66: 115.51 | AZ66: 117.1 | BA66: 119.06 | BB66: 121.7 | BC66: 124.5 | BD66: 125.9 | BE66: 127.77 | BF66: 129.08 | BG66: 129.18 | BH66: 129.67 | BI66: 129.34 | BJ66: 130.08 | BK66: 131.09 | BL66: 130.42 | BM66: 129.71 | BN66: 130.26 | BO66: 130.86 | BP66: 131.17496 | BQ66: 132.15776 | BR66: 133.56188 | BS66: 134.85856 | BT66: 135.25083 | BU66: 136.04445 | CY66: 107.29 | CZ66: 108.13 | DA66: 108.98 | DB66: 109.5 | DC66: 110.61 | DD66: 109.58 | DE66: 111.81 | DF66: 112.3 | DG66: 112.29 | DH66: 112.2 | DI66: 119.06 | DJ66: 127.77 | DK66: 129.34 | DL66: 129.71 | DM66: 132.15776 | DN66: 136.04445 | DO66: 140.04544 | DP66: 144.1641 | DQ66: 148.40389 | DR66: 152.76837 | DS66: 157.2612 | DT66: 161.88617 | DU66: 166.64715 | DV66: 171.54816 | DW66: 176.59329 | DX66: 181.78681 | DY66: 187.13306 | DZ66: 192.63654 | EA66: 198.30187 | EB66: 204.13382
... A69: Nicaragua | C69: 108.87 | D69: 105.71 | E69: 102.18 | F69: 100.83 | G69: 101.1 | H69: 100.27 | I69: 97.8 | J69: 96.23 | K69: 94.3 | L69: 95.27 | M69: 97.75 | N69: 97.36 | O69: 98.24 | P69: 97.35 | Q69: 96.77 | R69: 97.3 | S69: 97.59 | T69: 97.6 | U69: 96.49 | V69: 96.63 | W69: 96.07 | X69: 97.32 | Y69: 99.36 | Z69: 101.74 | AA69: 101.44 | AB69: 102.34 | AC69: 102.8 | AD69: 103.77 | AE69: 102.01 | AF69: 101.49 | AG69: 101.77 | AH69: 101.46 | AI69: 98.92 | AJ69: 96.64 | AK69: 97.11 | AL69: 95.03 | AM69: 95.52 | AN69: 96.21 | AO69: 96.99 | AP69: 95.41 | AQ69: 96.33 | AR69: 96.5 | AS69: 95.82 | AT69: 95.63 | AU69: 98.3 | AV69: 96.02 | AW69: 93.92 | AX69: 93.23 | AY69: 92.11 | AZ69: 92.76 | BA69: 94.03 | BB69: 94.53 | BC69: 95.67 | BD69: 98.54 | BE69: 99.87 | BF69: 98.08 | BG69: 98.42 | BH69: 98.9 | BI69: 99.51 | BJ69: 99.47 | BK69: 100.95 | BL69: 101.39 | BM69: 101.96 | BN69: 102.81 | BO69: 100.57 | BP69: 101.5757 | BQ69: 102.59146 | BR69: 103.61737 | BS69: 104.65355 | BT69: 105.70008 | BU69: 106.75708 | CY69: 97.75 | CZ69: 96.77 | DA69: 96.49 | DB69: 99.36 | DC69: 102.8 | DD69: 101.77 | DE69: 97.11 | DF69: 96.99 | DG69: 95.82 | DH69: 93.92 | DI69: 94.03 | DJ69: 99.87 | DK69: 99.51 | DL69: 101.96 | DM69: 102.59146 | DN69: 106.75708 | DO69: 111.09185 | DP69: 115.60262 | DQ69: 120.29655 | DR69: 125.18107 | DS69: 130.26393 | DT69: 135.55317 | DU69: 141.05717 | DV69: 146.78465 | DW69: 152.7447 | DX69: 158.94675 | DY69: 165.40062 | DZ69: 172.11655 | EA69: 179.10517 | EB69: 186.37756
A70: CHUF | B70: 20959.77 | C70: 20933.02 | D70: 20834.45 | E70: 20942.88 | F70: 20998.52 | G70: 21202.16 | H70: 21339.99 | I70: 21455.55 | J70: 21578.26 | K70: 21889.88 | L70: 22012.69 | M70: 22294.03 | N70: 22533.51 | O70: 22627.36 | P70: 22591.05 | Q70: 22840.75 | R70: 22869.38 | S70: 22852.67 | T70: 23091.03 | U70: 23309.56 | V70: 23606.97 | W70: 24023.61 | X70: 24168.02 | Y70: 24627.1 | Z70: 24622.78 | AA70: 24982.96 | AB70: 25346.89 | AC70: 25629.09 | AD70: 25812.05 | AE70: 26052.07 | AF70: 26224.3 | AG70: 26347.98 | AH70: 26471.94 | AI70: 26665.09 | AJ70: 26656.79 | AK70: 26798.14 | AL70: 26966.89 | AM70: 27158.77 | AN70: 27357.45 | AO70: 27565.79 | AP70: 27565.76 | AQ70: 27903.3 | AR70: 28048.53 | AS70: 28309.94 | AT70: 28597.46 | AU70: 28696.42 | AV70: 28707.85 | AW70: 29070.33 | AX70: 29394.77 | AY70: 29709.83 | AZ70: 30088.37 | BA70: 30991.74 | BB70: 31727.74 | BC70: 33086.83 | BD70: 34258.23 | BE70: 35110.98 | BF70: 35575.48 | BG70: 36089.48 | BH70: 36197.53 | BI70: 36789.36 | BJ70: 37093.52 | BK70: 37571.86 | BL70: 37910.42 | BM70: 38416.69 | BN70: 38894.11 | BO70: 39267.07 | BP70: 39556.447 | BQ70: 40021.879 | BR70: 40387.622 | BS70: 40454.396 | BT70: 40705.222 | BU70: 41229.508 | CY70: 22294.03 | CZ70: 22840.75 | DA70: 23309.56 | DB70: 24627.1 | DC70: 25629.09 | DD70: 26347.98 | DE70: 26798.14 | DF70: 27565.79 | DG70: 28309.94 | DH70: 29070.33 | DI70: 30991.74 | DJ70: 35110.98 | DK70: 36789.36 | DL70: 38416.69 | DM70: 40021.879 | DN70: 41229.508 | DO70: 42487.008 | DP70: 43761.618 | DQ70: 45074.467 | DR70: 46426.701 | DS70: 47819.502 | DT70: 49254.087 | DU70: 50731.71 | DV70: 52253.661 | DW70: 53821.271 | DX70: 55435.909 | DY70: 57098.986 | DZ70: 58811.956 | EA70: 60576.314 | EB70: 62393.604
A75: Inflacion YoY
A76: USA | G76: 0.011215606 | H76: 0.011183122 | I76: 0.01437793 | J76: 0.026192415 | K76: 0.035023182 | L76: 0.038126217 | M76: 0.030620668 | N76: 0.025828753 | O76: 0.016538704 | P76: 0.019497169 | Q76: 0.01759505 | R76: 0.015187472 | S76: 0.017157935 | T76: 0.010947341 | U76: 0.015128384 | V76: 0.016126949 | W76: 0.020589817 | X76: 0.01684051 | Y76: 0.0065312139 | Z76: -0.00022031284 | AA76: 0.0017957181 | AB76: 8.8429616e-05 | AC76: 0.0063872475 | AD76: 0.008916161 | AE76: 0.010792865 | AF76: 0.015486446 | AG76: 0.020507989 | AH76: 0.024411962 | AI76: 0.016405658 | AJ76: 0.021805652 | AK76: 0.021299307 | AL76: 0.023309498 | AM76: 0.028075507 | AN76: 0.023320551 | AO76: 0.020023809 | AP76: 0.018831864 | AQ76: 0.016711949 | AR76: 0.016844977 | AS76: 0.023195275 | AT76: 0.0149404 | AU76: 0.0071665628 | AV76: 0.013910229 | AW76: 0.013204191 | AX76: 0.026236457 | AY76: 0.053174189 | AZ76: 0.053635234 | BA76: 0.071594573 | BB76: 0.085407801 | BC76: 0.089992981 | BD76: 0.082057516 | BE76: 0.064108317 | BF76: 0.049313486 | BG76: 0.030592533 | BH76: 0.036950823 | BI76: 0.033222002 | BJ76: 0.034690014 | BK76: 0.029700854 | BL76: 0.024325415 | BM76: 0.028723663 | BN76: 0.024055853 | BO76: 0.026726833 | BP76: 0.034 | BQ76: 0.0347 | BR76: 0.0326 | BS76: 0.0301 | BT76: 0.026 | BU76: 0.026 | CZ76: 0.01759505 | DA76: 0.015128384 | DB76: 0.0065312139 | DC76: 0.0063872475 | DD76: 0.020507989 | DE76: 0.021299307 | DF76: 0.020023809 | DG76: 0.023195275 | DH76: 0.013204191 | DI76: 0.071594573 | DJ76: 0.064108317 | DK76: 0.033222002 | DL76: 0.028723663 | DM76: 0.0347 | DN76: 0.026 | DO76: 0.02 | DP76: 0.02 | DQ76: 0.02 | DR76: 0.02 | DS76: 0.02 | DT76: 0.02 | DU76: 0.02 | DV76: 0.02 | DW76: 0.02 | DX76: 0.02 | DY76: 0.02 | DZ76: 0.02 | EA76: 0.02 | EB76: 0.02
A77: Chile | I77: 0.029837725 | J77: 0.033725355 | K77: 0.034305317 | L77: 0.032795242 | M77: 0.044391732 | N77: 0.037811611 | O77: 0.026533997 | P77: 0.028298782 | Q77: 0.014763141 | R77: 0.01531517 | S77: 0.018901454 | T77: 0.01968 | U77: 0.030215827 | V77: 0.038583677 | W77: 0.04772475 | X77: 0.051310215 | Y77: 0.046399752 | Z77: 0.041889619 | AA77: 0.044188862 | AB77: 0.04641791 | AC77: 0.043897375 | AD77: 0.044460748 | AE77: 0.042028986 | AF77: 0.030951362 | AG77: 0.026992471 | AH77: 0.027535825 | AI77: 0.016968011 | AJ77: 0.01452684 | AK77: 0.022686402 | AL77: 0.01804758 | AM77: 0.025437637 | AN77: 0.031365062 | AO77: 0.025699986 | AP77: 0.024845555 | AQ77: 0.027073886 | AR77: 0.022477853 | AS77: 0.029935382 | AT77: 0.037347661 | AU77: 0.02623036 | AV77: 0.030906505 | AW77: 0.029833547 | AX77: 0.028928752 | AY77: 0.038086802 | AZ77: 0.05343703 | BA77: 0.071739401 | BB77: 0.094045427 | BC77: 0.12493905 | BD77: 0.13729459 | BE77: 0.12772622 | BF77: 0.11098642 | BG77: 0.075522809 | BH77: 0.051094126 | BI77: 0.039399239 | BJ77: 0.037373737 | BK77: 0.041910135 | BL77: 0.041338779 | BM77: 0.045328583 | BN77: 0.048685492 | BO77: 0.041191259 | BP77: 0.0437 | BQ77: 0.044 | BR77: 0.032 | BS77: 0.029 | BT77: 0.029 | BU77: 0.031 | CZ77: 0.014763141 | DA77: 0.030215827 | DB77: 0.046399752 | DC77: 0.043897375 | DD77: 0.026992471 | DE77: 0.022686402 | DF77: 0.025699986 | DG77: 0.029935382 | DH77: 0.029833547 | DI77: 0.071739401 | DJ77: 0.12772622 | DK77: 0.039399239 | DL77: 0.045328583 | DM77: 0.044 | DN77: 0.031 | DO77: 0.03 | DP77: 0.03 | DQ77: 0.03 | DR77: 0.03 | DS77: 0.03 | DT77: 0.03 | DU77: 0.03 | DV77: 0.03 | DW77: 0.03 | DX77: 0.03 | DY77: 0.03 | DZ77: 0.03 | EA77: 0.03 | EB77: 0.03
A78: Peru | G78: 0.016435986 | H78: 0.023672055 | I78: 0.020716444 | J78: 0.026664765 | K78: 0.029078014 | L78: 0.037225042 | M78: 0.047357294 | N78: 0.042361111 | O78: 0.039972433 | P78: 0.037384448 | Q78: 0.026510564 | R78: 0.025849434 | S78: 0.027700464 | T78: 0.028305596 | U78: 0.02857892 | V78: 0.033900507 | W78: 0.034562806 | X78: 0.027399006 | Y78: 0.03224573 | Z78: 0.030150754 | AA78: 0.035402643 | AB78: 0.039072191 | AC78: 0.044079516 | AD78: 0.04304878 | AE78: 0.033469781 | AF78: 0.031276113 | AG78: 0.032284768 | AH78: 0.039752134 | AI78: 0.027260019 | AJ78: 0.029517305 | AK78: 0.013632719 | AL78: 0.0035983358 | AM78: 0.014288954 | AN78: 0.012705195 | AO78: 0.021925859 | AP78: 0.022408964 | AQ78: 0.022920394 | AR78: 0.018541135 | AS78: 0.01902234 | AT78: 0.01830137 | AU78: 0.01606733 | AV78: 0.018203619 | AW78: 0.01975255 | AX78: 0.025936289 | AY78: 0.032487091 | AZ78: 0.052349855 | BA78: 0.064282673 | BB78: 0.068289101 | BC78: 0.088143363 | BD78: 0.085249237 | BE78: 0.0846 | BF78: 0.083955224 | BG78: 0.06463041 | BH78: 0.050431196 | BI78: 0.032362161 | BJ78: 0.03043754 | BK78: 0.022843781 | BL78: 0.017758344 | BM78: 0.01964812 | BN78: 0.012835165 | BO78: 0.016970017 | BP78: 0.018 | BQ78: 0.0225 | BR78: 0.0225 | BS78: 0.024 | BT78: 0.0225 | BU78: 0.0225 | CZ78: 0.026510564 | DA78: 0.02857892 | DB78: 0.03224573 | DC78: 0.044079516 | DD78: 0.032284768 | DE78: 0.013632719 | DF78: 0.021925859 | DG78: 0.01902234 | DH78: 0.01975255 | DI78: 0.064282673 | DJ78: 0.0846 | DK78: 0.032362161 | DL78: 0.01964812 | DM78: 0.0225 | DN78: 0.0225 | DO78: 0.0225 | DP78: 0.0225 | DQ78: 0.0225 | DR78: 0.0225 | DS78: 0.0225 | DT78: 0.0225 | DU78: 0.0225 | DV78: 0.0225 | DW78: 0.0225 | DX78: 0.0225 | DY78: 0.0225 | DZ78: 0.0225 | EA78: 0.0225 | EB78: 0.0225
A79: Colombia | G79: 0.022424667 | H79: 0.022727273 | I79: 0.031601124 | J79: 0.031879658 | K79: 0.032350925 | L79: 0.037311385 | M79: 0.037304289 | N79: 0.033970844 | O79: 0.032001062 | P79: 0.030944195 | Q79: 0.024412653 | R79: 0.019143707 | S79: 0.021487391 | T79: 0.022703951 | U79: 0.019346573 | V79: 0.025130093 | W79: 0.02796322 | X79: 0.028596513 | Y79: 0.036576169 | Z79: 0.045561471 | AA79: 0.044112241 | AB79: 0.053408121 | AC79: 0.067660968 | AD79: 0.079692126 | AE79: 0.086022767 | AF79: 0.072809353 | AG79: 0.057467348 | AH79: 0.046940118 | AI79: 0.039874649 | AJ79: 0.039706517 | AK79: 0.040919343 | AL79: 0.03132202 | AM79: 0.032006651 | AN79: 0.032274803 | AO79: 0.031778787 | AP79: 0.032199086 | AQ79: 0.03423623 | AR79: 0.03810194 | AS79: 0.038 | AT79: 0.038476678 | AU79: 0.0220037 | AV79: 0.019659113 | AW79: 0.016184971 | AX79: 0.015066806 | AY79: 0.036296085 | AZ79: 0.045113496 | BA79: 0.056219188 | BB79: 0.085324869 | BC79: 0.096800883 | BD79: 0.11441294 | BE79: 0.131227 | BF79: 0.13340788 | BG79: 0.1212807 | BH79: 0.10992416 | BI79: 0.092755693 | BJ79: 0.073689004 | BK79: 0.071759605 | BL79: 0.05811476 | BM79: 0.051989544 | BN79: 0.050890585 | BO79: 0.048263356 | BP79: 0.0437 | BQ79: 0.0444 | BR79: 0.0389 | BS79: 0.0375 | BT79: 0.035 | BU79: 0.035 | CZ79: 0.024412653 | DA79: 0.019346573 | DB79: 0.036576169 | DC79: 0.067660968 | DD79: 0.057467348 | DE79: 0.040919343 | DF79: 0.031778787 | DG79: 0.038 | DH79: 0.016184971 | DI79: 0.056219188 | DJ79: 0.131227 | DK79: 0.092755693 | DL79: 0.051989544 | DM79: 0.0444 | DN79: 0.035 | DO79: 0.035 | DP79: 0.035 | DQ79: 0.035 | DR79: 0.035 | DS79: 0.035 | DT79: 0.035 | DU79: 0.035 | DV79: 0.035 | DW79: 0.035 | DX79: 0.035 | DY79: 0.035 | DZ79: 0.035 | EA79: 0.035 | EB79: 0.035
A80: Argentina | G80: 0.21749438 | H80: 0.22987092 | I80: 0.22922619 | J80: 0.20501198 | K80: 0.21551955 | L80: 0.21937866 | M80: 0.21238588 | N80: 0.21892434 | O80: 0.221329 | P80: 0.22802809 | Q80: 0.23897181 | R80: 0.22789435 | S80: 0.23070542 | T80: 0.2439749 | U80: 0.26402635 | V80: 0.36138074 | W80: 0.40156262 | X80: 0.40263594 | Y80: 0.38036889 | Z80: 0.28031854 | AA80: 0.25527215 | AB80: 0.24036995 | AC80: 0.26924874 | AD80: 0.3501866 | AE80: 0.45732224 | AF80: 0.42555619 | AG80: 0.3929687 | AH80: 0.32273166 | AI80: 0.21787171 | AJ80: 0.23855583 | AK80: 0.24825718 | AL80: 0.25316436 | AM80: 0.29298672 | AN80: 0.40373392 | AO80: 0.4763516 | AP80: 0.54819565 | AQ80: 0.55883643 | AR80: 0.53800208 | AS80: 0.53961739 | AT80: 0.48413889 | AU80: 0.42842689 | AV80: 0.36620551 | AW80: 0.36141688 | AX80: 0.42650957 | AY80: 0.50200329 | AZ80: 0.52472448 | BA80: 0.50943298 | BB80: 0.5510588 | BC80: 0.63984698 | BD80: 0.83029328 | BE80: 0.94792775 | BF80: 1.0429548 | BG80: 1.1557949 | BH80: 1.3828142 | BI80: 2.1140676 | BJ80: 2.8786889 | BK80: 2.7152976 | BL80: 2.0900161 | BM80: 1.1776383 | BN80: 0.55930179 | BO80: 0.39420251 | BP80: 0.31817917 | BQ80: 0.28099027 | BR80: 0.22649949 | BS80: 0.19317425 | BT80: 0.15956064 | BU80: 0.13239559 | CZ80: 0.23897181 | DA80: 0.26402635 | DB80: 0.38036889 | DC80: 0.26924874 | DD80: 0.3929687 | DE80: 0.24825718 | DF80: 0.4763516 | DG80: 0.53961739 | DH80: 0.36141688 | DI80: 0.50943298 | DJ80: 0.94792775 | DK80: 2.1140676 | DL80: 1.1776383 | DM80: 0.28099027 | DN80: 0.13239559 | DO80: 0.08 | DP80: 0.08 | DQ80: 0.08 | DR80: 0.08 | DS80: 0.08 | DT80: 0.08 | DU80: 0.08 | DV80: 0.08 | DW80: 0.08 | DX80: 0.08 | DY80: 0.08 | DZ80: 0.08 | EA80: 0.08 | EB80: 0.08
